Workbook

Sheet query2
A1: id | B1: doi | C1: title | D1: publication_year | E1: publication_date | F1: ids | G1: language | H1: type | I1: countries_distinct_count | J1: institutions_distinct_count | K1: fwci | L1: has_fulltext | M1: cited_by_count | N1: citation_normalized_percentile | O1: cited_by_percentile_year | P1: biblio | Q1: sustainable_development_goals | R1: counts_by_year
A2: https://openalex.org/W3128206428 | B2: https://doi.org/10.1038/s41467-021-21219-y | C2: Functional and versatile superhydrophobic coatings via stoichiometric silanization | D2: 2021 | E2: 44239 | F2: {'openalex': 'https://openalex.org/W3128206428', 'doi': 'https://doi.org/10.1038/s41467-021-21219-y', 'mag': '3128206428', 'pmid': 'https://pubmed.ncbi.nlm.nih.gov/33579959'} | G2: en | H2: article | I2: 1 | J2: 5 | K2: 20.071 | L2: TRUE | M2: 294 | N2: {'value': 0.99853177, 'is_in_top_1_percent': True, 'is_in_top_10_percent': True} | O2: {'min': 99, 'max': 100} | P2: {'volume': '12', 'issue': '1', 'first_page': '982', 'last_page': '982'} | Q2: [{'display_name': 'Industry, innovation and infrastructure', 'score': 0.46000000834465027, 'id': 'https://metadata.un.org/sdg/9'}] | R2: [{'year': 2026, 'cited_by_count': 7}, {'year': 2025, 'cited_by_count': 65}, {'year': 2024, 'cited_by_count': 76}, {'year': 2023, 'cited_by_count': 69}, {'year': 2022, 'cited_by_count': 61}, {'year': 2021, 'cited_by_count': 16}]
A3: https://openalex.org/W3197182136 | B3: https://doi.org/10.1088/2631-8695/ac2353 | C3: A review of primary technologies of thin-film solar cells | D3: 2021 | E3: 44440 | F3: {'openalex': 'https://openalex.org/W3197182136', 'doi': 'https://doi.org/10.1088/2631-8695/ac2353', 'mag': '3197182136'} | G3: en | H3: review | I3: 2 | J3: 8 | K3: 8.8239 | L3: FALSE | M3: 124 | N3: {'value': 0.98505979, 'is_in_top_1_percent': False, 'is_in_top_10_percent': True} | O3: {'min': 93, 'max': 100} | P3: {'volume': '3', 'issue': '3', 'first_page': '032001', 'last_page': '032001'} | Q3: [{'score': 0.5099999904632568, 'display_name': 'Industry, innovation and infrastructure', 'id': 'https://metadata.un.org/sdg/9'}] | R3: [{'year': 2026, 'cited_by_count': 4}, {'year': 2025, 'cited_by_count': 32}, {'year': 2024, 'cited_by_count': 44}, {'year': 2023, 'cited_by_count': 24}, {'year': 2022, 'cited_by_count': 18}, {'year': 2021, 'cited_by_count': 2}]
A4: https://openalex.org/W3080210839 | B4: https://doi.org/10.1126/sciadv.aba5847 | C4: Phase transition enhanced superior elasticity in freestanding single-crystalline multiferroic BiFeO <sub>3</sub> membranes | D4: 2020 | E4: 44064 | F4: {'openalex': 'https://openalex.org/W3080210839', 'doi': 'https://doi.org/10.1126/sciadv.aba5847', 'mag': '3080210839', 'pmid': 'https://pubmed.ncbi.nlm.nih.gov/32937363'} | G4: en | H4: article | I4: 3 | J4: 21 | K4: 4.3853 | L4: FALSE | M4: 123 | N4: {'value': 0.9578073, 'is_in_top_1_percent': False, 'is_in_top_10_percent': True} | O4: {'min': 99, 'max': 100} | P4: {'volume': '6', 'issue': '34', 'first_page': None, 'last_page': None} | Q4: [] | R4: [{'year': 2026, 'cited_by_count': 4}, {'year': 2025, 'cited_by_count': 24}, {'year': 2024, 'cited_by_count': 29}, {'year': 2023, 'cited_by_count': 23}, {'year': 2022, 'cited_by_count': 31}, {'year': 2021, 'cited_by_count': 12}]
A5: https://openalex.org/W3097814634 | B5: https://doi.org/10.1038/s41598-020-75393-y | C5: Material properties and structure of natural graphite sheet | D5: 2020 | E5: 44133 | F5: {'openalex': 'https://openalex.org/W3097814634', 'doi': 'https://doi.org/10.1038/s41598-020-75393-y', 'mag': '3097814634', 'pmid': 'https://pubmed.ncbi.nlm.nih.gov/33122759'} | G5: en | H5: article | I5: 2 | J5: 4 | K5: 2.5592 | L5: TRUE | M5: 82 | N5: {'value': 0.90500596, 'is_in_top_1_percent': False, 'is_in_top_10_percent': True} | O5: {'min': 94, 'max': 100} | P5: {'volume': '10', 'issue': '1', 'first_page': '18672', 'last_page': '18672'} | Q5: [{'score': 0.5199999809265137, 'display_name': 'Affordable and clean energy', 'id': 'https://metadata.un.org/sdg/7'}] | R5: [{'year': 2026, 'cited_by_count': 2}, {'year': 2025, 'cited_by_count': 27}, {'year': 2024, 'cited_by_count': 21}, {'year': 2023, 'cited_by_count': 18}, {'year': 2022, 'cited_by_count': 8}, {'year': 2021, 'cited_by_count': 4}, {'year': 2020, 'cited_by_count': 2}]
A6: https://openalex.org/W4283015959 | B6: https://doi.org/10.1016/j.cossms.2022.101016 | C6: Recent progress in bismuth-based high Curie temperature piezo-/ferroelectric perovskites for electromechanical transduction applications | D6: 2022 | E6: 44728 | F6: {'openalex': 'https://openalex.org/W4283015959', 'doi': 'https://doi.org/10.1016/j.cossms.2022.101016'} | G6: en | H6: article | I6: 2 | J6: 13 | K6: 5.1836 | L6: FALSE | M6: 73 | N6: {'value': 0.9703689, 'is_in_top_1_percent': False, 'is_in_top_10_percent': True} | O6: {'min': 97, 'max': 100} | P6: {'volume': '26', 'issue': '5', 'first_page': '101016', 'last_page': '101016'} | Q6: [{'id': 'https://metadata.un.org/sdg/9', 'score': 0.4699999988079071, 'display_name': 'Industry, innovation and infrastructure'}] | R6: [{'year': 2026, 'cited_by_count': 3}, {'year': 2025, 'cited_by_count': 24}, {'year': 2024, 'cited_by_count': 25}, {'year': 2023, 'cited_by_count': 17}, {'year': 2022, 'cited_by_count': 4}]
A7: https://openalex.org/W3160146843 | B7: https://doi.org/10.1016/j.ensm.2021.05.011 | C7: Materials design and fundamental understanding of tellurium-based electrochemistry for rechargeable batteries | D7: 2021 | E7: 44330 | F7: {'openalex': 'https://openalex.org/W3160146843', 'doi': 'https://doi.org/10.1016/j.ensm.2021.05.011', 'mag': '3160146843'} | G7: en | H7: article | I7: 1 | J7: 4 | K7: 5.6152 | L7: FALSE | M7: 71 | N7: {'value': 0.96650302, 'is_in_top_1_percent': False, 'is_in_top_10_percent': True} | O7: {'min': 95, 'max': 100} | P7: {'volume': '40', 'issue': None, 'first_page': '166', 'last_page': '188'} | Q7: [{'score': 0.7900000214576721, 'display_name': 'Affordable and clean energy', 'id': 'https://metadata.un.org/sdg/7'}] | R7: [{'year': 2026, 'cited_by_count': 2}, {'year': 2025, 'cited_by_count': 13}, {'year': 2024, 'cited_by_count': 23}, {'year': 2023, 'cited_by_count': 19}, {'year': 2022, 'cited_by_count': 11}, {'year': 2021, 'cited_by_count': 3}]
A8: https://openalex.org/W4307815345 | B8: https://doi.org/10.1016/j.ijhydene.2022.10.080 | C8: The mechanism and sorption kinetic analysis of hydrogen storage at room temperature using acid functionalized carbon nanotubes | D8: 2022 | E8: 44863 | F8: {'openalex': 'https://openalex.org/W4307815345', 'doi': 'https://doi.org/10.1016/j.ijhydene.2022.10.080'} | G8: en | H8: article | I8: 2 | J8: 4 | K8: 5.0355 | L8: FALSE | M8: 69 | N8: {'value': 0.96913033, 'is_in_top_1_percent': False, 'is_in_top_10_percent': True} | O8: {'min': 89, 'max': 100} | P8: {'volume': '48', 'issue': '5', 'first_page': '1930', 'last_page': '1942'} | Q8: [] | R8: [{'year': 2026, 'cited_by_count': 1}, {'year': 2025, 'cited_by_count': 26}, {'year': 2024, 'cited_by_count': 27}, {'year': 2023, 'cited_by_count': 14}, {'year': 2022, 'cited_by_count': 1}]
A9: https://openalex.org/W4394770414 | B9: https://doi.org/10.1016/j.tips.2024.03.004 | C9: Direct in vivo CAR T cell engineering | D9: 2024 | E9: 45394 | F9: {'openalex': 'https://openalex.org/W4394770414', 'doi': 'https://doi.org/10.1016/j.tips.2024.03.004', 'pmid': 'https://pubmed.ncbi.nlm.nih.gov/38614815'} | G9: en | H9: article | I9: 1 | J9: 4 | K9: 20.5378 | L9: FALSE | M9: 68 | N9: {'value': 0.99619071, 'is_in_top_1_percent': True, 'is_in_top_10_percent': True} | O9: {'min': 99, 'max': 100} | P9: {'volume': '45', 'issue': '5', 'first_page': '406', 'last_page': '418'} | Q9: [{'id': 'https://metadata.un.org/sdg/3', 'score': 0.6100000143051147, 'display_name': 'Good health and well-being'}] | R9: [{'year': 2026, 'cited_by_count': 5}, {'year': 2025, 'cited_by_count': 49}, {'year': 2024, 'cited_by_count': 14}]
A10: https://openalex.org/W3083114603 | B10: https://doi.org/10.1007/s13204-020-01542-4 | C10: Scrutinizing the charge storage mechanism in SrO based composites for asymmetric supercapacitors by diffusion-controlled process | D10: 2020 | E10: 44078 | F10: {'openalex': 'https://openalex.org/W3083114603', 'doi': 'https://doi.org/10.1007/s13204-020-01542-4', 'mag': '3083114603'} | G10: en | H10: article | I10: 4 | J10: 7 | K10: 1.8604 | L10: FALSE | M10: 68 | N10: {'value': 0.85417147, 'is_in_top_1_percent': False, 'is_in_top_10_percent': False} | O10: {'min': 97, 'max': 100} | P10: {'volume': '10', 'issue': '11', 'first_page': '3999', 'last_page': '4011'} | Q10: [{'score': 0.4099999964237213, 'display_name': 'Industry, innovation and infrastructure', 'id': 'https://metadata.un.org/sdg/9'}] | R10: [{'year': 2026, 'cited_by_count': 2}, {'year': 2025, 'cited_by_count': 23}, {'year': 2024, 'cited_by_count': 15}, {'year': 2023, 'cited_by_count': 14}, {'year': 2022, 'cited_by_count': 9}, {'year': 2021, 'cited_by_count': 5}]
A11: https://openalex.org/W4311425960 | B11: https://doi.org/10.1016/j.addma.2022.103357 | C11: Review of transfer learning in modeling additive manufacturing processes | D11: 2022 | E11: 44907 | F11: {'openalex': 'https://openalex.org/W4311425960', 'doi': 'https://doi.org/10.1016/j.addma.2022.103357'} | G11: en | H11: article | I11: 1 | J11: 3 | K11: 8.3579 | L11: FALSE | M11: 67 | N11: {'value': 0.98037312, 'is_in_top_1_percent': False, 'is_in_top_10_percent': True} | O11: {'min': 98, 'max': 100} | P11: {'volume': '61', 'issue': None, 'first_page': '103357', 'last_page': '103357'} | Q11: [{'score': 0.550000011920929, 'display_name': 'Industry, innovation and infrastructure', 'id': 'https://metadata.un.org/sdg/9'}] | R11: [{'year': 2026, 'cited_by_count': 4}, {'year': 2025, 'cited_by_count': 24}, {'year': 2024, 'cited_by_count': 33}, {'year': 2023, 'cited_by_count': 6}]
A12: https://openalex.org/W3169143473 | B12: https://doi.org/10.1016/j.optmat.2021.111258 | C12: Performance analysis of several electron/hole transport layers in thin film MAPbI3-based perovskite solar cells: A simulation study | D12: 2021 | E12: 44356 | F12: {'openalex': 'https://openalex.org/W3169143473', 'doi': 'https://doi.org/10.1016/j.optmat.2021.111258', 'mag': '3169143473'} | G12: en | H12: article | I12: 2 | J12: 3 | K12: 3.71 | L12: FALSE | M12: 64 | N12: {'value': 0.93766708, 'is_in_top_1_percent': False, 'is_in_top_10_percent': True} | O12: {'min': 89, 'max': 100} | P12: {'volume': '118', 'issue': None, 'first_page': '111258', 'last_page': '111258'} | Q12: [{'score': 0.7099999785423279, 'display_name': 'Affordable and clean energy', 'id': 'https://metadata.un.org/sdg/7'}] | R12: [{'year': 2025, 'cited_by_count': 27}, {'year': 2024, 'cited_by_count': 20}, {'year': 2023, 'cited_by_count': 10}, {'year': 2022, 'cited_by_count': 6}, {'year': 2021, 'cited_by_count': 1}]
A13: https://openalex.org/W3139159936 | B13: https://doi.org/10.1016/j.ijhydene.2021.02.077 | C13: Optimizing electrochemical performance of sonochemically and hydrothermally synthesized cobalt phosphate for supercapattery devices | D13: 2021 | E13: 44265 | F13: {'openalex': 'https://openalex.org/W3139159936', 'doi': 'https://doi.org/10.1016/j.ijhydene.2021.02.077', 'mag': '3139159936'} | G13: en | H13: article | I13: 2 | J13: 5 | K13: 3.2506 | L13: FALSE | M13: 62 | N13: {'value': 0.93041065, 'is_in_top_1_percent': False, 'is_in_top_10_percent': True} | O13: {'min': 97, 'max': 100} | P13: {'volume': '46', 'issue': '29', 'first_page': '15807', 'last_page': '15819'} | Q13: [{'id': 'https://metadata.un.org/sdg/7', 'score': 0.8799999952316284, 'display_name': 'Affordable and clean energy'}] | R13: [{'year': 2026, 'cited_by_count': 1}, {'year': 2025, 'cited_by_count': 11}, {'year': 2024, 'cited_by_count': 12}, {'year': 2023, 'cited_by_count': 22}, {'year': 2022, 'cited_by_count': 6}, {'year': 2021, 'cited_by_count': 10}]
... A114: https://openalex.org/W4385202502 | B114: https://doi.org/10.1016/j.aquatox.2023.106640 | C114: rGO outperforms GO in generating oxidative stress and DNA strand breaks in zebrafish liver cells | D114: 2023 | E114: 45131 | F114: {'openalex': 'https://openalex.org/W4385202502', 'doi': 'https://doi.org/10.1016/j.aquatox.2023.106640', 'pmid': 'https://pubmed.ncbi.nlm.nih.gov/37595501'} | G114: en | H114: article | I114: 3 | J114: 10 | K114: 0.5632 | L114: FALSE | M114: 5 | N114: {'value': 0.6152184, 'is_in_top_1_percent': False, 'is_in_top_10_percent': False} | O114: {'min': 89, 'max': 97} | P114: {'volume': '262', 'issue': None, 'first_page': '106640', 'last_page': '106640'} | Q114: [{'score': 0.699999988079071, 'id': 'https://metadata.un.org/sdg/14', 'display_name': 'Life below water'}] | R114: [{'year': 2025, 'cited_by_count': 1}, {'year': 2024, 'cited_by_count': 3}, {'year': 2023, 'cited_by_count': 1}]
A115: https://openalex.org/W3008540537 | B115: https://doi.org/10.1101/2020.02.24.963421 | C115: Convergent evolution of niche structure in Northeast Pacific kelp forests | D115: 2020 | E115: 43887 | F115: {'openalex': 'https://openalex.org/W3008540537', 'doi': 'https://doi.org/10.1101/2020.02.24.963421', 'mag': '3008540537'} | G115: en | H115: preprint | I115: 1 | J115: 4 | L115: TRUE | M115: 5 | P115: {'volume': None, 'issue': None, 'first_page': None, 'last_page': None} | Q115: [{'score': 0.6800000071525574, 'id': 'https://metadata.un.org/sdg/15', 'display_name': 'Life in Land'}] | R115: [{'year': 2024, 'cited_by_count': 2}, {'year': 2023, 'cited_by_count': 1}, {'year': 2020, 'cited_by_count': 2}]
A116: https://openalex.org/W4367367779 | B116: https://doi.org/10.1002/aisy.202300015 | C116: A 3Dâ€Printed Computer | D116: 2023 | E116: 45045 | F116: {'openalex': 'https://openalex.org/W4367367779', 'doi': 'https://doi.org/10.1002/aisy.202300015'} | G116: en | H116: article | I116: 1 | J116: 2 | K116: 0.7006 | L116: TRUE | M116: 4 | N116: {'value': 0.74358744, 'is_in_top_1_percent': False, 'is_in_top_10_percent': False} | O116: {'min': 89, 'max': 96} | P116: {'volume': '5', 'issue': '8', 'first_page': None, 'last_page': None} | Q116: [] | R116: [{'year': 2025, 'cited_by_count': 1}, {'year': 2024, 'cited_by_count': 2}, {'year': 2023, 'cited_by_count': 1}]
A117: https://openalex.org/W4200423026 | B117: https://doi.org/10.1109/wifs53200.2021.9648379 | C117: 3D Print-Scan Resilient Localized Mesh Watermarking | D117: 2021 | E117: 44537 | F117: {'openalex': 'https://openalex.org/W4200423026', 'doi': 'https://doi.org/10.1109/wifs53200.2021.9648379'} | G117: en | H117: article | I117: 2 | J117: 4 | K117: 0.2882 | L117: FALSE | M117: 4 | N117: {'value': 0.57455882, 'is_in_top_1_percent': False, 'is_in_top_10_percent': False} | O117: {'min': 89, 'max': 96} | P117: {'volume': None, 'issue': None, 'first_page': '1', 'last_page': '6'} | Q117: [] | R117: [{'year': 2023, 'cited_by_count': 1}, {'year': 2022, 'cited_by_count': 2}, {'year': 2012, 'cited_by_count': 1}]
A118: https://openalex.org/W4385251277 | B118: https://doi.org/10.1103/physrevlett.131.049701 | C118: Comment on â€œAnisotropic Scattering Caused by Apical Oxygen Vacancies in Thin Films of Overdoped High-Temperature Cuprate Superconductorsâ€ | D118: 2023 | E118: 45132 | F118: {'openalex': 'https://openalex.org/W4385251277', 'doi': 'https://doi.org/10.1103/physrevlett.131.049701', 'pmid': 'https://pubmed.ncbi.nlm.nih.gov/37566842'} | G118: en | H118: article | I118: 3 | J118: 7 | K118: 0.7707 | L118: FALSE | M118: 4 | N118: {'value': 0.68151869, 'is_in_top_1_percent': False, 'is_in_top_10_percent': False} | O118: {'min': 90, 'max': 96} | P118: {'volume': '131', 'issue': '4', 'first_page': '049701', 'last_page': '049701'} | Q118: [] | R118: [{'year': 2025, 'cited_by_count': 1}, {'year': 2024, 'cited_by_count': 1}, {'year': 2023, 'cited_by_count': 2}]
A119: https://openalex.org/W3037279216 | B119: https://doi.org/10.1016/b978-0-12-818475-2.00002-7 | C119: Mechanical properties of two-dimensional materials: atomistic modeling and future directions | D119: 2020 | E119: 43831 | F119: {'openalex': 'https://openalex.org/W3037279216', 'doi': 'https://doi.org/10.1016/b978-0-12-818475-2.00002-7', 'mag': '3037279216'} | G119: en | H119: book-chapter | I119: 1 | J119: 3 | K119: 1.888 | L119: FALSE | M119: 4 | N119: {'value': 0.86023959, 'is_in_top_1_percent': False, 'is_in_top_10_percent': False} | O119: {'min': 89, 'max': 96} | P119: {'volume': None, 'issue': None, 'first_page': '9', 'last_page': '35'} | Q119: [{'score': 0.4699999988079071, 'display_name': 'Industry, innovation and infrastructure', 'id': 'https://metadata.un.org/sdg/9'}] | R119: [{'year': 2023, 'cited_by_count': 1}, {'year': 2022, 'cited_by_count': 2}, {'year': 2021, 'cited_by_count': 1}]
A120: https://openalex.org/W3173423777 | B120: https://doi.org/10.1016/j.nanoen.2021.106280 | C120: Self-powered integrated opto-electro-mechanical nano-actuators | D120: 2021 | E120: 44371 | F120: {'openalex': 'https://openalex.org/W3173423777', 'doi': 'https://doi.org/10.1016/j.nanoen.2021.106280', 'mag': '3173423777'} | G120: en | H120: article | I120: 1 | J120: 2 | K120: 0.601 | L120: FALSE | M120: 4 | N120: {'value': 0.67230664, 'is_in_top_1_percent': False, 'is_in_top_10_percent': False} | O120: {'min': 89, 'max': 97} | P120: {'volume': '88', 'issue': None, 'first_page': '106280', 'last_page': '106280'} | Q120: [{'display_name': 'Affordable and clean energy', 'id': 'https://metadata.un.org/sdg/7', 'score': 0.9100000262260437}] | R120: [{'year': 2022, 'cited_by_count': 3}, {'year': 2021, 'cited_by_count': 1}]
A121: https://openalex.org/W4394579167 | B121: https://doi.org/10.1007/s13233-024-00261-x | C121: Heat-resistant luminescent films: a thermal study of fluorene/thiophene copolymer-elastomer blends | D121: 2024 | E121: 45390 | F121: {'openalex': 'https://openalex.org/W4394579167', 'doi': 'https://doi.org/10.1007/s13233-024-00261-x'} | G121: en | H121: article | I121: 2 | J121: 5 | K121: 0.7167 | L121: FALSE | M121: 4 | N121: {'value': 0.61852671, 'is_in_top_1_percent': False, 'is_in_top_10_percent': False} | O121: {'min': 91, 'max': 99} | P121: {'volume': '32', 'issue': '8', 'first_page': '757', 'last_page': '766'} | Q121: [] | R121: [{'year': 2026, 'cited_by_count': 1}, {'year': 2025, 'cited_by_count': 1}, {'year': 2024, 'cited_by_count': 2}]
A122: https://openalex.org/W4387937498 | B122: https://doi.org/10.1002/batt.202300367 | C122: Preconditioning Operation of Membraneless Vanadium Micro Redox Flow Batteries | D122: 2023 | E122: 45224 | F122: {'openalex': 'https://openalex.org/W4387937498', 'doi': 'https://doi.org/10.1002/batt.202300367'} | G122: en | H122: article | I122: 2 | J122: 6 | K122: 0.5361 | L122: FALSE | M122: 4 | N122: {'value': 0.6564174, 'is_in_top_1_percent': False, 'is_in_top_10_percent': False} | O122: {'min': 91, 'max': 97} | P122: {'volume': '7', 'issue': '2', 'first_page': None, 'last_page': None} | Q122: [{'display_name': 'Affordable and clean energy', 'id': 'https://metadata.un.org/sdg/7', 'score': 0.5899999737739563}] | R122: [{'year': 2025, 'cited_by_count': 1}, {'year': 2024, 'cited_by_count': 3}]
A123: https://openalex.org/W3136656899 | B123: https://doi.org/10.1002/aisy.202100003 | C123: Soft Bionic Sensors and Actuators | D123: 2021 | E123: 44256 | F123: {'openalex': 'https://openalex.org/W3136656899', 'doi': 'https://doi.org/10.1002/aisy.202100003', 'mag': '3136656899'} | G123: en | H123: article | I123: 2 | J123: 2 | K123: 0.3342 | L123: TRUE | M123: 4 | N123: {'value': 0.51777992, 'is_in_top_1_percent': False, 'is_in_top_10_percent': False} | O123: {'min': 89, 'max': 97} | P123: {'volume': '3', 'issue': '3', 'first_page': None, 'last_page': None} | Q123: [{'id': 'https://metadata.un.org/sdg/9', 'score': 0.47999998927116394, 'display_name': 'Industry, innovation and infrastructure'}] | R123: [{'year': 2024, 'cited_by_count': 3}, {'year': 2023, 'cited_by_count': 1}]
A124: https://openalex.org/W4308507325 | B124: https://doi.org/10.1088/1748-0221/17/11/c11002 | C124: Pre-production results from ATLAS ITk Strip Sensors Quality Assurance Testchip | D124: 2022 | E124: 44866 | F124: {'openalex': 'https://openalex.org/W4308507325', 'doi': 'https://doi.org/10.1088/1748-0221/17/11/c11002'} | G124: en | H124: article | I124: 6 | J124: 31 | K124: 0.497 | L124: FALSE | M124: 4 | N124: {'value': 0.90668791, 'is_in_top_1_percent': False, 'is_in_top_10_percent': True} | O124: {'min': 90, 'max': 97} | P124: {'volume': '17', 'issue': '11', 'first_page': 'C11002', 'last_page': 'C11002'} | Q124: [{'id': 'https://metadata.un.org/sdg/9', 'score': 0.5199999809265137, 'display_name': 'Industry, innovation and infrastructure'}] | R124: [{'year': 2024, 'cited_by_count': 1}, {'year': 2023, 'cited_by_count': 3}]
A125: https://openalex.org/W4402221351 | B125: https://doi.org/10.1016/j.jallcom.2024.176341 | C125: Cutting-edge developments in perovskite solar cells: The role of dimensional and mixed-dimensional engineering | D125: 2024 | E125: 45539 | F125: {'openalex': 'https://openalex.org/W4402221351', 'doi': 'https://doi.org/10.1016/j.jallcom.2024.176341'} | G125: en | H125: article | I125: 5 | J125: 6 | K125: 0.9227 | L125: FALSE | M125: 4 | N125: {'value': 0.74642119, 'is_in_top_1_percent': False, 'is_in_top_10_percent': False} | O125: {'min': 90, 'max': 97} | P125: {'volume': '1006', 'issue': None, 'first_page': '176341', 'last_page': '176341'} | Q125: [] | R125: [{'year': 2025, 'cited_by_count': 3}, {'year': 2024, 'cited_by_count': 1}]
A126: https://openalex.org/W4400528642 | B126: https://doi.org/10.1021/acsami.4c01045 | C126: Electrostatic Correlations Lead to High Capacitance in Zwitterion-Containing Thin Films | D126: 2024 | E126: 45484 | F126: {'openalex': 'https://openalex.org/W4400528642', 'doi': 'https://doi.org/10.1021/acsami.4c01045', 'pmid': 'https://pubmed.ncbi.nlm.nih.gov/38990772'} | G126: en | H126: article | I126: 2 | J126: 5 | K126: 0.3572 | L126: FALSE | M126: 3 | N126: {'value': 0.47464376, 'is_in_top_1_percent': False, 'is_in_top_10_percent': False} | O126: {'min': 96, 'max': 97} | P126: {'volume': '16', 'issue': '29', 'first_page': '38290', 'last_page': '38299'} | Q126: [{'display_name': 'Affordable and clean energy', 'score': 0.5699999928474426, 'id': 'https://metadata.un.org/sdg/7'}] | R126: [{'year': 2025, 'cited_by_count': 3}]
A127: https://openalex.org/W4400601698 | B127: https://doi.org/10.1016/j.enconman.2024.118780 | C127: Stationary thin film microgroove-based sorber reactor for sorption heat transformers: Surface modification, sorption dynamics, and crystallization | D127: 2024 | E127: 45486 | F127: {'openalex': 'https://openalex.org/W4400601698', 'doi': 'https://doi.org/10.1016/j.enconman.2024.118780'} | G127: en | H127: article | I127: 1 | J127: 3 | K127: 0.7099 | L127: FALSE | M127: 3 | N127: {'value': 0.64717391, 'is_in_top_1_percent': False, 'is_in_top_10_percent': False} | O127: {'min': 90, 'max': 96} | P127: {'volume': '315', 'issue': None, 'first_page': '118780', 'last_page': '118780'} | Q127: [] | R127: [{'year': 2025, 'cited_by_count': 2}, {'year': 2024, 'cited_by_count': 1}]
... A133: https://openalex.org/W3011360285 | B133: https://doi.org/10.1080/00207543.2020.1735656 | C133: M/PH/C queue under a congestion-based staffing policy with applications in steel industryÂ operations | D133: 2020 | E133: 43901 | F133: {'openalex': 'https://openalex.org/W3011360285', 'doi': 'https://doi.org/10.1080/00207543.2020.1735656', 'mag': '3011360285'} | G133: en | H133: article | I133: 3 | J133: 3 | K133: 0.5085 | L133: FALSE | M133: 3 | N133: {'value': 0.69348537, 'is_in_top_1_percent': False, 'is_in_top_10_percent': False} | O133: {'min': 89, 'max': 94} | P133: {'volume': '59', 'issue': '5', 'first_page': '1319', 'last_page': '1330'} | Q133: [{'score': 0.6600000262260437, 'id': 'https://metadata.un.org/sdg/9', 'display_name': 'Industry, innovation and infrastructure'}] | R133: [{'year': 2024, 'cited_by_count': 1}, {'year': 2021, 'cited_by_count': 1}, {'year': 2020, 'cited_by_count': 1}]
A134: https://openalex.org/W4399390162 | B134: https://doi.org/10.20944/preprints202406.0404.v1 | C134: Physics-Informed Online Learning for Temperature Prediction in Metal AM | D134: 2024 | E134: 45449 | F134: {'openalex': 'https://openalex.org/W4399390162', 'doi': 'https://doi.org/10.20944/preprints202406.0404.v1'} | G134: en | H134: preprint | I134: 1 | J134: 4 | L134: FALSE | M134: 3 | P134: {'volume': None, 'issue': None, 'first_page': None, 'last_page': None} | Q134: [] | R134: [{'year': 2026, 'cited_by_count': 1}, {'year': 2025, 'cited_by_count': 2}]
A135: https://openalex.org/W4393072836 | B135: https://doi.org/10.1111/sjtg.12539 | C135: Guest Editorial: The social life of Chinese infrastructures in Southeast Asia | D135: 2024 | E135: 45373 | F135: {'openalex': 'https://openalex.org/W4393072836', 'doi': 'https://doi.org/10.1111/sjtg.12539'} | G135: en | H135: editorial | I135: 2 | J135: 2 | K135: 11.940961 | L135: FALSE | M135: 3 | N135: {'value': 0.9622204, 'is_in_top_1_percent': False, 'is_in_top_10_percent': True} | O135: {'min': 96, 'max': 97} | P135: {'volume': '45', 'issue': '2', 'first_page': '169', 'last_page': '180'} | Q135: [{'display_name': 'Industry, innovation and infrastructure', 'score': 0.5400000214576721, 'id': 'https://metadata.un.org/sdg/9'}]
A136: https://openalex.org/W4386214571 | B136: https://doi.org/10.1109/fleps57599.2023.10220223 | C136: A 3D Printed Wearable Electromyography Wristband | D136: 2023 | E136: 45116 | F136: {'openalex': 'https://openalex.org/W4386214571', 'doi': 'https://doi.org/10.1109/fleps57599.2023.10220223'} | G136: en | H136: article | I136: 1 | J136: 4 | K136: 0.2253 | L136: FALSE | M136: 2 | N136: {'value': 0.47881622, 'is_in_top_1_percent': False, 'is_in_top_10_percent': False} | O136: {'min': 90, 'max': 95} | P136: {'volume': None, 'issue': None, 'first_page': '1', 'last_page': '4'} | Q136: [] | R136: [{'year': 2025, 'cited_by_count': 1}, {'year': 2024, 'cited_by_count': 1}]
A137: https://openalex.org/W4404316322 | B137: https://doi.org/10.1115/detc2024-142944 | C137: Low-Cost Melt Pool Temperature Prediction Using Visible Light Camera and Machine Learning in Laser Hot-Wire Directed Energy Deposition | D137: 2024 | E137: 45529 | F137: {'openalex': 'https://openalex.org/W4404316322', 'doi': 'https://doi.org/10.1115/detc2024-142944'} | G137: en | H137: article | I137: 1 | J137: 4 | K137: 0.4733 | L137: FALSE | M137: 2 | N137: {'value': 0.60384992, 'is_in_top_1_percent': False, 'is_in_top_10_percent': False} | O137: {'min': 91, 'max': 99} | P137: {'volume': None, 'issue': None, 'first_page': None, 'last_page': None} | Q137: [{'display_name': 'Affordable and clean energy', 'score': 0.8399999737739563, 'id': 'https://metadata.un.org/sdg/7'}] | R137: [{'year': 2026, 'cited_by_count': 1}, {'year': 2025, 'cited_by_count': 1}]
A138: https://openalex.org/W4387698028 | B138: https://doi.org/10.1088/1361-6528/ad0410 | C138: Editorial: Focus on green nanomaterials for a sustainable internet of things | D138: 2023 | E138: 45216 | F138: {'openalex': 'https://openalex.org/W4387698028', 'doi': 'https://doi.org/10.1088/1361-6528/ad0410', 'pmid': 'https://pubmed.ncbi.nlm.nih.gov/37848022'} | G138: en | H138: editorial | I138: 4 | J138: 6 | K138: 0.29970634 | L138: FALSE | M138: 2 | N138: {'value': 0.43692553, 'is_in_top_1_percent': False, 'is_in_top_10_percent': False} | O138: {'min': 90, 'max': 95} | P138: {'volume': '35', 'issue': '4', 'first_page': '040201', 'last_page': '040201'} | Q138: [{'display_name': 'Responsible consumption and production', 'score': 0.4399999976158142, 'id': 'https://metadata.un.org/sdg/12'}] | R138: [{'year': 2025, 'cited_by_count': 1}, {'year': 2024, 'cited_by_count': 1}]
A139: https://openalex.org/W4389118116 | B139: https://doi.org/10.1021/acs.chas.3c00072 | C139: Signage to Indicate the Presence of Engineered Nanomaterials in the Workplace: Lessons from a Trial Study That Led to Implementation in a Worksite | D139: 2023 | E139: 45259 | F139: {'openalex': 'https://openalex.org/W4389118116', 'doi': 'https://doi.org/10.1021/acs.chas.3c00072'} | G139: en | H139: article | I139: 2 | J139: 3 | K139: 1.3505 | L139: FALSE | M139: 2 | N139: {'value': 0.8986711, 'is_in_top_1_percent': False, 'is_in_top_10_percent': False} | O139: {'min': 90, 'max': 95} | P139: {'volume': '31', 'issue': '1', 'first_page': '77', 'last_page': '84'} | Q139: [] | R139: [{'year': 2025, 'cited_by_count': 1}, {'year': 2024, 'cited_by_count': 1}]
A140: https://openalex.org/W4401723141 | B140: https://doi.org/10.1103/physrevapplied.22.024058 | C140: Antiferromagnetic coupling across nonmagnetic transition-metal films alloyed with ferromagnetic elements | D140: 2024 | E140: 45525 | F140: {'openalex': 'https://openalex.org/W4401723141', 'doi': 'https://doi.org/10.1103/physrevapplied.22.024058'} | G140: en | H140: article | I140: 3 | J140: 10 | K140: 0.736 | L140: FALSE | M140: 2 | N140: {'value': 0.69511739, 'is_in_top_1_percent': False, 'is_in_top_10_percent': False} | O140: {'min': 95, 'max': 96} | P140: {'volume': '22', 'issue': '2', 'first_page': None, 'last_page': None} | Q140: [] | R140: [{'year': 2025, 'cited_by_count': 2}]
A141: https://openalex.org/W4319996310 | B141: https://doi.org/10.1109/jflex.2023.3237991 | C141: Speed and Scalability of Ambipolar Deep-Subthreshold TFTs for Ultralow-Power Printed Electronics | D141: 2023 | E141: 44927 | F141: {'openalex': 'https://openalex.org/W4319996310', 'doi': 'https://doi.org/10.1109/jflex.2023.3237991'} | G141: en | H141: article | I141: 2 | J141: 4 | K141: 0.2678 | L141: FALSE | M141: 2 | N141: {'value': 0.50497858, 'is_in_top_1_percent': False, 'is_in_top_10_percent': False} | O141: {'min': 89, 'max': 95} | P141: {'volume': '2', 'issue': '1', 'first_page': '11', 'last_page': '17'} | Q141: [{'id': 'https://metadata.un.org/sdg/7', 'score': 0.8799999952316284, 'display_name': 'Affordable and clean energy'}] | R141: [{'year': 2025, 'cited_by_count': 1}, {'year': 2023, 'cited_by_count': 1}]
A142: https://openalex.org/W4323318307 | B142: https://doi.org/10.3390/bioengineering10030326 | C142: Detecting Safety Anomalies in pHRI Activities via Force Myography | D142: 2023 | E142: 44990 | F142: {'openalex': 'https://openalex.org/W4323318307', 'doi': 'https://doi.org/10.3390/bioengineering10030326', 'pmid': 'https://pubmed.ncbi.nlm.nih.gov/36978717'} | G142: en | H142: article | I142: 1 | J142: 2 | K142: 0.225 | L142: FALSE | M142: 2 | N142: {'value': 0.45254565, 'is_in_top_1_percent': False, 'is_in_top_10_percent': False} | O142: {'min': 89, 'max': 95} | P142: {'volume': '10', 'issue': '3', 'first_page': '326', 'last_page': '326'} | Q142: [] | R142: [{'year': 2025, 'cited_by_count': 1}, {'year': 2023, 'cited_by_count': 1}]
A143: https://openalex.org/W4322731223 | B143: https://doi.org/10.1109/mems49605.2023.10052235 | C143: Modified Beam Structures for Improved Resonant Sensing | D143: 2023 | E143: 44941 | F143: {'openalex': 'https://openalex.org/W4322731223', 'doi': 'https://doi.org/10.1109/mems49605.2023.10052235'} | G143: en | H143: article | I143: 1 | J143: 2 | K143: 0.2836 | L143: FALSE | M143: 2 | N143: {'value': 0.51571983, 'is_in_top_1_percent': False, 'is_in_top_10_percent': False} | O143: {'min': 89, 'max': 94} | P143: {'volume': None, 'issue': None, 'first_page': '779', 'last_page': '782'} | Q143: [{'id': 'https://metadata.un.org/sdg/7', 'score': 0.5099999904632568, 'display_name': 'Affordable and clean energy'}] | R143: [{'year': 2024, 'cited_by_count': 1}, {'year': 2023, 'cited_by_count': 1}]
A144: https://openalex.org/W4391638944 | B144: https://doi.org/10.1149/ma2023-02371770mtgabs | C144: Measuring Thermal Conductivity of Single Thickness Fibrous Gas Diffusion Layers Using Transient Plane Source Method | D144: 2023 | E144: 45282 | F144: {'openalex': 'https://openalex.org/W4391638944', 'doi': 'https://doi.org/10.1149/ma2023-02371770mtgabs'} | G144: en | H144: article | I144: 1 | J144: 5 | K144: 0.4331 | L144: FALSE | M144: 2 | N144: {'value': 0.58864057, 'is_in_top_1_percent': False, 'is_in_top_10_percent': False} | O144: {'min': 95, 'max': 96} | P144: {'volume': 'MA2023-02', 'issue': '37', 'first_page': '1770', 'last_page': '1770'} | Q144: [{'id': 'https://metadata.un.org/sdg/6', 'score': 0.75, 'display_name': 'Clean water and sanitation'}] | R144: [{'year': 2025, 'cited_by_count': 2}]
A145: https://openalex.org/W3217242043 | B145: https://doi.org/10.1002/solr.202100992 | C145: Serendipitous Doping in Nickel Oxide upon Microwaveâ€Induced Lowâ€Temperature Crystallization Enhances Efficiency of Perovskite Solar Cells | D145: 2021 | E145: 44530 | F145: {'openalex': 'https://openalex.org/W3217242043', 'doi': 'https://doi.org/10.1002/solr.202100992', 'mag': '3217242043'} | G145: en | H145: article | I145: 3 | J145: 8 | K145: 0.2005 | L145: FALSE | M145: 2 | N145: {'value': 0.52472715, 'is_in_top_1_percent': False, 'is_in_top_10_percent': False} | O145: {'min': 94, 'max': 96} | P145: {'volume': '6', 'issue': '2', 'first_page': None, 'last_page': None} | Q145: [{'score': 0.7900000214576721, 'id': 'https://metadata.un.org/sdg/7', 'display_name': 'Affordable and clean energy'}] | R145: [{'year': 2023, 'cited_by_count': 2}]
A146: https://openalex.org/W4393064730 | B146: https://doi.org/10.1139/cjc-2023-0232 | C146: The success of computational material design for sustainable energy catalysis | D146: 2024 | E146: 45373 | F146: {'openalex': 'https://openalex.org/W4393064730', 'doi': 'https://doi.org/10.1139/cjc-2023-0232'} | G146: en | H146: article | I146: 2 | J146: 2 | K146: 0.1231 | L146: FALSE | M146: 1 | N146: {'value': 0.3662099, 'is_in_top_1_percent': False, 'is_in_top_10_percent': False} | O146: {'min': 90, 'max': 94} | P146: {'volume': '102', 'issue': '5', 'first_page': '298', 'last_page': '309'} | Q146: [] | R146: [{'year': 2024, 'cited_by_count': 1}]
A147: https://openalex.org/W4362664378 | B147: https://doi.org/10.1016/j.supflu.2023.105939 | C147: Solvent selection in physical supercritical fluid deposition | D147: 2023 | E147: 45022 | F147: {'openalex': 'https://openalex.org/W4362664378', 'doi': 'https://doi.org/10.1016/j.supflu.2023.105939'} | G147: en | H147: article | I147: 1 | J147: 2 | K147: 0.1126 | L147: FALSE | M147: 1 | N147: {'value': 0.3712048, 'is_in_top_1_percent': False, 'is_in_top_10_percent': False} | O147: {'min': 91, 'max': 95} | P147: {'volume': '198', 'issue': None, 'first_page': '105939', 'last_page': '105939'} | Q147: [] | R147: [{'year': 2025, 'cited_by_count': 1}]
... A160: https://openalex.org/W4285399112 | B160: https://doi.org/10.1149/ma2022-01412468mtgabs | C160: Modeling and Simulation of the Mechanical Properties of Reinforced Fuel Cell Membranes | D160: 2022 | E160: 44749 | F160: {'openalex': 'https://openalex.org/W4285399112', 'doi': 'https://doi.org/10.1149/ma2022-01412468mtgabs'} | G160: en | H160: article | I160: 1 | J160: 3 | K160: 0.0915 | L160: FALSE | M160: 1 | N160: {'value': 0.39155855, 'is_in_top_1_percent': False, 'is_in_top_10_percent': False} | O160: {'min': 90, 'max': 94} | P160: {'volume': 'MA2022-01', 'issue': '41', 'first_page': '2468', 'last_page': '2468'} | Q160: [{'score': 0.46000000834465027, 'id': 'https://metadata.un.org/sdg/7', 'display_name': 'Affordable and clean energy'}] | R160: [{'year': 2024, 'cited_by_count': 1}]
A161: https://openalex.org/W4386211272 | B161: https://doi.org/10.1109/fleps57599.2023.10220417 | C161: A 3D Printed Architecture Sensor for Structural Health Monitoring | D161: 2023 | E161: 45116 | F161: {'openalex': 'https://openalex.org/W4386211272', 'doi': 'https://doi.org/10.1109/fleps57599.2023.10220417'} | G161: en | H161: article | I161: 1 | J161: 3 | K161: 0 | L161: FALSE | M161: 0 | N161: {'value': 0.10846288, 'is_in_top_1_percent': False, 'is_in_top_10_percent': False} | P161: {'volume': None, 'issue': None, 'first_page': '1', 'last_page': '4'} | Q161: [] | R161: []
A162: https://openalex.org/W4404633749 | B162: https://doi.org/10.1016/b978-0-323-95478-5.00044-3 | C162: Microfabrication Techniques for Creating Cell Culture Substrates | D162: 2024 | E162: 45619 | F162: {'openalex': 'https://openalex.org/W4404633749', 'doi': 'https://doi.org/10.1016/b978-0-323-95478-5.00044-3'} | G162: en | H162: book-chapter | I162: 1 | J162: 4 | K162: 0 | L162: FALSE | M162: 0 | N162: {'value': 0.54979686, 'is_in_top_1_percent': False, 'is_in_top_10_percent': False} | P162: {'volume': None, 'issue': None, 'first_page': '243', 'last_page': '250'} | Q162: [{'id': 'https://metadata.un.org/sdg/2', 'score': 0.44999998807907104, 'display_name': 'Zero hunger'}] | R162: []
A163: https://openalex.org/W4398151864 | B163: https://doi.org/10.2139/ssrn.4834657 | C163: The Total Heat Transfer Rate in the Evaporating Thin Film: A New Analytical Solution | D163: 2024 | E163: 45292 | F163: {'openalex': 'https://openalex.org/W4398151864', 'doi': 'https://doi.org/10.2139/ssrn.4834657'} | G163: en | H163: preprint | I163: 1 | J163: 3 | L163: FALSE | M163: 0 | P163: {'volume': None, 'issue': None, 'first_page': None, 'last_page': None} | Q163: [{'id': 'https://metadata.un.org/sdg/6', 'score': 0.5600000023841858, 'display_name': 'Clean water and sanitation'}] | R163: []
A164: https://openalex.org/W3024614237 | B164: https://doi.org/10.1149/ma2020-01462626mtgabs | C164: Gold-Copper Metal Alloys: Crystalline Materials for the CO<sub>2</sub> Reduction Reaction | D164: 2020 | E164: 43952 | F164: {'openalex': 'https://openalex.org/W3024614237', 'doi': 'https://doi.org/10.1149/ma2020-01462626mtgabs', 'mag': '3024614237'} | G164: en | H164: article | I164: 1 | J164: 2 | K164: 0 | L164: FALSE | M164: 0 | N164: {'value': 0.03394662, 'is_in_top_1_percent': False, 'is_in_top_10_percent': False} | P164: {'volume': 'MA2020-01', 'issue': '46', 'first_page': '2626', 'last_page': '2626'} | Q164: [] | R164: []
A165: https://openalex.org/W4312707143 | B165: https://doi.org/10.1115/detc2022-89511 | C165: Iterative Uncertainty Calibration for Modeling Metal Additive Manufacturing Processes Using Statistical Moment-Based Metric | D165: 2022 | E165: 44787 | F165: {'openalex': 'https://openalex.org/W4312707143', 'doi': 'https://doi.org/10.1115/detc2022-89511'} | G165: en | H165: article | I165: 1 | J165: 3 | K165: 0 | L165: FALSE | M165: 0 | N165: {'value': 0.18620448, 'is_in_top_1_percent': False, 'is_in_top_10_percent': False} | P165: {'volume': None, 'issue': None, 'first_page': None, 'last_page': None} | Q165: [] | R165: []
A166: https://openalex.org/W4310745399 | B166: https://doi.org/10.48550/arxiv.2212.01137 | C166: Depth-resolved measurement of the Meissner screening profile in a niobium thin film from spin-lattice relaxation of the implanted $Î²$-emitter $^{8}$Li | D166: 2022 | E166: 44897 | F166: {'openalex': 'https://openalex.org/W4310745399', 'doi': 'https://doi.org/10.48550/arxiv.2212.01137'} | G166: en | H166: preprint | I166: 1 | J166: 14 | L166: FALSE | M166: 0 | P166: {'volume': None, 'issue': None, 'first_page': None, 'last_page': None} | Q166: [] | R166: []
A167: https://openalex.org/W4402512755 | B167: https://doi.org/10.1016/j.renene.2024.121338 | C167: A novel membrane-based absorber for sorption heat transformers: A comparative experimental study of a thin-film absorbent and salt-impregnated adsorbents | D167: 2024 | E167: 45548 | F167: {'openalex': 'https://openalex.org/W4402512755', 'doi': 'https://doi.org/10.1016/j.renene.2024.121338'} | G167: en | H167: article | I167: 1 | J167: 5 | K167: 0 | L167: FALSE | M167: 0 | N167: {'value': 0.15149304, 'is_in_top_1_percent': False, 'is_in_top_10_percent': False} | P167: {'volume': '235', 'issue': None, 'first_page': '121338', 'last_page': '121338'} | Q167: [{'score': 0.4000000059604645, 'display_name': 'Affordable and clean energy', 'id': 'https://metadata.un.org/sdg/7'}] | R167: []
A168: https://openalex.org/W4392704888 | B168: https://doi.org/10.29363/nanoge.matsus.2024.301 | C168: Computational Screening Of Non-copper-based Catalysts For Electrochemical CO2 Reduction Reaction | D168: 2023 | E168: 45278 | F168: {'openalex': 'https://openalex.org/W4392704888', 'doi': 'https://doi.org/10.29363/nanoge.matsus.2024.301'} | G168: en | H168: article | I168: 1 | J168: 1 | K168: 0 | L168: FALSE | M168: 0 | N168: {'value': 0.14369067, 'is_in_top_1_percent': False, 'is_in_top_10_percent': False} | P168: {'volume': None, 'issue': None, 'first_page': None, 'last_page': None} | Q168: [] | R168: []
A169: https://openalex.org/W4392704354 | B169: https://doi.org/10.29363/nanoge.matsus.2024.316 | C169: Computational Design of Two-dimensional Materials for Electrocatalysis | D169: 2023 | E169: 45278 | F169: {'openalex': 'https://openalex.org/W4392704354', 'doi': 'https://doi.org/10.29363/nanoge.matsus.2024.316'} | G169: en | H169: article | I169: 1 | J169: 1 | K169: 0 | L169: FALSE | M169: 0 | N169: {'value': 0.18066588, 'is_in_top_1_percent': False, 'is_in_top_10_percent': False} | P169: {'volume': None, 'issue': None, 'first_page': None, 'last_page': None} | Q169: [] | R169: []
A170: https://openalex.org/W4401269834 | B170: https://doi.org/10.1016/j.energy.2024.132617 | C170: A novel microgroove-based absorber for sorption heat transformation systems: Analytical modeling and experimental investigation | D170: 2024 | E170: 45506 | F170: {'openalex': 'https://openalex.org/W4401269834', 'doi': 'https://doi.org/10.1016/j.energy.2024.132617'} | G170: en | H170: article | I170: 1 | J170: 3 | K170: 0 | L170: FALSE | M170: 0 | N170: {'value': 0.11807571, 'is_in_top_1_percent': False, 'is_in_top_10_percent': False} | P170: {'volume': '307', 'issue': None, 'first_page': '132617', 'last_page': '132617'} | Q170: [{'score': 0.47999998927116394, 'id': 'https://metadata.un.org/sdg/7', 'display_name': 'Affordable and clean energy'}] | R170: []
A171: https://openalex.org/W3117209513 | B171: https://doi.org/10.1149/ma2020-02352253mtgabs | C171: Cumulative Damage Modeling of Fuel Cell Membranes | D171: 2020 | E171: 44158 | F171: {'openalex': 'https://openalex.org/W3117209513', 'doi': 'https://doi.org/10.1149/ma2020-02352253mtgabs', 'mag': '3117209513'} | G171: en | H171: article | I171: 1 | J171: 4 | K171: 0 | L171: FALSE | M171: 0 | N171: {'value': 0.14442036, 'is_in_top_1_percent': False, 'is_in_top_10_percent': False} | P171: {'volume': 'MA2020-02', 'issue': '35', 'first_page': '2253', 'last_page': '2253'} | Q171: [{'score': 0.4399999976158142, 'id': 'https://metadata.un.org/sdg/7', 'display_name': 'Affordable and clean energy'}] | R171: []
A172: https://openalex.org/W4312847846 | B172: https://doi.org/10.1109/ifetc53656.2022.9948498 | C172: Message from the Organising Committee | D172: 2022 | E172: 44794 | F172: {'openalex': 'https://openalex.org/W4312847846', 'doi': 'https://doi.org/10.1109/ifetc53656.2022.9948498'} | G172: en | H172: article | I172: 5 | J172: 15 | L172: FALSE | M172: 0 | P172: {'volume': None, 'issue': None, 'first_page': 'vi', 'last_page': 'vi'} | Q172: [] | R172: []
A173: https://openalex.org/W4207034161 | B173: https://doi.org/10.1109/nmdc50713.2021.9677477 | C173: Individual Nanoflakes of Two Dimensional Materials Harmonic Generation with Ultralow Pump Power | D173: 2021 | E173: 44542 | F173: {'openalex': 'https://openalex.org/W4207034161', 'doi': 'https://doi.org/10.1109/nmdc50713.2021.9677477'} | G173: en | H173: article | I173: 1 | J173: 6 | K173: 0 | L173: FALSE | M173: 0 | N173: {'value': 0.18656309, 'is_in_top_1_percent': False, 'is_in_top_10_percent': False} | P173: {'volume': '100', 'issue': None, 'first_page': '1', 'last_page': '4'} | Q173: [{'score': 0.7799999713897705, 'id': 'https://metadata.un.org/sdg/7', 'display_name': 'Affordable and clean energy'}] | R173: []
A174: https://openalex.org/W4402588229 | B174: https://doi.org/10.48550/arxiv.2407.17575 | C174: Transition from ferromagnetic to noncollinear to paramagnetic state with increasing Ru concentration in FeRu films | D174: 2024 | E174: 45497 | F174: {'openalex': 'https://openalex.org/W4402588229', 'doi': 'https://doi.org/10.48550/arxiv.2407.17575'} | G174: en | H174: preprint | I174: 3 | J174: 14 | L174: FALSE | M174: 0 | P174: {'volume': None, 'issue': None, 'first_page': None, 'last_page': None} | Q174: [] | R174: []
A175: https://openalex.org/W4402813081 | B175: https://doi.org/10.1103/physrevb.110.104429 | C175: Transition from ferromagnetic to noncollinear to paramagnetic state with increasing Ru concentration in FeRu films | D175: 2024 | E175: 45559 | F175: {'openalex': 'https://openalex.org/W4402813081', 'doi': 'https://doi.org/10.1103/physrevb.110.104429'} | G175: en | H175: article | I175: 3 | J175: 14 | K175: 0 | L175: FALSE | M175: 0 | N175: {'value': 0.14487439, 'is_in_top_1_percent': False, 'is_in_top_10_percent': False} | P175: {'volume': '110', 'issue': '10', 'first_page': None, 'last_page': None} | Q175: [] | R175: []
A176: https://openalex.org/W3209077064 | B176: https://doi.org/10.33774/chemrxiv-2021-lj2bz | C176: High-Performance, Single-Crystal Gold Bowtie Nano-Antennas via Epitaxial Electroless Deposition | D176: 2021 | E176: 44452 | F176: {'openalex': 'https://openalex.org/W3209077064', 'doi': 'https://doi.org/10.33774/chemrxiv-2021-lj2bz', 'mag': '3209077064'} | G176: en | H176: preprint | I176: 1 | J176: 3 | K176: 0 | L176: FALSE | M176: 0 | N176: {'value': 0.09730379, 'is_in_top_1_percent': False, 'is_in_top_10_percent': False} | P176: {'volume': None, 'issue': None, 'first_page': None, 'last_page': None} | Q176: [] | R176: []
A177: https://openalex.org/W4309813892 | B177: https://doi.org/10.1149/ma2022-02401481mtgabs | C177: Effects of Wet Film Application Parameters on the Structure and Performance of Fuel Cell Catalyst Layers Prepared Using Scalable Methods | D177: 2022 | E177: 44843 | F177: {'openalex': 'https://openalex.org/W4309813892', 'doi': 'https://doi.org/10.1149/ma2022-02401481mtgabs'} | G177: en | H177: article | I177: 1 | J177: 3 | K177: 0 | L177: FALSE | M177: 0 | N177: {'value': 0.0976117, 'is_in_top_1_percent': False, 'is_in_top_10_percent': False} | P177: {'volume': 'MA2022-02', 'issue': '40', 'first_page': '1481', 'last_page': '1481'} | Q177: [] | R177: []
A178: https://openalex.org/W4285398177 | B178: https://doi.org/10.1149/ma2022-0113925mtgabs | C178: Hot Electron Extraction Enabled By Single-Crystal Metal Films and Nanostructures | D178: 2022 | E178: 44749 | F178: {'openalex': 'https://openalex.org/W4285398177', 'doi': 'https://doi.org/10.1149/ma2022-0113925mtgabs'} | G178: en | H178: article | I178: 1 | J178: 5 | K178: 0 | L178: FALSE | M178: 0 | N178: {'value': 0.04447675, 'is_in_top_1_percent': False, 'is_in_top_10_percent': False} | P178: {'volume': 'MA2022-01', 'issue': '13', 'first_page': '925', 'last_page': '925'} | Q178: [{'display_name': 'Affordable and clean energy', 'score': 0.4399999976158142, 'id': 'https://metadata.un.org/sdg/7'}] | R178: []
A179: https://openalex.org/W4309813911 | B179: https://doi.org/10.1149/ma2022-02401482mtgabs | C179: Optimized Decal Transfer Method for the Mitigation of Incidental Particle Deposition at the Interface of Proton Exchange Membranes and Catalyst Layers | D179: 2022 | E179: 44843 | F179: {'openalex': 'https://openalex.org/W4309813911', 'doi': 'https://doi.org/10.1149/ma2022-02401482mtgabs'} | G179: en | H179: article | I179: 2 | J179: 8 | K179: 0 | L179: FALSE | M179: 0 | N179: {'value': 0.09763409, 'is_in_top_1_percent': False, 'is_in_top_10_percent': False} | P179: {'volume': 'MA2022-02', 'issue': '40', 'first_page': '1482', 'last_page': '1482'} | Q179: [{'display_name': 'Industry, innovation and infrastructure', 'score': 0.5799999833106995, 'id': 'https://metadata.un.org/sdg/9'}] | R179: []
A180: https://openalex.org/W4285399167 | B180: https://doi.org/10.1149/ma2022-01552300mtgabs | C180: Niobium Oxide Coated Mesoporous Platinum Nanoparticles for the Oxygen Reduction Reaction | D180: 2022 | E180: 44749 | F180: {'openalex': 'https://openalex.org/W4285399167', 'doi': 'https://doi.org/10.1149/ma2022-01552300mtgabs'} | G180: en | H180: article | I180: 1 | J180: 3 | K180: 0 | L180: FALSE | M180: 0 | N180: {'value': 0.04223857, 'is_in_top_1_percent': False, 'is_in_top_10_percent': False} | P180: {'volume': 'MA2022-01', 'issue': '55', 'first_page': '2300', 'last_page': '2300'} | Q180: [{'display_name': 'Affordable and clean energy', 'score': 0.7900000214576721, 'id': 'https://metadata.un.org/sdg/7'}] | R180: []
A181: https://openalex.org/W3217264739 | B181: https://doi.org/10.1016/b978-0-12-823708-3.00005-5 | C181: Advanced modifications in nonnoble materials for proton exchange membrane | D181: 2021 | E181: 44519 | F181: {'openalex': 'https://openalex.org/W3217264739', 'doi': 'https://doi.org/10.1016/b978-0-12-823708-3.00005-5', 'mag': '3217264739'} | G181: en | H181: book-chapter | I181: 2 | J181: 2 | K181: 0 | L181: FALSE | M181: 0 | N181: {'value': 0.31518102, 'is_in_top_1_percent': False, 'is_in_top_10_percent': False} | P181: {'volume': None, 'issue': None, 'first_page': '243', 'last_page': '277'} | Q181: [{'display_name': 'Responsible consumption and production', 'score': 0.4000000059604645, 'id': 'https://metadata.un.org/sdg/12'}] | R181: []
A182: https://openalex.org/W4391270781 | B182: https://doi.org/10.1117/12.3003437 | C182: Segmental airway phantom for endobronchial optical coherence tomography | D182: 2024 | E182: 45317 | F182: {'openalex': 'https://openalex.org/W4391270781', 'doi': 'https://doi.org/10.1117/12.3003437'} | G182: en | H182: article | I182: 1 | J182: 6 | K182: 0 | L182: FALSE | M182: 0 | N182: {'value': 0.01700399, 'is_in_top_1_percent': False, 'is_in_top_10_percent': False} | P182: {'volume': None, 'issue': None, 'first_page': '25', 'last_page': '25'} | Q182: [] | R182: []
A183: https://openalex.org/W4400068792 | B183: https://doi.org/10.2139/ssrn.4877451 | C183: Developing a Soft Micropatterned Substrate to Enhance Maturation of Human Induced Pluripotent Stem Cell-Derived Cardiomyocytes&amp;nbsp;(hiPSC-CMs) | D183: 2024 | E183: 45292 | F183: {'openalex': 'https://openalex.org/W4400068792', 'doi': 'https://doi.org/10.2139/ssrn.4877451'} | G183: en | H183: preprint | I183: 1 | J183: 5 | L183: FALSE | M183: 0 | P183: {'volume': None, 'issue': None, 'first_page': None, 'last_page': None} | Q183: [{'display_name': 'Zero hunger', 'score': 0.7300000190734863, 'id': 'https://metadata.un.org/sdg/2'}] | R183: []
A184: https://openalex.org/W4400619239 | B184: https://doi.org/10.1101/2024.07.12.599409 | C184: Developing a Soft Micropatterned Substrate to Enhance Maturation of Human Induced Pluripotent Stem Cell-Derived Cardiomyocytes (hiPSC-CMs) | D184: 2024 | E184: 45486 | F184: {'openalex': 'https://openalex.org/W4400619239', 'doi': 'https://doi.org/10.1101/2024.07.12.599409'} | G184: en | H184: preprint | I184: 1 | J184: 5 | L184: FALSE | M184: 0 | P184: {'volume': None, 'issue': None, 'first_page': None, 'last_page': None} | Q184: [] | R184: []
A185: https://openalex.org/W4403486965 | B185: https://doi.org/10.1115/1.4066889 | C185: Design, Analysis, and Testing of an Additively Manufactured Catalytic Combustor for a Micro-Wave Rotor Turbine | D185: 2024 | E185: 45582 | F185: {'openalex': 'https://openalex.org/W4403486965', 'doi': 'https://doi.org/10.1115/1.4066889'} | G185: en | H185: article | I185: 3 | J185: 4 | K185: 0 | L185: FALSE | M185: 0 | N185: {'value': 0.20210283, 'is_in_top_1_percent': False, 'is_in_top_10_percent': False} | P185: {'volume': '147', 'issue': '7', 'first_page': None, 'last_page': None} | Q185: [{'display_name': 'Affordable and clean energy', 'score': 0.800000011920929, 'id': 'https://metadata.un.org/sdg/7'}] | R185: []
A186: https://openalex.org/W4401941713 | B186: https://doi.org/10.1115/gt2024-125961 | C186: Design, Analysis, and Testing of an Additively Manufactured Catalytic Combustor for a Micro-Wave Rotor Turbine | D186: 2024 | E186: 45467 | F186: {'openalex': 'https://openalex.org/W4401941713', 'doi': 'https://doi.org/10.1115/gt2024-125961'} | G186: en | H186: article | I186: 3 | J186: 4 | K186: 0 | L186: FALSE | M186: 0 | N186: {'value': 0.15012181, 'is_in_top_1_percent': False, 'is_in_top_10_percent': False} | P186: {'volume': None, 'issue': None, 'first_page': None, 'last_page': None} | Q186: [{'display_name': 'Affordable and clean energy', 'score': 0.800000011920929, 'id': 'https://metadata.un.org/sdg/7'}] | R186: []
A187: https://openalex.org/W4391402871 | B187: https://doi.org/10.22541/au.170670450.06565845/v1 | C187: Growth-promoting Effect of Graphene Oxide on Tissue Culture Seedlings of Poplar | D187: 2024 | E187: 45322 | F187: {'openalex': 'https://openalex.org/W4391402871', 'doi': 'https://doi.org/10.22541/au.170670450.06565845/v1'} | G187: en | H187: preprint | I187: 3 | J187: 12 | K187: 0 | L187: FALSE | M187: 0 | N187: {'value': 0.01096726, 'is_in_top_1_percent': False, 'is_in_top_10_percent': False} | P187: {'volume': None, 'issue': None, 'first_page': None, 'last_page': None} | Q187: [] | R187: []
A188: https://openalex.org/W4285399147 | B188: https://doi.org/10.1149/ma2022-01552295mtgabs | C188: Cathodic Pd<sub>1-X</sub>Ni<sub>X</sub> Nanocatalyst Development for Alkaline Fuel Cell Applications | D188: 2022 | E188: 44749 | F188: {'openalex': 'https://openalex.org/W4285399147', 'doi': 'https://doi.org/10.1149/ma2022-01552295mtgabs'} | G188: en | H188: article | I188: 1 | J188: 6 | K188: 0 | L188: FALSE | M188: 0 | N188: {'value': 0.04218169, 'is_in_top_1_percent': False, 'is_in_top_10_percent': False} | P188: {'volume': 'MA2022-01', 'issue': '55', 'first_page': '2295', 'last_page': '2295'} | Q188: [{'display_name': 'Affordable and clean energy', 'score': 0.8100000023841858, 'id': 'https://metadata.un.org/sdg/7'}] | R188: []
A189: https://openalex.org/W4285399061 | B189: https://doi.org/10.1149/ma2022-01532200mtgabs | C189: (Invited) Textile-based Electronic/fluidic Platforms Towards Wearable Diagnostic Sensor Systems | D189: 2022 | E189: 44749 | F189: {'openalex': 'https://openalex.org/W4285399061', 'doi': 'https://doi.org/10.1149/ma2022-01532200mtgabs'} | G189: en | H189: article | I189: 1 | J189: 1 | K189: 0 | L189: FALSE | M189: 0 | N189: {'value': 0.06345257, 'is_in_top_1_percent': False, 'is_in_top_10_percent': False} | P189: {'volume': 'MA2022-01', 'issue': '53', 'first_page': '2200', 'last_page': '2200'} | Q189: [] | R189: []
A190: https://openalex.org/W3114285583 | B190: https://doi.org/10.1149/ma2020-02332130mtgabs | C190: In-Situ Capabilities of Lab-Based X-Ray Microscopy for Polymer Electrolyte Fuel Cells | D190: 2020 | E190: 44158 | F190: {'openalex': 'https://openalex.org/W3114285583', 'doi': 'https://doi.org/10.1149/ma2020-02332130mtgabs', 'mag': '3114285583'} | G190: en | H190: article | I190: 2 | J190: 3 | K190: 0 | L190: FALSE | M190: 0 | N190: {'value': 0.13533435, 'is_in_top_1_percent': False, 'is_in_top_10_percent': False} | P190: {'volume': 'MA2020-02', 'issue': '33', 'first_page': '2130', 'last_page': '2130'} | Q190: [{'display_name': 'Affordable and clean energy', 'score': 0.4699999988079071, 'id': 'https://metadata.un.org/sdg/7'}] | R190: []
A191: https://openalex.org/W4400275084 | B191: https://doi.org/10.1109/jflex.2024.3408001 | C191: Guest Editorial Special Issue on Self-Powered Sensors and Wearable Electronic Systems | D191: 2024 | E191: 45383 | F191: {'openalex': 'https://openalex.org/W4400275084', 'doi': 'https://doi.org/10.1109/jflex.2024.3408001'} | G191: en | H191: editorial | I191: 3 | J191: 4 | K191: 0 | L191: FALSE | M191: 0 | N191: {'value': 0.08989913, 'is_in_top_1_percent': False, 'is_in_top_10_percent': False} | P191: {'volume': '3', 'issue': '4', 'first_page': '118', 'last_page': '119'} | Q191: [{'display_name': 'Affordable and clean energy', 'score': 0.4300000071525574, 'id': 'https://metadata.un.org/sdg/7'}] | R191: []
A192: https://openalex.org/W4391663218 | B192: https://doi.org/10.1149/ma2023-02391922mtgabs | C192: In-Situ Fatigue Lifetime Modeling of a Reinforced Membrane by Projecting Critical Accumulated Plastic Dissipation Energy from Pressure Differential-Accelerated Mechanical Stress Tests | D192: 2023 | E192: 45282 | F192: {'openalex': 'https://openalex.org/W4391663218', 'doi': 'https://doi.org/10.1149/ma2023-02391922mtgabs'} | G192: en | H192: article | I192: 1 | J192: 3 | K192: 0 | L192: FALSE | M192: 0 | N192: {'value': 0.19508956, 'is_in_top_1_percent': False, 'is_in_top_10_percent': False} | P192: {'volume': 'MA2023-02', 'issue': '39', 'first_page': '1922', 'last_page': '1922'} | Q192: [{'display_name': 'Affordable and clean energy', 'score': 0.8399999737739563, 'id': 'https://metadata.un.org/sdg/7'}] | R192: []
A193: https://openalex.org/W4309811627 | B193: https://doi.org/10.1149/ma2022-02431616mtgabs | C193: Polythiophene, Polypyrrole and Carbon Nanotube-Based Catalyst for Alkaline Membrane Fuel Cell Cathode | D193: 2022 | E193: 44843 | F193: {'openalex': 'https://openalex.org/W4309811627', 'doi': 'https://doi.org/10.1149/ma2022-02431616mtgabs'} | G193: en | H193: article | I193: 2 | J193: 12 | K193: 0 | L193: FALSE | M193: 0 | N193: {'value': 0.09650986, 'is_in_top_1_percent': False, 'is_in_top_10_percent': False} | P193: {'volume': 'MA2022-02', 'issue': '43', 'first_page': '1616', 'last_page': '1616'} | Q193: [{'display_name': 'Industry, innovation and infrastructure', 'score': 0.4099999964237213, 'id': 'https://metadata.un.org/sdg/9'}] | R193: []
A194: https://openalex.org/W4391662651 | B194: https://doi.org/10.1149/ma2023-02391920mtgabs | C194: High Durability of Pemion<sup>Â®</sup> Proton Exchange Membranes in Cross-Pressure Accelerated Mechanical Stress Tests | D194: 2023 | E194: 45282 | F194: {'openalex': 'https://openalex.org/W4391662651', 'doi': 'https://doi.org/10.1149/ma2023-02391920mtgabs'} | G194: en | H194: article | I194: 1 | J194: 8 | K194: 0 | L194: FALSE | M194: 0 | N194: {'value': 0.1941071, 'is_in_top_1_percent': False, 'is_in_top_10_percent': False} | P194: {'volume': 'MA2023-02', 'issue': '39', 'first_page': '1920', 'last_page': '1920'} | Q194: [{'display_name': 'Industry, innovation and infrastructure', 'score': 0.6100000143051147, 'id': 'https://metadata.un.org/sdg/9'}] | R194: []
A195: https://openalex.org/W3114589188 | B195: https://doi.org/10.1149/ma2020-02372361mtgabs | C195: Transition Metal-Containing Nitrogen-Doped Nanocarbons Derived from 5-Methylresorcinol for Anion Exchange Membrane Fuel Cell Application | D195: 2020 | E195: 44158 | F195: {'openalex': 'https://openalex.org/W3114589188', 'doi': 'https://doi.org/10.1149/ma2020-02372361mtgabs', 'mag': '3114589188'} | G195: en | H195: article | I195: 3 | J195: 14 | K195: 0 | L195: FALSE | M195: 0 | N195: {'value': 0.13624321, 'is_in_top_1_percent': False, 'is_in_top_10_percent': False} | P195: {'volume': 'MA2020-02', 'issue': '37', 'first_page': '2361', 'last_page': '2361'} | Q195: [] | R195: []
A196: https://openalex.org/W4285398133 | B196: https://doi.org/10.1149/ma2022-01351418mtgabs | C196: Fe- and Co-Containing Nitrogen-Doped Nanocarbon Catalysts from 5-Methylresorcinol for Anion Exchange Membrane Fuel Cells | D196: 2022 | E196: 44749 | F196: {'openalex': 'https://openalex.org/W4285398133', 'doi': 'https://doi.org/10.1149/ma2022-01351418mtgabs'} | G196: en | H196: article | I196: 3 | J196: 15 | K196: 0 | L196: FALSE | M196: 0 | N196: {'value': 0.04043755, 'is_in_top_1_percent': False, 'is_in_top_10_percent': False} | P196: {'volume': 'MA2022-01', 'issue': '35', 'first_page': '1418', 'last_page': '1418'} | Q196: [] | R196: []
... A199: https://openalex.org/W4309811892 | B199: https://doi.org/10.1149/ma2022-02391413mtgabs | C199: Visualization of Water Distribution in Fuel Cell Microporous and Catalyst Layers with 3D Nanoscale X-Ray Imaging | D199: 2022 | E199: 44843 | F199: {'openalex': 'https://openalex.org/W4309811892', 'doi': 'https://doi.org/10.1149/ma2022-02391413mtgabs'} | G199: en | H199: article | I199: 1 | J199: 6 | K199: 0 | L199: FALSE | M199: 0 | N199: {'value': 0.11253197, 'is_in_top_1_percent': False, 'is_in_top_10_percent': False} | P199: {'volume': 'MA2022-02', 'issue': '39', 'first_page': '1413', 'last_page': '1413'} | Q199: [] | R199: []
A200: https://openalex.org/W4391536973 | B200: https://doi.org/10.21203/rs.3.rs-3884985/v1 | C200: Mn-inlaid antiphase boundaries in perovskite structure | D200: 2024 | E200: 45327 | F200: {'openalex': 'https://openalex.org/W4391536973', 'doi': 'https://doi.org/10.21203/rs.3.rs-3884985/v1'} | G200: en | H200: preprint

Sheet rio results
A1: Authors | B1: Author full names | C1: Author(s) ID | D1: Title | E1: Year | F1: Source title | G1: Volume | H1: Issue | I1: Art. No. | J1: Page start | K1: Page end | L1: Cited by | M1: DOI | N1: Link | O1: Affiliations | P1: Authors with affiliations | Q1: Correspondence Address | R1: Editors | S1: Publisher | T1: ISSN | U1: ISBN | V1: CODEN | W1: PubMed ID | X1: Language of Original Document | Y1: Abbreviated Source Title | Z1: Document Type | AA1: Publication Stage | AB1: Open Access | AC1: Source | AD1: EID
A2: Zhang, L.; Zhou, A.G.; Sun, B.R.; Chen, K.S.; Yu, H.-Z. | B2: Zhang, Lishen (57197774098); Zhou, Alvin G.C. (57221976275); Sun, Brigitta R. (57221981307); Chen, Kennedy S. (57215129380); Yu, Huazhong Hogan (7405855808) | C2: 57197774098; 57221976275; 57221981307; 57215129380; 7405855808 | D2: Functional and versatile superhydrophobic coatings via stoichiometric silanization | E2: 2021 | F2: Nature Communications | G2: 12 | H2: 1 | I2: 982 | L2: 279 | M2: 10.1038/s41467-021-21219-y | N2: https://www.scopus.com/inward/record.uri?eid=2-s2.0-85100856146&doi=10.1038%2Fs41467-021-21219-y&partnerID=40&md5=1c9709e9a52862247d20f96acfb64228 | O2: Simon Fraser University, Burnaby, BC, Canada | P2: Zhang, Lishen, Simon Fraser University, Burnaby, BC, Canada; Zhou, Alvin G.C., Simon Fraser University, Burnaby, BC, Canada; Sun, Brigitta R., Simon Fraser University, Burnaby, BC, Canada; Chen, Kennedy S., Simon Fraser University, Burnaby, BC, Canada; Yu, Huazhong Hogan, Simon Fraser University, Burnaby, BC, Canada | Q2: H.-Z. Yu; Department of Chemistry, Simon Fraser University, Burnaby, Canada; email: hogan_yu@sfu.ca | S2: Nature Research | W2: 33579959 | X2: English | Y2: Nat. Commun. | Z2: Article | AA2: Final | AB2: All Open Access; Gold Open Access; Green Accepted Open Access; Green Open Access | AC2: Scopus | AD2: 2-s2.0-85100856146
A3: Pearce, L.A.; Min, J.E.; Piske, M.; Zhou, H.; Homayra, F.; Slaunwhite, A.; Irvine, M.; McGowan, G.; Nosyk, B. | B3: Pearce, Lindsay A. (57202779892); Min, Jeong-eun (56007375400); Piske, Micah (55565383400); Zhou, Haoxuan (57213170548); Homayra, Fahmida (55960372900); Slaunwhite, Amanda Kathleen (56479230500); Irvine, Michael A. (56921713500); McGowan, Gina (56313570200); Nosyk, Bohdan (12809172100) | C3: 57202779892; 56007375400; 55565383400; 57213170548; 55960372900; 56479230500; 56921713500; 56313570200; 12809172100 | D3: Opioid agonist treatment and risk of mortality during opioid overdose public health emergency: Population based retrospective cohort study | E3: 2020 | F3: The BMJ | G3: 368 | I3: m772 | L3: 170 | M3: 10.1136/bmj.m772 | N3: https://www.scopus.com/inward/record.uri?eid=2-s2.0-85082731697&doi=10.1136%2Fbmj.m772&partnerID=40&md5=f1c5435206fedf49c48f60e06b9f7c14 | O3: Health Economic Research Unit, British Columbia Centre for Excellence in HIV-AIDS, Vancouver, BC, Canada; BC Centre for Disease Control, Vancouver, BC, Canada; British Columbia Ministry of Mental Health and Addictions, Victoria, BC, Canada; Faculty of Health Sciences, Simon Fraser University, Burnaby, BC, Canada | P3: Pearce, Lindsay A., Health Economic Research Unit, British Columbia Centre for Excellence in HIV-AIDS, Vancouver, BC, Canada; Min, Jeong-eun, Health Economic Research Unit, British Columbia Centre for Excellence in HIV-AIDS, Vancouver, BC, Canada; Piske, Micah, Health Economic Research Unit, British Columbia Centre for Excellence in HIV-AIDS, Vancouver, BC, Canada; Zhou, Haoxuan, Health Economic Research Unit, British Columbia Centre for Excellence in HIV-AIDS, Vancouver, BC, Canada; Homayra, Fahmida, Health Economic Research Unit, British Columbia Centre for Excellence in HIV-AIDS, Vancouver, BC, Canada; Slaunwhite, Amanda Kathleen, BC Centre for Disease Control, Vancouver, BC, Canada; Irvine, Michael A., BC Centre for Disease Control, Vancouver, BC, Canada; McGowan, Gina, British Columbia Ministry of Mental Health and Addictions, Victoria, BC, Canada; Nosyk, Bohdan, Health Economic Research Unit, British Columbia Centre for Excellence in HIV-AIDS, Vancouver, BC, Canada, Faculty of Health Sciences, Simon Fraser University, Burnaby, BC, Canada | Q3: B. Nosyk; Health Economic Research Unit, British Columbia Centre for Excellence in HIV/AIDS, Vancouver, V6Z 1Y6, Canada; email: bnosyk@cfenet.ubc.ca | S3: BMJ Publishing Group subscriptions@bmjgroup.com | T3: 00071447; 09598146; 17561833 | V3: BMJOA | W3: 32234712 | X3: English | Y3: BMJ | Z3: Article | AA3: Final | AB3: All Open Access; Green Accepted Open Access; Green Open Access; Hybrid Gold Open Access | AC3: Scopus | AD3: 2-s2.0-85082731697
A4: Higginbottom, D.B.; Kurkjian, A.T.K.; Chartrand, C.; Kazemi, M.; Brunelle, N.A.; MacQuarrie, E.R.; Klein, J.R.; Lee-Hone, N.R.; Stacho, J.; Ruether, M.; Bowness, C.; Bergeron, L.; DeAbreu, A.; Harrigan, S.R.; Kanaganayagam, J.; Marsden, D.W.; Richards, T.S.; Stott, L.A.; Roorda, S.; Morse, K.J.; Thewalt, M.L.W.; Simmons, S. | B4: Higginbottom, Daniel B. (55330606100); Kurkjian, Alexander T.K. (57203221971); Chartrand, Camille (57204605790); Kazemi, Moein (57223359408); Brunelle, Nicholas A. (57209575083); MacQuarrie, Evan R. (57188644453); Klein, James R. (57224657048); Lee-Hone, Nicholas R. (36998669900); Stacho, Jakub (57223357653); Ruether, Myles (57223768812); Bowness, Camille (57201136091); Bergeron, Laurent (57215486728); DeAbreu, Adam (56572674100); Harrigan, Stephen R. (57202744897); Kanaganayagam, Joshua (57222237504); Marsden, Danica W. (36615535300); Richards, Timothy S. (57201129737); Stott, Leea A. (57223368667); Roorda, Sjoerd (57206537236); Morse, Kevin J. (55904832900); Thewalt, Michael L.W. (7006609975); Simmons, Stephanie (36460336500) | C4: 55330606100; 57203221971; 57204605790; 57223359408; 57209575083; 57188644453; 57224657048; 36998669900; 57223357653; 57223768812; 57201136091; 57215486728; 56572674100; 57202744897; 57222237504; 36615535300; 57201129737; 57223368667; 57206537236; 55904832900; 7006609975; 36460336500 | D4: Optical observation of single spins in silicon | E4: 2022 | F4: Nature | G4: 607 | H4: 7918 | J4: 266 | K4: 270 | L4: 142 | M4: 10.1038/s41586-022-04821-y | N4: https://www.scopus.com/inward/record.uri?eid=2-s2.0-85133989154&doi=10.1038%2Fs41586-022-04821-y&partnerID=40&md5=1c1948c613feda6c3e6912afbf89622e | O4: Department of Physics, Simon Fraser University, Burnaby, BC, Canada; Photonic, Coquitlam, BC, Canada; Department of Physics, University of Montreal, Montreal, QC, Canada | P4: Higginbottom, Daniel B., Department of Physics, Simon Fraser University, Burnaby, BC, Canada; Kurkjian, Alexander T.K., Department of Physics, Simon Fraser University, Burnaby, BC, Canada, Photonic, Coquitlam, BC, Canada; Chartrand, Camille, Department of Physics, Simon Fraser University, Burnaby, BC, Canada, Photonic, Coquitlam, BC, Canada; Kazemi, Moein, Department of Physics, Simon Fraser University, Burnaby, BC, Canada; Brunelle, Nicholas A., Department of Physics, Simon Fraser University, Burnaby, BC, Canada; MacQuarrie, Evan R., Department of Physics, Simon Fraser University, Burnaby, BC, Canada, Photonic, Coquitlam, BC, Canada; Klein, James R., Department of Physics, Simon Fraser University, Burnaby, BC, Canada; Lee-Hone, Nicholas R., Department of Physics, Simon Fraser University, Burnaby, BC, Canada, Photonic, Coquitlam, BC, Canada; Stacho, Jakub, Department of Physics, Simon Fraser University, Burnaby, BC, Canada; Ruether, Myles, Department of Physics, Simon Fraser University, Burnaby, BC, Canada; Bowness, Camille, Department of Physics, Simon Fraser University, Burnaby, BC, Canada, Photonic, Coquitlam, BC, Canada; Bergeron, Laurent, Department of Physics, Simon Fraser University, Burnaby, BC, Canada; DeAbreu, Adam, Department of Physics, Simon Fraser University, Burnaby, BC, Canada; Harrigan, Stephen R., Department of Physics, Simon Fraser University, Burnaby, BC, Canada; Kanaganayagam, Joshua, Department of Physics, Simon Fraser University, Burnaby, BC, Canada; Marsden, Danica W., Department of Physics, Simon Fraser University, Burnaby, BC, Canada; Richards, Timothy S., Department of Physics, Simon Fraser University, Burnaby, BC, Canada; Stott, Leea A., Department of Physics, Simon Fraser University, Burnaby, BC, Canada; Roorda, Sjoerd, Department of Physics, University of Montreal, Montreal, QC, Canada; Morse, Kevin J., Department of Physics, Simon Fraser University, Burnaby, BC, Canada, Photonic, Coquitlam, BC, Canada; Thewalt, Michael L.W., Department of Physics, Simon Fraser University, Burnaby, BC, Canada; Simmons, Stephanie, Department of Physics, Simon Fraser University, Burnaby, BC, Canada, Photonic, Coquitlam, BC, Canada | Q4: S. Simmons; Department of Physics, Simon Fraser University, Burnaby, Canada; email: s.simmons@sfu.ca | S4: Nature Research | T4: 280836 | U4: 9780203448410; 0203448413 | V4: NATUA | W4: 35831600 | X4: English | Y4: Nature | Z4: Article | AA4: Final | AC4: Scopus | AD4: 2-s2.0-85133989154
A5: Li, X.; Aftab, S.; Hussain, S.; Kabir, F.; Henaish, A.M.A.; Al-Sehemi, A.G.; Pallavolu, M.R.; Ganesh, G. | B5: Li, Xin (56098157600); Aftab, Sikandar (57200114034); Hussain, Sajjad Z. (56435246200); Kabir, Fahmid (57204906651); Henaish, A. M.A. (56524476600); Al-Sehemi, Abdullah G. (6507858932); Pallavolu, Mohan Reddy (57201352403); Ganesh, Koyyada (55843979000) | C5: 56098157600; 57200114034; 56435246200; 57204906651; 56524476600; 6507858932; 57201352403; 55843979000 | D5: Dimensional diversity (0D, 1D, 2D, and 3D) in perovskite solar cells: exploring the potential of mixed-dimensional integrations | E5: 2024 | F5: Journal of Materials Chemistry A | G5: 12 | H5: 8 | J5: 4421 | K5: 4440 | L5: 122 | M5: 10.1039/d3ta06953b | N5: https://www.scopus.com/inward/record.uri?eid=2-s2.0-85184412995&doi=10.1039%2Fd3ta06953b&partnerID=40&md5=185ab9e781db04c445744d9690dac7c0 | O5: National University of Defense Technology China, Changsha, Hunan, China; Advanced Laser Technology Laboratory of Anhui Province, Hefei, Anhui, China; Department of Intelligent Mechatronics Engineering, Sejong University, Seoul, South Korea; Department of Nanotechnology and Advanced Materials Engineering, Sejong University, Seoul, South Korea; School of Engineering Science, Simon Fraser University, Burnaby, BC, Canada; Department of Physics, Tanta University, Tanta, Gharbia, Egypt; NANOTECH Center, Ural Federal University, Yekaterinburg, Sverdlovskaya, Russian Federation; King Khalid University, Abha, Asir, Saudi Arabia; Department of Chemistry, King Khalid University, Abha, Asir, Saudi Arabia; School of Chemical Engineering, Yeungnam University, Gyeongsan, Gyeongsangbuk-do, South Korea; Department of Chemistry, K L Deemed to be University, Vaddeswaram, AP, India | P5: Li, Xin, National University of Defense Technology China, Changsha, Hunan, China, Advanced Laser Technology Laboratory of Anhui Province, Hefei, Anhui, China; Aftab, Sikandar, Department of Intelligent Mechatronics Engineering, Sejong University, Seoul, South Korea; Hussain, Sajjad Z., Department of Nanotechnology and Advanced Materials Engineering, Sejong University, Seoul, South Korea; Kabir, Fahmid, School of Engineering Science, Simon Fraser University, Burnaby, BC, Canada; Henaish, A. M.A., Department of Physics, Tanta University, Tanta, Gharbia, Egypt, NANOTECH Center, Ural Federal University, Yekaterinburg, Sverdlovskaya, Russian Federation; Al-Sehemi, Abdullah G., King Khalid University, Abha, Asir, Saudi Arabia, Department of Chemistry, King Khalid University, Abha, Asir, Saudi Arabia; Pallavolu, Mohan Reddy, School of Chemical Engineering, Yeungnam University, Gyeongsan, Gyeongsangbuk-do, South Korea; Ganesh, Koyyada, School of Chemical Engineering, Yeungnam University, Gyeongsan, Gyeongsangbuk-do, South Korea, Department of Chemistry, K L Deemed to be University, Vaddeswaram, AP, India | Q5: S. Aftab; Department of Intelligent Mechatronics Engineering, Sejong University, Seoul, 05006, South Korea; email: aftab@sejong.ac.kr; M.R. Pallavolu; School of Chemical Engineering, Yeungnam University, Gyeongsan, 38541, South Korea; email: pmreddy@yu.ac.kr; G. Koyyada; School of Chemical Engineering, Yeungnam University, Gyeongsan, 38541, South Korea; email: ganeshkoyyada@gmail.com | S5: Royal Society of Chemistry | T5: 20507488 | V5: JMCAE | X5: English | Y5: J. Mater. Chem. A | Z5: Review | AA5: Final | AB5: All Open Access; Bronze Open Access | AC5: Scopus | AD5: 2-s2.0-85184412995
A6: Efaz1, E.T.; Rhaman, M.M.; Safayat-Al-Imam, S.; Bashar, K.L.; Kabir, F.; Mourtaza, M.D.E.; Sakib, S.N.; Mozahid, F.A. | B6: Efaz1, Erteza Tawsif (57298797900); Rhaman, Md Meganur (55975350800); Safayat-Al-Imam, Safayat Al (56412939400); Bashar, Khandaker Lubaba (57189522753); Kabir, Fahmid (57204906651); Mourtaza, Md Ehasan (57297792200); Sakib, Syed Nazmus (56412971600); Mozahid, Faisal (57203888125) | C6: 57298797900; 55975350800; 56412939400; 57189522753; 57204906651; 57297792200; 56412971600; 57203888125 | D6: A review of primary technologies of thin-film solar cells | E6: 2021 | F6: Engineering Research Express | G6: 3 | H6: 3 | I6: 32001 | L6: 121 | M6: 10.1088/2631-8695/ac2353 | N6: https://www.scopus.com/inward/record.uri?eid=2-s2.0-85117206710&doi=10.1088%2F2631-8695%2Fac2353&partnerID=40&md5=396afdd55a88a66e82bcadce31051e6f | O6: Department of Electrical and Electronic Engineering, Ahsanullah University of Science and Technology, Dhaka, Bangladesh; Faculty of Applied Sciences, Simon Fraser University, Burnaby, BC, Canada; Department of Business Administration, East West University, Dhaka, Bangladesh; Department of Electronics and Telecommunication Engineering, Daffodil International University, Dhaka, Bangladesh; Department of Glass and Ceramic Engineering, Bangladesh University of Engineering and Technology, Dhaka, Dhaka, Bangladesh | P6: Efaz1, Erteza Tawsif, Department of Electrical and Electronic Engineering, Ahsanullah University of Science and Technology, Dhaka, Bangladesh; Rhaman, Md Meganur, Department of Electrical and Electronic Engineering, Ahsanullah University of Science and Technology, Dhaka, Bangladesh; Safayat-Al-Imam, Safayat Al, Department of Electrical and Electronic Engineering, Ahsanullah University of Science and Technology, Dhaka, Bangladesh; Bashar, Khandaker Lubaba, Department of Electrical and Electronic Engineering, Ahsanullah University of Science and Technology, Dhaka, Bangladesh; Kabir, Fahmid, Faculty of Applied Sciences, Simon Fraser University, Burnaby, BC, Canada; Mourtaza, Md Ehasan, Department of Business Administration, East West University, Dhaka, Bangladesh; Sakib, Syed Nazmus, Department of Electronics and Telecommunication Engineering, Daffodil International University, Dhaka, Bangladesh; Mozahid, Faisal, Department of Glass and Ceramic Engineering, Bangladesh University of Engineering and Technology, Dhaka, Dhaka, Bangladesh | Q6: E.T. Efaz1; Department of Electrical & Electronic Engineering, Ahsanullah University of Science & Technology, Dhaka, 1208, Bangladesh; email: ertezatawsif@gmail.com | S6: IOP Publishing Ltd | X6: English | Y6: Eng. Res. Exp. | Z6: Review | AA6: Final | AB6: All Open Access; Bronze Open Access | AC6: Scopus | AD6: 2-s2.0-85117206710
A7: Pecunia, V.; Silva, S.R.P.; Phillips, J.D.; Artegiani, E.; Romeo, A.; Shim, H.; Park, J.; Kim, J.H.; Yun, J.S.; Welch, G.C.; Larson, B.W.; Creran, M.; Laventure, A.; Sasitharan, K.; Flores-Díaz, N.; Freitag, M.; Xu, J.; Brown, T.M.; Li, B.; Wang, Y.; Li, Z.; Hou, B.; Hamadani, B.H.; Defay, E.; Kovacova, V.; Glinšek, S.; Kar-Narayan, S.; Bai, Y.; Kim, D.B.; Cho, Y.S.; Žukauskaitė, A.; Barth, S.; Fan, F.R.; Wu, W.; Costa, P.; del Campo, J.; Lanceros-Mendez, S.; Khanbareh, H.; Wang, Z.L.; Pu, X.; Pan, C.; Zhang, R.; Xu, J.; Zhao, X.; Zhou, Y.; Chen, G.; Tat, T.; Ock, I.W.; Chen, J.; Graham, S.A.; Yu, J.S.; Huang, L.-Z.; Li, D.-D.; Ma, M.-G.; Luo, J.; Jiang, F.; Lee, P.S.; Dudem, B.; Vivekananthan, V.; Kanatzidis, M.G.; Xie, H.; Shi, X.-L.; Chen, Z.-G.; Riss, A.; Parzer, M.; Garmroudi, F.; Bauer, E.; Zavanelli, D.; Brod, M.K.; Al Malki, M.A.; Snyder, G.J.; Kovnir, K.; Kauzlarich, S.M.; Uher, C.; Lan, J.; Lin, Y.-H.; Fonseca, L.; Morata, A.; Martin-Gonzalez, M.; Pennelli, G.; Berthebaud, D.; Mori, T.; Quinn, R.J.; Bos, J.G.; Candolfi, C.; Gougeon, P.; Gall, P.; Lenoir, B.; Venkateshvaran, D.; Kaestner, B.; Zhao, Y.; Zhang, G.; Nonoguchi, Y.; Schroeder, B.C.; Bilotti, E.; Menon, A.K.; Urban, J.J.; Fenwick, O.; Asker, C.; Talin, A.A. | B7: Pecunia, Vincenzo (36017327500); Silva, S. Ravi P. (7203043276); Phillips, Jamie D. (7404582496); Artegiani, Elisa (57191348127); Romeo, Alessandro (58138480300); Shim, Hongjae (57192209517); Park, Jongsung (56918806300); Kim, Jinhyeok (55453169100); Yun, Jae-Sung (55832742300); Welch, Gregory Charles (12041090100); Larson, Bryon W. (36773189100); Creran, Myles (58535531600); Laventure, Audrey (55383011400); Sasitharan, Kezia (57195677221); Flores-Díaz, Natalie (57201473809); Freitag, Marina (36463418100); Xu, Jie (57212042971); Brown, Thomas M. (56447631100); Li, Benxuan (57208771142); Wang, Yiwen (59855615100); Li, Zhe (57189902521); Hou, Bo (55642219000); Hamadani, Behrang H. (6507764848); Defay, Emmanuel (14046735700); Kovacova, Veronika (55571109000); Glinšek, Sebastjan (17434167500); Kar-Narayan, Sohini (25631060300); Bai, Yang (59607678400); Kim, Da Bin (57199860969); Cho, Yong Soo (14828535700); Žukauskaitė, Agnė (36175284100); Barth, Stephan (56043298400); Fan, Feng Ru (57226692672); Wu, Wenzhuo (35106384100); Costa, P. Filipe Ribeiro (56335530700); del Campo, Francisco Javier (58067163600); Lanceros-Mendez, Senentxu (57211501457); Khanbareh, Hamideh (24080849200); Wang, Zhong Lin (56430045300); Pu, Xiong (56532311000); Pan, Caofeng (8976786800); Zhang, Renyun (59849824300); Xu, Jing (59051250200); Zhao, Xun (57216909561); Zhou, Yihao (57211925344); Chen, Guorui (57216042917); Tat, Trinny (57219476083); Ock, Il Woo (56313153700); Chen, Jun (57837247800); Graham, Sontyana Adonijah (57207243824); Yu, Jae Su (13607137200); Huang, Lingzhi (59816436300); Li, Dandan (59284102700); Ma, Ming Guo (59868408100); Luo, J. K. (8389079800); Jiang, Feng (57196082995); Lee, Pooi See (7406117427); Dudem, Bhaskar (56509565000); Vivekananthan, Venkateswaran (57193266678); Kanatzidis, Mercouri G. (35392448100); Xie, Hongyao (56193548100); Shi, Xiaolei (57195547608); Chen, Zhigang (57188708630); Riss, Alexander (8664614200); Parzer, Michael (57457146300); Garmroudi, Fabian (57218712021); Bauer, Ernst (57198009404); Zavanelli, Duncan (57435926900); Brod, Madison K. (57219744253); Al Malki, Muath (57190383635); Snyder, Gerald Jeffrey (35547214000); Kovnir, K. A. (55882620400); Kauzlarich, Susan M. (7006232158); Uher, Ctirad (7005831713); Lan, Jinle (26031483100); Lin, Yuan Hua (59045784400); Fonseca, Luis (57205120606); Morata, Alex (8323905300); Martin-Gonzalez, Marisol Soledad (7003937804); Pennelli, Giovanni (6603933710); Berthebaud, David (16644550500); Mori, Takao (55560924100); Quinn, Robert J. (57209231603); Bos, Jan Willem G. (12799772000); Candolfi, Christophe (25624601500); Gougeon, Patrick (7005780077); Gall, Philippe (11439224200); Lenoir, Bertrand (57203026145); Venkateshvaran, Deepak (25229425600); Kaestner, Bernd (8282463200); Zhao, Yunshan (59795284400); Zhang, Gang (59285805300); Nonoguchi, Yoshiyuki (20433884600); Schroeder, Bob C. (37116115600); Bilotti, Emiliano (23011558200); Menon, Akanksha K. (57102776100); Urban, Jeffrey J. (7202366328); Fenwick, Oliver (8644567300); Asker, Ceyla (58535456800); Talin, Albert Alec (57136554400) | C7: 36017327500; 7203043276; 7404582496; 57191348127; 58138480300; 57192209517; 56918806300; 55453169100; 55832742300; 12041090100; 36773189100; 58535531600; 55383011400; 57195677221; 57201473809; 36463418100; 57212042971; 56447631100; 57208771142; 59855615100; 57189902521; 55642219000; 6507764848; 14046735700; 55571109000; 17434167500; 25631060300; 59607678400; 57199860969; 14828535700; 36175284100; 56043298400; 57226692672; 35106384100; 56335530700; 58067163600; 57211501457; 24080849200; 56430045300; 56532311000; 8976786800; 59849824300; 59051250200; 57216909561; 57211925344; 57216042917; 57219476083; 56313153700; 57837247800; 57207243824; 13607137200; 59816436300; 59284102700; 59868408100; 8389079800; 57196082995; 7406117427; 56509565000; 57193266678; 35392448100; 56193548100; 57195547608; 57188708630; 8664614200; 57457146300; 57218712021; 57198009404; 57435926900; 57219744253; 57190383635; 35547214000; 55882620400; 7006232158; 7005831713; 26031483100; 59045784400; 57205120606; 8323905300; 7003937804; 6603933710; 16644550500; 55560924100; 57209231603; 12799772000; 25624601500; 7005780077; 11439224200; 57203026145; 25229425600; 8282463200; 59795284400; 59285805300; 20433884600; 37116115600; 23011558200; 57102776100; 7202366328; 8644567300; 58535456800; 57136554400 | D7: Roadmap on energy harvesting materials | E7: 2023 | F7: JPhys Materials | G7: 6 | H7: 4 | I7: 42501 | L7: 111 | M7: 10.1088/2515-7639/acc550 | N7: https://www.scopus.com/inward/record.uri?eid=2-s2.0-85167708123&doi=10.1088%2F2515-7639%2Facc550&partnerID=40&md5=e5694e34525039171892fb33c4d7fafd | O7: School of Sustainable Energy Engineering, Simon Fraser University, Burnaby, BC, Canada; Department of Electrical and Electronic Engineering, University of Surrey, Guildford, Surrey, United Kingdom; Department of Electrical & Computer Engineering, University of Delaware, Newark, DE, United States; Department of Computer Science, Università degli Studi di Verona, Verona, VR, Italy; School of Photovoltaic and Renewable Energy Engineering, UNSW Sydney, Sydney, NSW, Australia; Department of Energy Engineering, Gyeongsang National University, Jinju, Gyeongsangnam-do, South Korea; Department of Materials Science and Engineering, Chonnam National University, Gwangju, South Korea; University of Calgary, Calgary, AB, Canada; National Renewable Energy Laboratory, Golden, CO, United States; Department of Chemistry, University of Montreal, Montreal, QC, Canada; Bedson Building, Newcastle University, Newcastle, Tyne and Wear, United Kingdom; Department of Electronics Engineering, Università degli Studi di Roma "Tor Vergata", Rome, RM, Italy; Institute of Microscale Optoelectronics, International Collaborative Laboratory of 2D Materials for Optoelectronics Science and Technology, Shenzhen, Guangdong, China; Electrical Engineering Division, Cambridge, Cambridgeshire, United Kingdom; Queen Mary University of London, London, United Kingdom; Cardiff University, Cardiff, South Glamorgan, Wales, United Kingdom; National Institute of Standards and Technology, Gaithersburg, MD, United States; Materials Research and Technology Department, Luxembourg Institute of Science and Technology, Esch-sur-Alzette, Esch-sur-Alzette, Luxembourg; Department of Materials Science and Metallurgy, University of Cambridge, Cambridge, Cambridgeshire, United Kingdom; Microelectronics Research Unit, Oulun Yliopisto, Oulu, North Ostrobothnia, Finland; Department of Materials Science and Engineering, Yonsei University, Seoul, South Korea; Fraunhofer-Institut Für Organische Elektronik, Elektronenstrahl- Und Plasmatechnik, Dresden, Sachsen, Germany; College of Chemistry and Chemical Engineering, Xiamen University, Xiamen, Fujian, China; Edwardson School of Industrial Engineering, West Lafayette, IN, United States; Universidade do Minho, Braga, Braga, Portugal; Laboratory of Physics for Materials and Emergent Technologies, Universidade do Minho, Braga, Braga, Portugal; Applications and Nanostructures, BCMaterials - Basque Center for Materials, Applications and Nanostructures, Leioa, Biscay, Spain | P7: Pecunia, Vincenzo, School of Sustainable Energy Engineering, Simon Fraser University, Burnaby, BC, Canada; Silva, S. Ravi P., Department of Electrical and Electronic Engineering, University of Surrey, Guildford, Surrey, United Kingdom; Phillips, Jamie D., Department of Electrical & Computer Engineering, University of Delaware, Newark, DE, United States; Artegiani, Elisa, Department of Computer Science, Università degli Studi di Verona, Verona, VR, Italy; Romeo, Alessandro, Department of Computer Science, Università degli Studi di Verona, Verona, VR, Italy; Shim, Hongjae, School of Photovoltaic and Renewable Energy Engineering, UNSW Sydney, Sydney, NSW, Australia; Park, Jongsung, Department of Energy Engineering, Gyeongsang National University, Jinju, Gyeongsangnam-do, South Korea; Kim, Jinhyeok, Department of Materials Science and Engineering, Chonnam National University, Gwangju, South Korea; Yun, Jae-Sung, Department of Electrical and Electronic Engineering, University of Surrey, Guildford, Surrey, United Kingdom; Welch, Gregory Charles, University of Calgary, Calgary, AB, Canada; Larson, Bryon W., National Renewable Energy Laboratory, Golden, CO, United States; Creran, Myles, Department of Chemistry, University of Montreal, Montreal, QC, Canada; Laventure, Audrey, Department of Chemistry, University of Montreal, Montreal, QC, Canada; Sasitharan, Kezia, Bedson Building, Newcastle University, Newcastle, Tyne and Wear, United Kingdom; Flores-Díaz, Natalie, Bedson Building, Newcastle University, Newcastle, Tyne and Wear, United Kingdom; Freitag, Marina, Bedson Building, Newcastle University, Newcastle, Tyne and Wear, United Kingdom; Xu, Jie, Department of Electronics Engineering, Università degli Studi di Roma "Tor Vergata", Rome, RM, Italy; Brown, Thomas M., Department of Electronics Engineering, Università degli Studi di Roma "Tor Vergata", Rome, RM, Italy; Li, Benxuan, Institute of Microscale Optoelectronics, International Collaborative Laboratory of 2D Materials for Optoelectronics Science and Technology, Shenzhen, Guangdong, China, Electrical Engineering Division, Cambridge, Cambridgeshire, United Kingdom; Wang, Yiwen, Queen Mary University of London, London, United Kingdom; Li, Zhe, Queen Mary University of London, London, United Kingdom; Hou, Bo, Cardiff University, Cardiff, South Glamorgan, Wales, United Kingdom; Hamadani, Behrang H., National Institute of Standards and Technology, Gaithersburg, MD, United States; Defay, Emmanuel, Materials Research and Technology Department, Luxembourg Institute of Science and Technology, Esch-sur-Alzette, Esch-sur-Alzette, Luxembourg; Kovacova, Veronika, Materials Research and Technology Department, Luxembourg Institute of Science and Technology, Esch-sur-Alzette, Esch-sur-Alzette, Luxembourg; Glinšek, Sebastjan, Materials Research and Technology Department, Luxembourg Institute of Science and Technology, Esch-sur-Alzette, Esch-sur-Alzette, Luxembourg; Kar-Narayan, Sohini, Department of Materials Science and Metallurgy, University of Cambridge, Cambridge, Cambridgeshire, United Kingdom; Bai, Yang, Microelectronics Research Unit, Oulun Yliopisto, Oulu, North Ostrobothnia, Finland; Kim, Da Bin, Department of Materials Science and Engineering, Yonsei University, Seoul, South Korea; Cho, Yong Soo, Department of Materials Science and Engineering, Yonsei University, Seoul, South Korea; Žukauskaitė, Agnė, Fraunhofer-Institut Für Organische Elektronik, Elektronenstrahl- Und Plasmatechnik, Dresden, Sachsen, Germany, ; Barth, Stephan, Fraunhofer-Institut Für Organische Elektronik, Elektronenstrahl- Und Plasmatechnik, Dresden, Sachsen, Germany; Fan, Feng Ru, College of Chemistry and Chemical Engineering, Xiamen University, Xiamen, Fujian, China; Wu, Wenzhuo, Edwardson School of Industrial Engineering, West Lafayette, IN, United States; Costa, P. Filipe Ribeiro, Universidade do Minho, Braga, Braga, Portugal, Laboratory of Physics for Materials and Emergent Technologies, Universidade do Minho, Braga, Braga, Portugal; del Campo, Francisco Javier, Applications and Nanostructures, BCMaterials - Basque Center for Materials, Applications and Nanostructures, Leioa, Biscay, Spain, ; Lanceros-Mendez, Senentxu, Universidade do Minho, Braga, Braga, Portugal, Laboratory of Physics for Materials and Emergent Technologies, Universidade do Minho, Braga, Braga, Portugal, Applications and Nanostructures, BCMaterials - Basque Center for Materials, Applications and Nanostructures, Leioa, Biscay, Spain, ; Khanbareh, Hamideh, ; Wang, Zhong Lin, ; Pu, Xiong, ; Pan, Caofeng, ; Zhang, Renyun, ; Xu, Jing, ; Zhao, Xun, ; Zhou, Yihao, ; Chen, Guorui, ; Tat, Trinny, ; Ock, Il Woo, ; Chen, Jun, ; Graham, Sontyana Adonijah, ; Yu, Jae Su, ; Huang, Lingzhi, ; Li, Dandan, ; Ma, Ming Guo, ; Luo, J. K., ; Jiang, Feng, ; Lee, Pooi See, ; Dudem, Bhaskar, Department of Electrical and Electronic Engineering, University of Surrey, Guildford, Surrey, United Kingdom; Vivekananthan, Venkateswaran, Department of Electrical and Electronic Engineering, University of Surrey, Guildford, Surrey, United Kingdom, ; Kanatzidis, Mercouri G., ; Xie, Hongyao, ; Shi, Xiaolei, ; Chen, Zhigang, ; Riss, Alexander, ; Parzer, Michael, ; Garmroudi, Fabian, ; Bauer, Ernst, ; Zavanelli, Duncan, ; Brod, Madison K., ; Al Malki, Muath, ; Snyder, Gerald Jeffrey, ; Kovnir, K. A., , ; Kauzlarich, Susan M., ; Uher, Ctirad, ; Lan, Jinle, ; Lin, Yuan Hua, ; Fonseca, Luis, ; Morata, Alex, ; Martin-Gonzalez, Marisol Soledad, ; Pennelli, Giovanni, ; Berthebaud, David, ; Mori, Takao, , ; Quinn, Robert J., ; Bos, Jan Willem G., ; Candolfi, Christophe, ; Gougeon, Patrick, ; Gall, Philippe, ; Lenoir, Bertrand, ; Venkateshvaran, Deepak, ; Kaestner, Bernd, ; Zhao, Yunshan, ; Zhang, Gang, ; Nonoguchi, Yoshiyuki, ; Schroeder, Bob C., ; Bilotti, Emiliano, ; Menon, Akanksha K., ; Urban, Jeffrey J., ; Fenwick, Oliver, ; Asker, Ceyla, ; Talin, Albert Alec, | Q7: V. Pecunia; School of Sustainable Energy Engineering, Simon Fraser University, Surrey, V3T 0N1 BC, Canada; email: vincenzo_pecunia@sfu.ca; S.R.P. Silva; Advanced Technology Institute, Department of Electrical and Electronic Engineering, University of Surrey, Surrey, Guildford, GU2 7XH, United Kingdom; email: sk568@cam.ac.uk; S. Kar-Narayan; Department of Materials Science and Metallurgy, University of Cambridge, Cambridge, 27 Charles Babbage Road, CB3 0FS, United Kingdom; email: s.silva@surrey.ac.uk | S7: Institute of Physics | X7: English | Y7: JPhys mater. | Z7: Article | AA7: Final | AB7: All Open Access; Gold Open Access; Green Accepted Open Access; Green Open Access | AC7: Scopus | AD7: 2-s2.0-85167708123
A8: Radchenko, V.; Morgenstern, A.; Jalilian, A.R.; Ramogida, C.F.; Cutler, C.; Duchemin, C.; Hoehr, C.; Haddad, F.; Bruchertseifer, F.; Gausemel, H.; Yang, H.; Osso, J.A.; Washiyama, K.; Czerwinski, K.; Leufgen, K.; Pruszynski, M.; Valzdorf, O.; Causey, P.; Schaffer, P.; Perron, R.; Maxim, S.; Wilbur, D.; Stora, T.; Li, Y. | B8: Radchenko, Valery I. (57740320900); Morgenstern, Alfred (7003443298); Jalilian, Amir Reza (35310287700); Ramogida, Caterina Fortunata (37034801500); Cutler, Cathy Sue (7103162185); Duchemin, Charlotte (55959087100); Hoehr, Cornelia (55326269700); Haddad, Férid (7203034613); Bruchertseifer, Frank (16174125700); Gausemel, Haavar (57349276900); Yang, Hua (56019802000); Osso, João Alberto (6603085730); Washiyama, Kohshin (35742134900); Czerwinski, Kenneth R. (7004040079); Leufgen, Kirsten (57349421600); Pruszynski, Marek (58371125400); Valzdorf, Olga (57349421700); Causey, Patrick W. (55879681100); Schaffer, Paul (7102320285); Perron, Randy W. (57215078283); Maxim, Samsonov (57349562100); Wilbur, Daniel Scott (21735578000); Stora, Thierry (6602903896); Li, Yawen (57199181452) | C8: 57740320900; 7003443298; 35310287700; 37034801500; 7103162185; 55959087100; 55326269700; 7203034613; 16174125700; 57349276900; 56019802000; 6603085730; 35742134900; 7004040079; 57349421600; 58371125400; 57349421700; 55879681100; 7102320285; 57215078283; 57349562100; 21735578000; 6602903896; 57199181452 | D8: Production and supply of a-particle-emitting radionuclides for targeted a-therapy | E8: 2021 | F8: Journal of Nuclear Medicine | G8: 62 | H8: 11 | J8: 1495 | K8: 1503 | L8: 104 | M8: 10.2967/jnumed.120.261016 | N8: https://www.scopus.com/inward/record.uri?eid=2-s2.0-85119600442&doi=10.2967%2Fjnumed.120.261016&partnerID=40&md5=ddf421502a6ea3b9fa951d1526b491fc | O8: Division of Life Sciences, TRIUMF, Vancouver, BC, Canada; The University of British Columbia, Vancouver, BC, Canada; European Commission Joint Research Centre, Brussels, Belgium; International Atomic Energy Agency, Vienna, Vienna, Vienna, Austria; Simon Fraser University, Burnaby, BC, Canada; Collider-Accelerator Department, Brookhaven National Laboratory, Upton, NY, United States; Organisation Européenne pour la Recherche Nucléaire, Geneva, GE, Switzerland; Departement Natuurkunde en Sterrenkunde, Leuven, Vlaams-Brabant, Belgium; Arronax, Nantes, France; Bayer American Samoa, Oslo, Norway; Advanced Clinical Research Center, Fukushima Medical University, Fukushima, Fukushima, Japan; Radiochemistry Program, University of Nevada, Las Vegas, Las Vegas, NV, United States; SCIPROM Sarl, St Sulpice, Switzerland; Institute of Nuclear Chemistry and Technology, Warsaw, Warsaw, MA, Poland; NOMATEN Centre of Excellence, Narodowe Centrum Badań Jądrowych, Otwock, Otwock, MA, Poland; The State Atomic Energy Corporation ROSATOM, Moscow, Russian Federation; BWXT Medical Ltd., Ottawa, ON, Canada; Laboratoires Nucléaires Canadiens, Chalk River, ON, Canada; The State Atomic Energy Corporation ROSATOM, Moscow, Russian Federation; University of Washington School of Medicine, Seattle, WA, United States | P8: Radchenko, Valery I., Division of Life Sciences, TRIUMF, Vancouver, BC, Canada, The University of British Columbia, Vancouver, BC, Canada; Morgenstern, Alfred, European Commission Joint Research Centre, Brussels, Belgium; Jalilian, Amir Reza, International Atomic Energy Agency, Vienna, Vienna, Vienna, Austria; Ramogida, Caterina Fortunata, Division of Life Sciences, TRIUMF, Vancouver, BC, Canada, Simon Fraser University, Burnaby, BC, Canada; Cutler, Cathy Sue, Collider-Accelerator Department, Brookhaven National Laboratory, Upton, NY, United States; Duchemin, Charlotte, Organisation Européenne pour la Recherche Nucléaire, Geneva, GE, Switzerland, Departement Natuurkunde en Sterrenkunde, Leuven, Vlaams-Brabant, Belgium; Hoehr, Cornelia, Division of Life Sciences, TRIUMF, Vancouver, BC, Canada; Haddad, Férid, Arronax, Nantes, France; Bruchertseifer, Frank, European Commission Joint Research Centre, Brussels, Belgium; Gausemel, Haavar, Bayer American Samoa, Oslo, Norway; Yang, Hua, Division of Life Sciences, TRIUMF, Vancouver, BC, Canada; Osso, João Alberto, International Atomic Energy Agency, Vienna, Vienna, Vienna, Austria; Washiyama, Kohshin, Advanced Clinical Research Center, Fukushima Medical University, Fukushima, Fukushima, Japan; Czerwinski, Kenneth R., Radiochemistry Program, University of Nevada, Las Vegas, Las Vegas, NV, United States; Leufgen, Kirsten, SCIPROM Sarl, St Sulpice, Switzerland; Pruszynski, Marek, Institute of Nuclear Chemistry and Technology, Warsaw, Warsaw, MA, Poland, NOMATEN Centre of Excellence, Narodowe Centrum Badań Jądrowych, Otwock, Otwock, MA, Poland; Valzdorf, Olga, The State Atomic Energy Corporation ROSATOM, Moscow, Russian Federation; Causey, Patrick W., BWXT Medical Ltd., Ottawa, ON, Canada; Schaffer, Paul, Division of Life Sciences, TRIUMF, Vancouver, BC, Canada; Perron, Randy W., Laboratoires Nucléaires Canadiens, Chalk River, ON, Canada; Maxim, Samsonov, The State Atomic Energy Corporation ROSATOM, Moscow, Russian Federation; Wilbur, Daniel Scott, University of Washington School of Medicine, Seattle, WA, United States; Stora, Thierry, Organisation Européenne pour la Recherche Nucléaire, Geneva, GE, Switzerland; Li, Yawen, University of Washington School of Medicine, Seattle, WA, United States | Q8: V. Radchenko; Life Sciences Division, TRIUMF, Vancouver, Canada; email: vradchenko@triumf.ca | S8: Society of Nuclear Medicine Inc. | T8: 1615505 | V8: JNMEA | W8: 34301779 | X8: English | Y8: J. Nucl. Med. | Z8: Review | AA8: Final | AB8: All Open Access; Bronze Open Access; Green Accepted Open Access; Green Open Access | AC8: Scopus | AD8: 2-s2.0-85119600442
A9: Hillier, A.D.; Blundell, S.J.; McKenzie, I.; Umegaki, I.; Shu, L.; Wright, J.A.; Prokscha, T.; Bert, F.; Shimomura, K.; Berlie, A.; Alberto, H.; Watanabe, I. | B9: Hillier, Adrian D. (7102718125); Blundell, Stephen J. (7004826134); McKenzie, Iain D. (7202607692); Umegaki, Izumi (26538413500); Shu, Lei (57200616279); Wright, Joseph A. (11441061300); Prokscha, Thomas (6701645335); Bert, Fabrice (7006916787); Shimomura, Kouichiro (59800260000); Berlie, Adam (36969653800); Alberto, Helena Vieira (57209266041); Watanabe, Isao (7402438308) | C9: 7102718125; 7004826134; 7202607692; 26538413500; 57200616279; 11441061300; 6701645335; 7006916787; 59800260000; 36969653800; 57209266041; 7402438308 | D9: Muon spin spectroscopy | E9: 2022 | F9: Nature Reviews Methods Primers | G9: 2 | H9: 1 | I9: 4 | L9: 90 | M9: 10.1038/s43586-021-00089-0 | N9: https://www.scopus.com/inward/record.uri?eid=2-s2.0-85124787281&doi=10.1038%2Fs43586-021-00089-0&partnerID=40&md5=0536b5b651d8f414560ad4cf58d68f0a | O9: ISIS Neutron and Muon Source, Didcot, Oxfordshire, United Kingdom; University of Oxford, Oxford, Oxfordshire, United Kingdom; TRIUMF, Vancouver, BC, Canada; Simon Fraser University, Burnaby, BC, Canada; Department of Physics and Astronomy, University of Waterloo, Waterloo, ON, Canada; Toyota Central R&D Labs., Inc., Nagakute, Aichi, Japan; Department of Physics, Fudan University, Shanghai, China; School of Chemistry, University of East Anglia, Norwich, Norfolk, United Kingdom; Laboratory for Muon Spin Spectroscopy, Paul Scherrer Institut, Villigen, AG, Switzerland; Université Paris-Saclay, Gif-sur-Yvette, Ile-de-France, France; High Energy Accelerator Research Organization, Tsukuba, Tsukuba, Ibaraki, Japan; Department of Physics, Centre for Physics of the University of Coimbra, Coimbra, Portugal; Advanced Meson Science Laboratory, Riken, Wako, Saitama, Japan | P9: Hillier, Adrian D., ISIS Neutron and Muon Source, Didcot, Oxfordshire, United Kingdom; Blundell, Stephen J., University of Oxford, Oxford, Oxfordshire, United Kingdom; McKenzie, Iain D., TRIUMF, Vancouver, BC, Canada, Simon Fraser University, Burnaby, BC, Canada, Department of Physics and Astronomy, University of Waterloo, Waterloo, ON, Canada; Umegaki, Izumi, Toyota Central R&D Labs., Inc., Nagakute, Aichi, Japan; Shu, Lei, Department of Physics, Fudan University, Shanghai, China; Wright, Joseph A., School of Chemistry, University of East Anglia, Norwich, Norfolk, United Kingdom; Prokscha, Thomas, Laboratory for Muon Spin Spectroscopy, Paul Scherrer Institut, Villigen, AG, Switzerland; Bert, Fabrice, Université Paris-Saclay, Gif-sur-Yvette, Ile-de-France, France; Shimomura, Kouichiro, High Energy Accelerator Research Organization, Tsukuba, Tsukuba, Ibaraki, Japan; Berlie, Adam, ISIS Neutron and Muon Source, Didcot, Oxfordshire, United Kingdom; Alberto, Helena Vieira, Department of Physics, Centre for Physics of the University of Coimbra, Coimbra, Portugal; Watanabe, Isao, Advanced Meson Science Laboratory, Riken, Wako, Saitama, Japan | Q9: A.D. Hillier; ISIS Neutron and Muon Facility, STFC Rutherford Appleton Laboratory, Didcot, United Kingdom; email: adrian.hillier@stfc.ac.uk | S9: Springer Nature | X9: English | Y9: Nat. Rev. Method. Prim. | Z9: Review | AA9: Final | AC9: Scopus | AD9: 2-s2.0-85124787281
A10: Peng, B.; Peng, R.-C.; Zhang, Y.-Q.; Dong, G.; Zhou, Z.; Zhou, Y.; Li, T.; Liu, Z.; Luo, Z.; Wang, S.; Xia, Y.; Qiu, R.; Cheng, X.; Xue, F.; Hu, Z.; Ren, W.; Ye, Z.-G.; Chen, L.-Q.; Shan, Z.; Min, T.; Liu, M. | B10: Peng, Bing (56870780100); Peng, Renci (56417134700); Zhang, Yongqiang (54390551600); Dong, Guohua (55325115100); Zhou, Ziyao (53867616700); Zhou, Yuqing (57200202447); Li, Tao (57003828500); Liu, Zhijie (59817868800); Luo, Zhenlin (8836577000); Wang, Shaohao (37079675100); Xia, Yan (7403027419); Qiu, Ruibin (57219048930); Cheng, Xiaoxing (56754458300); Xue, Fei (57217026643); Hu, Zhongqiang (25641266000); Ren, Wei (57201421397); Ye, Zuo Guang (24443034100); Chen, Long qing (54790583500); Shan, Zhiwei (24559528100); Min, Tai (22968144400); Liu, Ming (56517197100) | C10: 56870780100; 56417134700; 54390551600; 55325115100; 53867616700; 57200202447; 57003828500; 59817868800; 8836577000; 37079675100; 7403027419; 57219048930; 56754458300; 57217026643; 25641266000; 57201421397; 24443034100; 54790583500; 24559528100; 22968144400; 56517197100 | D10: Phase transition enhanced superior elasticity in freestanding single-crystalline multiferroic BiFeO3membranes | E10: 2020 | F10: Science Advances | G10: 6 | H10: 34 | I10: eaba5847 | L10: 89 | M10: 10.1126/sciadv.aba5847 | N10: https://www.scopus.com/inward/record.uri?eid=2-s2.0-85091128174&doi=10.1126%2Fsciadv.aba5847&partnerID=40&md5=b2391eb58b20527dca35cfd8d0788080 | O10: Electronic Materials Research Laboratory, Xi'an Jiaotong University, Xi'an, Shaanxi, China; Center for Advancing Materials Performance from the Nanoscale (CAMP-Nano), Xi'an Jiaotong University, Xi'an, Shaanxi, China; Center for Spintronics and Quantum Systems, Xi'an Jiaotong University, Xi'an, Shaanxi, China; National Synchrotron Radiation Laboratory, University of Science and Technology of China, Hefei, Anhui, China; Department of Microelectronics Science and Engineering, Fuzhou University, Fuzhou, Fujian, China; College of Physics and Information Engineering, Fuzhou University, Fuzhou, Fujian, China; Pennsylvania State University, University Park, PA, United States; Simon Fraser University, Burnaby, BC, Canada | P10: Peng, Bing, Electronic Materials Research Laboratory, Xi'an Jiaotong University, Xi'an, Shaanxi, China; Peng, Renci, Electronic Materials Research Laboratory, Xi'an Jiaotong University, Xi'an, Shaanxi, China; Zhang, Yongqiang, Center for Advancing Materials Performance from the Nanoscale (CAMP-Nano), Xi'an Jiaotong University, Xi'an, Shaanxi, China; Dong, Guohua, Electronic Materials Research Laboratory, Xi'an Jiaotong University, Xi'an, Shaanxi, China; Zhou, Ziyao, Electronic Materials Research Laboratory, Xi'an Jiaotong University, Xi'an, Shaanxi, China; Zhou, Yuqing, Center for Spintronics and Quantum Systems, Xi'an Jiaotong University, Xi'an, Shaanxi, China; Li, Tao, Center for Spintronics and Quantum Systems, Xi'an Jiaotong University, Xi'an, Shaanxi, China; Liu, Zhijie, National Synchrotron Radiation Laboratory, University of Science and Technology of China, Hefei, Anhui, China; Luo, Zhenlin, National Synchrotron Radiation Laboratory, University of Science and Technology of China, Hefei, Anhui, China; Wang, Shaohao, Department of Microelectronics Science and Engineering, Fuzhou University, Fuzhou, Fujian, China; Xia, Yan, College of Physics and Information Engineering, Fuzhou University, Fuzhou, Fujian, China; Qiu, Ruibin, Electronic Materials Research Laboratory, Xi'an Jiaotong University, Xi'an, Shaanxi, China; Cheng, Xiaoxing, Pennsylvania State University, University Park, PA, United States; Xue, Fei, Pennsylvania State University, University Park, PA, United States; Hu, Zhongqiang, Electronic Materials Research Laboratory, Xi'an Jiaotong University, Xi'an, Shaanxi, China; Ren, Wei, Electronic Materials Research Laboratory, Xi'an Jiaotong University, Xi'an, Shaanxi, China; Ye, Zuo Guang, Simon Fraser University, Burnaby, BC, Canada; Chen, Long qing, Pennsylvania State University, University Park, PA, United States; Shan, Zhiwei, Center for Advancing Materials Performance from the Nanoscale (CAMP-Nano), Xi'an Jiaotong University, Xi'an, Shaanxi, China; Min, Tai, Center for Spintronics and Quantum Systems, Xi'an Jiaotong University, Xi'an, Shaanxi, China; Liu, Ming, Electronic Materials Research Laboratory, Xi'an Jiaotong University, Xi'an, Shaanxi, China | Q10: Z. Zhou; Electronic Materials Research Laboratory, Key Laboratory of the Ministry of Education, School of Electronic and Information Engineering, Center for Spintronics and Quantum System, State Key Laboratory for Mechanical Behavior of Materials, Xi'an Jiaotong University, Xi'an, 710049, China; email: ziyaozhou@xjtu.edu.cn; M. Liu; Electronic Materials Research Laboratory, Key Laboratory of the Ministry of Education, School of Electronic and Information Engineering, Center for Spintronics and Quantum System, State Key Laboratory for Mechanical Behavior of Materials, Xi'an Jiaotong University, Xi'an, 710049, China; email: mingliu@xjtu.edu.cn; T. Li; Center for Spintronics and Quantum System, State Key Laboratory for Mechanical Behavior of Materials, School of Materials Science and Engineering, Xi'an Jiaotong University, Xi'an, Shaanxi, 710049, China; email: taoli66@xjtu.edu.cn | S10: American Association for the Advancement of Science | W10: 32937363 | X10: English | Y10: Sci. Adv. | Z10: Article | AA10: Final | AB10: All Open Access; Gold Open Access; Green Accepted Open Access; Green Open Access | AC10: Scopus | AD10: 2-s2.0-85091128174
A11: Lashitew, A.A.; Ross, M.L.; Werker, E. | B11: Lashitew, Addisu A. (54179465800); Ross, Michael L. (7403662259); Werker, Eric D. (22936119100) | C11: 54179465800; 7403662259; 22936119100 | D11: What Drives Successful Economic Diversification in Resource-Rich Countries? | E11: 2021 | F11: World Bank Research Observer | G11: 36 | H11: 2 | J11: 164 | K11: 196 | L11: 82 | M11: 10.1093/wbro/lkaa001 | N11: https://www.scopus.com/inward/record.uri?eid=2-s2.0-85121205816&doi=10.1093%2Fwbro%2Flkaa001&partnerID=40&md5=6905f769ad75447e2cababadd52ea2e0 | O11: The Brookings Institution, Washington, D.C., United States; Department of Political Science, University of California, Los Angeles, Los Angeles, CA, United States; Beedie School of Business, Burnaby, BC, Canada | P11: Lashitew, Addisu A., The Brookings Institution, Washington, D.C., United States; Ross, Michael L., Department of Political Science, University of California, Los Angeles, Los Angeles, CA, United States; Werker, Eric D., Beedie School of Business, Burnaby, BC, Canada | S11: Oxford University Press | T11: 2573032 | X11: English | Y11: World Bank Res. Obs. | Z11: Article | AA11: Final | AB11: All Open Access; Bronze Open Access | AC11: Scopus | AD11: 2-s2.0-85121205816
A12: McNeil, B.L.; Robertson, A.K.H.; Fu, W.; Yang, H.; Hoehr, C.; Ramogida, C.F.; Schaffer, P. | B12: McNeil, Brooke L. (57198862611); Robertson, Andrew Kyle Henderson (57198466545); Fu, Winnie (57222617965); Yang, Hua (56019802000); Hoehr, Cornelia (55326269700); Ramogida, Caterina Fortunata (37034801500); Schaffer, Paul (7102320285) | C12: 57198862611; 57198466545; 57222617965; 56019802000; 55326269700; 37034801500; 7102320285 | D12: Production, purification, and radiolabeling of the 203Pb/212Pb theranostic pair | E12: 2021 | F12: EJNMMI Radiopharmacy and Chemistry | G12: 6 | H12: 1 | I12: 6 | L12: 79 | M12: 10.1186/s41181-021-00121-4 | N12: https://www.scopus.com/inward/record.uri?eid=2-s2.0-85103473552&doi=10.1186%2Fs41181-021-00121-4&partnerID=40&md5=447bf58e442f10dcdf83e3fd52656cdb | O12: Division of Life Sciences, TRIUMF, Vancouver, BC, Canada; Department of Chemistry, Simon Fraser University, Burnaby, BC, Canada; Department of Physics and Astronomy, The University of British Columbia, Vancouver, BC, Canada; Department of Radiology, The University of British Columbia, Vancouver, BC, Canada | P12: McNeil, Brooke L., Division of Life Sciences, TRIUMF, Vancouver, BC, Canada, Department of Chemistry, Simon Fraser University, Burnaby, BC, Canada; Robertson, Andrew Kyle Henderson, Division of Life Sciences, TRIUMF, Vancouver, BC, Canada, Department of Physics and Astronomy, The University of British Columbia, Vancouver, BC, Canada; Fu, Winnie, Division of Life Sciences, TRIUMF, Vancouver, BC, Canada; Yang, Hua, Division of Life Sciences, TRIUMF, Vancouver, BC, Canada; Hoehr, Cornelia, Division of Life Sciences, TRIUMF, Vancouver, BC, Canada; Ramogida, Caterina Fortunata, Division of Life Sciences, TRIUMF, Vancouver, BC, Canada, Department of Chemistry, Simon Fraser University, Burnaby, BC, Canada; Schaffer, Paul, Division of Life Sciences, TRIUMF, Vancouver, BC, Canada, Department of Chemistry, Simon Fraser University, Burnaby, BC, Canada, Department of Radiology, The University of British Columbia, Vancouver, BC, Canada | Q12: C.F. Ramogida; Life Sciences Division, TRIUMF, Vancouver, Canada; email: cfr@sfu.ca; P. Schaffer; Life Sciences Division, TRIUMF, Vancouver, Canada; email: pschaffer@triumf.ca | S12: Springer Science and Business Media Deutschland GmbH | X12: English | Y12: EJNMMI Radiopharm. Chem. | Z12: Article | AA12: Final | AB12: All Open Access; Gold Open Access; Green Accepted Open Access; Green Open Access | AC12: Scopus | AD12: 2-s2.0-85103473552
A13: Tang, Y.; Rahmani Dehaghani, M.; Wang, G.G. | B13: Tang, Yifan (57203408641); Rahmani Dehaghani, Mostafa (57980243500); Wang, G. Gary (55599185800) | C13: 57203408641; 57980243500; 55599185800 | D13: Review of transfer learning in modeling additive manufacturing processes | E13: 2023 | F13: Additive Manufacturing | G13: 61 | I13: 103357 | L13: 77 | M13: 10.1016/j.addma.2022.103357 | N13: https://www.scopus.com/inward/record.uri?eid=2-s2.0-85144042254&doi=10.1016%2Fj.addma.2022.103357&partnerID=40&md5=fd34b4a80340a59200c1da4d14df9c4c | O13: Product Design and Optimization Laboratory, Simon Fraser University, Burnaby, BC, Canada | P13: Tang, Yifan, Product Design and Optimization Laboratory, Simon Fraser University, Burnaby, BC, Canada; Rahmani Dehaghani, Mostafa, Product Design and Optimization Laboratory, Simon Fraser University, Burnaby, BC, Canada; Wang, G. Gary, Product Design and Optimization Laboratory, Simon Fraser University, Burnaby, BC, Canada | Q13: G.G. Wang; Product Design and Optimization Laboratory, Simon Fraser University, Surrey, Canada; email: gary_wang@sfu.ca | S13: Elsevier B.V. | X13: English | Y13: Addit. Manuf. | Z13: Review | AA13: Final | AC13: Scopus | AD13: 2-s2.0-85144042254
A14: Liu, Z.; Wu, H.; Yuan, Y.; Wan, H.; Luo, Z.; Gao, P.; Zhuang, J.; Zhang, J.; Zhang, N.; Li, J.; Zhan, Y.; Ren, W.; Ye, Z.-G. | B14: Liu, Zenghui (56599407500); Wu, Hua (7405584390); Yuan, Yi (57207812926); Wan, Hongyan (57191164138); Luo, Zeng (57194680258); Gao, Pan (55763930900); Zhuang, Jian (57202600151); Zhang, Jie (56016217200); Zhang, Nan (26023886900); Li, Jingrui (7410067435); Zhan, Yage (7102619897); Ren, Wei (57201421397); Ye, Zuo Guang (24443034100) | C14: 56599407500; 7405584390; 57207812926; 57191164138; 57194680258; 55763930900; 57202600151; 56016217200; 26023886900; 7410067435; 7102619897; 57201421397; 24443034100 | D14: Recent progress in bismuth-based high Curie temperature piezo-/ferroelectric perovskites for electromechanical transduction applications | E14: 2022 | F14: Current Opinion in Solid State and Materials Science | G14: 26 | H14: 5 | I14: 101016 | L14: 73 | M14: 10.1016/j.cossms.2022.101016 | N14: https://www.scopus.com/inward/record.uri?eid=2-s2.0-85132215202&doi=10.1016%2Fj.cossms.2022.101016&partnerID=40&md5=944fa29dc666aaa7f3748061e6a37ab9 | O14: Electronic Materials Research Laboratory, Xi'an Jiaotong University, Xi'an, Shaanxi, China; College of Sciences, Donghua University, Shanghai, Shanghai, China; Department of Chemistry and 4D LABS, Simon Fraser University, Burnaby, BC, Canada; School of Electronic Information and Artificial Intelligence, Shaanxi University of Science and Technology, Xinyang, Shaanxi, China | P14: Liu, Zenghui, Electronic Materials Research Laboratory, Xi'an Jiaotong University, Xi'an, Shaanxi, China; Wu, Hua, College of Sciences, Donghua University, Shanghai, Shanghai, China; Yuan, Yi, Department of Chemistry and 4D LABS, Simon Fraser University, Burnaby, BC, Canada; Wan, Hongyan, Electronic Materials Research Laboratory, Xi'an Jiaotong University, Xi'an, Shaanxi, China; Luo, Zeng, Electronic Materials Research Laboratory, Xi'an Jiaotong University, Xi'an, Shaanxi, China; Gao, Pan, School of Electronic Information and Artificial Intelligence, Shaanxi University of Science and Technology, Xinyang, Shaanxi, China; Zhuang, Jian, Electronic Materials Research Laboratory, Xi'an Jiaotong University, Xi'an, Shaanxi, China; Zhang, Jie, Electronic Materials Research Laboratory, Xi'an Jiaotong University, Xi'an, Shaanxi, China; Zhang, Nan, Electronic Materials Research Laboratory, Xi'an Jiaotong University, Xi'an, Shaanxi, China; Li, Jingrui, Electronic Materials Research Laboratory, Xi'an Jiaotong University, Xi'an, Shaanxi, China; Zhan, Yage, College of Sciences, Donghua University, Shanghai, Shanghai, China; Ren, Wei, Electronic Materials Research Laboratory, Xi'an Jiaotong University, Xi'an, Shaanxi, China; Ye, Zuo Guang, Department of Chemistry and 4D LABS, Simon Fraser University, Burnaby, BC, Canada | Q14: Z. Liu; Electronic Materials Research Laboratory, Key Laboratory of the Ministry of Education & International Center for Dielectric Research, School of Electronic Science and Engineering, Xi'an Jiaotong University, Xi'an, 710049, China; email: liu.z.h@xjtu.edu.cn | S14: Elsevier Ltd | T14: 13590286 | X14: English | Y14: Curr. Opin. Solid State Mater. Sci. | Z14: Review | AA14: Final | AC14: Scopus | AD14: 2-s2.0-85132215202
A15: Liu, J.; Lou, J.; Liu, J.; Xiong, L.; Pei, J.; Sun, J. | B15: Liu, Jinfei (50061600600); Lou, Jian (57002257800); Liu, Junxu (57216522149); Xiong, Li (47461765600); Pei, Jian (15074136200); Sun, Jimeng (9737233900) | C15: 50061600600; 57002257800; 57216522149; 47461765600; 15074136200; 9737233900 | D15: Dealer: An end-to-end model marketplace with differential privacy | E15: 2021 | F15: Proceedings of the VLDB Endowment | G15: 14 | H15: 6 | J15: 957 | K15: 969 | L15: 71 | M15: 10.14778/3447689.3447700 | N15: https://www.scopus.com/inward/record.uri?eid=2-s2.0-85102659336&doi=10.14778%2F3447689.3447700&partnerID=40&md5=0315f19536de8ac3cb99b33b9b536815 | O15: Zhejiang University, Hangzhou, Zhejiang, China; Emory University, Atlanta, GA, United States; Renmin University of China, Beijing, China; Simon Fraser University, Burnaby, BC, Canada; UIUC, Berkeley, IL, United States | P15: Liu, Jinfei, Zhejiang University, Hangzhou, Zhejiang, China; Lou, Jian, Emory University, Atlanta, GA, United States; Liu, Junxu, Renmin University of China, Beijing, China; Xiong, Li, Emory University, Atlanta, GA, United States; Pei, Jian, Simon Fraser University, Burnaby, BC, Canada; Sun, Jimeng, UIUC, Berkeley, IL, United States | S15: VLDB Endowment | X15: English | Y15: Proc. VLDB Endow. | Z15: Article | AA15: Final | AC15: Scopus | AD15: 2-s2.0-85102659336
A16: Cermak, M.; Perez, N.; Collins, M.; Bahrami, M. | B16: Cermak, Martin (57193993567); Perez, Nicolas (57219663938); Collins, Michael R. (7404083839); Bahrami, Majid M. (35499001600) | C16: 57193993567; 57219663938; 7404083839; 35499001600 | D16: Material properties and structure of natural graphite sheet | E16: 2020 | F16: Scientific Reports | G16: 10 | H16: 1 | I16: 18672 | L16: 70 | M16: 10.1038/s41598-020-75393-y | N16: https://www.scopus.com/inward/record.uri?eid=2-s2.0-85094668236&doi=10.1038%2Fs41598-020-75393-y&partnerID=40&md5=76172ca4adccd1550326b9af2786271f | O16: Laboratory for Alternative Energy Conversion (LAEC), Simon Fraser University, Burnaby, BC, Canada; INSA Lyon, Villeurbanne, Auvergne-Rhone-Alpes, France; Department of Mechanical and Mechatronics Engineering, University of Waterloo, Waterloo, ON, Canada | P16: Cermak, Martin, Laboratory for Alternative Energy Conversion (LAEC), Simon Fraser University, Burnaby, BC, Canada; Perez, Nicolas, Laboratory for Alternative Energy Conversion (LAEC), Simon Fraser University, Burnaby, BC, Canada, INSA Lyon, Villeurbanne, Auvergne-Rhone-Alpes, France; Collins, Michael R., Department of Mechanical and Mechatronics Engineering, University of Waterloo, Waterloo, ON, Canada; Bahrami, Majid M., Laboratory for Alternative Energy Conversion (LAEC), Simon Fraser University, Burnaby, BC, Canada | Q16: M. Cermak; Laboratory for Alternative Energy Conversion, School of Mechatronic Systems Engineering, Faculty of Applied Science, Simon Fraser University, Surrey, 250-13450 102 Avenue, V3T 0A3, Canada; email: mcermak@sfu.ca; M. Bahrami; Laboratory for Alternative Energy Conversion, School of Mechatronic Systems Engineering, Faculty of Applied Science, Simon Fraser University, Surrey, 250-13450 102 Avenue, V3T 0A3, Canada; email: mbahrami@sfu.ca | S16: Nature Research subscriptions@nature.com | W16: 33122759 | X16: English | Y16: Sci. Rep. | Z16: Article | AA16: Final | AB16: All Open Access; Gold Open Access; Green Accepted Open Access; Green Open Access | AC16: Scopus | AD16: 2-s2.0-85094668236
A17: Buvat, G.; Eslamibidgoli, M.J.; Youssef, A.H.; Garbarino, S.; Ruediger, A.; Eikerling, M.; Guay, D. | B17: Buvat, Gaëtan (56916105800); Eslamibidgoli, Mohammad Javad (55444628700); Youssef, Azza Hadj (57204040160); Garbarino, Sébastien (26040680900); Ruediger, Andreas Peter (6601982880); Eikerling, M. H. (6604046486); Guay, Daniel (35482565400) | C17: 56916105800; 55444628700; 57204040160; 26040680900; 6601982880; 6604046486; 35482565400 | D17: Effect of IrO6 Octahedron Distortion on the OER Activity at (100) IrO2 Thin Film | E17: 2020 | F17: ACS Catalysis | G17: 10 | H17: 1 | J17: 806 | K17: 817 | L17: 70 | M17: 10.1021/acscatal.9b04347 | N17: https://www.scopus.com/inward/record.uri?eid=2-s2.0-85077127535&doi=10.1021%2Facscatal.9b04347&partnerID=40&md5=4d9922df895ee52d381e85139efb7e5a | O17: Centre Énergie Matériaux Télécommunications, Varennes, QC, Canada; Simon Fraser University, Burnaby, BC, Canada; PRIMA Québec, Montreal, QC, Canada; Institute of Energy and Climate Research, Forschungszentrum Jülich GmbH, Julich, Germany | P17: Buvat, Gaëtan, Centre Énergie Matériaux Télécommunications, Varennes, QC, Canada; Eslamibidgoli, Mohammad Javad, Centre Énergie Matériaux Télécommunications, Varennes, QC, Canada, Simon Fraser University, Burnaby, BC, Canada; Youssef, Azza Hadj, Centre Énergie Matériaux Télécommunications, Varennes, QC, Canada; Garbarino, Sébastien, PRIMA Québec, Montreal, QC, Canada; Ruediger, Andreas Peter, Centre Énergie Matériaux Télécommunications, Varennes, QC, Canada; Eikerling, M. H., Institute of Energy and Climate Research, Forschungszentrum Jülich GmbH, Julich, Germany; Guay, Daniel, Centre Énergie Matériaux Télécommunications, Varennes, QC, Canada | Q17: D. Guay; INRS-énergie, Matériaux Télécommunications, Varennes, 1650 Lionel-Boulet Boulevard, J3X 1S2, Canada; email: guay@emt.inrs.ca | S17: American Chemical Society service@acs.org | T17: 21555435 | V17: ACCAC | X17: English | Y17: ACS Catal. | Z17: Article | AA17: Final | AC17: Scopus | AD17: 2-s2.0-85077127535
A18: Dabić, M.; Vlačić, E.; Ramanathan, U.; Egri, C.P. | B18: Dabić, Marina (6507123949); Vlačić, Ernest (57201136437); Ramanathan, Usha (35222184300); Egri, Carolyn P. (6602228740) | C18: 6507123949; 57201136437; 35222184300; 6602228740 | D18: Evolving Absorptive Capacity: The Mediating Role of Systematic Knowledge Management | E18: 2020 | F18: IEEE Transactions on Engineering Management | G18: 67 | H18: 3 | I18: 8643412 | J18: 783 | K18: 793 | L18: 68 | M18: 10.1109/TEM.2019.2893133 | N18: https://www.scopus.com/inward/record.uri?eid=2-s2.0-85088872853&doi=10.1109%2FTEM.2019.2893133&partnerID=40&md5=8bc955e1e6fff52a589ba1cd439d2d27 | O18: University of Zagreb, Faculty of Economics and Business, Zagreb, Croatia; NOVAMINA CIT, Zagreb, Croatia; Nottingham Business School, Nottingham, Nottinghamshire, United Kingdom; Beedie School of Business, Burnaby, BC, Canada | P18: Dabić, Marina, University of Zagreb, Faculty of Economics and Business, Zagreb, Croatia; Vlačić, Ernest, NOVAMINA CIT, Zagreb, Croatia; Ramanathan, Usha, Nottingham Business School, Nottingham, Nottinghamshire, United Kingdom; Egri, Carolyn P., Beedie School of Business, Burnaby, BC, Canada | Q18: M. Dabic; Faculty of Economics and Business, University of Zagreb, Zagreb, 10000, Croatia; email: mdabic@efzg.hr | S18: Institute of Electrical and Electronics Engineers Inc. | T18: 189391 | V18: IEEMA | X18: English | Y18: IEEE Trans Eng Manage | Z18: Article | AA18: Final | AC18: Scopus | AD18: 2-s2.0-85088872853
A19: Iqbal, M.Z.; Zakar, S.; Tayyab, M.; Haider, S.S.; Alzaid, M.; Afzal, A.M.; Aftab, S. | B19: Iqbal, Muhammad Zahir (59594047700); Zakar, Sana (57211666662); Tayyab, Muhammad (59260634800); Haider, Syed Shabhi (57210752357); Alzaid, Meshal M. (57193761447); Afzal, Amir Muhammad (57200106539); Aftab, Sikandar (57200114034) | C19: 59594047700; 57211666662; 59260634800; 57210752357; 57193761447; 57200106539; 57200114034 | D19: Scrutinizing the charge storage mechanism in SrO based composites for asymmetric supercapacitors by diffusion-controlled process | E19: 2020 | F19: Applied Nanoscience (Switzerland) | G19: 10 | H19: 11 | J19: 3999 | K19: 4011 | L19: 65 | M19: 10.1007/s13204-020-01542-4 | N19: https://www.scopus.com/inward/record.uri?eid=2-s2.0-85090302394&doi=10.1007%2Fs13204-020-01542-4&partnerID=40&md5=690a8dbdb42c18c4ba7c098257d314f2 | O19: Nanotechnology Research Laboratory, Ghulam Ishaq Khan Institute of Engineering Sciences and Technology, Topi, Khyber Pakhtunkhwa, Pakistan; Department of Physics, Jouf University, Sakakah, Al Jawf, Saudi Arabia; Department of Electrical and Biological Physics, Kwangwoon University, Seoul, South Korea; Department of Engineering, Simon Fraser University, Burnaby, BC, Canada | P19: Iqbal, Muhammad Zahir, Nanotechnology Research Laboratory, Ghulam Ishaq Khan Institute of Engineering Sciences and Technology, Topi, Khyber Pakhtunkhwa, Pakistan; Zakar, Sana, Nanotechnology Research Laboratory, Ghulam Ishaq Khan Institute of Engineering Sciences and Technology, Topi, Khyber Pakhtunkhwa, Pakistan; Tayyab, Muhammad, Nanotechnology Research Laboratory, Ghulam Ishaq Khan Institute of Engineering Sciences and Technology, Topi, Khyber Pakhtunkhwa, Pakistan; Haider, Syed Shabhi, Nanotechnology Research Laboratory, Ghulam Ishaq Khan Institute of Engineering Sciences and Technology, Topi, Khyber Pakhtunkhwa, Pakistan; Alzaid, Meshal M., Department of Physics, Jouf University, Sakakah, Al Jawf, Saudi Arabia; Afzal, Amir Muhammad, Department of Electrical and Biological Physics, Kwangwoon University, Seoul, South Korea; Aftab, Sikandar, Department of Engineering, Simon Fraser University, Burnaby, BC, Canada | Q19: M.Z. Iqbal; Nanotechnology Research Laboratory, Faculty of Engineering Sciences, GIK Institute of Engineering Sciences and Technology, Topi, 23640, Pakistan; email: zahir.upc@gmail.com | S19: Springer Science and Business Media Deutschland GmbH | T19: 21905509 | X19: English | Y19: Appl. Nanosci. (Switzerland) | Z19: Article | AA19: Final | AC19: Scopus | AD19: 2-s2.0-85090302394
A20: Short, L.; Holt, R.A.; Cullis, P.R.; Evgin, L. | B20: Short, Lauralie (58761774500); Holt, Robert A. (7402085535); Cullis, Pieter R. (7101856304); Evgin, Laura (35421820800) | C20: 58761774500; 7402085535; 7101856304; 35421820800 | D20: Direct in vivo CAR T cell engineering | E20: 2024 | F20: Trends in Pharmacological Sciences | G20: 45 | H20: 5 | J20: 406 | K20: 418 | L20: 64 | M20: 10.1016/j.tips.2024.03.004 | N20: https://www.scopus.com/inward/record.uri?eid=2-s2.0-85190171601&doi=10.1016%2Fj.tips.2024.03.004&partnerID=40&md5=0a33d1c815d193bafb481a6cb42d1060 | O20: British Columbia Cancer Agency, Vancouver, BC, Canada; Interdisciplinary Oncology Program, The University of British Columbia, Vancouver, BC, Canada; Department of Medical Genetics, The University of British Columbia, Vancouver, BC, Canada; Department of Biochemistry and Molecular Biology, Simon Fraser University, Burnaby, BC, Canada; Department of Biochemistry and Molecular Biology, The University of British Columbia, Vancouver, BC, Canada | P20: Short, Lauralie, British Columbia Cancer Agency, Vancouver, BC, Canada, Interdisciplinary Oncology Program, The University of British Columbia, Vancouver, BC, Canada; Holt, Robert A., British Columbia Cancer Agency, Vancouver, BC, Canada, Interdisciplinary Oncology Program, The University of British Columbia, Vancouver, BC, Canada, Department of Medical Genetics, The University of British Columbia, Vancouver, BC, Canada, Department of Biochemistry and Molecular Biology, Simon Fraser University, Burnaby, BC, Canada; Cullis, Pieter R., Department of Biochemistry and Molecular Biology, The University of British Columbia, Vancouver, BC, Canada; Evgin, Laura, British Columbia Cancer Agency, Vancouver, BC, Canada, Interdisciplinary Oncology Program, The University of British Columbia, Vancouver, BC, Canada, Department of Medical Genetics, The University of British Columbia, Vancouver, BC, Canada | S20: Elsevier Ltd | T20: 1656147 | V20: TPHSD | W20: 38614815 | X20: English | Y20: Trends Pharmacol. Sci. | Z20: Review | AA20: Final | AB20: All Open Access; Hybrid Gold Open Access | AC20: Scopus | AD20: 2-s2.0-85190171601
A21: Chakraborty, A.; Pai, N.; Zhao, J.; Tuttle, B.R.; Simonov, A.N.; Pecunia, V. | B21: Chakraborty, Abhisek (57191486372); Pai, Narendra K. (57194281275); Zhao, Jing (57214117753); Tuttle, Blair R. (56262850800); Simonov, Alexandr N. (35894458100); Pecunia, Vincenzo (36017327500) | C21: 57191486372; 57194281275; 57214117753; 56262850800; 35894458100; 36017327500 | D21: Rudorffites and Beyond: Perovskite-Inspired Silver/Copper Pnictohalides for Next-Generation Environmentally Friendly Photovoltaics and Optoelectronics | E21: 2022 | F21: Advanced Functional Materials | G21: 32 | H21: 36 | I21: 2203300 | L21: 64 | M21: 10.1002/adfm.202203300 | N21: https://www.scopus.com/inward/record.uri?eid=2-s2.0-85134421629&doi=10.1002%2Fadfm.202203300&partnerID=40&md5=14df76d8e8d501b497ef0ef86025a92f | O21: Joint International Research Laboratory of Carbon-Based Functional Materials and Devices, Soochow University, Suzhou, Jiangsu, China; Department of Chemical Engineering, Monash University, Melbourne, VIC, Australia; Department of Physics, Penn State Behrend, Erie, PA, United States; School of Chemistry, Monash University, Melbourne, VIC, Australia; School of Sustainable Energy Engineering, Simon Fraser University, Burnaby, BC, Canada | P21: Chakraborty, Abhisek, Joint International Research Laboratory of Carbon-Based Functional Materials and Devices, Soochow University, Suzhou, Jiangsu, China; Pai, Narendra K., Department of Chemical Engineering, Monash University, Melbourne, VIC, Australia; Zhao, Jing, Joint International Research Laboratory of Carbon-Based Functional Materials and Devices, Soochow University, Suzhou, Jiangsu, China; Tuttle, Blair R., Department of Physics, Penn State Behrend, Erie, PA, United States; Simonov, Alexandr N., School of Chemistry, Monash University, Melbourne, VIC, Australia; Pecunia, Vincenzo, School of Sustainable Energy Engineering, Simon Fraser University, Burnaby, BC, Canada | Q21: A.N. Simonov; School of Chemistry, Monash University, 3800, Australia; email: alexandr.simonov@monash.edu; V. Pecunia; School of Sustainable Energy Engineering, Simon Fraser University, Surrey, V3T 0N1, Canada; email: pecunia@sfu.ca | S21: John Wiley and Sons Inc | T21: 1616301X | V21: AFMDC | X21: English | Y21: Adv. Funct. Mater. | Z21: Review | AA21: Final | AB21: All Open Access; Hybrid Gold Open Access | AC21: Scopus | AD21: 2-s2.0-85134421629
A22: Praats, R.; Käärik, M.; Kikas, A.; Kisand, V.; Aruväli, J.; Paiste, P.; Merisalu, M.; Leis, J.; Sammelselg, V.; Zagal, J.H.; Holdcroft, S.; Nakashima, N.; Tammeveski, K. | B22: Praats, Reio (57205640449); Käärik, Maike (15735143100); Kikas, Arvo (6603881774); Kisand, Vambola (7004348077); Aruväli, Jaan (6508076618); Paiste, Päärn (57189352891); Merisalu, Maido (36990846300); Leis, Jaan (56233840400); Sammelselg, Väino (7004105800); Zagal, Jose H. (7006164899); Holdcroft, Steven J. (7004469945); Nakashima, Naotoshi (7102319939); Tammeveski, Kaido (6603704456) | C22: 57205640449; 15735143100; 6603881774; 7004348077; 6508076618; 57189352891; 36990846300; 56233840400; 7004105800; 7006164899; 7004469945; 7102319939; 6603704456 | D22: Electrocatalytic oxygen reduction reaction on iron phthalocyanine-modified carbide-derived carbon/carbon nanotube composite electrocatalysts | E22: 2020 | F22: Electrochimica Acta | G22: 334 | I22: 135575 | L22: 64 | M22: 10.1016/j.electacta.2019.135575 | N22: https://www.scopus.com/inward/record.uri?eid=2-s2.0-85077345443&doi=10.1016%2Fj.electacta.2019.135575&partnerID=40&md5=c54564a40889e271f7e517252e7d2a8f | O22: Institute of Chemistry, Tartu Ülikool, Tartu, Tartumaa, Estonia; Institute of Physics, Tartu Ülikool, Tartu, Tartumaa, Estonia; Ökoloogia ja Maateaduste Instituut, Tartu, Tartumaa, Estonia; Departamento de Química de los Materiales, Universidad de Santiago de Chile, Santiago, RM, Chile; Simon Fraser University, Burnaby, BC, Canada; International Institute for Carbon-Neutral Energy Research (WPI-I2CNER), Kyushu University, Fukuoka, Fukuoka, Japan | P22: Praats, Reio, Institute of Chemistry, Tartu Ülikool, Tartu, Tartumaa, Estonia; Käärik, Maike, Institute of Chemistry, Tartu Ülikool, Tartu, Tartumaa, Estonia; Kikas, Arvo, Institute of Physics, Tartu Ülikool, Tartu, Tartumaa, Estonia; Kisand, Vambola, Institute of Physics, Tartu Ülikool, Tartu, Tartumaa, Estonia; Aruväli, Jaan, Ökoloogia ja Maateaduste Instituut, Tartu, Tartumaa, Estonia; Paiste, Päärn, Ökoloogia ja Maateaduste Instituut, Tartu, Tartumaa, Estonia; Merisalu, Maido, Institute of Chemistry, Tartu Ülikool, Tartu, Tartumaa, Estonia, Institute of Physics, Tartu Ülikool, Tartu, Tartumaa, Estonia; Leis, Jaan, Institute of Chemistry, Tartu Ülikool, Tartu, Tartumaa, Estonia; Sammelselg, Väino, Institute of Chemistry, Tartu Ülikool, Tartu, Tartumaa, Estonia, Institute of Physics, Tartu Ülikool, Tartu, Tartumaa, Estonia; Zagal, Jose H., Departamento de Química de los Materiales, Universidad de Santiago de Chile, Santiago, RM, Chile; Holdcroft, Steven J., Simon Fraser University, Burnaby, BC, Canada; Nakashima, Naotoshi, International Institute for Carbon-Neutral Energy Research (WPI-I2CNER), Kyushu University, Fukuoka, Fukuoka, Japan; Tammeveski, Kaido, Institute of Chemistry, Tartu Ülikool, Tartu, Tartumaa, Estonia | Q22: K. Tammeveski; Institute of Chemistry, University of Tartu, Tartu, Ravila 14a, 50411, Estonia; email: kaido.tammeveski@ut.ee | S22: Elsevier Ltd | T22: 134686 | V22: ELCAA | X22: English | Y22: Electrochim Acta | Z22: Article | AA22: Final | AC22: Scopus | AD22: 2-s2.0-85077345443
A23: Heng, W.; Yang, G.; Kim, W.S.; Xu, K. | B23: Heng, Wenzheng (57212027826); Yang, Geng (54961736000); Kim, Woo Soo (17136903100); Xu, Kaichen (57189468699) | C23: 57212027826; 54961736000; 17136903100; 57189468699 | D23: Emerging wearable flexible sensors for sweat analysis | E23: 2022 | F23: Bio-Design and Manufacturing | G23: 5 | H23: 1 | J23: 64 | K23: 84 | L23: 63 | M23: 10.1007/s42242-021-00171-2 | N23: https://www.scopus.com/inward/record.uri?eid=2-s2.0-85120303080&doi=10.1007%2Fs42242-021-00171-2&partnerID=40&md5=20ea28c8633c8b489c1e10d83d636933 | O23: State Key Laboratory of Fluid Power and Mechatronic Systems, Hangzhou, Zhejiang, China; California Institute of Technology Division of Engineering and Applied Science, Pasadena, CA, United States; School of Mechatronic Systems Engineering, Simon Fraser University, Burnaby, BC, Canada | P23: Heng, Wenzheng, State Key Laboratory of Fluid Power and Mechatronic Systems, Hangzhou, Zhejiang, China, California Institute of Technology Division of Engineering and Applied Science, Pasadena, CA, United States; Yang, Geng, State Key Laboratory of Fluid Power and Mechatronic Systems, Hangzhou, Zhejiang, China; Kim, Woo Soo, School of Mechatronic Systems Engineering, Simon Fraser University, Burnaby, BC, Canada; Xu, Kaichen, State Key Laboratory of Fluid Power and Mechatronic Systems, Hangzhou, Zhejiang, China | Q23: G. Yang; State Key Laboratory of Fluid Power and Mechatronic Systems, School of Mechanical Engineering, Zhejiang University, Hangzhou, 310027, China; email: yanggeng@zju.edu.cn; K. Xu; State Key Laboratory of Fluid Power and Mechatronic Systems, School of Mechanical Engineering, Zhejiang University, Hangzhou, 310027, China; email: xukc@zju.edu.cn | S23: Springer | T23: 20965524 | X23: English | Y23: Bio-Des. Manufact. | Z23: Review | AA23: Final | AC23: Scopus | AD23: 2-s2.0-85120303080
A24: Borden, S.A.; Saatchi, A.; Vandergrift, G.W.; Palaty, J.; Lysyshyn, M.; Gill, C. | B24: Borden, Scott A. (57204782022); Saatchi, Armin (57222205914); Vandergrift, Gregory W. (56568381000); Palaty, Jan (7801485606); Lysyshyn, Mark (57195582410); Gill, Christopher G. (57212485188) | C24: 57204782022; 57222205914; 56568381000; 7801485606; 57195582410; 57212485188 | D24: A new quantitative drug checking technology for harm reduction: Pilot study in Vancouver, Canada using paper spray mass spectrometry | E24: 2022 | F24: Drug and Alcohol Review | G24: 41 | H24: 2 | J24: 410 | K24: 418 | L24: 62 | M24: 10.1111/dar.13370 | N24: https://www.scopus.com/inward/record.uri?eid=2-s2.0-85111746417&doi=10.1111%2Fdar.13370&partnerID=40&md5=311280bd1168f032adcac4454425fa64 | O24: Department of Chemistry, Vancouver Island University, Nanaimo, BC, Canada; University of Victoria, Victoria, BC, Canada; LifeLabs Medical Laboratories, Burnaby, BC, Canada; School of Population and Public Health, The University of British Columbia, Vancouver, BC, Canada; Vancouver Coastal Health, Vancouver, BC, Canada; Simon Fraser University, Burnaby, BC, Canada; Department of Occupational and Environmental Health, University of Washington, Seattle, WA, United States | P24: Borden, Scott A., Department of Chemistry, Vancouver Island University, Nanaimo, BC, Canada, University of Victoria, Victoria, BC, Canada; Saatchi, Armin, Department of Chemistry, Vancouver Island University, Nanaimo, BC, Canada; Vandergrift, Gregory W., Department of Chemistry, Vancouver Island University, Nanaimo, BC, Canada, University of Victoria, Victoria, BC, Canada; Palaty, Jan, LifeLabs Medical Laboratories, Burnaby, BC, Canada; Lysyshyn, Mark, School of Population and Public Health, The University of British Columbia, Vancouver, BC, Canada, Vancouver Coastal Health, Vancouver, BC, Canada; Gill, Christopher G., Department of Chemistry, Vancouver Island University, Nanaimo, BC, Canada, University of Victoria, Victoria, BC, Canada, Simon Fraser University, Burnaby, BC, Canada, Department of Occupational and Environmental Health, University of Washington, Seattle, WA, United States | Q24: C.G. Gill; Applied Environmental Research Laboratories, Department of Chemistry, Vancouver Island University, Nanaimo, Canada; email: chris.gill@viu.ca | S24: John Wiley and Sons Inc | T24: 9595236 | W24: 34347332 | X24: English | Y24: Drug Alcohol Rev. | Z24: Article | AA24: Final | AB24: All Open Access; Green Accepted Open Access; Green Open Access; Hybrid Gold Open Access | AC24: Scopus | AD24: 2-s2.0-85111746417
A25: Goudswaard, M.; Abraham, A.; Goveia da Rocha, B.; Andersen, K.; Liang, R.-H. | B25: Goudswaard, Maas (57218862818); Abraham, Abel (57218863799); Goveia da Rocha, Bruna (57209308626); Andersen, Kristina (24079506700); Liang, Ronghao (57014209000) | C25: 57218862818; 57218863799; 57209308626; 24079506700; 57014209000 | D25: FabriClick: Interweaving pushbuttons into fabrics using 3d printing and digital embroidery | E25: 2020 | F25: DIS 2020 - Proceedings of the 2020 ACM Designing Interactive Systems Conference | J25: 379 | K25: 393 | L25: 61 | M25: 10.1145/3357236.3395569 | N25: https://www.scopus.com/inward/record.uri?eid=2-s2.0-85090502866&doi=10.1145%2F3357236.3395569&partnerID=40&md5=6f3915b176cdc5fdf1eb028c441e3174 | O25: Technische Universiteit Eindhoven, Eindhoven, Noord-Brabant, Netherlands; Simon Fraser University, Burnaby, BC, Canada | P25: Goudswaard, Maas, Technische Universiteit Eindhoven, Eindhoven, Noord-Brabant, Netherlands; Abraham, Abel, Technische Universiteit Eindhoven, Eindhoven, Noord-Brabant, Netherlands, Simon Fraser University, Burnaby, BC, Canada; Goveia da Rocha, Bruna, Technische Universiteit Eindhoven, Eindhoven, Noord-Brabant, Netherlands; Andersen, Kristina, Technische Universiteit Eindhoven, Eindhoven, Noord-Brabant, Netherlands; Liang, Ronghao, Technische Universiteit Eindhoven, Eindhoven, Noord-Brabant, Netherlands | S25: Association for Computing Machinery, Inc acmhelp@acm.org | U25: 9781450000000 | X25: English | Y25: DIS Companion - Companion Publ. ACM Des. Interact. Syst. Conf. | Z25: Conference paper | AA25: Final | AC25: Scopus | AD25: 2-s2.0-85090502866
A26: Pinjari, S.; Bera, T.; Kapur, G.S.; Kjeang, E. | B26: Pinjari, Syedvali (57200221609); Bera, Tapan (57220445204); Kapur, Gurpreet Singh (7004114808); Kjeang, Erik (16066971400) | C26: 57200221609; 57220445204; 7004114808; 16066971400 | D26: The mechanism and sorption kinetic analysis of hydrogen storage at room temperature using acid functionalized carbon nanotubes | E26: 2023 | F26: International Journal of Hydrogen Energy | G26: 48 | H26: 5 | J26: 1930 | K26: 1942 | L26: 60 | M26: 10.1016/j.ijhydene.2022.10.080 | N26: https://www.scopus.com/inward/record.uri?eid=2-s2.0-85144970761&doi=10.1016%2Fj.ijhydene.2022.10.080&partnerID=40&md5=b6d79b51c1256fa965ddfedd952ae253 | O26: Fuel Cell Research Laboratory, Simon Fraser University, Burnaby, BC, Canada; Alternative Energy, Indian Oil Corporation Limited, New Delhi, India | P26: Pinjari, Syedvali, Fuel Cell Research Laboratory, Simon Fraser University, Burnaby, BC, Canada, Alternative Energy, Indian Oil Corporation Limited, New Delhi, India; Bera, Tapan, Alternative Energy, Indian Oil Corporation Limited, New Delhi, India; Kapur, Gurpreet Singh, Alternative Energy, Indian Oil Corporation Limited, New Delhi, India; Kjeang, Erik, Fuel Cell Research Laboratory, Simon Fraser University, Burnaby, BC, Canada | Q26: E. Kjeang; Fuel Cell Research Laboratory, Simon Fraser University, Surrey, 250-13450 102 Avenue, V3T0A3, Canada; email: ekjeang@sfu.ca | S26: Elsevier Ltd | T26: 3603199 | U26: 80311393 | V26: IJHED | X26: English | Y26: Int J Hydrogen Energy | Z26: Article | AA26: Final | AC26: Scopus | AD26: 2-s2.0-85144970761
A27: Park, S.H.; Goodall, G.; Kim, W.S. | B27: Park, Seong-hyeon (57203850725); Goodall, Geordie (57216749159); Kim, Woo Soo (17136903100) | C27: 57203850725; 57216749159; 17136903100 | D27: Perspective on 3D-designed micro-supercapacitors | E27: 2020 | F27: Materials and Design | G27: 193 | I27: 108797 | L27: 60 | M27: 10.1016/j.matdes.2020.108797 | N27: https://www.scopus.com/inward/record.uri?eid=2-s2.0-85084468330&doi=10.1016%2Fj.matdes.2020.108797&partnerID=40&md5=5b143ca834d4ad2ef5c85c935edf90a0 | O27: Additive Manufacturing Laboratory, Simon Fraser University, Burnaby, BC, Canada | P27: Park, Seong-hyeon, Additive Manufacturing Laboratory, Simon Fraser University, Burnaby, BC, Canada; Goodall, Geordie, Additive Manufacturing Laboratory, Simon Fraser University, Burnaby, BC, Canada; Kim, Woo Soo, Additive Manufacturing Laboratory, Simon Fraser University, Burnaby, BC, Canada | Q27: W.S. Kim; Additive Manufacturing Laboratory, School of Mechatronic Systems Engineering, Simon Fraser University, Surrey, Canada; email: woosook@sfu.ca | S27: Elsevier Ltd | T27: 2641275 | U27: 9781860000000 | X27: English | Y27: Mater. Des. | Z27: Review | AA27: Final | AB27: All Open Access; Gold Open Access; Green Accepted Open Access; Green Open Access | AC27: Scopus | AD27: 2-s2.0-85084468330
A28: Iqbal, M.Z.; Khan, J.; Siddique, S.; Afzal, A.M.; Aftab, S. | B28: Iqbal, Muhammad Zahir (59594047700); Khan, Junaid Ahmad (57220763239); Siddique, Salma (55777825500); Afzal, Amir Muhammad (57200106539); Aftab, Sikandar (57200114034) | C28: 59594047700; 57220763239; 55777825500; 57200106539; 57200114034 | D28: Optimizing electrochemical performance of sonochemically and hydrothermally synthesized cobalt phosphate for supercapattery devices | E28: 2021 | F28: International Journal of Hydrogen Energy | G28: 46 | H28: 29 | J28: 15807 | K28: 15819 | L28: 57 | M28: 10.1016/j.ijhydene.2021.02.077 | N28: https://www.scopus.com/inward/record.uri?eid=2-s2.0-85102279922&doi=10.1016%2Fj.ijhydene.2021.02.077&partnerID=40&md5=1ef97b6675aad5fa4807f48d24d7135e | O28: Faculty of Engineering Sciences, Ghulam Ishaq Khan Institute of Engineering Sciences and Technology, Topi, Khyber Pakhtunkhwa, Pakistan; Institute of Industrial Biotechnology, Government College University Lahore, Lahore, Punjab, Pakistan; Department of Physics, Riphah International University, Islamabad, Pakistan; Department of Engineering, Simon Fraser University, Burnaby, BC, Canada | P28: Iqbal, Muhammad Zahir, Faculty of Engineering Sciences, Ghulam Ishaq Khan Institute of Engineering Sciences and Technology, Topi, Khyber Pakhtunkhwa, Pakistan; Khan, Junaid Ahmad, Faculty of Engineering Sciences, Ghulam Ishaq Khan Institute of Engineering Sciences and Technology, Topi, Khyber Pakhtunkhwa, Pakistan; Siddique, Salma, Institute of Industrial Biotechnology, Government College University Lahore, Lahore, Punjab, Pakistan; Afzal, Amir Muhammad, Department of Physics, Riphah International University, Islamabad, Pakistan; Aftab, Sikandar, Department of Engineering, Simon Fraser University, Burnaby, BC, Canada | Q28: M.Z. Iqbal; Nanotechnology Research Laboratory, Faculty of Engineering Sciences, GIK Institute of Engineering Sciences and Technology, Topi, 23640, Pakistan; email: zahir.upc@gmail.com | S28: Elsevier Ltd | T28: 3603199 | U28: 80311393 | V28: IJHED | X28: English | Y28: Int J Hydrogen Energy | Z28: Article | AA28: Final | AC28: Scopus | AD28: 2-s2.0-85102279922
A29: Iqbal, M.Z.; Khan, J.; Awan, H.T.A.; Alzaid, M.; Afzal, A.M.; Aftab, S. | B29: Iqbal, Muhammad Zahir (59594047700); Khan, Junaid Ahmad (57220763239); Awan, Hafiz Taimoor Ahmed (57953063900); Alzaid, Meshal M. (57193761447); Afzal, Amir Muhammad (57200106539); Aftab, Sikandar (57200114034) | C29: 59594047700; 57220763239; 57953063900; 57193761447; 57200106539; 57200114034 | D29: Cobalt-manganese-zinc ternary phosphate for high performance supercapattery devices | E29: 2020 | F29: Dalton Transactions | G29: 49 | H29: 46 | J29: 16715 | K29: 16727 | L29: 57 | M29: 10.1039/d0dt03313h | N29: https://www.scopus.com/inward/record.uri?eid=2-s2.0-85097587342&doi=10.1039%2Fd0dt03313h&partnerID=40&md5=2a98746b8bdf7189e623ca6b7aee8ee5 | O29: Nanotechnology Research Laboratory, Ghulam Ishaq Khan Institute of Engineering Sciences and Technology, Topi, Khyber Pakhtunkhwa, Pakistan; Faculty of Engineering Sciences, Ghulam Ishaq Khan Institute of Engineering Sciences and Technology, Topi, Khyber Pakhtunkhwa, Pakistan; Department of Physics, Jouf University, Sakakah, Al Jawf, Saudi Arabia; Department of Electrical and Biological Physics, Kwangwoon University, Seoul, South Korea; Department of Engineering, Simon Fraser University, Burnaby, BC, Canada | P29: Iqbal, Muhammad Zahir, Nanotechnology Research Laboratory, Ghulam Ishaq Khan Institute of Engineering Sciences and Technology, Topi, Khyber Pakhtunkhwa, Pakistan; Khan, Junaid Ahmad, Nanotechnology Research Laboratory, Ghulam Ishaq Khan Institute of Engineering Sciences and Technology, Topi, Khyber Pakhtunkhwa, Pakistan; Awan, Hafiz Taimoor Ahmed, Faculty of Engineering Sciences, Ghulam Ishaq Khan Institute of Engineering Sciences and Technology, Topi, Khyber Pakhtunkhwa, Pakistan; Alzaid, Meshal M., Department of Physics, Jouf University, Sakakah, Al Jawf, Saudi Arabia; Afzal, Amir Muhammad, Department of Electrical and Biological Physics, Kwangwoon University, Seoul, South Korea; Aftab, Sikandar, Department of Engineering, Simon Fraser University, Burnaby, BC, Canada | Q29: M.Z. Iqbal; Nanotechnology Research Laboratory, Faculty of Engineering Sciences, GIK Institute of Engineering Sciences and Technology, Topi, Khyber Pakhtunkhwa, 23640, Pakistan; email: zahir.upc@gmail.com | S29: Royal Society of Chemistry | T29: 14779226 | V29: DTARA | W29: 33185641 | X29: English | Y29: Dalton Trans. | Z29: Article | AA29: Final | AC29: Scopus | AD29: 2-s2.0-85097587342
A30: Abnavi, H.; Maram, D.K.; Abnavi, A. | B30: Abnavi, Hamed (57221131396); Maram, Daniyal Khosh (57210573338); Abnavi, Amin (57194502466) | C30: 57221131396; 57210573338; 57194502466 | D30: Performance analysis of several electron/hole transport layers in thin film MAPbI3-based perovskite solar cells: A simulation study | E30: 2021 | F30: Optical Materials | G30: 118 | I30: 111258 | L30: 56 | M30: 10.1016/j.optmat.2021.111258 | N30: https://www.scopus.com/inward/record.uri?eid=2-s2.0-85108090069&doi=10.1016%2Fj.optmat.2021.111258&partnerID=40&md5=3e7ff16f5e6127d9558f0ce69573191d | O30: Department of Electrical Engineering, Amirkabir University of Technology, Tehran, Tehran, Iran; School of Engineering Science, Simon Fraser University, Burnaby, BC, Canada | P30: Abnavi, Hamed, Department of Electrical Engineering, Amirkabir University of Technology, Tehran, Tehran, Iran; Maram, Daniyal Khosh, Department of Electrical Engineering, Amirkabir University of Technology, Tehran, Tehran, Iran; Abnavi, Amin, School of Engineering Science, Simon Fraser University, Burnaby, BC, Canada | Q30: A. Abnavi; School of Engineering Science, Simon Fraser University, Burnaby, 8888 University Drive, Canada; email: amin_abnavi@sfu.ca | S30: Elsevier B.V. | T30: 9253467 | V30: OMATE | X30: English | Y30: Opt Mater | Z30: Article | AA30: Final | AC30: Scopus | AD30: 2-s2.0-85108090069
A31: Iqbal, M.Z.; Khan, J.; Afzal, A.M.; Aftab, S. | B31: Iqbal, Muhammad Zahir (59594047700); Khan, Junaid Ahmad (57220763239); Afzal, Amir Muhammad (57200106539); Aftab, Sikandar (57200114034) | C31: 59594047700; 57220763239; 57200106539; 57200114034 | D31: Exploring the synergetic electrochemical performance of cobalt sulfide/cobalt phosphate composites for supercapattery devices with high-energy and rate capability | E31: 2021 | F31: Electrochimica Acta | G31: 384 | I31: 138358 | L31: 55 | M31: 10.1016/j.electacta.2021.138358 | N31: https://www.scopus.com/inward/record.uri?eid=2-s2.0-85105104828&doi=10.1016%2Fj.electacta.2021.138358&partnerID=40&md5=a621e0a9d153f045d4d52291448ece9d | O31: Nanotechnology Research Laboratory, Ghulam Ishaq Khan Institute of Engineering Sciences and Technology, Topi, Khyber Pakhtunkhwa, Pakistan; Department of Physics, Riphah International University, Islamabad, Pakistan; Department of Engineering, Simon Fraser University, Burnaby, BC, Canada | P31: Iqbal, Muhammad Zahir, Nanotechnology Research Laboratory, Ghulam Ishaq Khan Institute of Engineering Sciences and Technology, Topi, Khyber Pakhtunkhwa, Pakistan; Khan, Junaid Ahmad, Nanotechnology Research Laboratory, Ghulam Ishaq Khan Institute of Engineering Sciences and Technology, Topi, Khyber Pakhtunkhwa, Pakistan; Afzal, Amir Muhammad, Department of Physics, Riphah International University, Islamabad, Pakistan; Aftab, Sikandar, Department of Engineering, Simon Fraser University, Burnaby, BC, Canada | Q31: M.Z. Iqbal; Nanotechnology Research Laboratory, Faculty of Engineering Sciences, GIK Institute of Engineering Sciences and Technology, Topi, 23640, Pakistan; email: zahir.upc@gmail.com | S31: Elsevier Ltd | T31: 134686 | V31: ELCAA | X31: English | Y31: Electrochim Acta | Z31: Article | AA31: Final | AC31: Scopus | AD31: 2-s2.0-85105104828
A32: Kaur, M.; Kim, T.-H.; Kim, W.S. | B32: Kaur, Manpreet (58588589500); Kim, Tae Ho (56168759700); Kim, Woo Soo (17136903100) | C32: 58588589500; 56168759700; 17136903100 | D32: New Frontiers in 3D Structural Sensing Robots | E32: 2021 | F32: Advanced Materials | G32: 33 | H32: 19 | I32: 2002534 | L32: 54 | M32: 10.1002/adma.202002534 | N32: https://www.scopus.com/inward/record.uri?eid=2-s2.0-85100159592&doi=10.1002%2Fadma.202002534&partnerID=40&md5=e00122ccde55039765b1adb563592510 | O32: School of Mechatronic Systems Engineering, Simon Fraser University, Burnaby, BC, Canada | P32: Kaur, Manpreet, School of Mechatronic Systems Engineering, Simon Fraser University, Burnaby, BC, Canada; Kim, Tae Ho, School of Mechatronic Systems Engineering, Simon Fraser University, Burnaby, BC, Canada; Kim, Woo Soo, School of Mechatronic Systems Engineering, Simon Fraser University, Burnaby, BC, Canada | Q32: W.S. Kim; Additive Manufacturing Laboratory, School of Mechatronics System Engineering, Simon Fraser University, Surrey, V3T 0A3, Canada; email: woosook@sfu.ca | S32: John Wiley and Sons Inc | T32: 9359648 | V32: ADVME | W32: 33458908 | X32: English | Y32: Adv Mater | Z32: Article | AA32: Final | AC32: Scopus | AD32: 2-s2.0-85100159592
A33: Alzaid, M.; Iqbal, M.Z.; Alam, S.; Almoisheer, N.; Afzal, A.M.; Aftab, S. | B33: Alzaid, Meshal M. (57193761447); Iqbal, Muhammad Zahir (59594047700); Alam, Shahid (57213490911); Almoisheer, Noha (57205387043); Afzal, Amir Muhammad (57200106539); Aftab, Sikandar (57200114034) | C33: 57193761447; 59594047700; 57213490911; 57205387043; 57200106539; 57200114034 | D33: Binary composites of nickel-manganese phosphates for supercapattery devices | E33: 2021 | F33: Journal of Energy Storage | G33: 33 | I33: 102020 | L33: 52 | M33: 10.1016/j.est.2020.102020 | N33: https://www.scopus.com/inward/record.uri?eid=2-s2.0-85097040257&doi=10.1016%2Fj.est.2020.102020&partnerID=40&md5=79d0a0306c288a45af9944cb78fe5474 | O33: Physics Department College of Science, Jouf University, Sakakah, Al Jawf, Saudi Arabia; Nanotechnology Research Laboratory, Ghulam Ishaq Khan Institute of Engineering Sciences and Technology, Topi, Khyber Pakhtunkhwa, Pakistan; Department of Electrical and Biological Physics, Kwangwoon University, Seoul, South Korea; Department of Engineering, Simon Fraser University, Burnaby, BC, Canada | P33: Alzaid, Meshal M., Physics Department College of Science, Jouf University, Sakakah, Al Jawf, Saudi Arabia; Iqbal, Muhammad Zahir, Nanotechnology Research Laboratory, Ghulam Ishaq Khan Institute of Engineering Sciences and Technology, Topi, Khyber Pakhtunkhwa, Pakistan; Alam, Shahid, Nanotechnology Research Laboratory, Ghulam Ishaq Khan Institute of Engineering Sciences and Technology, Topi, Khyber Pakhtunkhwa, Pakistan; Almoisheer, Noha, Physics Department College of Science, Jouf University, Sakakah, Al Jawf, Saudi Arabia; Afzal, Amir Muhammad, Department of Electrical and Biological Physics, Kwangwoon University, Seoul, South Korea; Aftab, Sikandar, Department of Engineering, Simon Fraser University, Burnaby, BC, Canada | Q33: M. Alzaid; Physics Department College of Science, Jouf University, Al Jouf, P.O. Box 2014, Saudi Arabia; email: mmalzaid@ju.edu.sa | S33: Elsevier Ltd | X33: English | Y33: J. Energy Storage | Z33: Article | AA33: Final | AC33: Scopus | AD33: 2-s2.0-85097040257
A34: Kabir, F.; Manir, S.; Bhuiyan, M.M.H.; Aftab, S.; Ghanbari, H.; Hasani, A.; Fawzy, M.; de Silva, G.L.T.; Mohammadzadeh, M.R.; Ahmadi, R.; Abnavi, A.; Askar, A.; Adachi, M.M. | B34: Kabir, Fahmid (57204906651); Manir, Serajum (57575354600); Bhuiyan, M. M.H. (35839789200); Aftab, Sikandar (57200114034); Ghanbari, Hamidreza (57576416100); Hasani, Amirhossein (56501775400); Fawzy, Mirette (57223906642); de Silva, G. L.Thushani (57575566400); Mohammadzadeh, Mohammad Reza (60202275600); Ahmadi, Ribwar (57278170200); Abnavi, Amin (57194502466); Askar, Abdelrahman M. (56699722300); Adachi, Michael M. (16432591400) | C34: 57204906651; 57575354600; 35839789200; 57200114034; 57576416100; 56501775400; 57223906642; 57575566400; 60202275600; 57278170200; 57194502466; 56699722300; 16432591400 | D34: Instability of dye-sensitized solar cells using natural dyes and approaches to improving stability – An overview | E34: 2022 | F34: Sustainable Energy Technologies and Assessments | G34: 52 | I34: 102196 | L34: 51 | M34: 10.1016/j.seta.2022.102196 | N34: https://www.scopus.com/inward/record.uri?eid=2-s2.0-85128240243&doi=10.1016%2Fj.seta.2022.102196&partnerID=40&md5=5b7b51de12b65a0a2438fb7c1eb0b636 | O34: School of Engineering Science, Simon Fraser University, Burnaby, BC, Canada; Institute of Radiation and Polymer Technology, Atomic Energy Research Establishment, Dhaka, Dhaka, Bangladesh; Institute of Nuclear Science and Technology, Atomic Energy Research Establishment, Dhaka, Bangladesh; Department of Intelligent Mechatronics Engineering, Sejong University, Seoul, South Korea; Department of Physics, Simon Fraser University, Burnaby, BC, Canada | P34: Kabir, Fahmid, School of Engineering Science, Simon Fraser University, Burnaby, BC, Canada; Manir, Serajum, Institute of Radiation and Polymer Technology, Atomic Energy Research Establishment, Dhaka, Dhaka, Bangladesh; Bhuiyan, M. M.H., Institute of Nuclear Science and Technology, Atomic Energy Research Establishment, Dhaka, Bangladesh; Aftab, Sikandar, School of Engineering Science, Simon Fraser University, Burnaby, BC, Canada, Department of Intelligent Mechatronics Engineering, Sejong University, Seoul, South Korea; Ghanbari, Hamidreza, School of Engineering Science, Simon Fraser University, Burnaby, BC, Canada; Hasani, Amirhossein, School of Engineering Science, Simon Fraser University, Burnaby, BC, Canada; Fawzy, Mirette, Department of Physics, Simon Fraser University, Burnaby, BC, Canada; de Silva, G. L.Thushani, School of Engineering Science, Simon Fraser University, Burnaby, BC, Canada; Mohammadzadeh, Mohammad Reza, School of Engineering Science, Simon Fraser University, Burnaby, BC, Canada; Ahmadi, Ribwar, School of Engineering Science, Simon Fraser University, Burnaby, BC, Canada; Abnavi, Amin, School of Engineering Science, Simon Fraser University, Burnaby, BC, Canada; Askar, Abdelrahman M., School of Engineering Science, Simon Fraser University, Burnaby, BC, Canada; Adachi, Michael M., School of Engineering Science, Simon Fraser University, Burnaby, BC, Canada | Q34: F. Kabir; School of Engineering Science, Simon Fraser University, Canada; email: fahmid.kabir07@gmail.com | S34: Elsevier Ltd | T34: 22131388 | X34: English | Y34: Sustainable Energy Technol. Assess. | Z34: Review | AA34: Final | AC34: Scopus | AD34: 2-s2.0-85128240243
A35: Aftab, S.; Li, X.; Kabir, F.; Akman, E.; Aslam, M.; Pallavolu, M.R.; Ganesh, G.; Assiri, M.A.; Rajpar, A.H. | B35: Aftab, Sikandar (57200114034); Li, Xin (56098157600); Kabir, Fahmid (57204906651); Akman, Erdi (56304768400); Aslam, Muhammad Zeeshan (59800219300); Pallavolu, Mohan Reddy (57201352403); Ganesh, Koyyada (55843979000); Assiri, Mohammed Ail (57195309416); Rajpar, A. H. (16550858500) | C35: 57200114034; 56098157600; 57204906651; 56304768400; 59800219300; 57201352403; 55843979000; 57195309416; 16550858500 | D35: Lighting the future: Perovskite nanorods and their advances across applications | E35: 2024 | F35: Nano Energy | G35: 124 | I35: 109504 | L35: 47 | M35: 10.1016/j.nanoen.2024.109504 | N35: https://www.scopus.com/inward/record.uri?eid=2-s2.0-85189500418&doi=10.1016%2Fj.nanoen.2024.109504&partnerID=40&md5=70116e7c703021a39e4e42076db851da | O35: Department of Semiconductor Systems Engineering, Sejong University, Seoul, South Korea; Department of Artificial Intelligence, Sejong University, Seoul, South Korea; National University of Defense Technology China, Changsha, Hunan, China; Advanced Laser Technology Laboratory of Anhui Province, Hefei, Anhui, China; School of Engineering Sciences, Simon Fraser University, Burnaby, BC, Canada; Scientific and Technological Research & Application Center, Karamanoğlu Mehmetbey Üniversitesi, Karaman, Karaman, Turkey; Institute of Physics and Technology, Yekaterinburg, Sverdlovskaya, Russian Federation; School of Chemical Engineering, Yeungnam University, Gyeongsan, Gyeongsangbuk-do, South Korea; Department of Chemistry, K L Deemed to be University, Vaddeswaram, AP, India; Department of Chemistry, King Khalid University, Abha, Asir, Saudi Arabia; Department of Mechanical Engineering, Jouf University, Sakakah, Al Jawf, Saudi Arabia | P35: Aftab, Sikandar, Department of Semiconductor Systems Engineering, Sejong University, Seoul, South Korea, Department of Artificial Intelligence, Sejong University, Seoul, South Korea; Li, Xin, National University of Defense Technology China, Changsha, Hunan, China, Advanced Laser Technology Laboratory of Anhui Province, Hefei, Anhui, China; Kabir, Fahmid, School of Engineering Sciences, Simon Fraser University, Burnaby, BC, Canada; Akman, Erdi, Scientific and Technological Research & Application Center, Karamanoğlu Mehmetbey Üniversitesi, Karaman, Karaman, Turkey; Aslam, Muhammad Zeeshan, Institute of Physics and Technology, Yekaterinburg, Sverdlovskaya, Russian Federation; Pallavolu, Mohan Reddy, School of Chemical Engineering, Yeungnam University, Gyeongsan, Gyeongsangbuk-do, South Korea; Ganesh, Koyyada, School of Chemical Engineering, Yeungnam University, Gyeongsan, Gyeongsangbuk-do, South Korea, Department of Chemistry, K L Deemed to be University, Vaddeswaram, AP, India; Assiri, Mohammed Ail, Department of Chemistry, King Khalid University, Abha, Asir, Saudi Arabia; Rajpar, A. H., Department of Mechanical Engineering, Jouf University, Sakakah, Al Jawf, Saudi Arabia | Q35: S. Aftab; Department of Semiconductor Systems Engineering and Clean Energy, Sejong University, Seoul, 05006, South Korea; email: physics.sikandar@gmail.com; X. Li; State Key Laboratory of Pulsed Power Laser Technology, National University of Defense Technology, Hefei, Anhui, 230037, China; email: lixinkiller@nudt.edu.cn; M.R. Pallavolu; School of Chemical Engineering, Yeungnam University, Gyeongsan, 38541, South Korea; email: pmreddy@yu.ac.kr; G. Koyyada; School of Chemical Engineering, Yeungnam University, Gyeongsan, 38541, South Korea; email: ganeshkoyyada@gmail.com | S35: Elsevier Ltd | T35: 22112855 | X35: English | Y35: Nano Energy | Z35: Review | AA35: Final | AB35: All Open Access; Green Accepted Open Access; Green Open Access | AC35: Scopus | AD35: 2-s2.0-85189500418
A36: Veh, P.; Britton, B.; Holdcroft, S.; Zengerle, R.; Vierrath, S.; Breitwieser, M. | B36: Veh, Philipp (57215563295); Britton, Ben (57202916499); Holdcroft, Steven J. (7004469945); Zengerle, Roland (7006742524); Vierrath, Severin (56572897000); Breitwieser, Matthias (55910257900) | C36: 57215563295; 57202916499; 7004469945; 7006742524; 56572897000; 55910257900 | D36: Improving the water management in anion-exchange membrane fuel cells: via ultra-thin, directly deposited solid polymer electrolyte | E36: 2020 | F36: RSC Advances | G36: 10 | H36: 15 | J36: 8645 | K36: 8652 | L36: 45 | M36: 10.1039/c9ra09628k | N36: https://www.scopus.com/inward/record.uri?eid=2-s2.0-85081173407&doi=10.1039%2Fc9ra09628k&partnerID=40&md5=b790937ddd8c4bb36283de591f91808c | O36: Electrochemical Energy Systems, Universität Freiburg, Freiburg im Breisgau, Baden-Wurttemberg, Germany; Department of Chemistry, Simon Fraser University, Burnaby, BC, Canada; Hahn-Schickard, Freiburg im Breisgau, D-79110, Germany; Universität Freiburg, Freiburg im Breisgau, Baden-Wurttemberg, Germany | P36: Veh, Philipp, Electrochemical Energy Systems, Universität Freiburg, Freiburg im Breisgau, Baden-Wurttemberg, Germany; Britton, Ben, Department of Chemistry, Simon Fraser University, Burnaby, BC, Canada; Holdcroft, Steven J., Department of Chemistry, Simon Fraser University, Burnaby, BC, Canada; Zengerle, Roland, Electrochemical Energy Systems, Universität Freiburg, Freiburg im Breisgau, Baden-Wurttemberg, Germany, Hahn-Schickard, Freiburg im Breisgau, D-79110, Germany; Vierrath, Severin, Electrochemical Energy Systems, Universität Freiburg, Freiburg im Breisgau, Baden-Wurttemberg, Germany, Hahn-Schickard, Freiburg im Breisgau, D-79110, Germany, Universität Freiburg, Freiburg im Breisgau, Baden-Wurttemberg, Germany; Breitwieser, Matthias, Electrochemical Energy Systems, Universität Freiburg, Freiburg im Breisgau, Baden-Wurttemberg, Germany, Hahn-Schickard, Freiburg im Breisgau, D-79110, Germany | S36: Royal Society of Chemistry | V36: RSCAC | X36: English | Y36: RSC Adv. | Z36: Article | AA36: Final | AB36: All Open Access; Gold Open Access; Green Final Open Access; Green Open Access | AC36: Scopus | AD36: 2-s2.0-85081173407
A37: Hira, A.; Pacini, H.; Attafuah-Wadee, K.; Vivas-Eugui, D.; Saltzberg, M.; Yeoh, T.N. | B37: Hira, Anil (6602185359); Pacini, Henrique (36548985000); Attafuah-Wadee, Kweku (57782258800); Vivas-Eugui, David (55824606000); Saltzberg, Michael A. (6603999244); Yeoh, Tze Ni (57806874700) | C37: 6602185359; 36548985000; 57782258800; 55824606000; 6603999244; 57806874700 | D37: Plastic Waste Mitigation Strategies: A Review of Lessons from Developing Countries | E37: 2022 | F37: Journal of Developing Societies | G37: 38 | H37: 3 | J37: 336 | K37: 359 | L37: 44 | M37: 10.1177/0169796X221104855 | N37: https://www.scopus.com/inward/record.uri?eid=2-s2.0-85134353842&doi=10.1177%2F0169796X221104855&partnerID=40&md5=3d22570830c5a961b83b2acb526a62cc | O37: Simon Fraser University, Burnaby, BC, Canada; United Nations Conference on Trade and Development, Geneva, GE, Switzerland; Resources Transformation Ghana, Ghana; DuPont, Wilmington, DE, United States; Circular Economy Alliance, Australia | P37: Hira, Anil, Simon Fraser University, Burnaby, BC, Canada; Pacini, Henrique, United Nations Conference on Trade and Development, Geneva, GE, Switzerland; Attafuah-Wadee, Kweku, Resources Transformation Ghana, Ghana; Vivas-Eugui, David, United Nations Conference on Trade and Development, Geneva, GE, Switzerland; Saltzberg, Michael A., DuPont, Wilmington, DE, United States; Yeoh, Tze Ni, Circular Economy Alliance, Australia | Q37: A. Hira; Simon Fraser University, Canada; email: anil_hira@sfu.ca | S37: SAGE Publications Ltd | T37: 0169796X | X37: English | Y37: J. Dev. Soc. | Z37: Article | AA37: Final | AB37: All Open Access; Hybrid Gold Open Access | AC37: Scopus | AD37: 2-s2.0-85134353842
A38: Lee, S.; van Santen, J.A.; Farzaneh, N.; Liu, D.Y.; Pye, C.R.; Baumeister, T.U.H.; Wong, W.R.; Linington, R.G. | B38: Lee, Sanghoon (57212311772); van Santen, Jeffrey A. (56699718200); Farzaneh, Nima (57442070700); Liu, Dennis Y. (57203150185); Pye, Cameron R. (56441192900); Baumeister, Tim U.H. (57200964945); Wong, Weng Ruh (55204702700); Linington, Roger G. (6508105568) | C38: 57212311772; 56699718200; 57442070700; 57203150185; 56441192900; 57200964945; 55204702700; 6508105568 | D38: NP Analyst: An Open Online Platform for Compound Activity Mapping | E38: 2022 | F38: ACS Central Science | G38: 8 | H38: 2 | J38: 223 | K38: 234 | L38: 44 | M38: 10.1021/acscentsci.1c01108 | N38: https://www.scopus.com/inward/record.uri?eid=2-s2.0-85124140185&doi=10.1021%2Facscentsci.1c01108&partnerID=40&md5=147156a26617aefef382c53e6fc45577 | O38: Simon Fraser University, Burnaby, BC, Canada; Unnatural Products, Santa Cruz, CA, United States; Department of Chemistry and Biochemistry, University of California, Santa Cruz, Santa Cruz, CA, United States | P38: Lee, Sanghoon, Simon Fraser University, Burnaby, BC, Canada; van Santen, Jeffrey A., Simon Fraser University, Burnaby, BC, Canada; Farzaneh, Nima, Simon Fraser University, Burnaby, BC, Canada; Liu, Dennis Y., Simon Fraser University, Burnaby, BC, Canada; Pye, Cameron R., Unnatural Products, Santa Cruz, CA, United States; Baumeister, Tim U.H., Simon Fraser University, Burnaby, BC, Canada; Wong, Weng Ruh, Department of Chemistry and Biochemistry, University of California, Santa Cruz, Santa Cruz, CA, United States; Linington, Roger G., Simon Fraser University, Burnaby, BC, Canada | Q38: R.G. Linington; Department of Chemistry, Simon Fraser University, Burnaby, 8888 University Drive, V5A 1S6, Canada; email: rliningt@sfu.ca | S38: American Chemical Society | T38: 23747943 | V38: ACSCI | X38: English | Y38: ACS Cent. Sci. | Z38: Article | AA38: Final | AB38: All Open Access; Gold Open Access; Green Accepted Open Access; Green Open Access | AC38: Scopus | AD38: 2-s2.0-85124140185
A39: Zou, S.; Zuo, X.; Qian, Y.; Wang, S.; Xu, C.; Gong, M.; Cheng, L. | B39: Zou, Shihao (57211756484); Zuo, Xinxin (56599836200); Qian, Yiming (56547882400); Wang, Sen (56436950500); Xu, Chi (57219131928); Gong, Minglun (7201566763); Cheng, Li (56428060700) | C39: 57211756484; 56599836200; 56547882400; 56436950500; 57219131928; 7201566763; 56428060700 | D39: 3D Human Shape Reconstruction from a Polarization Image | E39: 2020 | F39: Lecture Notes in Computer Science (including subseries Lecture Notes in Artificial Intelligence and Lecture Notes in Bioinformatics) | G39: 12359 LNCS | J39: 351 | K39: 368 | L39: 44 | M39: 10.1007/978-3-030-58568-6_21 | N39: https://www.scopus.com/inward/record.uri?eid=2-s2.0-85097082605&doi=10.1007%2F978-3-030-58568-6_21&partnerID=40&md5=a3a149e2ae7a57cc184be10deaa1989d | O39: University of Alberta, Edmonton, AB, Canada; Simon Fraser University, Burnaby, BC, Canada; School of Automation, China University of Geosciences, Wuhan, Hubei, China; University of Guelph, Guelph, ON, Canada | P39: Zou, Shihao, University of Alberta, Edmonton, AB, Canada; Zuo, Xinxin, University of Alberta, Edmonton, AB, Canada; Qian, Yiming, Simon Fraser University, Burnaby, BC, Canada; Wang, Sen, University of Alberta, Edmonton, AB, Canada; Xu, Chi, School of Automation, China University of Geosciences, Wuhan, Hubei, China; Gong, Minglun, University of Guelph, Guelph, ON, Canada; Cheng, Li, University of Alberta, Edmonton, AB, Canada | Q39: S. Zou; University of Alberta, Edmonton, Canada; email: szou2@ualberta.ca | R39: Vedaldi, A.; Bischof, H.; Brox, T.; Frahm, J. | S39: Springer Science and Business Media Deutschland GmbH | T39: 3029743 | U39: 9789819698936; 9789819698042; 9789819698110; 9789819698905; 9783032004949; 9789819512324; 9783032026019; 9783032008909; 9783031915802; 9789819698141 | X39: English | Y39: Lect. Notes Comput. Sci. | Z39: Conference paper | AA39: Final | AC39: Scopus | AD39: 2-s2.0-85097082605
A40: Aftab, S.; Ganesh, G.; Mukhtar, M.; Kabir, F.; Nazir, G.; Memon, S.A.; Aslam, M.; Assiri, M.A.; Kim, J.H. | B40: Aftab, Sikandar (57200114034); Ganesh, Koyyada (55843979000); Mukhtar, Maria (57216159606); Kabir, Fahmid (57204906651); Nazir, Ghazanfar (56769819400); Memon, Sufyan Ali (57132317100); Aslam, Muhammad Zeeshan (59800219300); Assiri, Mohammed Ail (57195309416); Kim, Jae-hong (57210416369) | C40: 57200114034; 55843979000; 57216159606; 57204906651; 56769819400; 57132317100; 59800219300; 57195309416; 57210416369 | D40: Laser-Induced Graphene for Advanced Sensing: Comprehensive Review of Applications | E40: 2024 | F40: ACS Sensors | G40: 9 | H40: 9 | J40: 4536 | K40: 4554 | L40: 43 | M40: 10.1021/acssensors.4c01717 | N40: https://www.scopus.com/inward/record.uri?eid=2-s2.0-85205075733&doi=10.1021%2Facssensors.4c01717&partnerID=40&md5=b55b264a422d25284a770f5afe9e5747 | O40: Department of Semiconductor Systems Engineering, Sejong University, Seoul, South Korea; Department of Artificial Intelligence, Sejong University, Seoul, South Korea; School of Chemical Engineering, Yeungnam University, Gyeongsan, Gyeongsangbuk-do, South Korea; School of Engineering Science, Simon Fraser University, Burnaby, BC, Canada; Department of Nanotechnology and Advanced Materials Engineering, Sejong University, Seoul, South Korea; Sejong University, Seoul, South Korea; Institute of Physics and Technology, Yekaterinburg, Sverdlovskaya, Russian Federation; Department of Chemistry, King Khalid University, Abha, Asir, Saudi Arabia; Department of Chemistry, SR University, Warangal, TS, India | P40: Aftab, Sikandar, Department of Semiconductor Systems Engineering, Sejong University, Seoul, South Korea, Department of Artificial Intelligence, Sejong University, Seoul, South Korea; Ganesh, Koyyada, School of Chemical Engineering, Yeungnam University, Gyeongsan, Gyeongsangbuk-do, South Korea, Department of Chemistry, SR University, Warangal, TS, India; Mukhtar, Maria, Department of Semiconductor Systems Engineering, Sejong University, Seoul, South Korea, Department of Artificial Intelligence, Sejong University, Seoul, South Korea; Kabir, Fahmid, School of Engineering Science, Simon Fraser University, Burnaby, BC, Canada; Nazir, Ghazanfar, Department of Nanotechnology and Advanced Materials Engineering, Sejong University, Seoul, South Korea; Memon, Sufyan Ali, Sejong University, Seoul, South Korea; Aslam, Muhammad Zeeshan, Institute of Physics and Technology, Yekaterinburg, Sverdlovskaya, Russian Federation; Assiri, Mohammed Ail, Department of Chemistry, King Khalid University, Abha, Asir, Saudi Arabia; Kim, Jae-hong, School of Chemical Engineering, Yeungnam University, Gyeongsan, Gyeongsangbuk-do, South Korea | Q40: S. Aftab; Department of Semiconductor Systems Engineering and Clean Energy, Sejong University, Seoul, 05006, South Korea; email: aftab@sejong.ac.kr; J.H. Kim; School of Chemical Engineering, Yeungnam University, Gyeongsan, 38541, South Korea; email: jaehkim@ynu.ac.kr | S40: American Chemical Society | W40: 39284075 | X40: English | Y40: ACS Sensors | Z40: Review | AA40: Final | AC40: Scopus | AD40: 2-s2.0-85205075733
A41: Gilbert, W.; Tanttu, T.; Lim, W.H.; Feng, M.K.; Huang, J.Y.; Cifuentes, J.D.; Serrano, S.; Mai, P.Y.; Leon, R.C.C.; Escott, C.C.; Itoh, K.M.; Abrosimov, N.V.; Pohl, H.-J.; Thewalt, M.L.W.; Hudson, F.E.; Morello, A.; Laucht, A.; Yang, C.H.; Saraiva, A.; Dzurak, A.S. | B41: Gilbert, Will (57212149896); Tanttu, Tuomo (55446775700); Lim, Weehan (26637045100); Feng, Mengke (57217336415); Huang, Jonathan Yue (57219790228); Cifuentes, Jesús D. (57226893320); Serrano, Santiago (57425351400); Mai, Philip Y. (57425640300); Leon, Ross C.C. (56405191800); Escott, Christopher C. (6504198132); Itoh, Kohei M. (59944295500); Abrosimov, Nikolay V. (7006393260); Pohl, Hans Joachim (7102592505); Thewalt, Michael L.W. (7006609975); Hudson, Fay E. (8625632100); Morello, Andrea (7005087193); Laucht, Arne (18536478200); Yang, C. H. (57208200900); Saraiva, Andre L. (8598462500); Dzurak, Andrew S. (7004650676) | C41: 57212149896; 55446775700; 26637045100; 57217336415; 57219790228; 57226893320; 57425351400; 57425640300; 56405191800; 6504198132; 59944295500; 7006393260; 7102592505; 7006609975; 8625632100; 7005087193; 18536478200; 57208200900; 8598462500; 7004650676 | D41: On-demand electrical control of spin qubits | E41: 2023 | F41: Nature Nanotechnology | G41: 18 | H41: 2 | J41: 131 | K41: 136 | L41: 41 | M41: 10.1038/s41565-022-01280-4 | N41: https://www.scopus.com/inward/record.uri?eid=2-s2.0-85146168792&doi=10.1038%2Fs41565-022-01280-4&partnerID=40&md5=ae3ea80070406b7f383f2ca6e451d10d | O41: University of New South Wales, School of Electrical Engineering and Telecommunications, Sydney, NSW, Australia; Diraq, Sydney, NSW, Australia; Keio University, Tokyo, Japan; Leibniz-Institut für Kristallzüchtung, Berlin, Germany; VITCON Projectconsult GmbH, Jena, Germany; Department of Physics, Simon Fraser University, Burnaby, BC, Canada | P41: Gilbert, Will, University of New South Wales, School of Electrical Engineering and Telecommunications, Sydney, NSW, Australia, Diraq, Sydney, NSW, Australia; Tanttu, Tuomo, University of New South Wales, School of Electrical Engineering and Telecommunications, Sydney, NSW, Australia, Diraq, Sydney, NSW, Australia; Lim, Weehan, University of New South Wales, School of Electrical Engineering and Telecommunications, Sydney, NSW, Australia, Diraq, Sydney, NSW, Australia; Feng, Mengke, University of New South Wales, School of Electrical Engineering and Telecommunications, Sydney, NSW, Australia; Huang, Jonathan Yue, University of New South Wales, School of Electrical Engineering and Telecommunications, Sydney, NSW, Australia; Cifuentes, Jesús D., University of New South Wales, School of Electrical Engineering and Telecommunications, Sydney, NSW, Australia; Serrano, Santiago, University of New South Wales, School of Electrical Engineering and Telecommunications, Sydney, NSW, Australia; Mai, Philip Y., University of New South Wales, School of Electrical Engineering and Telecommunications, Sydney, NSW, Australia; Leon, Ross C.C., University of New South Wales, School of Electrical Engineering and Telecommunications, Sydney, NSW, Australia; Escott, Christopher C., University of New South Wales, School of Electrical Engineering and Telecommunications, Sydney, NSW, Australia, Diraq, Sydney, NSW, Australia; Itoh, Kohei M., Keio University, Tokyo, Japan; Abrosimov, Nikolay V., Leibniz-Institut für Kristallzüchtung, Berlin, Germany; Pohl, Hans Joachim, VITCON Projectconsult GmbH, Jena, Germany; Thewalt, Michael L.W., Department of Physics, Simon Fraser University, Burnaby, BC, Canada; Hudson, Fay E., University of New South Wales, School of Electrical Engineering and Telecommunications, Sydney, NSW, Australia, Diraq, Sydney, NSW, Australia; Morello, Andrea, University of New South Wales, School of Electrical Engineering and Telecommunications, Sydney, NSW, Australia; Laucht, Arne, University of New South Wales, School of Electrical Engineering and Telecommunications, Sydney, NSW, Australia, Diraq, Sydney, NSW, Australia; Yang, C. H., University of New South Wales, School of Electrical Engineering and Telecommunications, Sydney, NSW, Australia, Diraq, Sydney, NSW, Australia; Saraiva, Andre L., University of New South Wales, School of Electrical Engineering and Telecommunications, Sydney, NSW, Australia, Diraq, Sydney, NSW, Australia; Dzurak, Andrew S., University of New South Wales, School of Electrical Engineering and Telecommunications, Sydney, NSW, Australia, Diraq, Sydney, NSW, Australia | Q41: W. Gilbert; School of Electrical Engineering and Telecommunications, The University of New South Wales, Sydney, Australia; email: w.gilbert@unsw.edu.au; A. Saraiva; School of Electrical Engineering and Telecommunications, The University of New South Wales, Sydney, Australia; email: a.saraiva@unsw.edu.au; A.S. Dzurak; School of Electrical Engineering and Telecommunications, The University of New South Wales, Sydney, Australia; email: a.dzurak@unsw.edu.au | S41: Nature Research | T41: 17483387 | W41: 36635331 | X41: English | Y41: Nat. Nanotechnol. | Z41: Article | AA41: Final | AC41: Scopus | AD41: 2-s2.0-85146168792
A42: Kim, T.-H.; Vanloo, J.; Kim, W.S. | B42: Kim, Tae Ho (56168759700); Vanloo, Jaydon (57221717207); Kim, Woo Soo (17136903100) | C42: 56168759700; 57221717207; 17136903100 | D42: 3D Origami Sensing Robots for Cooperative Healthcare Monitoring | E42: 2021 | F42: Advanced Materials Technologies | G42: 6 | H42: 3 | I42: 2000938 | L42: 41 | M42: 10.1002/admt.202000938 | N42: https://www.scopus.com/inward/record.uri?eid=2-s2.0-85099904146&doi=10.1002%2Fadmt.202000938&partnerID=40&md5=aac2b691467a2a3b17350d911c86f151 | O42: School of Mechatronic Systems Engineering, Simon Fraser University, Burnaby, BC, Canada | P42: Kim, Tae Ho, School of Mechatronic Systems Engineering, Simon Fraser University, Burnaby, BC, Canada; Vanloo, Jaydon, School of Mechatronic Systems Engineering, Simon Fraser University, Burnaby, BC, Canada; Kim, Woo Soo, School of Mechatronic Systems Engineering, Simon Fraser University, Burnaby, BC, Canada | Q42: W.S. Kim; School of Mechatronic Systems Engineering, Simon Fraser University, Surrey, V3T 0A3, Canada; email: woosook@sfu.ca | S42: John Wiley and Sons Inc | X42: English | Y42: Adv. Mater. Technol. | Z42: Article | AA42: Final | AC42: Scopus | AD42: 2-s2.0-85099904146
A43: Kim, T.-H.; Bao, C.; Chen, Z.; Kim, W.S. | B43: Kim, Tae Ho (56168759700); Bao, Chao (56612844400); Chen, Ziniu (57432972100); Kim, Woo Soo (17136903100) | C43: 56168759700; 56612844400; 57432972100; 17136903100 | D43: 3D printed leech-inspired origami dry electrodes for electrophysiology sensing robots | E43: 2022 | F43: npj Flexible Electronics | G43: 6 | H43: 1 | I43: 5 | L43: 39 | M43: 10.1038/s41528-022-00139-x | N43: https://www.scopus.com/inward/record.uri?eid=2-s2.0-85123795583&doi=10.1038%2Fs41528-022-00139-x&partnerID=40&md5=5380b28d043125b7d1dc4a938fb129ed | O43: School of Mechatronic Systems Engineering, Simon Fraser University, Burnaby, BC, Canada | P43: Kim, Tae Ho, School of Mechatronic Systems Engineering, Simon Fraser University, Burnaby, BC, Canada; Bao, Chao, School of Mechatronic Systems Engineering, Simon Fraser University, Burnaby, BC, Canada; Chen, Ziniu, School of Mechatronic Systems Engineering, Simon Fraser University, Burnaby, BC, Canada; Kim, Woo Soo, School of Mechatronic Systems Engineering, Simon Fraser University, Burnaby, BC, Canada | Q43: W.S. Kim; Additive Manufacturing Laboratory, School of Mechatronic Systems Engineering, Simon Fraser University, Surrey, Canada; email: woosook@sfu.ca | S43: Nature Research | X43: English | Y43: npj Flex. Electron. | Z43: Article | AA43: Final | AB43: All Open Access; Gold Open Access; Green Accepted Open Access; Green Open Access | AC43: Scopus | AD43: 2-s2.0-85123795583
A44: Dewapriya, M.A.N.; Rajapakse, R.K.N.D.; Dias, W.P.S. | B44: Dewapriya, M. A.N. (55837608800); Rajapakse, R. K.N.D. (57216149626); Dias, Priyan (7005009320) | C44: 55837608800; 57216149626; 7005009320 | D44: Characterizing fracture stress of defective graphene samples using shallow and deep artificial neural networks | E44: 2020 | F44: Carbon | G44: 163 | J44: 425 | K44: 440 | L44: 38 | M44: 10.1016/j.carbon.2020.03.038 | N44: https://www.scopus.com/inward/record.uri?eid=2-s2.0-85082671689&doi=10.1016%2Fj.carbon.2020.03.038&partnerID=40&md5=c2b1f6aa6897ba07da557f25302a0505 | O44: School of Engineering Science, Simon Fraser University, Burnaby, BC, Canada; Department of Civil Engineering, University of Moratuwa, Moratuwa, Sri Lanka; Sri Lanka Institute of Information Technology, Colombo, Sri Lanka | P44: Dewapriya, M. A.N., School of Engineering Science, Simon Fraser University, Burnaby, BC, Canada; Rajapakse, R. K.N.D., School of Engineering Science, Simon Fraser University, Burnaby, BC, Canada, Sri Lanka Institute of Information Technology, Colombo, Sri Lanka; Dias, Priyan, Department of Civil Engineering, University of Moratuwa, Moratuwa, Sri Lanka | Q44: M.A.N. Dewapriya; School of Engineering Science, Simon Fraser University, Burnaby, Canada; email: NuwanArachchige@cunet.carleton.ca | S44: Elsevier Ltd | T44: 86223 | V44: CRBNA | X44: English | Y44: Carbon | Z44: Article | AA44: Final | AC44: Scopus | AD44: 2-s2.0-85082671689
A45: Rezek, Z.; Holdaway, S.J.; Olszewski, D.I.; Lin, S.C.; Douglass, M.; McPherron, S.P.; Ioviţǎ, R.; Braun, D.R.; Sandgathe, D. | B45: Rezek, Zeljko (26647716500); Holdaway, Simon J. (6603091783); Olszewski, Deborah I. (26032261900); Lin, Sam C. (55579447400); Douglass, Matthew J. (24721411100); McPherron, Shannon Patrick P. (6506777264); Ioviţǎ, Radu P. (6506567945); Braun, David R. (23972180300); Sandgathe, Dennis M. (6506827825) | C45: 26647716500; 6603091783; 26032261900; 55579447400; 24721411100; 6506777264; 6506567945; 23972180300; 6506827825 | D45: Aggregates, Formational Emergence, and the Focus on Practice in Stone Artifact Archaeology | E45: 2020 | F45: Journal of Archaeological Method and Theory | G45: 27 | H45: 4 | J45: 887 | K45: 928 | L45: 37 | M45: 10.1007/s10816-020-09445-y | N45: https://www.scopus.com/inward/record.uri?eid=2-s2.0-85079147360&doi=10.1007%2Fs10816-020-09445-y&partnerID=40&md5=cbd7d18a587b5f968928b635cfe3352a | O45: Department of Human Evolution, Max-Planck-Institut für Evolutionäre Anthropologie, Leipzig, Sachsen, Germany; University of Pennsylvania, Philadelphia, PA, United States; School of Social Sciences, University of Auckland, Auckland, AUK, New Zealand; Department of Anthropology, University of Pennsylvania, Philadelphia, PA, United States; Faculty of Science, Medicine and Health, Wollongong, NSW, Australia; University of Wollongong, Wollongong, NSW, Australia; Department of Anthropology, University of Nebraska–Lincoln, Lincoln, NE, United States; Center for the Study of Human Origins, New York University, New York, NY, United States; Department of Early Prehistory and Quaternary Ecology, Eberhard Karls Universität Tübingen, Tubingen, Baden-Wurttemberg, Germany; Department of Anthropology, The George Washington University, Washington, D.C., United States; Archaeology Department, University of Cape Town, Cape Town, Western Cape, South Africa; Department of Anthropology, Simon Fraser University, Burnaby, BC, Canada | P45: Rezek, Zeljko, Department of Human Evolution, Max-Planck-Institut für Evolutionäre Anthropologie, Leipzig, Sachsen, Germany, University of Pennsylvania, Philadelphia, PA, United States; Holdaway, Simon J., School of Social Sciences, University of Auckland, Auckland, AUK, New Zealand; Olszewski, Deborah I., Department of Anthropology, University of Pennsylvania, Philadelphia, PA, United States; Lin, Sam C., Faculty of Science, Medicine and Health, Wollongong, NSW, Australia, University of Wollongong, Wollongong, NSW, Australia; Douglass, Matthew J., Department of Anthropology, University of Nebraska–Lincoln, Lincoln, NE, United States; McPherron, Shannon Patrick P., Department of Human Evolution, Max-Planck-Institut für Evolutionäre Anthropologie, Leipzig, Sachsen, Germany; Ioviţǎ, Radu P., Center for the Study of Human Origins, New York University, New York, NY, United States, Department of Early Prehistory and Quaternary Ecology, Eberhard Karls Universität Tübingen, Tubingen, Baden-Wurttemberg, Germany; Braun, David R., Department of Human Evolution, Max-Planck-Institut für Evolutionäre Anthropologie, Leipzig, Sachsen, Germany, Department of Anthropology, The George Washington University, Washington, D.C., United States, Archaeology Department, University of Cape Town, Cape Town, Western Cape, South Africa; Sandgathe, Dennis M., Department of Anthropology, Simon Fraser University, Burnaby, BC, Canada | Q45: Z. Rezek; Department of Human Evolution, Max Planck Institute for Evolutionary Anthropology, Leipzig, 04103, Germany; email: zeljko_rezek@eva.mpg.de | S45: Springer | T45: 10725369 | X45: English | Y45: J. Archaeol. Method and Theory | Z45: Article | AA45: Final | AB45: All Open Access; Green Accepted Open Access; Green Open Access; Hybrid Gold Open Access | AC45: Scopus | AD45: 2-s2.0-85079147360
A46: Karimi Mamaghan, M.; Mohammadi, M.; Jula, P.; Pirayesh, A.; Ahmadi, H. | B46: Karimi Mamaghan, Maryam (57203638620); Mohammadi, Mehrdad (55613229146); Jula, P. (6507477022); Pirayesh, Amir (57222311169); Ahmadi, Hadi (57197276444) | C46: 57203638620; 55613229146; 6507477022; 57222311169; 57197276444 | D46: A learning-based metaheuristic for a multi-objective agile inspection planning model under uncertainty | E46: 2020 | F46: European Journal of Operational Research | G46: 285 | H46: 2 | J46: 513 | K46: 537 | L46: 37 | M46: 10.1016/j.ejor.2020.01.061 | N46: https://www.scopus.com/inward/record.uri?eid=2-s2.0-85080942007&doi=10.1016%2Fj.ejor.2020.01.061&partnerID=40&md5=05903e5478e4cb8938fae94eb2a4c0d9 | O46: UBL, Laboratoire des Sciences et Techniques de l'Information, de la Communication et de la Connaissance (Lab-Sticc), Brest, Brittany, France; Beedie School of Business, Burnaby, BC, Canada; The Centre of Excellence in Supply Chain (CESIT), KEDGE Business School, Talence, Nouvelle-Aquitaine, France; Islamic Azad University, South Tehran Branch, Tehran, Tehran Province, Iran | P46: Karimi Mamaghan, Maryam, UBL, Laboratoire des Sciences et Techniques de l'Information, de la Communication et de la Connaissance (Lab-Sticc), Brest, Brittany, France; Mohammadi, Mehrdad, UBL, Laboratoire des Sciences et Techniques de l'Information, de la Communication et de la Connaissance (Lab-Sticc), Brest, Brittany, France; Jula, P., Beedie School of Business, Burnaby, BC, Canada; Pirayesh, Amir, The Centre of Excellence in Supply Chain (CESIT), KEDGE Business School, Talence, Nouvelle-Aquitaine, France; Ahmadi, Hadi, Islamic Azad University, South Tehran Branch, Tehran, Tehran Province, Iran | Q46: M. Karimi-Mamaghan; IMT Atlantique, Lab-STICC, UBL, Brest, F-29238, France; email: maryam.karimi@imt-atlantique.fr | S46: Elsevier B.V. | T46: 3772217 | V46: EJORD | X46: English | Y46: Eur J Oper Res | Z46: Article | AA46: Final | AC46: Scopus | AD46: 2-s2.0-85080942007
A47: Wakeling, J.M.; Ross, S.A.; Ryan, D.S.; Bolsterlee, B.; Konno, R.N.; Domínguez-Rivera, S.A.; Nigam, N. | B47: Wakeling, James M. (7004442395); Ross, Stephanie A. (57193016869); Ryan, David S. (57203414190); Bolsterlee, Bart (54886484000); Konno, Ryan N. (57211986800); Domínguez-Rivera, Sebastián A. (56966316300); Nigam, Nilima A. (6701732470) | C47: 7004442395; 57193016869; 57203414190; 54886484000; 57211986800; 56966316300; 6701732470 | D47: The Energy of Muscle Contraction. I. Tissue Force and Deformation During Fixed-End Contractions | E47: 2020 | F47: Frontiers in Physiology | G47: 11 | I47: 813 | L47: 37 | M47: 10.3389/fphys.2020.00813 | N47: https://www.scopus.com/inward/record.uri?eid=2-s2.0-85090886938&doi=10.3389%2Ffphys.2020.00813&partnerID=40&md5=f184a2c44005b6a1f7a4ff16d3575926 | O47: Department of Biomedical Physiology and Kinesiology, Simon Fraser University, Burnaby, BC, Canada; Department of Mathematics, Simon Fraser University, Burnaby, BC, Canada; Neuroscience Research Australia, Sydney, NSW, Australia; Graduate School of Biomedical Engineering, UNSW Sydney, Sydney, NSW, Australia; Department of Physics and Astronomy, The University of British Columbia, Vancouver, BC, Canada | P47: Wakeling, James M., Department of Biomedical Physiology and Kinesiology, Simon Fraser University, Burnaby, BC, Canada, Department of Mathematics, Simon Fraser University, Burnaby, BC, Canada; Ross, Stephanie A., Department of Biomedical Physiology and Kinesiology, Simon Fraser University, Burnaby, BC, Canada; Ryan, David S., Department of Biomedical Physiology and Kinesiology, Simon Fraser University, Burnaby, BC, Canada; Bolsterlee, Bart, Neuroscience Research Australia, Sydney, NSW, Australia, Graduate School of Biomedical Engineering, UNSW Sydney, Sydney, NSW, Australia; Konno, Ryan N., Department of Physics and Astronomy, The University of British Columbia, Vancouver, BC, Canada; Domínguez-Rivera, Sebastián A., Department of Mathematics, Simon Fraser University, Burnaby, BC, Canada; Nigam, Nilima A., Department of Mathematics, Simon Fraser University, Burnaby, BC, Canada | Q47: J.M. Wakeling; Department of Biomedical Physiology and Kinesiology, Simon Fraser University, Burnaby, Canada; email: wakeling@sfu.ca; J.M. Wakeling; Department of Biomedical Physiology and Kinesiology, Simon Fraser University, Burnaby, Canada; email: wakeling@sfu.ca | S47: Frontiers Media S.A. info@frontiersin.org | X47: English | Y47: Front. Physiol. | Z47: Article | AA47: Final | AB47: All Open Access; Gold Open Access; Green Accepted Open Access; Green Open Access | AC47: Scopus | AD47: 2-s2.0-85090886938
A48: Iqbal, M.W.; Asghar, M.; Noor, N.A.; Ullah, H.; Zahid, T.; Aftab, S.; Mahmood, A. | B48: Iqbal, Muhammad Waqas (57210908320); Asghar, Mazia (57263047300); Noor, Naveed Ahmad (35812147900); Ullah, Hamid (57208601029); Zahid, Tausif (57190029688); Aftab, Sikandar (57200114034); Mahmood, Asif Khalid (57197949063) | C48: 57210908320; 57263047300; 35812147900; 57208601029; 57190029688; 57200114034; 57197949063 | D48: Analysis of ternary AlGaX2(X = As, Sb) compounds for optoelectronic and renewable energy devices using density functional theory | E48: 2021 | F48: Physica Scripta | G48: 96 | H48: 12 | I48: 125706 | L48: 36 | M48: 10.1088/1402-4896/ac2024 | N48: https://www.scopus.com/inward/record.uri?eid=2-s2.0-85115175504&doi=10.1088%2F1402-4896%2Fac2024&partnerID=40&md5=bb564ef6e38d53b014adab92dfa8843e | O48: Department of Physics, Riphah International University, Islamabad, Pakistan; Department of Electrical Engineering, Riphah International University, Islamabad, Pakistan; Department of Electrical Engineering, Simon Fraser University, Burnaby, BC, Canada; Department of Chemical Engineering, King Saud University, Riyadh, Riyad, Saudi Arabia | P48: Iqbal, Muhammad Waqas, Department of Physics, Riphah International University, Islamabad, Pakistan; Asghar, Mazia, Department of Physics, Riphah International University, Islamabad, Pakistan; Noor, Naveed Ahmad, Department of Physics, Riphah International University, Islamabad, Pakistan; Ullah, Hamid, Department of Physics, Riphah International University, Islamabad, Pakistan; Zahid, Tausif, Department of Electrical Engineering, Riphah International University, Islamabad, Pakistan; Aftab, Sikandar, Department of Electrical Engineering, Simon Fraser University, Burnaby, BC, Canada; Mahmood, Asif Khalid, Department of Chemical Engineering, King Saud University, Riyadh, Riyad, Saudi Arabia | Q48: N.A. Noor; Department of Physics, RIPHAH International University, Campus Lahore, Pakistan; email: naveedcssp@gmail.com | S48: IOP Publishing Ltd | T48: 318949 | V48: PHSTB | X48: English | Y48: Phys Scr | Z48: Article | AA48: Final | AC48: Scopus | AD48: 2-s2.0-85115175504
A49: Simpson, R. | B49: Simpson, Rylan (57193081269) | C49: 57193081269 | D49: Calling the Police: Dispatchers as Important Interpreters and Manufacturers of Calls for Service Data | E49: 2021 | F49: Policing (Oxford) | G49: 15 | H49: 2 | J49: 1537 | K49: 1545 | L49: 36 | M49: 10.1093/police/paaa040 | N49: https://www.scopus.com/inward/record.uri?eid=2-s2.0-85142660477&doi=10.1093%2Fpolice%2Fpaaa040&partnerID=40&md5=50b067a8c6d540981bffe275d0ddf298 | O49: School of Criminology, Simon Fraser University, Burnaby, BC, Canada | P49: Simpson, Rylan, School of Criminology, Simon Fraser University, Burnaby, BC, Canada | Q49: R. Simpson; School of Criminology, Simon Fraser University, Burnaby, V5A 1S6, Canada; email: rylan_simpson@sfu.ca | S49: Oxford University Press | T49: 17524512 | X49: English | Y49: Policing | Z49: Review | AA49: Final | AC49: Scopus | AD49: 2-s2.0-85142660477
A50: Aftab, S.; Abbas, A.; Iqbal, M.Z.; Hussain, S.; Kabir, F.; Akman, E.; Xu, F.; Hegazy, H.H. | B50: Aftab, Sikandar (57200114034); Abbas, Aumber (57210095246); Iqbal, Muhammad Zahir (59594047700); Hussain, Sajjad Z. (56435246200); Kabir, Fahmid (57204906651); Akman, Erdi (56304768400); Xu, Fan (57222171955); Hegazy, Hosameldin Helmy (6603894858) | C50: 57200114034; 57210095246; 59594047700; 56435246200; 57204906651; 56304768400; 57222171955; 6603894858 | D50: Recent advances in nanomaterials based biosensors | E50: 2023 | F50: TrAC - Trends in Analytical Chemistry | G50: 167 | I50: 117223 | L50: 35 | M50: 10.1016/j.trac.2023.117223 | N50: https://www.scopus.com/inward/record.uri?eid=2-s2.0-85168408007&doi=10.1016%2Fj.trac.2023.117223&partnerID=40&md5=18e7bc00766e095fc0a3d61f81d4915f | O50: Department of Intelligent Mechatronics Engineering, Sejong University, Seoul, South Korea; Songshan Lake Materials Laboratory, Dongguan, Guangdong, China; ZENTECH Research Laboratory, Ghulam Ishaq Khan Institute of Engineering Sciences and Technology, Topi, Khyber Pakhtunkhwa, Pakistan; Department of Nanotechnology and Advanced Materials Engineering, Sejong University, Seoul, South Korea; School of Engineering Science, Simon Fraser University, Burnaby, BC, Canada; Scientific and Technological Research & Application Center, Karamanoğlu Mehmetbey Üniversitesi, Karaman, Karaman, Turkey; Ltd., Shenzhen, Guangdong, China; Department of Physics, King Khalid University, Abha, Asir, Saudi Arabia; King Khalid University, Abha, Asir, Saudi Arabia | P50: Aftab, Sikandar, Department of Intelligent Mechatronics Engineering, Sejong University, Seoul, South Korea; Abbas, Aumber, Songshan Lake Materials Laboratory, Dongguan, Guangdong, China; Iqbal, Muhammad Zahir, ZENTECH Research Laboratory, Ghulam Ishaq Khan Institute of Engineering Sciences and Technology, Topi, Khyber Pakhtunkhwa, Pakistan; Hussain, Sajjad Z., Department of Nanotechnology and Advanced Materials Engineering, Sejong University, Seoul, South Korea; Kabir, Fahmid, School of Engineering Science, Simon Fraser University, Burnaby, BC, Canada; Akman, Erdi, Scientific and Technological Research & Application Center, Karamanoğlu Mehmetbey Üniversitesi, Karaman, Karaman, Turkey; Xu, Fan, Ltd., Shenzhen, Guangdong, China; Hegazy, Hosameldin Helmy, Department of Physics, King Khalid University, Abha, Asir, Saudi Arabia, King Khalid University, Abha, Asir, Saudi Arabia | Q50: S. Aftab; Department of Intelligent Mechatronics Engineering, Sejong University, Seoul, 05006, South Korea; email: physics.sikandar@gmail.com | S50: Elsevier B.V. | T50: 1659936 | V50: TTAED | X50: English | Y50: TrAC Trends Anal. Chem. | Z50: Review | AA50: Final | AB50: All Open Access; Green Accepted Open Access; Green Open Access | AC50: Scopus | AD50: 2-s2.0-85168408007
A51: Baker, D.; Bao, C.; Kim, W.S. | B51: Baker, Daina V. (58754207900); Bao, Chao (56612844400); Kim, Woo Soo (17136903100) | C51: 58754207900; 56612844400; 17136903100 | D51: Highly Conductive 3D Printable Materials for 3D Structural Electronics | E51: 2021 | F51: ACS Applied Electronic Materials | G51: 3 | H51: 6 | J51: 2423 | K51: 2433 | L51: 35 | M51: 10.1021/acsaelm.1c00296 | N51: https://www.scopus.com/inward/record.uri?eid=2-s2.0-85110885683&doi=10.1021%2Facsaelm.1c00296&partnerID=40&md5=ce89e7c47d60552c6d3f427ea5a81c6c | O51: School of Sustainable Energy Engineering, Simon Fraser University, Burnaby, BC, Canada; School of Mechatronic Systems Engineering, Simon Fraser University, Burnaby, BC, Canada | P51: Baker, Daina V., School of Sustainable Energy Engineering, Simon Fraser University, Burnaby, BC, Canada; Bao, Chao, School of Mechatronic Systems Engineering, Simon Fraser University, Burnaby, BC, Canada; Kim, Woo Soo, School of Mechatronic Systems Engineering, Simon Fraser University, Burnaby, BC, Canada | Q51: W.S. Kim; School of Mechatronic Systems Engineering, Simon Fraser University, Surrey, V3T 0A3, Canada; email: woosook@sfu.ca | S51: American Chemical Society | X51: English | Y51: ACS Appl. Electron. Mater. | Z51: Review | AA51: Final | AC51: Scopus | AD51: 2-s2.0-85110885683
A52: Bamorovat Abadi, G.; Bahrami, M. | B52: Bamorovat Abadi, Gholamreza (56971470300); Bahrami, Majid M. (35499001600) | C52: 56971470300; 35499001600 | D52: The effect of surface roughness on capillary rise in micro-grooves | E52: 2022 | F52: Scientific Reports | G52: 12 | H52: 1 | I52: 14867 | L52: 34 | M52: 10.1038/s41598-022-19111-w | N52: https://www.scopus.com/inward/record.uri?eid=2-s2.0-85137105631&doi=10.1038%2Fs41598-022-19111-w&partnerID=40&md5=a29b19e373c928fba431a7738dd7e36c | O52: School of Mechatronic Systems Engineering, Simon Fraser University, Burnaby, BC, Canada | P52: Bamorovat Abadi, Gholamreza, School of Mechatronic Systems Engineering, Simon Fraser University, Burnaby, BC, Canada; Bahrami, Majid M., School of Mechatronic Systems Engineering, Simon Fraser University, Burnaby, BC, Canada | Q52: G. Bamorovat Abadi; Laboratory for Alternative Energy Conversion (LAEC), School of Mechatronic Systems Engineering, Simon Fraser University, Surrey, V3T 0A3, Canada; email: gbamorov@sfu.ca; M. Bahrami; Laboratory for Alternative Energy Conversion (LAEC), School of Mechatronic Systems Engineering, Simon Fraser University, Surrey, V3T 0A3, Canada; email: mbahrami@sfu.ca | S52: Nature Research | W52: 36050409 | X52: English | Y52: Sci. Rep. | Z52: Article | AA52: Final | AB52: All Open Access; Gold Open Access; Green Accepted Open Access; Green Open Access | AC52: Scopus | AD52: 2-s2.0-85137105631
A53: Aftab, S.; Shehzad, M.A.; Salman Ajmal, H.M.; Kabir, F.; Iqbal, M.Z.; Al-Kahtani, A.A. | B53: Aftab, Sikandar (57200114034); Shehzad, Muhammad Arslan (56199002300); Salman Ajmal, Hafiz Muhammad (57203278009); Kabir, Fahmid (57204906651); Iqbal, Muhammad Zahir (59594047700); Al-Kahtani, Abdullah A.S. (6602956099) | C53: 57200114034; 56199002300; 57203278009; 57204906651; 59594047700; 6602956099 | D53: Bulk Photovoltaic Effect in Two-Dimensional Distorted MoTe2 | E53: 2023 | F53: ACS Nano | G53: 17 | H53: 18 | J53: 17884 | K53: 17896 | L53: 33 | M53: 10.1021/acsnano.3c03593 | N53: https://www.scopus.com/inward/record.uri?eid=2-s2.0-85171730544&doi=10.1021%2Facsnano.3c03593&partnerID=40&md5=00a04ecd1725aa43bb6886c1fbb851c4 | O53: Department of Intelligent Mechatronics Engineering, Sejong University, Seoul, South Korea; Northwestern University, Evanston, IL, United States; Department of Biomedical Engineering, University of Engineering and Technology, Lahore, Lahore, Punjab, Pakistan; School of Engineering Science, Simon Fraser University, Burnaby, BC, Canada; Nanotechnology Research Laboratory, Ghulam Ishaq Khan Institute of Engineering Sciences and Technology, Topi, Khyber Pakhtunkhwa, Pakistan; Department of Chemistry, King Saud University, Riyadh, Riyad, Saudi Arabia | P53: Aftab, Sikandar, Department of Intelligent Mechatronics Engineering, Sejong University, Seoul, South Korea; Shehzad, Muhammad Arslan, Northwestern University, Evanston, IL, United States; Salman Ajmal, Hafiz Muhammad, Department of Biomedical Engineering, University of Engineering and Technology, Lahore, Lahore, Punjab, Pakistan; Kabir, Fahmid, School of Engineering Science, Simon Fraser University, Burnaby, BC, Canada; Iqbal, Muhammad Zahir, Nanotechnology Research Laboratory, Ghulam Ishaq Khan Institute of Engineering Sciences and Technology, Topi, Khyber Pakhtunkhwa, Pakistan; Al-Kahtani, Abdullah A.S., Department of Chemistry, King Saud University, Riyadh, Riyad, Saudi Arabia | Q53: S. Aftab; Department of Intelligent Mechatronics Engineering, Sejong University, Seoul, 05006, South Korea; email: aftab@sejong.ac.kr | S53: American Chemical Society | T53: 19360851 | W53: 37656985 | X53: English | Y53: ACS Nano | Z53: Article | AA53: Final | AC53: Scopus | AD53: 2-s2.0-85171730544
