Workbook

Sheet query3
A1: id | B1: doi | C1: title | D1: publication_year | E1: publication_date | F1: ids | G1: language | H1: type | I1: institutions | J1: countries_distinct_count | K1: institutions_distinct_count | L1: fwci | M1: cited_by_count | N1: citation_normalized_percentile | O1: cited_by_percentile_year | P1: biblio | Q1: sustainable_development_goals | R1: counts_by_year
A2: https://openalex.org/W3010336234 | B2: https://doi.org/10.1016/s0140-6736(20)30526-2 | C2: COVID-19: the gendered impacts of the outbreak | D2: 2020 | E2: 43891 | F2: {'openalex': 'https://openalex.org/W3010336234', 'doi': 'https://doi.org/10.1016/s0140-6736(20)30526-2', 'mag': '3010336234', 'pmid': 'https://pubmed.ncbi.nlm.nih.gov/32151325'} | G2: en | H2: article | I2: [] | J2: 3 | K2: 3 | L2: 332.2687 | M2: 1743 | N2: {'value': 1.0, 'is_in_top_1_percent': True, 'is_in_top_10_percent': True} | O2: {'min': 90, 'max': 100} | P2: {'volume': '395', 'issue': '10227', 'first_page': '846', 'last_page': '848'} | Q2: [{'score': 0.8100000023841858, 'id': 'https://metadata.un.org/sdg/3', 'display_name': 'Good health and well-being'}] | R2: [{'year': 2026, 'cited_by_count': 5}, {'year': 2025, 'cited_by_count': 44}, {'year': 2024, 'cited_by_count': 116}, {'year': 2023, 'cited_by_count': 209}, {'year': 2022, 'cited_by_count': 325}, {'year': 2021, 'cited_by_count': 532}, {'year': 2020, 'cited_by_count': 510}, {'year': 2019, 'cited_by_count': 1}]
A3: https://openalex.org/W4383913712 | B3: https://doi.org/10.1111/1748-8583.12524 | C3: Human resource management in the age of generative artificial intelligence: Perspectives and research directions on ChatGPT | D3: 2023 | E3: 45108 | F3: {'openalex': 'https://openalex.org/W4383913712', 'doi': 'https://doi.org/10.1111/1748-8583.12524'} | G3: en | H3: article | I3: [] | J3: 7 | K3: 23 | L3: 25.9729 | M3: 671 | N3: {'value': 0.99602829, 'is_in_top_1_percent': True, 'is_in_top_10_percent': True} | O3: {'min': 89, 'max': 100} | P3: {'volume': '33', 'issue': '3', 'first_page': '606', 'last_page': '659'} | Q3: [{'display_name': 'Decent work and economic growth', 'score': 0.7099999785423279, 'id': 'https://metadata.un.org/sdg/8'}] | R3: [{'year': 2026, 'cited_by_count': 36}, {'year': 2025, 'cited_by_count': 316}, {'year': 2024, 'cited_by_count': 252}, {'year': 2023, 'cited_by_count': 66}, {'year': 2020, 'cited_by_count': 1}]
A4: https://openalex.org/W3038709602 | B4: https://doi.org/10.1080/14494035.2020.1787628 | C4: Mobilizing Policy (In)Capacity to Fight COVID-19: Understanding Variations in State Responses | D4: 2020 | E4: 44014 | F4: {'openalex': 'https://openalex.org/W3038709602', 'doi': 'https://doi.org/10.1080/14494035.2020.1787628', 'mag': '3038709602', 'pmid': 'https://pubmed.ncbi.nlm.nih.gov/35039722'} | G4: en | H4: article | I4: [] | J4: 3 | K4: 5 | L4: 143.6959 | M4: 553 | N4: {'value': 0.99973491, 'is_in_top_1_percent': True, 'is_in_top_10_percent': True} | O4: {'min': 99, 'max': 100} | P4: {'volume': '39', 'issue': '3', 'first_page': '285', 'last_page': '308'} | Q4: [{'display_name': 'Good health and well-being', 'score': 0.75, 'id': 'https://metadata.un.org/sdg/3'}] | R4: [{'year': 2026, 'cited_by_count': 10}, {'year': 2025, 'cited_by_count': 59}, {'year': 2024, 'cited_by_count': 71}, {'year': 2023, 'cited_by_count': 103}, {'year': 2022, 'cited_by_count': 126}, {'year': 2021, 'cited_by_count': 148}, {'year': 2020, 'cited_by_count': 35}]
A5: https://openalex.org/W3021430513 | B5: https://doi.org/10.1017/s0008423920000396 | C5: How Right-Leaning Media Coverage of COVID-19 Facilitated the Spread of Misinformation in the Early Stages of the Pandemic in the U.S. | D5: 2020 | E5: 43952 | F5: {'openalex': 'https://openalex.org/W3021430513', 'doi': 'https://doi.org/10.1017/s0008423920000396', 'mag': '3021430513'} | G5: en | H5: article | I5: [] | J5: 2 | K5: 3 | L5: 116.8417 | M5: 441 | N5: {'value': 0.99959241, 'is_in_top_1_percent': True, 'is_in_top_10_percent': True} | O5: {'min': 99, 'max': 100} | P5: {'volume': '53', 'issue': '2', 'first_page': '335', 'last_page': '342'} | Q5: [{'id': 'https://metadata.un.org/sdg/3', 'display_name': 'Good health and well-being', 'score': 0.8199999928474426}] | R5: [{'year': 2026, 'cited_by_count': 3}, {'year': 2025, 'cited_by_count': 31}, {'year': 2024, 'cited_by_count': 72}, {'year': 2023, 'cited_by_count': 80}, {'year': 2022, 'cited_by_count': 114}, {'year': 2021, 'cited_by_count': 100}, {'year': 2020, 'cited_by_count': 41}]
A6: https://openalex.org/W3202368191 | B6: https://doi.org/10.1016/j.jclepro.2021.129099 | C6: Digital agricultural technologies for food loss and waste prevention and reduction: Global trends, adoption opportunities and barriers | D6: 2021 | E6: 44468 | F6: {'openalex': 'https://openalex.org/W3202368191', 'doi': 'https://doi.org/10.1016/j.jclepro.2021.129099', 'mag': '3202368191'} | G6: en | H6: article | I6: [] | J6: 1 | K6: 3 | L6: 21.2312 | M6: 203 | N6: {'value': 0.99773959, 'is_in_top_1_percent': True, 'is_in_top_10_percent': True} | O6: {'min': 89, 'max': 100} | P6: {'volume': '323', 'issue': None, 'first_page': '129099', 'last_page': '129099'} | Q6: [{'score': 0.7799999713897705, 'display_name': 'Zero hunger', 'id': 'https://metadata.un.org/sdg/2'}] | R6: [{'year': 2026, 'cited_by_count': 11}, {'year': 2025, 'cited_by_count': 56}, {'year': 2024, 'cited_by_count': 62}, {'year': 2023, 'cited_by_count': 41}, {'year': 2022, 'cited_by_count': 32}, {'year': 2021, 'cited_by_count': 1}]
A7: https://openalex.org/W4387643322 | B7: https://doi.org/10.1016/j.chbah.2023.100022 | C7: ChatGPT in education: Methods, potentials, and limitations | D7: 2023 | E7: 45139 | F7: {'openalex': 'https://openalex.org/W4387643322', 'doi': 'https://doi.org/10.1016/j.chbah.2023.100022'} | G7: en | H7: article | I7: [] | J7: 1 | K7: 2 | L7: 7.6368 | M7: 197 | N7: {'value': 0.97616972, 'is_in_top_1_percent': False, 'is_in_top_10_percent': True} | O7: {'min': 94, 'max': 100} | P7: {'volume': '1', 'issue': '2', 'first_page': '100022', 'last_page': '100022'} | Q7: [{'display_name': 'Quality Education', 'score': 0.7799999713897705, 'id': 'https://metadata.un.org/sdg/4'}] | R7: [{'year': 2026, 'cited_by_count': 14}, {'year': 2025, 'cited_by_count': 97}, {'year': 2024, 'cited_by_count': 84}, {'year': 2023, 'cited_by_count': 2}]
A8: https://openalex.org/W3130387723 | B8: https://doi.org/10.1177/2053168021993979 | C8: How populism and conservative media fuel conspiracy beliefs about COVID-19 and what it means for COVID-19 behaviors | D8: 2021 | E8: 44197 | F8: {'openalex': 'https://openalex.org/W3130387723', 'doi': 'https://doi.org/10.1177/2053168021993979', 'mag': '3130387723'} | G8: en | H8: article | I8: [] | J8: 2 | K8: 2 | L8: 54.4455 | M8: 175 | N8: {'value': 0.99911792, 'is_in_top_1_percent': True, 'is_in_top_10_percent': True} | O8: {'min': 99, 'max': 100} | P8: {'volume': '8', 'issue': '1', 'first_page': None, 'last_page': None} | Q8: [{'display_name': 'Good health and well-being', 'score': 0.7900000214576721, 'id': 'https://metadata.un.org/sdg/3'}] | R8: [{'year': 2026, 'cited_by_count': 5}, {'year': 2025, 'cited_by_count': 20}, {'year': 2024, 'cited_by_count': 32}, {'year': 2023, 'cited_by_count': 31}, {'year': 2022, 'cited_by_count': 61}, {'year': 2021, 'cited_by_count': 26}]
A9: https://openalex.org/W3135252207 | B9: https://doi.org/10.21203/rs.3.rs-311311/v1 | C9: Energy system analytics and good governance -U4RIA goals of Energy Modelling for Policy Support | D9: 2021 | E9: 44265 | F9: {'openalex': 'https://openalex.org/W3135252207', 'doi': 'https://doi.org/10.21203/rs.3.rs-311311/v1', 'mag': '3135252207'} | G9: en | H9: preprint | I9: [] | J9: 13 | K9: 36 | M9: 169 | P9: {'volume': None, 'issue': None, 'first_page': None, 'last_page': None} | Q9: [] | R9: [{'year': 2025, 'cited_by_count': 5}, {'year': 2024, 'cited_by_count': 24}, {'year': 2023, 'cited_by_count': 23}, {'year': 2022, 'cited_by_count': 12}, {'year': 2021, 'cited_by_count': 105}]
A10: https://openalex.org/W3112317149 | B10: https://doi.org/10.1093/biosci/biaa144 | C10: Indigenous Systems of Management for Culturally and Ecologically Resilient Pacific Salmon (<i>Oncorhynchus</i>spp.) Fisheries | D10: 2020 | E10: 44132 | F10: {'openalex': 'https://openalex.org/W3112317149', 'doi': 'https://doi.org/10.1093/biosci/biaa144', 'mag': '3112317149', 'pmid': 'https://pubmed.ncbi.nlm.nih.gov/33613129'} | G10: en | H10: article | I10: [] | J10: 3 | K10: 20 | L10: 17.4097 | M10: 156 | N10: {'value': 0.99638182, 'is_in_top_1_percent': True, 'is_in_top_10_percent': True} | O10: {'min': 99, 'max': 100} | P10: {'volume': '71', 'issue': '2', 'first_page': '186', 'last_page': '204'} | Q10: [] | R10: [{'year': 2026, 'cited_by_count': 10}, {'year': 2025, 'cited_by_count': 43}, {'year': 2024, 'cited_by_count': 27}, {'year': 2023, 'cited_by_count': 31}, {'year': 2022, 'cited_by_count': 32}, {'year': 2021, 'cited_by_count': 13}]
A11: https://openalex.org/W3024728740 | B11: https://doi.org/10.1016/s0140-6736(20)31032-1 | C11: Global coordination on cross-border travel and trade measures crucial to COVID-19 response | D11: 2020 | E11: 43952 | F11: {'openalex': 'https://openalex.org/W3024728740', 'doi': 'https://doi.org/10.1016/s0140-6736(20)31032-1', 'mag': '3024728740', 'pmid': 'https://pubmed.ncbi.nlm.nih.gov/32416788'} | G11: en | H11: article | I11: [] | J11: 4 | K11: 4 | L11: 42.2019 | M11: 135 | N11: {'value': 0.99770258, 'is_in_top_1_percent': True, 'is_in_top_10_percent': True} | O11: {'min': 98, 'max': 100} | P11: {'volume': '395', 'issue': '10237', 'first_page': '1593', 'last_page': '1595'} | Q11: [{'score': 0.5199999809265137, 'display_name': 'Good health and well-being', 'id': 'https://metadata.un.org/sdg/3'}] | R11: [{'year': 2025, 'cited_by_count': 5}, {'year': 2024, 'cited_by_count': 9}, {'year': 2023, 'cited_by_count': 40}, {'year': 2022, 'cited_by_count': 37}, {'year': 2021, 'cited_by_count': 27}, {'year': 2020, 'cited_by_count': 17}]
A12: https://openalex.org/W3033762036 | B12: https://doi.org/10.1016/j.marpol.2020.104039 | C12: Considering Indigenous Peoples and local communities in governance of the global ocean commons | D12: 2020 | E12: 43988 | F12: {'openalex': 'https://openalex.org/W3033762036', 'doi': 'https://doi.org/10.1016/j.marpol.2020.104039', 'mag': '3033762036'} | G12: en | H12: article | I12: [] | J12: 4 | K12: 11 | L12: 11.3656 | M12: 133 | N12: {'value': 0.99008262, 'is_in_top_1_percent': True, 'is_in_top_10_percent': True} | O12: {'min': 90, 'max': 100} | P12: {'volume': '119', 'issue': None, 'first_page': '104039', 'last_page': '104039'} | Q12: [{'id': 'https://metadata.un.org/sdg/14', 'display_name': 'Life below water', 'score': 0.44999998807907104}] | R12: [{'year': 2026, 'cited_by_count': 3}, {'year': 2025, 'cited_by_count': 17}, {'year': 2024, 'cited_by_count': 40}, {'year': 2023, 'cited_by_count': 26}, {'year': 2022, 'cited_by_count': 21}, {'year': 2021, 'cited_by_count': 21}, {'year': 2020, 'cited_by_count': 4}, {'year': 2019, 'cited_by_count': 1}]
A13: https://openalex.org/W3133990882 | B13: https://doi.org/10.1111/rego.12392 | C13: Assessing the regulatory challenges of emerging disruptive technologies | D13: 2021 | E13: 44259 | F13: {'openalex': 'https://openalex.org/W3133990882', 'doi': 'https://doi.org/10.1111/rego.12392', 'mag': '3133990882'} | G13: en | H13: article | I13: [] | J13: 2 | K13: 3 | L13: 23.1344 | M13: 124 | N13: {'value': 0.99549441, 'is_in_top_1_percent': True, 'is_in_top_10_percent': True} | O13: {'min': 89, 'max': 100} | P13: {'volume': '15', 'issue': '4', 'first_page': '1009', 'last_page': '1019'} | Q13: [{'score': 0.4699999988079071, 'display_name': 'Peace, Justice and strong institutions', 'id': 'https://metadata.un.org/sdg/16'}] | R13: [{'year': 2026, 'cited_by_count': 7}, {'year': 2025, 'cited_by_count': 32}, {'year': 2024, 'cited_by_count': 26}, {'year': 2023, 'cited_by_count': 32}, {'year': 2022, 'cited_by_count': 20}, {'year': 2021, 'cited_by_count': 6}, {'year': 2020, 'cited_by_count': 1}]
A14: https://openalex.org/W3024740263 | B14: https://doi.org/10.1017/s0008423920000463 | C14: Novel Coronavirus, Old Partisanship: COVID-19 Attitudes and Behaviours in the United States and Canada | D14: 2020 | E14: 43963 | F14: {'openalex': 'https://openalex.org/W3024740263', 'doi': 'https://doi.org/10.1017/s0008423920000463', 'mag': '3024740263'} | G14: en | H14: article | I14: [] | J14: 2 | K14: 3 | L14: 74.4061 | M14: 110 | N14: {'value': 0.99931782, 'is_in_top_1_percent': True, 'is_in_top_10_percent': True} | O14: {'min': 97, 'max': 100} | P14: {'volume': '53', 'issue': '2', 'first_page': '357', 'last_page': '364'} | Q14: [{'score': 0.8500000238418579, 'id': 'https://metadata.un.org/sdg/3', 'display_name': 'Good health and well-being'}] | R14: [{'year': 2026, 'cited_by_count': 1}, {'year': 2025, 'cited_by_count': 6}, {'year': 2024, 'cited_by_count': 14}, {'year': 2023, 'cited_by_count': 22}, {'year': 2022, 'cited_by_count': 19}, {'year': 2021, 'cited_by_count': 37}, {'year': 2020, 'cited_by_count': 11}]
A15: https://openalex.org/W3004603131 | B15: https://doi.org/10.1177/0308518x20904070 | C15: Banking on refugees: Racialized expropriation in the fintech era | D15: 2020 | E15: 43865 | F15: {'openalex': 'https://openalex.org/W3004603131', 'doi': 'https://doi.org/10.1177/0308518x20904070', 'mag': '3004603131'} | G15: en | H15: article | I15: [] | J15: 2 | K15: 2 | L15: 11.6731 | M15: 108 | N15: {'value': 0.98377692, 'is_in_top_1_percent': False, 'is_in_top_10_percent': True} | O15: {'min': 97, 'max': 100} | P15: {'volume': '52', 'issue': '8', 'first_page': '1498', 'last_page': '1515'} | Q15: [{'score': 0.49000000953674316, 'display_name': 'Reduced inequalities', 'id': 'https://metadata.un.org/sdg/10'}] | R15: [{'year': 2026, 'cited_by_count': 12}, {'year': 2025, 'cited_by_count': 35}, {'year': 2024, 'cited_by_count': 12}, {'year': 2023, 'cited_by_count': 19}, {'year': 2022, 'cited_by_count': 21}, {'year': 2021, 'cited_by_count': 4}, {'year': 2020, 'cited_by_count': 5}]
A16: https://openalex.org/W4224236076 | B16: https://doi.org/10.1016/j.trip.2022.100602 | C16: Is the 15-minute city within reach? Evaluating walking and cycling accessibility to grocery stores in Vancouver | D16: 2022 | E16: 44669 | F16: {'openalex': 'https://openalex.org/W4224236076', 'doi': 'https://doi.org/10.1016/j.trip.2022.100602', 'pmid': 'https://pubmed.ncbi.nlm.nih.gov/37981961'} | G16: en | H16: article | I16: [] | J16: 1 | K16: 3 | L16: 22.4454 | M16: 106 | N16: {'value': 0.99740818, 'is_in_top_1_percent': True, 'is_in_top_10_percent': True} | O16: {'min': 98, 'max': 100} | P16: {'volume': '14', 'issue': None, 'first_page': '100602', 'last_page': '100602'} | Q16: [{'score': 0.5799999833106995, 'id': 'https://metadata.un.org/sdg/11', 'display_name': 'Sustainable cities and communities'}] | R16: [{'year': 2026, 'cited_by_count': 5}, {'year': 2025, 'cited_by_count': 48}, {'year': 2024, 'cited_by_count': 33}, {'year': 2023, 'cited_by_count': 14}, {'year': 2022, 'cited_by_count': 6}]
A17: https://openalex.org/W4360603406 | B17: https://doi.org/10.1016/s0140-6736(23)00012-0 | C17: Conceptualising commercial entities in public health: beyond unhealthy commodities and transnational corporations | D17: 2023 | E17: 45008 | F17: {'openalex': 'https://openalex.org/W4360603406', 'doi': 'https://doi.org/10.1016/s0140-6736(23)00012-0', 'pmid': 'https://pubmed.ncbi.nlm.nih.gov/36966783'} | G17: en | H17: review | I17: [] | J17: 7 | K17: 12 | L17: 34.9744 | M17: 105 | N17: {'value': 0.99886156, 'is_in_top_1_percent': True, 'is_in_top_10_percent': True} | O17: {'min': 99, 'max': 100} | P17: {'volume': '401', 'issue': '10383', 'first_page': '1214', 'last_page': '1228'} | Q17: [] | R17: [{'year': 2026, 'cited_by_count': 5}, {'year': 2025, 'cited_by_count': 34}, {'year': 2024, 'cited_by_count': 35}, {'year': 2023, 'cited_by_count': 31}]
A18: https://openalex.org/W2998016237 | B18: https://doi.org/10.1111/add.14947 | C18: The cascade of care for opioid use disorder: a retrospective study in British Columbia, Canada | D18: 2020 | E18: 43833 | F18: {'openalex': 'https://openalex.org/W2998016237', 'doi': 'https://doi.org/10.1111/add.14947', 'mag': '2998016237', 'pmid': 'https://pubmed.ncbi.nlm.nih.gov/31899565'} | G18: en | H18: article | I18: [] | J18: 1 | K18: 9 | L18: 10.4768 | M18: 95 | N18: {'value': 0.98737794, 'is_in_top_1_percent': False, 'is_in_top_10_percent': True} | O18: {'min': 97, 'max': 100} | P18: {'volume': '115', 'issue': '8', 'first_page': '1482', 'last_page': '1493'} | Q18: [{'display_name': 'No poverty', 'score': 0.5, 'id': 'https://metadata.un.org/sdg/1'}] | R18: [{'year': 2026, 'cited_by_count': 1}, {'year': 2025, 'cited_by_count': 20}, {'year': 2024, 'cited_by_count': 15}, {'year': 2023, 'cited_by_count': 16}, {'year': 2022, 'cited_by_count': 20}, {'year': 2021, 'cited_by_count': 16}, {'year': 2020, 'cited_by_count': 7}]
A19: https://openalex.org/W3158732668 | B19: https://doi.org/10.1016/s2468-2667(21)00070-0 | C19: A global public health convention for the 21st century | D19: 2021 | E19: 44322 | F19: {'openalex': 'https://openalex.org/W3158732668', 'doi': 'https://doi.org/10.1016/s2468-2667(21)00070-0', 'mag': '3158732668', 'pmid': 'https://pubmed.ncbi.nlm.nih.gov/33964227'} | G19: en | H19: review | I19: [] | J19: 6 | K19: 21 | L19: 5.2114 | M19: 88 | N19: {'value': 0.96591309, 'is_in_top_1_percent': False, 'is_in_top_10_percent': True} | O19: {'min': 99, 'max': 100} | P19: {'volume': '6', 'issue': '6', 'first_page': 'e428', 'last_page': 'e433'} | Q19: [{'display_name': 'Partnerships for the goals', 'score': 0.49000000953674316, 'id': 'https://metadata.un.org/sdg/17'}] | R19: [{'year': 2025, 'cited_by_count': 7}, {'year': 2024, 'cited_by_count': 12}, {'year': 2023, 'cited_by_count': 40}, {'year': 2022, 'cited_by_count': 15}, {'year': 2021, 'cited_by_count': 14}]
A20: https://openalex.org/W3165160003 | B20: https://doi.org/10.1016/j.copsyc.2021.04.009 | C20: Recent developments in the social identity approach to the psychology of climate change | D20: 2021 | E20: 44317 | F20: {'openalex': 'https://openalex.org/W3165160003', 'doi': 'https://doi.org/10.1016/j.copsyc.2021.04.009', 'mag': '3165160003'} | G20: en | H20: review | I20: [] | J20: 1 | K20: 4 | L20: 23.5931 | M20: 88 | N20: {'value': 0.99503831, 'is_in_top_1_percent': True, 'is_in_top_10_percent': True} | O20: {'min': 97, 'max': 100} | P20: {'volume': '42', 'issue': None, 'first_page': '95', 'last_page': '101'} | Q20: [{'score': 0.5600000023841858, 'id': 'https://metadata.un.org/sdg/13', 'display_name': 'Climate action'}] | R20: [{'year': 2026, 'cited_by_count': 5}, {'year': 2025, 'cited_by_count': 18}, {'year': 2024, 'cited_by_count': 25}, {'year': 2023, 'cited_by_count': 23}, {'year': 2022, 'cited_by_count': 12}, {'year': 2021, 'cited_by_count': 5}]
A21: https://openalex.org/W3188001216 | B21: https://doi.org/10.1080/19491247.2021.1940686 | C21: â€˜Trappedâ€™, â€˜anxiousâ€™ and â€˜traumatisedâ€™: COVID-19 intensified the impact of housing inequality on Australiansâ€™ mental health | D21: 2021 | E21: 44412 | F21: {'openalex': 'https://openalex.org/W3188001216', 'doi': 'https://doi.org/10.1080/19491247.2021.1940686', 'mag': '3188001216'} | G21: en | H21: article | I21: [] | J21: 4 | K21: 9 | L21: 8.3266 | M21: 87 | N21: {'value': 0.97822198, 'is_in_top_1_percent': False, 'is_in_top_10_percent': True} | O21: {'min': 93, 'max': 100} | P21: {'volume': '23', 'issue': '2', 'first_page': '260', 'last_page': '291'} | Q21: [{'score': 0.5, 'display_name': 'No poverty', 'id': 'https://metadata.un.org/sdg/1'}] | R21: [{'year': 2025, 'cited_by_count': 17}, {'year': 2024, 'cited_by_count': 34}, {'year': 2023, 'cited_by_count': 17}, {'year': 2022, 'cited_by_count': 17}, {'year': 2021, 'cited_by_count': 2}]
... A38: https://openalex.org/W4307130818 | B38: https://doi.org/10.1177/00207314221134040 | C38: Is Neoliberalism Killing Us? A Cross Sectional Study of the Impact of Neoliberal Beliefs on Health and Social Wellbeing in the Midst of the COVID-19 Pandemic | D38: 2022 | E38: 44856 | F38: {'openalex': 'https://openalex.org/W4307130818', 'doi': 'https://doi.org/10.1177/00207314221134040', 'pmid': 'https://pubmed.ncbi.nlm.nih.gov/36278290'} | G38: en | H38: article | I38: [] | J38: 1 | K38: 2 | L38: 8.0921 | M38: 53 | N38: {'value': 0.98440659, 'is_in_top_1_percent': False, 'is_in_top_10_percent': True} | O38: {'min': 99, 'max': 100} | P38: {'volume': '53', 'issue': '3', 'first_page': '363', 'last_page': '373'} | Q38: [{'id': 'https://metadata.un.org/sdg/1', 'display_name': 'No poverty', 'score': 0.6800000071525574}] | R38: [{'year': 2026, 'cited_by_count': 2}, {'year': 2025, 'cited_by_count': 11}, {'year': 2024, 'cited_by_count': 40}]
A39: https://openalex.org/W4389685183 | B39: https://doi.org/10.4324/9781003343431 | C39: Designing Public Policies | D39: 2023 | E39: 45273 | F39: {'openalex': 'https://openalex.org/W4389685183', 'doi': 'https://doi.org/10.4324/9781003343431'} | G39: en | H39: book | I39: [] | J39: 1 | K39: 2 | M39: 53 | P39: {'volume': None, 'issue': None, 'first_page': None, 'last_page': None} | Q39: [] | R39: [{'year': 2026, 'cited_by_count': 5}, {'year': 2025, 'cited_by_count': 14}, {'year': 2024, 'cited_by_count': 6}, {'year': 2023, 'cited_by_count': 2}, {'year': 2022, 'cited_by_count': 11}, {'year': 2021, 'cited_by_count': 2}, {'year': 2020, 'cited_by_count': 2}, {'year': 2017, 'cited_by_count': 2}, {'year': 2016, 'cited_by_count': 1}, {'year': 2015, 'cited_by_count': 2}, {'year': 2014, 'cited_by_count': 3}, {'year': 2013, 'cited_by_count': 1}, {'year': 2012, 'cited_by_count': 1}]
A40: https://openalex.org/W3097822616 | B40: https://doi.org/10.1139/facets-2021-0018 | C40: Letâ€™s do better: public representations of COVID-19 science | D40: 2021 | E40: 44197 | F40: {'openalex': 'https://openalex.org/W3097822616', 'doi': 'https://doi.org/10.1139/facets-2021-0018', 'mag': '3097822616'} | G40: en | H40: article | I40: [] | J40: 1 | K40: 4 | L40: 15.9698 | M40: 52 | N40: {'value': 0.99013861, 'is_in_top_1_percent': True, 'is_in_top_10_percent': True} | O40: {'min': 97, 'max': 100} | P40: {'volume': '6', 'issue': None, 'first_page': '403', 'last_page': '423'} | Q40: [] | R40: [{'year': 2026, 'cited_by_count': 1}, {'year': 2025, 'cited_by_count': 7}, {'year': 2024, 'cited_by_count': 11}, {'year': 2023, 'cited_by_count': 17}, {'year': 2022, 'cited_by_count': 12}, {'year': 2021, 'cited_by_count': 4}]
A41: https://openalex.org/W3117903907 | B41: https://doi.org/10.1136/bmjopen-2020-048353 | C41: Evaluation of risk mitigation measures for people with substance use disorders to address the dual public health crises of COVID-19 and overdose in British Columbia: a mixed-method study protocol | D41: 2021 | E41: 44348 | F41: {'openalex': 'https://openalex.org/W3117903907', 'doi': 'https://doi.org/10.1136/bmjopen-2020-048353', 'mag': '3117903907', 'pmid': 'https://pubmed.ncbi.nlm.nih.gov/34108170'} | G41: en | H41: article | I41: [] | J41: 1 | K41: 15 | L41: 9.0336 | M41: 52 | N41: {'value': 0.9836983, 'is_in_top_1_percent': False, 'is_in_top_10_percent': True} | O41: {'min': 93, 'max': 100} | P41: {'volume': '11', 'issue': '6', 'first_page': 'e048353', 'last_page': 'e048353'} | Q41: [{'id': 'https://metadata.un.org/sdg/3', 'display_name': 'Good health and well-being', 'score': 0.800000011920929}] | R41: [{'year': 2026, 'cited_by_count': 1}, {'year': 2025, 'cited_by_count': 4}, {'year': 2024, 'cited_by_count': 14}, {'year': 2023, 'cited_by_count': 23}, {'year': 2022, 'cited_by_count': 8}, {'year': 2021, 'cited_by_count': 2}]
A42: https://openalex.org/W4405056567 | B42: https://doi.org/10.1126/science.adn1477 | C42: Ecological erosion and expanding extinction risk of sharks and rays | D42: 2024 | E42: 45631 | F42: {'openalex': 'https://openalex.org/W4405056567', 'doi': 'https://doi.org/10.1126/science.adn1477', 'pmid': 'https://pubmed.ncbi.nlm.nih.gov/39636992'} | G42: en | H42: article | I42: [] | J42: 5 | K42: 15 | L42: 36.7019 | M42: 50 | N42: {'value': 0.99922988, 'is_in_top_1_percent': True, 'is_in_top_10_percent': True} | O42: {'min': 90, 'max': 100} | P42: {'volume': '386', 'issue': '6726', 'first_page': 'eadn1477', 'last_page': 'eadn1477'} | Q42: [{'score': 0.5199999809265137, 'id': 'https://metadata.un.org/sdg/14', 'display_name': 'Life below water'}] | R42: [{'year': 2026, 'cited_by_count': 10}, {'year': 2025, 'cited_by_count': 39}, {'year': 2024, 'cited_by_count': 1}]
A43: https://openalex.org/W3040179572 | B43: https://doi.org/10.1371/journal.pmed.1003172 | C43: Associations of substance use, psychosis, and mortality among people living in precarious housing or homelessness: A longitudinal, community-based study in Vancouver, Canada | D43: 2020 | E43: 44018 | F43: {'openalex': 'https://openalex.org/W3040179572', 'doi': 'https://doi.org/10.1371/journal.pmed.1003172', 'mag': '3040179572', 'pmid': 'https://pubmed.ncbi.nlm.nih.gov/32628679'} | G43: en | H43: article | I43: [] | J43: 1 | K43: 20 | L43: 9.6234 | M43: 47 | N43: {'value': 0.98266187, 'is_in_top_1_percent': False, 'is_in_top_10_percent': True} | O43: {'min': 97, 'max': 100} | P43: {'volume': '17', 'issue': '7', 'first_page': 'e1003172', 'last_page': 'e1003172'} | Q43: [{'id': 'https://metadata.un.org/sdg/3', 'display_name': 'Good health and well-being', 'score': 0.8999999761581421}] | R43: [{'year': 2026, 'cited_by_count': 1}, {'year': 2025, 'cited_by_count': 5}, {'year': 2024, 'cited_by_count': 5}, {'year': 2023, 'cited_by_count': 9}, {'year': 2022, 'cited_by_count': 10}, {'year': 2021, 'cited_by_count': 17}]
A44: https://openalex.org/W3035757489 | B44: https://doi.org/10.1002/ejsp.2703 | C44: On the protective role of identification with a stigmatized identity: Promoting engagement and discouraging disengagement coping strategies | D44: 2020 | E44: 44033 | F44: {'openalex': 'https://openalex.org/W3035757489', 'doi': 'https://doi.org/10.1002/ejsp.2703', 'mag': '3035757489'} | G44: en | H44: article | I44: [] | J44: 5 | K44: 6 | L44: 9.0682 | M44: 47 | N44: {'value': 0.97807194, 'is_in_top_1_percent': False, 'is_in_top_10_percent': True} | O44: {'min': 96, 'max': 99} | P44: {'volume': '50', 'issue': '6', 'first_page': '1125', 'last_page': '1142'} | Q44: [{'score': 0.6000000238418579, 'id': 'https://metadata.un.org/sdg/10', 'display_name': 'Reduced inequalities'}] | R44: [{'year': 2026, 'cited_by_count': 1}, {'year': 2025, 'cited_by_count': 10}, {'year': 2024, 'cited_by_count': 10}, {'year': 2023, 'cited_by_count': 8}, {'year': 2022, 'cited_by_count': 8}, {'year': 2021, 'cited_by_count': 7}, {'year': 2020, 'cited_by_count': 3}]
A45: https://openalex.org/W3186602906 | B45: https://doi.org/10.1136/bmjgh-2021-006794 | C45: Building a multisystemic understanding of societal resilience to the COVID-19 pandemic | D45: 2021 | E45: 44378 | F45: {'openalex': 'https://openalex.org/W3186602906', 'doi': 'https://doi.org/10.1136/bmjgh-2021-006794', 'mag': '3186602906', 'pmid': 'https://pubmed.ncbi.nlm.nih.gov/34301677'} | G45: en | H45: review | I45: [] | J45: 5 | K45: 29 | L45: 3.5826 | M45: 47 | N45: {'value': 0.9379845, 'is_in_top_1_percent': False, 'is_in_top_10_percent': True} | O45: {'min': 97, 'max': 100} | P45: {'volume': '6', 'issue': '7', 'first_page': 'e006794', 'last_page': 'e006794'} | Q45: [] | R45: [{'year': 2026, 'cited_by_count': 1}, {'year': 2025, 'cited_by_count': 6}, {'year': 2024, 'cited_by_count': 15}, {'year': 2023, 'cited_by_count': 15}, {'year': 2022, 'cited_by_count': 10}]
A46: https://openalex.org/W4376273128 | B46: https://doi.org/10.1016/j.polgeo.2023.102904 | C46: Asymmetries in urban, suburban, and rural place-based resentment | D46: 2023 | E46: 45058 | F46: {'openalex': 'https://openalex.org/W4376273128', 'doi': 'https://doi.org/10.1016/j.polgeo.2023.102904'} | G46: en | H46: article | I46: [] | J46: 1 | K46: 2 | L46: 26.702 | M46: 47 | N46: {'value': 0.99655693, 'is_in_top_1_percent': True, 'is_in_top_10_percent': True} | O46: {'min': 89, 'max': 100} | P46: {'volume': '105', 'issue': None, 'first_page': '102904', 'last_page': '102904'} | Q46: [{'id': 'https://metadata.un.org/sdg/1', 'display_name': 'No poverty', 'score': 0.4699999988079071}] | R46: [{'year': 2026, 'cited_by_count': 2}, {'year': 2025, 'cited_by_count': 25}, {'year': 2024, 'cited_by_count': 15}, {'year': 2023, 'cited_by_count': 4}, {'year': 2022, 'cited_by_count': 1}]
A47: https://openalex.org/W4281746126 | B47: https://doi.org/10.1111/bjet.13246 | C47: Conceptions and perspectives of data literacy in secondary education | D47: 2022 | E47: 44713 | F47: {'openalex': 'https://openalex.org/W4281746126', 'doi': 'https://doi.org/10.1111/bjet.13246'} | G47: en | H47: article | I47: [] | J47: 1 | K47: 1 | L47: 17.801 | M47: 46 | N47: {'value': 0.98758539, 'is_in_top_1_percent': False, 'is_in_top_10_percent': True} | O47: {'min': 96, 'max': 100} | P47: {'volume': '53', 'issue': '5', 'first_page': '1080', 'last_page': '1095'} | Q47: [{'id': 'https://metadata.un.org/sdg/4', 'display_name': 'Quality Education', 'score': 0.8899999856948853}] | R47: [{'year': 2026, 'cited_by_count': 4}, {'year': 2025, 'cited_by_count': 12}, {'year': 2024, 'cited_by_count': 18}, {'year': 2023, 'cited_by_count': 9}, {'year': 2022, 'cited_by_count': 3}]
A48: https://openalex.org/W3040074229 | B48: https://doi.org/10.1016/j.cities.2020.102816 | C48: Under pressure: Factors shaping urban greenspace provision in a mid-sized city | D48: 2020 | E48: 44016 | F48: {'openalex': 'https://openalex.org/W3040074229', 'doi': 'https://doi.org/10.1016/j.cities.2020.102816', 'mag': '3040074229', 'pmid': 'https://pubmed.ncbi.nlm.nih.gov/32834327'} | G48: en | H48: article | I48: [] | J48: 2 | K48: 4 | L48: 2.8588 | M48: 46 | N48: {'value': 0.9164395, 'is_in_top_1_percent': False, 'is_in_top_10_percent': True} | O48: {'min': 98, 'max': 99} | P48: {'volume': '106', 'issue': None, 'first_page': '102816', 'last_page': '102816'} | Q48: [{'score': 0.41999998688697815, 'display_name': 'Sustainable cities and communities', 'id': 'https://metadata.un.org/sdg/11'}] | R48: [{'year': 2025, 'cited_by_count': 8}, {'year': 2024, 'cited_by_count': 8}, {'year': 2023, 'cited_by_count': 11}, {'year': 2022, 'cited_by_count': 11}, {'year': 2021, 'cited_by_count': 8}]
A49: https://openalex.org/W4405021649 | B49: https://doi.org/10.3389/fmed.2024.1495582 | C49: Why we need to be careful with LLMs in medicine | D49: 2024 | E49: 45630 | F49: {'openalex': 'https://openalex.org/W4405021649', 'doi': 'https://doi.org/10.3389/fmed.2024.1495582', 'pmid': 'https://pubmed.ncbi.nlm.nih.gov/39697212'} | G49: en | H49: article | I49: [] | J49: 1 | K49: 1 | L49: 6.5255 | M49: 46 | N49: {'value': 0.96979969, 'is_in_top_1_percent': False, 'is_in_top_10_percent': True} | O49: {'min': 99, 'max': 100} | P49: {'volume': '11', 'issue': None, 'first_page': '1495582', 'last_page': '1495582'} | Q49: [{'id': 'https://metadata.un.org/sdg/5', 'display_name': 'Gender equality', 'score': 0.46000000834465027}] | R49: [{'year': 2026, 'cited_by_count': 7}, {'year': 2025, 'cited_by_count': 39}]
A50: https://openalex.org/W3126397122 | B50: https://doi.org/10.1007/s10433-020-00599-y | C50: Ageing in place processes in the neighbourhood environment: aÂ proposed conceptual framework from a capability approach | D50: 2021 | E50: 44234 | F50: {'openalex': 'https://openalex.org/W3126397122', 'doi': 'https://doi.org/10.1007/s10433-020-00599-y', 'mag': '3126397122', 'pmid': 'https://pubmed.ncbi.nlm.nih.gov/35250420'} | G50: en | H50: article | I50: [] | J50: 1 | K50: 2 | L50: 8.7113 | M50: 45 | N50: {'value': 0.97450912, 'is_in_top_1_percent': False, 'is_in_top_10_percent': True} | O50: {'min': 89, 'max': 100} | P50: {'volume': '19', 'issue': '1', 'first_page': '63', 'last_page': '74'} | Q50: [{'id': 'https://metadata.un.org/sdg/11', 'display_name': 'Sustainable cities and communities', 'score': 0.41999998688697815}] | R50: [{'year': 2026, 'cited_by_count': 4}, {'year': 2025, 'cited_by_count': 17}, {'year': 2024, 'cited_by_count': 9}, {'year': 2023, 'cited_by_count': 8}, {'year': 2022, 'cited_by_count': 6}, {'year': 2021, 'cited_by_count': 1}]
A51: https://openalex.org/W3201507460 | B51: https://doi.org/10.1016/j.erss.2021.102255 | C51: Unsettling transitions: Representing Indigenous peoples and knowledge in transitions research | D51: 2021 | E51: 44453 | F51: {'openalex': 'https://openalex.org/W3201507460', 'doi': 'https://doi.org/10.1016/j.erss.2021.102255', 'mag': '3201507460'} | G51: en | H51: article | I51: [] | J51: 2 | K51: 3 | L51: 3.9144 | M51: 45 | N51: {'value': 0.93785528, 'is_in_top_1_percent': False, 'is_in_top_10_percent': True} | O51: {'min': 93, 'max': 100} | P51: {'volume': '81', 'issue': None, 'first_page': '102255', 'last_page': '102255'} | Q51: [{'id': 'https://metadata.un.org/sdg/10', 'display_name': 'Reduced inequalities', 'score': 0.4000000059604645}] | R51: [{'year': 2026, 'cited_by_count': 6}, {'year': 2025, 'cited_by_count': 6}, {'year': 2024, 'cited_by_count': 15}, {'year': 2023, 'cited_by_count': 14}, {'year': 2022, 'cited_by_count': 2}, {'year': 2021, 'cited_by_count': 2}]
... A188: https://openalex.org/W4391215992 | B188: https://doi.org/10.1016/j.tree.2024.01.001 | C188: Relational place-based solutions for environmental policy misalignments | D188: 2024 | E188: 45316 | F188: {'openalex': 'https://openalex.org/W4391215992', 'doi': 'https://doi.org/10.1016/j.tree.2024.01.001'} | G188: en | H188: article | I188: [] | J188: 1 | K188: 11 | L188: 3.5872 | M188: 12 | N188: {'value': 0.92637074, 'is_in_top_1_percent': False, 'is_in_top_10_percent': True} | O188: {'min': 96, 'max': 100} | P188: {'volume': '39', 'issue': '3', 'first_page': '217', 'last_page': '220'} | Q188: [{'score': 0.5400000214576721, 'id': 'https://metadata.un.org/sdg/13', 'display_name': 'Climate action'}] | R188: [{'year': 2026, 'cited_by_count': 4}, {'year': 2025, 'cited_by_count': 5}, {'year': 2024, 'cited_by_count': 3}]
A189: https://openalex.org/W3195573675 | B189: https://doi.org/10.21203/rs.3.rs-759005/v1 | C189: COVID-19 vaccine hesitancy in Africa: A scoping review | D189: 2021 | E189: 44424 | F189: {'openalex': 'https://openalex.org/W3195573675', 'doi': 'https://doi.org/10.21203/rs.3.rs-759005/v1', 'mag': '3195573675'} | G189: en | H189: review | I189: [] | J189: 2 | K189: 7 | M189: 12 | P189: {'volume': None, 'issue': None, 'first_page': None, 'last_page': None} | Q189: [{'id': 'https://metadata.un.org/sdg/3', 'score': 0.8299999833106995, 'display_name': 'Good health and well-being'}] | R189: [{'year': 2025, 'cited_by_count': 3}, {'year': 2024, 'cited_by_count': 3}, {'year': 2023, 'cited_by_count': 4}, {'year': 2022, 'cited_by_count': 2}]
A190: https://openalex.org/W4206514936 | B190: https://doi.org/10.1371/journal.pgph.0000078 | C190: Analyzing natural herd immunity media discourse in the United Kingdom and the United States | D190: 2022 | E190: 44573 | F190: {'openalex': 'https://openalex.org/W4206514936', 'doi': 'https://doi.org/10.1371/journal.pgph.0000078', 'pmid': 'https://pubmed.ncbi.nlm.nih.gov/36962077'} | G190: en | H190: article | I190: [] | J190: 2 | K190: 4 | L190: 1.904 | M190: 12 | N190: {'value': 0.84684191, 'is_in_top_1_percent': False, 'is_in_top_10_percent': False} | O190: {'min': 94, 'max': 98} | P190: {'volume': '2', 'issue': '1', 'first_page': 'e0000078', 'last_page': 'e0000078'} | Q190: [{'id': 'https://metadata.un.org/sdg/3', 'score': 0.7400000095367432, 'display_name': 'Good health and well-being'}] | R190: [{'year': 2025, 'cited_by_count': 4}, {'year': 2024, 'cited_by_count': 3}, {'year': 2023, 'cited_by_count': 3}, {'year': 2022, 'cited_by_count': 2}]
A191: https://openalex.org/W4289523079 | B191: https://doi.org/10.1017/gov.2022.26 | C191: What Do We Know about Power Sharing after 50 Years? | D191: 2022 | E191: 44775 | F191: {'openalex': 'https://openalex.org/W4289523079', 'doi': 'https://doi.org/10.1017/gov.2022.26'} | G191: en | H191: article | I191: [] | J191: 5 | K191: 5 | L191: 4.5481 | M191: 12 | N191: {'value': 0.94528662, 'is_in_top_1_percent': False, 'is_in_top_10_percent': True} | O191: {'min': 94, 'max': 99} | P191: {'volume': '58', 'issue': '4', 'first_page': '899', 'last_page': '920'} | Q191: [] | R191: [{'year': 2025, 'cited_by_count': 6}, {'year': 2024, 'cited_by_count': 2}, {'year': 2023, 'cited_by_count': 4}]
A192: https://openalex.org/W4224110254 | B192: https://doi.org/10.1177/14713012221084173 | C192: Out-of-home participation among people living with dementia: A study in four countries | D192: 2022 | E192: 44668 | F192: {'openalex': 'https://openalex.org/W4224110254', 'doi': 'https://doi.org/10.1177/14713012221084173', 'pmid': 'https://pubmed.ncbi.nlm.nih.gov/35435030'} | G192: en | H192: article | I192: [] | J192: 4 | K192: 11 | L192: 1.7453 | M192: 12 | N192: {'value': 0.83614929, 'is_in_top_1_percent': False, 'is_in_top_10_percent': False} | O192: {'min': 89, 'max': 99} | P192: {'volume': '21', 'issue': '5', 'first_page': '1636', 'last_page': '1652'} | Q192: [{'id': 'https://metadata.un.org/sdg/10', 'display_name': 'Reduced inequalities', 'score': 0.5699999928474426}] | R192: [{'year': 2026, 'cited_by_count': 1}, {'year': 2025, 'cited_by_count': 2}, {'year': 2024, 'cited_by_count': 8}, {'year': 2023, 'cited_by_count': 1}]
A193: https://openalex.org/W4392860930 | B193: https://doi.org/10.1016/j.oneear.2024.02.009 | C193: Mapping flows of blue economy finance: Ambitious narratives, opaque actions, and social equity risks | D193: 2024 | E193: 45366 | F193: {'openalex': 'https://openalex.org/W4392860930', 'doi': 'https://doi.org/10.1016/j.oneear.2024.02.009'} | G193: en | H193: article | I193: [] | J193: 5 | K193: 7 | L193: 8.8262 | M193: 12 | N193: {'value': 0.97343018, 'is_in_top_1_percent': False, 'is_in_top_10_percent': True} | O193: {'min': 94, 'max': 100} | P193: {'volume': '7', 'issue': '4', 'first_page': '638', 'last_page': '649'} | Q193: [{'score': 0.4399999976158142, 'id': 'https://metadata.un.org/sdg/8', 'display_name': 'Decent work and economic growth'}] | R193: [{'year': 2026, 'cited_by_count': 3}, {'year': 2025, 'cited_by_count': 7}, {'year': 2024, 'cited_by_count': 2}]
A194: https://openalex.org/W4377942449 | B194: https://doi.org/10.3389/fmars.2023.1045887 | C194: The use of influential power in ocean governance | D194: 2023 | E194: 45070 | F194: {'openalex': 'https://openalex.org/W4377942449', 'doi': 'https://doi.org/10.3389/fmars.2023.1045887'} | G194: en | H194: article | I194: [] | J194: 3 | K194: 6 | L194: 4.7241 | M194: 11 | N194: {'value': 0.94298021, 'is_in_top_1_percent': False, 'is_in_top_10_percent': True} | O194: {'min': 94, 'max': 99} | P194: {'volume': '10', 'issue': None, 'first_page': None, 'last_page': None} | Q194: [{'score': 0.8100000023841858, 'display_name': 'Life below water', 'id': 'https://metadata.un.org/sdg/14'}] | R194: [{'year': 2025, 'cited_by_count': 6}, {'year': 2024, 'cited_by_count': 3}, {'year': 2023, 'cited_by_count': 2}]
A195: https://openalex.org/W4205452337 | B195: https://doi.org/10.1111/boer.12328 | C195: Social trust, corporate governance, and stock price crash risk: Evidence from China | D195: 2022 | E195: 44581 | F195: {'openalex': 'https://openalex.org/W4205452337', 'doi': 'https://doi.org/10.1111/boer.12328'} | G195: en | H195: article | I195: [] | J195: 2 | K195: 2 | L195: 2.8031 | M195: 11 | N195: {'value': 0.90410027, 'is_in_top_1_percent': False, 'is_in_top_10_percent': True} | O195: {'min': 89, 'max': 99} | P195: {'volume': '74', 'issue': '4', 'first_page': '965', 'last_page': '994'} | Q195: [] | R195: [{'year': 2026, 'cited_by_count': 1}, {'year': 2025, 'cited_by_count': 1}, {'year': 2024, 'cited_by_count': 4}, {'year': 2023, 'cited_by_count': 4}, {'year': 2022, 'cited_by_count': 1}]
A196: https://openalex.org/W4394674895 | B196: https://doi.org/10.1111/1467-8500.12630 | C196: Expertise, policy advice, and policy advisory systems in an open, participatory, and populist era: New challenges to research and practice | D196: 2024 | E196: 45392 | F196: {'openalex': 'https://openalex.org/W4394674895', 'doi': 'https://doi.org/10.1111/1467-8500.12630'} | G196: en | H196: article | I196: [] | J196: 2 | K196: 3 | L196: 25.4972 | M196: 11 | N196: {'value': 0.99424008, 'is_in_top_1_percent': True, 'is_in_top_10_percent': True} | O196: {'min': 94, 'max': 99} | P196: {'volume': '83', 'issue': '2', 'first_page': '143', 'last_page': '155'} | Q196: [] | R196: [{'year': 2026, 'cited_by_count': 1}, {'year': 2025, 'cited_by_count': 8}, {'year': 2024, 'cited_by_count': 2}]
A197: https://openalex.org/W3126565504 | B197: https://doi.org/10.1016/j.geoforum.2021.01.019 | C197: Land use planning and the making of a â€˜properly propertiedâ€™ Vancouver | D197: 2021 | E197: 44227 | F197: {'openalex': 'https://openalex.org/W3126565504', 'doi': 'https://doi.org/10.1016/j.geoforum.2021.01.019', 'mag': '3126565504'} | G197: en | H197: article | I197: [] | J197: 1 | K197: 1 | L197: 7.87 | M197: 11 | N197: {'value': 0.96656996, 'is_in_top_1_percent': False, 'is_in_top_10_percent': True} | O197: {'min': 89, 'max': 100} | P197: {'volume': '120', 'issue': None, 'first_page': '46', 'last_page': '57'} | Q197: [{'score': 0.6800000071525574, 'id': 'https://metadata.un.org/sdg/11', 'display_name': 'Sustainable cities and communities'}] | R197: [{'year': 2026, 'cited_by_count': 2}, {'year': 2025, 'cited_by_count': 1}, {'year': 2024, 'cited_by_count': 5}, {'year': 2022, 'cited_by_count': 2}, {'year': 2021, 'cited_by_count': 1}]
A198: https://openalex.org/W4309592810 | B198: https://doi.org/10.1136/bmjopen-2022-061729 | C198: How client criminalisation under end-demand sex work laws shapes the occupational health and safety of sex workers in Metro Vancouver, Canada: a qualitative study | D198: 2022 | E198: 44866 | F198: {'openalex': 'https://openalex.org/W4309592810', 'doi': 'https://doi.org/10.1136/bmjopen-2022-061729', 'pmid': 'https://pubmed.ncbi.nlm.nih.gov/36414310'} | G198: en | H198: article | I198: [] | J198: 2 | K198: 7 | L198: 4.1694 | M198: 11 | N198: {'value': 0.94178968, 'is_in_top_1_percent': False, 'is_in_top_10_percent': True} | O198: {'min': 94, 'max': 99} | P198: {'volume': '12', 'issue': '11', 'first_page': 'e061729', 'last_page': 'e061729'} | Q198: [{'id': 'https://metadata.un.org/sdg/16', 'display_name': 'Peace, Justice and strong institutions', 'score': 0.6100000143051147}] | R198: [{'year': 2025, 'cited_by_count': 6}, {'year': 2024, 'cited_by_count': 2}, {'year': 2023, 'cited_by_count': 3}]
A199: https://openalex.org/W4223947867 | B199: https://doi.org/10.1111/joms.12818 | C199: Have a Go or Lay Low? Predicting Firmsâ€™ Rhetorical Commitment versus Avoidance in Response to Polylithic Governmental Pressures | D199: 2022 | E199: 44666 | F199: {'openalex': 'https://openalex.org/W4223947867', 'doi': 'https://doi.org/10.1111/joms.12818'} | G199: en | H199: article | I199: [] | J199: 1 | K199: 4 | L199: 1.7365 | M199: 11 | N199: {'value': 0.86834454, 'is_in_top_1_percent': False, 'is_in_top_10_percent': False} | O199: {'min': 89, 'max': 99} | P199: {'volume': '61', 'issue': '2', 'first_page': '307', 'last_page': '335'} | Q199: [{'score': 0.41999998688697815, 'display_name': 'Partnerships for the goals', 'id': 'https://metadata.un.org/sdg/17'}] | R199: [{'year': 2026, 'cited_by_count': 1}, {'year': 2025, 'cited_by_count': 2}, {'year': 2024, 'cited_by_count': 4}, {'year': 2023, 'cited_by_count': 3}, {'year': 2022, 'cited_by_count': 1}]
A200: https://openalex.org/W4384257491 | B200: https://doi.org/10.1016/j.drugpo.2023.104117 | C200: Socioeconomic marginalization and risk of overdose in a community-recruited cohort of people who use drugs: A longitudinal analysis | D200: 2023 | E200: 45120 | F200: {'openalex': 'https://openalex.org/W4384257491', 'doi': 'https://doi.org/10.1016/j.drugpo.2023.104117'} | G200: en | H200: article | I200: [] | J200: 2 | K200: 9 | L200: 3.2516 | M200: 11 | N200: {'value': 0.91949883, 'is_in_top_1_percent': False, 'is_in_top_10_percent': True} | O200: {'min': 89, 'max': 100} | P200: {'volume': '119', 'issue': None, 'first_page': '104117', 'last_page': '104117'} | Q200: [{'score': 0.7699999809265137, 'display_name': 'No poverty', 'id': 'https://metadata.un.org/sdg/1'}] | R200: [{'year': 2026, 'cited_by_count': 2}, {'year': 2025, 'cited_by_count': 5}, {'year': 2024, 'cited_by_count': 3}, {'year': 2023, 'cited_by_count': 1}]
A201: https://openalex.org/W4308024747 | B201: https://doi.org/10.1080/10584609.2022.2137743 | C201: Damage Control: How Campaign Teams Interpret and Respond to Online Incivility | D201: 2022 | E201: 44866 | F201: {'openalex': 'https://openalex.org/W4308024747', 'doi': 'https://doi.org/10.1080/10584609.2022.2137743'} | G201: en | H201: article | I201: [] | J201: 1 | K201: 5 | L201: 3.2891 | M201: 11 | N201: {'value': 0.91976564, 'is_in_top_1_percent': False, 'is_in_top_10_percent': True} | O201: {'min': 94, 'max': 99} | P201: {'volume': '40', 'issue': '3', 'first_page': '283', 'last_page': '303'} | Q201: [] | R201: [{'year': 2025, 'cited_by_count': 6}, {'year': 2024, 'cited_by_count': 3}, {'year': 2023, 'cited_by_count': 2}]
... A216: https://openalex.org/W3012848187 | B216: https://doi.org/10.1177/1363459320912808 | C216: What was lost, missing, sought and hoped for: Qualitatively exploring medical crowdfunding campaign narratives for Lyme disease | D216: 2020 | E216: 43913 | F216: {'openalex': 'https://openalex.org/W3012848187', 'doi': 'https://doi.org/10.1177/1363459320912808', 'mag': '3012848187', 'pmid': 'https://pubmed.ncbi.nlm.nih.gov/32202156'} | G216: en | H216: article | I216: [] | J216: 1 | K216: 3 | L216: 1.7796 | M216: 10 | N216: {'value': 0.86263853, 'is_in_top_1_percent': False, 'is_in_top_10_percent': False} | O216: {'min': 89, 'max': 99} | P216: {'volume': '25', 'issue': '6', 'first_page': '707', 'last_page': '721'} | Q216: [{'id': 'https://metadata.un.org/sdg/10', 'display_name': 'Reduced inequalities', 'score': 0.5099999904632568}] | R216: [{'year': 2026, 'cited_by_count': 1}, {'year': 2025, 'cited_by_count': 2}, {'year': 2023, 'cited_by_count': 1}, {'year': 2022, 'cited_by_count': 4}, {'year': 2021, 'cited_by_count': 1}, {'year': 2020, 'cited_by_count': 1}]
A217: https://openalex.org/W4302410655 | B217: https://doi.org/10.3386/w30368 | C217: The Slaughter of the Bison and Reversal of Fortunes on the Great Plains | D217: 2022 | E217: 44774 | F217: {'openalex': 'https://openalex.org/W4302410655', 'doi': 'https://doi.org/10.3386/w30368'} | G217: en | H217: report | I217: [] | J217: 4 | K217: 3 | M217: 10 | P217: {'volume': None, 'issue': None, 'first_page': None, 'last_page': None} | Q217: [] | R217: [{'year': 2026, 'cited_by_count': 2}, {'year': 2025, 'cited_by_count': 1}, {'year': 2024, 'cited_by_count': 2}, {'year': 2023, 'cited_by_count': 4}, {'year': 2021, 'cited_by_count': 1}]
A218: https://openalex.org/W4224307223 | B218: https://doi.org/10.1287/isre.2022.1100 | C218: The Dark Side of Technological Modularity: Opportunistic Information Hiding During Interorganizational System Adoption | D218: 2022 | E218: 44672 | F218: {'openalex': 'https://openalex.org/W4224307223', 'doi': 'https://doi.org/10.1287/isre.2022.1100'} | G218: en | H218: article | I218: [] | J218: 1 | K218: 3 | L218: 1.7365 | M218: 10 | N218: {'value': 0.86867642, 'is_in_top_1_percent': False, 'is_in_top_10_percent': False} | O218: {'min': 94, 'max': 98} | P218: {'volume': '33', 'issue': '3', 'first_page': '1072', 'last_page': '1092'} | Q218: [{'score': 0.6299999952316284, 'display_name': 'Industry, innovation and infrastructure', 'id': 'https://metadata.un.org/sdg/9'}] | R218: [{'year': 2025, 'cited_by_count': 5}, {'year': 2024, 'cited_by_count': 3}, {'year': 2023, 'cited_by_count': 2}]
A219: https://openalex.org/W4400651964 | B219: https://doi.org/10.5751/es-15122-290304 | C219: Colonialism and the Blue Economy: confronting historical legacies to enable equitable ocean development | D219: 2024 | E219: 45292 | F219: {'openalex': 'https://openalex.org/W4400651964', 'doi': 'https://doi.org/10.5751/es-15122-290304'} | G219: en | H219: article | I219: [] | J219: 3 | K219: 2 | L219: 7.3396 | M219: 10 | N219: {'value': 0.96639123, 'is_in_top_1_percent': False, 'is_in_top_10_percent': True} | O219: {'min': 90, 'max': 99} | P219: {'volume': '29', 'issue': '3', 'first_page': None, 'last_page': None} | Q219: [{'score': 0.800000011920929, 'id': 'https://metadata.un.org/sdg/14', 'display_name': 'Life below water'}] | R219: [{'year': 2026, 'cited_by_count': 1}, {'year': 2025, 'cited_by_count': 8}, {'year': 2024, 'cited_by_count': 1}]
A220: https://openalex.org/W3200355573 | B220: https://doi.org/10.1515/opis-2020-0118 | C220: Disinformation under a networked authoritarian state: Saudi trollsâ€™ credibility attacks against Jamal Khashoggi | D220: 2021 | E220: 44197 | F220: {'openalex': 'https://openalex.org/W3200355573', 'doi': 'https://doi.org/10.1515/opis-2020-0118', 'mag': '3200355573'} | G220: en | H220: article | I220: [] | J220: 1 | K220: 1 | L220: 2.1777 | M220: 9 | N220: {'value': 0.90008672, 'is_in_top_1_percent': False, 'is_in_top_10_percent': True} | O220: {'min': 89, 'max': 98} | P220: {'volume': '5', 'issue': '1', 'first_page': '140', 'last_page': '162'} | Q220: [{'score': 0.6299999952316284, 'display_name': 'Peace, Justice and strong institutions', 'id': 'https://metadata.un.org/sdg/16'}] | R220: [{'year': 2025, 'cited_by_count': 3}, {'year': 2024, 'cited_by_count': 4}, {'year': 2023, 'cited_by_count': 1}, {'year': 2022, 'cited_by_count': 1}]
A221: https://openalex.org/W4376648636 | B221: https://doi.org/10.1016/j.pnpbp.2023.110795 | C221: Movement disorders associated with substance use in adults living in precarious housing or homelessness | D221: 2023 | E221: 45061 | F221: {'openalex': 'https://openalex.org/W4376648636', 'doi': 'https://doi.org/10.1016/j.pnpbp.2023.110795', 'pmid': 'https://pubmed.ncbi.nlm.nih.gov/37196752'} | G221: en | H221: article | I221: [] | J221: 1 | K221: 14 | L221: 1.8991 | M221: 9 | N221: {'value': 0.8621438, 'is_in_top_1_percent': False, 'is_in_top_10_percent': False} | O221: {'min': 89, 'max': 98} | P221: {'volume': '126', 'issue': None, 'first_page': '110795', 'last_page': '110795'} | Q221: [{'display_name': 'Good health and well-being', 'score': 0.8500000238418579, 'id': 'https://metadata.un.org/sdg/3'}] | R221: [{'year': 2025, 'cited_by_count': 2}, {'year': 2024, 'cited_by_count': 6}, {'year': 2023, 'cited_by_count': 1}]
A222: https://openalex.org/W4381838898 | B222: https://doi.org/10.1186/s12888-023-04945-z | C222: Association of homelessness and psychiatric hospital readmissionâ€”a retrospective cohort study 2016â€“2020 | D222: 2023 | E222: 45100 | F222: {'openalex': 'https://openalex.org/W4381838898', 'doi': 'https://doi.org/10.1186/s12888-023-04945-z', 'pmid': 'https://pubmed.ncbi.nlm.nih.gov/37353747'} | G222: en | H222: article | I222: [] | J222: 1 | K222: 5 | L222: 4.0236 | M222: 9 | N222: {'value': 0.93600895, 'is_in_top_1_percent': False, 'is_in_top_10_percent': True} | O222: {'min': 94, 'max': 100} | P222: {'volume': '23', 'issue': '1', 'first_page': '459', 'last_page': '459'} | Q222: [{'display_name': 'Good health and well-being', 'score': 0.7799999713897705, 'id': 'https://metadata.un.org/sdg/3'}] | R222: [{'year': 2026, 'cited_by_count': 2}, {'year': 2025, 'cited_by_count': 5}, {'year': 2024, 'cited_by_count': 2}]
A223: https://openalex.org/W3040788855 | B223: https://doi.org/10.1080/02673037.2020.1789564 | C223: Moving from government to governance: addressing housing pressures during rapid industrial development in Kitimat, BC, Canada | D223: 2020 | E223: 44021 | F223: {'openalex': 'https://openalex.org/W3040788855', 'doi': 'https://doi.org/10.1080/02673037.2020.1789564', 'mag': '3040788855'} | G223: en | H223: article | I223: [] | J223: 1 | K223: 3 | L223: 1.1532 | M223: 9 | N223: {'value': 0.80836182, 'is_in_top_1_percent': False, 'is_in_top_10_percent': False} | O223: {'min': 89, 'max': 98} | P223: {'volume': '36', 'issue': '10', 'first_page': '1618', 'last_page': '1643'} | Q223: [{'display_name': 'No poverty', 'score': 0.550000011920929, 'id': 'https://metadata.un.org/sdg/1'}] | R223: [{'year': 2024, 'cited_by_count': 4}, {'year': 2023, 'cited_by_count': 1}, {'year': 2022, 'cited_by_count': 1}, {'year': 2021, 'cited_by_count': 3}]
A224: https://openalex.org/W3123382469 | B224: https://doi.org/10.1177/0706743721989158 | C224: Overall and Gender-specific Associations between Dimensions of Adverse Childhood Experiences and Mental Health Outcomes among Homeless Adults: Associations GÃ©nÃ©rales et SexospÃ©cifiques Entre les Dimensions des ExpÃ©riences DÃ©favorables de Lâ€™enfance et les RÃ©sultats de SantÃ© Mentale Chez les Adultes Sans Abri | D224: 2021 | E224: 44223 | F224: {'openalex': 'https://openalex.org/W3123382469', 'doi': 'https://doi.org/10.1177/0706743721989158', 'mag': '3123382469', 'pmid': 'https://pubmed.ncbi.nlm.nih.gov/33502253'} | G224: en | H224: article | I224: [] | J224: 2 | K224: 9 | L224: 2.2831 | M224: 9 | N224: {'value': 0.8825463, 'is_in_top_1_percent': False, 'is_in_top_10_percent': False} | O224: {'min': 91, 'max': 97} | P224: {'volume': '66', 'issue': '10', 'first_page': '906', 'last_page': '917'} | Q224: [{'display_name': 'Gender equality', 'score': 0.4300000071525574, 'id': 'https://metadata.un.org/sdg/5'}] | R224: [{'year': 2025, 'cited_by_count': 1}, {'year': 2024, 'cited_by_count': 2}, {'year': 2023, 'cited_by_count': 4}, {'year': 2021, 'cited_by_count': 2}]
A225: https://openalex.org/W4304698159 | B225: https://doi.org/10.46292/sci21-00056 | C225: Modifiable Sociostructural and Environmental Factors That Impact the Health and Quality of Life of People With Spinal Cord Injury: A Scoping Review | D225: 2022 | E225: 44844 | F225: {'openalex': 'https://openalex.org/W4304698159', 'doi': 'https://doi.org/10.46292/sci21-00056', 'pmid': 'https://pubmed.ncbi.nlm.nih.gov/36819929'} | G225: en | H225: review | I225: [] | J225: 1 | K225: 4 | L225: 1.1646 | M225: 9 | N225: {'value': 0.78079003, 'is_in_top_1_percent': False, 'is_in_top_10_percent': False} | O225: {'min': 89, 'max': 99} | P225: {'volume': '29', 'issue': '1', 'first_page': '42', 'last_page': '53'} | Q225: [] | R225: [{'year': 2026, 'cited_by_count': 1}, {'year': 2025, 'cited_by_count': 4}, {'year': 2024, 'cited_by_count': 2}, {'year': 2023, 'cited_by_count': 1}, {'year': 2022, 'cited_by_count': 1}]
A226: https://openalex.org/W4360915057 | B226: https://doi.org/10.1177/16094069231157350 | C226: Protocol for A Mixed-Methods Study: Dementia-Inclusive Streets and Community Access, Participation, and Engagement (DemSCAPE) | D226: 2023 | E226: 45008 | F226: {'openalex': 'https://openalex.org/W4360915057', 'doi': 'https://doi.org/10.1177/16094069231157350'} | G226: en | H226: article | I226: [] | J226: 1 | K226: 10 | L226: 3.3074 | M226: 9 | N226: {'value': 0.9059428, 'is_in_top_1_percent': False, 'is_in_top_10_percent': True} | O226: {'min': 96, 'max': 99} | P226: {'volume': '22', 'issue': None, 'first_page': None, 'last_page': None} | Q226: [{'score': 0.6299999952316284, 'id': 'https://metadata.un.org/sdg/10', 'display_name': 'Reduced inequalities'}] | R226: [{'year': 2025, 'cited_by_count': 6}, {'year': 2024, 'cited_by_count': 3}]
A227: https://openalex.org/W4224294770 | B227: https://doi.org/10.3389/fpos.2022.834223 | C227: â€œGuided by Science and Evidenceâ€? The Politics of Border Management in Canada's Response to the COVID-19 Pandemic | D227: 2022 | E227: 44670 | F227: {'openalex': 'https://openalex.org/W4224294770', 'doi': 'https://doi.org/10.3389/fpos.2022.834223'} | G227: en | H227: article | I227: [] | J227: 1 | K227: 3 | L227: 6.4663 | M227: 9 | N227: {'value': 0.96289031, 'is_in_top_1_percent': False, 'is_in_top_10_percent': True} | O227: {'min': 89, 'max': 97} | P227: {'volume': '4', 'issue': None, 'first_page': None, 'last_page': None} | Q227: [{'score': 0.4099999964237213, 'id': 'https://metadata.un.org/sdg/3', 'display_name': 'Good health and well-being'}] | R227: [{'year': 2025, 'cited_by_count': 3}, {'year': 2024, 'cited_by_count': 3}, {'year': 2023, 'cited_by_count': 1}, {'year': 2022, 'cited_by_count': 1}, {'year': 2016, 'cited_by_count': 1}]
A228: https://openalex.org/W4388411517 | B228: https://doi.org/10.1093/geront/gnad151 | C228: Meanings of Aging in the Right Place for Older Clients of a Temporary Housing Program | D228: 2023 | E228: 45230 | F228: {'openalex': 'https://openalex.org/W4388411517', 'doi': 'https://doi.org/10.1093/geront/gnad151', 'pmid': 'https://pubmed.ncbi.nlm.nih.gov/37930091'} | G228: en | H228: article | I228: [] | J228: 2 | K228: 5 | L228: 4.0236 | M228: 9 | N228: {'value': 0.93907771, 'is_in_top_1_percent': False, 'is_in_top_10_percent': True} | O228: {'min': 89, 'max': 99} | P228: {'volume': '64', 'issue': '5', 'first_page': None, 'last_page': None} | Q228: [{'id': 'https://metadata.un.org/sdg/11', 'score': 0.8299999833106995, 'display_name': 'Sustainable cities and communities'}] | R228: [{'year': 2025, 'cited_by_count': 7}, {'year': 2024, 'cited_by_count': 1}, {'year': 2023, 'cited_by_count': 1}]
A229: https://openalex.org/W4293207036 | B229: https://doi.org/10.1024/1662-9647/a000301 | C229: Abuse of Marginalized Older Adults During COVID-19 | D229: 2022 | E229: 44799 | F229: {'openalex': 'https://openalex.org/W4293207036', 'doi': 'https://doi.org/10.1024/1662-9647/a000301'} | G229: en | H229: article | I229: [] | J229: 1 | K229: 3 | L229: 4.1628 | M229: 9 | N229: {'value': 0.94596554, 'is_in_top_1_percent': False, 'is_in_top_10_percent': True} | O229: {'min': 89, 'max': 99} | P229: {'volume': '36', 'issue': '3', 'first_page': '161', 'last_page': '173'} | Q229: [{'score': 0.6800000071525574, 'id': 'https://metadata.un.org/sdg/1', 'display_name': 'No poverty'}] | R229: [{'year': 2026, 'cited_by_count': 1}, {'year': 2025, 'cited_by_count': 2}, {'year': 2024, 'cited_by_count': 2}, {'year': 2023, 'cited_by_count': 3}, {'year': 2022, 'cited_by_count': 1}]
... A282: https://openalex.org/W4403065771 | B282: https://doi.org/10.1057/s41599-024-03804-w | C282: The impact of COVID-19 on the debate on open science: a qualitative analysis of published materials from the period of the pandemic | D282: 2024 | E282: 45567 | F282: {'openalex': 'https://openalex.org/W4403065771', 'doi': 'https://doi.org/10.1057/s41599-024-03804-w'} | G282: en | H282: article | I282: [] | J282: 4 | K282: 11 | L282: 6.4668 | M282: 6 | N282: {'value': 0.96527039, 'is_in_top_1_percent': False, 'is_in_top_10_percent': True} | O282: {'min': 90, 'max': 99} | P282: {'volume': '11', 'issue': '1', 'first_page': None, 'last_page': None} | Q282: [] | R282: [{'year': 2026, 'cited_by_count': 1}, {'year': 2025, 'cited_by_count': 4}, {'year': 2024, 'cited_by_count': 1}]
A283: https://openalex.org/W3115823313 | C283: Exerting Sovereignty Through Relational Self-determination: A Case Study of Mineral Development In Stkâ€™emlupsemc te SecwÃ©pemc Territory | D283: 2020 | E283: 44188 | F283: {'openalex': 'https://openalex.org/W3115823313', 'mag': '3115823313'} | G283: en | H283: article | I283: [] | J283: 1 | K283: 2 | L283: 0.3818 | M283: 6 | N283: {'value': 0.63439288, 'is_in_top_1_percent': False, 'is_in_top_10_percent': False} | O283: {'min': 89, 'max': 96} | P283: {'volume': '15', 'issue': '4', 'first_page': None, 'last_page': None} | Q283: [{'id': 'https://metadata.un.org/sdg/8', 'display_name': 'Decent work and economic growth', 'score': 0.41999998688697815}] | R283: [{'year': 2025, 'cited_by_count': 1}, {'year': 2024, 'cited_by_count': 2}, {'year': 2023, 'cited_by_count': 1}, {'year': 2021, 'cited_by_count': 2}]
A284: https://openalex.org/W3189390687 | B284: https://doi.org/10.1080/10826084.2021.1958865 | C284: Characterization of Bodily Pain and Use of Both Prescription and Non-Prescription Opioids in Tenants of Precarious Housing | D284: 2021 | E284: 44410 | F284: {'openalex': 'https://openalex.org/W3189390687', 'doi': 'https://doi.org/10.1080/10826084.2021.1958865', 'mag': '3189390687', 'pmid': 'https://pubmed.ncbi.nlm.nih.gov/34338612'} | G284: en | H284: article | I284: [] | J284: 1 | K284: 15 | L284: 0.961 | M284: 6 | N284: {'value': 0.76459854, 'is_in_top_1_percent': False, 'is_in_top_10_percent': False} | O284: {'min': 90, 'max': 97} | P284: {'volume': '56', 'issue': '13', 'first_page': '1951', 'last_page': '1961'} | Q284: [{'id': 'https://metadata.un.org/sdg/1', 'display_name': 'No poverty', 'score': 0.7900000214576721}] | R284: [{'year': 2025, 'cited_by_count': 1}, {'year': 2024, 'cited_by_count': 1}, {'year': 2023, 'cited_by_count': 4}]
A285: https://openalex.org/W4239423526 | B285: https://doi.org/10.1017/s0144686x21000477 | C285: Cultural generativity in perspective: motivations of older Jewish volunteers | D285: 2021 | E285: 44308 | F285: {'openalex': 'https://openalex.org/W4239423526', 'doi': 'https://doi.org/10.1017/s0144686x21000477'} | G285: en | H285: article | I285: [] | J285: 2 | K285: 3 | L285: 0.53345883 | M285: 6 | N285: {'value': 0.71351001, 'is_in_top_1_percent': False, 'is_in_top_10_percent': False} | O285: {'min': 89, 'max': 96} | P285: {'volume': '43', 'issue': '1', 'first_page': '203', 'last_page': '221'} | Q285: [{'score': 0.5400000214576721, 'id': 'https://metadata.un.org/sdg/10', 'display_name': 'Reduced inequalities'}, {'score': 0.5099999904632568, 'id': 'https://metadata.un.org/sdg/16', 'display_name': 'Peace, Justice and strong institutions'}] | R285: [{'year': 2025, 'cited_by_count': 2}, {'year': 2024, 'cited_by_count': 2}, {'year': 2023, 'cited_by_count': 1}, {'year': 2022, 'cited_by_count': 1}]
A286: https://openalex.org/W3165746017 | B286: https://doi.org/10.1080/09540121.2021.1929813 | C286: Tobacco smoking and HIV-related immunologic and virologic response among individuals of the Canadian HIV Observational Cohort (CANOC) | D286: 2021 | E286: 44348 | F286: {'openalex': 'https://openalex.org/W3165746017', 'doi': 'https://doi.org/10.1080/09540121.2021.1929813', 'mag': '3165746017', 'pmid': 'https://pubmed.ncbi.nlm.nih.gov/34074181'} | G286: en | H286: article | I286: [] | J286: 1 | K286: 16 | L286: 0.386 | M286: 6 | N286: {'value': 0.62683995, 'is_in_top_1_percent': False, 'is_in_top_10_percent': False} | O286: {'min': 90, 'max': 97} | P286: {'volume': '34', 'issue': '8', 'first_page': '982', 'last_page': '991'} | Q286: [{'score': 0.9100000262260437, 'display_name': 'Good health and well-being', 'id': 'https://metadata.un.org/sdg/3'}] | R286: [{'year': 2024, 'cited_by_count': 1}, {'year': 2023, 'cited_by_count': 3}, {'year': 2022, 'cited_by_count': 2}]
A287: https://openalex.org/W4390022862 | B287: https://doi.org/10.1093/fsr/owad048 | C287: Corpse identification in mass disasters and other violence: the ethical challenges of a humanitarian approach | D287: 2023 | E287: 45279 | F287: {'openalex': 'https://openalex.org/W4390022862', 'doi': 'https://doi.org/10.1093/fsr/owad048', 'pmid': 'https://pubmed.ncbi.nlm.nih.gov/38545402'} | G287: en | H287: article | I287: [] | J287: 4 | K287: 3 | L287: 9.493 | M287: 6 | N287: {'value': 0.97490246, 'is_in_top_1_percent': False, 'is_in_top_10_percent': True} | O287: {'min': 94, 'max': 98} | P287: {'volume': '9', 'issue': '1', 'first_page': 'owad048', 'last_page': 'owad048'} | Q287: [{'score': 0.75, 'display_name': 'Peace, Justice and strong institutions', 'id': 'https://metadata.un.org/sdg/16'}] | R287: [{'year': 2025, 'cited_by_count': 4}, {'year': 2024, 'cited_by_count': 2}]
A288: https://openalex.org/W4307848427 | B288: https://doi.org/10.1177/08862605221118611 | C288: Prevalence and Social-Structural Correlates of Gender-Based Violence Against Women Living With HIV in Metro Vancouver, Canada | D288: 2022 | E288: 44866 | F288: {'openalex': 'https://openalex.org/W4307848427', 'doi': 'https://doi.org/10.1177/08862605221118611', 'pmid': 'https://pubmed.ncbi.nlm.nih.gov/36317864'} | G288: en | H288: article | I288: [] | J288: 1 | K288: 9 | L288: 1.8952 | M288: 6 | N288: {'value': 0.88619638, 'is_in_top_1_percent': False, 'is_in_top_10_percent': False} | O288: {'min': 94, 'max': 99} | P288: {'volume': '38', 'issue': '5-6', 'first_page': '4562', 'last_page': '4588'} | Q288: [{'score': 0.7699999809265137, 'id': 'https://metadata.un.org/sdg/5', 'display_name': 'Gender equality'}] | R288: [{'year': 2026, 'cited_by_count': 1}, {'year': 2024, 'cited_by_count': 3}, {'year': 2023, 'cited_by_count': 2}]
A289: https://openalex.org/W3041239410 | B289: https://doi.org/10.1007/s10584-020-02777-4 | C289: Unveiling assumptions through interdisciplinary scrutiny: Observations from the German Priority Program on Climate Engineering (SPP 1689) | D289: 2020 | E289: 44023 | F289: {'openalex': 'https://openalex.org/W3041239410', 'doi': 'https://doi.org/10.1007/s10584-020-02777-4', 'mag': '3041239410'} | G289: en | H289: article | I289: [] | J289: 3 | K289: 8 | L289: 0.5006 | M289: 6 | N289: {'value': 0.66767395, 'is_in_top_1_percent': False, 'is_in_top_10_percent': False} | O289: {'min': 90, 'max': 97} | P289: {'volume': '162', 'issue': '1', 'first_page': '57', 'last_page': '66'} | Q289: [{'id': 'https://metadata.un.org/sdg/13', 'score': 0.8299999833106995, 'display_name': 'Climate action'}] | R289: [{'year': 2024, 'cited_by_count': 1}, {'year': 2021, 'cited_by_count': 2}, {'year': 2020, 'cited_by_count': 3}]
A290: https://openalex.org/W4380446312 | B290: https://doi.org/10.1215/00219118-10849752 | C290: Public Camp Orders and the Power of Microstructures in the Thai-Burmese Borderland | D290: 2023 | E290: 45090 | F290: {'openalex': 'https://openalex.org/W4380446312', 'doi': 'https://doi.org/10.1215/00219118-10849752'} | G290: en | H290: article | I290: [] | J290: 1 | K290: 1 | L290: 6.284 | M290: 6 | N290: {'value': 0.96235029, 'is_in_top_1_percent': False, 'is_in_top_10_percent': True} | O290: {'min': 89, 'max': 97} | P290: {'volume': '82', 'issue': '3', 'first_page': '497', 'last_page': '499'} | Q290: [] | R290: [{'year': 2025, 'cited_by_count': 1}, {'year': 2024, 'cited_by_count': 3}, {'year': 2023, 'cited_by_count': 1}, {'year': 2022, 'cited_by_count': 1}]
A291: https://openalex.org/W4386151837 | B291: https://doi.org/10.1002/gps.5985 | C291: Participatory action research: An exploration from a Freirean perspective of research involving people with dementia | D291: 2023 | E291: 45139 | F291: {'openalex': 'https://openalex.org/W4386151837', 'doi': 'https://doi.org/10.1002/gps.5985', 'pmid': 'https://pubmed.ncbi.nlm.nih.gov/37622384'} | G291: en | H291: article | I291: [] | J291: 1 | K291: 5 | L291: 4.7955 | M291: 5 | N291: {'value': 0.95247281, 'is_in_top_1_percent': False, 'is_in_top_10_percent': True} | O291: {'min': 89, 'max': 97} | P291: {'volume': '38', 'issue': '8', 'first_page': 'e5985', 'last_page': 'e5985'} | Q291: [{'id': 'https://metadata.un.org/sdg/10', 'display_name': 'Reduced inequalities', 'score': 0.6200000047683716}] | R291: [{'year': 2025, 'cited_by_count': 3}, {'year': 2024, 'cited_by_count': 1}, {'year': 2023, 'cited_by_count': 1}]
A292: https://openalex.org/W4200567016 | B292: https://doi.org/10.5206/ijoh.2022.1.13455 | C292: Hospital-to-Shelter/Housing Interventions for Persons Experiencing Homelessness | D292: 2021 | E292: 44538 | F292: {'openalex': 'https://openalex.org/W4200567016', 'doi': 'https://doi.org/10.5206/ijoh.2022.1.13455'} | G292: en | H292: article | I292: [] | J292: 3 | K292: 8 | L292: 0.5708 | M292: 5 | N292: {'value': 0.7610751, 'is_in_top_1_percent': False, 'is_in_top_10_percent': False} | O292: {'min': 89, 'max': 97} | P292: {'volume': '2', 'issue': '1', 'first_page': '136', 'last_page': '151'} | Q292: [] | R292: [{'year': 2025, 'cited_by_count': 3}, {'year': 2023, 'cited_by_count': 1}, {'year': 2022, 'cited_by_count': 1}]
A293: https://openalex.org/W4309456561 | B293: https://doi.org/10.3390/nu14224882 | C293: Dietary Intake and the Neighbourhood Environment in the BC Generations Project | D293: 2022 | E293: 44883 | F293: {'openalex': 'https://openalex.org/W4309456561', 'doi': 'https://doi.org/10.3390/nu14224882', 'pmid': 'https://pubmed.ncbi.nlm.nih.gov/36432566'} | G293: en | H293: article | I293: [] | J293: 1 | K293: 4 | L293: 0.7832 | M293: 5 | N293: {'value': 0.73052664, 'is_in_top_1_percent': False, 'is_in_top_10_percent': False} | O293: {'min': 90, 'max': 99} | P293: {'volume': '14', 'issue': '22', 'first_page': '4882', 'last_page': '4882'} | Q293: [{'score': 0.7799999713897705, 'display_name': 'No poverty', 'id': 'https://metadata.un.org/sdg/1'}] | R293: [{'year': 2026, 'cited_by_count': 1}, {'year': 2025, 'cited_by_count': 3}, {'year': 2024, 'cited_by_count': 1}]
A294: https://openalex.org/W3117901711 | B294: https://doi.org/10.1007/978-3-030-57089-7_12 | C294: Advancing the Concept of Resilience for Older Adults Who Are Experiencing Homelessness | D294: 2020 | E294: 43831 | F294: {'openalex': 'https://openalex.org/W3117901711', 'doi': 'https://doi.org/10.1007/978-3-030-57089-7_12', 'mag': '3117901711'} | G294: en | H294: book-chapter | I294: [] | J294: 3 | K294: 3 | L294: 1.6201 | M294: 5 | N294: {'value': 0.88353193, 'is_in_top_1_percent': False, 'is_in_top_10_percent': False} | O294: {'min': 89, 'max': 98} | P294: {'volume': None, 'issue': None, 'first_page': '245', 'last_page': '268'} | Q294: [] | R294: [{'year': 2025, 'cited_by_count': 4}, {'year': 2023, 'cited_by_count': 1}]
A295: https://openalex.org/W3201566118 | B295: https://doi.org/10.1016/j.jadr.2021.100229 | C295: Psychometric properties and correlates of the Beck Depression Inventory in a community-based and homeless or precariously housed sample | D295: 2021 | E295: 44449 | F295: {'openalex': 'https://openalex.org/W3201566118', 'doi': 'https://doi.org/10.1016/j.jadr.2021.100229', 'mag': '3201566118'} | G295: en | H295: article | I295: [] | J295: 1 | K295: 14 | L295: 0.4218 | M295: 5 | N295: {'value': 0.66794147, 'is_in_top_1_percent': False, 'is_in_top_10_percent': False} | O295: {'min': 94, 'max': 97} | P295: {'volume': '6', 'issue': None, 'first_page': '100229', 'last_page': '100229'} | Q295: [{'display_name': 'No poverty', 'score': 0.7300000190734863, 'id': 'https://metadata.un.org/sdg/1'}] | R295: [{'year': 2025, 'cited_by_count': 3}, {'year': 2023, 'cited_by_count': 2}]
... A313: https://openalex.org/W4387310596 | B313: https://doi.org/10.1177/07311214231193355 | C313: Moral Panic and Electric Micromobilities: Seeking Space for Mobility Justice | D313: 2023 | E313: 45202 | F313: {'openalex': 'https://openalex.org/W4387310596', 'doi': 'https://doi.org/10.1177/07311214231193355'} | G313: en | H313: article | I313: [] | J313: 1 | K313: 7 | L313: 2.9024 | M313: 5 | N313: {'value': 0.91875391, 'is_in_top_1_percent': False, 'is_in_top_10_percent': True} | O313: {'min': 90, 'max': 98} | P313: {'volume': '67', 'issue': '1-3', 'first_page': '83', 'last_page': '108'} | Q313: [{'score': 0.6100000143051147, 'id': 'https://metadata.un.org/sdg/10', 'display_name': 'Reduced inequalities'}] | R313: [{'year': 2025, 'cited_by_count': 4}, {'year': 2024, 'cited_by_count': 1}]
A314: https://openalex.org/W4210576129 | B314: https://doi.org/10.1101/2022.02.03.479041 | C314: Science in motion: A qualitative analysis of journalistsâ€™ use and perception of preprints | D314: 2022 | E314: 44596 | F314: {'openalex': 'https://openalex.org/W4210576129', 'doi': 'https://doi.org/10.1101/2022.02.03.479041'} | G314: en | H314: preprint | I314: [] | J314: 2 | K314: 5 | M314: 5 | P314: {'volume': None, 'issue': None, 'first_page': None, 'last_page': None} | Q314: [{'score': 0.4300000071525574, 'id': 'https://metadata.un.org/sdg/3', 'display_name': 'Good health and well-being'}] | R314: [{'year': 2025, 'cited_by_count': 1}, {'year': 2024, 'cited_by_count': 3}, {'year': 2022, 'cited_by_count': 1}]
A315: https://openalex.org/W3092929609 | B315: https://doi.org/10.1017/s0008423920000888 | C315: Comparing Ambiguities: Municipalities, Francophone Minority Communities and Immigration in Canada | D315: 2021 | E315: 44215 | F315: {'openalex': 'https://openalex.org/W3092929609', 'doi': 'https://doi.org/10.1017/s0008423920000888', 'mag': '3092929609'} | G315: en | H315: article | I315: [] | J315: 1 | K315: 1 | L315: 0.9806 | M315: 5 | N315: {'value': 0.72346083, 'is_in_top_1_percent': False, 'is_in_top_10_percent': False} | O315: {'min': 89, 'max': 96} | P315: {'volume': '54', 'issue': '1', 'first_page': '75', 'last_page': '95'} | Q315: [{'score': 0.6700000166893005, 'display_name': 'Reduced inequalities', 'id': 'https://metadata.un.org/sdg/10'}] | R315: [{'year': 2025, 'cited_by_count': 1}, {'year': 2023, 'cited_by_count': 2}, {'year': 2022, 'cited_by_count': 1}, {'year': 2021, 'cited_by_count': 1}]
A316: https://openalex.org/W3123433566 | B316: https://doi.org/10.1111/hsc.13289 | C316: A paradox of need: Gaps in access to dental care among people who use drugs in Canada's publicly funded healthcare system | D316: 2021 | E316: 44221 | F316: {'openalex': 'https://openalex.org/W3123433566', 'doi': 'https://doi.org/10.1111/hsc.13289', 'mag': '3123433566', 'pmid': 'https://pubmed.ncbi.nlm.nih.gov/33491849'} | G316: en | H316: article | I316: [] | J316: 1 | K316: 5 | L316: 0.3844 | M316: 5 | N316: {'value': 0.62475264, 'is_in_top_1_percent': False, 'is_in_top_10_percent': False} | O316: {'min': 89, 'max': 97} | P316: {'volume': '29', 'issue': '6', 'first_page': '1799', 'last_page': '1806'} | Q316: [{'score': 0.75, 'id': 'https://metadata.un.org/sdg/1', 'display_name': 'No poverty'}] | R316: [{'year': 2025, 'cited_by_count': 3}, {'year': 2024, 'cited_by_count': 1}, {'year': 2022, 'cited_by_count': 1}]
A317: https://openalex.org/W4312071469 | B317: https://doi.org/10.33423/jhetp.v22i16.5615 | C317: Navigating Colonial Space: A Case Study of an Indigenous Student-Led Decolonial Movement in Canadian Higher Education | D317: 2022 | E317: 44889 | F317: {'openalex': 'https://openalex.org/W4312071469', 'doi': 'https://doi.org/10.33423/jhetp.v22i16.5615'} | G317: en | H317: article | I317: [] | J317: 1 | K317: 3 | L317: 2.8492 | M317: 5 | N317: {'value': 0.92074098, 'is_in_top_1_percent': False, 'is_in_top_10_percent': True} | O317: {'min': 91, 'max': 96} | P317: {'volume': '22', 'issue': '16', 'first_page': None, 'last_page': None} | Q317: [{'score': 0.47999998927116394, 'id': 'https://metadata.un.org/sdg/17', 'display_name': 'Partnerships for the goals'}] | R317: [{'year': 2025, 'cited_by_count': 1}, {'year': 2024, 'cited_by_count': 2}, {'year': 2023, 'cited_by_count': 2}]
A318: https://openalex.org/W4224287928 | B318: https://doi.org/10.3390/rel13040363 | C318: Waking up from Delusion: Mindfulness (Sati) and Right Mind-and-Heart (Bodhicitta) for Educating Activists | D318: 2022 | E318: 44666 | F318: {'openalex': 'https://openalex.org/W4224287928', 'doi': 'https://doi.org/10.3390/rel13040363'} | G318: en | H318: article | I318: [] | J318: 1 | K318: 3 | L318: 0.9383 | M318: 5 | N318: {'value': 0.73333043, 'is_in_top_1_percent': False, 'is_in_top_10_percent': False} | O318: {'min': 89, 'max': 96} | P318: {'volume': '13', 'issue': '4', 'first_page': '363', 'last_page': '363'} | Q318: [{'score': 0.6800000071525574, 'id': 'https://metadata.un.org/sdg/13', 'display_name': 'Climate action'}] | R318: [{'year': 2025, 'cited_by_count': 2}, {'year': 2024, 'cited_by_count': 2}, {'year': 2023, 'cited_by_count': 1}]
A319: https://openalex.org/W4393133250 | B319: https://doi.org/10.1007/978-3-031-47044-8_5 | C319: The Anthropocene Subject and Emancipation: The Challenge of â€œEmancipatoryâ€ Pedagogy in an Era of Climate Crisis | D319: 2024 | E319: 45292 | F319: {'openalex': 'https://openalex.org/W4393133250', 'doi': 'https://doi.org/10.1007/978-3-031-47044-8_5'} | G319: en | H319: book-chapter | I319: [] | J319: 1 | K319: 1 | L319: 5.4051 | M319: 5 | N319: {'value': 0.95998548, 'is_in_top_1_percent': False, 'is_in_top_10_percent': True} | O319: {'min': 96, 'max': 100} | P319: {'volume': None, 'issue': None, 'first_page': '87', 'last_page': '116'} | Q319: [{'score': 0.5799999833106995, 'display_name': 'Climate action', 'id': 'https://metadata.un.org/sdg/13'}] | R319: [{'year': 2026, 'cited_by_count': 2}, {'year': 2025, 'cited_by_count': 3}]
A320: https://openalex.org/W4393332756 | B320: https://doi.org/10.1016/j.marpol.2024.106116 | C320: Diversity, challenges, and opportunities of Fishery Improvement Projects in the Latin America and the Caribbean region | D320: 2024 | E320: 45380 | F320: {'openalex': 'https://openalex.org/W4393332756', 'doi': 'https://doi.org/10.1016/j.marpol.2024.106116'} | G320: en | H320: article | I320: [] | J320: 2 | K320: 6 | L320: 6.8497 | M320: 5 | N320: {'value': 0.9647513, 'is_in_top_1_percent': False, 'is_in_top_10_percent': True} | O320: {'min': 94, 'max': 99} | P320: {'volume': '163', 'issue': None, 'first_page': '106116', 'last_page': '106116'} | Q320: [] | R320: [{'year': 2026, 'cited_by_count': 1}, {'year': 2025, 'cited_by_count': 2}, {'year': 2024, 'cited_by_count': 2}]
A321: https://openalex.org/W4200143230 | B321: https://doi.org/10.1108/ijssp-09-2021-0245 | C321: Robo-Advice (RA): implications for the sociology of the professions | D321: 2021 | E321: 44560 | F321: {'openalex': 'https://openalex.org/W4200143230', 'doi': 'https://doi.org/10.1108/ijssp-09-2021-0245'} | G321: en | H321: article | I321: [] | J321: 1 | K321: 2 | L321: 0.8578 | M321: 5 | N321: {'value': 0.79054109, 'is_in_top_1_percent': False, 'is_in_top_10_percent': False} | O321: {'min': 89, 'max': 97} | P321: {'volume': '43', 'issue': '1/2', 'first_page': '17', 'last_page': '32'} | Q321: [{'id': 'https://metadata.un.org/sdg/9', 'score': 0.5199999809265137, 'display_name': 'Industry, innovation and infrastructure'}] | R321: [{'year': 2025, 'cited_by_count': 1}, {'year': 2024, 'cited_by_count': 3}, {'year': 2023, 'cited_by_count': 1}]
A322: https://openalex.org/W4220988406 | B322: https://doi.org/10.5204/mcj.2852 | C322: How Google Autocomplete Algorithms about Conspiracy Theorists Mislead the Public | D322: 2022 | E322: 44641 | F322: {'openalex': 'https://openalex.org/W4220988406', 'doi': 'https://doi.org/10.5204/mcj.2852'} | G322: en | H322: article | I322: [] | J322: 1 | K322: 4 | L322: 1.8952 | M322: 5 | N322: {'value': 0.87702342, 'is_in_top_1_percent': False, 'is_in_top_10_percent': False} | O322: {'min': 89, 'max': 96} | P322: {'volume': '25', 'issue': '1', 'first_page': None, 'last_page': None} | Q322: [{'display_name': 'Peace, Justice and strong institutions', 'score': 0.6399999856948853, 'id': 'https://metadata.un.org/sdg/16'}] | R322: [{'year': 2025, 'cited_by_count': 1}, {'year': 2024, 'cited_by_count': 1}, {'year': 2023, 'cited_by_count': 2}, {'year': 2022, 'cited_by_count': 1}]
A323: https://openalex.org/W4327725286 | B323: https://doi.org/10.5117/9789463720762 | C323: The Propagation of Misinformation in Social Media | D323: 2023 | E323: 45002 | F323: {'openalex': 'https://openalex.org/W4327725286', 'doi': 'https://doi.org/10.5117/9789463720762'} | G323: en | H323: book | I323: [] | J323: 3 | K323: 1 | L323: 1.6521 | M323: 4 | N323: {'value': 0.85024155, 'is_in_top_1_percent': False, 'is_in_top_10_percent': False} | O323: {'min': 89, 'max': 96} | P323: {'volume': None, 'issue': None, 'first_page': None, 'last_page': None} | Q323: [{'score': 0.7099999785423279, 'display_name': 'Reduced inequalities', 'id': 'https://metadata.un.org/sdg/10'}] | R323: [{'year': 2025, 'cited_by_count': 1}, {'year': 2024, 'cited_by_count': 2}, {'year': 2023, 'cited_by_count': 1}]
A324: https://openalex.org/W3159459105 | B324: https://doi.org/10.1007/978-3-030-64171-9_1 | C324: Overview and Evidence-Based Recommendations to Address Health and Human Rights Inequities Faced by Sex Workers | D324: 2021 | E324: 44197 | F324: {'openalex': 'https://openalex.org/W3159459105', 'doi': 'https://doi.org/10.1007/978-3-030-64171-9_1', 'mag': '3159459105'} | G324: en | H324: book-chapter | I324: [] | J324: 2 | K324: 4 | L324: 3.5616 | M324: 4 | N324: {'value': 0.92314183, 'is_in_top_1_percent': False, 'is_in_top_10_percent': True} | O324: {'min': 94, 'max': 96} | P324: {'volume': None, 'issue': None, 'first_page': '1', 'last_page': '11'} | Q324: [{'display_name': 'Gender equality', 'score': 0.6399999856948853, 'id': 'https://metadata.un.org/sdg/5'}] | R324: [{'year': 2025, 'cited_by_count': 2}, {'year': 2024, 'cited_by_count': 2}]
A325: https://openalex.org/W4312756171 | B325: https://doi.org/10.1007/978-3-031-05020-6 | C325: Media Governance | D325: 2022 | E325: 44562 | F325: {'openalex': 'https://openalex.org/W4312756171', 'doi': 'https://doi.org/10.1007/978-3-031-05020-6'} | G325: en | H325: book | I325: [] | J325: 2 | K325: 2 | L325: 2.8283 | M325: 4 | N325: {'value': 0.93141026, 'is_in_top_1_percent': False, 'is_in_top_10_percent': True} | O325: {'min': 97, 'max': 98} | P325: {'volume': None, 'issue': None, 'first_page': None, 'last_page': None} | Q325: [] | R325: [{'year': 2025, 'cited_by_count': 4}]
A326: https://openalex.org/W4311057734 | B326: https://doi.org/10.1007/s10796-022-10359-1 | C326: Does Social Capital Arise from Enterprise or Public Social Media Use? A Model of Social Media Antecedents and Consequences | D326: 2022 | E326: 44896 | F326: {'openalex': 'https://openalex.org/W4311057734', 'doi': 'https://doi.org/10.1007/s10796-022-10359-1'} | G326: en | H326: article | I326: [] | J326: 2 | K326: 3 | L326: 1.1963 | M326: 4 | N326: {'value': 0.82268061, 'is_in_top_1_percent': False, 'is_in_top_10_percent': False} | O326: {'min': 94, 'max': 96} | P326: {'volume': '25', 'issue': '6', 'first_page': '2353', 'last_page': '2375'} | Q326: [] | R326: [{'year': 2025, 'cited_by_count': 2}, {'year': 2024, 'cited_by_count': 2}]
... A394: https://openalex.org/W4287250160 | B394: https://doi.org/10.5281/zenodo.5495559 | C394: Research transparency: Less about rigor and more about responsibility | D394: 2021 | E394: 44286 | F394: {'openalex': 'https://openalex.org/W4287250160', 'doi': 'https://doi.org/10.5281/zenodo.5495559'} | G394: en | H394: article | I394: [] | J394: 1 | K394: 1 | L394: 0.3844 | M394: 3 | N394: {'value': 0.67444746, 'is_in_top_1_percent': False, 'is_in_top_10_percent': False} | O394: {'min': 91, 'max': 96} | P394: {'volume': None, 'issue': None, 'first_page': None, 'last_page': None} | Q394: [] | R394: [{'year': 2025, 'cited_by_count': 1}, {'year': 2022, 'cited_by_count': 2}]
A395: https://openalex.org/W4393072836 | B395: https://doi.org/10.1111/sjtg.12539 | C395: Guest Editorial: The social life of Chinese infrastructures in Southeast Asia | D395: 2024 | E395: 45373 | F395: {'openalex': 'https://openalex.org/W4393072836', 'doi': 'https://doi.org/10.1111/sjtg.12539'} | G395: en | H395: editorial | I395: [] | J395: 2 | K395: 2 | L395: 11.940961 | M395: 3 | N395: {'value': 0.9622204, 'is_in_top_1_percent': False, 'is_in_top_10_percent': True} | O395: {'min': 96, 'max': 97} | P395: {'volume': '45', 'issue': '2', 'first_page': '169', 'last_page': '180'} | Q395: [{'id': 'https://metadata.un.org/sdg/9', 'display_name': 'Industry, innovation and infrastructure', 'score': 0.5400000214576721}]
A396: https://openalex.org/W3091039029 | B396: https://doi.org/10.1177/0169796x20962878 | C396: Developing State Capacity: The Missing Variable for Corporate Social Responsibility? | D396: 2020 | E396: 44075 | F396: {'openalex': 'https://openalex.org/W3091039029', 'doi': 'https://doi.org/10.1177/0169796x20962878', 'mag': '3091039029'} | G396: en | H396: article | I396: [] | J396: 1 | K396: 1 | L396: 1.3712 | M396: 2 | N396: {'value': 0.85394727, 'is_in_top_1_percent': False, 'is_in_top_10_percent': False} | O396: {'min': 89, 'max': 94} | P396: {'volume': '36', 'issue': '3', 'first_page': '290', 'last_page': '311'} | Q396: [] | R396: [{'year': 2022, 'cited_by_count': 1}, {'year': 2020, 'cited_by_count': 1}]
A397: https://openalex.org/W4403352964 | B397: https://doi.org/10.1016/j.jcrimjus.2024.102299 | C397: To tent and protect: Homeless encampments as â€œprotective facilitiesâ€ | D397: 2024 | E397: 45577 | F397: {'openalex': 'https://openalex.org/W4403352964', 'doi': 'https://doi.org/10.1016/j.jcrimjus.2024.102299'} | G397: en | H397: article | I397: [] | J397: 2 | K397: 6 | L397: 2.3412 | M397: 2 | N397: {'value': 0.9037275, 'is_in_top_1_percent': False, 'is_in_top_10_percent': True} | O397: {'min': 91, 'max': 99} | P397: {'volume': '95', 'issue': None, 'first_page': '102299', 'last_page': '102299'} | Q397: [] | R397: [{'year': 2026, 'cited_by_count': 1}, {'year': 2025, 'cited_by_count': 1}]
A398: https://openalex.org/W4381432484 | B398: https://doi.org/10.2478/njms-2023-0003 | C398: Guarding informationâ€™s Other: Theorising beyond information and communications technologies for disinformation | D398: 2023 | E398: 45078 | F398: {'openalex': 'https://openalex.org/W4381432484', 'doi': 'https://doi.org/10.2478/njms-2023-0003'} | G398: en | H398: article | I398: [] | J398: 1 | K398: 1 | L398: 1.161 | M398: 2 | N398: {'value': 0.82566845, 'is_in_top_1_percent': False, 'is_in_top_10_percent': False} | O398: {'min': 95, 'max': 96} | P398: {'volume': '5', 'issue': '1', 'first_page': '32', 'last_page': '48'} | Q398: [] | R398: [{'year': 2025, 'cited_by_count': 2}]
A399: https://openalex.org/W4385949575 | B399: https://doi.org/10.1080/15614263.2023.2246620 | C399: In the eye of the powerholder: examining the relationship between uniform and accoutrement combinations and police self-legitimacy | D399: 2023 | E399: 45155 | F399: {'openalex': 'https://openalex.org/W4385949575', 'doi': 'https://doi.org/10.1080/15614263.2023.2246620'} | G399: en | H399: article | I399: [] | J399: 2 | K399: 2 | L399: 2.4873 | M399: 2 | N399: {'value': 0.90661437, 'is_in_top_1_percent': False, 'is_in_top_10_percent': True} | O399: {'min': 90, 'max': 95} | P399: {'volume': '25', 'issue': '3', 'first_page': '358', 'last_page': '375'} | Q399: [{'score': 0.7099999785423279, 'display_name': 'Gender equality', 'id': 'https://metadata.un.org/sdg/5'}] | R399: [{'year': 2025, 'cited_by_count': 1}, {'year': 2024, 'cited_by_count': 1}]
A400: https://openalex.org/W4320855876 | B400: https://doi.org/10.1080/13854046.2023.2178513 | C400: Using serial position effects to investigate memory dysfunction in homeless and precariously housed persons | D400: 2023 | E400: 44972 | F400: {'openalex': 'https://openalex.org/W4320855876', 'doi': 'https://doi.org/10.1080/13854046.2023.2178513', 'pmid': 'https://pubmed.ncbi.nlm.nih.gov/36790121'} | G400: en | H400: article | I400: [] | J400: 1 | K400: 18 | L400: 0.8941 | M400: 2 | N400: {'value': 0.74926747, 'is_in_top_1_percent': False, 'is_in_top_10_percent': False} | O400: {'min': 94, 'max': 96} | P400: {'volume': '37', 'issue': '8', 'first_page': '1710', 'last_page': '1727'} | Q400: [{'display_name': 'No poverty', 'score': 0.5, 'id': 'https://metadata.un.org/sdg/1'}] | R400: [{'year': 2024, 'cited_by_count': 2}]
A401: https://openalex.org/W4403500157 | B401: https://doi.org/10.26522/ssj.v18i3.4801 | C401: Unpacking Mental Health: Intersectionality-informed Approaches to Upholding Human Rights and Realizing Social Justice (Guest Editors' Introduction) | D401: 2024 | E401: 45581 | F401: {'openalex': 'https://openalex.org/W4403500157', 'doi': 'https://doi.org/10.26522/ssj.v18i3.4801'} | G401: en | H401: article | I401: [] | J401: 2 | K401: 3 | L401: 2.1129 | M401: 2 | N401: {'value': 0.88278959, 'is_in_top_1_percent': False, 'is_in_top_10_percent': False} | O401: {'min': 91, 'max': 99} | P401: {'volume': '18', 'issue': '3', 'first_page': '376', 'last_page': '398'} | Q401: [{'display_name': 'Reduced inequalities', 'score': 0.44999998807907104, 'id': 'https://metadata.un.org/sdg/10'}] | R401: [{'year': 2026, 'cited_by_count': 1}, {'year': 2025, 'cited_by_count': 1}]
A402: https://openalex.org/W4390572093 | B402: https://doi.org/10.1016/j.jpsychires.2024.01.003 | C402: Relationship between drug-induced movement disorders and psychosis in adults living in precarious housing or homelessness | D402: 2024 | E402: 45294 | F402: {'openalex': 'https://openalex.org/W4390572093', 'doi': 'https://doi.org/10.1016/j.jpsychires.2024.01.003', 'pmid': 'https://pubmed.ncbi.nlm.nih.gov/38185074'} | G402: en | H402: article | I402: [] | J402: 1 | K402: 15 | L402: 0.8168 | M402: 2 | N402: {'value': 0.69470161, 'is_in_top_1_percent': False, 'is_in_top_10_percent': False} | O402: {'min': 91, 'max': 99} | P402: {'volume': '170', 'issue': None, 'first_page': '290', 'last_page': '296'} | Q402: [{'display_name': 'Sustainable cities and communities', 'score': 0.4000000059604645, 'id': 'https://metadata.un.org/sdg/11'}] | R402: [{'year': 2026, 'cited_by_count': 1}, {'year': 2025, 'cited_by_count': 1}]
...

Sheet rio results
A1: Authors | B1: Author full names | C1: Author(s) ID | D1: Title | E1: Year | F1: Source title | G1: Volume | H1: Issue | I1: Art. No. | J1: Page start | K1: Page end | L1: Cited by | M1: DOI | N1: Link | O1: Affiliations | P1: Authors with affiliations | Q1: Correspondence Address | R1: Editors | S1: Publisher | T1: ISSN | U1: ISBN | V1: CODEN | W1: PubMed ID | X1: Language of Original Document | Y1: Abbreviated Source Title | Z1: Document Type | AA1: Publication Stage | AB1: Open Access | AC1: Source | AD1: EID
A2: Sachs, J.D.; S Abdool Karim, S.S.A.; Aknin, L.B.; Allen, J.; Brosbøl, K.; Colombo, F.; Barron, G.C.; Espinosa, M.F.; Gaspar, V.; Gaviria, A.; Haines, A.; Hotez, P.J.; Koundouri, P.; Bascuñán, F.L.; Lee, J.-K.; Pate, M.A.; Ramos, G.; Reddy, K.S.; Serageldin, I.; Thwaites, J.; Vike-Freiberga, V.; Wang, C.; Were, M.K.; Xue, L.; Bahadur, C.; Bottazzi, M.E.; Bullen, C.; Laryea-Adjei, G.; Ben Amor, Y.B.; Karadağ, O.; Lafortune, G.; Torres, E.; Barredo, L.; Bartels, J.G.E.; Joshi, N.; Hellard, M.; Huynh, U.K.; Khandelwal, S.; Lazarus, J.V.; Michie, S. | B2: Sachs, Jeffrey David (7101926169); S Abdool Karim, Salim Safurdeen S. (57159115100); Aknin, Lara B. (23984324100); Allen, Joseph A. (16834469500); Brosbøl, Kirsten (57219249780); Colombo, Francesca (57222157141); Barron, Gabriela Cuevas (57224643988); Espinosa, Maria Fernanda (57225440135); Gaspar, Vítor (7003585319); Gaviria, Alejandro (6602903221); Haines, Andy P. (19334435800); Hotez, Peter J. (7004958298); Koundouri, Phoebe C. (14060612200); Bascuñán, Felipe Larraín (57883443700); Lee, Jong-koo (25028188800); Pate, Muhammad Ali (36175181000); Ramos, Gabriela (43061495200); Reddy, K. Srinath (35417788900); Serageldin, Ismail (6603772913); Thwaites, John W. (57219255286); Vike-Freiberga, Vaira (26647851600); Wang, Chen (57196394775); Were, Miriam K. (24761349500); Xue, Lan (36350478100); Bahadur, Chandrika (6504617035); Bottazzi, Maria Elena (6603937133); Bullen, Christopher R. (56560797800); Laryea-Adjei, George (15819414000); Ben Amor, Yanis (42160940900); Karadağ, Ozge (37057020400); Lafortune, Guillaume (57218225190); Torres, Emma (58374077200); Barredo, Lauren (57219108849); Bartels, Juliana G.E. (57219255704); Joshi, Neena (59883988200); Hellard, Margaret E. (7004178983); Huynh, Uyen Kim (57039258100); Khandelwal, Shweta (57201619873); Lazarus, J. V. (55431519100); Michie, Susan F. (7004779970) | C2: 7101926169; 57159115100; 23984324100; 16834469500; 57219249780; 57222157141; 57224643988; 57225440135; 7003585319; 6602903221; 19334435800; 7004958298; 14060612200; 57883443700; 25028188800; 36175181000; 43061495200; 35417788900; 6603772913; 57219255286; 26647851600; 57196394775; 24761349500; 36350478100; 6504617035; 6603937133; 56560797800; 15819414000; 42160940900; 37057020400; 57218225190; 58374077200; 57219108849; 57219255704; 59883988200; 7004178983; 57039258100; 57201619873; 55431519100; 7004779970 | D2: The Lancet Commission on lessons for the future from the COVID-19 pandemic | E2: 2022 | F2: The Lancet | G2: 400 | H2: 10359 | J2: 1224 | K2: 1280 | L2: 601 | M2: 10.1016/S0140-6736(22)01585-9 | N2: https://www.scopus.com/inward/record.uri?eid=2-s2.0-85139284208&doi=10.1016%2FS0140-6736%2822%2901585-9&partnerID=40&md5=163f0ab62a00294402fe6fd220cd7bc2 | O2: Center for Sustainable Development, Columbia University, New York, NY, United States; Mailman School of Public Health, New York, NY, United States; Simon Fraser University, Burnaby, BC, Canada; Department of Global Health and Population, Harvard T.H. Chan School of Public Health, Boston, MA, United States; Department of Environmental Health, Harvard T.H. Chan School of Public Health, Boston, MA, United States; Parliamentarians for the Global Goals, Copenhagen, Denmark; Health Division, L'Organisation de Coopération et de Développement Economiques, Paris, Ile-de-France, France; UHC2030, Geneva, Switzerland; Robert Bosch Academy, Berlin, Germany; International Monetary Fund, Washington, D.C., DC, United States; Ministry of National Education, Bogota, Colombia; Department of Public Health, London School of Hygiene & Tropical Medicine, London, United Kingdom; Department of Population Health, London School of Hygiene & Tropical Medicine, London, United Kingdom; National School of Tropical Medicine, Baylor College of Medicine, Houston, TX, United States; Department of International & European Economic Studies, Athens University of Economics and Business, Athens, Attica, Greece; Department of Technology, Technical University of Denmark, Lyngby, Hovedstaden, Denmark; European Association of Environmental and Resource Economists, Athens, Greece; Department of Economics, Pontificia Universidad Católica de Chile, Santiago, RM, Chile; National Academy of Medicine of Korea, Seoul, Seoul, South Korea; UNESCO United Nations Educational, Scientific and Cultural Organization, Paris, France; Public Health Foundation of India, New Delhi, India; Bibliotheca Alexandrina, Alexandria, Egypt; Monash University, Melbourne, VIC, Australia; Nizami Ganjavi International Center, Baku, Azerbaijan; Beijing Tiantan Hospital, Capital Medical University, Beijing, China; China-Japan Friendship Hospital, Beijing, Beijing, China; Champions of an AIDS-Free Generation in Africa, Nairobi, Kenya; Schwarzman College, Tsinghua University, Beijing, China; The Lancet COVID-19 Commission Regional Task Force: India, New Delhi, India; National Institute for Health Innovation, University of Auckland, Auckland, AUK, New Zealand; UNICEF, New York, NY, United States; Sustainable Development Solutions Network, Paris, France; United Nations, New York, NY, United States; Burnet Institute, Melbourne, VIC, Australia; UNICEF, New York, NY, United States; Instituto de Salud Global de Barcelona, Barcelona, Barcelona, Spain; Centre for Behaviour Change, University College London, London, United Kingdom | P2: Sachs, Jeffrey David, Center for Sustainable Development, Columbia University, New York, NY, United States; S Abdool Karim, Salim Safurdeen S., Mailman School of Public Health, New York, NY, United States; Aknin, Lara B., Simon Fraser University, Burnaby, BC, Canada; Allen, Joseph A., Department of Environmental Health, Harvard T.H. Chan School of Public Health, Boston, MA, United States; Brosbøl, Kirsten, Parliamentarians for the Global Goals, Copenhagen, Denmark; Colombo, Francesca, Health Division, L'Organisation de Coopération et de Développement Economiques, Paris, Ile-de-France, France; Barron, Gabriela Cuevas, UHC2030, Geneva, Switzerland; Espinosa, Maria Fernanda, Robert Bosch Academy, Berlin, Germany; Gaspar, Vítor, International Monetary Fund, Washington, D.C., DC, United States; Gaviria, Alejandro, Ministry of National Education, Bogota, Colombia; Haines, Andy P., Department of Public Health, London School of Hygiene & Tropical Medicine, London, United Kingdom, Department of Population Health, London School of Hygiene & Tropical Medicine, London, United Kingdom; Hotez, Peter J., National School of Tropical Medicine, Baylor College of Medicine, Houston, TX, United States; Koundouri, Phoebe C., Department of International & European Economic Studies, Athens University of Economics and Business, Athens, Attica, Greece, Department of Technology, Technical University of Denmark, Lyngby, Hovedstaden, Denmark, European Association of Environmental and Resource Economists, Athens, Greece; Bascuñán, Felipe Larraín, Department of Economics, Pontificia Universidad Católica de Chile, Santiago, RM, Chile; Lee, Jong-koo, National Academy of Medicine of Korea, Seoul, Seoul, South Korea; Pate, Muhammad Ali, Department of Global Health and Population, Harvard T.H. Chan School of Public Health, Boston, MA, United States; Ramos, Gabriela, UNESCO United Nations Educational, Scientific and Cultural Organization, Paris, France; Reddy, K. Srinath, Public Health Foundation of India, New Delhi, India; Serageldin, Ismail, Bibliotheca Alexandrina, Alexandria, Egypt; Thwaites, John W., Monash University, Melbourne, VIC, Australia; Vike-Freiberga, Vaira, Nizami Ganjavi International Center, Baku, Azerbaijan; Wang, Chen, Beijing Tiantan Hospital, Capital Medical University, Beijing, China, China-Japan Friendship Hospital, Beijing, Beijing, China; Were, Miriam K., Champions of an AIDS-Free Generation in Africa, Nairobi, Kenya; Xue, Lan, Schwarzman College, Tsinghua University, Beijing, China; Bahadur, Chandrika, The Lancet COVID-19 Commission Regional Task Force: India, New Delhi, India; Bottazzi, Maria Elena, National School of Tropical Medicine, Baylor College of Medicine, Houston, TX, United States; Bullen, Christopher R., National Institute for Health Innovation, University of Auckland, Auckland, AUK, New Zealand; Laryea-Adjei, George, UNICEF, New York, NY, United States; Ben Amor, Yanis, Center for Sustainable Development, Columbia University, New York, NY, United States; Karadağ, Ozge, Center for Sustainable Development, Columbia University, New York, NY, United States; Lafortune, Guillaume, Sustainable Development Solutions Network, Paris, France; Torres, Emma, United Nations, New York, NY, United States; Barredo, Lauren, United Nations, New York, NY, United States; Bartels, Juliana G.E., Center for Sustainable Development, Columbia University, New York, NY, United States; Joshi, Neena, United Nations, New York, NY, United States; Hellard, Margaret E., Burnet Institute, Melbourne, VIC, Australia; Huynh, Uyen Kim, UNICEF, New York, NY, United States; Khandelwal, Shweta, Public Health Foundation of India, New Delhi, India; Lazarus, J. V., Instituto de Salud Global de Barcelona, Barcelona, Barcelona, Spain; Michie, Susan F., Centre for Behaviour Change, University College London, London, United Kingdom | Q2: J.D. Sachs; Center for Sustainable Development, Columbia University, New York, United States; email: sachs@columbia.edu | S2: Elsevier B.V. | T2: 01406736; 1474547X | V2: LANCA | W2: 36115368 | X2: English | Y2: Lancet | Z2: Review | AA2: Final | AB2: All Open Access; Green Accepted Open Access; Green Open Access | AC2: Scopus | AD2: 2-s2.0-85139284208
A3: Budhwar, P.; Chowdhury, S.; Wood, G.; Aguinis, H.; Bamber, G.J.; Beltran, J.R.; Boselie, P.; Cooke, F.; Decker, S.; DeNisi, A.; Prasanta K. Dey, P.K.; Guest, D.; Knoblich, A.J.; Malik, A.; Paauwe, J.; Papagiannidis, S.; Patel, C.; Pereira, V.; Ren, S.; Rogelberg, S.; Saunders, M.N.K.; Tung, R.L.; Varma, A. | B3: Budhwar, Pawan S. (6701694690); Chowdhury, Soumyadeb (57201962502); Wood, Geoffrey T. (10043338900); Aguinis, Herman (7006100196); Bamber, Greg J. (6602312369); Beltran, Jose R. (58485320200); Boselie, Paul (8717563000); Cooke, Fang Lee (7102561934); Decker, Stephanie (35832594400); DeNisi, Angelo S. (6602731645); Prasanta K. Dey, Prasanta Kumar (34568899900); Guest, David E. (7005035099); Knoblich, Andrew J. (58486780800); Malik, Ashish (56208258600); Paauwe, Jaap (6507836949); Papagiannidis, Savvas (8848778400); Patel, Charmi (56258661200); Pereira, Vijay Edward (37108422900); Ren, Shuang (51665996800); Rogelberg, Steven G. (6701498798); Saunders, Mark N.K. (7201859502); Tung, Rosalie L. (7004507673); Varma, Arup (7202665999) | C3: 6701694690; 57201962502; 10043338900; 7006100196; 6602312369; 58485320200; 8717563000; 7102561934; 35832594400; 6602731645; 34568899900; 7005035099; 58486780800; 56208258600; 6507836949; 8848778400; 56258661200; 37108422900; 51665996800; 6701498798; 7201859502; 7004507673; 7202665999 | D3: Human resource management in the age of generative artificial intelligence: Perspectives and research directions on ChatGPT | E3: 2023 | F3: Human Resource Management Journal | G3: 33 | H3: 3 | J3: 606 | K3: 659 | L3: 600 | M3: 10.1111/1748-8583.12524 | N3: https://www.scopus.com/inward/record.uri?eid=2-s2.0-85164660060&doi=10.1111%2F1748-8583.12524&partnerID=40&md5=e9c678da5e21f530c252436b62be8bf6 | O3: Aston University, Birmingham, West Midlands, United Kingdom; Information, TBS Business School, Toulouse, Occitanie, France; DAN Department of Management and Organizational Studies, Western University, London, ON, Canada; Cranfield University, Cranfield, Bedfordshire, United Kingdom; University of Bath, Bath, Somerset, United Kingdom; Trinity Business School, Dublin, Leinster, Ireland; GW School of Business, Washington, D.C., United States; Monash University, Melbourne, VIC, Australia; Department of Human Resources & Organizational Behavior, Rutgers School of Business-Camden, Camden, NJ, United States; Department of Human Resource Studies, Tilburg University, Tilburg, Noord-Brabant, Netherlands; Utrecht University School of Governance, Utrecht, Netherlands; Monash University, Melbourne, VIC, Australia; Department of Strategy and International Business, Birmingham Business School, Birmingham, United Kingdom; A. B. Freeman School of Business, New Orleans, LA, United States; Department of Operations and Information Management, Aston Business School, Birmingham, West Midlands, United Kingdom; King’s Business School, London, United Kingdom; Organizational Science, The University of North Carolina at Charlotte, Charlotte, NC, United States; College of Human and Social Futures, Newcastle Business School, Newcastle, NSW, Australia; Newcastle University Business School, United Kingdom, Newcastle, Tyne and Wear, United Kingdom; Henley Business School, Reading, Berkshire, United Kingdom; NEOMA Business School, Mont-Saint-Aignan, Normandie, France; Queen’s Business School, Queen's University Belfast, Belfast, Northern Ireland, United Kingdom; Department of Management, Birmingham Business School, Birmingham, United Kingdom; Simon Fraser University, Burnaby, BC, Canada; Quinlan School of Business, Loyola University Chicago, Chicago, IL, United States | P3: Budhwar, Pawan S., Aston University, Birmingham, West Midlands, United Kingdom; Chowdhury, Soumyadeb, Information, TBS Business School, Toulouse, Occitanie, France; Wood, Geoffrey T., DAN Department of Management and Organizational Studies, Western University, London, ON, Canada, Cranfield University, Cranfield, Bedfordshire, United Kingdom, University of Bath, Bath, Somerset, United Kingdom, Trinity Business School, Dublin, Leinster, Ireland; Aguinis, Herman, GW School of Business, Washington, D.C., United States; Bamber, Greg J., Monash University, Melbourne, VIC, Australia, Department of Human Resources & Organizational Behavior, Rutgers School of Business-Camden, Camden, NJ, United States, Department of Human Resource Studies, Tilburg University, Tilburg, Noord-Brabant, Netherlands; Beltran, Jose R., Department of Human Resources & Organizational Behavior, Rutgers School of Business-Camden, Camden, NJ, United States; Boselie, Paul, Utrecht University School of Governance, Utrecht, Netherlands; Cooke, Fang Lee, Monash University, Melbourne, VIC, Australia; Decker, Stephanie, Department of Strategy and International Business, Birmingham Business School, Birmingham, United Kingdom; DeNisi, Angelo S., A. B. Freeman School of Business, New Orleans, LA, United States; Prasanta K. Dey, Prasanta Kumar, Department of Operations and Information Management, Aston Business School, Birmingham, West Midlands, United Kingdom; Guest, David E., King’s Business School, London, United Kingdom; Knoblich, Andrew J., Organizational Science, The University of North Carolina at Charlotte, Charlotte, NC, United States; Malik, Ashish, College of Human and Social Futures, Newcastle Business School, Newcastle, NSW, Australia; Paauwe, Jaap, Department of Human Resource Studies, Tilburg University, Tilburg, Noord-Brabant, Netherlands; Papagiannidis, Savvas, Newcastle University Business School, United Kingdom, Newcastle, Tyne and Wear, United Kingdom; Patel, Charmi, Henley Business School, Reading, Berkshire, United Kingdom; Pereira, Vijay Edward, NEOMA Business School, Mont-Saint-Aignan, Normandie, France; Ren, Shuang, Queen’s Business School, Queen's University Belfast, Belfast, Northern Ireland, United Kingdom; Rogelberg, Steven G., Organizational Science, The University of North Carolina at Charlotte, Charlotte, NC, United States; Saunders, Mark N.K., Department of Management, Birmingham Business School, Birmingham, United Kingdom; Tung, Rosalie L., Simon Fraser University, Burnaby, BC, Canada; Varma, Arup, Quinlan School of Business, Loyola University Chicago, Chicago, IL, United States | Q3: S. Chowdhury; Information, Operations and Management Sciences Department, TBS Business School, Toulouse, France; email: s.chowdhury@tbs-education.fr | S3: John Wiley and Sons Inc | T3: 9545395 | X3: English | Y3: Hum. Resour. Manage. J. | Z3: Review | AA3: Final | AB3: All Open Access; Green Accepted Open Access; Green Open Access; Hybrid Gold Open Access | AC3: Scopus | AD3: 2-s2.0-85164660060
A4: Capano, G.; Howlett, M.; Jarvis, D.S.L.; Ramesh, M.; Goyal, N. | B4: Capano, Giliberto (23767017600); Howlett, Michael P. (7004315057); Jarvis, Darryl Stuart L. (35758736700); Ramesh, M. (7006248680); Goyal, Nihit (57194183948) | C4: 23767017600; 7004315057; 35758736700; 7006248680; 57194183948 | D4: Mobilizing Policy (In)Capacity to Fight COVID-19: Understanding Variations in State Responses | E4: 2020 | F4: Policy and Society | J4: 285 | K4: 308 | L4: 445 | M4: 10.1080/14494035.2020.1787628 | N4: https://www.scopus.com/inward/record.uri?eid=2-s2.0-85087618935&doi=10.1080%2F14494035.2020.1787628&partnerID=40&md5=22c83a7148d8510ce0cb367510b516ce | O4: Alma Mater Studiorum Università di Bologna, Bologna, BO, Italy; Simon Fraser University, Burnaby, BC, Canada; The Education University of Hong Kong, Hong Kong, Hong Kong; National University of Singapore, Singapore City, Singapore | P4: Capano, Giliberto, Alma Mater Studiorum Università di Bologna, Bologna, BO, Italy; Howlett, Michael P., Simon Fraser University, Burnaby, BC, Canada; Jarvis, Darryl Stuart L., The Education University of Hong Kong, Hong Kong, Hong Kong; Ramesh, M., National University of Singapore, Singapore City, Singapore; Goyal, Nihit, National University of Singapore, Singapore City, Singapore | Q4: G. Capano; University of Bologna, Italy; email: giliberto.capano@unibo.it | S4: Taylor and Francis Ltd. | T4: 14494035 | X4: English | Y4: Policy Soc. | Z4: Article | AA4: Final | AB4: All Open Access; Gold Open Access; Green Accepted Open Access; Green Open Access | AC4: Scopus | AD4: 2-s2.0-85087618935
A5: Motta, M.; Stecula, D.A.; Farhart, C. | B5: Motta, Matthew P. (57200447460); Stecula, Dominik Andrzej (56071614400); Farhart, Christina E. (56004173900) | C5: 57200447460; 56071614400; 56004173900 | D5: How right-leaning media coverage of Covid-19 facilitated the spread of misinformation in the early stages of the pandemic in the U.S. | E5: 2020 | F5: Canadian Journal of Political Science | G5: 53 | H5: 2 | J5: 335 | K5: 342 | L5: 341 | M5: 10.1017/S0008423920000396 | N5: https://www.scopus.com/inward/record.uri?eid=2-s2.0-85084363001&doi=10.1017%2FS0008423920000396&partnerID=40&md5=3ce09a13e790658b2882442f7ed652ce | O5: Department of Political Science, Oklahoma State University, Stillwater, OK, United States; University of Pennsylvania Annenberg School for Communications, Philadelphia, PA, United States; Centre for Public Opinion and Political Representation, Simon Fraser University, Burnaby, BC, Canada; Department of Political Science, Carleton College, USA, Northfield, MN, United States | P5: Motta, Matthew P., Department of Political Science, Oklahoma State University, Stillwater, OK, United States; Stecula, Dominik Andrzej, University of Pennsylvania Annenberg School for Communications, Philadelphia, PA, United States, Centre for Public Opinion and Political Representation, Simon Fraser University, Burnaby, BC, Canada; Farhart, Christina E., Department of Political Science, Carleton College, USA, Northfield, MN, United States | Q5: M. Motta; Department of Political Science, Oklahoma State University, 210 Murray Hall, Stillwater, 74078, United States; email: matthew.motta@okstate.edu | S5: Cambridge University Press journals_subscriptions@cup.cam.ac.uk | T5: 84239 | X5: English | Y5: Can. J. Polit. Sci. | Z5: Article | AA5: Final | AB5: All Open Access; Green Final Open Access; Green Open Access; Hybrid Gold Open Access | AC5: Scopus | AD5: 2-s2.0-85084363001
A6: Capano, G.; Howlett, M. | B6: Capano, Giliberto (23767017600); Howlett, Michael P. (7004315057) | C6: 23767017600; 7004315057 | D6: The Knowns and Unknowns of Policy Instrument Analysis: Policy Tools and the Current Research Agenda on Policy Mixes | E6: 2020 | F6: SAGE Open | G6: 10 | H6: 1 | L6: 297 | M6: 10.1177/2158244019900568 | N6: https://www.scopus.com/inward/record.uri?eid=2-s2.0-85078118455&doi=10.1177%2F2158244019900568&partnerID=40&md5=3c1feae0b9dda08d509a37a2b1e1483e | O6: Alma Mater Studiorum Università di Bologna, Bologna, BO, Italy; Simon Fraser University, Burnaby, BC, Canada | P6: Capano, Giliberto, Alma Mater Studiorum Università di Bologna, Bologna, BO, Italy; Howlett, Michael P., Simon Fraser University, Burnaby, BC, Canada | Q6: M. Howlett; Simon Fraser University, Burnaby, Canada; email: howlett@sfu.ca | S6: SAGE Publications Inc. | X6: English | Y6: SAGE Open | Z6: Article | AA6: Final | AB6: All Open Access; Gold Open Access; Green Accepted Open Access; Green Open Access | AC6: Scopus | AD6: 2-s2.0-85078118455
A7: Radke, H.R.M.; Kutlaca, M.; Siem, B.; Wright, S.C.; Becker, J.C. | B7: Radke, Helena R.M. (54385826800); Kutlaca, Maja (56255329800); Siem, Birte (13907620900); Wright, Stephen C. (57211220396); Becker, Julia Christina (27067529000) | C7: 54385826800; 56255329800; 13907620900; 57211220396; 27067529000 | D7: Beyond Allyship: Motivations for Advantaged Group Members to Engage in Action for Disadvantaged Groups | E7: 2020 | F7: Personality and Social Psychology Review | G7: 24 | H7: 4 | J7: 291 | K7: 315 | L7: 282 | M7: 10.1177/1088868320918698 | N7: https://www.scopus.com/inward/record.uri?eid=2-s2.0-85084509878&doi=10.1177%2F1088868320918698&partnerID=40&md5=59aea277defe91fc8cc6435907919175 | O7: The University of Edinburgh, Edinburgh, Scotland, United Kingdom; Osnabrück University, Osnabruck, Niedersachsen, Germany; Durham University, Durham, County Durham, United Kingdom; FernUniversität in Hagen, Hagen, Nordrhein-Westfalen, Germany; Simon Fraser University, Burnaby, BC, Canada | P7: Radke, Helena R.M., The University of Edinburgh, Edinburgh, Scotland, United Kingdom; Kutlaca, Maja, Osnabrück University, Osnabruck, Niedersachsen, Germany, Durham University, Durham, County Durham, United Kingdom; Siem, Birte, FernUniversität in Hagen, Hagen, Nordrhein-Westfalen, Germany; Wright, Stephen C., Simon Fraser University, Burnaby, BC, Canada; Becker, Julia Christina, Osnabrück University, Osnabruck, Niedersachsen, Germany | Q7: H.R.M. Radke; The University of Edinburgh, United Kingdom; email: helena.radke@ed.ac.uk | S7: SAGE Publications Inc. | T7: 10888683 | W7: 32390573 | X7: English | Y7: Pers. Soc. Psychol. Rev. | Z7: Review | AA7: Final | AB7: All Open Access; Green Accepted Open Access; Green Open Access; Hybrid Gold Open Access | AC7: Scopus | AD7: 2-s2.0-85084509878
A8: Fernández-Llamazares, Á.; Lepofsky, D.; Lertzman, K.; Armstrong, C.G.; Brondízio, E.S.; Gavin, M.C.; Lyver, P.O.; Nicholas, G.P.; Pascua, P.; Reo, N.J.; Reyes-García, V.; Turner, N.J.; Yletyinen, J.; Anderson, E.N.; Balée, W.; Carino, J.; Davíd-Chavez, D.M.; Dunn, C.P.; Garnett, S.C.; Greening La'goot, S.; Niniwum Selapem, S.J.; Kuhnlein, H.; Molnár, Z.; Odonne, G.; Retter, G.-B.; Ripple, W.J.; Sáfián, L.; Bahraman, A.S.; Torrents-Ticó, M.; Vaughan, M.B. | B8: Fernández-Llamazares, Álvaro (55442838400); Lepofsky, Dana S. (6603240852); Lertzman, Ken P. (6701825638); Armstrong, Chelsey Geralda Denise (56608716400); Brondízio, Eduardo Sonnewend (6603037978); Gavin, Michael C. (15047812600); Lyver, Phil O’ ’b (6601968591); Nicholas, George P. (14828144700); Pascua, Pua'ala (57195414986); Reo, Nicholas James (36100226900); Reyes-García, Victoria E. (6507160889); Turner, Nancy Jean (7202572839); Yletyinen, Johanna (55829719800); Anderson, Eugene N. (36893617500); Balée, William (9268590700); Carino, Joji (36477093900); Davíd-Chavez, Dominique M. (57008316300); Dunn, Christopher P. (59863375500); Garnett, Stephen T. (7004285282); Greening La'goot, Spencer (58680264800); Niniwum Selapem, Shain Jackson (58680265600); Kuhnlein, Harriet V. (7006226753); Molnár, Zsolt (22035813200); Odonne, Guillaume (15926113900); Retter, Gunn Britt (57223678175); Ripple, William J. (7003774540); Sáfián, László (57206847402); Bahraman, Abolfazl Sharifian (57217053186); Torrents-Ticó, Miquel (57200563129); Vaughan, Mehana Blaich (59662839800) | C8: 55442838400; 6603240852; 6701825638; 56608716400; 6603037978; 15047812600; 6601968591; 14828144700; 57195414986; 36100226900; 6507160889; 7202572839; 55829719800; 36893617500; 9268590700; 36477093900; 57008316300; 59863375500; 7004285282; 58680264800; 58680265600; 7006226753; 22035813200; 15926113900; 57223678175; 7003774540; 57206847402; 57217053186; 57200563129; 59662839800 | D8: Scientists' Warning to Humanity on Threats to Indigenous and Local Knowledge Systems | E8: 2021 | F8: Journal of Ethnobiology | G8: 41 | H8: 2 | J8: 144 | K8: 169 | L8: 211 | M8: 10.2993/0278-0771-41.2.144 | N8: https://www.scopus.com/inward/record.uri?eid=2-s2.0-85114055438&doi=10.2993%2F0278-0771-41.2.144&partnerID=40&md5=8c8f5e2852e9e64813800a3879a1898f | O8: Faculty of Biological and Environmental Sciences, Helsingin Yliopisto, Helsinki, Uusimaa, Finland; Organismal and Evolutionary Biology Research Programme, Helsingin Yliopisto, Helsinki, Uusimaa, Finland; Department of Archaeology, Simon Fraser University, Burnaby, BC, Canada; School of Resource and Environmental Management, Simon Fraser University, Burnaby, BC, Canada; Indigenous Studies, Simon Fraser University, Burnaby, BC, Canada; Department of Anthropology, Indiana University Bloomington, Bloomington, IN, United States; Department of Human Dimensions of Natural Resources, Colorado State University, Fort Collins, CO, United States; Max-Planck-Institut für Geoanthropologie, Jena, Thuringen, Germany; Manaaki Whenua – Landcare Research, Lincoln, CAN, New Zealand; Center for Biodiversity and Conservation, American Museum of Natural History, New York, NY, United States; Native American Studies and Environmental Studies, Dartmouth College, Hanover, NH, United States; Institució Catalana de Recerca i Estudis Avançats, Barcelona, Barcelona, Spain; ICTA-UAB Institut de Ciència i Tecnologia Ambientals, Cerdanyola del Valles, Barcelona, Spain; Departament d'Antropologia Social i Cultural, Universitat Autònoma de Barcelona, Cerdanyola del Valles, Barcelona, Spain; Emeritus, University of Victoria, Victoria, BC, Canada; University of California, Riverside, Riverside, CA, United States; Department of Anthropology, Tulane University, New Orleans, LA, United States; Forest Peoples' Programme, United Kingdom; Colorado State University, Fort Collins, CO, United States; The University of Arizona, Tucson, AZ, United States; Cornell Botanic Gardens, Ithaca, NY, United States; Research Institute for the Environment and Livelihoods, Charles Darwin University, Darwin, NT, Australia; Gitga'at First Nation, Hartley Bay, BC, Canada; Shain Jackson (Niniwum Selapem) Shishálh First Nation, BC, Canada; Centre for Indigenous Peoples' Nutrition and Environment, Sainte-Anne-de-Bellevue, QC, Canada; Centre for Ecological Research, Vácrátót, Vacratot, Hungary; Université de Guyane, Cayenne, French Guiana, France; Arctic and Environmental Unit, Saami Council, Karasjok, Norway; Department of Forest Ecosystems and Society, Oregon State University, Corvallis, OR, United States; Traditional Shepherd, Hajdúsámson, Hungary; Gorgan University of Agricultural Sciences and Natural Resources, Gorgan, Golestan, Iran; Department of Natural Resources and Environmental Management, University of Hawaiʻi at Mānoa, Honolulu, HI, United States | P8: Fernández-Llamazares, Álvaro, Faculty of Biological and Environmental Sciences, Helsingin Yliopisto, Helsinki, Uusimaa, Finland, Organismal and Evolutionary Biology Research Programme, Helsingin Yliopisto, Helsinki, Uusimaa, Finland; Lepofsky, Dana S., Department of Archaeology, Simon Fraser University, Burnaby, BC, Canada; Lertzman, Ken P., School of Resource and Environmental Management, Simon Fraser University, Burnaby, BC, Canada; Armstrong, Chelsey Geralda Denise, Indigenous Studies, Simon Fraser University, Burnaby, BC, Canada; Brondízio, Eduardo Sonnewend, Department of Anthropology, Indiana University Bloomington, Bloomington, IN, United States; Gavin, Michael C., Department of Human Dimensions of Natural Resources, Colorado State University, Fort Collins, CO, United States, Max-Planck-Institut für Geoanthropologie, Jena, Thuringen, Germany; Lyver, Phil O’ ’b, Manaaki Whenua – Landcare Research, Lincoln, CAN, New Zealand; Nicholas, George P., Department of Archaeology, Simon Fraser University, Burnaby, BC, Canada; Pascua, Pua'ala, Center for Biodiversity and Conservation, American Museum of Natural History, New York, NY, United States; Reo, Nicholas James, Native American Studies and Environmental Studies, Dartmouth College, Hanover, NH, United States; Reyes-García, Victoria E., Institució Catalana de Recerca i Estudis Avançats, Barcelona, Barcelona, Spain, ICTA-UAB Institut de Ciència i Tecnologia Ambientals, Cerdanyola del Valles, Barcelona, Spain, Departament d'Antropologia Social i Cultural, Universitat Autònoma de Barcelona, Cerdanyola del Valles, Barcelona, Spain; Turner, Nancy Jean, Emeritus, University of Victoria, Victoria, BC, Canada; Yletyinen, Johanna, Manaaki Whenua – Landcare Research, Lincoln, CAN, New Zealand; Anderson, Eugene N., University of California, Riverside, Riverside, CA, United States; Balée, William, Department of Anthropology, Tulane University, New Orleans, LA, United States; Carino, Joji, Forest Peoples' Programme, United Kingdom; Davíd-Chavez, Dominique M., Colorado State University, Fort Collins, CO, United States, The University of Arizona, Tucson, AZ, United States; Dunn, Christopher P., Cornell Botanic Gardens, Ithaca, NY, United States; Garnett, Stephen T., Research Institute for the Environment and Livelihoods, Charles Darwin University, Darwin, NT, Australia; Greening La'goot, Spencer, Department of Archaeology, Simon Fraser University, Burnaby, BC, Canada, Gitga'at First Nation, Hartley Bay, BC, Canada; Niniwum Selapem, Shain Jackson, Shain Jackson (Niniwum Selapem) Shishálh First Nation, BC, Canada; Kuhnlein, Harriet V., Centre for Indigenous Peoples' Nutrition and Environment, Sainte-Anne-de-Bellevue, QC, Canada; Molnár, Zsolt, Centre for Ecological Research, Vácrátót, Vacratot, Hungary; Odonne, Guillaume, Université de Guyane, Cayenne, French Guiana, France; Retter, Gunn Britt, Arctic and Environmental Unit, Saami Council, Karasjok, Norway; Ripple, William J., Department of Forest Ecosystems and Society, Oregon State University, Corvallis, OR, United States; Sáfián, László, Traditional Shepherd, Hajdúsámson, Hungary; Bahraman, Abolfazl Sharifian, Gorgan University of Agricultural Sciences and Natural Resources, Gorgan, Golestan, Iran; Torrents-Ticó, Miquel, Faculty of Biological and Environmental Sciences, Helsingin Yliopisto, Helsinki, Uusimaa, Finland, Organismal and Evolutionary Biology Research Programme, Helsingin Yliopisto, Helsinki, Uusimaa, Finland; Vaughan, Mehana Blaich, Department of Natural Resources and Environmental Management, University of Hawaiʻi at Mānoa, Honolulu, HI, United States | Q8: Á. Fernández-Llamazares; Helsinki Institute of Sustainability Science (HELSUS), Faculty of Biological and Environmental Sciences, University of Helsinki, Helsinki, PO Box 65 (Viikinkaari 1), FI-00014, Finland; email: alvaro.fernandez-llamazares@helsinki.fi | S8: Society of Ethnobiology | T8: 2780771 | X8: English | Y8: J. Ethnobiology | Z8: Article | AA8: Final | AB8: All Open Access; Green Accepted Open Access; Green Open Access; Hybrid Gold Open Access | AC8: Scopus | AD8: 2-s2.0-85114055438
A9: Hudson, M.; Garrison, N.A.; Sterling, R.; Caron, N.R.; Fox, K.; Yracheta, J.; Anderson, J.; Wilcox, P.; Arbour, L.; Brown, A.; Tauali’i, M.; Kukutai, T.; Haring, R.; te Aika, B.; Baynam, G.S.; Dearden, P.K.; Chagné, D.; Malhi, R.S.; Garba, I.; Tiffin, N.; Bolnick, D.; Stott, M.; Rolleston, A.K.; Ballantyne, L.L.; Lovett, R.; Davíd-Chavez, D.M.; Martinez, A.; Sporle, A.; Walter, M.; Reading, J.; Carroll, S.R. | B9: Hudson, Māui L. (16678829800); Garrison, Nanibaa’ A. (55413610800); Sterling, Rogena (57221555782); Caron, Nadine R. (7004233867); Fox, Keolu P. (55418985100); Yracheta, Joseph Manuel (56784340400); Anderson, Jane E. (55731042900); Wilcox, Phillip L. (7006411149); Arbour, Laura T. (55945800600); Brown, Alex D.H. (55498786000); Tauali’i, Maile M. (14056970700); Kukutai, Tahu Hera (22980446300); Haring, Rodney C. (23477302600); te Aika, Ben (57200542695); Baynam, Gareth S. (14324494700); Dearden, Peter K. (7004027723); Chagné, David (7801376697); Malhi, Ripan S. (6603513746); Garba, Ibrahim (57204945814); Tiffin, Nicki T. (8938267600); Bolnick, Deborah A. (35447569100); Stott, Matthew B. (23037484200); Rolleston, Anna K. (23470504900); Ballantyne, Leah L. (57210860304); Lovett, R. W. (24468439600); Davíd-Chavez, Dominique M. (57008316300); Martinez, Andrew (57210569398); Sporle, Andrew A. (6602367272); Walter, Maggie (36455185800); Reading, Jeff L. (7005374971); Carroll, Stephanie Russo (57210577556) | C9: 16678829800; 55413610800; 57221555782; 7004233867; 55418985100; 56784340400; 55731042900; 7006411149; 55945800600; 55498786000; 14056970700; 22980446300; 23477302600; 57200542695; 14324494700; 7004027723; 7801376697; 6603513746; 57204945814; 8938267600; 35447569100; 23037484200; 23470504900; 57210860304; 24468439600; 57008316300; 57210569398; 6602367272; 36455185800; 7005374971; 57210577556 | D9: Rights, interests and expectations: Indigenous perspectives on unrestricted access to genomic data | E9: 2020 | F9: Nature Reviews Genetics | G9: 21 | H9: 6 | J9: 377 | K9: 384 | L9: 203 | M9: 10.1038/s41576-020-0228-x | N9: https://www.scopus.com/inward/record.uri?eid=2-s2.0-85083224298&doi=10.1038%2Fs41576-020-0228-x&partnerID=40&md5=349a8d890b88d0c4f405664d2132432d | O9: Faculty of Māori and Indigenous Studies, University of Waikato, Hamilton, WKO, New Zealand; University of Otago, Dunedin, OTA, New Zealand; Institute for Society and Genetics, University of California, Los Angeles, Los Angeles, CA, United States; Faculty of Law, University of Waikato, Hamilton, WKO, New Zealand; Centre for Excellence in Indigenous Health, The University of British Columbia, Vancouver, BC, Canada; British Columbia Cancer, Canada‘s Michael Smith Genome Sciences Centre, Vancouver, BC, Canada; Global Health Program, University of California, San Diego, La Jolla, CA, United States; Johns Hopkins Bloomberg School of Public Health, Baltimore, MD, United States; Native BioData Consortium, Eagle Butte, SD, United States; Department of Anthropology, New York University, New York, NY, United States; Department of Mathematics and Statistics, University of Otago, Dunedin, OTA, New Zealand; Department of Medical Genetics, The University of British Columbia, Vancouver, BC, Canada; Aboriginal Health Equity, South Australian Health and Medical Research Institute, Adelaide, SA, Australia; The University of Adelaide, Adelaide, SA, Australia; Clinical Transformation, Permanente Medical Group, United States; National Institute of Demographic and Economic Analysis, University of Waikato, Hamilton, WKO, New Zealand; Center for Indigenous Cancer Research, Roswell Park Cancer Institute, Buffalo, NY, United States; Faculty of Medicine, Dentistry and Health Sciences, The University of Western Australia, Perth, WA, Australia; University of Otago, Dunedin, OTA, New Zealand; Plant & Food Research, New Zealand, Auckland, AUK, New Zealand; Genomics Aotearoa, Palmerston North, New Zealand; Department of Anthropology, University of Illinois Urbana-Champaign, Urbana, IL, United States; Native Nations Institute, The University of Arizona, Tucson, AZ, United States; Computational Biology Division, University of Cape Town, Cape Town, Western Cape, South Africa; University of Cape Town, Cape Town, Western Cape, South Africa; Centre for Infectious Disease Epidemiology and Research, University of Cape Town, Cape Town, Western Cape, South Africa; Department of Anthropology, University of Connecticut, Storrs, CT, United States; Institute for Systems Genomics, University of Connecticut, Storrs, CT, United States; School of Biological Sciences, University of Canterbury, Christchurch, CAN, New Zealand; The Centre for Health, Manawaora, Tauranga, New Zealand; The Australian National University, Canberra, ACT, Australia; Colorado State University, Fort Collins, CO, United States; Department of Statistics, University of Auckland, Auckland, AUK, New Zealand; School of Social Sciences, University of Tasmania, Hobart, TS, Australia; Maiam nayri Wingara (Australian Indigenous Data Sovereignty Collective), Hobart, TS, Australia; Global Indigenous Data Alliance, Onate, Spain; Faculty of Health Sciences, Simon Fraser University, Burnaby, BC, Canada; Mel and Enid Zuckerman College of Public Health, The University of Arizona, Tucson, AZ, United States | P9: Hudson, Māui L., Faculty of Māori and Indigenous Studies, University of Waikato, Hamilton, WKO, New Zealand, University of Otago, Dunedin, OTA, New Zealand; Garrison, Nanibaa’ A., Institute for Society and Genetics, University of California, Los Angeles, Los Angeles, CA, United States; Sterling, Rogena, Faculty of Law, University of Waikato, Hamilton, WKO, New Zealand; Caron, Nadine R., Centre for Excellence in Indigenous Health, The University of British Columbia, Vancouver, BC, Canada, British Columbia Cancer, Canada‘s Michael Smith Genome Sciences Centre, Vancouver, BC, Canada; Fox, Keolu P., Global Health Program, University of California, San Diego, La Jolla, CA, United States; Yracheta, Joseph Manuel, Johns Hopkins Bloomberg School of Public Health, Baltimore, MD, United States, Native BioData Consortium, Eagle Butte, SD, United States; Anderson, Jane E., Department of Anthropology, New York University, New York, NY, United States; Wilcox, Phillip L., University of Otago, Dunedin, OTA, New Zealand, Department of Mathematics and Statistics, University of Otago, Dunedin, OTA, New Zealand; Arbour, Laura T., Department of Medical Genetics, The University of British Columbia, Vancouver, BC, Canada; Brown, Alex D.H., Aboriginal Health Equity, South Australian Health and Medical Research Institute, Adelaide, SA, Australia, The University of Adelaide, Adelaide, SA, Australia; Tauali’i, Maile M., Clinical Transformation, Permanente Medical Group, United States; Kukutai, Tahu Hera, National Institute of Demographic and Economic Analysis, University of Waikato, Hamilton, WKO, New Zealand; Haring, Rodney C., Center for Indigenous Cancer Research, Roswell Park Cancer Institute, Buffalo, NY, United States; te Aika, Ben, University of Otago, Dunedin, OTA, New Zealand; Baynam, Gareth S., Faculty of Medicine, Dentistry and Health Sciences, The University of Western Australia, Perth, WA, Australia; Dearden, Peter K., University of Otago, Dunedin, OTA, New Zealand, University of Otago, Dunedin, OTA, New Zealand; Chagné, David, Plant & Food Research, New Zealand, Auckland, AUK, New Zealand, Genomics Aotearoa, Palmerston North, New Zealand; Malhi, Ripan S., Department of Anthropology, University of Illinois Urbana-Champaign, Urbana, IL, United States; Garba, Ibrahim, Native Nations Institute, The University of Arizona, Tucson, AZ, United States; Tiffin, Nicki T., Computational Biology Division, University of Cape Town, Cape Town, Western Cape, South Africa, University of Cape Town, Cape Town, Western Cape, South Africa, Centre for Infectious Disease Epidemiology and Research, University of Cape Town, Cape Town, Western Cape, South Africa; Bolnick, Deborah A., Department of Anthropology, University of Connecticut, Storrs, CT, United States, Institute for Systems Genomics, University of Connecticut, Storrs, CT, United States; Stott, Matthew B., School of Biological Sciences, University of Canterbury, Christchurch, CAN, New Zealand; Rolleston, Anna K., The Centre for Health, Manawaora, Tauranga, New Zealand; Ballantyne, Leah L., Department of Medical Genetics, The University of British Columbia, Vancouver, BC, Canada; Lovett, R. W., The Australian National University, Canberra, ACT, Australia; Davíd-Chavez, Dominique M., Native Nations Institute, The University of Arizona, Tucson, AZ, United States, Colorado State University, Fort Collins, CO, United States; Martinez, Andrew, Native Nations Institute, The University of Arizona, Tucson, AZ, United States; Sporle, Andrew A., Department of Statistics, University of Auckland, Auckland, AUK, New Zealand; Walter, Maggie, School of Social Sciences, University of Tasmania, Hobart, TS, Australia, Maiam nayri Wingara (Australian Indigenous Data Sovereignty Collective), Hobart, TS, Australia, Global Indigenous Data Alliance, Onate, Spain; Reading, Jeff L., Faculty of Health Sciences, Simon Fraser University, Burnaby, BC, Canada; Carroll, Stephanie Russo, Native Nations Institute, The University of Arizona, Tucson, AZ, United States, Mel and Enid Zuckerman College of Public Health, The University of Arizona, Tucson, AZ, United States | Q9: M. Hudson; Faculty of Māori and Indigenous Studies, University of Waikato, Hamilton, New Zealand; email: maui.hudson@waikato.ac.nz | S9: Nature Research | T9: 14710056 | V9: NRGAA | W9: 32251390 | X9: English | Y9: Nat. Rev. Gen. | Z9: Review | AA9: Final | AC9: Scopus | AD9: 2-s2.0-85083224298
A10: Benyam, A.A.; Soma, T.; D.g Fraser, E. | B10: Benyam, Addisalem (Addis) (57201357832); Soma, Tammara (57190267343); D.g Fraser, Evan (8323188600) | C10: 57201357832; 57190267343; 8323188600 | D10: Digital agricultural technologies for food loss and waste prevention and reduction: Global trends, adoption opportunities and barriers | E10: 2021 | F10: Journal of Cleaner Production | G10: 323 | I10: 129099 | L10: 182 | M10: 10.1016/j.jclepro.2021.129099 | N10: https://www.scopus.com/inward/record.uri?eid=2-s2.0-85115964736&doi=10.1016%2Fj.jclepro.2021.129099&partnerID=40&md5=0485fcd7e24da84e1c722cf346b4024a | O10: Research Fellow, Simon Fraser University, Burnaby, BC, Canada; Research Director, Simon Fraser University, Burnaby, BC, Canada; Department of Geography, University of Guelph, Guelph, ON, Canada | P10: Benyam, Addisalem (Addis), Research Fellow, Simon Fraser University, Burnaby, BC, Canada; Soma, Tammara, Research Director, Simon Fraser University, Burnaby, BC, Canada; D.g Fraser, Evan, Department of Geography, University of Guelph, Guelph, ON, Canada | Q10: A.A. Benyam; Research Fellow, Food Systems Lab, Simon Fraser University, Burnaby, 8888 University Dr, V5A 1S6, Canada; email: addis@foodsystemslab.ca | S10: Elsevier Ltd | T10: 9596526 | V10: JCROE | X10: English | Y10: J. Clean. Prod. | Z10: Review | AA10: Final | AC10: Scopus | AD10: 2-s2.0-85115964736
A11: Hässler, T.; Ullrich, J.; Bernardino, M.; Shnabel, N.; Van Laar, C.V.; Valdenegro, D.; Sebben, S.; Tropp, L.R.; Visintin, E.P.; González Gutierrez, R.; Ditlmann, R.K.; Abrams, D.; Selvanathan, H.P.; Branković, M.; Wright, S.C.; von Zimmermann, J.; Pasek, M.; Aydin, A.L.; Žeželj, I.; Pereira, A.; Lantos, N.A.; Sainz, M.; Glenz, A.; Oberpfalzerová, H.; Bilewicz, M.; Kende, A.; Kuzawinska, O.; Otten, S.; Maloku, E.; Noor, M.; Gul, P.; Pistella, J.; Baiocco, R.; Jelić, M.; Osin, E.; Bareket, O.; Čorkalo Biruški, D.C.; Cook, J.E.; Dawood, M.; Droogendyk, L.; Loyo, A.H.; Kelmendi, K.; Ugarte, L.M. | B11: Hässler, Tabea (56204885600); Ullrich, Johannes (16475186000); Bernardino, Michelle (57190167014); Shnabel, Nurit (26533499300); Van Laar, Colette (6603372206); Valdenegro, Daniel (55817856800); Sebben, Simone (57214227223); Tropp, Linda R. (6603178539); Visintin, Emilio Paolo (54879282800); González Gutierrez, Roberto (36339388700); Ditlmann, Ruth K. (24168449800); Abrams, Dominic (7101975318); Selvanathan, Hema Preya (57203394907); Branković, Marija (25925678200); Wright, Stephen C. (57211220396); von Zimmermann, Jorina (57192954118); Pasek, Michael H. (57194570825); Aydin, Anna Lisa (55838605500); Žeželj, Iris L. (34871182900); Pereira, Adrienne (57193762945); Lantos, Nóra Anna (57130916700); Sainz, Mario (57945842000); Glenz, Andreas (55759422600); Oberpfalzerová, Hana (57214224541); Bilewicz, Michał (55954148000); Kende, Anna (55503955800); Kuzawinska, Olga (57216567560); Otten, Sabine (7003408957); Maloku, Edona (57200552602); Noor, Masi (24177414200); Gul, Pelin (55925254000); Pistella, Jessica (57090960200); Baiocco, Roberto (23979327100); Jelić, Margareta (15065426400); Osin, Evgeny Nikolaevich (35737831400); Bareket, Orly (56946913300); Čorkalo Biruški, Dinka (6602722147); Cook, Jonathan E. (36781937300); Dawood, Maneeza (57214218798); Droogendyk, Lisa M. (56431060800); Loyo, Angélica Herrera (57214232282); Kelmendi, Kaltrina (56368423500); Ugarte, Luiza Mugnol (57214226775) | C11: 56204885600; 16475186000; 57190167014; 26533499300; 6603372206; 55817856800; 57214227223; 6603178539; 54879282800; 36339388700; 24168449800; 7101975318; 57203394907; 25925678200; 57211220396; 57192954118; 57194570825; 55838605500; 34871182900; 57193762945; 57130916700; 57945842000; 55759422600; 57214224541; 55954148000; 55503955800; 57216567560; 7003408957; 57200552602; 24177414200; 55925254000; 57090960200; 23979327100; 15065426400; 35737831400; 56946913300; 6602722147; 36781937300; 57214218798; 56431060800; 57214232282; 56368423500; 57214226775 | D11: A large-scale test of the link between intergroup contact and support for social change | E11: 2020 | F11: Nature Human Behaviour | G11: 4 | H11: 4 | J11: 380 | K11: 386 | L11: 159 | M11: 10.1038/s41562-019-0815-z | N11: https://www.scopus.com/inward/record.uri?eid=2-s2.0-85078474231&doi=10.1038%2Fs41562-019-0815-z&partnerID=40&md5=01bcabad03c6c85973896501e683518a | O11: Department of Psychology, Universität Zürich, Zurich, ZH, Switzerland; School of Psychology, Pontificia Universidad Católica de Chile, Santiago, RM, Chile; School of Psychological Sciences, Tel Aviv University, Tel Aviv-Yafo, Tel Aviv District, Israel; Department of Psychology, KU Leuven, Leuven, Vlaams-Brabant, Belgium; School of Politics and International Studies, University of Leeds, Leeds, West Yorkshire, United Kingdom; University of Massachusetts Amherst, Amherst, MA, United States; Department of Humanities, University of Ferrara, Ferrara, FE, Italy; Institute of Psychology, Université de Lausanne (UNIL), Lausanne, VD, Switzerland; Wissenschaftszentrum Berlin fur Sozialforschung, Berlin, Berlin, Germany; School of Psychology, University of Kent, Canterbury, Kent, United Kingdom; The University of Queensland, Brisbane, QLD, Australia; Department of Psychology, Singidunum University, Belgrade, Serbia; Department of Psychology, Simon Fraser University, Burnaby, BC, Canada; University College London, London, United Kingdom; Department of Psychology, The New School, New York, NY, United States; Artis International, Scottsdale, AZ, United States; Department of Psychology, Goethe-Universität Frankfurt am Main, Frankfurt am Main, Hessen, Germany; Department of Psychology, University of Belgrade, Belgrade, Serbia; Department of Social Psychology, Eötvös Loránd Tudományegyetem, Budapest, Hungary; Department of Psychology, Universidad de Granada, Granada, Granada, Spain; Department of Psychology, Universidad de Monterrey, San Pedro Garza Garcia, NLE, Mexico; Institute of Political Studies, Charles University, Prague, Czech Republic; Faculty of Psychology, University of Warsaw, Warsaw, MA, Poland; Department of Psychology, Rijksuniversiteit Groningen, Groningen, Groningen, Netherlands; Social Sciences Unit, Rochester Institute of Technology Kosovo, Pristina, Serbia; Department of Psychology, Keele University, Keele, Staffordshire, United Kingdom; College of Liberal Arts and Sciences, Ames, IA, United States; Faculty of Medicine and Psychology, Rome, RM, Italy; Department of Psychology, University of Zagreb, Zagreb, Croatia; HSE University, Moscow, Russian Federation; Department of Psychology, Pennsylvania State University, University Park, PA, United States; Department of Psychology, Columbia University, New York, NY, United States; Department of Psychology, Sheridan College Institute of Technology and Advanced Learning, Oakville, ON, Canada; Department of Informatics, ETH Zürich, Zurich, ZH, Switzerland; Department of Psychology, University of Pristina - Kosovska Mitrovica, Kosovska Mitrovica, Vojvodina, Serbia; Department of Psychology, Instituto D'Or de Pesquisa e Ensino, Rio de Janeiro, RJ, Brazil | P11: Hässler, Tabea, Department of Psychology, Universität Zürich, Zurich, ZH, Switzerland; Ullrich, Johannes, Department of Psychology, Universität Zürich, Zurich, ZH, Switzerland; Bernardino, Michelle, School of Psychology, Pontificia Universidad Católica de Chile, Santiago, RM, Chile; Shnabel, Nurit, School of Psychological Sciences, Tel Aviv University, Tel Aviv-Yafo, Tel Aviv District, Israel; Van Laar, Colette, Department of Psychology, KU Leuven, Leuven, Vlaams-Brabant, Belgium; Valdenegro, Daniel, School of Politics and International Studies, University of Leeds, Leeds, West Yorkshire, United Kingdom; Sebben, Simone, Department of Psychology, Universität Zürich, Zurich, ZH, Switzerland; Tropp, Linda R., University of Massachusetts Amherst, Amherst, MA, United States; Visintin, Emilio Paolo, Department of Humanities, University of Ferrara, Ferrara, FE, Italy, Institute of Psychology, Université de Lausanne (UNIL), Lausanne, VD, Switzerland; González Gutierrez, Roberto, School of Psychology, Pontificia Universidad Católica de Chile, Santiago, RM, Chile; Ditlmann, Ruth K., Wissenschaftszentrum Berlin fur Sozialforschung, Berlin, Berlin, Germany; Abrams, Dominic, School of Psychology, University of Kent, Canterbury, Kent, United Kingdom; Selvanathan, Hema Preya, University of Massachusetts Amherst, Amherst, MA, United States, The University of Queensland, Brisbane, QLD, Australia; Branković, Marija, Department of Psychology, Singidunum University, Belgrade, Serbia; Wright, Stephen C., Department of Psychology, Simon Fraser University, Burnaby, BC, Canada; von Zimmermann, Jorina, University College London, London, United Kingdom; Pasek, Michael H., Department of Psychology, The New School, New York, NY, United States, Artis International, Scottsdale, AZ, United States; Aydin, Anna Lisa, Department of Psychology, Goethe-Universität Frankfurt am Main, Frankfurt am Main, Hessen, Germany; Žeželj, Iris L., Department of Psychology, University of Belgrade, Belgrade, Serbia; Pereira, Adrienne, Department of Humanities, University of Ferrara, Ferrara, FE, Italy; Lantos, Nóra Anna, Department of Social Psychology, Eötvös Loránd Tudományegyetem, Budapest, Hungary; Sainz, Mario, Department of Psychology, Universidad de Granada, Granada, Granada, Spain, Department of Psychology, Universidad de Monterrey, San Pedro Garza Garcia, NLE, Mexico; Glenz, Andreas, Department of Psychology, Universität Zürich, Zurich, ZH, Switzerland; Oberpfalzerová, Hana, Institute of Political Studies, Charles University, Prague, Czech Republic; Bilewicz, Michał, Faculty of Psychology, University of Warsaw, Warsaw, MA, Poland; Kende, Anna, Department of Social Psychology, Eötvös Loránd Tudományegyetem, Budapest, Hungary; Kuzawinska, Olga, Faculty of Psychology, University of Warsaw, Warsaw, MA, Poland; Otten, Sabine, Department of Psychology, Rijksuniversiteit Groningen, Groningen, Groningen, Netherlands; Maloku, Edona, Social Sciences Unit, Rochester Institute of Technology Kosovo, Pristina, Serbia; Noor, Masi, Department of Psychology, Keele University, Keele, Staffordshire, United Kingdom; Gul, Pelin, College of Liberal Arts and Sciences, Ames, IA, United States; Pistella, Jessica, Faculty of Medicine and Psychology, Rome, RM, Italy; Baiocco, Roberto, Faculty of Medicine and Psychology, Rome, RM, Italy; Jelić, Margareta, Department of Psychology, University of Zagreb, Zagreb, Croatia; Osin, Evgeny Nikolaevich, HSE University, Moscow, Russian Federation; Bareket, Orly, School of Psychological Sciences, Tel Aviv University, Tel Aviv-Yafo, Tel Aviv District, Israel; Čorkalo Biruški, Dinka, Department of Psychology, University of Zagreb, Zagreb, Croatia; Cook, Jonathan E., Department of Psychology, Pennsylvania State University, University Park, PA, United States; Dawood, Maneeza, Department of Psychology, Columbia University, New York, NY, United States; Droogendyk, Lisa M., Department of Psychology, Sheridan College Institute of Technology and Advanced Learning, Oakville, ON, Canada; Loyo, Angélica Herrera, Department of Informatics, ETH Zürich, Zurich, ZH, Switzerland; Kelmendi, Kaltrina, Department of Psychology, University of Pristina - Kosovska Mitrovica, Kosovska Mitrovica, Vojvodina, Serbia; Ugarte, Luiza Mugnol, Department of Psychology, Instituto D'Or de Pesquisa e Ensino, Rio de Janeiro, RJ, Brazil | Q11: T. Hässler; Department of Psychology, University of Zurich, Zurich, Switzerland; email: tabea.haessler@uzh.ch | S11: Nature Research | W11: 31988440 | X11: English | Y11: Nat. Hum. Behav. | Z11: Article | AA11: Final | AB11: All Open Access; Bronze Open Access; Green Accepted Open Access; Green Final Open Access; Green Open Access | AC11: Scopus | AD11: 2-s2.0-85078474231
A12: Ackah, B.B.B.; Woo, M.; Stallwood, L.; Fazal, Z.A.; Okpani, A.; Ukah, U.V.; Adu, P.A. | B12: Ackah, Betty Bozoma Blay (57205417680); Woo, Michael (57754876500); Stallwood, Lisa (57218141706); Fazal, Zahra A. (57354100900); Okpani, Arnold Ikedichi (57222594636); Ukah, Ugochinyere Vivian (59157709400); Adu, Prince Asumadu (57192295693) | C12: 57205417680; 57754876500; 57218141706; 57354100900; 57222594636; 59157709400; 57192295693 | D12: COVID-19 vaccine hesitancy in Africa: a scoping review | E12: 2022 | F12: Global Health Research and Policy | G12: 7 | H12: 1 | I12: 21 | L12: 152 | M12: 10.1186/s41256-022-00255-1 | N12: https://www.scopus.com/inward/record.uri?eid=2-s2.0-85134411707&doi=10.1186%2Fs41256-022-00255-1&partnerID=40&md5=b80f5a2b5333119cf57ce2db84f4d143 | O12: School of Communication, Simon Fraser University, Burnaby, BC, Canada; School of Population and Public Health, The University of British Columbia, Vancouver, BC, Canada; National Primary Health Care Development Agency, Abuja, FCT, Nigeria; Biostatistics and Occupational Health, School of Medicine, Montreal, QC, Canada | P12: Ackah, Betty Bozoma Blay, School of Communication, Simon Fraser University, Burnaby, BC, Canada; Woo, Michael, School of Population and Public Health, The University of British Columbia, Vancouver, BC, Canada; Stallwood, Lisa, School of Population and Public Health, The University of British Columbia, Vancouver, BC, Canada; Fazal, Zahra A., School of Population and Public Health, The University of British Columbia, Vancouver, BC, Canada; Okpani, Arnold Ikedichi, National Primary Health Care Development Agency, Abuja, FCT, Nigeria; Ukah, Ugochinyere Vivian, Biostatistics and Occupational Health, School of Medicine, Montreal, QC, Canada; Adu, Prince Asumadu, School of Population and Public Health, The University of British Columbia, Vancouver, BC, Canada | Q12: P.A. Adu; School of Population and Public Health, University of British Columbia, Vancouver, 2206 E Mall, V6T 1Z3, Canada; email: prince.adu@alumni.ubc.ca | S12: BioMed Central Ltd | W12: 35850783 | X12: English | Y12: Glob. Health. Res. Policy | Z12: Review | AA12: Final | AB12: All Open Access; Gold Open Access; Green Accepted Open Access; Green Final Open Access; Green Open Access | AC12: Scopus | AD12: 2-s2.0-85134411707
A13: Stecula, D.A.; Pickup, M. | B13: Stecula, Dominik Andrzej (56071614400); Pickup, Mark Alexander (15757997300) | C13: 56071614400; 15757997300 | D13: How populism and conservative media fuel conspiracy beliefs about COVID-19 and what it means for COVID-19 behaviors | E13: 2021 | F13: Research and Politics | G13: 8 | H13: 1 | L13: 147 | M13: 10.1177/2053168021993979 | N13: https://www.scopus.com/inward/record.uri?eid=2-s2.0-85101001632&doi=10.1177%2F2053168021993979&partnerID=40&md5=4c7a1f2e1250024eb3fbd1f1d615925e | O13: Colorado State University, Fort Collins, CO, United States; Simon Fraser University, Burnaby, BC, Canada | P13: Stecula, Dominik Andrzej, Colorado State University, Fort Collins, CO, United States; Pickup, Mark Alexander, Simon Fraser University, Burnaby, BC, Canada | Q13: D.A. Stecula; Colorado State University, Fort Collins, United States; email: dominik.stecula@colostate.edu | S13: SAGE Publications Ltd | X13: English | Y13: Res. Polit. | Z13: Article | AA13: Final | AB13: All Open Access; Gold Open Access; Green Accepted Open Access; Green Open Access | AC13: Scopus | AD13: 2-s2.0-85101001632
A14: Atlas, W.I.; Ban, N.C.; Moore, J.W.; Tuohy, A.M.; Greening, S.; Reid, A.J.; Morven, N.; White, E.; Housty, W.G.; Housty, J.A.; Service, C.N.; Greba, L.; Harrison, S.; Sharpe, C.; Butts, K.I.R.; Shepert, W.M.; Sweeney-Bergen, E.; MacIntyre, D.; Sloat, M.R.; Connors, K. | B14: Atlas, William I. (36514095700); Ban, Natalie C. (8268547200); Moore, Jonathan W. (7405239862); Tuohy, Adrian M. (57209828150); Greening, Spencer (57213334854); Reid, Andrea J. (55589415600); Morven, Nicole (57223131343); White, Elroy (57223139712); Housty, William G. (56244862300); Housty, Jess A. (56422151900); Service, Christina N. (55427006400); Greba, Larry (49663244800); Harrison, Sam (57223135601); Sharpe, Ciara (57208024858); Butts, Katherine I.R. (57223138073); Shepert, William M. (57203889554); Sweeney-Bergen, Elissa K. (57209583555); MacIntyre, Donna (56779681900); Sloat, Matthew R. (55988867800); Connors, Katrina (57217675110) | C14: 36514095700; 8268547200; 7405239862; 57209828150; 57213334854; 55589415600; 57223131343; 57223139712; 56244862300; 56422151900; 55427006400; 49663244800; 57223135601; 57208024858; 57223138073; 57203889554; 57209583555; 56779681900; 55988867800; 57217675110 | D14: Indigenous Systems of Management for Culturally and Ecologically Resilient Pacific Salmon (Oncorhynchus spp.) Fisheries | E14: 2021 | F14: BioScience | G14: 71 | H14: 2 | J14: 186 | K14: 204 | L14: 142 | M14: 10.1093/biosci/biaa144 | N14: https://www.scopus.com/inward/record.uri?eid=2-s2.0-85101955803&doi=10.1093%2Fbiosci%2Fbiaa144&partnerID=40&md5=71bf21e7d85ee9a4f4331f1e4d780c36 | O14: Pacific Salmon Foundation, Vancouver, BC, Canada; School of Environmental Studies, University of Victoria, Victoria, BC, Canada; Wild Salmon Center, Portland, OR, United States; Department of Biological Sciences, Simon Fraser University, Burnaby, BC, Canada; Wild Fish Conservancy, DUVALL, WA, United States; Institute of Environmental and Interdisciplinary Science, Ottawa, ON, Canada; NISGA'A NATION, BC, Canada; Central Coast Archaeology, Bella Bella, BC, Canada; Heiltsuk Integrated Resource Management Department, Bella Bella, BC, Canada; QQs Projects Society, Bella Bella, BC, Canada; Heiltsuk Nation, Bella Bella, BC, Canada; Kitasoo First Nation, Klemtu, BC, Canada; Lax Kw’Alaams Band, Lax Kw’Alaams, BC, Canada; Lake Babine Nation Fisheries, Burns Lake, BC, Canada; Faculty of Environment, Simon Fraser University, Burnaby, BC, Canada; Gitga'at Nation, BC, Canada; Department of Forest and Conservation Sciences, The University of British Columbia, Vancouver, BC, Canada | P14: Atlas, William I., Pacific Salmon Foundation, Vancouver, BC, Canada, School of Environmental Studies, University of Victoria, Victoria, BC, Canada, Wild Salmon Center, Portland, OR, United States; Ban, Natalie C., School of Environmental Studies, University of Victoria, Victoria, BC, Canada; Moore, Jonathan W., Department of Biological Sciences, Simon Fraser University, Burnaby, BC, Canada; Tuohy, Adrian M., Wild Fish Conservancy, DUVALL, WA, United States; Greening, Spencer, Pacific Salmon Foundation, Vancouver, BC, Canada, Faculty of Environment, Simon Fraser University, Burnaby, BC, Canada, Gitga'at Nation, BC, Canada; Reid, Andrea J., Institute of Environmental and Interdisciplinary Science, Ottawa, ON, Canada, NISGA'A NATION, BC, Canada, Department of Forest and Conservation Sciences, The University of British Columbia, Vancouver, BC, Canada; Morven, Nicole, NISGA'A NATION, BC, Canada; White, Elroy, Central Coast Archaeology, Bella Bella, BC, Canada, Heiltsuk Nation, Bella Bella, BC, Canada; Housty, William G., Heiltsuk Integrated Resource Management Department, Bella Bella, BC, Canada, Heiltsuk Nation, Bella Bella, BC, Canada; Housty, Jess A., QQs Projects Society, Bella Bella, BC, Canada, Heiltsuk Nation, Bella Bella, BC, Canada; Service, Christina N., Kitasoo First Nation, Klemtu, BC, Canada; Greba, Larry, Kitasoo First Nation, Klemtu, BC, Canada; Harrison, Sam, Kitasoo First Nation, Klemtu, BC, Canada; Sharpe, Ciara, Lax Kw’Alaams Band, Lax Kw’Alaams, BC, Canada; Butts, Katherine I.R., Lax Kw’Alaams Band, Lax Kw’Alaams, BC, Canada; Shepert, William M., Lax Kw’Alaams Band, Lax Kw’Alaams, BC, Canada; Sweeney-Bergen, Elissa K., Lake Babine Nation Fisheries, Burns Lake, BC, Canada; MacIntyre, Donna, Lake Babine Nation Fisheries, Burns Lake, BC, Canada; Sloat, Matthew R., Wild Salmon Center, Portland, OR, United States; Connors, Katrina, Pacific Salmon Foundation, Vancouver, BC, Canada | S14: Oxford University Press | T14: 63568 | V14: BISNA | X14: English | Y14: BioScience | Z14: Article | AA14: Final | AB14: All Open Access; Bronze Open Access; Green Accepted Open Access; Green Open Access | AC14: Scopus | AD14: 2-s2.0-85101955803
A15: Stubbs, J.L.; Thornton, A.E.; Sevick, J.M.; Silverberg, N.D.; Barr, A.M.; Honer, W.G.; Panenka, W.J. | B15: Stubbs, Jacob Liam (57199173174); Thornton, Allen E. (7101607212); Sevick, Jessica M. (57213231707); Silverberg, Noah D. (18438336300); Barr, Alasdair M. (35474239200); Honer, William G. (7004460814); Panenka, William J. (55305981100) | C15: 57199173174; 7101607212; 57213231707; 18438336300; 35474239200; 7004460814; 55305981100 | D15: Traumatic brain injury in homeless and marginally housed individuals: a systematic review and meta-analysis | E15: 2020 | F15: The Lancet Public Health | G15: 5 | H15: 1 | J15: e19 | K15: e32 | L15: 127 | M15: 10.1016/S2468-2667(19)30188-4 | N15: https://www.scopus.com/inward/record.uri?eid=2-s2.0-85077727549&doi=10.1016%2FS2468-2667%2819%2930188-4&partnerID=40&md5=9180f75d03c5638d76e7283c1d431220 | O15: Department of Psychiatry, The University of British Columbia, Vancouver, BC, Canada; Division of Physical Medicine and Rehabilitation, The University of British Columbia, Vancouver, BC, Canada; Department of Anesthesiology, The University of British Columbia, Vancouver, BC, Canada; British Columbia Mental Health and Addictions Research Institute, Vancouver, BC, Canada; Department of Psychology, Simon Fraser University, Burnaby, BC, Canada; Rehabilitation Research Program, Vancouver Coastal Health Research Institute, Vancouver, BC, Canada; British Columbia Provincial Neuropsychiatry Program, Vancouver, BC, Canada | P15: Stubbs, Jacob Liam, Department of Psychiatry, The University of British Columbia, Vancouver, BC, Canada, British Columbia Mental Health and Addictions Research Institute, Vancouver, BC, Canada; Thornton, Allen E., British Columbia Mental Health and Addictions Research Institute, Vancouver, BC, Canada, Department of Psychology, Simon Fraser University, Burnaby, BC, Canada; Sevick, Jessica M., Department of Psychiatry, The University of British Columbia, Vancouver, BC, Canada, British Columbia Mental Health and Addictions Research Institute, Vancouver, BC, Canada; Silverberg, Noah D., Division of Physical Medicine and Rehabilitation, The University of British Columbia, Vancouver, BC, Canada, Rehabilitation Research Program, Vancouver Coastal Health Research Institute, Vancouver, BC, Canada; Barr, Alasdair M., Department of Anesthesiology, The University of British Columbia, Vancouver, BC, Canada, British Columbia Mental Health and Addictions Research Institute, Vancouver, BC, Canada; Honer, William G., Department of Psychiatry, The University of British Columbia, Vancouver, BC, Canada, British Columbia Mental Health and Addictions Research Institute, Vancouver, BC, Canada; Panenka, William J., Department of Psychiatry, The University of British Columbia, Vancouver, BC, Canada, British Columbia Mental Health and Addictions Research Institute, Vancouver, BC, Canada, British Columbia Provincial Neuropsychiatry Program, Vancouver, BC, Canada | Q15: J.L. Stubbs; Department of Psychiatry, University of British Columbia, Vancouver, Canada; email: j.stubbs@alumni.ubc.ca | S15: Elsevier Ltd | W15: 31806487 | X15: English | Y15: Lancet Public Health | Z15: Article | AA15: Final | AB15: All Open Access; Gold Open Access | AC15: Scopus | AD15: 2-s2.0-85077727549
A16: Forslund, T.; Granqvist, P.; van IJzendoorn, M.H.; Sagi-Schwartz, A.; Glaser, D.; Steele, M.; Hammarlund, M.; Schuengel, C.; Bakermans-Kranenburg, M.J.; Steele, H.; Shaver, P.R.; Lux, U.; Simmonds, J.; Jacobvitz, D.; Groh, A.M.; Bernard, K.; Cyr, C.; Hazen, N.L.; Foster, S.; Psouni, E.; Cowan, P.A.; Cowan, C.P.; Rifkin-Graboi, A.; Wilkins, D.; Pierrehumbert, B.; Tarabulsy, G.M.; Cárcamo, R.A.; Wang, Z.; Liang, X.; Kaźmierczak, M.; Pawlicka, P.; Ayiro, L.; Chansa, T.; Sichimba, F.; Mooya, H.; McLean, L.; Veríssimo, M.; Gojman de Millán, S.; Marlene Marie Moretti, M.M.; Bacro, F.; Peltola, M.J.; Galbally, M.; Kondo-Ikemura, K.; Behrens, K.Y.; Scott, S.; Fresno, A.F.; Spencer-Contreras, R.; Posada, G.; Cassibba, R.; Barrantes-Vidal, N.; Palacios, J.; Barone, L.; Madigan, S.; Mason-Jones, K.; Reijman, S.; Juffer, F.; Fearon, R.P.; Bernier, A.; Cicchetti, D.; Roisman, G.I.; Cassidy, J.; Kindler, H.; Zimmermann, P.; Feldman, R.; Spangle, G.; Zeanah, C.H.; Dozier, M.; Belsky, J.; Lamb, M.E.; Duschinsky, R. | B16: Forslund, Tommie (57208786335); Granqvist, Pehr Granqvistand (6602281537); van IJzendoorn, Marinus H. (7005398271); Sagi-Schwartz, Abraham (7006933186); Glaser, Danya (7102074282); Steele, Miriam (56260170600); Hammarlund, Mårten (57221534814); Schuengel, Carlo (6602281287); Bakermans-Kranenburg, Marian J. (6701679127); Steele, Howard (7004571268); Shaver, Phillip R. (57203070175); Lux, Ulrike (56545715500); Simmonds, John (16246342900); Jacobvitz, Deborah B. (6603068426); Groh, Ashley M. (26537486100); Bernard, Kristin (35104289000); Cyr, Chantal (7003816689); Hazen, Nancy L. (8508553200); Foster, Sarah L. (57195201280); Psouni, Elia (6506739482); Cowan, Philip A. (7101694404); Cowan, Carolyn Pape (7103083204); Rifkin-Graboi, Anne E. (57211249392); Wilkins, David (35504016600); Pierrehumbert, Blaise (6603781343); Tarabulsy, George M. (6602206972); Cárcamo, Rodrigo A. (55586483100); Wang, Zhengyan (15732310200); Liang, Xi (56228352800); Kaźmierczak, Maria (36955068800); Pawlicka, Paulina (55356540900); Ayiro, Lilian (57221532900); Chansa, Tamara (57221520508); Sichimba, Francis (57190761430); Mooya, Haatembo (57190762169); McLean, Loyola M. (24725006200); Veríssimo, Manuela (14323784700); Gojman de Millán, Sonia (6507544981); Marlene Marie Moretti, Marlene M. (7102632689); Bacro, Fabien (26034553500); Peltola, Mikko J. (59827729500); Galbally, Megan (15065261700); Kondo-Ikemura, Kiyomi (6506653369); Behrens, Kazuko Y. (7004078919); Scott, Stephen K. (7401505816); Fresno, Andres (26034519500); Spencer-Contreras, Rosario (26034731300); Posada, Germán E. (6603792041); Cassibba, Rosalinda (6505829393); Barrantes-Vidal, Neus I. (6507516897); Palacios, Jesús P. (12139498000); Barone, Lavinia (9736349600); Madigan, Sheri L. (7004362362); Mason-Jones, Karen (57428450500); Reijman, Sophie (55344308100); Juffer, Femmie (6603157213); Fearon, Pasco R.M. (59608794400); Bernier, Annie (7003417976); Cicchetti, Dante (35499611700); Roisman, Glenn I. (6602728149); Cassidy, Jude (7201543471); Kindler, Heinz (24338347400); Zimmermann, Peter Lutz (24801090500); Feldman, Ruth (7402660220); Spangle, Gottfried (57428028900); Zeanah, Charles H. (7006020893); Dozier, Mary (7004257744); Belsky, J. (7006451757); Lamb, Michael E. (7102285207); Duschinsky, Robbie (36986651700) | C16: 57208786335; 6602281537; 7005398271; 7006933186; 7102074282; 56260170600; 57221534814; 6602281287; 6701679127; 7004571268; 57203070175; 56545715500; 16246342900; 6603068426; 26537486100; 35104289000; 7003816689; 8508553200; 57195201280; 6506739482; 7101694404; 7103083204; 57211249392; 35504016600; 6603781343; 6602206972; 55586483100; 15732310200; 56228352800; 36955068800; 55356540900; 57221532900; 57221520508; 57190761430; 57190762169; 24725006200; 14323784700; 6507544981; 7102632689; 26034553500; 59827729500; 15065261700; 6506653369; 7004078919; 7401505816; 26034519500; 26034731300; 6603792041; 6505829393; 6507516897; 12139498000; 9736349600; 7004362362; 57428450500; 55344308100; 6603157213; 59608794400; 7003417976; 35499611700; 6602728149; 7201543471; 24338347400; 24801090500; 7402660220; 57428028900; 7006020893; 7004257744; 7006451757; 7102285207; 36986651700 | D16: Attachment goes to court: Child protection and custody issues; El Apego Va a Juicio: Problemas de Custodia y Protección Infantil | E16: 2022 | F16: Anuario de Psicologia Juridica | G16: 32 | H16: 1 | L16: 115 | M16: 10.1080/14616734.2020.1840762 | N16: https://www.scopus.com/inward/record.uri?eid=2-s2.0-85099397481&doi=10.1080%2F14616734.2020.1840762&partnerID=40&md5=067a51e3b269888ddfb8965c57c780a9 | O16: Department of Psychology, Stockholms universitet, Stockholm, Stockholm, Sweden; SUF Resource Center, Uppsala, Uppsala, Sweden; Department of Psychology, Erasmus Universiteit Rotterdam, Rotterdam, Zuid-Holland, Netherlands; School of Psychological Sciences, University of Haifa, Haifa, Israel; Great Ormond Street Hospital for Children NHS Foundation Trust, London, United Kingdom; Educational and Health Psychology, University College London, London, United Kingdom; Department of Psychology, The New School, New York, NY, United States; Department of Clinical Child and Family Studies, Vrije Universiteit Amsterdam, Amsterdam, Noord-Holland, Netherlands; University of California, Davis, Davis, CA, United States; Department of Families and Family Policies, Deutsches Jugendinstitut, Munich, Bayern, Germany; CoramBAAF Academy of Adoption and Fostering, London, United Kingdom; Department of Human Development and Family Sciences, The University of Texas at Austin, Austin, TX, United States; Department of Psychology, University of Missouri, Columbia, MO, United States; Department of Psychology, Stony Brook University, Stony Brook, NY, United States; Department of Psychology, Université du Québec à Montréal, Montreal, QC, Canada; Department of Social Work, University of Northumbria, Newcastle, Tyne and Wear, United Kingdom; Institutionen för Psykologi, Lund, Skane, Sweden; Department of Psychology, University of California, Berkeley, Berkeley, CA, United States; A*STAR Institute for Human Development and Potential, Singapore City, Singapore; College of Arts, Humanities and Social Sciences, Cardiff, Wales, United Kingdom; Université de Lausanne (UNIL), Lausanne, VD, Switzerland; School of Psychology, Université Laval, Quebec, QC, Canada; Department of Psychology, Universidad de Magallanes, Punta Arenas, MA, Chile; Research Center for Child Development, Capital Normal University, Beijing, Beijing, China; Institute of Psychology, Uniwersytet Gdański, Gdansk, Pomeranian, Poland; Department of Educational Psychology, Maseno University, Maseno, Nyanza, Kenya; Department of Psychology, University of Zambia, Lusaka, Zambia; Faculty of Medicine and Health, Sydney, NSW, Australia; ISPA - Instituto Universitário, Lisbon, Portugal; Centro de investigación del Seminario de Sociopsicoanálisis, Mexico City, Mexico; Department of Psychology, Simon Fraser University, Burnaby, BC, Canada; Faculté de Psychologie, Nantes Université, Nantes, Pays-de-la-Loire, France; Human Information Processing Laboratory, Tampere University, Tampere, Pirkanmaa, Finland; Engineering and Education, Murdoch University, Perth, WA, Australia; School of Medicine, The University of Notre Dame Australia, Fremantle, WA, Australia; King Edward Memorial Hospital for Women, Perth, WA, Australia; Department of Psychology, Teikyo University, Tokyo, Japan; Department of Social and Behavioral Sciences, SUNY Polytechnic Institute, Utica, NY, United States; Psychology and Neuroscience, King's College London, London, United Kingdom; Department of Psychology, Universidad de Talca, Talca, ML, Chile; College of Health and Human Sciences, West Lafayette, IN, United States; Department of Educational Sciences, Università degli studi di Bari Aldo Moro, Bari, BA, Italy; Departament de Psicologia Clínica i de la Salut, Universitat Autònoma de Barcelona, Cerdanyola del Valles, Barcelona, Spain; Sant Pere Claver - Fundació Sanitària, Barcelona, Catalonia, Spain; Centro de Investigación Biomédica En Red de Salud Mental, Madrid, Madrid, Spain; Departamento de Psicología Evolutiva y de la Educación, Universidad de Sevilla, Sevilla, Seville, Spain; Department of Brain and Behavioral Sciences, Università degli Studi di Pavia, Pavia, PV, Italy; Cumming School of Medicine, Calgary, AB, Canada; Alberta Children’s Hospital Research Institute, Calgary, AB, Canada; Center for Health and Community, University of California, Fairfield, CA, United States; Department of Public Health and Primary Care, Cambridge, Cambridgeshire, United Kingdom; Centre for Child and Family Studies, Universiteit Leiden, Leiden, Zuid-Holland, Netherlands; Educational and Health Psychology, University College London, London, United Kingdom; Department of Psychology, University of Montreal, Montreal, QC, Canada; Department of Psychiatry, University of Minnesota Twin Cities, Minneapolis, MN, United States; University of Minnesota Twin Cities, Minneapolis, MN, United States; Department of Psychology, University of Maryland, College Park, College Park, MD, United States; Deutsches Jugendinstitut, Munich, Bayern, Germany; Department of Developmental Psychology, Bergische Universität Wuppertal, Wuppertal, Nordrhein-Westfalen, Germany; Baruch Ivcher School of Psychology, Reichman University, Herzliya, Tel Aviv, Israel; Yale Child Study Center, New Haven, CT, United States; Department of Psychology, Friedrich-Alexander-Universität Erlangen-Nürnberg, Erlangen, Bayern, Germany; Tulane University School of Medicine, New Orleans, LA, United States; Department of Psychological and Brain Sciences, University of Delaware, Newark, DE, United States; Department of Human Ecology, University of California, Fairfield, CA, United States; Department of Psychology, University of Cambridge, Cambridge, Cambridgeshire, United Kingdom | P16: Forslund, Tommie, Department of Psychology, Stockholms universitet, Stockholm, Stockholm, Sweden, SUF Resource Center, Uppsala, Uppsala, Sweden; Granqvist, Pehr Granqvistand, Department of Psychology, Stockholms universitet, Stockholm, Stockholm, Sweden; van IJzendoorn, Marinus H., Department of Psychology, Erasmus Universiteit Rotterdam, Rotterdam, Zuid-Holland, Netherlands; Sagi-Schwartz, Abraham, School of Psychological Sciences, University of Haifa, Haifa, Israel; Glaser, Danya, Great Ormond Street Hospital for Children NHS Foundation Trust, London, United Kingdom, Educational and Health Psychology, University College London, London, United Kingdom; Steele, Miriam, Department of Psychology, The New School, New York, NY, United States; Hammarlund, Mårten, Department of Psychology, Stockholms universitet, Stockholm, Stockholm, Sweden; Schuengel, Carlo, Department of Clinical Child and Family Studies, Vrije Universiteit Amsterdam, Amsterdam, Noord-Holland, Netherlands; Bakermans-Kranenburg, Marian J., Department of Clinical Child and Family Studies, Vrije Universiteit Amsterdam, Amsterdam, Noord-Holland, Netherlands; Steele, Howard, Department of Psychology, The New School, New York, NY, United States; Shaver, Phillip R., University of California, Davis, Davis, CA, United States; Lux, Ulrike, Department of Families and Family Policies, Deutsches Jugendinstitut, Munich, Bayern, Germany; Simmonds, John, CoramBAAF Academy of Adoption and Fostering, London, United Kingdom; Jacobvitz, Deborah B., Department of Human Development and Family Sciences, The University of Texas at Austin, Austin, TX, United States; Groh, Ashley M., Department of Psychology, University of Missouri, Columbia, MO, United States; Bernard, Kristin, Department of Psychology, Stony Brook University, Stony Brook, NY, United States; Cyr, Chantal, Department of Psychology, Université du Québec à Montréal, Montreal, QC, Canada; Hazen, Nancy L., Department of Human Development and Family Sciences, The University of Texas at Austin, Austin, TX, United States; Foster, Sarah L., Department of Social Work, University of Northumbria, Newcastle, Tyne and Wear, United Kingdom; Psouni, Elia, Institutionen för Psykologi, Lund, Skane, Sweden; Cowan, Philip A., Department of Psychology, University of California, Berkeley, Berkeley, CA, United States; Cowan, Carolyn Pape, Department of Psychology, University of California, Berkeley, Berkeley, CA, United States; Rifkin-Graboi, Anne E., A*STAR Institute for Human Development and Potential, Singapore City, Singapore; Wilkins, David, College of Arts, Humanities and Social Sciences, Cardiff, Wales, United Kingdom; Pierrehumbert, Blaise, Université de Lausanne (UNIL), Lausanne, VD, Switzerland; Tarabulsy, George M., School of Psychology, Université Laval, Quebec, QC, Canada; Cárcamo, Rodrigo A., Department of Psychology, Universidad de Magallanes, Punta Arenas, MA, Chile; Wang, Zhengyan, Research Center for Child Development, Capital Normal University, Beijing, Beijing, China; Liang, Xi, Research Center for Child Development, Capital Normal University, Beijing, Beijing, China; Kaźmierczak, Maria, Institute of Psychology, Uniwersytet Gdański, Gdansk, Pomeranian, Poland; Pawlicka, Paulina, Institute of Psychology, Uniwersytet Gdański, Gdansk, Pomeranian, Poland; Ayiro, Lilian, Department of Educational Psychology, Maseno University, Maseno, Nyanza, Kenya; Chansa, Tamara, Department of Psychology, University of Zambia, Lusaka, Zambia; Sichimba, Francis, Department of Psychology, University of Zambia, Lusaka, Zambia; Mooya, Haatembo, Department of Psychology, University of Zambia, Lusaka, Zambia; McLean, Loyola M., Faculty of Medicine and Health, Sydney, NSW, Australia; Veríssimo, Manuela, ISPA - Instituto Universitário, Lisbon, Portugal; Gojman de Millán, Sonia, Centro de investigación del Seminario de Sociopsicoanálisis, Mexico City, Mexico; Marlene Marie Moretti, Marlene M., Department of Psychology, Simon Fraser University, Burnaby, BC, Canada; Bacro, Fabien, Faculté de Psychologie, Nantes Université, Nantes, Pays-de-la-Loire, France; Peltola, Mikko J., Human Information Processing Laboratory, Tampere University, Tampere, Pirkanmaa, Finland; Galbally, Megan, Engineering and Education, Murdoch University, Perth, WA, Australia, School of Medicine, The University of Notre Dame Australia, Fremantle, WA, Australia, King Edward Memorial Hospital for Women, Perth, WA, Australia; Kondo-Ikemura, Kiyomi, Department of Psychology, Teikyo University, Tokyo, Japan; Behrens, Kazuko Y., Department of Social and Behavioral Sciences, SUNY Polytechnic Institute, Utica, NY, United States; Scott, Stephen K., Psychology and Neuroscience, King's College London, London, United Kingdom; Fresno, Andres, Department of Psychology, Universidad de Talca, Talca, ML, Chile; Spencer-Contreras, Rosario, Department of Psychology, Universidad de Talca, Talca, ML, Chile; Posada, Germán E., College of Health and Human Sciences, West Lafayette, IN, United States; Cassibba, Rosalinda, Department of Educational Sciences, Università degli studi di Bari Aldo Moro, Bari, BA, Italy; Barrantes-Vidal, Neus I., Departament de Psicologia Clínica i de la Salut, Universitat Autònoma de Barcelona, Cerdanyola del Valles, Barcelona, Spain, Sant Pere Claver - Fundació Sanitària, Barcelona, Catalonia, Spain, Centro de Investigación Biomédica En Red de Salud Mental, Madrid, Madrid, Spain; Palacios, Jesús P., Departamento de Psicología Evolutiva y de la Educación, Universidad de Sevilla, Sevilla, Seville, Spain; Barone, Lavinia, Department of Brain and Behavioral Sciences, Università degli Studi di Pavia, Pavia, PV, Italy; Madigan, Sheri L., Cumming School of Medicine, Calgary, AB, Canada, Alberta Children’s Hospital Research Institute, Calgary, AB, Canada; Mason-Jones, Karen, Center for Health and Community, University of California, Fairfield, CA, United States; Reijman, Sophie, Department of Public Health and Primary Care, Cambridge, Cambridgeshire, United Kingdom; Juffer, Femmie, Centre for Child and Family Studies, Universiteit Leiden, Leiden, Zuid-Holland, Netherlands; Fearon, Pasco R.M., Educational and Health Psychology, University College London, London, United Kingdom; Bernier, Annie, Department of Psychology, University of Montreal, Montreal, QC, Canada; Cicchetti, Dante, Department of Psychiatry, University of Minnesota Twin Cities, Minneapolis, MN, United States; Roisman, Glenn I., University of Minnesota Twin Cities, Minneapolis, MN, United States; Cassidy, Jude, Department of Psychology, University of Maryland, College Park, College Park, MD, United States; Kindler, Heinz, Deutsches Jugendinstitut, Munich, Bayern, Germany; Zimmermann, Peter Lutz, Department of Developmental Psychology, Bergische Universität Wuppertal, Wuppertal, Nordrhein-Westfalen, Germany; Feldman, Ruth, Baruch Ivcher School of Psychology, Reichman University, Herzliya, Tel Aviv, Israel, Yale Child Study Center, New Haven, CT, United States; Spangle, Gottfried, Department of Psychology, Friedrich-Alexander-Universität Erlangen-Nürnberg, Erlangen, Bayern, Germany; Zeanah, Charles H., Tulane University School of Medicine, New Orleans, LA, United States; Dozier, Mary, Department of Psychological and Brain Sciences, University of Delaware, Newark, DE, United States; Belsky, J., Department of Human Ecology, University of California, Fairfield, CA, United States; Lamb, Michael E., Department of Psychology, University of Cambridge, Cambridge, Cambridgeshire, United Kingdom; Duschinsky, Robbie, Department of Psychology, University of Cambridge, Cambridge, Cambridgeshire, United Kingdom | Q16: T. Forslund; Department of Psychology, Stockholm University, Stockholm, Sweden; email: tommie.forslund@psychology.su.se | S16: Colegio Oficial de la Psicologia de Madrid | T16: 11330740 | W16: 33427578 | X16: Spanish | Y16: Anu. Psicol. Jurid. | Z16: Article | AA16: Final | AB16: All Open Access; Green Accepted Open Access; Green Open Access; Hybrid Gold Open Access | AC16: Scopus | AD16: 2-s2.0-85099397481
A17: Taeihagh, A.; Ramesh, M.; Howlett, M. | B17: Taeihagh, Araz (57203976934); Ramesh, M. (7006248680); Howlett, Michael P. (7004315057) | C17: 57203976934; 7006248680; 7004315057 | D17: Assessing the regulatory challenges of emerging disruptive technologies | E17: 2021 | F17: Regulation and Governance | G17: 15 | H17: 4 | J17: 1009 | K17: 1019 | L17: 113 | M17: 10.1111/rego.12392 | N17: https://www.scopus.com/inward/record.uri?eid=2-s2.0-85101910581&doi=10.1111%2Frego.12392&partnerID=40&md5=602f91ee5526fefdc4ebd9980e04f3d3 | O17: Lee Kuan Yew School of Public Policy, Singapore City, Singapore; Simon Fraser University, Burnaby, BC, Canada | P17: Taeihagh, Araz, Lee Kuan Yew School of Public Policy, Singapore City, Singapore; Ramesh, M., Lee Kuan Yew School of Public Policy, Singapore City, Singapore; Howlett, Michael P., Simon Fraser University, Burnaby, BC, Canada | Q17: A. Taeihagh; Lee Kuan Yew School of Public Policy, National University of Singapore, Singapore; email: spparaz@nus.edu.sg | S17: John Wiley and Sons Inc | T17: 17485983 | X17: English | Y17: Regul. Governance | Z17: Article | AA17: Final | AB17: All Open Access; Hybrid Gold Open Access | AC17: Scopus | AD17: 2-s2.0-85101910581
A18: Vierros, M.K.; Harrison, A.-L.; Sloat, M.R.; Ortuño Crespo, G.O.; Moore, J.W.; Dunn, D.C.; Ota, Y.; Cisneros-Montemayor, A.M.; Shillinger, G.L.; Watson, T.K.; Govan, H. | B18: Vierros, Marjo K. (24451401600); Harrison, Autumn-Lynn Lynn (36021181800); Sloat, Matthew R. (55988867800); Ortuño Crespo, Guillermo (57201949487); Moore, Jonathan W. (7405239862); Dunn, Daniel C. (23977458400); Ota, Yoshitaka (36183559300); Cisneros-Montemayor, Andrés Miguel (36094057100); Shillinger, George L. (36780505400); Watson, Trisha Kehaulani (54916273800); Govan, Hugh (55568817800) | C18: 24451401600; 36021181800; 55988867800; 57201949487; 7405239862; 23977458400; 36183559300; 36094057100; 36780505400; 54916273800; 55568817800 | D18: Considering Indigenous Peoples and local communities in governance of the global ocean commons | E18: 2020 | F18: Marine Policy | G18: 119 | I18: 104039 | L18: 111 | M18: 10.1016/j.marpol.2020.104039 | N18: https://www.scopus.com/inward/record.uri?eid=2-s2.0-85085976665&doi=10.1016%2Fj.marpol.2020.104039&partnerID=40&md5=6a746c2eb4391f428983c3cb66eedc82 | O18: Coastal Policy and Humanities Research, Vancouver, BC, Canada; Smithsonian Migratory Bird Center, National Zoo, Washington, D.C., DC, United States; Wild Salmon Center, Portland, OR, United States; Marine Geospatial Ecology Lab, Duke University Marine Laboratory, Beaufort, NC, United States; Department of Biological Sciences, Simon Fraser University, Burnaby, BC, Canada; Centre for Biodiversity and Conservation Science, The University of Queensland, Brisbane, QLD, Australia; School of Marine and Environmental Affairs, University of Washington, Seattle, WA, United States; Nippon Foundation Ocean Nexus Program, The University of British Columbia, Vancouver, BC, Canada; Upwell, Monterey, CA, United States; MigraMar, Mexico City, Mexico; Honua Consulting, Honolulu, HI, United States; School of Government, Development and International Affairs, University of the South Pacific, Suva, Fiji | P18: Vierros, Marjo K., Coastal Policy and Humanities Research, Vancouver, BC, Canada; Harrison, Autumn-Lynn Lynn, Smithsonian Migratory Bird Center, National Zoo, Washington, D.C., DC, United States; Sloat, Matthew R., Wild Salmon Center, Portland, OR, United States; Ortuño Crespo, Guillermo, Marine Geospatial Ecology Lab, Duke University Marine Laboratory, Beaufort, NC, United States; Moore, Jonathan W., Department of Biological Sciences, Simon Fraser University, Burnaby, BC, Canada; Dunn, Daniel C., Marine Geospatial Ecology Lab, Duke University Marine Laboratory, Beaufort, NC, United States, Centre for Biodiversity and Conservation Science, The University of Queensland, Brisbane, QLD, Australia; Ota, Yoshitaka, School of Marine and Environmental Affairs, University of Washington, Seattle, WA, United States; Cisneros-Montemayor, Andrés Miguel, Nippon Foundation Ocean Nexus Program, The University of British Columbia, Vancouver, BC, Canada; Shillinger, George L., Upwell, Monterey, CA, United States, MigraMar, Mexico City, Mexico; Watson, Trisha Kehaulani, Honua Consulting, Honolulu, HI, United States; Govan, Hugh, School of Government, Development and International Affairs, University of the South Pacific, Suva, Fiji | Q18: M.K. Vierros; Coastal Policy and Humanities Research, Vancouver, 313-1869 Spyglass Place, BC V5Z 4K7, Canada; email: mvierros@shaw.ca | S18: Elsevier Ltd | T18: 0308597X | X18: English | Y18: Mar. Policy | Z18: Article | AA18: Final | AB18: All Open Access; Hybrid Gold Open Access | AC18: Scopus | AD18: 2-s2.0-85085976665
A19: Samantha Sherman, C.S.; Simpfendorfer, C.A.; Pacoureau, N.; Matsushiba, J.H.; Yan, H.F.; Walls, R.H.L.; Rigby, C.L.; VanderWright, W.J.; Jabado, R.W.; Pollom, R.A.; Carlson, J.K.; Charvet, P.; Bin Ali, A.; Fahmi, u.; Cheok, J.; Derrick, D.H.; Herman, K.B.; Finucci, B.; Eddy, T.D.; Palomares, M.L.D.; Avalos-Castillo, C.G.; Kinattumkara, B.; Blanco-Parra, M.-D.-P.; Dharmadi; Espinoza, M.; Fernando, D.; Haque, A.B.; Mejía-Falla, P.A.; Navia, A.F.; Pérez-Jiménez, J.C.; Utzurrum, J.; Yuneni, R.R.; Dulvy, N.K. | B19: Samantha Sherman, C. Samantha (57201135135); Simpfendorfer, Colin Ashley (7006384244); Pacoureau, Nathan (57193672572); Matsushiba, Jay H. (57322681100); Yan, Helen F. (57207830284); Walls, Rachel H.L. (57193609072); Rigby, Cassandra L. (55861767500); VanderWright, Wade J. (57221648300); Jabado, Rima W. (55620252300); Pollom, Riley A. (56648020100); Carlson, John K. (7402114854); Charvet, Patricia (36088750500); Bin Ali, Ahmad (58068610900); Fahmi, undefined (15831840800); Cheok, Jessica (57191909106); Derrick, Danielle H. (57217233093); Herman, Katelyn B. (57204150378); Finucci, Brittany (57191157018); Eddy, Tyler D. (36625376900); Palomares, Maria Lourdes D. (6701408907); Avalos-Castillo, Cristopher G. (57202275200); Kinattumkara, Bineesh K. (57211978864); Blanco-Parra, Maria del Pilar (36126073500); Dharmadi (54899255700); Espinoza, Mario (36936003300); Fernando, Daniel (56443685100); Haque, Alifa Bintha (57205220343); Mejía-Falla, Paola Andrea (15830273300); Navia, Andrés Felipe (57220258131); Pérez-Jiménez, Juan Carlos (56000863100); Utzurrum, Jean (57219975081); Yuneni, Ranny Ramadhani (57224985119); Dulvy, Nicholas K. (6701844802) | C19: 57201135135; 7006384244; 57193672572; 57322681100; 57207830284; 57193609072; 55861767500; 57221648300; 55620252300; 56648020100; 7402114854; 36088750500; 58068610900; 15831840800; 57191909106; 57217233093; 57204150378; 57191157018; 36625376900; 6701408907; 57202275200; 57211978864; 36126073500; 54899255700; 36936003300; 56443685100; 57205220343; 15830273300; 57220258131; 56000863100; 57219975081; 57224985119; 6701844802 | D19: Half a century of rising extinction risk of coral reef sharks and rays | E19: 2023 | F19: Nature Communications | G19: 14 | H19: 1 | I19: 15 | L19: 100 | M19: 10.1038/s41467-022-35091-x | N19: https://www.scopus.com/inward/record.uri?eid=2-s2.0-85146411755&doi=10.1038%2Fs41467-022-35091-x&partnerID=40&md5=b1d71dcf59a6c52f3f1db052e9064081 | O19: Department of Biological Sciences, Simon Fraser University, Burnaby, BC, Canada; TRAFFIC International, Cambridge, Cambridgeshire, United Kingdom; College of Science and Engineering, James Cook University, Townsville, QLD, Australia; Institute for Marine and Antarctic Studies, Hobart, TS, Australia; Department of Fish and Wildlife Conservation, Virginia Polytechnic Institute and State University, Blacksburg, VA, United States; College of Science and Engineering, James Cook University, Townsville, QLD, Australia; James Cook University, Townsville, QLD, Australia; Elasmo Project, Dubai, Dubai, United Arab Emirates; Species Recovery Program, Seattle, WA, United States; National Oceanic and Atmospheric Administration, Washington, D.C., DC, United States; Universidade Federal do Ceará, Fortaleza, CE, Brazil; Universidade Federal do Parana, Curitiba, PR, Brazil; Chendering, Southeast Asian Fisheries Development Center, Kuala Terengganu, Terengganu, Malaysia; Research Center for Oceanography, Badan Riset dan Inovasi Nasional, Central Jakarta, Jakarta, Indonesia; Georgia Aquarium, Atlanta, GA, United States; National Institute of Water and Atmospheric Research, Auckland, AUK, New Zealand; Centre for Fisheries Ecosystems Research, Marine Institute of Memorial University of Newfoundland, St John's, NL, Canada; Institute for the Oceans and Fisheries, The University of British Columbia, Vancouver, BC, Canada; Fundación Mundo Azul, Villa Canales, Guatemala; Centro de Estudios del Mar y Acuicultura, Universidad de San Carlos de Guatemala, Guatemala City, Guatemala; Zoological Survey of India, Kolkata, WB, India; Consejo Nacional de Humanidades, Ciencias y Tecnologías, Mexico, Mexico; Del Bosque, Universidad Autónoma del Estado de Quintana Roo, Chetumal, ROO, Mexico; Fundación Internacional para la Naturaleza y la Sustentabilidad (FINS), Chetumal, ROO, Mexico; Centro de Investigación en Ciencias del Mar y Limnología, Universidad de Costa Rica, San Jose, San Jose, Costa Rica; Universidad de Costa Rica, San Jose, San Jose, Costa Rica; Blue Resources Trust, Kalkudah, Batticaloa, Sri Lanka; Department of Biology and Environment Science, Linnaeus University, Kalmar, Kalmar, Kalmar, Sweden; University of Oxford, Oxford, Oxfordshire, United Kingdom; Department of Zoology, University of Dhaka, Dhaka, Bangladesh; Wildlife Conservation Society - WCS Colombia, Cali, Valle del Cauca, Colombia; Fundación colombiana para la investigación y conservación de tiburones y rayas - SQUALUS, Cali, Valle del Cauca, Colombia; El Colegio de la Frontera Sur, Tapachula, CHP, Mexico; 1st Avenue, Marine Wildlife Watch of the Philippines, Bonifacio Global City, Philippines; Silliman University, Dumaguete, Philippines; WWF-Indonesia, Jakarta, Indonesia | P19: Samantha Sherman, C. Samantha, Department of Biological Sciences, Simon Fraser University, Burnaby, BC, Canada, TRAFFIC International, Cambridge, Cambridgeshire, United Kingdom; Simpfendorfer, Colin Ashley, College of Science and Engineering, James Cook University, Townsville, QLD, Australia, Institute for Marine and Antarctic Studies, Hobart, TS, Australia; Pacoureau, Nathan, Department of Fish and Wildlife Conservation, Virginia Polytechnic Institute and State University, Blacksburg, VA, United States; Matsushiba, Jay H., Department of Biological Sciences, Simon Fraser University, Burnaby, BC, Canada; Yan, Helen F., College of Science and Engineering, James Cook University, Townsville, QLD, Australia, James Cook University, Townsville, QLD, Australia; Walls, Rachel H.L., Department of Biological Sciences, Simon Fraser University, Burnaby, BC, Canada; Rigby, Cassandra L., College of Science and Engineering, James Cook University, Townsville, QLD, Australia; VanderWright, Wade J., Department of Biological Sciences, Simon Fraser University, Burnaby, BC, Canada; Jabado, Rima W., College of Science and Engineering, James Cook University, Townsville, QLD, Australia, Elasmo Project, Dubai, Dubai, United Arab Emirates; Pollom, Riley A., Species Recovery Program, Seattle, WA, United States; Carlson, John K., National Oceanic and Atmospheric Administration, Washington, D.C., DC, United States; Charvet, Patricia, Universidade Federal do Ceará, Fortaleza, CE, Brazil, Universidade Federal do Parana, Curitiba, PR, Brazil; Bin Ali, Ahmad, Chendering, Southeast Asian Fisheries Development Center, Kuala Terengganu, Terengganu, Malaysia; Fahmi, undefined, Research Center for Oceanography, Badan Riset dan Inovasi Nasional, Central Jakarta, Jakarta, Indonesia; Cheok, Jessica, Department of Biological Sciences, Simon Fraser University, Burnaby, BC, Canada; Derrick, Danielle H., Department of Biological Sciences, Simon Fraser University, Burnaby, BC, Canada; Herman, Katelyn B., Georgia Aquarium, Atlanta, GA, United States; Finucci, Brittany, National Institute of Water and Atmospheric Research, Auckland, AUK, New Zealand; Eddy, Tyler D., Centre for Fisheries Ecosystems Research, Marine Institute of Memorial University of Newfoundland, St John's, NL, Canada; Palomares, Maria Lourdes D., Institute for the Oceans and Fisheries, The University of British Columbia, Vancouver, BC, Canada; Avalos-Castillo, Cristopher G., Fundación Mundo Azul, Villa Canales, Guatemala, Centro de Estudios del Mar y Acuicultura, Universidad de San Carlos de Guatemala, Guatemala City, Guatemala; Kinattumkara, Bineesh K., Zoological Survey of India, Kolkata, WB, India; Blanco-Parra, Maria del Pilar, Consejo Nacional de Humanidades, Ciencias y Tecnologías, Mexico, Mexico, Del Bosque, Universidad Autónoma del Estado de Quintana Roo, Chetumal, ROO, Mexico, Fundación Internacional para la Naturaleza y la Sustentabilidad (FINS), Chetumal, ROO, Mexico; Dharmadi, null, ; Espinoza, Mario, Centro de Investigación en Ciencias del Mar y Limnología, Universidad de Costa Rica, San Jose, San Jose, Costa Rica, Universidad de Costa Rica, San Jose, San Jose, Costa Rica; Fernando, Daniel, Blue Resources Trust, Kalkudah, Batticaloa, Sri Lanka, Department of Biology and Environment Science, Linnaeus University, Kalmar, Kalmar, Kalmar, Sweden; Haque, Alifa Bintha, University of Oxford, Oxford, Oxfordshire, United Kingdom, Department of Zoology, University of Dhaka, Dhaka, Bangladesh; Mejía-Falla, Paola Andrea, Wildlife Conservation Society - WCS Colombia, Cali, Valle del Cauca, Colombia, Fundación colombiana para la investigación y conservación de tiburones y rayas - SQUALUS, Cali, Valle del Cauca, Colombia; Navia, Andrés Felipe, Fundación colombiana para la investigación y conservación de tiburones y rayas - SQUALUS, Cali, Valle del Cauca, Colombia; Pérez-Jiménez, Juan Carlos, El Colegio de la Frontera Sur, Tapachula, CHP, Mexico; Utzurrum, Jean, 1st Avenue, Marine Wildlife Watch of the Philippines, Bonifacio Global City, Philippines, Silliman University, Dumaguete, Philippines; Yuneni, Ranny Ramadhani, WWF-Indonesia, Jakarta, Indonesia; Dulvy, Nicholas K., Department of Biological Sciences, Simon Fraser University, Burnaby, BC, Canada | Q19: C.S. Sherman; Earth to Ocean Research Group, Biological Sciences, Simon Fraser University, Burnaby, 8888 University Drive, V5A 1S6, Canada; email: sammsherman27@gmail.com | S19: Nature Research | W19: 36650137 | X19: English | Y19: Nat. Commun. | Z19: Article | AA19: Final | AB19: All Open Access; Gold Open Access; Green Accepted Open Access; Green Open Access | AC19: Scopus | AD19: 2-s2.0-85146411755
A20: Hosford, K.; Beairsto, J.; Winters, M. | B20: Hosford, Kate (57202954215); Beairsto, Jeneva (57205549634); Winters, Meghan L. (16235208800) | C20: 57202954215; 57205549634; 16235208800 | D20: Is the 15-minute city within reach? Evaluating walking and cycling accessibility to grocery stores in Vancouver | E20: 2022 | F20: Transportation Research Interdisciplinary Perspectives | G20: 14 | I20: 100602 | L20: 95 | M20: 10.1016/j.trip.2022.100602 | N20: https://www.scopus.com/inward/record.uri?eid=2-s2.0-85128317259&doi=10.1016%2Fj.trip.2022.100602&partnerID=40&md5=15c93ad16f6629e912ec5a38ecc5729d | O20: Simon Fraser University, Burnaby, BC, Canada | P20: Hosford, Kate, Simon Fraser University, Burnaby, BC, Canada; Beairsto, Jeneva, Simon Fraser University, Burnaby, BC, Canada; Winters, Meghan L., Simon Fraser University, Burnaby, BC, Canada | Q20: K. Hosford; Faculty of Health Sciences, Simon Fraser University, Burnaby, 8888 University Drive, V5A1S6, Canada; email: khosford@sfu.ca | S20: Elsevier Ltd | X20: English | Y20: Transp. Res. Interdiscip. Perspect. | Z20: Article | AA20: Final | AB20: All Open Access; Gold Open Access; Green Accepted Open Access; Green Open Access | AC20: Scopus | AD20: 2-s2.0-85128317259
A21: McAlvay, A.C.; Armstrong, C.G.; Baker, J.; Elk, L.B.; Bosco, S.; Hanazaki, N.; Joseph, L.; Martinez-Cruz, T.E.; Nesbitt, M.; Palmer, M.A.; Priprá de Almeida, W.C.; Anderson, J.; Asfaw, Z.; Borokini, I.T.; Cano-Contreras, E.J.; Hoyte, S.; Hudson, M.; Ladio, A.H.; Odonne, G.; Peter, S.; Rashford, J.; Wall, J.; Wolverton, S.; Vandebroek, I. | B21: McAlvay, Alex C. (57193439995); Armstrong, Chelsey Geralda Denise (56608716400); Baker, Janelle Marie (57195205719); Elk, Linda Black (57241528500); Bosco, Samantha (57241543700); Hanazaki, Natalia (6602817855); Joseph, Leigh (57221385946); Martinez-Cruz, Tania Eulalia (56524655800); Nesbitt, Mark (36726113300); Palmer, Meredith Alberta (57217070491); Priprá de Almeida, Walderes Cocta (57241495600); Anderson, Jane E. (55731042900); Asfaw, Zemede (57226701465); Borokini, Israel T. (57202092362); Cano-Contreras, Eréndira Juanita (57241558400); Hoyte, Simon (57216410102); Hudson, Māui L. (16678829800); Ladio, Ana Haydeé (6603227336); Odonne, Guillaume (15926113900); Peter, Sonia (58925947500); Rashford, John H. (6602587387); Wall, Jeffrey Robert (56168382500); Wolverton, Steve (6603656118); Vandebroek, Ina (6507733866) | C21: 57193439995; 56608716400; 57195205719; 57241528500; 57241543700; 6602817855; 57221385946; 56524655800; 36726113300; 57217070491; 57241495600; 55731042900; 57226701465; 57202092362; 57241558400; 57216410102; 16678829800; 6603227336; 15926113900; 58925947500; 6602587387; 56168382500; 6603656118; 6507733866 | D21: Ethnobiology Phase VI: Decolonizing Institutions, Projects, and Scholarship | E21: 2021 | F21: Journal of Ethnobiology | G21: 41 | H21: 2 | J21: 170 | K21: 191 | L21: 95 | M21: 10.2993/0278-0771-41.2.170 | N21: https://www.scopus.com/inward/record.uri?eid=2-s2.0-85114055417&doi=10.2993%2F0278-0771-41.2.170&partnerID=40&md5=17904e2fc1b56ac82792f50726622676 | O21: Institute of Economic Botany, New York, NY, United States; Indigenous Studies, Simon Fraser University, Burnaby, BC, Canada; Anthropology Program, Athabasca University, Athabasca, AB, Canada; UNITED TRIBES TECHNICAL COLLEGE, Bismarck, ND, United States; Horticulture Section, Cornell University, Ithaca, NY, United States; Departamento de Ecologia e Zoologia, Universidade Federal de Santa Catarina, Florianopolis, SC, Brazil; School of Environmental Studies, University of Victoria, Victoria, BC, Canada; Natural Resources Institute, Chatham, Kent, United Kingdom; Royal Botanic Gardens, Kew, Richmond, Surrey, United Kingdom; Department of Science and Technology Studies, Cornell University, Ithaca, NY, United States; Department of History, Universidade Federal de Santa Catarina, Florianopolis, SC, Brazil; Anthropology and Museum Studies, New York University, New York, NY, United States; Department of Plant Biology and Biodiversity Management, Addis Ababa University, Addis Ababa, Ethiopia; Department of Biology, University of Nevada, Reno, Reno, NV, United States; Universidad Nacional Autónoma de México, Mexico, Mexico; Department of Anthropology, University College London, London, United Kingdom; University of Waikato, Hamilton, WKO, New Zealand; Universidad Nacional del Comahue, Neuquen, Neuquen, Argentina; Laboratoire Ecologie, Evolution, Interactions des systèmes amazoniens (LEEISA), Cayenne, French Guiana, France; Biocultural Education and Research Programme, St James, Barbados; Department of Sociology and Anthropology, College of Charleston, Charleston, SC, United States; Department of Geography, University of Guelph, Guelph, ON, Canada; Department of Geography and the Environment, University of North Texas, Denton, TX, United States | P21: McAlvay, Alex C., Institute of Economic Botany, New York, NY, United States; Armstrong, Chelsey Geralda Denise, Indigenous Studies, Simon Fraser University, Burnaby, BC, Canada; Baker, Janelle Marie, Anthropology Program, Athabasca University, Athabasca, AB, Canada; Elk, Linda Black, UNITED TRIBES TECHNICAL COLLEGE, Bismarck, ND, United States; Bosco, Samantha, Horticulture Section, Cornell University, Ithaca, NY, United States; Hanazaki, Natalia, Departamento de Ecologia e Zoologia, Universidade Federal de Santa Catarina, Florianopolis, SC, Brazil; Joseph, Leigh, School of Environmental Studies, University of Victoria, Victoria, BC, Canada; Martinez-Cruz, Tania Eulalia, Natural Resources Institute, Chatham, Kent, United Kingdom; Nesbitt, Mark, Royal Botanic Gardens, Kew, Richmond, Surrey, United Kingdom; Palmer, Meredith Alberta, Department of Science and Technology Studies, Cornell University, Ithaca, NY, United States; Priprá de Almeida, Walderes Cocta, Department of History, Universidade Federal de Santa Catarina, Florianopolis, SC, Brazil; Anderson, Jane E., Anthropology and Museum Studies, New York University, New York, NY, United States; Asfaw, Zemede, Department of Plant Biology and Biodiversity Management, Addis Ababa University, Addis Ababa, Ethiopia; Borokini, Israel T., Department of Biology, University of Nevada, Reno, Reno, NV, United States; Cano-Contreras, Eréndira Juanita, Universidad Nacional Autónoma de México, Mexico, Mexico; Hoyte, Simon, Department of Anthropology, University College London, London, United Kingdom; Hudson, Māui L., University of Waikato, Hamilton, WKO, New Zealand; Ladio, Ana Haydeé, Universidad Nacional del Comahue, Neuquen, Neuquen, Argentina; Odonne, Guillaume, Laboratoire Ecologie, Evolution, Interactions des systèmes amazoniens (LEEISA), Cayenne, French Guiana, France; Peter, Sonia, Biocultural Education and Research Programme, St James, Barbados; Rashford, John H., Department of Sociology and Anthropology, College of Charleston, Charleston, SC, United States; Wall, Jeffrey Robert, Department of Geography, University of Guelph, Guelph, ON, Canada; Wolverton, Steve, Department of Geography and the Environment, University of North Texas, Denton, TX, United States; Vandebroek, Ina, Institute of Economic Botany, New York, NY, United States | Q21: A.C. Mcalvay; Institute of Economic Botany, New York Botanical Garden, Bronx, 2900 Southern Blvd, 10458, United States; email: amcalvay@nybg.org | S21: Society of Ethnobiology | T21: 2780771 | X21: English | Y21: J. Ethnobiology | Z21: Article | AA21: Final | AB21: All Open Access; Green Accepted Open Access; Green Open Access; Hybrid Gold Open Access | AC21: Scopus | AD21: 2-s2.0-85114055417
A22: Bennett, N.J.; Alava, J.J.; Ferguson, C.E.; Blythe, J.; Morgera, E.; Boyd, D.; Côté, I.M. | B22: Bennett, Nathan J. (36774187200); Alava, Juan José (12139754400); Ferguson, Caroline E. (57215671151); Blythe, Jessica L. (60336728800); Morgera, Elisa (6507416841); Boyd, David R. (57220714305); Côté, Isabelle M. (7005488549) | C22: 36774187200; 12139754400; 57215671151; 60336728800; 6507416841; 57220714305; 7005488549 | D22: Environmental (in)justice in the Anthropocene ocean | E22: 2023 | F22: Marine Policy | G22: 147 | I22: 105383 | L22: 92 | M22: 10.1016/j.marpol.2022.105383 | N22: https://www.scopus.com/inward/record.uri?eid=2-s2.0-85145820297&doi=10.1016%2Fj.marpol.2022.105383&partnerID=40&md5=11f31882269a3e26bf2b07e7a612917c | O22: EqualSea Lab, Centro de Investigación Interdisciplinar en Tecnoloxías Ambientais (CRETUS), Santiago de Compostela, A Coruna, Spain; School of Public Policy and Global Affairs, The University of British Columbia, Vancouver, BC, Canada; The Peopled Seas Initiative, Vancouver, BC, Canada; People and the Ocean Specialist Group, International Union for Conservation of Nature and Natural Resources, Gland, Switzerland; Ocean Pollution Research Unit, The University of British Columbia, Vancouver, BC, Canada; School of Resource and Environmental Management, Simon Fraser University, Burnaby, BC, Canada; University of California, Santa Barbara, Santa Barbara, CA, United States; Environmental Sustainability Research Centre, Brock University, St. Catharines, ON, Canada; University of Strathclyde, Glasgow, Scotland, United Kingdom; Environment and Sustainability, The University of British Columbia, Vancouver, BC, Canada; Department of Biological Sciences, Simon Fraser University, Burnaby, BC, Canada | P22: Bennett, Nathan J., EqualSea Lab, Centro de Investigación Interdisciplinar en Tecnoloxías Ambientais (CRETUS), Santiago de Compostela, A Coruna, Spain, School of Public Policy and Global Affairs, The University of British Columbia, Vancouver, BC, Canada, The Peopled Seas Initiative, Vancouver, BC, Canada, People and the Ocean Specialist Group, International Union for Conservation of Nature and Natural Resources, Gland, Switzerland; Alava, Juan José, Ocean Pollution Research Unit, The University of British Columbia, Vancouver, BC, Canada, School of Resource and Environmental Management, Simon Fraser University, Burnaby, BC, Canada; Ferguson, Caroline E., University of California, Santa Barbara, Santa Barbara, CA, United States; Blythe, Jessica L., Environmental Sustainability Research Centre, Brock University, St. Catharines, ON, Canada; Morgera, Elisa, University of Strathclyde, Glasgow, Scotland, United Kingdom; Boyd, David R., School of Public Policy and Global Affairs, The University of British Columbia, Vancouver, BC, Canada, Environment and Sustainability, The University of British Columbia, Vancouver, BC, Canada; Côté, Isabelle M., Department of Biological Sciences, Simon Fraser University, Burnaby, BC, Canada | Q22: N.J. Bennett; EqualSea Lab, Cross-disciplinary Research Center in Environmental Technologies, Universidade de Santiago de Compostela, Santiago de Compostela, Spain; email: nathan.bennett@ubc.ca | S22: Elsevier Ltd | T22: 0308597X | X22: English | Y22: Mar. Policy | Z22: Article | AA22: Final | AC22: Scopus | AD22: 2-s2.0-85145820297
