Workbook

Sheet query1
A1: id | B1: doi | C1: title | D1: publication_year | E1: publication_date | F1: language | G1: type | H1: open_access | I1: authorships | J1: countries_distinct_count | K1: institutions_distinct_count | L1: fwci | M1: has_fulltext | N1: cited_by_count | O1: biblio | P1: primary_topic | Q1: topics | R1: keywords | S1: concepts | T1: sustainable_development_goals | U1: referenced_works_count
A2: https://openalex.org/W2998917588 | B2: https://doi.org/10.3390/rs12020266 | C2: Flood Detection and Susceptibility Mapping Using Sentinel-1 Remote Sensing Data and a Machine Learning Approach: Hybrid Intelligence of Bagging Ensemble Based on K-Nearest Neighbor Classifier | D2: 2020 | E2: 43843 | F2: en | G2: article | H2: {'is_oa': True, 'oa_status': 'gold', 'oa_url': 'https://www.mdpi.com/2072-4292/12/2/266/pdf?version=1579681280', 'any_repository_has_fulltext': True} | I2: [{'author_position': 'first', 'author': {'id': 'https://openalex.org/A5091211368', 'display_name': 'Himan Shahabi', 'orcid': 'https://orcid.org/0000-0001-5091-6947'}, 'institutions': [{'id': 'https://openalex.org/I3124704065', 'display_name': 'University of Kurdistan', 'ror': 'https://ror.org/04k89yk85', 'country_code': 'IR', 'type': 'education', 'lineage': ['https://openalex.org/I3124704065']}], 'countries': ['IR'], 'is_corresponding': True, 'raw_author_name': 'Himan Shahabi', 'raw_affiliation_strings': ['Board Member of Department of Zrebar Lake Environmental Research, Kurdistan Studies Institute, University of Kurdistan, Sanandaj 66177-15175, Iran', 'Department of Geomorphology, Faculty of Natural Resources, University of Kurdistan, Sanandaj 66177-15175, Iran'], 'affiliations': [{'raw_affiliation_string': 'Board Member of Department of Zrebar Lake Environmental Research, Kurdistan Studies Institute, University of Kurdistan, Sanandaj 66177-15175, Iran', 'institution_ids': ['https://openalex.org/I3124704065']}, {'raw_affiliation_string': 'Department of Geomorphology, Faculty of Natural Resources, University of Kurdistan, Sanandaj 66177-15175, Iran', 'institution_ids': ['https://openalex.org/I3124704065']}]}, {'author_position': 'middle', 'author': {'id': 'https://openalex.org/A5063537118', 'display_name': 'Ataollah Shirzadi', 'orcid': 'https://orcid.org/0000-0001-9668-8687'}, 'institutions': [{'id': 'https://openalex.org/I3124704065', 'display_name': 'University of Kurdistan', 'ror': 'https://ror.org/04k89yk85', 'country_code': 'IR', 'type': 'education', 'lineage': ['https://openalex.org/I3124704065']}], 'countries': ['IR'], 'is_corresponding': False, 'raw_author_name': 'Ataollah Shirzadi', 'raw_affiliation_strings': ['Department of Rangeland and Watershed Management, Faculty of Natural Resources, University of Kurdistan, Sanandaj 66177-15175, Iran'], 'affiliations': [{'raw_affiliation_string': 'Department of Rangeland and Watershed Management, Faculty of Natural Resources, University of Kurdistan, Sanandaj 66177-15175, Iran', 'institution_ids': ['https://openalex.org/I3124704065']}]}, {'author_position': 'middle', 'author': {'id': 'https://openalex.org/A5024191113', 'display_name': 'Kayvan Ghaderi', 'orcid': 'https://orcid.org/0000-0002-0741-7744'}, 'institutions': [{'id': 'https://openalex.org/I3124704065', 'display_name': 'University of Kurdistan', 'ror': 'https://ror.org/04k89yk85', 'country_code': 'IR', 'type': 'education', 'lineage': ['https://openalex.org/I3124704065']}], 'countries': ['IR'], 'is_corresponding': False, 'raw_author_name': 'Kayvan Ghaderi', 'raw_affiliation_strings': ['Department of Information Technology and Computer Engineering, Faculty of Engineering, University of Kurdistan, Sanandaj 66177-15175, Iran'], 'affiliations': [{'raw_affiliation_string': 'Department of Information Technology and Computer Engineering, Faculty of Engineering, University of Kurdistan, Sanandaj 66177-15175, Iran', 'institution_ids': ['https://openalex.org/I3124704065']}]}, {'author_position': 'middle', 'author': {'id': 'https://openalex.org/A5081211065', 'display_name': 'Ebrahim Omidvar', 'orcid': 'https://orcid.org/0000-0002-8784-3646'}, 'institutions': [{'id': 'https://openalex.org/I105818395', 'display_name': 'University of Kashan', 'ror': 'https://ror.org/015zmr509', 'country_code': 'IR', 'type': 'education', 'lineage': ['https://openalex.org/I105818395']}], 'countries': ['IR'], 'is_corresponding': False, 'raw_author_name': 'Ebrahim Omidvar', 'raw_affiliation_strings': ['Department of Rangeland and Watershed Management, Faculty of Natural Resources and Earth Sciences, University of Kashan, Kashan 87317-53153, Iran'], 'affiliations': [{'raw_affiliation_string': 'Department of Rangeland and Watershed Management, Faculty of Natural Resources and Earth Sciences, University of Kashan, Kashan 87317-53153, Iran', 'institution_ids': ['https://openalex.org/I105818395']}]}, {'author_position': 'middle', 'author': {'id': 'https://openalex.org/A5070829177', 'display_name': 'Nadhir Alâ€Ansari', 'orcid': 'https://orcid.org/0000-0002-6790-2653'}, 'institutions': [{'id': 'https://openalex.org/I190632392', 'display_name': 'LuleÃ¥ University of Technology', 'ror': 'https://ror.org/016st3p78', 'country_code': 'SE', 'type': 'education', 'lineage': ['https://openalex.org/I190632392']}], 'countries': ['SE'], 'is_corresponding': False, 'raw_author_name': 'Nadhir Al-Ansari', 'raw_affiliation_strings': ['Department of Civil, Environmental and Natural Resources Engineering, Lulea University of Technology, 971 87 Lulea, Sweden'], 'affiliations': [{'raw_affiliation_string': 'Department of Civil, Environmental and Natural Resources Engineering, Lulea University of Technology, 971 87 Lulea, Sweden', 'institution_ids': ['https://openalex.org/I190632392']}]}, {'author_position': 'middle', 'author': {'id': 'https://openalex.org/A5090873433', 'display_name': 'John J. Clague', 'orcid': 'https://orcid.org/0000-0002-2697-2233'}, 'institutions': [{'id': 'https://openalex.org/I18014758', 'display_name': 'Simon Fraser University', 'ror': 'https://ror.org/0213rcc28', 'country_code': 'CA', 'type': 'education', 'lineage': ['https://openalex.org/I18014758']}], 'countries': ['CA'], 'is_corresponding': False, 'raw_author_name': 'John J. Clague', 'raw_affiliation_strings': ['Department of Earth Sciences Simon Fraser University 8888 University Drive Burnaby, Burnaby, BC V5A 1S6, Canada'], 'affiliations': [{'raw_affiliation_string': 'Department of Earth Sciences Simon Fraser University 8888 University Drive Burnaby, Burnaby, BC V5A 1S6, Canada', 'institution_ids': ['https://openalex.org/I18014758']}]}, {'author_position': 'middle', 'author': {'id': 'https://openalex.org/A5081186550', 'display_name': 'Marten Geertsema', 'orcid': 'https://orcid.org/0000-0002-4650-8251'}, 'institutions': [{'id': 'https://openalex.org/I4210131853', 'display_name': 'Ministry of Forests', 'ror': 'https://ror.org/03cx3d993', 'country_code': 'CA', 'type': 'government', 'lineage': ['https://openalex.org/I4210131853']}], 'countries': ['CA'], 'is_corresponding': False, 'raw_author_name': 'Marten Geertsema', 'raw_affiliation_strings': ['British Columbia, Ministry of Forests, Lands, Natural Resource Operations and Rural Development, Prince George, BC V2L 1R5, Canada'], 'affiliations': [{'raw_affiliation_string': 'British Columbia, Ministry of Forests, Lands, Natural Resource Operations and Rural Development, Prince George, BC V2L 1R5, Canada', 'institution_ids': ['https://openalex.org/I4210131853']}]}, {'author_position': 'middle', 'author': {'id': 'https://openalex.org/A5083514118', 'display_name': 'Khabat Khosravi', 'orcid': 'https://orcid.org/0000-0001-5773-4003'}, 'institutions': [{'id': 'https://openalex.org/I79817857', 'display_name': 'University of Guelph', 'ror': 'https://ror.org/01r7awg59', 'country_code': 'CA', 'type': 'education', 'lineage': ['https://openalex.org/I79817857']}], 'countries': ['CA'], 'is_corresponding': False, 'raw_author_name': 'Khabat Khosravi', 'raw_affiliation_strings': ['School of Engineering, University of Guelph, Guelph, ON N1G 2W1, Canada'], 'affiliations': [{'raw_affiliation_string': 'School of Engineering, University of Guelph, Guelph, ON N1G 2W1, Canada', 'institution_ids': ['https://openalex.org/I79817857']}]}, {'author_position': 'middle', 'author': {'id': 'https://openalex.org/A5053124996', 'display_name': 'Ata Amini', 'orcid': 'https://orcid.org/0000-0001-9358-185X'}, 'institutions': [{'id': 'https://openalex.org/I4210141426', 'display_name': 'Agricultural Research & Education Organization', 'ror': 'https://ror.org/032hv6w38', 'country_code': 'IR', 'type': 'nonprofit', 'lineage': ['https://openalex.org/I4210141426']}, {'id': 'https://openalex.org/I4210088633', 'display_name': 'Soil Conservation and Watershed Management Research', 'ror': 'https://ror.org/0066jc902', 'country_code': 'IR', 'type': 'facility', 'lineage': ['https://openalex.org/I4210088633']}], 'countries': ['IR'], 'is_corresponding': False, 'raw_author_name': 'Ata Amini', 'raw_affiliation_strings': ['Kurdistan Agricultural and Natural Resources Research and Education Center, AREEO, Sanandaj 66177-15175, Iran'], 'affiliations': [{'raw_affiliation_string': 'Kurdistan Agricultural and Natural Resources Research and Education Center, AREEO, Sanandaj 66177-15175, Iran', 'institution_ids': ['https://openalex.org/I4210088633', 'https://openalex.org/I4210141426']}]}, {'author_position': 'middle', 'author': {'id': 'https://openalex.org/A5007654910', 'display_name': 'Sepideh Bahrami', 'orcid': 'https://orcid.org/0000-0003-2174-2145'}, 'institutions': [{'id': 'https://openalex.org/I134113660', 'display_name': 'University of Nevada, Reno', 'ror': 'https://ror.org/01keh0577', 'country_code': 'US', 'type': 'education', 'lineage': ['https://openalex.org/I134113660']}], 'countries': ['US'], 'is_corresponding': False, 'raw_author_name': 'Sepideh Bahrami', 'raw_affiliation_strings': ['Department of Hydrological Sciences, University of Nevada, 89557-02601-775-685-8040, Reno, NV 89557, USA'], 'affiliations': [{'raw_affiliation_string': 'Department of Hydrological Sciences, University of Nevada, 89557-02601-775-685-8040, Reno, NV 89557, USA', 'institution_ids': ['https://openalex.org/I134113660']}]}, {'author_position': 'middle', 'author': {'id': 'https://openalex.org/A5039567207', 'display_name': 'Omid Rahmati', 'orcid': 'https://orcid.org/0000-0001-5672-8525'}, 'institutions': [{'id': 'https://openalex.org/I4210141426', 'display_name': 'Agricultural Research & Education Organization', 'ror': 'https://ror.org/032hv6w38', 'country_code': 'IR', 'type': 'nonprofit', 'lineage': ['https://openalex.org/I4210141426']}, {'id': 'https://openalex.org/I4210088633', 'display_name': 'Soil Conservation and Watershed Management Research', 'ror': 'https://ror.org/0066jc902', 'country_code': 'IR', 'type': 'facility', 'lineage': ['https://openalex.org/I4210088633']}], 'countries': ['IR'], 'is_corresponding': False, 'raw_author_name': 'Omid Rahmati', 'raw_affiliation_strings': ['Kurdistan Agricultural and Natural Resources Research and Education Center, AREEO, Sanandaj 66177-15175, Iran'], 'affiliations': [{'raw_affiliation_string': 'Kurdistan Agricultural and Natural Resources Research and Education Center, AREEO, Sanandaj 66177-15175, Iran', 'institution_ids': ['https://openalex.org/I4210088633', 'https://openalex.org/I4210141426']}]}, {'author_position': 'middle', 'author': {'id': 'https://openalex.org/A5090793544', 'display_name': 'Kyoumars Habibi', 'orcid': 'https://orcid.org/0000-0002-7093-9625'}, 'institutions': [{'id': 'https://openalex.org/I3124704065', 'display_name': 'University of Kurdistan', 'ror': 'https://ror.org/04k89yk85', 'country_code': 'IR', 'type': 'education', 'lineage': ['https://openalex.org/I3124704065']}], 'countries': ['IR'], 'is_corresponding': False, 'raw_author_name': 'Kyoumars Habibi', 'raw_affiliation_strings': ['Department of urban and regional planning, Faculty of Art and Architecture, University of Kurdistan, Sanandaj 66177-15175, Iran'], 'affiliations': [{'raw_affiliation_string': 'Department of urban and regional planning, Faculty of Art and Architecture, University of Kurdistan, Sanandaj 66177-15175, Iran', 'institution_ids': ['https://openalex.org/I3124704065']}]}, {'author_position': 'middle', 'author': {'id': 'https://openalex.org/A5002151224', 'display_name': 'Ayub Mohammadi', 'orcid': 'https://orcid.org/0000-0001-8848-8917'}, 'institutions': [{'id': 'https://openalex.org/I4576418', 'display_name': 'University of Technology Malaysia', 'ror': 'https://ror.org/026w31v75', 'country_code': 'MY', 'type': 'education', 'lineage': ['https://openalex.org/I4576418']}], 'countries': ['MY'], 'is_corresponding': False, 'raw_author_name': 'Ayub Mohammadi', 'raw_affiliation_strings': ['Department of Geoinformation, Faculty of Built Environment and Surveying, Universiti Teknologi Malaysia (UTM), 81310 Johor Bahru, Malaysia'], 'affiliations': [{'raw_affiliation_string': 'Department of Geoinformation, Faculty of Built Environment and Surveying, Universiti Teknologi Malaysia (UTM), 81310 Johor Bahru, Malaysia', 'institution_ids': ['https://openalex.org/I4576418']}]}, {'author_position': 'middle', 'author': {'id': 'https://openalex.org/A5080411341', 'display_name': 'Hoang Nguyen', 'orcid': 'https://orcid.org/0000-0001-6122-8314'}, 'institutions': [{'id': 'https://openalex.org/I170238339', 'display_name': 'Duy Tan University', 'ror': 'https://ror.org/05ezss144', 'country_code': 'VN', 'type': 'education', 'lineage': ['https://openalex.org/I170238339']}], 'countries': ['VN'], 'is_corresponding': False, 'raw_author_name': 'Hoang Nguyen', 'raw_affiliation_strings': ['Institute of Research and Development, Duy Tan University, Da Nang 550000, Vietnam'], 'affiliations': [{'raw_affiliation_string': 'Institute of Research and Development, Duy Tan University, Da Nang 550000, Vietnam', 'institution_ids': ['https://openalex.org/I170238339']}]}, {'author_position': 'middle', 'author': {'id': 'https://openalex.org/A5050922013', 'display_name': 'Assefa M. Melesse', 'orcid': 'https://orcid.org/0000-0003-4724-9367'}, 'institutions': [{'id': 'https://openalex.org/I19700959', 'display_name': 'Florida International University', 'ror': 'https://ror.org/02gz6gg07', 'country_code': 'US', 'type': 'education', 'lineage': ['https://openalex.org/I19700959']}], 'countries': ['US'], 'is_corresponding': False, 'raw_author_name': 'Assefa M. Melesse', 'raw_affiliation_strings': ['Department of Earth and Environment, Florida International University, Miami, FL 33199, USA'], 'affiliations': [{'raw_affiliation_string': 'Department of Earth and Environment, Florida International University, Miami, FL 33199, USA', 'institution_ids': ['https://openalex.org/I19700959']}]}, {'author_position': 'middle', 'author': {'id': 'https://openalex.org/A5110285224', 'display_name': 'Baharin Bin Ahmad', 'orcid': None}, 'institutions': [{'id': 'https://openalex.org/I4576418', 'display_name': 'University of Technology Malaysia', 'ror': 'https://ror.org/026w31v75', 'country_code': 'MY', 'type': 'education', 'lineage': ['https://openalex.org/I4576418']}], 'countries': ['MY'], 'is_corresponding': False, 'raw_author_name': 'Baharin Bin Ahmad', 'raw_affiliation_strings': ['Department of Geoinformation, Faculty of Built Environment and Surveying, Universiti Teknologi Malaysia (UTM), 81310 Johor Bahru, Malaysia'], 'affiliations': [{'raw_affiliation_string': 'Department of Geoinformation, Faculty of Built Environment and Surveying, Universiti Teknologi Malaysia (UTM), 81310 Johor Bahru, Malaysia', 'institution_ids': ['https://openalex.org/I4576418']}]}, {'author_position': 'last', 'author': {'id': 'https://openalex.org/A5108111405', 'display_name': 'Anuar Ahmad', 'orcid': None}, 'institutions': [{'id': 'https://openalex.org/I4576418', 'display_name': 'University of Technology Malaysia', 'ror': 'https://ror.org/026w31v75', 'country_code': 'MY', 'type': 'education', 'lineage': ['https://openalex.org/I4576418']}], 'countries': ['MY'], 'is_corresponding': False, 'raw_author_name': 'Anuar Ahmad', 'raw_affiliation_strings': ['Department of Geoinformation, Faculty of Built Environment and Surveying, Universiti Teknologi Malaysia (UTM), 81310 Johor Bahru, Malaysia'], 'affiliations': [{'raw_affiliation_string': 'Department of Geoinformation, Faculty of Built Environment and Surveying, Universiti Teknologi Malaysia (UTM), 81310 Johor Bahru, Malaysia', 'institution_ids': ['https://openalex.org/I4576418']}]}] | J2: 6 | K2: 17 | L2: 21.4237 | M2: FALSE | N2: 355 | O2: {'volume': '12', 'issue': '2', 'first_page': '266', 'last_page': '266'} | P2: {'id': 'https://openalex.org/T10930', 'display_name': 'Flood Risk Assessment and Management', 'score': 1.0, 'subfield': {'id': 'https://openalex.org/subfields/2306', 'display_name': 'Global and Planetary Change'}, 'field': {'id': 'https://openalex.org/fields/23', 'display_name': 'Environmental Science'}, 'domain': {'id': 'https://openalex.org/domains/3', 'display_name': 'Physical Sciences'}} | Q2: [{'id': 'https://openalex.org/T10930', 'display_name': 'Flood Risk Assessment and Management', 'score': 1.0, 'subfield': {'id': 'https://openalex.org/subfields/2306', 'display_name': 'Global and Planetary Change'}, 'field': {'id': 'https://openalex.org/fields/23', 'display_name': 'Environmental Science'}, 'domain': {'id': 'https://openalex.org/domains/3', 'display_name': 'Physical Sciences'}}, {'id': 'https://openalex.org/T12543', 'display_name': 'Groundwater and Watershed Analysis', 'score': 0.9921000003814697, 'subfield': {'id': 'https://openalex.org/subfields/2305', 'display_name': 'Environmental Engineering'}, 'field': {'id': 'https://openalex.org/fields/23', 'display_name': 'Environmental Science'}, 'domain': {'id': 'https://openalex.org/domains/3', 'display_name': 'Physical Sciences'}}, {'id': 'https://openalex.org/T10330', 'display_name': 'Hydrology and Watershed Management Studies', 'score': 0.9915000200271606, 'subfield': {'id': 'https://openalex.org/subfields/2312', 'display_name': 'Water Science and Technology'}, 'field': {'id': 'https://openalex.org/fields/23', 'display_name': 'Environmental Science'}, 'domain': {'id': 'https://openalex.org/domains/3', 'display_name': 'Physical Sciences'}}] | R2: [{'id': 'https://openalex.org/keywords/overfitting', 'display_name': 'Overfitting', 'score': 0.752395749092102}, {'id': 'https://openalex.org/keywords/computer-science', 'display_name': 'Computer science', 'score': 0.6012298464775085}, {'id': 'https://openalex.org/keywords/flood-myth', 'display_name': 'Flood myth', 'score': 0.5734686851501465}, {'id': 'https://openalex.org/keywords/artificial-intelligence', 'display_name': 'Artificial intelligence', 'score': 0.5104095339775085}, {'id': 'https://openalex.org/keywords/k-nearest-neighbors-algorithm', 'display_name': 'k-nearest neighbors algorithm', 'score': 0.46870845556259155}, {'id': 'https://openalex.org/keywords/ensemble-learning', 'display_name': 'Ensemble learning', 'score': 0.4673502743244171}, {'id': 'https://openalex.org/keywords/data-mining', 'display_name': 'Data mining', 'score': 0.4642764925956726}, {'id': 'https://openalex.org/keywords/adaboost', 'display_name': 'AdaBoost', 'score': 0.4611509144306183}, {'id': 'https://openalex.org/keywords/machine-learning', 'display_name': 'Machine learning', 'score': 0.42886656522750854}, {'id': 'https://openalex.org/keywords/bootstrap-aggregating', 'display_name': 'Bootstrap aggregating', 'score': 0.42870351672172546}, {'id': 'https://openalex.org/keywords/random-forest', 'display_name': 'Random forest', 'score': 0.42514973878860474}, {'id': 'https://openalex.org/keywords/classifier', 'display_name': 'Classifier (UML)', 'score': 0.4000876545906067}, {'id': 'https://openalex.org/keywords/remote-sensing', 'display_name': 'Remote sensing', 'score': 0.3343126177787781}, {'id': 'https://openalex.org/keywords/pattern-recognition', 'display_name': 'Pattern recognition (psychology)', 'score': 0.32905542850494385}, {'id': 'https://openalex.org/keywords/artificial-neural-network', 'display_name': 'Artificial neural network', 'score': 0.15411809086799622}, {'id': 'https://openalex.org/keywords/geography', 'display_name': 'Geography', 'score': 0.11170724034309387}] | S2: [{'id': 'https://openalex.org/C22019652', 'wikidata': 'https://www.wikidata.org/wiki/Q331309', 'display_name': 'Overfitting', 'level': 3, 'score': 0.752395749092102}, {'id': 'https://openalex.org/C41008148', 'wikidata': 'https://www.wikidata.org/wiki/Q21198', 'display_name': 'Computer science', 'level': 0, 'score': 0.6012298464775085}, {'id': 'https://openalex.org/C74256435', 'wikidata': 'https://www.wikidata.org/wiki/Q134052', 'display_name': 'Flood myth', 'level': 2, 'score': 0.5734686851501465}, {'id': 'https://openalex.org/C154945302', 'wikidata': 'https://www.wikidata.org/wiki/Q11660', 'display_name': 'Artificial intelligence', 'level': 1, 'score': 0.5104095339775085}, {'id': 'https://openalex.org/C113238511', 'wikidata': 'https://www.wikidata.org/wiki/Q1071612', 'display_name': 'k-nearest neighbors algorithm', 'level': 2, 'score': 0.46870845556259155}, {'id': 'https://openalex.org/C45942800', 'wikidata': 'https://www.wikidata.org/wiki/Q245652', 'display_name': 'Ensemble learning', 'level': 2, 'score': 0.4673502743244171}, {'id': 'https://openalex.org/C124101348', 'wikidata': 'https://www.wikidata.org/wiki/Q172491', 'display_name': 'Data mining', 'level': 1, 'score': 0.4642764925956726}, {'id': 'https://openalex.org/C141404830', 'wikidata': 'https://www.wikidata.org/wiki/Q2823869', 'display_name': 'AdaBoost', 'level': 3, 'score': 0.4611509144306183}, {'id': 'https://openalex.org/C119857082', 'wikidata': 'https://www.wikidata.org/wiki/Q2539', 'display_name': 'Machine learning', 'level': 1, 'score': 0.42886656522750854}, {'id': 'https://openalex.org/C162040801', 'wikidata': 'https://www.wikidata.org/wiki/Q799897', 'display_name': 'Bootstrap aggregating', 'level': 2, 'score': 0.42870351672172546}, {'id': 'https://openalex.org/C169258074', 'wikidata': 'https://www.wikidata.org/wiki/Q245748', 'display_name': 'Random forest', 'level': 2, 'score': 0.42514973878860474}, {'id': 'https://openalex.org/C95623464', 'wikidata': 'https://www.wikidata.org/wiki/Q1096149', 'display_name': 'Classifier (UML)', 'level': 2, 'score': 0.4000876545906067}, {'id': 'https://openalex.org/C62649853', 'wikidata': 'https://www.wikidata.org/wiki/Q199687', 'display_name': 'Remote sensing', 'level': 1, 'score': 0.3343126177787781}, {'id': 'https://openalex.org/C153180895', 'wikidata': 'https://www.wikidata.org/wiki/Q7148389', 'display_name': 'Pattern recognition (psychology)', 'level': 2, 'score': 0.32905542850494385}, {'id': 'https://openalex.org/C50644808', 'wikidata': 'https://www.wikidata.org/wiki/Q192776', 'display_name': 'Artificial neural network', 'level': 2, 'score': 0.15411809086799622}, {'id': 'https://openalex.org/C205649164', 'wikidata': 'https://www.wikidata.org/wiki/Q1071', 'display_name': 'Geography', 'level': 0, 'score': 0.11170724034309387}, {'id': 'https://openalex.org/C166957645', 'wikidata': 'https://www.wikidata.org/wiki/Q23498', 'display_name': 'Archaeology', 'level': 1, 'score': 0.0}] | T2: [{'id': 'https://metadata.un.org/sdg/13', 'display_name': 'Climate action', 'score': 0.5699999928474426}] | U2: 129
A3: https://openalex.org/W3035624836 | B3: https://doi.org/10.1109/cvpr42600.2020.01111 | C3: SAPIEN: A SimulAted Part-Based Interactive ENvironment | D3: 2020 | E3: 43983 | F3: en | G3: preprint | H3: {'is_oa': False, 'oa_status': 'closed', 'oa_url': None, 'any_repository_has_fulltext': False} | I3: [{'author_position': 'first', 'author': {'id': 'https://openalex.org/A5008903324', 'display_name': 'Fanbo Xiang', 'orcid': 'https://orcid.org/0009-0005-5335-873X'}, 'institutions': [{'id': 'https://openalex.org/I2800935791', 'display_name': 'UC San Diego Health System', 'ror': 'https://ror.org/01kbfgm16', 'country_code': 'US', 'type': 'healthcare', 'lineage': ['https://openalex.org/I2800935791']}], 'countries': ['US'], 'is_corresponding': True, 'raw_author_name': 'Fanbo Xiang', 'raw_affiliation_strings': ['UC San Diego'], 'affiliations': [{'raw_affiliation_string': 'UC San Diego', 'institution_ids': ['https://openalex.org/I2800935791']}]}, {'author_position': 'middle', 'author': {'id': 'https://openalex.org/A5060146466', 'display_name': 'Yuzhe Qin', 'orcid': 'https://orcid.org/0000-0002-9321-9305'}, 'institutions': [{'id': 'https://openalex.org/I2800935791', 'display_name': 'UC San Diego Health System', 'ror': 'https://ror.org/01kbfgm16', 'country_code': 'US', 'type': 'healthcare', 'lineage': ['https://openalex.org/I2800935791']}], 'countries': ['US'], 'is_corresponding': False, 'raw_author_name': 'Yuzhe Qin', 'raw_affiliation_strings': ['UC San Diego'], 'affiliations': [{'raw_affiliation_string': 'UC San Diego', 'institution_ids': ['https://openalex.org/I2800935791']}]}, {'author_position': 'middle', 'author': {'id': 'https://openalex.org/A5051488351', 'display_name': 'Kaichun Mo', 'orcid': 'https://orcid.org/0000-0003-4365-5050'}, 'institutions': [{'id': 'https://openalex.org/I97018004', 'display_name': 'Stanford University', 'ror': 'https://ror.org/00f54p054', 'country_code': 'US', 'type': 'education', 'lineage': ['https://openalex.org/I97018004']}], 'countries': ['US'], 'is_corresponding': False, 'raw_author_name': 'Kaichun Mo', 'raw_affiliation_strings': ['Stanford University'], 'affiliations': [{'raw_affiliation_string': 'Stanford University', 'institution_ids': ['https://openalex.org/I97018004']}]}, {'author_position': 'middle', 'author': {'id': 'https://openalex.org/A5033298018', 'display_name': 'Yikuan Xia', 'orcid': None}, 'institutions': [{'id': 'https://openalex.org/I2800935791', 'display_name': 'UC San Diego Health System', 'ror': 'https://ror.org/01kbfgm16', 'country_code': 'US', 'type': 'healthcare', 'lineage': ['https://openalex.org/I2800935791']}], 'countries': ['US'], 'is_corresponding': False, 'raw_author_name': 'Yikuan Xia', 'raw_affiliation_strings': ['UC San Diego'], 'affiliations': [{'raw_affiliation_string': 'UC San Diego', 'institution_ids': ['https://openalex.org/I2800935791']}]}, {'author_position': 'middle', 'author': {'id': 'https://openalex.org/A5043239430', 'display_name': 'Hao Zhu', 'orcid': 'https://orcid.org/0000-0003-1596-4366'}, 'institutions': [{'id': 'https://openalex.org/I2800935791', 'display_name': 'UC San Diego Health System', 'ror': 'https://ror.org/01kbfgm16', 'country_code': 'US', 'type': 'healthcare', 'lineage': ['https://openalex.org/I2800935791']}], 'countries': ['US'], 'is_corresponding': False, 'raw_author_name': 'Hao Zhu', 'raw_affiliation_strings': ['UC San Diego'], 'affiliations': [{'raw_affiliation_string': 'UC San Diego', 'institution_ids': ['https://openalex.org/I2800935791']}]}, {'author_position': 'middle', 'author': {'id': 'https://openalex.org/A5075643825', 'display_name': 'Fangchen Liu', 'orcid': 'https://orcid.org/0000-0002-8987-6396'}, 'institutions': [{'id': 'https://openalex.org/I2800935791', 'display_name': 'UC San Diego Health System', 'ror': 'https://ror.org/01kbfgm16', 'country_code': 'US', 'type': 'healthcare', 'lineage': ['https://openalex.org/I2800935791']}], 'countries': ['US'], 'is_corresponding': False, 'raw_author_name': 'Fangchen Liu', 'raw_affiliation_strings': ['UC San Diego'], 'affiliations': [{'raw_affiliation_string': 'UC San Diego', 'institution_ids': ['https://openalex.org/I2800935791']}]}, {'author_position': 'middle', 'author': {'id': 'https://openalex.org/A5058453644', 'display_name': 'Minghua Liu', 'orcid': 'https://orcid.org/0000-0002-6603-1251'}, 'institutions': [{'id': 'https://openalex.org/I2800935791', 'display_name': 'UC San Diego Health System', 'ror': 'https://ror.org/01kbfgm16', 'country_code': 'US', 'type': 'healthcare', 'lineage': ['https://openalex.org/I2800935791']}], 'countries': ['US'], 'is_corresponding': False, 'raw_author_name': 'Minghua Liu', 'raw_affiliation_strings': ['UC San Diego'], 'affiliations': [{'raw_affiliation_string': 'UC San Diego', 'institution_ids': ['https://openalex.org/I2800935791']}]}, {'author_position': 'middle', 'author': {'id': 'https://openalex.org/A5044737861', 'display_name': 'Hanxiao Jiang', 'orcid': 'https://orcid.org/0000-0001-6245-361X'}, 'institutions': [{'id': 'https://openalex.org/I18014758', 'display_name': 'Simon Fraser University', 'ror': 'https://ror.org/0213rcc28', 'country_code': 'CA', 'type': 'education', 'lineage': ['https://openalex.org/I18014758']}], 'countries': ['CA'], 'is_corresponding': False, 'raw_author_name': 'Hanxiao Jiang', 'raw_affiliation_strings': ['Simon Fraser University'], 'affiliations': [{'raw_affiliation_string': 'Simon Fraser University', 'institution_ids': ['https://openalex.org/I18014758']}]}, {'author_position': 'middle', 'author': {'id': 'https://openalex.org/A5049269697', 'display_name': 'Yifu Yuan', 'orcid': None}, 'institutions': [{'id': 'https://openalex.org/I4210139270', 'display_name': 'UtopiaCompression (United States)', 'ror': 'https://ror.org/051d4q284', 'country_code': 'US', 'type': 'company', 'lineage': ['https://openalex.org/I4210139270']}], 'countries': ['US'], 'is_corresponding': False, 'raw_author_name': 'Yifu Yuan', 'raw_affiliation_strings': ['UC Los Angeles'], 'affiliations': [{'raw_affiliation_string': 'UC Los Angeles', 'institution_ids': ['https://openalex.org/I4210139270']}]}, {'author_position': 'middle', 'author': {'id': 'https://openalex.org/A5100351699', 'display_name': 'He Wang', 'orcid': 'https://orcid.org/0000-0003-1679-0337'}, 'institutions': [{'id': 'https://openalex.org/I97018004', 'display_name': 'Stanford University', 'ror': 'https://ror.org/00f54p054', 'country_code': 'US', 'type': 'education', 'lineage': ['https://openalex.org/I97018004']}], 'countries': ['US'], 'is_corresponding': False, 'raw_author_name': 'He Wang', 'raw_affiliation_strings': ['Stanford University'], 'affiliations': [{'raw_affiliation_string': 'Stanford University', 'institution_ids': ['https://openalex.org/I97018004']}]}, {'author_position': 'middle', 'author': {'id': 'https://openalex.org/A5100421473', 'display_name': 'Yi Li', 'orcid': 'https://orcid.org/0000-0002-2856-7290'}, 'institutions': [{'id': 'https://openalex.org/I1291425158', 'display_name': 'Google (United States)', 'ror': 'https://ror.org/00njsd438', 'country_code': 'US', 'type': 'company', 'lineage': ['https://openalex.org/I1291425158', 'https://openalex.org/I4210128969']}], 'countries': ['US'], 'is_corresponding': False, 'raw_author_name': 'Li Yi', 'raw_affiliation_strings': ['Google Research'], 'affiliations': [{'raw_affiliation_string': 'Google Research', 'institution_ids': ['https://openalex.org/I1291425158']}]}, {'author_position': 'middle', 'author': {'id': 'https://openalex.org/A5044978994', 'display_name': 'Anne Lynn S. Chang', 'orcid': 'https://orcid.org/0000-0002-2869-2147'}, 'institutions': [{'id': 'https://openalex.org/I18014758', 'display_name': 'Simon Fraser University', 'ror': 'https://ror.org/0213rcc28', 'country_code': 'CA', 'type': 'education', 'lineage': ['https://openalex.org/I18014758']}], 'countries': ['CA'], 'is_corresponding': False, 'raw_author_name': 'Angel X. Chang', 'raw_affiliation_strings': ['Simon Fraser University'], 'affiliations': [{'raw_affiliation_string': 'Simon Fraser University', 'institution_ids': ['https://openalex.org/I18014758']}]}, {'author_position': 'middle', 'author': {'id': 'https://openalex.org/A5065368881', 'display_name': 'Leonidas Guibas', 'orcid': 'https://orcid.org/0000-0002-8315-4886'}, 'institutions': [{'id': 'https://openalex.org/I97018004', 'display_name': 'Stanford University', 'ror': 'https://ror.org/00f54p054', 'country_code': 'US', 'type': 'education', 'lineage': ['https://openalex.org/I97018004']}], 'countries': ['US'], 'is_corresponding': False, 'raw_author_name': 'Leonidas J. Guibas', 'raw_affiliation_strings': ['Stanford University'], 'affiliations': [{'raw_affiliation_string': 'Stanford University', 'institution_ids': ['https://openalex.org/I97018004']}]}, {'author_position': 'last', 'author': {'id': 'https://openalex.org/A5091622325', 'display_name': 'Hao Su', 'orcid': 'https://orcid.org/0000-0002-9686-6540'}, 'institutions': [{'id': 'https://openalex.org/I2800935791', 'display_name': 'UC San Diego Health System', 'ror': 'https://ror.org/01kbfgm16', 'country_code': 'US', 'type': 'healthcare', 'lineage': ['https://openalex.org/I2800935791']}], 'countries': ['US'], 'is_corresponding': False, 'raw_author_name': 'Hao Su', 'raw_affiliation_strings': ['UC San Diego'], 'affiliations': [{'raw_affiliation_string': 'UC San Diego', 'institution_ids': ['https://openalex.org/I2800935791']}]}] | J3: 2 | K3: 14 | L3: 20.258692 | M3: FALSE | N3: 353 | O3: {'volume': None, 'issue': None, 'first_page': '11094', 'last_page': '11104'} | P3: {'id': 'https://openalex.org/T11714', 'display_name': 'Multimodal Machine Learning Applications', 'score': 0.9997000098228455, 'subfield': {'id': 'https://openalex.org/subfields/1707', 'display_name': 'Computer Vision and Pattern Recognition'}, 'field': {'id': 'https://openalex.org/fields/17', 'display_name': 'Computer Science'}, 'domain': {'id': 'https://openalex.org/domains/3', 'display_name': 'Physical Sciences'}} | Q3: [{'id': 'https://openalex.org/T11714', 'display_name': 'Multimodal Machine Learning Applications', 'score': 0.9997000098228455, 'subfield': {'id': 'https://openalex.org/subfields/1707', 'display_name': 'Computer Vision and Pattern Recognition'}, 'field': {'id': 'https://openalex.org/fields/17', 'display_name': 'Computer Science'}, 'domain': {'id': 'https://openalex.org/domains/3', 'display_name': 'Physical Sciences'}}, {'id': 'https://openalex.org/T10653', 'display_name': 'Robot Manipulation and Learning', 'score': 0.9994999766349792, 'subfield': {'id': 'https://openalex.org/subfields/2207', 'display_name': 'Control and Systems Engineering'}, 'field': {'id': 'https://openalex.org/fields/22', 'display_name': 'Engineering'}, 'domain': {'id': 'https://openalex.org/domains/3', 'display_name': 'Physical Sciences'}}, {'id': 'https://openalex.org/T10586', 'display_name': 'Robotic Path Planning Algorithms', 'score': 0.9990000128746033, 'subfield': {'id': 'https://openalex.org/subfields/1707', 'display_name': 'Computer Vision and Pattern Recognition'}, 'field': {'id': 'https://openalex.org/fields/17', 'display_name': 'Computer Science'}, 'domain': {'id': 'https://openalex.org/domains/3', 'display_name': 'Physical Sciences'}}] | R3: [{'id': 'https://openalex.org/keywords/robotics', 'display_name': 'Robotics', 'score': 0.7897522449493408}, {'id': 'https://openalex.org/keywords/artificial-intelligence', 'display_name': 'Artificial intelligence', 'score': 0.6961296200752258}, {'id': 'https://openalex.org/keywords/robot', 'display_name': 'Robot', 'score': 0.6861521601676941}, {'id': 'https://openalex.org/keywords/computer-science', 'display_name': 'Computer science', 'score': 0.658255934715271}, {'id': 'https://openalex.org/keywords/reinforcement-learning', 'display_name': 'Reinforcement learning', 'score': 0.6101622581481934}, {'id': 'https://openalex.org/keywords/humanâ€“computer-interaction', 'display_name': 'Humanâ€“computer interaction', 'score': 0.590071439743042}, {'id': 'https://openalex.org/keywords/task', 'display_name': 'Task (project management)', 'score': 0.5621821284294128}, {'id': 'https://openalex.org/keywords/motion', 'display_name': 'Motion (physics)', 'score': 0.5154355764389038}, {'id': 'https://openalex.org/keywords/set', 'display_name': 'Set (abstract data type)', 'score': 0.49389272928237915}, {'id': 'https://openalex.org/keywords/heuristic', 'display_name': 'Heuristic', 'score': 0.4710685610771179}, {'id': 'https://openalex.org/keywords/focus', 'display_name': 'Focus (optics)', 'score': 0.43487516045570374}, {'id': 'https://openalex.org/keywords/machine-learning', 'display_name': 'Machine learning', 'score': 0.3394186794757843}, {'id': 'https://openalex.org/keywords/engineering', 'display_name': 'Engineering', 'score': 0.19693204760551453}, {'id': 'https://openalex.org/keywords/systems-engineering', 'display_name': 'Systems engineering', 'score': 0.10156914591789246}] | S3: [{'id': 'https://openalex.org/C34413123', 'wikidata': 'https://www.wikidata.org/wiki/Q170978', 'display_name': 'Robotics', 'level': 3, 'score': 0.7897522449493408}, {'id': 'https://openalex.org/C154945302', 'wikidata': 'https://www.wikidata.org/wiki/Q11660', 'display_name': 'Artificial intelligence', 'level': 1, 'score': 0.6961296200752258}, {'id': 'https://openalex.org/C90509273', 'wikidata': 'https://www.wikidata.org/wiki/Q11012', 'display_name': 'Robot', 'level': 2, 'score': 0.6861521601676941}, {'id': 'https://openalex.org/C41008148', 'wikidata': 'https://www.wikidata.org/wiki/Q21198', 'display_name': 'Computer science', 'level': 0, 'score': 0.658255934715271}, {'id': 'https://openalex.org/C97541855', 'wikidata': 'https://www.wikidata.org/wiki/Q830687', 'display_name': 'Reinforcement learning', 'level': 2, 'score': 0.6101622581481934}, {'id': 'https://openalex.org/C107457646', 'wikidata': 'https://www.wikidata.org/wiki/Q207434', 'display_name': 'Humanâ€“computer interaction', 'level': 1, 'score': 0.590071439743042}, {'id': 'https://openalex.org/C2780451532', 'wikidata': 'https://www.wikidata.org/wiki/Q759676', 'display_name': 'Task (project management)', 'level': 2, 'score': 0.5621821284294128}, {'id': 'https://openalex.org/C104114177', 'wikidata': 'https://www.wikidata.org/wiki/Q79782', 'display_name': 'Motion (physics)', 'level': 2, 'score': 0.5154355764389038}, {'id': 'https://openalex.org/C177264268', 'wikidata': 'https://www.wikidata.org/wiki/Q1514741', 'display_name': 'Set (abstract data type)', 'level': 2, 'score': 0.49389272928237915}, {'id': 'https://openalex.org/C173801870', 'wikidata': 'https://www.wikidata.org/wiki/Q201413', 'display_name': 'Heuristic', 'level': 2, 'score': 0.4710685610771179}, {'id': 'https://openalex.org/C192209626', 'wikidata': 'https://www.wikidata.org/wiki/Q190909', 'display_name': 'Focus (optics)', 'level': 2, 'score': 0.43487516045570374}, {'id': 'https://openalex.org/C119857082', 'wikidata': 'https://www.wikidata.org/wiki/Q2539', 'display_name': 'Machine learning', 'level': 1, 'score': 0.3394186794757843}, {'id': 'https://openalex.org/C127413603', 'wikidata': 'https://www.wikidata.org/wiki/Q11023', 'display_name': 'Engineering', 'level': 0, 'score': 0.19693204760551453}, {'id': 'https://openalex.org/C201995342', 'wikidata': 'https://www.wikidata.org/wiki/Q682496', 'display_name': 'Systems engineering', 'level': 1, 'score': 0.10156914591789246}, {'id': 'https://openalex.org/C120665830', 'wikidata': 'https://www.wikidata.org/wiki/Q14620', 'display_name': 'Optics', 'level': 1, 'score': 0.0}, {'id': 'https://openalex.org/C199360897', 'wikidata': 'https://www.wikidata.org/wiki/Q9143', 'display_name': 'Programming language', 'level': 1, 'score': 0.0}, {'id': 'https://openalex.org/C121332964', 'wikidata': 'https://www.wikidata.org/wiki/Q413', 'display_name': 'Physics', 'level': 0, 'score': 0.0}] | T3: [] | U3: 82
A4: https://openalex.org/W3108888189 | B4: https://doi.org/10.1175/jcli-d-19-1013.1 | C4: Changes in Annual Extremes of Daily Temperature and Precipitation in CMIP6 Models | D4: 2020 | E4: 44166 | F4: en | G4: article | H4: {'is_oa': True, 'oa_status': 'hybrid', 'oa_url': 'https://journals.ametsoc.org/downloadpdf/journals/clim/34/9/JCLI-D-19-1013.1.pdf', 'any_repository_has_fulltext': True} | I4: [{'author_position': 'first', 'author': {'id': 'https://openalex.org/A5100323109', 'display_name': 'Chao Li', 'orcid': 'https://orcid.org/0000-0001-6863-9271'}, 'institutions': [{'id': 'https://openalex.org/I200845125', 'display_name': 'Nanjing University of Information Science and Technology', 'ror': 'https://ror.org/02y0rxk19', 'country_code': 'CN', 'type': 'education', 'lineage': ['https://openalex.org/I200845125']}, {'id': 'https://openalex.org/I66867065', 'display_name': 'East China Normal University', 'ror': 'https://ror.org/02n96ep67', 'country_code': 'CN', 'type': 'education', 'lineage': ['https://openalex.org/I66867065']}], 'countries': ['CN'], 'is_corresponding': True, 'raw_author_name': 'Chao Li', 'raw_affiliation_strings': ['a Key Laboratory of Geographic Information Science, Ministry of Education, East China Normal University, Shanghai, China', 'b School of Geographic Sciences, East China Normal University, Shanghai, China', 'd Nanjing University of Information Science and Technology, Nanjing, China', 'Nanjing University of Information Science and Technology, Nanjing, China', 'Key Laboratory of Geographic Information Science, Ministry of Education, East China Normal University, Shanghai, China', 'School of Geographic Sciences, East China Normal University, Shanghai, China'], 'affiliations': [{'raw_affiliation_string': 'a Key Laboratory of Geographic Information Science, Ministry of Education, East China Normal University, Shanghai, China', 'institution_ids': ['https://openalex.org/I66867065']}, {'raw_affiliation_string': 'b School of Geographic Sciences, East China Normal University, Shanghai, China', 'institution_ids': ['https://openalex.org/I66867065']}, {'raw_affiliation_string': 'd Nanjing University of Information Science and Technology, Nanjing, China', 'institution_ids': ['https://openalex.org/I200845125']}, {'raw_affiliation_string': 'Nanjing University of Information Science and Technology, Nanjing, China', 'institution_ids': ['https://openalex.org/I200845125']}, {'raw_affiliation_string': 'Key Laboratory of Geographic Information Science, Ministry of Education, East China Normal University, Shanghai, China', 'institution_ids': ['https://openalex.org/I66867065']}, {'raw_affiliation_string': 'School of Geographic Sciences, East China Normal University, Shanghai, China', 'institution_ids': ['https://openalex.org/I66867065']}]}, {'author_position': 'middle', 'author': {'id': 'https://openalex.org/A5062528804', 'display_name': 'Francis W. Zwiers', 'orcid': 'https://orcid.org/0000-0002-8375-5147'}, 'institutions': [{'id': 'https://openalex.org/I4210094865', 'display_name': 'Pacific Institute for Climate Solutions', 'ror': 'https://ror.org/00hv6g197', 'country_code': 'CA', 'type': 'facility', 'lineage': ['https://openalex.org/I141945490', 'https://openalex.org/I151934421', 'https://openalex.org/I18014758', 'https://openalex.org/I212119943', 'https://openalex.org/I4210094865']}, {'id': 'https://openalex.org/I200845125', 'display_name': 'Nanjing University of Information Science and Technology', 'ror': 'https://ror.org/02y0rxk19', 'country_code': 'CN', 'type': 'education', 'lineage': ['https://openalex.org/I200845125']}, {'id': 'https://openalex.org/I212119943', 'display_name': 'University of Victoria', 'ror': 'https://ror.org/04s5mat29', 'country_code': 'CA', 'type': 'education', 'lineage': ['https://openalex.org/I212119943']}], 'countries': ['CA', 'CN'], 'is_corresponding': False, 'raw_author_name': 'Francis Zwiers', 'raw_affiliation_strings': ['c Pacific Climate Impacts Consortium, University of Victoria, Victoria, British Columbia, Canada', 'd Nanjing University of Information Science and Technology, Nanjing, China', 'Nanjing University of Information Science and Technology, Nanjing, China', 'Pacific Climate Impacts Consortium, University of Victoria, Victoria, British Columbia, Canada'], 'affiliations': [{'raw_affiliation_string': 'c Pacific Climate Impacts Consortium, University of Victoria, Victoria, British Columbia, Canada', 'institution_ids': ['https://openalex.org/I4210094865', 'https://openalex.org/I212119943']}, {'raw_affiliation_string': 'd Nanjing University of Information Science and Technology, Nanjing, China', 'institution_ids': ['https://openalex.org/I200845125']}, {'raw_affiliation_string': 'Nanjing University of Information Science and Technology, Nanjing, China', 'institution_ids': ['https://openalex.org/I200845125']}, {'raw_affiliation_string': 'Pacific Climate Impacts Consortium, University of Victoria, Victoria, British Columbia, Canada', 'institution_ids': ['https://openalex.org/I4210094865', 'https://openalex.org/I212119943']}]}, {'author_position': 'middle', 'author': {'id': 'https://openalex.org/A5100387443', 'display_name': 'Xuebin Zhang', 'orcid': 'https://orcid.org/0000-0002-6551-6249'}, 'institutions': [{'id': 'https://openalex.org/I1342547582', 'display_name': 'Environment and Climate Change Canada', 'ror': 'https://ror.org/026ny0e17', 'country_code': 'CA', 'type': 'government', 'lineage': ['https://openalex.org/I1342547582', 'https://openalex.org/I2802286613']}], 'countries': ['CA'], 'is_corresponding': False, 'raw_author_name': 'Xuebin Zhang', 'raw_affiliation_strings': ['e Climate Research Division, Environment and Climate Change Canada, Toronto, Ontario, Canada', 'Climate Research Division, Environment and Climate Change Canada, Toronto, Ontario, Canada'], 'affiliations': [{'raw_affiliation_string': 'e Climate Research Division, Environment and Climate Change Canada, Toronto, Ontario, Canada', 'institution_ids': ['https://openalex.org/I1342547582']}, {'raw_affiliation_string': 'Climate Research Division, Environment and Climate Change Canada, Toronto, Ontario, Canada', 'institution_ids': ['https://openalex.org/I1342547582']}]}, {'author_position': 'middle', 'author': {'id': 'https://openalex.org/A5046034025', 'display_name': 'Guilong Li', 'orcid': 'https://orcid.org/0000-0003-3125-4567'}, 'institutions': [{'id': 'https://openalex.org/I1342547582', 'display_name': 'Environment and Climate Change Canada', 'ror': 'https://ror.org/026ny0e17', 'country_code': 'CA', 'type': 'government', 'lineage': ['https://openalex.org/I1342547582', 'https://openalex.org/I2802286613']}], 'countries': ['CA'], 'is_corresponding': False, 'raw_author_name': 'Guilong Li', 'raw_affiliation_strings': ['e Climate Research Division, Environment and Climate Change Canada, Toronto, Ontario, Canada', 'Climate Research Division, Environment and Climate Change Canada, Toronto, Ontario, Canada'], 'affiliations': [{'raw_affiliation_string': 'e Climate Research Division, Environment and Climate Change Canada, Toronto, Ontario, Canada', 'institution_ids': ['https://openalex.org/I1342547582']}, {'raw_affiliation_string': 'Climate Research Division, Environment and Climate Change Canada, Toronto, Ontario, Canada', 'institution_ids': ['https://openalex.org/I1342547582']}]}, {'author_position': 'middle', 'author': {'id': 'https://openalex.org/A5101472843', 'display_name': 'Ying Sun', 'orcid': 'https://orcid.org/0000-0003-2335-3485'}, 'institutions': [{'id': 'https://openalex.org/I141301092', 'display_name': 'China Meteorological Administration', 'ror': 'https://ror.org/00bx3rb98', 'country_code': 'CN', 'type': 'government', 'lineage': ['https://openalex.org/I141301092']}], 'countries': ['CN'], 'is_corresponding': False, 'raw_author_name': 'Ying Sun', 'raw_affiliation_strings': ['f Laboratory for Climate Studies, National Climate Center, China Meteorological Administration, Beijing, China', 'Laboratory for Climate Studies, National Climate Center, China Meteorological Administration, Beijing, China'], 'affiliations': [{'raw_affiliation_string': 'f Laboratory for Climate Studies, National Climate Center, China Meteorological Administration, Beijing, China', 'institution_ids': ['https://openalex.org/I141301092']}, {'raw_affiliation_string': 'Laboratory for Climate Studies, National Climate Center, China Meteorological Administration, Beijing, China', 'institution_ids': ['https://openalex.org/I141301092']}]}, {'author_position': 'last', 'author': {'id': 'https://openalex.org/A5029017675', 'display_name': 'Michael Wehner', 'orcid': 'https://orcid.org/0000-0001-5991-0082'}, 'institutions': [{'id': 'https://openalex.org/I2800337505', 'display_name': 'Bexley Hall', 'ror': 'https://ror.org/05v69pw95', 'country_code': 'US', 'type': 'education', 'lineage': ['https://openalex.org/I2800337505']}], 'countries': ['US'], 'is_corresponding': False, 'raw_author_name': 'Michael Wehner', 'raw_affiliation_strings': ['g Computational Research Division, Lawrence Berkley National Laboratory, Berkley, California', 'Computational Research Division, Lawrence Berkley National Laboratory, Berkley, California'], 'affiliations': [{'raw_affiliation_string': 'g Computational Research Division, Lawrence Berkley National Laboratory, Berkley, California', 'institution_ids': ['https://openalex.org/I2800337505']}, {'raw_affiliation_string': 'Computational Research Division, Lawrence Berkley National Laboratory, Berkley, California', 'institution_ids': []}]}] | J4: 3 | K4: 6 | L4: 16.6184 | M4: TRUE | N4: 329 | O4: {'volume': '34', 'issue': '9', 'first_page': '3441', 'last_page': '3460'} | P4: {'id': 'https://openalex.org/T10029', 'display_name': 'Climate variability and models', 'score': 0.9998999834060669, 'subfield': {'id': 'https://openalex.org/subfields/2306', 'display_name': 'Global and Planetary Change'}, 'field': {'id': 'https://openalex.org/fields/23', 'display_name': 'Environmental Science'}, 'domain': {'id': 'https://openalex.org/domains/3', 'display_name': 'Physical Sciences'}} | Q4: [{'id': 'https://openalex.org/T10029', 'display_name': 'Climate variability and models', 'score': 0.9998999834060669, 'subfield': {'id': 'https://openalex.org/subfields/2306', 'display_name': 'Global and Planetary Change'}, 'field': {'id': 'https://openalex.org/fields/23', 'display_name': 'Environmental Science'}, 'domain': {'id': 'https://openalex.org/domains/3', 'display_name': 'Physical Sciences'}}, {'id': 'https://openalex.org/T11588', 'display_name': 'Atmospheric and Environmental Gas Dynamics', 'score': 0.9975000023841858, 'subfield': {'id': 'https://openalex.org/subfields/2306', 'display_name': 'Global and Planetary Change'}, 'field': {'id': 'https://openalex.org/fields/23', 'display_name': 'Environmental Science'}, 'domain': {'id': 'https://openalex.org/domains/3', 'display_name': 'Physical Sciences'}}, {'id': 'https://openalex.org/T10466', 'display_name': 'Meteorological Phenomena and Simulations', 'score': 0.996999979019165, 'subfield': {'id': 'https://openalex.org/subfields/1902', 'display_name': 'Atmospheric Science'}, 'field': {'id': 'https://openalex.org/fields/19', 'display_name': 'Earth and Planetary Sciences'}, 'domain': {'id': 'https://openalex.org/domains/3', 'display_name': 'Physical Sciences'}}] | R4: [{'id': 'https://openalex.org/keywords/precipitation', 'display_name': 'Precipitation', 'score': 0.8168666362762451}, {'id': 'https://openalex.org/keywords/coupled-model-intercomparison-project', 'display_name': 'Coupled model intercomparison project', 'score': 0.8089784383773804}, {'id': 'https://openalex.org/keywords/environmental-science', 'display_name': 'Environmental science', 'score': 0.7747020721435547}, {'id': 'https://openalex.org/keywords/climatology', 'display_name': 'Climatology', 'score': 0.7484180331230164}, {'id': 'https://openalex.org/keywords/pooling', 'display_name': 'Pooling', 'score': 0.5613932609558105}, {'id': 'https://openalex.org/keywords/forcing', 'display_name': 'Forcing (mathematics)', 'score': 0.4951871931552887}, {'id': 'https://openalex.org/keywords/climate-model', 'display_name': 'Climate model', 'score': 0.47099965810775757}, {'id': 'https://openalex.org/keywords/surface-air-temperature', 'display_name': 'Surface air temperature', 'score': 0.43429940938949585}, {'id': 'https://openalex.org/keywords/mean-radiant-temperature', 'display_name': 'Mean radiant temperature', 'score': 0.4107043445110321}, {'id': 'https://openalex.org/keywords/atmospheric-sciences', 'display_name': 'Atmospheric sciences', 'score': 0.3687288761138916}, {'id': 'https://openalex.org/keywords/climate-change', 'display_name': 'Climate change', 'score': 0.36225682497024536}, {'id': 'https://openalex.org/keywords/meteorology', 'display_name': 'Meteorology', 'score': 0.28965359926223755}, {'id': 'https://openalex.org/keywords/computer-science', 'display_name': 'Computer science', 'score': 0.13357016444206238}, {'id': 'https://openalex.org/keywords/geology', 'display_name': 'Geology', 'score': 0.10647240281105042}, {'id': 'https://openalex.org/keywords/geography', 'display_name': 'Geography', 'score': 0.07832589745521545}] | S4: [{'id': 'https://openalex.org/C107054158', 'wikidata': 'https://www.wikidata.org/wiki/Q25257', 'display_name': 'Precipitation', 'level': 2, 'score': 0.8168666362762451}, {'id': 'https://openalex.org/C25022447', 'wikidata': 'https://www.wikidata.org/wiki/Q5178021', 'display_name': 'Coupled model intercomparison project', 'level': 4, 'score': 0.8089784383773804}, {'id': 'https://openalex.org/C39432304', 'wikidata': 'https://www.wikidata.org/wiki/Q188847', 'display_name': 'Environmental science', 'level': 0, 'score': 0.7747020721435547}, {'id': 'https://openalex.org/C49204034', 'wikidata': 'https://www.wikidata.org/wiki/Q52139', 'display_name': 'Climatology', 'level': 1, 'score': 0.7484180331230164}, {'id': 'https://openalex.org/C70437156', 'wikidata': 'https://www.wikidata.org/wiki/Q7228652', 'display_name': 'Pooling', 'level': 2, 'score': 0.5613932609558105}, {'id': 'https://openalex.org/C197115733', 'wikidata': 'https://www.wikidata.org/wiki/Q1003136', 'display_name': 'Forcing (mathematics)', 'level': 2, 'score': 0.4951871931552887}, {'id': 'https://openalex.org/C168754636', 'wikidata': 'https://www.wikidata.org/wiki/Q620920', 'display_name': 'Climate model', 'level': 3, 'score': 0.47099965810775757}, {'id': 'https://openalex.org/C2994323764', 'wikidata': 'https://www.wikidata.org/wiki/Q909741', 'display_name': 'Surface air temperature', 'level': 3, 'score': 0.43429940938949585}, {'id': 'https://openalex.org/C42683663', 'wikidata': 'https://www.wikidata.org/wiki/Q3517834', 'display_name': 'Mean radiant temperature', 'level': 3, 'score': 0.4107043445110321}, {'id': 'https://openalex.org/C91586092', 'wikidata': 'https://www.wikidata.org/wiki/Q757520', 'display_name': 'Atmospheric sciences', 'level': 1, 'score': 0.3687288761138916}, {'id': 'https://openalex.org/C132651083', 'wikidata': 'https://www.wikidata.org/wiki/Q7942', 'display_name': 'Climate change', 'level': 2, 'score': 0.36225682497024536}, {'id': 'https://openalex.org/C153294291', 'wikidata': 'https://www.wikidata.org/wiki/Q25261', 'display_name': 'Meteorology', 'level': 1, 'score': 0.28965359926223755}, {'id': 'https://openalex.org/C41008148', 'wikidata': 'https://www.wikidata.org/wiki/Q21198', 'display_name': 'Computer science', 'level': 0, 'score': 0.13357016444206238}, {'id': 'https://openalex.org/C127313418', 'wikidata': 'https://www.wikidata.org/wiki/Q1069', 'display_name': 'Geology', 'level': 0, 'score': 0.10647240281105042}, {'id': 'https://openalex.org/C205649164', 'wikidata': 'https://www.wikidata.org/wiki/Q1071', 'display_name': 'Geography', 'level': 0, 'score': 0.07832589745521545}, {'id': 'https://openalex.org/C111368507', 'wikidata': 'https://www.wikidata.org/wiki/Q43518', 'display_name': 'Oceanography', 'level': 1, 'score': 0.0}, {'id': 'https://openalex.org/C154945302', 'wikidata': 'https://www.wikidata.org/wiki/Q11660', 'display_name': 'Artificial intelligence', 'level': 1, 'score': 0.0}] | T4: [{'display_name': 'Climate action', 'id': 'https://metadata.un.org/sdg/13', 'score': 0.8299999833106995}] | U4: 60
A5: https://openalex.org/W3042819938 | B5: https://doi.org/10.1111/ele.13568 | C5: A processâ€based metacommunity framework linking local and regional scale community ecology | D5: 2020 | E5: 44028 | F5: en | G5: article | H5: {'is_oa': True, 'oa_status': 'hybrid', 'oa_url': 'https://onlinelibrary.wiley.com/doi/pdfdirect/10.1111/ele.13568', 'any_repository_has_fulltext': True} | I5: [{'author_position': 'first', 'author': {'id': 'https://openalex.org/A5017037142', 'display_name': 'Patrick L. Thompson', 'orcid': 'https://orcid.org/0000-0002-5278-9045'}, 'institutions': [{'id': 'https://openalex.org/I141945490', 'display_name': 'University of British Columbia', 'ror': 'https://ror.org/03rmrcq20', 'country_code': 'CA', 'type': 'education', 'lineage': ['https://openalex.org/I141945490']}], 'countries': ['CA'], 'is_corresponding': True, 'raw_author_name': 'Patrick L. Thompson', 'raw_affiliation_strings': ['Department of Zoology &amp; Biodiversity Research Centre University of British Columbia Vancouver British Columbia Canada', 'Department of Zoology & Biodiversity Research Centre, University of British Columbia, Vancouver, British Columbia, Canada'], 'affiliations': [{'raw_affiliation_string': 'Department of Zoology &amp; Biodiversity Research Centre University of British Columbia Vancouver British Columbia Canada', 'institution_ids': ['https://openalex.org/I141945490']}, {'raw_affiliation_string': 'Department of Zoology & Biodiversity Research Centre, University of British Columbia, Vancouver, British Columbia, Canada', 'institution_ids': ['https://openalex.org/I141945490']}]}, {'author_position': 'middle', 'author': {'id': 'https://openalex.org/A5075156839', 'display_name': 'Laura Melissa Guzman', 'orcid': 'https://orcid.org/0000-0003-2198-9738'}, 'institutions': [{'id': 'https://openalex.org/I141945490', 'display_name': 'University of British Columbia', 'ror': 'https://ror.org/03rmrcq20', 'country_code': 'CA', 'type': 'education', 'lineage': ['https://openalex.org/I141945490']}, {'id': 'https://openalex.org/I18014758', 'display_name': 'Simon Fraser University', 'ror': 'https://ror.org/0213rcc28', 'country_code': 'CA', 'type': 'education', 'lineage': ['https://openalex.org/I18014758']}], 'countries': ['CA'], 'is_corresponding': False, 'raw_author_name': 'Laura Melissa Guzman', 'raw_affiliation_strings': ['Department of Biology Simon Fraser University Burnaby Canada', 'Department of Zoology &amp; Biodiversity Research Centre University of British Columbia Vancouver British Columbia Canada', 'Department of Biology, Simon Fraser University, Burnaby, Canada', 'Department of Zoology & Biodiversity Research Centre, University of British Columbia, Vancouver, British Columbia, Canada'], 'affiliations': [{'raw_affiliation_string': 'Department of Biology Simon Fraser University Burnaby Canada', 'institution_ids': ['https://openalex.org/I18014758']}, {'raw_affiliation_string': 'Department of Zoology &amp; Biodiversity Research Centre University of British Columbia Vancouver British Columbia Canada', 'institution_ids': ['https://openalex.org/I141945490']}, {'raw_affiliation_string': 'Department of Biology, Simon Fraser University, Burnaby, Canada', 'institution_ids': ['https://openalex.org/I18014758']}, {'raw_affiliation_string': 'Department of Zoology & Biodiversity Research Centre, University of British Columbia, Vancouver, British Columbia, Canada', 'institution_ids': ['https://openalex.org/I141945490']}]}, {'author_position': 'middle', 'author': {'id': 'https://openalex.org/A5043746667', 'display_name': 'Luc De Meester', 'orcid': 'https://orcid.org/0000-0001-5433-6843'}, 'institutions': [{'id': 'https://openalex.org/I4210133189', 'display_name': 'Institut fÃ¼r Angewandte GewÃ¤sserÃ¶kologie (Germany)', 'ror': 'https://ror.org/03c1b7x32', 'country_code': 'DE', 'type': 'company', 'lineage': ['https://openalex.org/I4210133189']}, {'id': 'https://openalex.org/I99464096', 'display_name': 'KU Leuven', 'ror': 'https://ror.org/05f950310', 'country_code': 'BE', 'type': 'education', 'lineage': ['https://openalex.org/I99464096']}, {'id': 'https://openalex.org/I75951250', 'display_name': 'Freie UniversitÃ¤t Berlin', 'ror': 'https://ror.org/046ak2485', 'country_code': 'DE', 'type': 'education', 'lineage': ['https://openalex.org/I75951250']}], 'countries': ['BE', 'DE'], 'is_corresponding': False, 'raw_author_name': 'Luc De Meester', 'raw_affiliation_strings': ['Institute of Biology Freie UniversitÃ¤t Berlin Berlin Germany', 'Laboratory of Aquatic Ecology, Evolution and Conservation KU Leuven Leuven Belgium', 'Leibniz Institut fÃ¼r GewasserÃ¶kologie und Binnenfischerei (IGB) Berlin Germany', 'Laboratory of Aquatic Ecology, Evolution and Conservation, KU Leuven, Leuven, Belgium'], 'affiliations': [{'raw_affiliation_string': 'Institute of Biology Freie UniversitÃ¤t Berlin Berlin Germany', 'institution_ids': ['https://openalex.org/I75951250']}, {'raw_affiliation_string': 'Laboratory of Aquatic Ecology, Evolution and Conservation KU Leuven Leuven Belgium', 'institution_ids': ['https://openalex.org/I99464096']}, {'raw_affiliation_string': 'Leibniz Institut fÃ¼r GewasserÃ¶kologie und Binnenfischerei (IGB) Berlin Germany', 'institution_ids': ['https://openalex.org/I4210133189']}, {'raw_affiliation_string': 'Laboratory of Aquatic Ecology, Evolution and Conservation, KU Leuven, Leuven, Belgium', 'institution_ids': ['https://openalex.org/I99464096']}]}, {'author_position': 'middle', 'author': {'id': 'https://openalex.org/A5083852063', 'display_name': 'ZsÃ³fia HorvÃ¡th', 'orcid': 'https://orcid.org/0000-0003-2857-1094'}, 'institutions': [{'id': 'https://openalex.org/I4210121644', 'display_name': 'HUN-REN Balaton Limnological Research Institute', 'ror': 'https://ror.org/02pnhwp93', 'country_code': 'HU', 'type': 'facility', 'lineage': ['https://openalex.org/I4210121644', 'https://openalex.org/I4387152226']}, {'id': 'https://openalex.org/I99464096', 'display_name': 'KU Leuven', 'ror': 'https://ror.org/05f950310', 'country_code': 'BE', 'type': 'education', 'lineage': ['https://openalex.org/I99464096']}, {'id': 'https://openalex.org/I4210134135', 'display_name': 'HUN-REN Centre for Ecological Research', 'ror': 'https://ror.org/04bhfmv97', 'country_code': 'HU', 'type': 'facility', 'lineage': ['https://openalex.org/I4210134135', 'https://openalex.org/I4387152226']}, {'id': 'https://openalex.org/I4210108751', 'display_name': 'Wasser Cluster Lunz', 'ror': 'https://ror.org/01q437m46', 'country_code': 'AT', 'type': 'facility', 'lineage': ['https://openalex.org/I4210108751']}], 'countries': ['AT', 'BE', 'HU'], 'is_corresponding': False, 'raw_author_name': 'ZsÃ³fia HorvÃ¡th', 'raw_affiliation_strings': ['Balaton Limnological Institute Centre for Ecological Research Tihany Hungary', 'Laboratory of Aquatic Ecology, Evolution and Conservation KU Leuven Leuven Belgium', 'WasserCluster Lunz â€ Biologische Station Lunz am See Austria', 'Balaton Limnological Institute, Centre for Ecological Research, Tihany, Hungary', 'Laboratory of Aquatic Ecology, Evolution and Conservation, KU Leuven, Leuven, Belgium', 'WasserCluster Lunz - Biologische Station, Lunz am See, Austria'], 'affiliations': [{'raw_affiliation_string': 'Balaton Limnological Institute Centre for Ecological Research Tihany Hungary', 'institution_ids': ['https://openalex.org/I4210121644', 'https://openalex.org/I4210134135']}, {'raw_affiliation_string': 'Laboratory of Aquatic Ecology, Evolution and Conservation KU Leuven Leuven Belgium', 'institution_ids': ['https://openalex.org/I99464096']}, {'raw_affiliation_string': 'WasserCluster Lunz â€ Biologische Station Lunz am See Austria', 'institution_ids': ['https://openalex.org/I4210108751']}, {'raw_affiliation_string': 'Balaton Limnological Institute, Centre for Ecological Research, Tihany, Hungary', 'institution_ids': ['https://openalex.org/I4210121644', 'https://openalex.org/I4210134135']}, {'raw_affiliation_string': 'Laboratory of Aquatic Ecology, Evolution and Conservation, KU Leuven, Leuven, Belgium', 'institution_ids': ['https://openalex.org/I99464096']}, {'raw_affiliation_string': 'WasserCluster Lunz - Biologische Station, Lunz am See, Austria', 'institution_ids': ['https://openalex.org/I4210108751']}]}, {'author_position': 'middle', 'author': {'id': 'https://openalex.org/A5001440834', 'display_name': 'Robert PtÃ¡ÄnÃ­k', 'orcid': 'https://orcid.org/0000-0001-7176-7653'}, 'institutions': [{'id': 'https://openalex.org/I4210108751', 'display_name': 'Wasser Cluster Lunz', 'ror': 'https://ror.org/01q437m46', 'country_code': 'AT', 'type': 'facility', 'lineage': ['https://openalex.org/I4210108751']}], 'countries': ['AT'], 'is_corresponding': False, 'raw_author_name': 'Robert Ptacnik', 'raw_affiliation_strings': ['WasserCluster Lunz â€ Biologische Station Lunz am See Austria', 'WasserCluster Lunz - Biologische Station, Lunz am See, Austria'], 'affiliations': [{'raw_affiliation_string': 'WasserCluster Lunz â€ Biologische Station Lunz am See Austria', 'institution_ids': ['https://openalex.org/I4210108751']}, {'raw_affiliation_string': 'WasserCluster Lunz - Biologische Station, Lunz am See, Austria', 'institution_ids': ['https://openalex.org/I4210108751']}]}, {'author_position': 'middle', 'author': {'id': 'https://openalex.org/A5078172461', 'display_name': 'Bram Vanschoenwinkel', 'orcid': 'https://orcid.org/0000-0002-8973-6297'}, 'institutions': [{'id': 'https://openalex.org/I13469542', 'display_name': 'Vrije Universiteit Brussel', 'ror': 'https://ror.org/006e5kg04', 'country_code': 'BE', 'type': 'education', 'lineage': ['https://openalex.org/I13469542']}, {'id': 'https://openalex.org/I26999989', 'display_name': 'University of the Free State', 'ror': 'https://ror.org/009xwd568', 'country_code': 'ZA', 'type': 'education', 'lineage': ['https://openalex.org/I26999989']}], 'countries': ['BE', 'ZA'], 'is_corresponding': False, 'raw_author_name': 'Bram Vanschoenwinkel', 'raw_affiliation_strings': ['Centre for Environmental Management University of the Free State Bloemfontein South Africa', 'Department of Biology Vrije Universiteit Brussel Biology Belgium', 'Centre for Environmental Management, University of the Free State, Bloemfontein, South Africa', 'Department of Biology, Vrije Universiteit Brussel, Biology, Belgium'], 'affiliations': [{'raw_affiliation_string': 'Centre for Environmental Management University of the Free State Bloemfontein South Africa', 'institution_ids': ['https://openalex.org/I26999989']}, {'raw_affiliation_string': 'Department of Biology Vrije Universiteit Brussel Biology Belgium', 'institution_ids': ['https://openalex.org/I13469542']}, {'raw_affiliation_string': 'Centre for Environmental Management, University of the Free State, Bloemfontein, South Africa', 'institution_ids': ['https://openalex.org/I26999989']}, {'raw_affiliation_string': 'Department of Biology, Vrije Universiteit Brussel, Biology, Belgium', 'institution_ids': ['https://openalex.org/I13469542']}]}, {'author_position': 'middle', 'author': {'id': 'https://openalex.org/A5012100850', 'display_name': 'Duarte S. Viana', 'orcid': 'https://orcid.org/0000-0002-7864-0871'}, 'institutions': [{'id': 'https://openalex.org/I2801030728', 'display_name': 'German Centre for Integrative Biodiversity Research', 'ror': 'https://ror.org/01jty7g66', 'country_code': 'DE', 'type': 'facility', 'lineage': ['https://openalex.org/I2801030728']}, {'id': 'https://openalex.org/I926574661', 'display_name': 'Leipzig University', 'ror': 'https://ror.org/03s7gtk40', 'country_code': 'DE', 'type': 'education', 'lineage': ['https://openalex.org/I926574661']}], 'countries': ['DE'], 'is_corresponding': False, 'raw_author_name': 'Duarte S. Viana', 'raw_affiliation_strings': ['German Centre for Integrative Biodiversity Research (iDiv) Halleâ€Jenaâ€Leipzig Leipzig Germany', 'Leipzig University RitterstraÃŸe 26 Leipzig 04109 Germany', 'German Centre for Integrative Biodiversity Research (iDiv), Halle-Jena-Leipzig, Leipzig, Germany'], 'affiliations': [{'raw_affiliation_string': 'German Centre for Integrative Biodiversity Research (iDiv) Halleâ€Jenaâ€Leipzig Leipzig Germany', 'institution_ids': ['https://openalex.org/I2801030728']}, {'raw_affiliation_string': 'Leipzig University RitterstraÃŸe 26 Leipzig 04109 Germany', 'institution_ids': ['https://openalex.org/I926574661']}, {'raw_affiliation_string': 'German Centre for Integrative Biodiversity Research (iDiv), Halle-Jena-Leipzig, Leipzig, Germany', 'institution_ids': ['https://openalex.org/I2801030728']}]}, {'author_position': 'last', 'author': {'id': 'https://openalex.org/A5036693278', 'display_name': 'Jonathan M. Chase', 'orcid': 'https://orcid.org/0000-0001-5580-4303'}, 'institutions': [{'id': 'https://openalex.org/I2801030728', 'display_name': 'German Centre for Integrative Biodiversity Research', 'ror': 'https://ror.org/01jty7g66', 'country_code': 'DE', 'type': 'facility', 'lineage': ['https://openalex.org/I2801030728']}, {'id': 'https://openalex.org/I68956291', 'display_name': 'Martin Luther University Halle-Wittenberg', 'ror': 'https://ror.org/05gqaka33', 'country_code': 'DE', 'type': 'education', 'lineage': ['https://openalex.org/I68956291']}], 'countries': ['DE'], 'is_corresponding': False, 'raw_author_name': 'Jonathan M. Chase', 'raw_affiliation_strings': ['Department of Computer Sciences Martin Luther University Halleâ€Wittenberg Leipzig Germany', 'German Centre for Integrative Biodiversity Research (iDiv) Halleâ€Jenaâ€Leipzig Leipzig Germany', 'Department of Computer Sciences, Martin Luther University, Halle-Wittenberg, Leipzig, Germany', 'German Centre for Integrative Biodiversity Research (iDiv), Halle-Jena-Leipzig, Leipzig, Germany'], 'affiliations': [{'raw_affiliation_string': 'Department of Computer Sciences Martin Luther University Halleâ€Wittenberg Leipzig Germany', 'institution_ids': ['https://openalex.org/I68956291']}, {'raw_affiliation_string': 'German Centre for Integrative Biodiversity Research (iDiv) Halleâ€Jenaâ€Leipzig Leipzig Germany', 'institution_ids': ['https://openalex.org/I2801030728']}, {'raw_affiliation_string': 'Department of Computer Sciences, Martin Luther University, Halle-Wittenberg, Leipzig, Germany', 'institution_ids': ['https://openalex.org/I68956291']}, {'raw_affiliation_string': 'German Centre for Integrative Biodiversity Research (iDiv), Halle-Jena-Leipzig, Leipzig, Germany', 'institution_ids': ['https://openalex.org/I2801030728']}]}] | J5: 6 | K5: 8 | L5: 42.608 | M5: FALSE | N5: 323 | O5: {'volume': '23', 'issue': '9', 'first_page': '1314', 'last_page': '1329'} | P5: {'id': 'https://openalex.org/T10005', 'display_name': 'Ecology and Vegetation Dynamics Studies', 'score': 0.9976999759674072, 'subfield': {'id': 'https://openalex.org/subfields/2309', 'display_name': 'Nature and Landscape Conservation'}, 'field': {'id': 'https://openalex.org/fields/23', 'display_name': 'Environmental Science'}, 'domain': {'id': 'https://openalex.org/domains/3', 'display_name': 'Physical Sciences'}} | Q5: [{'id': 'https://openalex.org/T10005', 'display_name': 'Ecology and Vegetation Dynamics Studies', 'score': 0.9976999759674072, 'subfield': {'id': 'https://openalex.org/subfields/2309', 'display_name': 'Nature and Landscape Conservation'}, 'field': {'id': 'https://openalex.org/fields/23', 'display_name': 'Environmental Science'}, 'domain': {'id': 'https://openalex.org/domains/3', 'display_name': 'Physical Sciences'}}, {'id': 'https://openalex.org/T10482', 'display_name': 'Mathematical and Theoretical Epidemiology and Ecology Models', 'score': 0.9929999709129333, 'subfield': {'id': 'https://openalex.org/subfields/2739', 'display_name': 'Public Health, Environmental and Occupational Health'}, 'field': {'id': 'https://openalex.org/fields/27', 'display_name': 'Medicine'}, 'domain': {'id': 'https://openalex.org/domains/4', 'display_name': 'Health Sciences'}}, {'id': 'https://openalex.org/T11764', 'display_name': 'Evolution and Genetic Dynamics', 'score': 0.9876000285148621, 'subfield': {'id': 'https://openalex.org/subfields/1311', 'display_name': 'Genetics'}, 'field': {'id': 'https://openalex.org/fields/13', 'display_name': 'Biochemistry, Genetics and Molecular Biology'}, 'domain': {'id': 'https://openalex.org/domains/1', 'display_name': 'Life Sciences'}}] | R5: [{'id': 'https://openalex.org/keywords/metacommunity', 'display_name': 'Metacommunity', 'score': 0.9825855493545532}, {'id': 'https://openalex.org/keywords/ecology', 'display_name': 'Ecology', 'score': 0.6972740292549133}, {'id': 'https://openalex.org/keywords/biological-dispersal', 'display_name': 'Biological dispersal', 'score': 0.5439803600311279}, {'id': 'https://openalex.org/keywords/abiotic-component', 'display_name': 'Abiotic component', 'score': 0.5041693449020386}, {'id': 'https://openalex.org/keywords/community', 'display_name': 'Community', 'score': 0.46322205662727356}, {'id': 'https://openalex.org/keywords/alternative-stable-state', 'display_name': 'Alternative stable state', 'score': 0.4263281226158142}, {'id': 'https://openalex.org/keywords/patch-dynamics', 'display_name': 'Patch dynamics', 'score': 0.41878557205200195}, {'id': 'https://openalex.org/keywords/computer-science', 'display_name': 'Computer science', 'score': 0.3374834656715393}, {'id': 'https://openalex.org/keywords/biology', 'display_name': 'Biology', 'score': 0.28165602684020996}, {'id': 'https://openalex.org/keywords/ecosystem', 'display_name': 'Ecosystem', 'score': 0.1632048785686493}, {'id': 'https://openalex.org/keywords/population', 'display_name': 'Population', 'score': 0.11609876155853271}] | S5: [{'id': 'https://openalex.org/C2778899818', 'wikidata': 'https://www.wikidata.org/wiki/Q6822432', 'display_name': 'Metacommunity', 'level': 4, 'score': 0.9825855493545532}, {'id': 'https://openalex.org/C18903297', 'wikidata': 'https://www.wikidata.org/wiki/Q7150', 'display_name': 'Ecology', 'level': 1, 'score': 0.6972740292549133}, {'id': 'https://openalex.org/C47559259', 'wikidata': 'https://www.wikidata.org/wiki/Q778143', 'display_name': 'Biological dispersal', 'level': 3, 'score': 0.5439803600311279}, {'id': 'https://openalex.org/C132215390', 'wikidata': 'https://www.wikidata.org/wiki/Q461335', 'display_name': 'Abiotic component', 'level': 2, 'score': 0.5041693449020386}, {'id': 'https://openalex.org/C4590074', 'wikidata': 'https://www.wikidata.org/wiki/Q5608096', 'display_name': 'Community', 'level': 3, 'score': 0.46322205662727356}, {'id': 'https://openalex.org/C12064787', 'wikidata': 'https://www.wikidata.org/wiki/Q4736552', 'display_name': 'Alternative stable state', 'level': 3, 'score': 0.4263281226158142}, {'id': 'https://openalex.org/C96291035', 'wikidata': 'https://www.wikidata.org/wiki/Q7144330', 'display_name': 'Patch dynamics', 'level': 3, 'score': 0.41878557205200195}, {'id': 'https://openalex.org/C41008148', 'wikidata': 'https://www.wikidata.org/wiki/Q21198', 'display_name': 'Computer science', 'level': 0, 'score': 0.3374834656715393}, {'id': 'https://openalex.org/C86803240', 'wikidata': 'https://www.wikidata.org/wiki/Q420', 'display_name': 'Biology', 'level': 0, 'score': 0.28165602684020996}, {'id': 'https://openalex.org/C110872660', 'wikidata': 'https://www.wikidata.org/wiki/Q37813', 'display_name': 'Ecosystem', 'level': 2, 'score': 0.1632048785686493}, {'id': 'https://openalex.org/C2908647359', 'wikidata': 'https://www.wikidata.org/wiki/Q2625603', 'display_name': 'Population', 'level': 2, 'score': 0.11609876155853271}, {'id': 'https://openalex.org/C149923435', 'wikidata': 'https://www.wikidata.org/wiki/Q37732', 'display_name': 'Demography', 'level': 1, 'score': 0.0}, {'id': 'https://openalex.org/C144024400', 'wikidata': 'https://www.wikidata.org/wiki/Q21201', 'display_name': 'Sociology', 'level': 0, 'score': 0.0}] | T5: [{'id': 'https://metadata.un.org/sdg/15', 'display_name': 'Life in Land', 'score': 0.7300000190734863}] | U5: 86
A6: https://openalex.org/W4327785494 | B6: https://doi.org/10.1109/tgrs.2023.3258666 | C6: SuperYOLO: Super Resolution Assisted Object Detection in Multimodal Remote Sensing Imagery | D6: 2023 | E6: 44927 | F6: en | G6: article | H6: {'is_oa': False, 'oa_status': 'closed', 'oa_url': None, 'any_repository_has_fulltext': False} | I6: [{'author_position': 'first', 'author': {'id': 'https://openalex.org/A5090736129', 'display_name': 'Jiaqing Zhang', 'orcid': 'https://orcid.org/0009-0007-3111-1116'}, 'institutions': [{'id': 'https://openalex.org/I149594827', 'display_name': 'Xidian University', 'ror': 'https://ror.org/05s92vm98', 'country_code': 'CN', 'type': 'education', 'lineage': ['https://openalex.org/I149594827']}], 'countries': ['CN'], 'is_corresponding': True, 'raw_author_name': 'Jiaqing Zhang', 'raw_affiliation_strings': ['State Key Laboratory of Integrated Services Networks, Xidian University, Xi&#x2019;an, China'], 'affiliations': [{'raw_affiliation_string': 'State Key Laboratory of Integrated Services Networks, Xidian University, Xi&#x2019;an, China', 'institution_ids': ['https://openalex.org/I149594827']}]}, {'author_position': 'middle', 'author': {'id': 'https://openalex.org/A5007285444', 'display_name': 'Jie Lei', 'orcid': 'https://orcid.org/0000-0003-0851-6565'}, 'institutions': [{'id': 'https://openalex.org/I149594827', 'display_name': 'Xidian University', 'ror': 'https://ror.org/05s92vm98', 'country_code': 'CN', 'type': 'education', 'lineage': ['https://openalex.org/I149594827']}], 'countries': ['CN'], 'is_corresponding': False, 'raw_author_name': 'Jie Lei', 'raw_affiliation_strings': ['State Key Laboratory of Integrated Services Networks, Xidian University, Xi&#x2019;an, China'], 'affiliations': [{'raw_affiliation_string': 'State Key Laboratory of Integrated Services Networks, Xidian University, Xi&#x2019;an, China', 'institution_ids': ['https://openalex.org/I149594827']}]}, {'author_position': 'middle', 'author': {'id': 'https://openalex.org/A5052163069', 'display_name': 'Weiying Xie', 'orcid': 'https://orcid.org/0000-0001-8310-024X'}, 'institutions': [{'id': 'https://openalex.org/I149594827', 'display_name': 'Xidian University', 'ror': 'https://ror.org/05s92vm98', 'country_code': 'CN', 'type': 'education', 'lineage': ['https://openalex.org/I149594827']}], 'countries': ['CN'], 'is_corresponding': False, 'raw_author_name': 'Weiying Xie', 'raw_affiliation_strings': ['State Key Laboratory of Integrated Services Networks, Xidian University, Xi&#x2019;an, China'], 'affiliations': [{'raw_affiliation_string': 'State Key Laboratory of Integrated Services Networks, Xidian University, Xi&#x2019;an, China', 'institution_ids': ['https://openalex.org/I149594827']}]}, {'author_position': 'middle', 'author': {'id': 'https://openalex.org/A5065889904', 'display_name': 'Zhenman Fang', 'orcid': 'https://orcid.org/0000-0003-0603-9697'}, 'institutions': [{'id': 'https://openalex.org/I18014758', 'display_name': 'Simon Fraser University', 'ror': 'https://ror.org/0213rcc28', 'country_code': 'CA', 'type': 'education', 'lineage': ['https://openalex.org/I18014758']}], 'countries': ['CA'], 'is_corresponding': False, 'raw_author_name': 'Zhenman Fang', 'raw_affiliation_strings': ['School of Engineering Science, Simon Fraser University, Burnaby, BC, Canada'], 'affiliations': [{'raw_affiliation_string': 'School of Engineering Science, Simon Fraser University, Burnaby, BC, Canada', 'institution_ids': ['https://openalex.org/I18014758']}]}, {'author_position': 'middle', 'author': {'id': 'https://openalex.org/A5067798266', 'display_name': 'Yunsong Li', 'orcid': 'https://orcid.org/0000-0002-0640-4060'}, 'institutions': [{'id': 'https://openalex.org/I149594827', 'display_name': 'Xidian University', 'ror': 'https://ror.org/05s92vm98', 'country_code': 'CN', 'type': 'education', 'lineage': ['https://openalex.org/I149594827']}], 'countries': ['CN'], 'is_corresponding': False, 'raw_author_name': 'Yunsong Li', 'raw_affiliation_strings': ['State Key Laboratory of Integrated Services Networks, Xidian University, Xi&#x2019;an, China'], 'affiliations': [{'raw_affiliation_string': 'State Key Laboratory of Integrated Services Networks, Xidian University, Xi&#x2019;an, China', 'institution_ids': ['https://openalex.org/I149594827']}]}, {'author_position': 'last', 'author': {'id': 'https://openalex.org/A5033017179', 'display_name': 'Qian Du', 'orcid': 'https://orcid.org/0000-0001-8354-7500'}, 'institutions': [{'id': 'https://openalex.org/I99041443', 'display_name': 'Mississippi State University', 'ror': 'https://ror.org/0432jq872', 'country_code': 'US', 'type': 'education', 'lineage': ['https://openalex.org/I4210141039', 'https://openalex.org/I99041443']}], 'countries': ['US'], 'is_corresponding': False, 'raw_author_name': 'Qian Du', 'raw_affiliation_strings': ['Department of Electronic and Computer Engineering, Mississippi State University, Starkville, MS, USA'], 'affiliations': [{'raw_affiliation_string': 'Department of Electronic and Computer Engineering, Mississippi State University, Starkville, MS, USA', 'institution_ids': ['https://openalex.org/I99041443']}]}] | J6: 3 | K6: 6 | L6: 46.147 | M6: FALSE | N6: 284 | O6: {'volume': '61', 'issue': None, 'first_page': '1', 'last_page': '15'} | P6: {'id': 'https://openalex.org/T11659', 'display_name': 'Advanced Image Fusion Techniques', 'score': 0.9980999827384949, 'subfield': {'id': 'https://openalex.org/subfields/2214', 'display_name': 'Media Technology'}, 'field': {'id': 'https://openalex.org/fields/22', 'display_name': 'Engineering'}, 'domain': {'id': 'https://openalex.org/domains/3', 'display_name': 'Physical Sciences'}} | Q6: [{'id': 'https://openalex.org/T11659', 'display_name': 'Advanced Image Fusion Techniques', 'score': 0.9980999827384949, 'subfield': {'id': 'https://openalex.org/subfields/2214', 'display_name': 'Media Technology'}, 'field': {'id': 'https://openalex.org/fields/22', 'display_name': 'Engineering'}, 'domain': {'id': 'https://openalex.org/domains/3', 'display_name': 'Physical Sciences'}}, {'id': 'https://openalex.org/T11105', 'display_name': 'Advanced Image Processing Techniques', 'score': 0.9977999925613403, 'subfield': {'id': 'https://openalex.org/subfields/1707', 'display_name': 'Computer Vision and Pattern Recognition'}, 'field': {'id': 'https://openalex.org/fields/17', 'display_name': 'Computer Science'}, 'domain': {'id': 'https://openalex.org/domains/3', 'display_name': 'Physical Sciences'}}, {'id': 'https://openalex.org/T10036', 'display_name': 'Advanced Neural Network Applications', 'score': 0.9969000220298767, 'subfield': {'id': 'https://openalex.org/subfields/1707', 'display_name': 'Computer Vision and Pattern Recognition'}, 'field': {'id': 'https://openalex.org/fields/17', 'display_name': 'Computer Science'}, 'domain': {'id': 'https://openalex.org/domains/3', 'display_name': 'Physical Sciences'}}] | R6: [{'id': 'https://openalex.org/keywords/computer-science', 'display_name': 'Computer science', 'score': 0.8446010947227478}, {'id': 'https://openalex.org/keywords/computation', 'display_name': 'Computation', 'score': 0.806489109992981}, {'id': 'https://openalex.org/keywords/object-detection', 'display_name': 'Object detection', 'score': 0.6983808875083923}, {'id': 'https://openalex.org/keywords/artificial-intelligence', 'display_name': 'Artificial intelligence', 'score': 0.6753076314926147}, {'id': 'https://openalex.org/keywords/pixel', 'display_name': 'Pixel', 'score': 0.6288599967956543}, {'id': 'https://openalex.org/keywords/feature', 'display_name': 'Feature (linguistics)', 'score': 0.5820839405059814}, {'id': 'https://openalex.org/keywords/image-resolution', 'display_name': 'Image resolution', 'score': 0.5314950346946716}, {'id': 'https://openalex.org/keywords/pattern-recognition', 'display_name': 'Pattern recognition (psychology)', 'score': 0.49267464876174927}, {'id': 'https://openalex.org/keywords/inference', 'display_name': 'Inference', 'score': 0.4808788597583771}, {'id': 'https://openalex.org/keywords/object', 'display_name': 'Object (grammar)', 'score': 0.46375659108161926}, {'id': 'https://openalex.org/keywords/flops', 'display_name': 'FLOPS', 'score': 0.46300533413887024}, {'id': 'https://openalex.org/keywords/computer-vision', 'display_name': 'Computer vision', 'score': 0.44324833154678345}, {'id': 'https://openalex.org/keywords/deep-learning', 'display_name': 'Deep learning', 'score': 0.41868436336517334}, {'id': 'https://openalex.org/keywords/artificial-neural-network', 'display_name': 'Artificial neural network', 'score': 0.4182599186897278}, {'id': 'https://openalex.org/keywords/algorithm', 'display_name': 'Algorithm', 'score': 0.21023279428482056}] | S6: [{'id': 'https://openalex.org/C41008148', 'wikidata': 'https://www.wikidata.org/wiki/Q21198', 'display_name': 'Computer science', 'level': 0, 'score': 0.8446010947227478}, {'id': 'https://openalex.org/C45374587', 'wikidata': 'https://www.wikidata.org/wiki/Q12525525', 'display_name': 'Computation', 'level': 2, 'score': 0.806489109992981}, {'id': 'https://openalex.org/C2776151529', 'wikidata': 'https://www.wikidata.org/wiki/Q3045304', 'display_name': 'Object detection', 'level': 3, 'score': 0.6983808875083923}, {'id': 'https://openalex.org/C154945302', 'wikidata': 'https://www.wikidata.org/wiki/Q11660', 'display_name': 'Artificial intelligence', 'level': 1, 'score': 0.6753076314926147}, {'id': 'https://openalex.org/C160633673', 'wikidata': 'https://www.wikidata.org/wiki/Q355198', 'display_name': 'Pixel', 'level': 2, 'score': 0.6288599967956543}, {'id': 'https://openalex.org/C2776401178', 'wikidata': 'https://www.wikidata.org/wiki/Q12050496', 'display_name': 'Feature (linguistics)', 'level': 2, 'score': 0.5820839405059814}, {'id': 'https://openalex.org/C205372480', 'wikidata': 'https://www.wikidata.org/wiki/Q210521', 'display_name': 'Image resolution', 'level': 2, 'score': 0.5314950346946716}, {'id': 'https://openalex.org/C153180895', 'wikidata': 'https://www.wikidata.org/wiki/Q7148389', 'display_name': 'Pattern recognition (psychology)', 'level': 2, 'score': 0.49267464876174927}, {'id': 'https://openalex.org/C2776214188', 'wikidata': 'https://www.wikidata.org/wiki/Q408386', 'display_name': 'Inference', 'level': 2, 'score': 0.4808788597583771}, {'id': 'https://openalex.org/C2781238097', 'wikidata': 'https://www.wikidata.org/wiki/Q175026', 'display_name': 'Object (grammar)', 'level': 2, 'score': 0.46375659108161926}, {'id': 'https://openalex.org/C3826847', 'wikidata': 'https://www.wikidata.org/wiki/Q188768', 'display_name': 'FLOPS', 'level': 2, 'score': 0.46300533413887024}, {'id': 'https://openalex.org/C31972630', 'wikidata': 'https://www.wikidata.org/wiki/Q844240', 'display_name': 'Computer vision', 'level': 1, 'score': 0.44324833154678345}, {'id': 'https://openalex.org/C108583219', 'wikidata': 'https://www.wikidata.org/wiki/Q197536', 'display_name': 'Deep learning', 'level': 2, 'score': 0.41868436336517334}, {'id': 'https://openalex.org/C50644808', 'wikidata': 'https://www.wikidata.org/wiki/Q192776', 'display_name': 'Artificial neural network', 'level': 2, 'score': 0.4182599186897278}, {'id': 'https://openalex.org/C11413529', 'wikidata': 'https://www.wikidata.org/wiki/Q8366', 'display_name': 'Algorithm', 'level': 1, 'score': 0.21023279428482056}, {'id': 'https://openalex.org/C173608175', 'wikidata': 'https://www.wikidata.org/wiki/Q232661', 'display_name': 'Parallel computing', 'level': 1, 'score': 0.0}, {'id': 'https://openalex.org/C41895202', 'wikidata': 'https://www.wikidata.org/wiki/Q8162', 'display_name': 'Linguistics', 'level': 1, 'score': 0.0}, {'id': 'https://openalex.org/C138885662', 'wikidata': 'https://www.wikidata.org/wiki/Q5891', 'display_name': 'Philosophy', 'level': 0, 'score': 0.0}] | T6: [{'id': 'https://metadata.un.org/sdg/10', 'display_name': 'Reduced inequalities', 'score': 0.6299999952316284}] | U6: 62
A7: https://openalex.org/W4226490845 | B7: https://doi.org/10.1109/tii.2022.3158974 | C7: Task Co-Offloading for D2D-Assisted Mobile Edge Computing in Industrial Internet of Things | D7: 2022 | E7: 44635 | F7: en | G7: article | H7: {'is_oa': False, 'oa_status': 'closed', 'oa_url': None, 'any_repository_has_fulltext': False} | I7: [{'author_position': 'first', 'author': {'id': 'https://openalex.org/A5036655672', 'display_name': 'Xingxia Dai', 'orcid': 'https://orcid.org/0000-0001-5540-9418'}, 'institutions': [{'id': 'https://openalex.org/I16609230', 'display_name': 'Hunan University', 'ror': 'https://ror.org/05htk5m33', 'country_code': 'CN', 'type': 'education', 'lineage': ['https://openalex.org/I16609230']}], 'countries': ['CN'], 'is_corresponding': True, 'raw_author_name': 'Xingxia Dai', 'raw_affiliation_strings': ['College of Computer Science and Electronic Engineering, Hunan University, Changsha, China'], 'affiliations': [{'raw_affiliation_string': 'College of Computer Science and Electronic Engineering, Hunan University, Changsha, China', 'institution_ids': ['https://openalex.org/I16609230']}]}, {'author_position': 'middle', 'author': {'id': 'https://openalex.org/A5001435169', 'display_name': 'Zhu Xiao', 'orcid': 'https://orcid.org/0000-0001-5645-160X'}, 'institutions': [{'id': 'https://openalex.org/I16609230', 'display_name': 'Hunan University', 'ror': 'https://ror.org/05htk5m33', 'country_code': 'CN', 'type': 'education', 'lineage': ['https://openalex.org/I16609230']}], 'countries': ['CN'], 'is_corresponding': False, 'raw_author_name': 'Zhu Xiao', 'raw_affiliation_strings': ['College of Computer Science and Electronic Engineering, Hunan University, Changsha, China'], 'affiliations': [{'raw_affiliation_string': 'College of Computer Science and Electronic Engineering, Hunan University, Changsha, China', 'institution_ids': ['https://openalex.org/I16609230']}]}, {'author_position': 'middle', 'author': {'id': 'https://openalex.org/A5061448582', 'display_name': 'Hongbo Jiang', 'orcid': 'https://orcid.org/0000-0001-7372-2539'}, 'institutions': [{'id': 'https://openalex.org/I16609230', 'display_name': 'Hunan University', 'ror': 'https://ror.org/05htk5m33', 'country_code': 'CN', 'type': 'education', 'lineage': ['https://openalex.org/I16609230']}], 'countries': ['CN'], 'is_corresponding': False, 'raw_author_name': 'Hongbo Jiang', 'raw_affiliation_strings': ['College of Computer Science and Electronic Engineering, Hunan University, Changsha, China'], 'affiliations': [{'raw_affiliation_string': 'College of Computer Science and Electronic Engineering, Hunan University, Changsha, China', 'institution_ids': ['https://openalex.org/I16609230']}]}, {'author_position': 'middle', 'author': {'id': 'https://openalex.org/A5018409592', 'display_name': 'Mamoun Alazab', 'orcid': 'https://orcid.org/0000-0002-1928-3704'}, 'institutions': [{'id': 'https://openalex.org/I29894533', 'display_name': 'Charles Darwin University', 'ror': 'https://ror.org/048zcaj52', 'country_code': 'AU', 'type': 'education', 'lineage': ['https://openalex.org/I29894533']}], 'countries': ['AU'], 'is_corresponding': False, 'raw_author_name': 'Mamoun Alazab', 'raw_affiliation_strings': ['College of Engineering, IT, and Environment, Charles Darwin University, Darwin, NT, Australia'], 'affiliations': [{'raw_affiliation_string': 'College of Engineering, IT, and Environment, Charles Darwin University, Darwin, NT, Australia', 'institution_ids': ['https://openalex.org/I29894533']}]}, {'author_position': 'middle', 'author': {'id': 'https://openalex.org/A5068489266', 'display_name': 'John C. S. Lui', 'orcid': 'https://orcid.org/0000-0001-7466-0384'}, 'institutions': [{'id': 'https://openalex.org/I177725633', 'display_name': 'Chinese University of Hong Kong', 'ror': 'https://ror.org/00t33hh48', 'country_code': 'CN', 'type': 'education', 'lineage': ['https://openalex.org/I177725633']}], 'countries': ['CN'], 'is_corresponding': False, 'raw_author_name': 'John C. S. Lui', 'raw_affiliation_strings': ['Department of Computer Science and Engineering, The Chinese University of Hong Kong, Hong Kong'], 'affiliations': [{'raw_affiliation_string': 'Department of Computer Science and Engineering, The Chinese University of Hong Kong, Hong Kong', 'institution_ids': ['https://openalex.org/I177725633']}]}, {'author_position': 'middle', 'author': {'id': 'https://openalex.org/A5004847496', 'display_name': 'Schahram Dustdar', 'orcid': 'https://orcid.org/0000-0001-6872-8821'}, 'institutions': [{'id': 'https://openalex.org/I145847075', 'display_name': 'TU Wien', 'ror': 'https://ror.org/04d836q62', 'country_code': 'AT', 'type': 'education', 'lineage': ['https://openalex.org/I145847075']}], 'countries': ['AT'], 'is_corresponding': False, 'raw_author_name': 'Schahram Dustdar', 'raw_affiliation_strings': ['TU Wien, Vienna, Austria'], 'affiliations': [{'raw_affiliation_string': 'TU Wien, Vienna, Austria', 'institution_ids': ['https://openalex.org/I145847075']}]}, {'author_position': 'last', 'author': {'id': 'https://openalex.org/A5039311485', 'display_name': 'Jiangchuan Liu', 'orcid': 'https://orcid.org/0000-0001-6592-1984'}, 'institutions': [{'id': 'https://openalex.org/I18014758', 'display_name': 'Simon Fraser University', 'ror': 'https://ror.org/0213rcc28', 'country_code': 'CA', 'type': 'education', 'lineage': ['https://openalex.org/I18014758']}], 'countries': ['CA'], 'is_corresponding': False, 'raw_author_name': 'Jiangchuan Liu', 'raw_affiliation_strings': ['School of Computing Science, Simon Fraser University, Burnaby, BC, Canada'], 'affiliations': [{'raw_affiliation_string': 'School of Computing Science, Simon Fraser University, Burnaby, BC, Canada', 'institution_ids': ['https://openalex.org/I18014758']}]}] | J7: 4 | K7: 7 | L7: 37.5716 | M7: FALSE | N7: 277 | O7: {'volume': '19', 'issue': '1', 'first_page': '480', 'last_page': '490'} | P7: {'id': 'https://openalex.org/T10273', 'display_name': 'IoT and Edge/Fog Computing', 'score': 0.9998000264167786, 'subfield': {'id': 'https://openalex.org/subfields/1705', 'display_name': 'Computer Networks and Communications'}, 'field': {'id': 'https://openalex.org/fields/17', 'display_name': 'Computer Science'}, 'domain': {'id': 'https://openalex.org/domains/3', 'display_name': 'Physical Sciences'}} | Q7: [{'id': 'https://openalex.org/T10273', 'display_name': 'IoT and Edge/Fog Computing', 'score': 0.9998000264167786, 'subfield': {'id': 'https://openalex.org/subfields/1705', 'display_name': 'Computer Networks and Communications'}, 'field': {'id': 'https://openalex.org/fields/17', 'display_name': 'Computer Science'}, 'domain': {'id': 'https://openalex.org/domains/3', 'display_name': 'Physical Sciences'}}, {'id': 'https://openalex.org/T13553', 'display_name': 'Age of Information Optimization', 'score': 0.996999979019165, 'subfield': {'id': 'https://openalex.org/subfields/1705', 'display_name': 'Computer Networks and Communications'}, 'field': {'id': 'https://openalex.org/fields/17', 'display_name': 'Computer Science'}, 'domain': {'id': 'https://openalex.org/domains/3', 'display_name': 'Physical Sciences'}}, {'id': 'https://openalex.org/T10764', 'display_name': 'Privacy-Preserving Technologies in Data', 'score': 0.9915000200271606, 'subfield': {'id': 'https://openalex.org/subfields/1702', 'display_name': 'Artificial Intelligence'}, 'field': {'id': 'https://openalex.org/fields/17', 'display_name': 'Computer Science'}, 'domain': {'id': 'https://openalex.org/domains/3', 'display_name': 'Physical Sciences'}}] | R7: [{'id': 'https://openalex.org/keywords/computer-science', 'display_name': 'Computer science', 'score': 0.8295243978500366}, {'id': 'https://openalex.org/keywords/mobile-edge-computing', 'display_name': 'Mobile edge computing', 'score': 0.7930303812026978}, {'id': 'https://openalex.org/keywords/computation-offloading', 'display_name': 'Computation offloading', 'score': 0.7782489657402039}, {'id': 'https://openalex.org/keywords/server', 'display_name': 'Server', 'score': 0.6685096621513367}, {'id': 'https://openalex.org/keywords/edge-computing', 'display_name': 'Edge computing', 'score': 0.6253806948661804}, {'id': 'https://openalex.org/keywords/computer-network', 'display_name': 'Computer network', 'score': 0.5997419953346252}, {'id': 'https://openalex.org/keywords/enhanced-data-rates-for-gsm-evolution', 'display_name': 'Enhanced Data Rates for GSM Evolution', 'score': 0.5741907358169556}, {'id': 'https://openalex.org/keywords/task', 'display_name': 'Task (project management)', 'score': 0.5460893511772156}, {'id': 'https://openalex.org/keywords/mobile-device', 'display_name': 'Mobile device', 'score': 0.5217141509056091}, {'id': 'https://openalex.org/keywords/node', 'display_name': 'Node (physics)', 'score': 0.509657621383667}, {'id': 'https://openalex.org/keywords/distributed-computing', 'display_name': 'Distributed computing', 'score': 0.4633524715900421}, {'id': 'https://openalex.org/keywords/mobile-computing', 'display_name': 'Mobile computing', 'score': 0.42005935311317444}, {'id': 'https://openalex.org/keywords/the-internet', 'display_name': 'The Internet', 'score': 0.41840124130249023}, {'id': 'https://openalex.org/keywords/small-cell', 'display_name': 'Small cell', 'score': 0.41177597641944885}, {'id': 'https://openalex.org/keywords/cellular-network', 'display_name': 'Cellular network', 'score': 0.4104534983634949}, {'id': 'https://openalex.org/keywords/operating-system', 'display_name': 'Operating system', 'score': 0.09561896324157715}, {'id': 'https://openalex.org/keywords/artificial-intelligence', 'display_name': 'Artificial intelligence', 'score': 0.08986067771911621}, {'id': 'https://openalex.org/keywords/engineering', 'display_name': 'Engineering', 'score': 0.0801149308681488}] | S7: [{'id': 'https://openalex.org/C41008148', 'wikidata': 'https://www.wikidata.org/wiki/Q21198', 'display_name': 'Computer science', 'level': 0, 'score': 0.8295243978500366}, {'id': 'https://openalex.org/C2776061582', 'wikidata': 'https://www.wikidata.org/wiki/Q25325231', 'display_name': 'Mobile edge computing', 'level': 3, 'score': 0.7930303812026978}, {'id': 'https://openalex.org/C2781041963', 'wikidata': 'https://www.wikidata.org/wiki/Q18348618', 'display_name': 'Computation offloading', 'level': 4, 'score': 0.7782489657402039}, {'id': 'https://openalex.org/C93996380', 'wikidata': 'https://www.wikidata.org/wiki/Q44127', 'display_name': 'Server', 'level': 2, 'score': 0.6685096621513367}, {'id': 'https://openalex.org/C2778456923', 'wikidata': 'https://www.wikidata.org/wiki/Q5337692', 'display_name': 'Edge computing', 'level': 3, 'score': 0.6253806948661804}, {'id': 'https://openalex.org/C31258907', 'wikidata': 'https://www.wikidata.org/wiki/Q1301371', 'display_name': 'Computer network', 'level': 1, 'score': 0.5997419953346252}, {'id': 'https://openalex.org/C162307627', 'wikidata': 'https://www.wikidata.org/wiki/Q204833', 'display_name': 'Enhanced Data Rates for GSM Evolution', 'level': 2, 'score': 0.5741907358169556}, {'id': 'https://openalex.org/C2780451532', 'wikidata': 'https://www.wikidata.org/wiki/Q759676', 'display_name': 'Task (project management)', 'level': 2, 'score': 0.5460893511772156}, {'id': 'https://openalex.org/C186967261', 'wikidata': 'https://www.wikidata.org/wiki/Q5082128', 'display_name': 'Mobile device', 'level': 2, 'score': 0.5217141509056091}, {'id': 'https://openalex.org/C62611344', 'wikidata': 'https://www.wikidata.org/wiki/Q1062658', 'display_name': 'Node (physics)', 'level': 2, 'score': 0.509657621383667}, {'id': 'https://openalex.org/C120314980', 'wikidata': 'https://www.wikidata.org/wiki/Q180634', 'display_name': 'Distributed computing', 'level': 1, 'score': 0.4633524715900421}, {'id': 'https://openalex.org/C144543869', 'wikidata': 'https://www.wikidata.org/wiki/Q2738570', 'display_name': 'Mobile computing', 'level': 2, 'score': 0.42005935311317444}, {'id': 'https://openalex.org/C110875604', 'wikidata': 'https://www.wikidata.org/wiki/Q75', 'display_name': 'The Internet', 'level': 2, 'score': 0.41840124130249023}, {'id': 'https://openalex.org/C179655311', 'wikidata': 'https://www.wikidata.org/wiki/Q7543020', 'display_name': 'Small cell', 'level': 3, 'score': 0.41177597641944885}, {'id': 'https://openalex.org/C153646914', 'wikidata': 'https://www.wikidata.org/wiki/Q535695', 'display_name': 'Cellular network', 'level': 2, 'score': 0.4104534983634949}, {'id': 'https://openalex.org/C111919701', 'wikidata': 'https://www.wikidata.org/wiki/Q9135', 'display_name': 'Operating system', 'level': 1, 'score': 0.09561896324157715}, {'id': 'https://openalex.org/C154945302', 'wikidata': 'https://www.wikidata.org/wiki/Q11660', 'display_name': 'Artificial intelligence', 'level': 1, 'score': 0.08986067771911621}, {'id': 'https://openalex.org/C127413603', 'wikidata': 'https://www.wikidata.org/wiki/Q11023', 'display_name': 'Engineering', 'level': 0, 'score': 0.0801149308681488}, {'id': 'https://openalex.org/C201995342', 'wikidata': 'https://www.wikidata.org/wiki/Q682496', 'display_name': 'Systems engineering', 'level': 1, 'score': 0.0}, {'id': 'https://openalex.org/C66938386', 'wikidata': 'https://www.wikidata.org/wiki/Q633538', 'display_name': 'Structural engineering', 'level': 1, 'score': 0.0}] | T7: [{'id': 'https://metadata.un.org/sdg/10', 'display_name': 'Reduced inequalities', 'score': 0.7400000095367432}] | U7: 35
A8: https://openalex.org/W3004697769 | B8: https://doi.org/10.5194/bg-17-2987-2020 | C8: Is there warming in the pipeline? A multi-model analysis of the Zero Emissions Commitment from CO <sub>2</sub> | D8: 2020 | E8: 43997 | F8: en | G8: article | H8: {'is_oa': True, 'oa_status': 'gold', 'oa_url': 'https://bg.copernicus.org/articles/17/2987/2020/bg-17-2987-2020.pdf', 'any_repository_has_fulltext': True} | I8: [{'author_position': 'first', 'author': {'id': 'https://openalex.org/A5062011169', 'display_name': 'Andrew H. MacDougall', 'orcid': 'https://orcid.org/0000-0001-7899-9940'}, 'institutions': [{'id': 'https://openalex.org/I197191942', 'display_name': 'St. Francis Xavier University', 'ror': 'https://ror.org/01wcaxs37', 'country_code': 'CA', 'type': 'education', 'lineage': ['https://openalex.org/I197191942']}], 'countries': ['CA'], 'is_corresponding': True, 'raw_author_name': 'Andrew H. MacDougall', 'raw_affiliation_strings': ['Climate & Environment, St. Francis Xavier University, Antigonish, Nova Scotia, B2G 2W5, Canada'], 'affiliations': [{'raw_affiliation_string': 'Climate & Environment, St. Francis Xavier University, Antigonish, Nova Scotia, B2G 2W5, Canada', 'institution_ids': ['https://openalex.org/I197191942']}]}, {'author_position': 'middle', 'author': {'id': 'https://openalex.org/A5063055679', 'display_name': 'Thomas L. FrÃ¶licher', 'orcid': 'https://orcid.org/0000-0003-2348-7854'}, 'institutions': [{'id': 'https://openalex.org/I1299204452', 'display_name': 'Oeschger Centre for Climate Change Research', 'ror': 'https://ror.org/0329s8h62', 'country_code': 'CH', 'type': 'facility', 'lineage': ['https://openalex.org/I1299204452']}, {'id': 'https://openalex.org/I118564535', 'display_name': 'University of Bern', 'ror': 'https://ror.org/02k7v4d05', 'country_code': 'CH', 'type': 'education', 'lineage': ['https://openalex.org/I118564535']}], 'countries': ['CH'], 'is_corresponding': False, 'raw_author_name': 'Thomas L. FrÃ¶licher', 'raw_affiliation_strings': ['Climate and Environmental Physics, Physics Institute, University of Bern, Bern, Switzerland', 'Oeschger Centre for Climate Change Research, University of Bern, Bern, Switzerland'], 'affiliations': [{'raw_affiliation_string': 'Climate and Environmental Physics, Physics Institute, University of Bern, Bern, Switzerland', 'institution_ids': ['https://openalex.org/I118564535']}, {'raw_affiliation_string': 'Oeschger Centre for Climate Change Research, University of Bern, Bern, Switzerland', 'institution_ids': ['https://openalex.org/I1299204452', 'https://openalex.org/I118564535']}]}, {'author_position': 'middle', 'author': {'id': 'https://openalex.org/A5025928838', 'display_name': 'Chris Jones', 'orcid': 'https://orcid.org/0000-0002-7141-9285'}, 'institutions': [{'id': 'https://openalex.org/I1293035123', 'display_name': 'Met Office', 'ror': 'https://ror.org/01ch2yn61', 'country_code': 'GB', 'type': 'funder', 'lineage': ['https://openalex.org/I1293035123']}], 'countries': ['GB'], 'is_corresponding': True, 'raw_author_name': 'Chris D. Jones', 'raw_affiliation_strings': ['Met Office Hadley Centre, Exeter, EX1 3PB, UK'], 'affiliations': [{'raw_affiliation_string': 'Met Office Hadley Centre, Exeter, EX1 3PB, UK', 'institution_ids': ['https://openalex.org/I1293035123']}]}, {'author_position': 'middle', 'author': {'id': 'https://openalex.org/A5017820045', 'display_name': 'Joeri Rogelj', 'orcid': 'https://orcid.org/0000-0003-2056-9061'}, 'institutions': [{'id': 'https://openalex.org/I47508984', 'display_name': 'Imperial College London', 'ror': 'https://ror.org/041kmwe10', 'country_code': 'GB', 'type': 'education', 'lineage': ['https://openalex.org/I47508984']}, {'id': 'https://openalex.org/I1317774081', 'display_name': 'International Institute for Applied Systems Analysis', 'ror': 'https://ror.org/02wfhk785', 'country_code': 'AT', 'type': 'funder', 'lineage': ['https://openalex.org/I1317774081']}], 'countries': ['AT', 'GB'], 'is_corresponding': True, 'raw_author_name': 'Joeri Rogelj', 'raw_affiliation_strings': ['Grantham Institute for Climate Change and the Environment, Imperial College London, London, SW7 2BU, UK', 'International Institute for Applied Systems Analysis (IIASA), Laxenburg, Austria'], 'affiliations': [{'raw_affiliation_string': 'Grantham Institute for Climate Change and the Environment, Imperial College London, London, SW7 2BU, UK', 'institution_ids': ['https://openalex.org/I47508984']}, {'raw_affiliation_string': 'International Institute for Applied Systems Analysis (IIASA), Laxenburg, Austria', 'institution_ids': ['https://openalex.org/I1317774081']}]}, {'author_position': 'middle', 'author': {'id': 'https://openalex.org/A5051571272', 'display_name': 'H. Damon Matthews', 'orcid': 'https://orcid.org/0000-0003-3625-390X'}, 'institutions': [{'id': 'https://openalex.org/I60158472', 'display_name': 'Concordia University', 'ror': 'https://ror.org/0420zvk78', 'country_code': 'CA', 'type': 'education', 'lineage': ['https://openalex.org/I60158472']}], 'countries': ['CA'], 'is_corresponding': True, 'raw_author_name': 'H. Damon Matthews', 'raw_affiliation_strings': ['Department of Geography, Concordia University, Montreal, Quebec, H3G 1M8, Canada'], 'affiliations': [{'raw_affiliation_string': 'Department of Geography, Concordia University, Montreal, Quebec, H3G 1M8, Canada', 'institution_ids': ['https://openalex.org/I60158472']}]}, {'author_position': 'middle', 'author': {'id': 'https://openalex.org/A5032945153', 'display_name': 'Kirsten Zickfeld', 'orcid': 'https://orcid.org/0000-0001-8866-6541'}, 'institutions': [{'id': 'https://openalex.org/I18014758', 'display_name': 'Simon Fraser University', 'ror': 'https://ror.org/0213rcc28', 'country_code': 'CA', 'type': 'education', 'lineage': ['https://openalex.org/I18014758']}], 'countries': ['CA'], 'is_corresponding': True, 'raw_author_name': 'Kirsten Zickfeld', 'raw_affiliation_strings': ['Department of Geography, Simon Fraser University, Burnaby, British Columbia, V5A 1S6, Canada'], 'affiliations': [{'raw_affiliation_string': 'Department of Geography, Simon Fraser University, Burnaby, British Columbia, V5A 1S6, Canada', 'institution_ids': ['https://openalex.org/I18014758']}]}, {'author_position': 'middle', 'author': {'id': 'https://openalex.org/A5053861379', 'display_name': 'Vivek K. Arora', 'orcid': 'https://orcid.org/0000-0002-2620-9342'}, 'institutions': [{'id': 'https://openalex.org/I1342547582', 'display_name': 'Environment and Climate Change Canada', 'ror': 'https://ror.org/026ny0e17', 'country_code': 'CA', 'type': 'funder', 'lineage': ['https://openalex.org/I1342547582', 'https://openalex.org/I2802286613']}], 'countries': ['CA'], 'is_corresponding': False, 'raw_author_name': 'Vivek K. Arora', 'raw_affiliation_strings': ['Canadian Centre for Climate Modelling and Analysis, Environment and Climate Change Canada, Victoria, British Columbia, V8W 2Y2, Canada'], 'affiliations': [{'raw_affiliation_string': 'Canadian Centre for Climate Modelling and Analysis, Environment and Climate Change Canada, Victoria, British Columbia, V8W 2Y2, Canada', 'institution_ids': ['https://openalex.org/I1342547582']}]}, {'author_position': 'middle', 'author': {'id': 'https://openalex.org/A5083004225', 'display_name': 'Noah J. Barrett', 'orcid': None}, 'institutions': [{'id': 'https://openalex.org/I197191942', 'display_name': 'St. Francis Xavier University', 'ror': 'https://ror.org/01wcaxs37', 'country_code': 'CA', 'type': 'education', 'lineage': ['https://openalex.org/I197191942']}], 'countries': ['CA'], 'is_corresponding': False, 'raw_author_name': 'Noah J. Barrett', 'raw_affiliation_strings': ['Climate & Environment, St. Francis Xavier University, Antigonish, Nova Scotia, B2G 2W5, Canada'], 'affiliations': [{'raw_affiliation_string': 'Climate & Environment, St. Francis Xavier University, Antigonish, Nova Scotia, B2G 2W5, Canada', 'institution_ids': ['https://openalex.org/I197191942']}]}, {'author_position': 'middle', 'author': {'id': 'https://openalex.org/A5090811532', 'display_name': '\ufeffVictor Brovkin', 'orcid': 'https://orcid.org/0000-0001-6420-3198'}, 'institutions': [{'id': 'https://openalex.org/I4210163131', 'display_name': 'Max Planck Institute for Meteorology', 'ror': 'https://ror.org/05esem239', 'country_code': 'DE', 'type': 'facility', 'lineage': ['https://openalex.org/I149899117', 'https://openalex.org/I4210163131']}, {'id': 'https://openalex.org/I159176309', 'display_name': 'UniversitÃ¤t Hamburg', 'ror': 'https://ror.org/00g30e956', 'country_code': 'DE', 'type': 'education', 'lineage': ['https://openalex.org/I159176309']}], 'countries': ['DE'], 'is_corresponding': True, 'raw_author_name': 'Victor Brovkin', 'raw_affiliation_strings': ['CEN, University of Hamburg, Hamburg, Germany', 'Max Planck Institute for Meteorology, Hamburg, Germany'], 'affiliations': [{'raw_affiliation_string': 'CEN, University of Hamburg, Hamburg, Germany', 'institution_ids': ['https://openalex.org/I159176309']}, {'raw_affiliation_string': 'Max Planck Institute for Meteorology, Hamburg, Germany', 'institution_ids': ['https://openalex.org/I4210163131']}]}, {'author_position': 'middle', 'author': {'id': 'https://openalex.org/A5063499543', 'display_name': 'Friedrich A. Burger', 'orcid': 'https://orcid.org/0000-0002-7781-8498'}, 'institutions': [{'id': 'https://openalex.org/I1299204452', 'display_name': 'Oeschger Centre for Climate Change Research', 'ror': 'https://ror.org/0329s8h62', 'country_code': 'CH', 'type': 'facility', 'lineage': ['https://openalex.org/I1299204452']}, {'id': 'https://openalex.org/I118564535', 'display_name': 'University of Bern', 'ror': 'https://ror.org/02k7v4d05', 'country_code': 'CH', 'type': 'education', 'lineage': ['https://openalex.org/I118564535']}], 'countries': ['CH'], 'is_corresponding': True, 'raw_author_name': 'Friedrich A. Burger', 'raw_affiliation_strings': ['Climate and Environmental Physics, Physics Institute, University of Bern, Bern, Switzerland', 'Oeschger Centre for Climate Change Research, University of Bern, Bern, Switzerland'], 'affiliations': [{'raw_affiliation_string': 'Climate and Environmental Physics, Physics Institute, University of Bern, Bern, Switzerland', 'institution_ids': ['https://openalex.org/I118564535']}, {'raw_affiliation_string': 'Oeschger Centre for Climate Change Research, University of Bern, Bern, Switzerland', 'institution_ids': ['https://openalex.org/I1299204452', 'https://openalex.org/I118564535']}]}, {'author_position': 'middle', 'author': {'id': 'https://openalex.org/A5020432609', 'display_name': 'M. Eby', 'orcid': None}, 'institutions': [{'id': 'https://openalex.org/I212119943', 'display_name': 'University of Victoria', 'ror': 'https://ror.org/04s5mat29', 'country_code': 'CA', 'type': 'education', 'lineage': ['https://openalex.org/I212119943']}], 'countries': ['CA'], 'is_corresponding': False, 'raw_author_name': 'Micheal Eby', 'raw_affiliation_strings': ['School of Earth and Ocean Sciences, University of Victoria, Victoria, British Columbia, V8W 2Y2, Canada'], 'affiliations': [{'raw_affiliation_string': 'School of Earth and Ocean Sciences, University of Victoria, Victoria, British Columbia, V8W 2Y2, Canada', 'institution_ids': ['https://openalex.org/I212119943']}]}, {'author_position': 'middle', 'author': {'id': 'https://openalex.org/A5037938558', 'display_name': 'Ð. Ð’. Ð•Ð»Ð¸ÑÐµÐµÐ²', 'orcid': 'https://orcid.org/0000-0001-7288-7649'}, 'institutions': [{'id': 'https://openalex.org/I4210150607', 'display_name': 'A.M. Obukhov Institute of Atmospheric Physics', 'ror': 'https://ror.org/03snt1857', 'country_code': 'RU', 'type': 'facility', 'lineage': ['https://openalex.org/I1313323035', 'https://openalex.org/I4210150607', 'https://openalex.org/I4210163714']}, {'id': 'https://openalex.org/I19880235', 'display_name': 'Lomonosov Moscow State University', 'ror': 'https://ror.org/010pmpe69', 'country_code': 'RU', 'type': 'education', 'lineage': ['https://openalex.org/I19880235']}], 'countries': ['RU'], 'is_corresponding': True, 'raw_author_name': 'Alexey V. Eliseev', 'raw_affiliation_strings': ['A.M. Obukhov Institute of Atmospheric Physics, Russian Academy of Sciences, Moscow, Russia', 'Faculty of Physics, Lomonosov Moscow State University, Moscow, Russia'], 'affiliations': [{'raw_affiliation_string': 'A.M. Obukhov Institute of Atmospheric Physics, Russian Academy of Sciences, Moscow, Russia', 'institution_ids': ['https://openalex.org/I4210150607']}, {'raw_affiliation_string': 'Faculty of Physics, Lomonosov Moscow State University, Moscow, Russia', 'institution_ids': ['https://openalex.org/I19880235']}]}, {'author_position': 'middle', 'author': {'id': 'https://openalex.org/A5028193808', 'display_name': 'Tomohiro Hajima', 'orcid': 'https://orcid.org/0000-0002-4828-5100'}, 'institutions': [{'id': 'https://openalex.org/I1315852903', 'display_name': 'Japan Agency for Marine-Earth Science and Technology', 'ror': 'https://ror.org/059qg2m13', 'country_code': 'JP', 'type': 'facility', 'lineage': ['https://openalex.org/I1315852903']}], 'countries': ['JP'], 'is_corresponding': False, 'raw_author_name': 'Tomohiro Hajima', 'raw_affiliation_strings': ['Research Center for Environmental Modeling and Application, Japan Agency for Marine-Earth Science and Technology, Yokohama, Japan'], 'affiliations': [{'raw_affiliation_string': 'Research Center for Environmental Modeling and Application, Japan Agency for Marine-Earth Science and Technology, Yokohama, Japan', 'institution_ids': ['https://openalex.org/I1315852903']}]}, {'author_position': 'middle', 'author': {'id': 'https://openalex.org/A5000461255', 'display_name': 'Philip B. Holden', 'orcid': 'https://orcid.org/0000-0002-2369-0062'}, 'institutions': [{'id': 'https://openalex.org/I204136569', 'display_name': 'The Open University', 'ror': 'https://ror.org/05mzfcs16', 'country_code': 'GB', 'type': 'education', 'lineage': ['https://openalex.org/I204136569']}], 'countries': ['GB'], 'is_corresponding': True, 'raw_author_name': 'Philip B. Holden', 'raw_affiliation_strings': ['School of Environment, Earth and Ecosystem Sciences, The Open University, Walton Hall, Milton Keynes, MK7 6AA, UK'], 'affiliations': [{'raw_affiliation_string': 'School of Environment, Earth and Ecosystem Sciences, The Open University, Walton Hall, Milton Keynes, MK7 6AA, UK', 'institution_ids': ['https://openalex.org/I204136569']}]}, {'author_position': 'middle', 'author': {'id': 'https://openalex.org/A5060949034', 'display_name': 'Aurich Jeltschâ€ThÃ¶mmes', 'orcid': 'https://orcid.org/0000-0002-2050-1975'}, 'institutions': [{'id': 'https://openalex.org/I118564535', 'display_name': 'University of Bern', 'ror': 'https://ror.org/02k7v4d05', 'country_code': 'CH', 'type': 'education', 'lineage': ['https://openalex.org/I118564535']}, {'id': 'https://openalex.org/I1299204452', 'display_name': 'Oeschger Centre for Climate Change Research', 'ror': 'https://ror.org/0329s8h62', 'country_code': 'CH', 'type': 'facility', 'lineage': ['https://openalex.org/I1299204452']}], 'countries': ['CH'], 'is_corresponding': False, 'raw_author_name': 'Aurich Jeltsch-ThÃ¶mmes', 'raw_affiliation_strings': ['Oeschger Centre for Climate Change Research, University of Bern, Bern, Switzerland', 'Climate and Environmental Physics, Physics Institute, University of Bern, Bern, Switzerland'], 'affiliations': [{'raw_affiliation_string': 'Oeschger Centre for Climate Change Research, University of Bern, Bern, Switzerland', 'institution_ids': ['https://openalex.org/I1299204452', 'https://openalex.org/I118564535']}, {'raw_affiliation_string': 'Climate and Environmental Physics, Physics Institute, University of Bern, Bern, Switzerland', 'institution_ids': ['https://openalex.org/I118564535']}]}, {'author_position': 'middle', 'author': {'id': 'https://openalex.org/A5076394811', 'display_name': 'Charles D. Koven', 'orcid': 'https://orcid.org/0000-0002-3367-0065'}, 'institutions': [{'id': 'https://openalex.org/I148283060', 'display_name': 'Lawrence Berkeley National Laboratory', 'ror': 'https://ror.org/02jbv0t02', 'country_code': 'US', 'type': 'facility', 'lineage': ['https://openalex.org/I1330989302', 'https://openalex.org/I148283060', 'https://openalex.org/I39565521']}], 'countries': ['US'], 'is_corresponding': True, 'raw_author_name': 'Charles Koven', 'raw_affiliation_strings': ['Climate and Ecosystem Sciences Division, Lawrence Berkeley National Lab, Berkeley, CA, USA'], 'affiliations': [{'raw_affiliation_string': 'Climate and Ecosystem Sciences Division, Lawrence Berkeley National Lab, Berkeley, CA, USA', 'institution_ids': ['https://openalex.org/I148283060']}]}, {'author_position': 'middle', 'author': {'id': 'https://openalex.org/A5079879047', 'display_name': 'Nadine Mengis', 'orcid': 'https://orcid.org/0000-0003-0312-7069'}, 'institutions': [{'id': 'https://openalex.org/I34403800', 'display_name': 'GEOMAR Helmholtz Centre for Ocean Research Kiel', 'ror': 'https://ror.org/02h2x0161', 'country_code': 'DE', 'type': 'facility', 'lineage': ['https://openalex.org/I1305996414', 'https://openalex.org/I34403800']}], 'countries': ['DE'], 'is_corresponding': True, 'raw_author_name': 'Nadine Mengis', 'raw_affiliation_strings': ['Biogeochemical Modelling Department, GEOMAR Ã¢\x80\x93 Helmholtz Centre for Ocean Research, Kiel, Germany', 'Biogeochemical Modelling Department, GEOMAR â€“ Helmholtz Centre for Ocean Research, Kiel, Germany'], 'affiliations': [{'raw_affiliation_string': 'Biogeochemical Modelling Department, GEOMAR Ã¢\x80\x93 Helmholtz Centre for Ocean Research, Kiel, Germany', 'institution_ids': ['https://openalex.org/I34403800']}, {'raw_affiliation_string': 'Biogeochemical Modelling Department, GEOMAR â€“ Helmholtz Centre for Ocean Research, Kiel, Germany', 'institution_ids': ['https://openalex.org/I34403800']}]}, {'author_position': 'middle', 'author': {'id': 'https://openalex.org/A5049584223', 'display_name': 'Laurie Menviel', 'orcid': 'https://orcid.org/0000-0002-5068-1591'}, 'institutions': [{'id': 'https://openalex.org/I31746571', 'display_name': 'UNSW Sydney', 'ror': 'https://ror.org/03r8z3t63', 'country_code': 'AU', 'type': 'education', 'lineage': ['https://openalex.org/I31746571']}], 'countries': ['AU'], 'is_corresponding': True, 'raw_author_name': 'Laurie Menviel', 'raw_affiliation_strings': ['Climate Change Research Centre, PANGEA, The University of New South Wales, Sydney, NSW, Australia'], 'affiliations': [{'raw_affiliation_string': 'Climate Change Research Centre, PANGEA, The University of New South Wales, Sydney, NSW, Australia', 'institution_ids': ['https://openalex.org/I31746571']}]}, {'author_position': 'middle', 'author': {'id': 'https://openalex.org/A5007474312', 'display_name': 'Martine Michou', 'orcid': 'https://orcid.org/0000-0002-1751-3326'}, 'institutions': [{'id': 'https://openalex.org/I4210113730', 'display_name': 'MÃ©tÃ©o-France', 'ror': 'https://ror.org/0233st365', 'country_code': 'FR', 'type': 'other', 'lineage': ['https://openalex.org/I4210113730']}, {'id': 'https://openalex.org/I17866349', 'display_name': 'UniversitÃ© de Toulouse', 'ror': 'https://ror.org/004raaa70', 'country_code': 'FR', 'type': 'education', 'lineage': ['https://openalex.org/I17866349']}, {'id': 'https://openalex.org/I1294671590', 'display_name': 'Centre National de la Recherche Scientifique', 'ror': 'https://ror.org/02feahw73', 'country_code': 'FR', 'type': 'funder', 'lineage': ['https://openalex.org/I1294671590']}], 'countries': ['FR'], 'is_corresponding': False, 'raw_author_name': 'Martine Michou', 'raw_affiliation_strings': ['CNRM, UniversitÃƒÂ© de Toulouse, MÃƒÂ©tÃƒÂ©o-France, CNRS, Toulouse, France', 'CNRM, UniversitÃ© de Toulouse, MÃ©tÃ©o-France, CNRS, Toulouse, France'], 'affiliations': [{'raw_affiliation_string': 'CNRM, UniversitÃƒÂ© de Toulouse, MÃƒÂ©tÃƒÂ©o-France, CNRS, Toulouse, France', 'institution_ids': ['https://openalex.org/I17866349', 'https://openalex.org/I1294671590']}, {'raw_affiliation_string': 'CNRM, UniversitÃ© de Toulouse, MÃ©tÃ©o-France, CNRS, Toulouse, France', 'institution_ids': ['https://openalex.org/I4210113730', 'https://openalex.org/I17866349', 'https://openalex.org/I1294671590']}]}, {'author_position': 'middle', 'author': {'id': 'https://openalex.org/A5034108360', 'display_name': 'Ð˜. Ð˜. ÐœÐ¾Ñ…Ð¾Ð²', 'orcid': 'https://orcid.org/0000-0003-0033-8581'}, 'institutions': [{'id': 'https://openalex.org/I4210150607', 'display_name': 'A.M. Obukhov Institute of Atmospheric Physics', 'ror': 'https://ror.org/03snt1857', 'country_code': 'RU', 'type': 'facility', 'lineage': ['https://openalex.org/I1313323035', 'https://openalex.org/I4210150607', 'https://openalex.org/I4210163714']}, {'id': 'https://openalex.org/I19880235', 'display_name': 'Lomonosov Moscow State University', 'ror': 'https://ror.org/010pmpe69', 'country_code': 'RU', 'type': 'education', 'lineage': ['https://openalex.org/I19880235']}], 'countries': ['RU'], 'is_corresponding': False, 'raw_author_name': 'Igor I. Mokhov', 'raw_affiliation_strings': ['A.M. Obukhov Institute of Atmospheric Physics, Russian Academy of Sciences, Moscow, Russia', 'Faculty of Physics, Lomonosov Moscow State University, Moscow, Russia'], 'affiliations': [{'raw_affiliation_string': 'A.M. Obukhov Institute of Atmospheric Physics, Russian Academy of Sciences, Moscow, Russia', 'institution_ids': ['https://openalex.org/I4210150607']}, {'raw_affiliation_string': 'Faculty of Physics, Lomonosov Moscow State University, Moscow, Russia', 'institution_ids': ['https://openalex.org/I19880235']}]}, {'author_position': 'middle', 'author': {'id': 'https://openalex.org/A5019071655', 'display_name': 'Akira Oka', 'orcid': 'https://orcid.org/0000-0002-8260-2907'}, 'institutions': [{'id': 'https://openalex.org/I74801974', 'display_name': 'The University of Tokyo', 'ror': 'https://ror.org/057zh3y96', 'country_code': 'JP', 'type': 'education', 'lineage': ['https://openalex.org/I74801974']}], 'countries': ['JP'], 'is_corresponding': False, 'raw_author_name': 'Akira Oka', 'raw_affiliation_strings': ['Atmosphere and Ocean Research Institute, The University of Tokyo, Tokyo, Japan'], 'affiliations': [{'raw_affiliation_string': 'Atmosphere and Ocean Research Institute, The University of Tokyo, Tokyo, Japan', 'institution_ids': ['https://openalex.org/I74801974']}]}, {'author_position': 'middle', 'author': {'id': 'https://openalex.org/A5026788850', 'display_name': 'JÃ¶rg Schwinger', 'orcid': 'https://orcid.org/0000-0002-7525-6882'}, 'institutions': [{'id': 'https://openalex.org/I4210107808', 'display_name': 'NORCE Norwegian Research Centre', 'ror': 'https://ror.org/02gagpf75', 'country_code': 'NO', 'type': 'facility', 'lineage': ['https://openalex.org/I4210107808']}, {'id': 'https://openalex.org/I2799966484', 'display_name': 'Bjerknes Centre for Climate Research', 'ror': 'https://ror.org/011n96f14', 'country_code': 'NO', 'type': 'facility', 'lineage': ['https://openalex.org/I2799966484']}], 'countries': ['NO'], 'is_corresponding': True, 'raw_author_name': 'JÃ¶rg Schwinger', 'raw_affiliation_strings': ['NORCE Norwegian Research Centre, Bjerknes Centre for Climate Research, Bergen, Norway'], 'affiliations': [{'raw_affiliation_string': 'NORCE Norwegian Research Centre, Bjerknes Centre for Climate Research, Bergen, Norway', 'institution_ids': ['https://openalex.org/I2799966484', 'https://openalex.org/I4210107808']}]}, {'author_position': 'middle', 'author': {'id': 'https://openalex.org/A5019912667', 'display_name': 'Roland SÃ©fÃ©rian', 'orcid': 'https://orcid.org/0000-0002-2571-2114'}, 'institutions': [{'id': 'https://openalex.org/I4210113730', 'display_name': 'MÃ©tÃ©o-France', 'ror': 'https://ror.org/0233st365', 'country_code': 'FR', 'type': 'other', 'lineage': ['https://openalex.org/I4210113730']}, {'id': 'https://openalex.org/I1294671590', 'display_name': 'Centre National de la Recherche Scientifique', 'ror': 'https://ror.org/02feahw73', 'country_code': 'FR', 'type': 'funder', 'lineage': ['https://openalex.org/I1294671590']}, {'id': 'https://openalex.org/I17866349', 'display_name': 'UniversitÃ© de Toulouse', 'ror': 'https://ror.org/004raaa70', 'country_code': 'FR', 'type': 'education', 'lineage': ['https://openalex.org/I17866349']}], 'countries': ['FR'], 'is_corresponding': False, 'raw_author_name': 'Roland SÃ©fÃ©rian', 'raw_affiliation_strings': ['CNRM, UniversitÃ© de Toulouse, MÃ©tÃ©o-France, CNRS, Toulouse, France'], 'affiliations': [{'raw_affiliation_string': 'CNRM, UniversitÃ© de Toulouse, MÃ©tÃ©o-France, CNRS, Toulouse, France', 'institution_ids': ['https://openalex.org/I4210113730', 'https://openalex.org/I17866349', 'https://openalex.org/I1294671590']}]}, {'author_position': 'middle', 'author': {'id': 'https://openalex.org/A5006935727', 'display_name': 'Gary Shaffer', 'orcid': 'https://orcid.org/0000-0002-2494-3471'}, 'institutions': [{'id': 'https://openalex.org/I124055696', 'display_name': 'University of Copenhagen', 'ror': 'https://ror.org/035b05819', 'country_code': 'DK', 'type': 'education', 'lineage': ['https://openalex.org/I124055696']}, {'id': 'https://openalex.org/I63471342', 'display_name': 'Universidad de Magallanes', 'ror': 'https://ror.org/049784n50', 'country_code': 'CL', 'type': 'education', 'lineage': ['https://openalex.org/I63471342']}], 'countries': ['CL', 'DK'], 'is_corresponding': False, 'raw_author_name': 'Gary Shaffer', 'raw_affiliation_strings': ['Niels Bohr Institute, University of Copenhagen, Copenhagen, Denmark', 'Research Center GAIA Antarctica, University of Magallanes, Punta Arenas, Chile'], 'affiliations': [{'raw_affiliation_string': 'Niels Bohr Institute, University of Copenhagen, Copenhagen, Denmark', 'institution_ids': ['https://openalex.org/I124055696']}, {'raw_affiliation_string': 'Research Center GAIA Antarctica, University of Magallanes, Punta Arenas, Chile', 'institution_ids': ['https://openalex.org/I63471342']}]}, {'author_position': 'middle', 'author': {'id': 'https://openalex.org/A5026244585', 'display_name': 'Andrei Sokolov', 'orcid': 'https://orcid.org/0000-0003-2406-3228'}, 'institutions': [{'id': 'https://openalex.org/I63966007', 'display_name': 'Massachusetts Institute of Technology', 'ror': 'https://ror.org/042nb2s44', 'country_code': 'US', 'type': 'education', 'lineage': ['https://openalex.org/I63966007']}], 'countries': ['US'], 'is_corresponding': False, 'raw_author_name': 'Andrei Sokolov', 'raw_affiliation_strings': ['Center for Global Change Science, Massachusetts Institute of Technology, Cambridge, USA'], 'affiliations': [{'raw_affiliation_string': 'Center for Global Change Science, Massachusetts Institute of Technology, Cambridge, USA', 'institution_ids': ['https://openalex.org/I63966007']}]}, {'author_position': 'middle', 'author': {'id': 'https://openalex.org/A5017088303', 'display_name': 'Kaoru Tachiiri', 'orcid': None}, 'institutions': [{'id': 'https://openalex.org/I1315852903', 'display_name': 'Japan Agency for Marine-Earth Science and Technology', 'ror': 'https://ror.org/059qg2m13', 'country_code': 'JP', 'type': 'facility', 'lineage': ['https://openalex.org/I1315852903']}], 'countries': ['JP'], 'is_corresponding': False, 'raw_author_name': 'Kaoru Tachiiri', 'raw_affiliation_strings': ['Research Center for Environmental Modeling and Application, Japan Agency for Marine-Earth Science and Technology, Yokohama, Japan'], 'affiliations': [{'raw_affiliation_string': 'Research Center for Environmental Modeling and Application, Japan Agency for Marine-Earth Science and Technology, Yokohama, Japan', 'institution_ids': ['https://openalex.org/I1315852903']}]}, {'author_position': 'middle', 'author': {'id': 'https://openalex.org/A5063959948', 'display_name': 'Jerry Tjiputra', 'orcid': 'https://orcid.org/0000-0002-4600-2453'}, 'institutions': [{'id': 'https://openalex.org/I4210107808', 'display_name': 'NORCE Norwegian Research Centre', 'ror': 'https://ror.org/02gagpf75', 'country_code': 'NO', 'type': 'facility', 'lineage': ['https://openalex.org/I4210107808']}, {'id': 'https://openalex.org/I2799966484', 'display_name': 'Bjerknes Centre for Climate Research', 'ror': 'https://ror.org/011n96f14', 'country_code': 'NO', 'type': 'facility', 'lineage': ['https://openalex.org/I2799966484']}], 'countries': ['NO'], 'is_corresponding': False, 'raw_author_name': 'Jerry Tjiputra', 'raw_affiliation_strings': ['NORCE Norwegian Research Centre, Bjerknes Centre for Climate Research, Bergen, Norway'], 'affiliations': [{'raw_affiliation_string': 'NORCE Norwegian Research Centre, Bjerknes Centre for Climate Research, Bergen, Norway', 'institution_ids': ['https://openalex.org/I2799966484', 'https://openalex.org/I4210107808']}]}, {'author_position': 'middle', 'author': {'id': 'https://openalex.org/A5035579254', 'display_name': 'A. Wiltshire', 'orcid': 'https://orcid.org/0000-0001-7307-173X'}, 'institutions': [{'id': 'https://openalex.org/I1293035123', 'display_name': 'Met Office', 'ror': 'https://ror.org/01ch2yn61', 'country_code': 'GB', 'type': 'funder', 'lineage': ['https://openalex.org/I1293035123']}], 'countries': ['GB'], 'is_corresponding': False, 'raw_author_name': 'Andrew Wiltshire', 'raw_affiliation_strings': ['Met Office Hadley Centre, Exeter, EX1 3PB, UK'], 'affiliations': [{'raw_affiliation_string': 'Met Office Hadley Centre, Exeter, EX1 3PB, UK', 'institution_ids': ['https://openalex.org/I1293035123']}]}, {'author_position': 'last', 'author': {'id': 'https://openalex.org/A5060070992', 'display_name': 'Tilo Ziehn', 'orcid': 'https://orcid.org/0000-0001-9873-9775'}, 'institutions': [{'id': 'https://openalex.org/I1281210470', 'display_name': 'CSIRO Oceans and Atmosphere', 'ror': 'https://ror.org/026nh4520', 'country_code': 'AU', 'type': 'facility', 'lineage': ['https://openalex.org/I1281210470', 'https://openalex.org/I1292875679', 'https://openalex.org/I2801453606', 'https://openalex.org/I4387156119']}, {'id': 'https://openalex.org/I1292875679', 'display_name': 'Commonwealth Scientific and Industrial Research Organisation', 'ror': 'https://ror.org/03qn8fb07', 'country_code': 'AU', 'type': 'funder', 'lineage': ['https://openalex.org/I1292875679', 'https://openalex.org/I2801453606', 'https://openalex.org/I4387156119']}], 'countries': ['AU'], 'is_corresponding': True, 'raw_author_name': 'Tilo Ziehn', 'raw_affiliation_strings': ['Commonwealth Scientific and Industrial Research Organisation, Oceans and Atmosphere, Aspendale, VIC, Australia'], 'affiliations': [{'raw_affiliation_string': 'Commonwealth Scientific and Industrial Research Organisation, Oceans and Atmosphere, Aspendale, VIC, Australia', 'institution_ids': ['https://openalex.org/I1281210470', 'https://openalex.org/I1292875679']}]}] | J8: 13 | K8: 29 | L8: 13.7152 | M8: FALSE | N8: 234 | O8: {'volume': '17', 'issue': '11', 'first_page': '2987', 'last_page': '3016'} | P8: {'id': 'https://openalex.org/T11588', 'display_name': 'Atmospheric and Environmental Gas Dynamics', 'score': 0.9991999864578247, 'subfield': {'id': 'https://openalex.org/subfields/2306', 'display_name': 'Global and Planetary Change'}, 'field': {'id': 'https://openalex.org/fields/23', 'display_name': 'Environmental Science'}, 'domain': {'id': 'https://openalex.org/domains/3', 'display_name': 'Physical Sciences'}} | Q8: [{'id': 'https://openalex.org/T11588', 'display_name': 'Atmospheric and Environmental Gas Dynamics', 'score': 0.9991999864578247, 'subfield': {'id': 'https://openalex.org/subfields/2306', 'display_name': 'Global and Planetary Change'}, 'field': {'id': 'https://openalex.org/fields/23', 'display_name': 'Environmental Science'}, 'domain': {'id': 'https://openalex.org/domains/3', 'display_name': 'Physical Sciences'}}, {'id': 'https://openalex.org/T10075', 'display_name': 'Atmospheric chemistry and aerosols', 'score': 0.9991000294685364, 'subfield': {'id': 'https://openalex.org/subfields/1902', 'display_name': 'Atmospheric Science'}, 'field': {'id': 'https://openalex.org/fields/19', 'display_name': 'Earth and Planetary Sciences'}, 'domain': {'id': 'https://openalex.org/domains/3', 'display_name': 'Physical Sciences'}}, {'id': 'https://openalex.org/T10967', 'display_name': 'Carbon Dioxide Capture Technologies', 'score': 0.9948999881744385, 'subfield': {'id': 'https://openalex.org/subfields/2210', 'display_name': 'Mechanical Engineering'}, 'field': {'id': 'https://openalex.org/fields/22', 'display_name': 'Engineering'}, 'domain': {'id': 'https://openalex.org/domains/3', 'display_name': 'Physical Sciences'}}] | R8: [{'id': 'https://openalex.org/keywords/zero', 'display_name': 'Zero (linguistics)', 'score': 0.4833259582519531}, {'id': 'https://openalex.org/keywords/chemistry', 'display_name': 'Chemistry', 'score': 0.4647476077079773}, {'id': 'https://openalex.org/keywords/ampere', 'display_name': 'Ampere', 'score': 0.4621843099594116}, {'id': 'https://openalex.org/keywords/zero-emission', 'display_name': 'Zero emission', 'score': 0.4253907799720764}, {'id': 'https://openalex.org/keywords/endocrinology', 'display_name': 'Endocrinology', 'score': 0.36692488193511963}, {'id': 'https://openalex.org/keywords/environmental-science', 'display_name': 'Environmental science', 'score': 0.36250007152557373}, {'id': 'https://openalex.org/keywords/internal-medicine', 'display_name': 'Internal medicine', 'score': 0.3370639681816101}, {'id': 'https://openalex.org/keywords/thermodynamics', 'display_name': 'Thermodynamics', 'score': 0.2718653678894043}, {'id': 'https://openalex.org/keywords/physics', 'display_name': 'Physics', 'score': 0.23128646612167358}, {'id': 'https://openalex.org/keywords/medicine', 'display_name': 'Medicine', 'score': 0.1634330153465271}, {'id': 'https://openalex.org/keywords/ecology', 'display_name': 'Ecology', 'score': 0.12881529331207275}, {'id': 'https://openalex.org/keywords/biology', 'display_name': 'Biology', 'score': 0.12666010856628418}] | S8: [{'id': 'https://openalex.org/C2780813799', 'wikidata': 'https://www.wikidata.org/wiki/Q3274237', 'display_name': 'Zero (linguistics)', 'level': 2, 'score': 0.4833259582519531}, {'id': 'https://openalex.org/C185592680', 'wikidata': 'https://www.wikidata.org/wiki/Q2329', 'display_name': 'Chemistry', 'level': 0, 'score': 0.4647476077079773}, {'id': 'https://openalex.org/C4941483', 'wikidata': 'https://www.wikidata.org/wiki/Q25272', 'display_name': 'Ampere', 'level': 3, 'score': 0.4621843099594116}, {'id': 'https://openalex.org/C118334743', 'wikidata': 'https://www.wikidata.org/wiki/Q846292', 'display_name': 'Zero emission', 'level': 2, 'score': 0.4253907799720764}, {'id': 'https://openalex.org/C134018914', 'wikidata': 'https://www.wikidata.org/wiki/Q162606', 'display_name': 'Endocrinology', 'level': 1, 'score': 0.36692488193511963}, {'id': 'https://openalex.org/C39432304', 'wikidata': 'https://www.wikidata.org/wiki/Q188847', 'display_name': 'Environmental science', 'level': 0, 'score': 0.36250007152557373}, {'id': 'https://openalex.org/C126322002', 'wikidata': 'https://www.wikidata.org/wiki/Q11180', 'display_name': 'Internal medicine', 'level': 1, 'score': 0.3370639681816101}, {'id': 'https://openalex.org/C97355855', 'wikidata': 'https://www.wikidata.org/wiki/Q11473', 'display_name': 'Thermodynamics', 'level': 1, 'score': 0.2718653678894043}, {'id': 'https://openalex.org/C121332964', 'wikidata': 'https://www.wikidata.org/wiki/Q413', 'display_name': 'Physics', 'level': 0, 'score': 0.23128646612167358}, {'id': 'https://openalex.org/C71924100', 'wikidata': 'https://www.wikidata.org/wiki/Q11190', 'display_name': 'Medicine', 'level': 0, 'score': 0.1634330153465271}, {'id': 'https://openalex.org/C18903297', 'wikidata': 'https://www.wikidata.org/wiki/Q7150', 'display_name': 'Ecology', 'level': 1, 'score': 0.12881529331207275}, {'id': 'https://openalex.org/C86803240', 'wikidata': 'https://www.wikidata.org/wiki/Q420', 'display_name': 'Biology', 'level': 0, 'score': 0.12666010856628418}, {'id': 'https://openalex.org/C148043351', 'wikidata': 'https://www.wikidata.org/wiki/Q4456944', 'display_name': 'Current (fluid)', 'level': 2, 'score': 0.0}, {'id': 'https://openalex.org/C41895202', 'wikidata': 'https://www.wikidata.org/wiki/Q8162', 'display_name': 'Linguistics', 'level': 1, 'score': 0.0}, {'id': 'https://openalex.org/C138885662', 'wikidata': 'https://www.wikidata.org/wiki/Q5891', 'display_name': 'Philosophy', 'level': 0, 'score': 0.0}] | T8: [{'id': 'https://metadata.un.org/sdg/14', 'score': 0.6499999761581421, 'display_name': 'Life below water'}] | U8: 115
A9: https://openalex.org/W4366365204 | B9: https://doi.org/10.1038/s41586-023-05867-2 | C9: Quantum critical dynamics in a 5,000-qubit programmable spin glass | D9: 2023 | E9: 45035 | F9: en | G9: article | H9: {'is_oa': False, 'oa_status': 'closed', 'oa_url': None, 'any_repository_has_fulltext': False} | I9: [{'author_position': 'first', 'author': {'id': 'https://openalex.org/A5052420215', 'display_name': 'Andrew D. King', 'orcid': 'https://orcid.org/0000-0001-8362-8941'}, 'institutions': [{'id': 'https://openalex.org/I1309087048', 'display_name': 'D-Wave Systems (Canada)', 'ror': 'https://ror.org/01mmn7c12', 'country_code': 'CA', 'type': 'company', 'lineage': ['https://openalex.org/I1309087048']}], 'countries': ['CA'], 'is_corresponding': True, 'raw_author_name': 'Andrew D. King', 'raw_affiliation_strings': ['D-Wave Quantum Inc., Burnaby, British Columbia, Canada. aking@dwavesys.com', 'D-Wave Quantum Inc., Burnaby, British Columbia, Canada'], 'affiliations': [{'raw_affiliation_string': 'D-Wave Quantum Inc., Burnaby, British Columbia, Canada. aking@dwavesys.com', 'institution_ids': []}, {'raw_affiliation_string': 'D-Wave Quantum Inc., Burnaby, British Columbia, Canada', 'institution_ids': ['https://openalex.org/I1309087048']}]}, {'author_position': 'middle', 'author': {'id': 'https://openalex.org/A5034139385', 'display_name': 'Jack Raymond', 'orcid': 'https://orcid.org/0000-0002-1808-6039'}, 'institutions': [{'id': 'https://openalex.org/I1309087048', 'display_name': 'D-Wave Systems (Canada)', 'ror': 'https://ror.org/01mmn7c12', 'country_code': 'CA', 'type': 'company', 'lineage': ['https://openalex.org/I1309087048']}], 'countries': ['CA'], 'is_corresponding': False, 'raw_author_name': 'Jack Raymond', 'raw_affiliation_strings': ['D-Wave Quantum Inc., Burnaby, British Columbia, Canada'], 'affiliations': [{'raw_affiliation_string': 'D-Wave Quantum Inc., Burnaby, British Columbia, Canada', 'institution_ids': ['https://openalex.org/I1309087048']}]}, {'author_position': 'middle', 'author': {'id': 'https://openalex.org/A5089555006', 'display_name': 'T. Lanting', 'orcid': 'https://orcid.org/0000-0003-2829-0196'}, 'institutions': [{'id': 'https://openalex.org/I1309087048', 'display_name': 'D-Wave Systems (Canada)', 'ror': 'https://ror.org/01mmn7c12', 'country_code': 'CA', 'type': 'company', 'lineage': ['https://openalex.org/I1309087048']}], 'countries': ['CA'], 'is_corresponding': False, 'raw_author_name': 'Trevor Lanting', 'raw_affiliation_strings': ['D-Wave Quantum Inc., Burnaby, British Columbia, Canada'], 'affiliations': [{'raw_affiliation_string': 'D-Wave Quantum Inc., Burnaby, British Columbia, Canada', 'institution_ids': ['https://openalex.org/I1309087048']}]}, {'author_position': 'middle', 'author': {'id': 'https://openalex.org/A5102862575', 'display_name': 'R. Harris', 'orcid': 'https://orcid.org/0000-0002-6394-926X'}, 'institutions': [{'id': 'https://openalex.org/I1309087048', 'display_name': 'D-Wave Systems (Canada)', 'ror': 'https://ror.org/01mmn7c12', 'country_code': 'CA', 'type': 'company', 'lineage': ['https://openalex.org/I1309087048']}], 'countries': ['CA'], 'is_corresponding': False, 'raw_author_name': 'Richard Harris', 'raw_affiliation_strings': ['D-Wave Quantum Inc., Burnaby, British Columbia, Canada'], 'affiliations': [{'raw_affiliation_string': 'D-Wave Quantum Inc., Burnaby, British Columbia, Canada', 'institution_ids': ['https://openalex.org/I1309087048']}]}, {'author_position': 'middle', 'author': {'id': 'https://openalex.org/A5091636310', 'display_name': 'Alex Zucca', 'orcid': 'https://orcid.org/0000-0002-1728-106X'}, 'institutions': [{'id': 'https://openalex.org/I1309087048', 'display_name': 'D-Wave Systems (Canada)', 'ror': 'https://ror.org/01mmn7c12', 'country_code': 'CA', 'type': 'company', 'lineage': ['https://openalex.org/I1309087048']}], 'countries': ['CA'], 'is_corresponding': False, 'raw_author_name': 'Alex Zucca', 'raw_affiliation_strings': ['D-Wave Quantum Inc., Burnaby, British Columbia, Canada'], 'affiliations': [{'raw_affiliation_string': 'D-Wave Quantum Inc., Burnaby, British Columbia, Canada', 'institution_ids': ['https://openalex.org/I1309087048']}]}, {'author_position': 'middle', 'author': {'id': 'https://openalex.org/A5073678218', 'display_name': 'Fabio Altomare', 'orcid': 'https://orcid.org/0000-0001-8380-3623'}, 'institutions': [{'id': 'https://openalex.org/I1309087048', 'display_name': 'D-Wave Systems (Canada)', 'ror': 'https://ror.org/01mmn7c12', 'country_code': 'CA', 'type': 'company', 'lineage': ['https://openalex.org/I1309087048']}], 'countries': ['CA'], 'is_corresponding': False, 'raw_author_name': 'Fabio Altomare', 'raw_affiliation_strings': ['D-Wave Quantum Inc., Burnaby, British Columbia, Canada'], 'affiliations': [{'raw_affiliation_string': 'D-Wave Quantum Inc., Burnaby, British Columbia, Canada', 'institution_ids': ['https://openalex.org/I1309087048']}]}, {'author_position': 'middle', 'author': {'id': 'https://openalex.org/A5072333621', 'display_name': 'A. J. Berkley', 'orcid': 'https://orcid.org/0000-0002-4235-8452'}, 'institutions': [{'id': 'https://openalex.org/I1309087048', 'display_name': 'D-Wave Systems (Canada)', 'ror': 'https://ror.org/01mmn7c12', 'country_code': 'CA', 'type': 'company', 'lineage': ['https://openalex.org/I1309087048']}], 'countries': ['CA'], 'is_corresponding': False, 'raw_author_name': 'Andrew J. Berkley', 'raw_affiliation_strings': ['D-Wave Quantum Inc., Burnaby, British Columbia, Canada'], 'affiliations': [{'raw_affiliation_string': 'D-Wave Quantum Inc., Burnaby, British Columbia, Canada', 'institution_ids': ['https://openalex.org/I1309087048']}]}, {'author_position': 'middle', 'author': {'id': 'https://openalex.org/A5046753100', 'display_name': 'Kelly Boothby', 'orcid': 'https://orcid.org/0000-0001-6870-0466'}, 'institutions': [{'id': 'https://openalex.org/I1309087048', 'display_name': 'D-Wave Systems (Canada)', 'ror': 'https://ror.org/01mmn7c12', 'country_code': 'CA', 'type': 'company', 'lineage': ['https://openalex.org/I1309087048']}], 'countries': ['CA'], 'is_corresponding': False, 'raw_author_name': 'Kelly Boothby', 'raw_affiliation_strings': ['D-Wave Quantum Inc., Burnaby, British Columbia, Canada'], 'affiliations': [{'raw_affiliation_string': 'D-Wave Quantum Inc., Burnaby, British Columbia, Canada', 'institution_ids': ['https://openalex.org/I1309087048']}]}, {'author_position': 'middle', 'author': {'id': 'https://openalex.org/A5056214096', 'display_name': 'Sara Ejtemaee', 'orcid': None}, 'institutions': [{'id': 'https://openalex.org/I1309087048', 'display_name': 'D-Wave Systems (Canada)', 'ror': 'https://ror.org/01mmn7c12', 'country_code': 'CA', 'type': 'company', 'lineage': ['https://openalex.org/I1309087048']}], 'countries': ['CA'], 'is_corresponding': False, 'raw_author_name': 'Sara Ejtemaee', 'raw_affiliation_strings': ['D-Wave Quantum Inc., Burnaby, British Columbia, Canada'], 'affiliations': [{'raw_affiliation_string': 'D-Wave Quantum Inc., Burnaby, British Columbia, Canada', 'institution_ids': ['https://openalex.org/I1309087048']}]}, {'author_position': 'middle', 'author': {'id': 'https://openalex.org/A5078609854', 'display_name': 'Colin Enderud', 'orcid': 'https://orcid.org/0000-0001-5431-6439'}, 'institutions': [{'id': 'https://openalex.org/I1309087048', 'display_name': 'D-Wave Systems (Canada)', 'ror': 'https://ror.org/01mmn7c12', 'country_code': 'CA', 'type': 'company', 'lineage': ['https://openalex.org/I1309087048']}], 'countries': ['CA'], 'is_corresponding': False, 'raw_author_name': 'Colin Enderud', 'raw_affiliation_strings': ['D-Wave Quantum Inc., Burnaby, British Columbia, Canada'], 'affiliations': [{'raw_affiliation_string': 'D-Wave Quantum Inc., Burnaby, British Columbia, Canada', 'institution_ids': ['https://openalex.org/I1309087048']}]}, {'author_position': 'middle', 'author': {'id': 'https://openalex.org/A5111912151', 'display_name': 'Emile Hoskinson', 'orcid': None}, 'institutions': [{'id': 'https://openalex.org/I1309087048', 'display_name': 'D-Wave Systems (Canada)', 'ror': 'https://ror.org/01mmn7c12', 'country_code': 'CA', 'type': 'company', 'lineage': ['https://openalex.org/I1309087048']}], 'countries': ['CA'], 'is_corresponding': False, 'raw_author_name': 'Emile Hoskinson', 'raw_affiliation_strings': ['D-Wave Quantum Inc., Burnaby, British Columbia, Canada'], 'affiliations': [{'raw_affiliation_string': 'D-Wave Quantum Inc., Burnaby, British Columbia, Canada', 'institution_ids': ['https://openalex.org/I1309087048']}]}, {'author_position': 'middle', 'author': {'id': 'https://openalex.org/A5091685844', 'display_name': 'Shuiyuan Huang', 'orcid': 'https://orcid.org/0000-0001-9799-1872'}, 'institutions': [{'id': 'https://openalex.org/I1309087048', 'display_name': 'D-Wave Systems (Canada)', 'ror': 'https://ror.org/01mmn7c12', 'country_code': 'CA', 'type': 'company', 'lineage': ['https://openalex.org/I1309087048']}], 'countries': ['CA'], 'is_corresponding': False, 'raw_author_name': 'Shuiyuan Huang', 'raw_affiliation_strings': ['D-Wave Quantum Inc., Burnaby, British Columbia, Canada'], 'affiliations': [{'raw_affiliation_string': 'D-Wave Quantum Inc., Burnaby, British Columbia, Canada', 'institution_ids': ['https://openalex.org/I1309087048']}]}, {'author_position': 'middle', 'author': {'id': 'https://openalex.org/A5002475393', 'display_name': 'E. Ladizinsky', 'orcid': None}, 'institutions': [{'id': 'https://openalex.org/I1309087048', 'display_name': 'D-Wave Systems (Canada)', 'ror': 'https://ror.org/01mmn7c12', 'country_code': 'CA', 'type': 'company', 'lineage': ['https://openalex.org/I1309087048']}], 'countries': ['CA'], 'is_corresponding': False, 'raw_author_name': 'Eric Ladizinsky', 'raw_affiliation_strings': ['D-Wave Quantum Inc., Burnaby, British Columbia, Canada'], 'affiliations': [{'raw_affiliation_string': 'D-Wave Quantum Inc., Burnaby, British Columbia, Canada', 'institution_ids': ['https://openalex.org/I1309087048']}]}, {'author_position': 'middle', 'author': {'id': 'https://openalex.org/A5109582683', 'display_name': 'Allison MacDonald', 'orcid': None}, 'institutions': [{'id': 'https://openalex.org/I1309087048', 'display_name': 'D-Wave Systems (Canada)', 'ror': 'https://ror.org/01mmn7c12', 'country_code': 'CA', 'type': 'company', 'lineage': ['https://openalex.org/I1309087048']}], 'countries': ['CA'], 'is_corresponding': False, 'raw_author_name': 'Allison J. R. MacDonald', 'raw_affiliation_strings': ['D-Wave Quantum Inc., Burnaby, British Columbia, Canada'], 'affiliations': [{'raw_affiliation_string': 'D-Wave Quantum Inc., Burnaby, British Columbia, Canada', 'institution_ids': ['https://openalex.org/I1309087048']}]}, {'author_position': 'middle', 'author': {'id': 'https://openalex.org/A5070034728', 'display_name': 'G. Marsden', 'orcid': None}, 'institutions': [{'id': 'https://openalex.org/I1309087048', 'display_name': 'D-Wave Systems (Canada)', 'ror': 'https://ror.org/01mmn7c12', 'country_code': 'CA', 'type': 'company', 'lineage': ['https://openalex.org/I1309087048']}], 'countries': ['CA'], 'is_corresponding': False, 'raw_author_name': 'Gaelen Marsden', 'raw_affiliation_strings': ['D-Wave Quantum Inc., Burnaby, British Columbia, Canada'], 'affiliations': [{'raw_affiliation_string': 'D-Wave Quantum Inc., Burnaby, British Columbia, Canada', 'institution_ids': ['https://openalex.org/I1309087048']}]}, {'author_position': 'middle', 'author': {'id': 'https://openalex.org/A5068192189', 'display_name': 'Reza Molavi', 'orcid': None}, 'institutions': [{'id': 'https://openalex.org/I1309087048', 'display_name': 'D-Wave Systems (Canada)', 'ror': 'https://ror.org/01mmn7c12', 'country_code': 'CA', 'type': 'company', 'lineage': ['https://openalex.org/I1309087048']}], 'countries': ['CA'], 'is_corresponding': False, 'raw_author_name': 'Reza Molavi', 'raw_affiliation_strings': ['D-Wave Quantum Inc., Burnaby, British Columbia, Canada'], 'affiliations': [{'raw_affiliation_string': 'D-Wave Quantum Inc., Burnaby, British Columbia, Canada', 'institution_ids': ['https://openalex.org/I1309087048']}]}, {'author_position': 'middle', 'author': {'id': 'https://openalex.org/A5114144531', 'display_name': 'Travis Oh', 'orcid': None}, 'institutions': [{'id': 'https://openalex.org/I1309087048', 'display_name': 'D-Wave Systems (Canada)', 'ror': 'https://ror.org/01mmn7c12', 'country_code': 'CA', 'type': 'company', 'lineage': ['https://openalex.org/I1309087048']}], 'countries': ['CA'], 'is_corresponding': False, 'raw_author_name': 'Travis Oh', 'raw_affiliation_strings': ['D-Wave Quantum Inc., Burnaby, British Columbia, Canada'], 'affiliations': [{'raw_affiliation_string': 'D-Wave Quantum Inc., Burnaby, British Columbia, Canada', 'institution_ids': ['https://openalex.org/I1309087048']}]}, {'author_position': 'middle', 'author': {'id': 'https://openalex.org/A5080248174', 'display_name': 'Gabriel Poulin-Lamarre', 'orcid': 'https://orcid.org/0000-0002-2602-6255'}, 'institutions': [{'id': 'https://openalex.org/I1309087048', 'display_name': 'D-Wave Systems (Canada)', 'ror': 'https://ror.org/01mmn7c12', 'country_code': 'CA', 'type': 'company', 'lineage': ['https://openalex.org/I1309087048']}], 'countries': ['CA'], 'is_corresponding': False, 'raw_author_name': 'Gabriel Poulin-Lamarre', 'raw_affiliation_strings': ['D-Wave Quantum Inc., Burnaby, British Columbia, Canada'], 'affiliations': [{'raw_affiliation_string': 'D-Wave Quantum Inc., Burnaby, British Columbia, Canada', 'institution_ids': ['https://openalex.org/I1309087048']}]}, {'author_position': 'middle', 'author': {'id': 'https://openalex.org/A5037341805', 'display_name': 'MaurÃ­cio Sedrez dos Reis', 'orcid': 'https://orcid.org/0000-0003-1331-3367'}, 'institutions': [{'id': 'https://openalex.org/I1309087048', 'display_name': 'D-Wave Systems (Canada)', 'ror': 'https://ror.org/01mmn7c12', 'country_code': 'CA', 'type': 'company', 'lineage': ['https://openalex.org/I1309087048']}], 'countries': ['CA'], 'is_corresponding': False, 'raw_author_name': 'Mauricio Reis', 'raw_affiliation_strings': ['D-Wave Quantum Inc., Burnaby, British Columbia, Canada'], 'affiliations': [{'raw_affiliation_string': 'D-Wave Quantum Inc., Burnaby, British Columbia, Canada', 'institution_ids': ['https://openalex.org/I1309087048']}]}, {'author_position': 'middle', 'author': {'id': 'https://openalex.org/A5005749576', 'display_name': 'Chris Rich', 'orcid': 'https://orcid.org/0000-0001-8989-3199'}, 'institutions': [{'id': 'https://openalex.org/I1309087048', 'display_name': 'D-Wave Systems (Canada)', 'ror': 'https://ror.org/01mmn7c12', 'country_code': 'CA', 'type': 'company', 'lineage': ['https://openalex.org/I1309087048']}], 'countries': ['CA'], 'is_corresponding': False, 'raw_author_name': 'Chris Rich', 'raw_affiliation_strings': ['D-Wave Quantum Inc., Burnaby, British Columbia, Canada'], 'affiliations': [{'raw_affiliation_string': 'D-Wave Quantum Inc., Burnaby, British Columbia, Canada', 'institution_ids': ['https://openalex.org/I1309087048']}]}, {'author_position': 'middle', 'author': {'id': 'https://openalex.org/A5072441184', 'display_name': 'Yuki Sato', 'orcid': 'https://orcid.org/0000-0003-2069-0355'}, 'institutions': [{'id': 'https://openalex.org/I1309087048', 'display_name': 'D-Wave Systems (Canada)', 'ror': 'https://ror.org/01mmn7c12', 'country_code': 'CA', 'type': 'company', 'lineage': ['https://openalex.org/I1309087048']}], 'countries': ['CA'], 'is_corresponding': False, 'raw_author_name': 'Yuki Sato', 'raw_affiliation_strings': ['D-Wave Quantum Inc., Burnaby, British Columbia, Canada'], 'affiliations': [{'raw_affiliation_string': 'D-Wave Quantum Inc., Burnaby, British Columbia, Canada', 'institution_ids': ['https://openalex.org/I1309087048']}]}, {'author_position': 'middle', 'author': {'id': 'https://openalex.org/A5020424443', 'display_name': 'Nicholas Tsai', 'orcid': 'https://orcid.org/0000-0001-5196-8677'}, 'institutions': [{'id': 'https://openalex.org/I1309087048', 'display_name': 'D-Wave Systems (Canada)', 'ror': 'https://ror.org/01mmn7c12', 'country_code': 'CA', 'type': 'company', 'lineage': ['https://openalex.org/I1309087048']}], 'countries': ['CA'], 'is_corresponding': False, 'raw_author_name': 'Nicholas Tsai', 'raw_affiliation_strings': ['D-Wave Quantum Inc., Burnaby, British Columbia, Canada'], 'affiliations': [{'raw_affiliation_string': 'D-Wave Quantum Inc., Burnaby, British Columbia, Canada', 'institution_ids': ['https://openalex.org/I1309087048']}]}, {'author_position': 'middle', 'author': {'id': 'https://openalex.org/A5015632833', 'display_name': 'Mark H. Volkmann', 'orcid': None}, 'institutions': [{'id': 'https://openalex.org/I1309087048', 'display_name': 'D-Wave Systems (Canada)', 'ror': 'https://ror.org/01mmn7c12', 'country_code': 'CA', 'type': 'company', 'lineage': ['https://openalex.org/I1309087048']}], 'countries': ['CA'], 'is_corresponding': False, 'raw_author_name': 'Mark Volkmann', 'raw_affiliation_strings': ['D-Wave Quantum Inc., Burnaby, British Columbia, Canada'], 'affiliations': [{'raw_affiliation_string': 'D-Wave Quantum Inc., Burnaby, British Columbia, Canada', 'institution_ids': ['https://openalex.org/I1309087048']}]}, {'author_position': 'middle', 'author': {'id': 'https://openalex.org/A5048382852', 'display_name': 'Jed D. Whittaker', 'orcid': 'https://orcid.org/0000-0002-0456-3244'}, 'institutions': [{'id': 'https://openalex.org/I1309087048', 'display_name': 'D-Wave Systems (Canada)', 'ror': 'https://ror.org/01mmn7c12', 'country_code': 'CA', 'type': 'company', 'lineage': ['https://openalex.org/I1309087048']}], 'countries': ['CA'], 'is_corresponding': False, 'raw_author_name': 'Jed D. Whittaker', 'raw_affiliation_strings': ['D-Wave Quantum Inc., Burnaby, British Columbia, Canada'], 'affiliations': [{'raw_affiliation_string': 'D-Wave Quantum Inc., Burnaby, British Columbia, Canada', 'institution_ids': ['https://openalex.org/I1309087048']}]}, {'author_position': 'middle', 'author': {'id': 'https://openalex.org/A5109881679', 'display_name': 'Jason Yao', 'orcid': None}, 'institutions': [{'id': 'https://openalex.org/I1309087048', 'display_name': 'D-Wave Systems (Canada)', 'ror': 'https://ror.org/01mmn7c12', 'country_code': 'CA', 'type': 'company', 'lineage': ['https://openalex.org/I1309087048']}], 'countries': ['CA'], 'is_corresponding': False, 'raw_author_name': 'Jason Yao', 'raw_affiliation_strings': ['D-Wave Quantum Inc., Burnaby, British Columbia, Canada'], 'affiliations': [{'raw_affiliation_string': 'D-Wave Quantum Inc., Burnaby, British Columbia, Canada', 'institution_ids': ['https://openalex.org/I1309087048']}]}, {'author_position': 'middle', 'author': {'id': 'https://openalex.org/A5033845918', 'display_name': 'Anders W. Sandvik', 'orcid': 'https://orcid.org/0000-0002-5638-4619'}, 'institutions': [{'id': 'https://openalex.org/I111088046', 'display_name': 'Boston University', 'ror': 'https://ror.org/05qwgg493', 'country_code': 'US', 'type': 'education', 'lineage': ['https://openalex.org/I111088046']}], 'countries': ['US'], 'is_corresponding': True, 'raw_author_name': 'Anders W. Sandvik', 'raw_affiliation_strings': ['Department of Physics, Boston University, Boston, MA, USA. sandvik@buphy.bu.edu', 'Department of Physics, Boston University, Boston, MA, USA'], 'affiliations': [{'raw_affiliation_string': 'Department of Physics, Boston University, Boston, MA, USA. sandvik@buphy.bu.edu', 'institution_ids': []}, {'raw_affiliation_string': 'Department of Physics, Boston University, Boston, MA, USA', 'institution_ids': ['https://openalex.org/I111088046']}]}, {'author_position': 'last', 'author': {'id': 'https://openalex.org/A5112270021', 'display_name': 'M. H. S. Amin', 'orcid': None}, 'institutions': [{'id': 'https://openalex.org/I18014758', 'display_name': 'Simon Fraser University', 'ror': 'https://ror.org/0213rcc28', 'country_code': 'CA', 'type': 'education', 'lineage': ['https://openalex.org/I18014758']}], 'countries': ['CA'], 'is_corresponding': True, 'raw_author_name': 'Mohammad H. Amin', 'raw_affiliation_strings': ['D-Wave Quantum Inc., Burnaby, British Columbia, Canada. mhsamin@dwavesys.com', 'Department of Physics, Simon Fraser University, Burnaby, British Columbia, Canada. mhsamin@dwavesys.com', 'Department of Physics, Simon Fraser University, Burnaby, British Columbia, Canada'], 'affiliations': [{'raw_affiliation_string': 'D-Wave Quantum Inc., Burnaby, British Columbia, Canada. mhsamin@dwavesys.com', 'institution_ids': []}, {'raw_affiliation_string': 'Department of Physics, Simon Fraser University, Burnaby, British Columbia, Canada. mhsamin@dwavesys.com', 'institution_ids': []}, {'raw_affiliation_string': 'Department of Physics, Simon Fraser University, Burnaby, British Columbia, Canada', 'institution_ids': ['https://openalex.org/I18014758']}]}] | J9: 2 | K9: 27 | L9: 44.7237 | M9: FALSE | N9: 217 | O9: {'volume': '617', 'issue': '7959', 'first_page': '61', 'last_page': '66'} | P9: {'id': 'https://openalex.org/T11804', 'display_name': 'Quantum many-body systems', 'score': 0.9994000196456909, 'subfield': {'id': 'https://openalex.org/subfields/3107', 'display_name': 'Atomic and Molecular Physics, and Optics'}, 'field': {'id': 'https://openalex.org/fields/31', 'display_name': 'Physics and Astronomy'}, 'domain': {'id': 'https://openalex.org/domains/3', 'display_name': 'Physical Sciences'}} | Q9: [{'id': 'https://openalex.org/T11804', 'display_name': 'Quantum many-body systems', 'score': 0.9994000196456909, 'subfield': {'id': 'https://openalex.org/subfields/3107', 'display_name': 'Atomic and Molecular Physics, and Optics'}, 'field': {'id': 'https://openalex.org/fields/31', 'display_name': 'Physics and Astronomy'}, 'domain': {'id': 'https://openalex.org/domains/3', 'display_name': 'Physical Sciences'}}, {'id': 'https://openalex.org/T10591', 'display_name': 'Theoretical and Computational Physics', 'score': 0.9983000159263611, 'subfield': {'id': 'https://openalex.org/subfields/3104', 'display_name': 'Condensed Matter Physics'}, 'field': {'id': 'https://openalex.org/fields/31', 'display_name': 'Physics and Astronomy'}, 'domain': {'id': 'https://openalex.org/domains/3', 'display_name': 'Physical Sciences'}}, {'id': 'https://openalex.org/T10682', 'display_name': 'Quantum Computing Algorithms and Architecture', 'score': 0.9983000159263611, 'subfield': {'id': 'https://openalex.org/subfields/1702', 'display_name': 'Artificial Intelligence'}, 'field': {'id': 'https://openalex.org/fields/17', 'display_name': 'Computer Science'}, 'domain': {'id': 'https://openalex.org/domains/3', 'display_name': 'Physical Sciences'}}] | R9: [{'id': 'https://openalex.org/keywords/quantum-annealing', 'display_name': 'Quantum annealing', 'score': 0.9202107787132263}, {'id': 'https://openalex.org/keywords/qubit', 'display_name': 'Qubit', 'score': 0.7343852519989014}, {'id': 'https://openalex.org/keywords/spin-glass', 'display_name': 'Spin glass', 'score': 0.7119998931884766}, {'id': 'https://openalex.org/keywords/physics', 'display_name': 'Physics', 'score': 0.6035236716270447}, {'id': 'https://openalex.org/keywords/quantum', 'display_name': 'Quantum', 'score': 0.5577681660652161}, {'id': 'https://openalex.org/keywords/statistical-physics', 'display_name': 'Statistical physics', 'score': 0.5047203302383423}, {'id': 'https://openalex.org/keywords/quantum-dynamics', 'display_name': 'Quantum dynamics', 'score': 0.45608681440353394}, {'id': 'https://openalex.org/keywords/quantum-computer', 'display_name': 'Quantum computer', 'score': 0.4537891745567322}, {'id': 'https://openalex.org/keywords/spin-engineering', 'display_name': 'Spin engineering', 'score': 0.4142260253429413}, {'id': 'https://openalex.org/keywords/quantum-mechanics', 'display_name': 'Quantum mechanics', 'score': 0.39180538058280945}, {'id': 'https://openalex.org/keywords/condensed-matter-physics', 'display_name': 'Condensed matter physics', 'score': 0.3259493112564087}, {'id': 'https://openalex.org/keywords/spin-polarization', 'display_name': 'Spin polarization', 'score': 0.19178906083106995}, {'id': 'https://openalex.org/keywords/electron', 'display_name': 'Electron', 'score': 0.07223254442214966}] | S9: [{'id': 'https://openalex.org/C90408235', 'wikidata': 'https://www.wikidata.org/wiki/Q938141', 'display_name': 'Quantum annealing', 'level': 4, 'score': 0.9202107787132263}, {'id': 'https://openalex.org/C203087015', 'wikidata': 'https://www.wikidata.org/wiki/Q378201', 'display_name': 'Qubit', 'level': 3, 'score': 0.7343852519989014}, {'id': 'https://openalex.org/C150775274', 'wikidata': 'https://www.wikidata.org/wiki/Q1490646', 'display_name': 'Spin glass', 'level': 2, 'score': 0.7119998931884766}, {'id': 'https://openalex.org/C121332964', 'wikidata': 'https://www.wikidata.org/wiki/Q413', 'display_name': 'Physics', 'level': 0, 'score': 0.6035236716270447}, {'id': 'https://openalex.org/C84114770', 'wikidata': 'https://www.wikidata.org/wiki/Q46344', 'display_name': 'Quantum', 'level': 2, 'score': 0.5577681660652161}, {'id': 'https://openalex.org/C121864883', 'wikidata': 'https://www.wikidata.org/wiki/Q677916', 'display_name': 'Statistical physics', 'level': 1, 'score': 0.5047203302383423}, {'id': 'https://openalex.org/C15184713', 'wikidata': 'https://www.wikidata.org/wiki/Q7269042', 'display_name': 'Quantum dynamics', 'level': 3, 'score': 0.45608681440353394}, {'id': 'https://openalex.org/C58053490', 'wikidata': 'https://www.wikidata.org/wiki/Q176555', 'display_name': 'Quantum computer', 'level': 3, 'score': 0.4537891745567322}, {'id': 'https://openalex.org/C150365167', 'wikidata': 'https://www.wikidata.org/wiki/Q7577404', 'display_name': 'Spin engineering', 'level': 4, 'score': 0.4142260253429413}, {'id': 'https://openalex.org/C62520636', 'wikidata': 'https://www.wikidata.org/wiki/Q944', 'display_name': 'Quantum mechanics', 'level': 1, 'score': 0.39180538058280945}, {'id': 'https://openalex.org/C26873012', 'wikidata': 'https://www.wikidata.org/wiki/Q214781', 'display_name': 'Condensed matter physics', 'level': 1, 'score': 0.3259493112564087}, {'id': 'https://openalex.org/C21690051', 'wikidata': 'https://www.wikidata.org/wiki/Q962347', 'display_name': 'Spin polarization', 'level': 3, 'score': 0.19178906083106995}, {'id': 'https://openalex.org/C147120987', 'wikidata': 'https://www.wikidata.org/wiki/Q2225', 'display_name': 'Electron', 'level': 2, 'score': 0.07223254442214966}] | T9: [{'id': 'https://metadata.un.org/sdg/7', 'display_name': 'Affordable and clean energy', 'score': 0.9100000262260437}] | U9: 62
A10: https://openalex.org/W4295929652 | B10: https://doi.org/10.1038/s41567-022-01741-6 | C10: Coherent quantum annealing in a programmable 2,000â€‰qubit Ising chain | D10: 2022 | E10: 44819 | F10: en | G10: article | H10: {'is_oa': False, 'oa_status': 'closed', 'oa_url': None, 'any_repository_has_fulltext': False} | I10: [{'author_position': 'first', 'author': {'id': 'https://openalex.org/A5052420215', 'display_name': 'Andrew D. King', 'orcid': 'https://orcid.org/0000-0001-8362-8941'}, 'institutions': [{'id': 'https://openalex.org/I1309087048', 'display_name': 'D-Wave Systems (Canada)', 'ror': 'https://ror.org/01mmn7c12', 'country_code': 'CA', 'type': 'company', 'lineage': ['https://openalex.org/I1309087048']}], 'countries': ['CA'], 'is_corresponding': True, 'raw_author_name': 'Andrew D. King', 'raw_affiliation_strings': ['D-Wave Systems, Burnaby, British Columbia, Canada'], 'affiliations': [{'raw_affiliation_string': 'D-Wave Systems, Burnaby, British Columbia, Canada', 'institution_ids': ['https://openalex.org/I1309087048']}]}, {'author_position': 'middle', 'author': {'id': 'https://openalex.org/A5014006988', 'display_name': 'Sei Suzuki', 'orcid': 'https://orcid.org/0000-0002-3235-9910'}, 'institutions': [{'id': 'https://openalex.org/I8588240', 'display_name': 'Saitama Medical University', 'ror': 'https://ror.org/04zb31v77', 'country_code': 'JP', 'type': 'education', 'lineage': ['https://openalex.org/I8588240']}], 'countries': ['JP'], 'is_corresponding': False, 'raw_author_name': 'Sei Suzuki', 'raw_affiliation_strings': ['Department of Liberal Arts, Saitama Medical University, Moroyama, Japan'], 'affiliations': [{'raw_affiliation_string': 'Department of Liberal Arts, Saitama Medical University, Moroyama, Japan', 'institution_ids': ['https://openalex.org/I8588240']}]}, {'author_position': 'middle', 'author': {'id': 'https://openalex.org/A5034139385', 'display_name': 'Jack Raymond', 'orcid': 'https://orcid.org/0000-0002-1808-6039'}, 'institutions': [{'id': 'https://openalex.org/I1309087048', 'display_name': 'D-Wave Systems (Canada)', 'ror': 'https://ror.org/01mmn7c12', 'country_code': 'CA', 'type': 'company', 'lineage': ['https://openalex.org/I1309087048']}], 'countries': ['CA'], 'is_corresponding': False, 'raw_author_name': 'Jack Raymond', 'raw_affiliation_strings': ['D-Wave Systems, Burnaby, British Columbia, Canada'], 'affiliations': [{'raw_affiliation_string': 'D-Wave Systems, Burnaby, British Columbia, Canada', 'institution_ids': ['https://openalex.org/I1309087048']}]}, {'author_position': 'middle', 'author': {'id': 'https://openalex.org/A5091636310', 'display_name': 'Alex Zucca', 'orcid': 'https://orcid.org/0000-0002-1728-106X'}, 'institutions': [{'id': 'https://openalex.org/I1309087048', 'display_name': 'D-Wave Systems (Canada)', 'ror': 'https://ror.org/01mmn7c12', 'country_code': 'CA', 'type': 'company', 'lineage': ['https://openalex.org/I1309087048']}], 'countries': ['CA'], 'is_corresponding': False, 'raw_author_name': 'Alex Zucca', 'raw_affiliation_strings': ['D-Wave Systems, Burnaby, British Columbia, Canada'], 'affiliations': [{'raw_affiliation_string': 'D-Wave Systems, Burnaby, British Columbia, Canada', 'institution_ids': ['https://openalex.org/I1309087048']}]}, {'author_position': 'middle', 'author': {'id': 'https://openalex.org/A5089555006', 'display_name': 'T. Lanting', 'orcid': 'https://orcid.org/0000-0003-2829-0196'}, 'institutions': [{'id': 'https://openalex.org/I1309087048', 'display_name': 'D-Wave Systems (Canada)', 'ror': 'https://ror.org/01mmn7c12', 'country_code': 'CA', 'type': 'company', 'lineage': ['https://openalex.org/I1309087048']}], 'countries': ['CA'], 'is_corresponding': False, 'raw_author_name': 'Trevor Lanting', 'raw_affiliation_strings': ['D-Wave Systems, Burnaby, British Columbia, Canada'], 'affiliations': [{'raw_affiliation_string': 'D-Wave Systems, Burnaby, British Columbia, Canada', 'institution_ids': ['https://openalex.org/I1309087048']}]}, {'author_position': 'middle', 'author': {'id': 'https://openalex.org/A5073678218', 'display_name': 'Fabio Altomare', 'orcid': 'https://orcid.org/0000-0001-8380-3623'}, 'institutions': [{'id': 'https://openalex.org/I1309087048', 'display_name': 'D-Wave Systems (Canada)', 'ror': 'https://ror.org/01mmn7c12', 'country_code': 'CA', 'type': 'company', 'lineage': ['https://openalex.org/I1309087048']}], 'countries': ['CA'], 'is_corresponding': False, 'raw_author_name': 'Fabio Altomare', 'raw_affiliation_strings': ['D-Wave Systems, Burnaby, British Columbia, Canada'], 'affiliations': [{'raw_affiliation_string': 'D-Wave Systems, Burnaby, British Columbia, Canada', 'institution_ids': ['https://openalex.org/I1309087048']}]}, {'author_position': 'middle', 'author': {'id': 'https://openalex.org/A5072333621', 'display_name': 'A. J. Berkley', 'orcid': 'https://orcid.org/0000-0002-4235-8452'}, 'institutions': [{'id': 'https://openalex.org/I1309087048', 'display_name': 'D-Wave Systems (Canada)', 'ror': 'https://ror.org/01mmn7c12', 'country_code': 'CA', 'type': 'company', 'lineage': ['https://openalex.org/I1309087048']}], 'countries': ['CA'], 'is_corresponding': False, 'raw_author_name': 'Andrew J. Berkley', 'raw_affiliation_strings': ['D-Wave Systems, Burnaby, British Columbia, Canada'], 'affiliations': [{'raw_affiliation_string': 'D-Wave Systems, Burnaby, British Columbia, Canada', 'institution_ids': ['https://openalex.org/I1309087048']}]}, {'author_position': 'middle', 'author': {'id': 'https://openalex.org/A5056214096', 'display_name': 'Sara Ejtemaee', 'orcid': None}, 'institutions': [{'id': 'https://openalex.org/I1309087048', 'display_name': 'D-Wave Systems (Canada)', 'ror': 'https://ror.org/01mmn7c12', 'country_code': 'CA', 'type': 'company', 'lineage': ['https://openalex.org/I1309087048']}], 'countries': ['CA'], 'is_corresponding': False, 'raw_author_name': 'Sara Ejtemaee', 'raw_affiliation_strings': ['D-Wave Systems, Burnaby, British Columbia, Canada'], 'affiliations': [{'raw_affiliation_string': 'D-Wave Systems, Burnaby, British Columbia, Canada', 'institution_ids': ['https://openalex.org/I1309087048']}]}, {'author_position': 'middle', 'author': {'id': 'https://openalex.org/A5111912151', 'display_name': 'Emile Hoskinson', 'orcid': None}, 'institutions': [{'id': 'https://openalex.org/I1309087048', 'display_name': 'D-Wave Systems (Canada)', 'ror': 'https://ror.org/01mmn7c12', 'country_code': 'CA', 'type': 'company', 'lineage': ['https://openalex.org/I1309087048']}], 'countries': ['CA'], 'is_corresponding': False, 'raw_author_name': 'Emile Hoskinson', 'raw_affiliation_strings': ['D-Wave Systems, Burnaby, British Columbia, Canada'], 'affiliations': [{'raw_affiliation_string': 'D-Wave Systems, Burnaby, British Columbia, Canada', 'institution_ids': ['https://openalex.org/I1309087048']}]}, {'author_position': 'middle', 'author': {'id': 'https://openalex.org/A5091685844', 'display_name': 'Shuiyuan Huang', 'orcid': 'https://orcid.org/0000-0001-9799-1872'}, 'institutions': [{'id': 'https://openalex.org/I1309087048', 'display_name': 'D-Wave Systems (Canada)', 'ror': 'https://ror.org/01mmn7c12', 'country_code': 'CA', 'type': 'company', 'lineage': ['https://openalex.org/I1309087048']}], 'countries': ['CA'], 'is_corresponding': False, 'raw_author_name': 'Shuiyuan Huang', 'raw_affiliation_strings': ['D-Wave Systems, Burnaby, British Columbia, Canada'], 'affiliations': [{'raw_affiliation_string': 'D-Wave Systems, Burnaby, British Columbia, Canada', 'institution_ids': ['https://openalex.org/I1309087048']}]}, {'author_position': 'middle', 'author': {'id': 'https://openalex.org/A5002475393', 'display_name': 'E. Ladizinsky', 'orcid': None}, 'institutions': [{'id': 'https://openalex.org/I1309087048', 'display_name': 'D-Wave Systems (Canada)', 'ror': 'https://ror.org/01mmn7c12', 'country_code': 'CA', 'type': 'company', 'lineage': ['https://openalex.org/I1309087048']}], 'countries': ['CA'], 'is_corresponding': False, 'raw_author_name': 'Eric Ladizinsky', 'raw_affiliation_strings': ['D-Wave Systems, Burnaby, British Columbia, Canada'], 'affiliations': [{'raw_affiliation_string': 'D-Wave Systems, Burnaby, British Columbia, Canada', 'institution_ids': ['https://openalex.org/I1309087048']}]}, {'author_position': 'middle', 'author': {'id': 'https://openalex.org/A5109582683', 'display_name': 'Allison MacDonald', 'orcid': None}, 'institutions': [{'id': 'https://openalex.org/I1309087048', 'display_name': 'D-Wave Systems (Canada)', 'ror': 'https://ror.org/01mmn7c12', 'country_code': 'CA', 'type': 'company', 'lineage': ['https://openalex.org/I1309087048']}], 'countries': ['CA'], 'is_corresponding': False, 'raw_author_name': 'Allison J. R. MacDonald', 'raw_affiliation_strings': ['D-Wave Systems, Burnaby, British Columbia, Canada'], 'affiliations': [{'raw_affiliation_string': 'D-Wave Systems, Burnaby, British Columbia, Canada', 'institution_ids': ['https://openalex.org/I1309087048']}]}, {'author_position': 'middle', 'author': {'id': 'https://openalex.org/A5070034728', 'display_name': 'G. Marsden', 'orcid': None}, 'institutions': [{'id': 'https://openalex.org/I1309087048', 'display_name': 'D-Wave Systems (Canada)', 'ror': 'https://ror.org/01mmn7c12', 'country_code': 'CA', 'type': 'company', 'lineage': ['https://openalex.org/I1309087048']}], 'countries': ['CA'], 'is_corresponding': False, 'raw_author_name': 'Gaelen Marsden', 'raw_affiliation_strings': ['D-Wave Systems, Burnaby, British Columbia, Canada'], 'affiliations': [{'raw_affiliation_string': 'D-Wave Systems, Burnaby, British Columbia, Canada', 'institution_ids': ['https://openalex.org/I1309087048']}]}, {'author_position': 'middle', 'author': {'id': 'https://openalex.org/A5114144531', 'display_name': 'Travis Oh', 'orcid': None}, 'institutions': [{'id': 'https://openalex.org/I1309087048', 'display_name': 'D-Wave Systems (Canada)', 'ror': 'https://ror.org/01mmn7c12', 'country_code': 'CA', 'type': 'company', 'lineage': ['https://openalex.org/I1309087048']}], 'countries': ['CA'], 'is_corresponding': False, 'raw_author_name': 'Travis Oh', 'raw_affiliation_strings': ['D-Wave Systems, Burnaby, British Columbia, Canada'], 'affiliations': [{'raw_affiliation_string': 'D-Wave Systems, Burnaby, British Columbia, Canada', 'institution_ids': ['https://openalex.org/I1309087048']}]}, {'author_position': 'middle', 'author': {'id': 'https://openalex.org/A5080248174', 'display_name': 'Gabriel Poulin-Lamarre', 'orcid': 'https://orcid.org/0000-0002-2602-6255'}, 'institutions': [{'id': 'https://openalex.org/I1309087048', 'display_name': 'D-Wave Systems (Canada)', 'ror': 'https://ror.org/01mmn7c12', 'country_code': 'CA', 'type': 'company', 'lineage': ['https://openalex.org/I1309087048']}], 'countries': ['CA'], 'is_corresponding': False, 'raw_author_name': 'Gabriel Poulin-Lamarre', 'raw_affiliation_strings': ['D-Wave Systems, Burnaby, British Columbia, Canada'], 'affiliations': [{'raw_affiliation_string': 'D-Wave Systems, Burnaby, British Columbia, Canada', 'institution_ids': ['https://openalex.org/I1309087048']}]}, {'author_position': 'middle', 'author': {'id': 'https://openalex.org/A5037341805', 'display_name': 'MaurÃ­cio Sedrez dos Reis', 'orcid': 'https://orcid.org/0000-0003-1331-3367'}, 'institutions': [{'id': 'https://openalex.org/I1309087048', 'display_name': 'D-Wave Systems (Canada)', 'ror': 'https://ror.org/01mmn7c12', 'country_code': 'CA', 'type': 'company', 'lineage': ['https://openalex.org/I1309087048']}], 'countries': ['CA'], 'is_corresponding': False, 'raw_author_name': 'Mauricio Reis', 'raw_affiliation_strings': ['D-Wave Systems, Burnaby, British Columbia, Canada'], 'affiliations': [{'raw_affiliation_string': 'D-Wave Systems, Burnaby, British Columbia, Canada', 'institution_ids': ['https://openalex.org/I1309087048']}]}, {'author_position': 'middle', 'author': {'id': 'https://openalex.org/A5005749576', 'display_name': 'Chris Rich', 'orcid': 'https://orcid.org/0000-0001-8989-3199'}, 'institutions': [{'id': 'https://openalex.org/I1309087048', 'display_name': 'D-Wave Systems (Canada)', 'ror': 'https://ror.org/01mmn7c12', 'country_code': 'CA', 'type': 'company', 'lineage': ['https://openalex.org/I1309087048']}], 'countries': ['CA'], 'is_corresponding': False, 'raw_author_name': 'Chris Rich', 'raw_affiliation_strings': ['D-Wave Systems, Burnaby, British Columbia, Canada'], 'affiliations': [{'raw_affiliation_string': 'D-Wave Systems, Burnaby, British Columbia, Canada', 'institution_ids': ['https://openalex.org/I1309087048']}]}, {'author_position': 'middle', 'author': {'id': 'https://openalex.org/A5072441184', 'display_name': 'Yuki Sato', 'orcid': 'https://orcid.org/0000-0003-2069-0355'}, 'institutions': [{'id': 'https://openalex.org/I1309087048', 'display_name': 'D-Wave Systems (Canada)', 'ror': 'https://ror.org/01mmn7c12', 'country_code': 'CA', 'type': 'company', 'lineage': ['https://openalex.org/I1309087048']}], 'countries': ['CA'], 'is_corresponding': False, 'raw_author_name': 'Yuki Sato', 'raw_affiliation_strings': ['D-Wave Systems, Burnaby, British Columbia, Canada'], 'affiliations': [{'raw_affiliation_string': 'D-Wave Systems, Burnaby, British Columbia, Canada', 'institution_ids': ['https://openalex.org/I1309087048']}]}, {'author_position': 'middle', 'author': {'id': 'https://openalex.org/A5048382852', 'display_name': 'Jed D. Whittaker', 'orcid': 'https://orcid.org/0000-0002-0456-3244'}, 'institutions': [{'id': 'https://openalex.org/I1309087048', 'display_name': 'D-Wave Systems (Canada)', 'ror': 'https://ror.org/01mmn7c12', 'country_code': 'CA', 'type': 'company', 'lineage': ['https://openalex.org/I1309087048']}], 'countries': ['CA'], 'is_corresponding': False, 'raw_author_name': 'Jed D. Whittaker', 'raw_affiliation_strings': ['D-Wave Systems, Burnaby, British Columbia, Canada'], 'affiliations': [{'raw_affiliation_string': 'D-Wave Systems, Burnaby, British Columbia, Canada', 'institution_ids': ['https://openalex.org/I1309087048']}]}, {'author_position': 'middle', 'author': {'id': 'https://openalex.org/A5109881679', 'display_name': 'Jason Yao', 'orcid': None}, 'institutions': [{'id': 'https://openalex.org/I1309087048', 'display_name': 'D-Wave Systems (Canada)', 'ror': 'https://ror.org/01mmn7c12', 'country_code': 'CA', 'type': 'company', 'lineage': ['https://openalex.org/I1309087048']}], 'countries': ['CA'], 'is_corresponding': False, 'raw_author_name': 'Jason Yao', 'raw_affiliation_strings': ['D-Wave Systems, Burnaby, British Columbia, Canada'], 'affiliations': [{'raw_affiliation_string': 'D-Wave Systems, Burnaby, British Columbia, Canada', 'institution_ids': ['https://openalex.org/I1309087048']}]}, {'author_position': 'middle', 'author': {'id': 'https://openalex.org/A5102862575', 'display_name': 'R. Harris', 'orcid': 'https://orcid.org/0000-0002-6394-926X'}, 'institutions': [{'id': 'https://openalex.org/I1309087048', 'display_name': 'D-Wave Systems (Canada)', 'ror': 'https://ror.org/01mmn7c12', 'country_code': 'CA', 'type': 'company', 'lineage': ['https://openalex.org/I1309087048']}], 'countries': ['CA'], 'is_corresponding': False, 'raw_author_name': 'Richard Harris', 'raw_affiliation_strings': ['D-Wave Systems, Burnaby, British Columbia, Canada'], 'affiliations': [{'raw_affiliation_string': 'D-Wave Systems, Burnaby, British Columbia, Canada', 'institution_ids': ['https://openalex.org/I1309087048']}]}, {'author_position': 'middle', 'author': {'id': 'https://openalex.org/A5083283029', 'display_name': 'Daniel A. Lidar', 'orcid': 'https://orcid.org/0000-0002-1671-1515'}, 'institutions': [{'id': 'https://openalex.org/I4210100980', 'display_name': 'Vienna Center for Quantum Science and Technology', 'ror': 'https://ror.org/014cpn338', 'country_code': 'AT', 'type': 'education', 'lineage': ['https://openalex.org/I129774422', 'https://openalex.org/I138211613', 'https://openalex.org/I145847075', 'https://openalex.org/I4210100980']}, {'id': 'https://openalex.org/I1174212', 'display_name': 'University of Southern California', 'ror': 'https://ror.org/03taz7m60', 'country_code': 'US', 'type': 'education', 'lineage': ['https://openalex.org/I1174212']}], 'countries': ['AT', 'US'], 'is_corresponding': False, 'raw_author_name': 'Daniel A. Lidar', 'raw_affiliation_strings': ['Center for Quantum Information Science & Technology (CQIST), University of Southern California, Los Angeles, CA, USA', 'Departments of Electrical and Computer Engineering, Chemistry, Physics & Astronomy, University of Southern California, Los Angeles, CA, USA'], 'affiliations': [{'raw_affiliation_string': 'Center for Quantum Information Science & Technology (CQIST), University of Southern California, Los Angeles, CA, USA', 'institution_ids': ['https://openalex.org/I4210100980']}, {'raw_affiliation_string': 'Departments of Electrical and Computer Engineering, Chemistry, Physics & Astronomy, University of Southern California, Los Angeles, CA, USA', 'institution_ids': ['https://openalex.org/I1174212']}]}, {'author_position': 'middle', 'author': {'id': 'https://openalex.org/A5057513894', 'display_name': 'Hidetoshi Nishimori', 'orcid': 'https://orcid.org/0000-0002-0924-1463'}, 'institutions': [{'id': 'https://openalex.org/I114531698', 'display_name': 'Tokyo Institute of Technology', 'ror': 'https://ror.org/0112mx960', 'country_code': 'JP', 'type': 'education', 'lineage': ['https://openalex.org/I114531698']}, {'id': 'https://openalex.org/I4210110652', 'display_name': 'RIKEN', 'ror': 'https://ror.org/01sjwvz98', 'country_code': 'JP', 'type': 'facility', 'lineage': ['https://openalex.org/I4210110652']}, {'id': 'https://openalex.org/I201537933', 'display_name': 'Tohoku University', 'ror': 'https://ror.org/01dq60k83', 'country_code': 'JP', 'type': 'education', 'lineage': ['https://openalex.org/I201537933']}], 'countries': ['JP'], 'is_corresponding': False, 'raw_author_name': 'Hidetoshi Nishimori', 'raw_affiliation_strings': ['Graduate School of Information Sciences, Tohoku University, Sendai, Japan', 'Interdisciplinary Theoretical and Mathematical Sciences, RIKEN, Wako, Japan', 'International Research Frontiers Initiative, Tokyo Institute of Technology, Tokyo, Japan'], 'affiliations': [{'raw_affiliation_string': 'Graduate School of Information Sciences, Tohoku University, Sendai, Japan', 'institution_ids': ['https://openalex.org/I201537933']}, {'raw_affiliation_string': 'Interdisciplinary Theoretical and Mathematical Sciences, RIKEN, Wako, Japan', 'institution_ids': ['https://openalex.org/I4210110652']}, {'raw_affiliation_string': 'International Research Frontiers Initiative, Tokyo Institute of Technology, Tokyo, Japan', 'institution_ids': ['https://openalex.org/I114531698']}]}, {'author_position': 'last', 'author': {'id': 'https://openalex.org/A5112270021', 'display_name': 'M. H. S. Amin', 'orcid': None}, 'institutions': [{'id': 'https://openalex.org/I18014758', 'display_name': 'Simon Fraser University', 'ror': 'https://ror.org/0213rcc28', 'country_code': 'CA', 'type': 'education', 'lineage': ['https://openalex.org/I18014758']}, {'id': 'https://openalex.org/I1309087048', 'display_name': 'D-Wave Systems (Canada)', 'ror': 'https://ror.org/01mmn7c12', 'country_code': 'CA', 'type': 'company', 'lineage': ['https://openalex.org/I1309087048']}], 'countries': ['CA'], 'is_corresponding': False, 'raw_author_name': 'Mohammad H. Amin', 'raw_affiliation_strings': ['D-Wave Systems, Burnaby, British Columbia, Canada', 'Department of Physics, Simon Fraser University, Burnaby, British Columbia, Canada'], 'affiliations': [{'raw_affiliation_string': 'D-Wave Systems, Burnaby, British Columbia, Canada', 'institution_ids': ['https://openalex.org/I1309087048']}, {'raw_affiliation_string': 'Department of Physics, Simon Fraser University, Burnaby, British Columbia, Canada', 'institution_ids': ['https://openalex.org/I18014758']}]}] | J10: 4 | K10: 24 | L10: 25.737 | M10: FALSE | N10: 199 | O10: {'volume': '18', 'issue': '11', 'first_page': '1324', 'last_page': '1328'} | P10: {'id': 'https://openalex.org/T10682', 'display_name': 'Quantum Computing Algorithms and Architecture', 'score': 0.9998999834060669, 'subfield': {'id': 'https://openalex.org/subfields/1702', 'display_name': 'Artificial Intelligence'}, 'field': {'id': 'https://openalex.org/fields/17', 'display_name': 'Computer Science'}, 'domain': {'id': 'https://openalex.org/domains/3', 'display_name': 'Physical Sciences'}} | Q10: [{'id': 'https://openalex.org/T10682', 'display_name': 'Quantum Computing Algorithms and Architecture', 'score': 0.9998999834060669, 'subfield': {'id': 'https://openalex.org/subfields/1702', 'display_name': 'Artificial Intelligence'}, 'field': {'id': 'https://openalex.org/fields/17', 'display_name': 'Computer Science'}, 'domain': {'id': 'https://openalex.org/domains/3', 'display_name': 'Physical Sciences'}}, {'id': 'https://openalex.org/T11804', 'display_name': 'Quantum many-body systems', 'score': 0.9998000264167786, 'subfield': {'id': 'https://openalex.org/subfields/3107', 'display_name': 'Atomic and Molecular Physics, and Optics'}, 'field': {'id': 'https://openalex.org/fields/31', 'display_name': 'Physics and Astronomy'}, 'domain': {'id': 'https://openalex.org/domains/3', 'display_name': 'Physical Sciences'}}, {'id': 'https://openalex.org/T10020', 'display_name': 'Quantum Information and Cryptography', 'score': 0.9994000196456909, 'subfield': {'id': 'https://openalex.org/subfields/1702', 'display_name': 'Artificial Intelligence'}, 'field': {'id': 'https://openalex.org/fields/17', 'display_name': 'Computer Science'}, 'domain': {'id': 'https://openalex.org/domains/3', 'display_name': 'Physical Sciences'}}] | R10: [{'id': 'https://openalex.org/keywords/quantum-annealing', 'display_name': 'Quantum annealing', 'score': 0.8873305916786194}, {'id': 'https://openalex.org/keywords/physics', 'display_name': 'Physics', 'score': 0.8853421211242676}, {'id': 'https://openalex.org/keywords/qubit', 'display_name': 'Qubit', 'score': 0.7430634498596191}, {'id': 'https://openalex.org/keywords/quantum-simulator', 'display_name': 'Quantum simulator', 'score': 0.6804690361022949}, {'id': 'https://openalex.org/keywords/quantum', 'display_name': 'Quantum', 'score': 0.640444815158844}, {'id': 'https://openalex.org/keywords/flux-qubit', 'display_name': 'Flux qubit', 'score': 0.5601723194122314}, {'id': 'https://openalex.org/keywords/quantum-phase-transition', 'display_name': 'Quantum phase transition', 'score': 0.5584156513214111}, {'id': 'https://openalex.org/keywords/quantum-mechanics', 'display_name': 'Quantum mechanics', 'score': 0.5553017258644104}, {'id': 'https://openalex.org/keywords/ising-model', 'display_name': 'Ising model', 'score': 0.5141342282295227}, {'id': 'https://openalex.org/keywords/quantum-computer', 'display_name': 'Quantum computer', 'score': 0.5096368789672852}, {'id': 'https://openalex.org/keywords/statistical-physics', 'display_name': 'Statistical physics', 'score': 0.4882981777191162}, {'id': 'https://openalex.org/keywords/quantum-system', 'display_name': 'Quantum system', 'score': 0.43224501609802246}, {'id': 'https://openalex.org/keywords/scaling', 'display_name': 'Scaling', 'score': 0.4268786907196045}, {'id': 'https://openalex.org/keywords/thermal-fluctuations', 'display_name': 'Thermal fluctuations', 'score': 0.4231742322444916}, {'id': 'https://openalex.org/keywords/open-quantum-system', 'display_name': 'Open quantum system', 'score': 0.4223310649394989}, {'id': 'https://openalex.org/keywords/condensed-matter-physics', 'display_name': 'Condensed matter physics', 'score': 0.3895549178123474}] | S10: [{'id': 'https://openalex.org/C90408235', 'wikidata': 'https://www.wikidata.org/wiki/Q938141', 'display_name': 'Quantum annealing', 'level': 4, 'score': 0.8873305916786194}, {'id': 'https://openalex.org/C121332964', 'wikidata': 'https://www.wikidata.org/wiki/Q413', 'display_name': 'Physics', 'level': 0, 'score': 0.8853421211242676}, {'id': 'https://openalex.org/C203087015', 'wikidata': 'https://www.wikidata.org/wiki/Q378201', 'display_name': 'Qubit', 'level': 3, 'score': 0.7430634498596191}, {'id': 'https://openalex.org/C161166931', 'wikidata': 'https://www.wikidata.org/wiki/Q7269096', 'display_name': 'Quantum simulator', 'level': 4, 'score': 0.6804690361022949}, {'id': 'https://openalex.org/C84114770', 'wikidata': 'https://www.wikidata.org/wiki/Q46344', 'display_name': 'Quantum', 'level': 2, 'score': 0.640444815158844}, {'id': 'https://openalex.org/C109546105', 'wikidata': 'https://www.wikidata.org/wiki/Q5463032', 'display_name': 'Flux qubit', 'level': 4, 'score': 0.5601723194122314}, {'id': 'https://openalex.org/C72190298', 'wikidata': 'https://www.wikidata.org/wiki/Q2118253', 'display_name': 'Quantum phase transition', 'level': 3, 'score': 0.5584156513214111}, {'id': 'https://openalex.org/C62520636', 'wikidata': 'https://www.wikidata.org/wiki/Q944', 'display_name': 'Quantum mechanics', 'level': 1, 'score': 0.5553017258644104}, {'id': 'https://openalex.org/C51329190', 'wikidata': 'https://www.wikidata.org/wiki/Q1076349', 'display_name': 'Ising model', 'level': 2, 'score': 0.5141342282295227}, {'id': 'https://openalex.org/C58053490', 'wikidata': 'https://www.wikidata.org/wiki/Q176555', 'display_name': 'Quantum computer', 'level': 3, 'score': 0.5096368789672852}, {'id': 'https://openalex.org/C121864883', 'wikidata': 'https://www.wikidata.org/wiki/Q677916', 'display_name': 'Statistical physics', 'level': 1, 'score': 0.4882981777191162}, {'id': 'https://openalex.org/C2778926657', 'wikidata': 'https://www.wikidata.org/wiki/Q944', 'display_name': 'Quantum system', 'level': 3, 'score': 0.43224501609802246}, {'id': 'https://openalex.org/C99844830', 'wikidata': 'https://www.wikidata.org/wiki/Q102441924', 'display_name': 'Scaling', 'level': 2, 'score': 0.4268786907196045}, {'id': 'https://openalex.org/C5637370', 'wikidata': 'https://www.wikidata.org/wiki/Q402478', 'display_name': 'Thermal fluctuations', 'level': 2, 'score': 0.4231742322444916}, {'id': 'https://openalex.org/C190474826', 'wikidata': 'https://www.wikidata.org/wiki/Q2495111', 'display_name': 'Open quantum system', 'level': 3, 'score': 0.4223310649394989}, {'id': 'https://openalex.org/C26873012', 'wikidata': 'https://www.wikidata.org/wiki/Q214781', 'display_name': 'Condensed matter physics', 'level': 1, 'score': 0.3895549178123474}, {'id': 'https://openalex.org/C33923547', 'wikidata': 'https://www.wikidata.org/wiki/Q395', 'display_name': 'Mathematics', 'level': 0, 'score': 0.0}, {'id': 'https://openalex.org/C2524010', 'wikidata': 'https://www.wikidata.org/wiki/Q8087', 'display_name': 'Geometry', 'level': 1, 'score': 0.0}] | T10: [{'id': 'https://metadata.un.org/sdg/11', 'display_name': 'Sustainable cities and communities', 'score': 0.4000000059604645}] | U10: 49
