Workbook

Sheet works2024
A1: id | B1: doi | C1: title | D1: publication_year | E1: publication_date | F1: ids | G1: language | H1: type | I1: countries_distinct_count | J1: institutions_distinct_count | K1: fwci | L1: cited_by_count | M1: citation_normalized_percentile | N1: sustainable_development_goals | O1: counts_by_year
A2: https://openalex.org/W2900744207 | B2: https://doi.org/10.4324/9781003469490-14 | C2: When Social Comparison Goes Awry: The Case of Pluralistic Ignorance | D2: 2024 | E2: 45344 | F2: {'openalex': 'https://openalex.org/W2900744207', 'doi': 'https://doi.org/10.4324/9781003469490-14', 'mag': '2900744207'} | G2: en | H2: book-chapter | I2: 2 | J2: 2 | K2: 149.0051 | L2: 235 | M2: {'value': 0.99980505, 'is_in_top_1_percent': True, 'is_in_top_10_percent': True} | N2: [{'display_name': 'Reduced inequalities', 'id': 'https://metadata.un.org/sdg/10', 'score': 0.7900000214576721}] | O2: [{'year': 2025, 'cited_by_count': 12}, {'year': 2024, 'cited_by_count': 18}, {'year': 2023, 'cited_by_count': 4}, {'year': 2022, 'cited_by_count': 6}, {'year': 2021, 'cited_by_count': 18}, {'year': 2020, 'cited_by_count': 19}, {'year': 2019, 'cited_by_count': 7}, {'year': 2018, 'cited_by_count': 14}, {'year': 2017, 'cited_by_count': 9}, {'year': 2016, 'cited_by_count': 11}, {'year': 2015, 'cited_by_count': 13}, {'year': 2014, 'cited_by_count': 9}, {'year': 2013, 'cited_by_count': 8}, {'year': 2012, 'cited_by_count': 4}]
A3: https://openalex.org/W4402715971 | B3: https://doi.org/10.1109/cvpr52733.2024.01840 | C3: PixelSplat: 3D Gaussian Splats from Image Pairs for Scalable Generalizable 3D Reconstruction | D3: 2024 | E3: 45459 | F3: {'openalex': 'https://openalex.org/W4402715971', 'doi': 'https://doi.org/10.1109/cvpr52733.2024.01840'} | G3: en | H3: article | I3: 2 | J3: 4 | K3: 91.3088 | L3: 142 | M3: {'value': 0.99918467, 'is_in_top_1_percent': True, 'is_in_top_10_percent': True} | N3: [] | O3: [{'year': 2026, 'cited_by_count': 7}, {'year': 2025, 'cited_by_count': 103}, {'year': 2024, 'cited_by_count': 32}]
A4: https://openalex.org/W4392983637 | B4: https://doi.org/10.1016/j.bushor.2024.03.001 | C4: Beware of botshit: How to manage the epistemic risks of generative chatbots | D4: 2024 | E4: 45371 | F4: {'openalex': 'https://openalex.org/W4392983637', 'doi': 'https://doi.org/10.1016/j.bushor.2024.03.001'} | G4: en | H4: article | I4: 3 | J4: 3 | K4: 75.7209 | L4: 93 | M4: {'value': 0.99960221, 'is_in_top_1_percent': True, 'is_in_top_10_percent': True} | N4: [] | O4: [{'year': 2026, 'cited_by_count': 7}, {'year': 2025, 'cited_by_count': 63}, {'year': 2024, 'cited_by_count': 23}]
A5: https://openalex.org/W4392950747 | B5: https://doi.org/10.1016/j.tree.2024.02.004 | C5: Priority effects transcend scales and disciplines in biology | D5: 2024 | E5: 45370 | F5: {'openalex': 'https://openalex.org/W4392950747', 'doi': 'https://doi.org/10.1016/j.tree.2024.02.004', 'pmid': 'https://pubmed.ncbi.nlm.nih.gov/38508922'} | G5: en | H5: article | I5: 6 | J5: 19 | K5: 60.5976 | L5: 52 | M5: {'value': 0.99933431, 'is_in_top_1_percent': True, 'is_in_top_10_percent': True} | N5: [] | O5: [{'year': 2026, 'cited_by_count': 6}, {'year': 2025, 'cited_by_count': 25}, {'year': 2024, 'cited_by_count': 21}]
A6: https://openalex.org/W4401211183 | B6: https://doi.org/10.1126/science.adl2362 | C6: Ecological roles and importance of sharks in the Anthropocene Ocean | D6: 2024 | E6: 45505 | F6: {'openalex': 'https://openalex.org/W4401211183', 'doi': 'https://doi.org/10.1126/science.adl2362', 'pmid': 'https://pubmed.ncbi.nlm.nih.gov/39088608'} | G6: en | H6: review | I6: 8 | J6: 30 | K6: 58.9835 | L6: 83 | M6: {'value': 0.99983356, 'is_in_top_1_percent': True, 'is_in_top_10_percent': True} | N6: [{'display_name': 'Life below water', 'id': 'https://metadata.un.org/sdg/14', 'score': 0.800000011920929}] | O6: [{'year': 2026, 'cited_by_count': 8}, {'year': 2025, 'cited_by_count': 65}, {'year': 2024, 'cited_by_count': 10}]
A7: https://openalex.org/W4398142197 | B7: https://doi.org/10.1080/25741292.2024.2353929 | C7: Calibration and specification in policy practice: Micro-dimensions of policy design | D7: 2024 | E7: 45384 | F7: {'openalex': 'https://openalex.org/W4398142197', 'doi': 'https://doi.org/10.1080/25741292.2024.2353929'} | G7: en | H7: article | I7: 2 | J7: 2 | K7: 57.8277 | L7: 25 | M7: {'value': 0.9989344, 'is_in_top_1_percent': True, 'is_in_top_10_percent': True} | N7: [{'id': 'https://metadata.un.org/sdg/1', 'display_name': 'No poverty', 'score': 0.5600000023841858}] | O7: [{'year': 2026, 'cited_by_count': 2}, {'year': 2025, 'cited_by_count': 20}, {'year': 2024, 'cited_by_count': 3}]
A8: https://openalex.org/W4399666151 | B8: https://doi.org/10.1109/jsac.2024.3414597 | C8: WiShield: Privacy Against Wi-Fi Human Tracking | D8: 2024 | E8: 45457 | F8: {'openalex': 'https://openalex.org/W4399666151', 'doi': 'https://doi.org/10.1109/jsac.2024.3414597'} | G8: en | H8: article | I8: 3 | J8: 8 | K8: 53.6056 | L8: 46 | M8: {'value': 0.99917021, 'is_in_top_1_percent': True, 'is_in_top_10_percent': True} | N8: [] | O8: [{'year': 2026, 'cited_by_count': 1}, {'year': 2025, 'cited_by_count': 44}, {'year': 2024, 'cited_by_count': 1}]
A9: https://openalex.org/W4390658537 | B9: https://doi.org/10.1332/030557321x16841388707452 | C9: Types of learning and varieties of innovation: how does policy learning enable policy innovation? | D9: 2024 | E9: 45299 | F9: {'openalex': 'https://openalex.org/W4390658537', 'doi': 'https://doi.org/10.1332/030557321x16841388707452'} | G9: en | H9: article | I9: 2 | J9: 2 | K9: 50.7781 | L9: 22 | M9: {'value': 0.99851606, 'is_in_top_1_percent': True, 'is_in_top_10_percent': True} | N9: [] | O9: [{'year': 2025, 'cited_by_count': 10}, {'year': 2024, 'cited_by_count': 12}]
A10: https://openalex.org/W4403897136 | B10: https://doi.org/10.1016/j.jcyt.2024.10.008 | C10: Delphi-driven consensus definition for mesenchymal stromal cells and clinical reporting guidelines for mesenchymal stromal cellâ€“based therapeutics | D10: 2024 | E10: 45595 | F10: {'openalex': 'https://openalex.org/W4403897136', 'doi': 'https://doi.org/10.1016/j.jcyt.2024.10.008', 'pmid': 'https://pubmed.ncbi.nlm.nih.gov/39580717'} | G10: en | H10: article | I10: 3 | J10: 24 | K10: 50.1096 | L10: 43 | M10: {'value': 0.99903708, 'is_in_top_1_percent': True, 'is_in_top_10_percent': True} | N10: [] | O10: [{'year': 2026, 'cited_by_count': 6}, {'year': 2025, 'cited_by_count': 37}]
A11: https://openalex.org/W4390718539 | B11: https://doi.org/10.1136/bmj-2023-076336 | C11: Effect of Risk Mitigation Guidance for opioid and stimulant dispensations on mortality and acute care visits during dual public health emergencies: retrospective cohort study | D11: 2024 | E11: 45301 | F11: {'openalex': 'https://openalex.org/W4390718539', 'doi': 'https://doi.org/10.1136/bmj-2023-076336', 'pmid': 'https://pubmed.ncbi.nlm.nih.gov/38199614'} | G11: en | H11: article | I11: 1 | J11: 12 | K11: 47.3804 | L11: 83 | M11: {'value': 0.99942541, 'is_in_top_1_percent': True, 'is_in_top_10_percent': True} | N11: [{'display_name': 'Good health and well-being', 'id': 'https://metadata.un.org/sdg/3', 'score': 0.8799999952316284}] | O11: [{'year': 2026, 'cited_by_count': 4}, {'year': 2025, 'cited_by_count': 42}, {'year': 2024, 'cited_by_count': 37}]
A12: https://openalex.org/W4402742293 | B12: https://doi.org/10.1109/comst.2024.3465447 | C12: Large Language Model (LLM) for Telecommunications: A Comprehensive Survey on Principles, Key Techniques, and Opportunities | D12: 2024 | E12: 45558 | F12: {'openalex': 'https://openalex.org/W4402742293', 'doi': 'https://doi.org/10.1109/comst.2024.3465447'} | G12: en | H12: article | I12: 2 | J12: 14 | K12: 46.9178 | L12: 129 | M12: {'value': 0.99899925, 'is_in_top_1_percent': True, 'is_in_top_10_percent': True} | N12: [] | O12: [{'year': 2026, 'cited_by_count': 11}, {'year': 2025, 'cited_by_count': 97}, {'year': 2024, 'cited_by_count': 21}]
A13: https://openalex.org/W4403842396 | B13: https://doi.org/10.1007/978-3-031-72640-8_10 | C13: MVDiffusion++: A Dense High-Resolution Multi-view Diffusion Model forÂ Single orÂ Sparse-View 3D Object Reconstruction | D13: 2024 | E13: 45593 | F13: {'openalex': 'https://openalex.org/W4403842396', 'doi': 'https://doi.org/10.1007/978-3-031-72640-8_10'} | G13: en | H13: book-chapter | I13: 2 | J13: 9 | K13: 44.785 | L13: 19 | M13: {'value': 0.99767225, 'is_in_top_1_percent': True, 'is_in_top_10_percent': True} | N13: [] | O13: [{'year': 2026, 'cited_by_count': 1}, {'year': 2025, 'cited_by_count': 14}, {'year': 2024, 'cited_by_count': 4}]
... A122: https://openalex.org/W4398236701 | B122: https://doi.org/10.1017/aaq.2024.26 | C122: LÃ­Äºwat Climbers Could See the Ocean from the Peak of QáºƒelqáºƒelÃºsten: Evaluating Oral Traditions with Viewshed Analyses from the Mount Meager Volcanic Complex Prior to Its 2360 BP Eruption | D122: 2024 | E122: 45435 | F122: {'openalex': 'https://openalex.org/W4398236701', 'doi': 'https://doi.org/10.1017/aaq.2024.26'} | G122: en | H122: article | I122: 1 | J122: 5 | K122: 11.9466 | L122: 7 | M122: {'value': 0.98008795, 'is_in_top_1_percent': False, 'is_in_top_10_percent': True} | N122: [{'id': 'https://metadata.un.org/sdg/14', 'score': 0.8700000047683716, 'display_name': 'Life below water'}] | O122: [{'year': 2026, 'cited_by_count': 1}, {'year': 2025, 'cited_by_count': 5}, {'year': 2024, 'cited_by_count': 1}]
A123: https://openalex.org/W4393072836 | B123: https://doi.org/10.1111/sjtg.12539 | C123: Guest Editorial: The social life of Chinese infrastructures in Southeast Asia | D123: 2024 | E123: 45373 | F123: {'openalex': 'https://openalex.org/W4393072836', 'doi': 'https://doi.org/10.1111/sjtg.12539'} | G123: en | H123: editorial | I123: 2 | J123: 2 | K123: 11.940961 | L123: 3 | M123: {'value': 0.9622204, 'is_in_top_1_percent': False, 'is_in_top_10_percent': True} | N123: [{'display_name': 'Industry, innovation and infrastructure', 'id': 'https://metadata.un.org/sdg/9', 'score': 0.5400000214576721}]
A124: https://openalex.org/W4399575743 | B124: https://doi.org/10.1371/journal.pone.0301775 | C124: Agropastoral and dietary practices of the northern Levant facing Late Holocene climate and environmental change: Isotopic analysis of plants, animals and humans from Bronze to Iron Age Tell Tweini | D124: 2024 | E124: 45455 | F124: {'openalex': 'https://openalex.org/W4399575743', 'doi': 'https://doi.org/10.1371/journal.pone.0301775', 'pmid': 'https://pubmed.ncbi.nlm.nih.gov/38865323'} | G124: en | H124: article | I124: 3 | J124: 8 | K124: 11.9315 | L124: 7 | M124: {'value': 0.98033421, 'is_in_top_1_percent': False, 'is_in_top_10_percent': True} | N124: [{'display_name': 'Life below water', 'id': 'https://metadata.un.org/sdg/14', 'score': 0.6700000166893005}] | O124: [{'year': 2025, 'cited_by_count': 6}, {'year': 2024, 'cited_by_count': 1}]
A125: https://openalex.org/W4403650529 | B125: https://doi.org/10.1007/978-3-031-72390-2_33 | C125: TrIND: Representing Anatomical Trees byÂ Denoising Diffusion ofÂ Implicit Neural Fields | D125: 2024 | E125: 45292 | F125: {'openalex': 'https://openalex.org/W4403650529', 'doi': 'https://doi.org/10.1007/978-3-031-72390-2_33'} | G125: en | H125: book-chapter | I125: 1 | J125: 2 | K125: 11.7855 | L125: 5 | M125: {'value': 0.98277467, 'is_in_top_1_percent': False, 'is_in_top_10_percent': True} | N125: [] | O125: [{'year': 2025, 'cited_by_count': 5}]
A126: https://openalex.org/W4402490890 | B126: https://doi.org/10.1017/s0266078424000075 | C126: English-medium education and the perpetuation of girlsâ€™ disadvantage | D126: 2024 | E126: 45536 | F126: {'openalex': 'https://openalex.org/W4402490890', 'doi': 'https://doi.org/10.1017/s0266078424000075'} | G126: en | H126: article | I126: 5 | J126: 11 | K126: 11.6751 | L126: 3 | M126: {'value': 0.98029815, 'is_in_top_1_percent': False, 'is_in_top_10_percent': True} | N126: [{'score': 0.46000000834465027, 'id': 'https://metadata.un.org/sdg/5', 'display_name': 'Gender equality'}] | O126: [{'year': 2025, 'cited_by_count': 3}]
A127: https://openalex.org/W4405178229 | B127: https://doi.org/10.1073/pnas.2404632121 | C127: Early human collective practices and symbolism in the Early Upper Paleolithic of Southwest Asia | D127: 2024 | E127: 45635 | F127: {'openalex': 'https://openalex.org/W4405178229', 'doi': 'https://doi.org/10.1073/pnas.2404632121', 'pmid': 'https://pubmed.ncbi.nlm.nih.gov/39652761'} | G127: en | H127: article | I127: 6 | J127: 26 | K127: 11.6476 | L127: 3 | M127: {'value': 0.98186022, 'is_in_top_1_percent': False, 'is_in_top_10_percent': True} | N127: [] | O127: [{'year': 2025, 'cited_by_count': 3}]
A128: https://openalex.org/W4399031176 | B128: https://doi.org/10.1007/978-3-031-61175-9_1 | C128: Disentangling the Problem Space: A Validated Problem Statement for Sustainability Support Systems | D128: 2024 | E128: 45292 | F128: {'openalex': 'https://openalex.org/W4399031176', 'doi': 'https://doi.org/10.1007/978-3-031-61175-9_1'} | G128: en | H128: book-chapter | I128: 2 | J128: 4 | K128: 11.6162 | L128: 4 | M128: {'value': 0.98370237, 'is_in_top_1_percent': False, 'is_in_top_10_percent': True} | N128: [{'score': 0.41999998688697815, 'id': 'https://metadata.un.org/sdg/12', 'display_name': 'Responsible consumption and production'}] | O128: [{'year': 2025, 'cited_by_count': 3}, {'year': 2024, 'cited_by_count': 1}]
A129: https://openalex.org/W4405097124 | B129: https://doi.org/10.1016/j.ijcci.2024.100708 | C129: Critical Artificial Intelligence literacy: A scoping review and framework synthesis | D129: 2024 | E129: 45632 | F129: {'openalex': 'https://openalex.org/W4405097124', 'doi': 'https://doi.org/10.1016/j.ijcci.2024.100708'} | G129: en | H129: review | I129: 1 | J129: 4 | K129: 11.6114 | L129: 27 | M129: {'value': 0.98522969, 'is_in_top_1_percent': False, 'is_in_top_10_percent': True} | N129: [{'score': 0.8799999952316284, 'id': 'https://metadata.un.org/sdg/4', 'display_name': 'Quality Education'}] | O129: [{'year': 2026, 'cited_by_count': 1}, {'year': 2025, 'cited_by_count': 25}, {'year': 2024, 'cited_by_count': 1}]
A130: https://openalex.org/W4401705192 | B130: https://doi.org/10.1057/s41267-024-00721-7 | C130: Techno-nationalism and cross-border acquisitions in an age of geopolitical rivalry | D130: 2024 | E130: 45523 | F130: {'openalex': 'https://openalex.org/W4401705192', 'doi': 'https://doi.org/10.1057/s41267-024-00721-7'} | G130: en | H130: article | I130: 1 | J130: 4 | K130: 11.5663 | L130: 20 | M130: {'value': 0.98359626, 'is_in_top_1_percent': False, 'is_in_top_10_percent': True} | N130: [] | O130: [{'year': 2026, 'cited_by_count': 7}, {'year': 2025, 'cited_by_count': 13}]
A131: https://openalex.org/W4399640511 | B131: https://doi.org/10.1007/s10567-024-00490-7 | C131: What is Parental Monitoring? | D131: 2024 | E131: 45444 | F131: {'openalex': 'https://openalex.org/W4399640511', 'doi': 'https://doi.org/10.1007/s10567-024-00490-7', 'pmid': 'https://pubmed.ncbi.nlm.nih.gov/38869680'} | G131: en | H131: review | I131: 2 | J131: 12 | K131: 11.5102 | L131: 17 | M131: {'value': 0.98990633, 'is_in_top_1_percent': False, 'is_in_top_10_percent': True} | N131: [] | O131: [{'year': 2025, 'cited_by_count': 10}, {'year': 2024, 'cited_by_count': 7}]
A132: https://openalex.org/W4393316810 | B132: https://doi.org/10.1111/jopy.12929 | C132: Diversity in singlehood experiences: Testing an attachment theory model of subâ€groups of singles | D132: 2024 | E132: 45380 | F132: {'openalex': 'https://openalex.org/W4393316810', 'doi': 'https://doi.org/10.1111/jopy.12929', 'pmid': 'https://pubmed.ncbi.nlm.nih.gov/38549507'} | G132: en | H132: article | I132: 2 | J132: 4 | K132: 11.4547 | L132: 17 | M132: {'value': 0.98802159, 'is_in_top_1_percent': False, 'is_in_top_10_percent': True} | N132: [{'id': 'https://metadata.un.org/sdg/10', 'display_name': 'Reduced inequalities', 'score': 0.5799999833106995}] | O132: [{'year': 2026, 'cited_by_count': 1}, {'year': 2025, 'cited_by_count': 12}, {'year': 2024, 'cited_by_count': 4}]
A133: https://openalex.org/W4401883861 | B133: https://doi.org/10.1108/edi-10-2023-0335 | C133: Beyond the resume: HR studentsâ€™ evaluations of interview performances by first and second language speakers | D133: 2024 | E133: 45530 | F133: {'openalex': 'https://openalex.org/W4401883861', 'doi': 'https://doi.org/10.1108/edi-10-2023-0335'} | G133: en | H133: article | I133: 2 | J133: 5 | K133: 11.452 | L133: 4 | M133: {'value': 0.98349291, 'is_in_top_1_percent': False, 'is_in_top_10_percent': True} | N133: [{'score': 0.5699999928474426, 'display_name': 'Reduced inequalities', 'id': 'https://metadata.un.org/sdg/10'}] | O133: [{'year': 2026, 'cited_by_count': 1}, {'year': 2025, 'cited_by_count': 1}, {'year': 2024, 'cited_by_count': 2}]
A134: https://openalex.org/W4402266216 | B134: https://doi.org/10.1371/journal.pone.0306813 | C134: Overfishing and climate change elevate extinction risk of endemic sharks and rays in the southwest Indian Ocean hotspot | D134: 2024 | E134: 45540 | F134: {'openalex': 'https://openalex.org/W4402266216', 'doi': 'https://doi.org/10.1371/journal.pone.0306813', 'pmid': 'https://pubmed.ncbi.nlm.nih.gov/39236015'} | G134: en | H134: article | I134: 7 | J134: 20 | K134: 11.3927 | L134: 17 | M134: {'value': 0.98976365, 'is_in_top_1_percent': False, 'is_in_top_10_percent': True} | N134: [] | O134: [{'year': 2026, 'cited_by_count': 3}, {'year': 2025, 'cited_by_count': 13}, {'year': 2023, 'cited_by_count': 1}]
A135: https://openalex.org/W4399366865 | B135: https://doi.org/10.1016/j.cub.2024.05.019 | C135: Maternal investment evolves with larger body size and higher diversification rate in sharks and rays | D135: 2024 | E135: 45444 | F135: {'openalex': 'https://openalex.org/W4399366865', 'doi': 'https://doi.org/10.1016/j.cub.2024.05.019'} | G135: en | H135: article | I135: 2 | J135: 4 | K135: 11.3703 | L135: 18 | M135: {'value': 0.98951442, 'is_in_top_1_percent': False, 'is_in_top_10_percent': True} | N135: [] | O135: [{'year': 2026, 'cited_by_count': 1}, {'year': 2025, 'cited_by_count': 12}, {'year': 2024, 'cited_by_count': 3}, {'year': 2023, 'cited_by_count': 1}, {'year': 2022, 'cited_by_count': 1}]
... A2128: https://openalex.org/W4392093461 | B2128: https://doi.org/10.1139/cjfas-2023-0306 | C2128: Forestry and stream temperatures: a response to comment by R.D. Moore | D2128: 2024 | E2128: 45345 | F2128: {'openalex': 'https://openalex.org/W4392093461', 'doi': 'https://doi.org/10.1139/cjfas-2023-0306'} | G2128: en | H2128: article | I2128: 1 | J2128: 4 | K2128: 0 | L2128: 0 | M2128: {'value': 0.01542486, 'is_in_top_1_percent': False, 'is_in_top_10_percent': False} | N2128: [{'display_name': 'Life in Land', 'id': 'https://metadata.un.org/sdg/15', 'score': 0.46000000834465027}] | O2128: []
A2129: https://openalex.org/W4392094683 | B2129: https://doi.org/10.1016/j.psyneuen.2023.106846 | C2129: =- Beyond the limited evidence for an association between childhood maltreatment and DNA methylation: the moderating role of genetic sensitivity to the environment -> #NAME? | D2129: 2024 | E2129: 45323 | F2129: {'openalex': 'https://openalex.org/W4392094683', 'doi': 'https://doi.org/10.1016/j.psyneuen.2023.106846'} | G2129: en | H2129: article | I2129: 1 | J2129: 10 | K2129: 0 | L2129: 0 | M2129: {'value': 0.02909351, 'is_in_top_1_percent': False, 'is_in_top_10_percent': False} | N2129: [] | O2129: []
A2130: https://openalex.org/W4392112157 | B2130: https://doi.org/10.1016/j.psyneuen.2023.106844 | C2130: =- Sensitization Effect of Perinatal Adversity on the association between Cumulative childhood and Adolescence Adversity and a Polyepigenetic Stress Score at the End of Adolescence: a Prospective Study -> #NAME? | D2130: 2024 | E2130: 45323 | F2130: {'openalex': 'https://openalex.org/W4392112157', 'doi': 'https://doi.org/10.1016/j.psyneuen.2023.106844'} | G2130: en | H2130: article | I2130: 1 | J2130: 1 | K2130: 0 | L2130: 0 | M2130: {'value': 0.03200094, 'is_in_top_1_percent': False, 'is_in_top_10_percent': False} | N2130: [] | O2130: []
A2131: https://openalex.org/W4392121382 | B2131: https://doi.org/10.1016/j.psyneuen.2023.106913 | C2131: Sensitization Effect of Perinatal Adversity on the Association Between Cumulative Childhood and Adolescence Adversity and a Polyepigenetic Stress Score at the End of Adolescence: A Prospective Study | D2131: 2024 | E2131: 45323 | F2131: {'openalex': 'https://openalex.org/W4392121382', 'doi': 'https://doi.org/10.1016/j.psyneuen.2023.106913'} | G2131: en | H2131: article | I2131: 1 | J2131: 5 | K2131: 0 | L2131: 0 | M2131: {'value': 0.0304958, 'is_in_top_1_percent': False, 'is_in_top_10_percent': False} | N2131: [] | O2131: []
A2132: https://openalex.org/W4392155912 | B2132: https://doi.org/10.54210/bj.2024.1110 | C2132: Good (virtual) grief: The potential of online communities for bereaved older adults during Covid-19 | D2132: 2024 | E2132: 45344 | F2132: {'openalex': 'https://openalex.org/W4392155912', 'doi': 'https://doi.org/10.54210/bj.2024.1110'} | G2132: en | H2132: article | I2132: 1 | J2132: 2 | K2132: 0 | L2132: 0 | M2132: {'value': 0.03065205, 'is_in_top_1_percent': False, 'is_in_top_10_percent': False} | N2132: [] | O2132: []
A2133: https://openalex.org/W4392169274 | B2133: https://doi.org/10.1103/physrevresearch.6.013204 | C2133: Characterization and optimized engineering of bosonic quantum interfaces under single-mode operational constraints | D2133: 2024 | E2133: 45348 | F2133: {'openalex': 'https://openalex.org/W4392169274', 'doi': 'https://doi.org/10.1103/physrevresearch.6.013204'} | G2133: en | H2133: article | I2133: 2 | J2133: 3 | K2133: 0 | L2133: 0 | M2133: {'value': 0.01505652, 'is_in_top_1_percent': False, 'is_in_top_10_percent': False} | N2133: [] | O2133: []
A2134: https://openalex.org/W4392174233 | B2134: https://doi.org/10.1007/978-981-97-0523-8_54 | C2134: Analysis and Forecast of USD/EUR Exchange Rate Based on ARIMA and GARCH Models | D2134: 2024 | E2134: 45292 | F2134: {'openalex': 'https://openalex.org/W4392174233', 'doi': 'https://doi.org/10.1007/978-981-97-0523-8_54'} | G2134: en | H2134: book-chapter | I2134: 3 | J2134: 3 | K2134: 0 | L2134: 0 | M2134: {'value': 0.08225806, 'is_in_top_1_percent': False, 'is_in_top_10_percent': False} | N2134: [] | O2134: []
A2135: https://openalex.org/W4392294111 | B2135: https://doi.org/10.1177/02697580241232436 | C2135: Towards a multifactorial framework of the Romaâ€™s victimisation: Discrimination, risky situations, and acceptance of violence as correlates of physical assault and harassment | D2135: 2024 | E2135: 45351 | F2135: {'openalex': 'https://openalex.org/W4392294111', 'doi': 'https://doi.org/10.1177/02697580241232436'} | G2135: en | H2135: article | I2135: 3 | J2135: 4 | K2135: 0 | L2135: 0 | M2135: {'value': 0.04142418, 'is_in_top_1_percent': False, 'is_in_top_10_percent': False} | N2135: [{'display_name': 'Peace, Justice and strong institutions', 'id': 'https://metadata.un.org/sdg/16', 'score': 0.5799999833106995}] | O2135: []
A2136: https://openalex.org/W4392295921 | B2136: https://doi.org/10.1037/tmb0000125.supp | C2136: Supplemental Material for Smartphones Undermine Social Connectedness More in Men Than Women: A Mini Mega-Analysis | D2136: 2024 | E2136: 45292 | F2136: {'openalex': 'https://openalex.org/W4392295921', 'doi': 'https://doi.org/10.1037/tmb0000125.supp'} | G2136: en | H2136: article | I2136: 2 | J2136: 3 | K2136: 0 | L2136: 0 | M2136: {'value': 0.03358903, 'is_in_top_1_percent': False, 'is_in_top_10_percent': False} | N2136: [{'display_name': 'Gender equality', 'id': 'https://metadata.un.org/sdg/5', 'score': 0.4399999976158142}] | O2136: []
A2137: https://openalex.org/W4392305793 | B2137: https://doi.org/10.5220/0012351300003654 | C2137: Military Badge Detection and Classification Algorithm for Automatic Processing of Documents | D2137: 2024 | E2137: 45292 | F2137: {'openalex': 'https://openalex.org/W4392305793', 'doi': 'https://doi.org/10.5220/0012351300003654'} | G2137: en | H2137: article | I2137: 1 | J2137: 3 | K2137: 0 | L2137: 0 | M2137: {'value': 0.02603913, 'is_in_top_1_percent': False, 'is_in_top_10_percent': False} | N2137: [] | O2137: []
A2138: https://openalex.org/W4392342931 | B2138: https://doi.org/10.18806/tesl.v40i1/1384 | C2138: Multisemiotics, Race, and Academic Literacies | D2138: 2024 | E2138: 45354 | F2138: {'openalex': 'https://openalex.org/W4392342931', 'doi': 'https://doi.org/10.18806/tesl.v40i1/1384'} | G2138: en | H2138: article | I2138: 1 | J2138: 2 | K2138: 0 | L2138: 0 | M2138: {'value': 0.02790536, 'is_in_top_1_percent': False, 'is_in_top_10_percent': False} | N2138: [{'display_name': 'Quality Education', 'id': 'https://metadata.un.org/sdg/4', 'score': 0.8500000238418579}] | O2138: []
A2139: https://openalex.org/W4392343223 | B2139: https://doi.org/10.18806/tesl.v40i1/1381 | C2139: Second Language Writing in Canada | D2139: 2024 | E2139: 45354 | F2139: {'openalex': 'https://openalex.org/W4392343223', 'doi': 'https://doi.org/10.18806/tesl.v40i1/1381'} | G2139: en | H2139: article | I2139: 1 | J2139: 3 | K2139: 0 | L2139: 0 | M2139: {'value': 0.03112805, 'is_in_top_1_percent': False, 'is_in_top_10_percent': False} | N2139: [{'display_name': 'Quality Education', 'id': 'https://metadata.un.org/sdg/4', 'score': 0.8700000047683716}] | O2139: []
A2140: https://openalex.org/W4392351102 | B2140: https://doi.org/10.1038/s44183-024-00051-z | C2140: Author Correction: Targeting ocean conservation outcomes through threat reduction | D2140: 2024 | E2140: 45353 | F2140: {'openalex': 'https://openalex.org/W4392351102', 'doi': 'https://doi.org/10.1038/s44183-024-00051-z'} | G2140: en | H2140: article | I2140: 7 | J2140: 14 | K2140: 0 | L2140: 0 | M2140: {'value': 0.02982918, 'is_in_top_1_percent': False, 'is_in_top_10_percent': False} | N2140: [{'display_name': 'Life below water', 'id': 'https://metadata.un.org/sdg/14', 'score': 0.49000000953674316}] | O2140: []
A2141: https://openalex.org/W4392376677 | B2141: https://doi.org/10.1002/jqs.3612 | C2141: Mechanism of organic matter enrichment in a basin with shallow biogenic gas: a case study of Pleistocene shale in the Qaidam Basin | D2141: 2024 | E2141: 45355 | F2141: {'openalex': 'https://openalex.org/W4392376677', 'doi': 'https://doi.org/10.1002/jqs.3612'} | G2141: en | H2141: article | I2141: 2 | J2141: 5 | K2141: 0 | L2141: 0 | M2141: {'value': 0.02367208, 'is_in_top_1_percent': False, 'is_in_top_10_percent': False} | N2141: [] | O2141: []
A2142: https://openalex.org/W4392389479 | B2142: https://doi.org/10.1002/vjch.202300222 | C2142: Potential oxidoreductases inhibitors from medicinal plantsâ€basedÂ phytochemicals: A review | D2142: 2024 | E2142: 45342 | F2142: {'openalex': 'https://openalex.org/W4392389479', 'doi': 'https://doi.org/10.1002/vjch.202300222'} | G2142: en | H2142: review | I2142: 3 | J2142: 4 | K2142: 0 | L2142: 0 | M2142: {'value': 0.0304798, 'is_in_top_1_percent': False, 'is_in_top_10_percent': False} | N2142: [{'display_name': 'Good health and well-being', 'id': 'https://metadata.un.org/sdg/3', 'score': 0.5400000214576721}] | O2142: []
... A2702: https://openalex.org/W4403398874 | B2702: https://doi.org/10.3390/molecules29204870 | C2702: Mechanism-Based Allylic Carbasugar Chlorides That Form Covalent Intermediates with Î±- and Î²-Galactosidases | D2702: 2024 | E2702: 45579 | F2702: {'openalex': 'https://openalex.org/W4403398874', 'doi': 'https://doi.org/10.3390/molecules29204870', 'pmid': 'https://pubmed.ncbi.nlm.nih.gov/39459237'} | G2702: en | H2702: article | I2702: 1 | J2702: 3 | K2702: 0 | L2702: 0 | M2702: {'value': 0.11615406, 'is_in_top_1_percent': False, 'is_in_top_10_percent': False} | N2702: [] | O2702: []
A2703: https://openalex.org/W4403405905 | C2703: The doctor will polygraph you now: ethical concerns with AI for fact-checking patients. | D2703: 2024 | E2703: 45607 | F2703: {'openalex': 'https://openalex.org/W4403405905', 'pmid': 'https://pubmed.ncbi.nlm.nih.gov/39398216'} | G2703: en | H2703: preprint | I2703: 3 | J2703: 13 | K2703: 0 | L2703: 0 | M2703: {'value': 0.13399263, 'is_in_top_1_percent': False, 'is_in_top_10_percent': False} | N2703: [] | O2703: []
A2704: https://openalex.org/W4403425141 | B2704: https://doi.org/10.1007/s00012-024-00874-4 | C2704: Graphs of finite algebras: maximality, rectangularity, and decomposition | D2704: 2024 | E2704: 45580 | F2704: {'openalex': 'https://openalex.org/W4403425141', 'doi': 'https://doi.org/10.1007/s00012-024-00874-4'} | G2704: en | H2704: article | I2704: 1 | J2704: 1 | K2704: 0 | L2704: 0 | M2704: {'value': 0.21871319, 'is_in_top_1_percent': False, 'is_in_top_10_percent': False} | N2704: [] | O2704: []
A2705: https://openalex.org/W4403433757 | B2705: https://doi.org/10.1002/pra2.1089 | C2705: Roles and Responsibilities in Universityâ€Community Engagement for Library and Information Scientists | D2705: 2024 | E2705: 45566 | F2705: {'openalex': 'https://openalex.org/W4403433757', 'doi': 'https://doi.org/10.1002/pra2.1089'} | G2705: en | H2705: article | I2705: 1 | J2705: 7 | K2705: 0 | L2705: 0 | M2705: {'value': 0.24997606, 'is_in_top_1_percent': False, 'is_in_top_10_percent': False} | N2705: [] | O2705: []
A2706: https://openalex.org/W4403449299 | B2706: https://doi.org/10.1130/abs/2024cd-399725 | C2706: <b>NEW CONSTRAINTS FROM THE CHALLIS-KAMLOOPS GROUP ON CRUSTAL EVOLUTION DURING EARLY EOCENE EXTENSION IN SOUTHEASTERN BRITISH COLUMBIA AND NORTHEASTERN WASHINGTON</b><sup/> | D2706: 2024 | E2706: 45292 | F2706: {'openalex': 'https://openalex.org/W4403449299', 'doi': 'https://doi.org/10.1130/abs/2024cd-399725'} | G2706: en | H2706: article | I2706: 3 | J2706: 5 | K2706: 0 | L2706: 0 | M2706: {'value': 0.16484688, 'is_in_top_1_percent': False, 'is_in_top_10_percent': False} | N2706: [{'score': 0.699999988079071, 'id': 'https://metadata.un.org/sdg/14', 'display_name': 'Life below water'}] | O2706: []
A2707: https://openalex.org/W4403456360 | B2707: https://doi.org/10.1785/0220240082 | C2707: Investigating 10 Yr of Volcanoacoustic Activity at Tungurahua Volcano, Ecuador, Aided by Machine Learning | D2707: 2024 | E2707: 45581 | F2707: {'openalex': 'https://openalex.org/W4403456360', 'doi': 'https://doi.org/10.1785/0220240082'} | G2707: en | H2707: article | I2707: 2 | J2707: 4 | K2707: 0 | L2707: 0 | M2707: {'value': 0.15501349, 'is_in_top_1_percent': False, 'is_in_top_10_percent': False} | N2707: [{'score': 0.6200000047683716, 'id': 'https://metadata.un.org/sdg/16', 'display_name': 'Peace, Justice and strong institutions'}] | O2707: []
A2708: https://openalex.org/W4403484384 | B2708: https://doi.org/10.1002/ange.202409309 | C2708: Reply to the Correspondence on â€œVisible Lightâ€Switchable Chalconeâ€Flavylium Photochromic Systems in Aqueous Mediaâ€ | D2708: 2024 | E2708: 45582 | F2708: {'openalex': 'https://openalex.org/W4403484384', 'doi': 'https://doi.org/10.1002/ange.202409309'} | G2708: en | H2708: article | I2708: 2 | J2708: 3 | K2708: 0 | L2708: 0 | M2708: {'value': 0.11066934, 'is_in_top_1_percent': False, 'is_in_top_10_percent': False} | N2708: [] | O2708: []
A2709: https://openalex.org/W4403485043 | B2709: https://doi.org/10.1002/anie.202409309 | C2709: Reply to the Correspondence on â€œVisible Lightâ€Switchable Chalconeâ€Flavylium Photochromic Systems in Aqueous Mediaâ€ | D2709: 2024 | E2709: 45582 | F2709: {'openalex': 'https://openalex.org/W4403485043', 'doi': 'https://doi.org/10.1002/anie.202409309', 'pmid': 'https://pubmed.ncbi.nlm.nih.gov/39417825'} | G2709: en | H2709: letter | I2709: 2 | J2709: 3 | K2709: 0 | L2709: 0 | M2709: {'value': 0.114366, 'is_in_top_1_percent': False, 'is_in_top_10_percent': False} | N2709: [] | O2709: []
A2710: https://openalex.org/W4403486965 | B2710: https://doi.org/10.1115/1.4066889 | C2710: Design, Analysis, and Testing of an Additively Manufactured Catalytic Combustor for a Micro-Wave Rotor Turbine | D2710: 2024 | E2710: 45582 | F2710: {'openalex': 'https://openalex.org/W4403486965', 'doi': 'https://doi.org/10.1115/1.4066889'} | G2710: en | H2710: article | I2710: 3 | J2710: 4 | K2710: 0 | L2710: 0 | M2710: {'value': 0.20210283, 'is_in_top_1_percent': False, 'is_in_top_10_percent': False} | N2710: [{'score': 0.800000011920929, 'id': 'https://metadata.un.org/sdg/7', 'display_name': 'Affordable and clean energy'}] | O2710: []
A2711: https://openalex.org/W4403486988 | B2711: https://doi.org/10.3233/faia240856 | C2711: Deep Generative Models for Subgraph Prediction | D2711: 2024 | E2711: 45581 | F2711: {'openalex': 'https://openalex.org/W4403486988', 'doi': 'https://doi.org/10.3233/faia240856'} | G2711: en | H2711: book-chapter | I2711: 1 | J2711: 4 | K2711: 0 | L2711: 0 | M2711: {'value': 0.38983673, 'is_in_top_1_percent': False, 'is_in_top_10_percent': False} | N2711: [] | O2711: []
A2712: https://openalex.org/W4403497064 | B2712: https://doi.org/10.1017/s1365100524000579 | C2712: A note on allowing state bankruptcy | D2712: 2024 | E2712: 45582 | F2712: {'openalex': 'https://openalex.org/W4403497064', 'doi': 'https://doi.org/10.1017/s1365100524000579'} | G2712: en | H2712: article | I2712: 1 | J2712: 1 | K2712: 0 | L2712: 0 | M2712: {'value': 0.2768854, 'is_in_top_1_percent': False, 'is_in_top_10_percent': False} | N2712: [{'score': 0.5099999904632568, 'id': 'https://metadata.un.org/sdg/8', 'display_name': 'Decent work and economic growth'}] | O2712: []
A2713: https://openalex.org/W4403514838 | B2713: https://doi.org/10.1016/j.thromres.2024.109161 | C2713: Scoping review of current evidence on the incidence of Venous thromboembolism (VTE) in the East Asian population | D2713: 2024 | E2713: 45566 | F2713: {'openalex': 'https://openalex.org/W4403514838', 'doi': 'https://doi.org/10.1016/j.thromres.2024.109161'} | G2713: en | H2713: article | I2713: 1 | J2713: 1 | K2713: 0 | L2713: 0 | M2713: {'value': 0.36298119, 'is_in_top_1_percent': False, 'is_in_top_10_percent': False} | N2713: [{'score': 0.6000000238418579, 'id': 'https://metadata.un.org/sdg/2', 'display_name': 'Zero hunger'}] | O2713: []
A2714: https://openalex.org/W4403530749 | B2714: https://doi.org/10.1145/3686169.3686208 | C2714: Making Space for Poems: An Invitation to More-than-Human Design | D2714: 2024 | E2714: 45583 | F2714: {'openalex': 'https://openalex.org/W4403530749', 'doi': 'https://doi.org/10.1145/3686169.3686208'} | G2714: en | H2714: article | I2714: 1 | J2714: 1 | K2714: 0 | L2714: 0 | M2714: {'value': 0.18308145, 'is_in_top_1_percent': False, 'is_in_top_10_percent': False} | N2714: [] | O2714: []
A2715: https://openalex.org/W4403541206 | B2715: https://doi.org/10.1080/15381501.2024.2413497 | C2715: â€œTears turning to diamonds:â€ creating empathic understanding toward women living with HIV through contemplative viewing of a virtual art exhibition | D2715: 2024 | E2715: 45583 | F2715: {'openalex': 'https://openalex.org/W4403541206', 'doi': 'https://doi.org/10.1080/15381501.2024.2413497'} | G2715: en | H2715: article | I2715: 6 | J2715: 11 | K2715: 0 | L2715: 0 | M2715: {'value': 0.28819407, 'is_in_top_1_percent': False, 'is_in_top_10_percent': False} | N2715: [{'score': 0.7300000190734863, 'id': 'https://metadata.un.org/sdg/5', 'display_name': 'Gender equality'}] | O2715: []
... A2725: https://openalex.org/W4403709511 | B2725: https://doi.org/10.24135/dcj.v6i2.33 | C2725: The Garrison and the Jamaican State: A Model for Co-optation | D2725: 2024 | E2725: 45589 | F2725: {'openalex': 'https://openalex.org/W4403709511', 'doi': 'https://doi.org/10.24135/dcj.v6i2.33'} | G2725: en | H2725: article | I2725: 1 | J2725: 1 | K2725: 0 | L2725: 0 | M2725: {'value': 0.29330177, 'is_in_top_1_percent': False, 'is_in_top_10_percent': False} | N2725: [] | O2725: []
A2726: https://openalex.org/W4403710011 | C2726: Palaeoecological reconstructions of Subboreal northwestern European wild horses, Equus ferus Boddaert, 1785. | D2726: 2024 | E2726: 45323 | F2726: {'openalex': 'https://openalex.org/W4403710011'} | G2726: en | H2726: article | I2726: 4 | J2726: 8 | K2726: 0 | L2726: 0 | M2726: {'value': 0.17157339, 'is_in_top_1_percent': False, 'is_in_top_10_percent': False} | N2726: [] | O2726: []
A2727: https://openalex.org/W4403715389 | B2727: https://doi.org/10.1145/3696762.3698047 | C2727: Summary of the Workshop on Visual Methods and Analyzing Visual Data in Human Computer Interaction | D2727: 2024 | E2727: 45589 | F2727: {'openalex': 'https://openalex.org/W4403715389', 'doi': 'https://doi.org/10.1145/3696762.3698047'} | G2727: en | H2727: article | I2727: 3 | J2727: 4 | K2727: 0 | L2727: 0 | M2727: {'value': 0.18952612, 'is_in_top_1_percent': False, 'is_in_top_10_percent': False} | N2727: [] | O2727: []
A2728: https://openalex.org/W4403715480 | B2728: https://doi.org/10.1145/3696762.3698046 | C2728: Summary of the Workshop on Interactions for Supporting Explanations and Promoting Comprehension | D2728: 2024 | E2728: 45589 | F2728: {'openalex': 'https://openalex.org/W4403715480', 'doi': 'https://doi.org/10.1145/3696762.3698046'} | G2728: en | H2728: article | I2728: 2 | J2728: 6 | K2728: 0 | L2728: 0 | M2728: {'value': 0.23545768, 'is_in_top_1_percent': False, 'is_in_top_10_percent': False} | N2728: [] | O2728: []
A2729: https://openalex.org/W4403719022 | B2729: https://doi.org/10.1371/journal.pone.0312622 | C2729: A protocol to simultaneously examine cardiorespiratory, cerebrovascular and neurophysiological responses inside a hypobaric chamber | D2729: 2024 | E2729: 45589 | F2729: {'openalex': 'https://openalex.org/W4403719022', 'doi': 'https://doi.org/10.1371/journal.pone.0312622', 'pmid': 'https://pubmed.ncbi.nlm.nih.gov/39446909'} | G2729: en | H2729: article | I2729: 1 | J2729: 5 | K2729: 0 | L2729: 0 | M2729: {'value': 0.18828265, 'is_in_top_1_percent': False, 'is_in_top_10_percent': False} | N2729: [{'id': 'https://metadata.un.org/sdg/14', 'display_name': 'Life below water', 'score': 0.5899999737739563}] | O2729: []
A2730: https://openalex.org/W4403724357 | B2730: https://doi.org/10.1109/dsaa61799.2024.10722777 | C2730: Multi-View Relational Evidential C-Medoid Clustering with Adaptive Weighted | D2730: 2024 | E2730: 45571 | F2730: {'openalex': 'https://openalex.org/W4403724357', 'doi': 'https://doi.org/10.1109/dsaa61799.2024.10722777'} | G2730: en | H2730: article | I2730: 2 | J2730: 3 | K2730: 0 | L2730: 0 | M2730: {'value': 0.16663396, 'is_in_top_1_percent': False, 'is_in_top_10_percent': False} | N2730: [{'id': 'https://metadata.un.org/sdg/2', 'display_name': 'Zero hunger', 'score': 0.4099999964237213}] | O2730: []
A2731: https://openalex.org/W4403749864 | B2731: https://doi.org/10.1186/s12889-024-20308-z | C2731: Model-based estimates of age-structured SARS-CoV-2 epidemiology in households | D2731: 2024 | E2731: 45590 | F2731: {'openalex': 'https://openalex.org/W4403749864', 'doi': 'https://doi.org/10.1186/s12889-024-20308-z', 'pmid': 'https://pubmed.ncbi.nlm.nih.gov/39455984'} | G2731: en | H2731: article | I2731: 2 | J2731: 8 | K2731: 0 | L2731: 0 | M2731: {'value': 0.20813037, 'is_in_top_1_percent': False, 'is_in_top_10_percent': False} | N2731: [{'id': 'https://metadata.un.org/sdg/3', 'display_name': 'Good health and well-being', 'score': 0.6299999952316284}] | O2731: []
A2732: https://openalex.org/W4403759712 | B2732: https://doi.org/10.1007/978-3-031-72664-4_25 | C2732: Rejection Sampling IMLE: Designing Priors forÂ Better Few-Shot Image Synthesis | D2732: 2024 | E2732: 45590 | F2732: {'openalex': 'https://openalex.org/W4403759712', 'doi': 'https://doi.org/10.1007/978-3-031-72664-4_25'} | G2732: en | H2732: book-chapter | I2732: 1 | J2732: 3 | K2732: 0 | L2732: 0 | M2732: {'value': 0.40909925, 'is_in_top_1_percent': False, 'is_in_top_10_percent': False} | N2732: [] | O2732: []
A2733: https://openalex.org/W4403766483 | B2733: https://doi.org/10.3390/ijerph21111413 | C2733: Interactive Simulation of Nonpharmaceutical Interventions of Airborne Disease Transmission in Office Settings | D2733: 2024 | E2733: 45590 | F2733: {'openalex': 'https://openalex.org/W4403766483', 'doi': 'https://doi.org/10.3390/ijerph21111413', 'pmid': 'https://pubmed.ncbi.nlm.nih.gov/39595680'} | G2733: en | H2733: article | I2733: 2 | J2733: 6 | K2733: 0 | L2733: 0 | M2733: {'value': 0.35194566, 'is_in_top_1_percent': False, 'is_in_top_10_percent': False} | N2733: [{'id': 'https://metadata.un.org/sdg/3', 'display_name': 'Good health and well-being', 'score': 0.5099999904632568}] | O2733: []
A2734: https://openalex.org/W4403774737 | B2734: https://doi.org/10.1177/07067437241293098 | C2734: Impacts and Implications of Cannabis Legalization on Key Outcomes Among Adolescents in Canada | D2734: 2024 | E2734: 45590 | F2734: {'openalex': 'https://openalex.org/W4403774737', 'doi': 'https://doi.org/10.1177/07067437241293098', 'pmid': 'https://pubmed.ncbi.nlm.nih.gov/39450450'} | G2734: en | H2734: article | I2734: 3 | J2734: 3 | K2734: 0 | L2734: 0 | M2734: {'value': 0.18554748, 'is_in_top_1_percent': False, 'is_in_top_10_percent': False} | N2734: [] | O2734: []
A2735: https://openalex.org/W4403791025 | B2735: https://doi.org/10.55092/aias20240007 | C2735: Developing a Machine Intelligence Quotient (MIQ) for evaluating autonomous vehicle intelligence: A Conceptual Framework | D2735: 2024 | E2735: 45292 | F2735: {'openalex': 'https://openalex.org/W4403791025', 'doi': 'https://doi.org/10.55092/aias20240007'} | G2735: en | H2735: article | I2735: 1 | J2735: 3 | K2735: 0 | L2735: 0 | M2735: {'value': 0.20067371, 'is_in_top_1_percent': False, 'is_in_top_10_percent': False} | N2735: [] | O2735: []
A2736: https://openalex.org/W4403808318 | B2736: https://doi.org/10.1016/j.jaccpubpol.2024.107263 | C2736: Government spending and CEO equity incentives: Evidence from changes in U.S. Senate committee chairs | D2736: 2024 | E2736: 45593 | F2736: {'openalex': 'https://openalex.org/W4403808318', 'doi': 'https://doi.org/10.1016/j.jaccpubpol.2024.107263'} | G2736: en | H2736: article | I2736: 4 | J2736: 4 | K2736: 0 | L2736: 0 | M2736: {'value': 0.32165388, 'is_in_top_1_percent': False, 'is_in_top_10_percent': False} | N2736: [] | O2736: []
A2737: https://openalex.org/W4403811844 | B2737: https://doi.org/10.4230/lipics.isaac.2024.24 | C2737: Exact Algorithms for Clustered Planarity with Linear Saturators | D2737: 2024 | E2737: 45292 | F2737: {'openalex': 'https://openalex.org/W4403811844', 'doi': 'https://doi.org/10.4230/lipics.isaac.2024.24'} | G2737: en | H2737: preprint | I2737: 6 | J2737: 6 | K2737: 0 | L2737: 0 | M2737: {'value': 0.35316632, 'is_in_top_1_percent': False, 'is_in_top_10_percent': False} | N2737: [] | O2737: []
A2738: https://openalex.org/W4403826060 | B2738: https://doi.org/10.1007/978-3-031-69918-4_9 | C2738: Disaggregating Sustainable Transitions Through Power and Governance Arrangements in Municipal Enterprises: A Case Study of the Canmore Community Housing Corporation | D2738: 2024 | E2738: 45593 | F2738: {'openalex': 'https://openalex.org/W4403826060', 'doi': 'https://doi.org/10.1007/978-3-031-69918-4_9'} | G2738: en | H2738: book-chapter | I2738: 1 | J2738: 5 | K2738: 0 | L2738: 0 | M2738: {'value': 0.6266129, 'is_in_top_1_percent': False, 'is_in_top_10_percent': False} | N2738: [] | O2738: []
... A2792: https://openalex.org/W4404427571 | B2792: https://doi.org/10.1111/soin.12646 | C2792: Book Review: Waiting to Inhale, by AkwasiOwusuâ€Bempah and TahiraRehmatullah. The MIT Press, Cambridge, MA; London, England. 2023. 256 pp. $22.95. ISBN: 9780262047685 | D2792: 2024 | E2792: 45610 | F2792: {'openalex': 'https://openalex.org/W4404427571', 'doi': 'https://doi.org/10.1111/soin.12646'} | G2792: en | H2792: article | I2792: 1 | J2792: 1 | K2792: 0 | L2792: 0 | M2792: {'value': 0.32448642, 'is_in_top_1_percent': False, 'is_in_top_10_percent': False} | N2792: [] | O2792: []
A2793: https://openalex.org/W4404433199 | C2793: Holistic approach to understand how teleost fish scales fulfill their biological function -from nano to macro structure organization | D2793: 2024 | E2793: 45357 | F2793: {'openalex': 'https://openalex.org/W4404433199'} | G2793: en | H2793: article | I2793: 5 | J2793: 6 | K2793: 0 | L2793: 0 | M2793: {'value': 0.18711771, 'is_in_top_1_percent': False, 'is_in_top_10_percent': False} | N2793: [{'id': 'https://metadata.un.org/sdg/14', 'display_name': 'Life below water', 'score': 0.6100000143051147}] | O2793: []
A2794: https://openalex.org/W4404460032 | B2794: https://doi.org/10.54254/2754-1169/104/2024bj0194 | C2794: withdraw | D2794: 2024 | E2794: 45611 | F2794: {'openalex': 'https://openalex.org/W4404460032', 'doi': 'https://doi.org/10.54254/2754-1169/104/2024bj0194'} | G2794: en | H2794: article | I2794: 1 | J2794: 1 | K2794: 0 | L2794: 0 | M2794: {'value': 0.12034412, 'is_in_top_1_percent': False, 'is_in_top_10_percent': False} | N2794: [] | O2794: []
A2795: https://openalex.org/W4404461877 | B2795: https://doi.org/10.1080/09638288.2024.2429747 | C2795: Barriers and facilitators encountered by healthcare providers when supporting individuals with SCI to change their bowel care | D2795: 2024 | E2795: 45614 | F2795: {'openalex': 'https://openalex.org/W4404461877', 'doi': 'https://doi.org/10.1080/09638288.2024.2429747', 'pmid': 'https://pubmed.ncbi.nlm.nih.gov/39555710'} | G2795: en | H2795: article | I2795: 1 | J2795: 7 | K2795: 0 | L2795: 0 | M2795: {'value': 0.33351017, 'is_in_top_1_percent': False, 'is_in_top_10_percent': False} | N2795: [] | O2795: []
A2796: https://openalex.org/W4404468475 | B2796: https://doi.org/10.1186/s40345-024-00361-8 | C2796: Correction: Perceived cognitive loss, symptomology, and psychological well-being with bipolar disorder | D2796: 2024 | E2796: 45614 | F2796: {'openalex': 'https://openalex.org/W4404468475', 'doi': 'https://doi.org/10.1186/s40345-024-00361-8', 'pmid': 'https://pubmed.ncbi.nlm.nih.gov/39557709'} | G2796: en | H2796: erratum | I2796: 2 | J2796: 5 | K2796: 0 | L2796: 0 | M2796: {'value': 0.29153903, 'is_in_top_1_percent': False, 'is_in_top_10_percent': False} | N2796: [{'id': 'https://metadata.un.org/sdg/5', 'score': 0.44999998807907104, 'display_name': 'Gender equality'}] | O2796: []
A2797: https://openalex.org/W4404482712 | B2797: https://doi.org/10.1386/jaah_00172_7 | C2797: Navigating well-being through shoreline walking as artistic practice | D2797: 2024 | E2797: 45614 | F2797: {'openalex': 'https://openalex.org/W4404482712', 'doi': 'https://doi.org/10.1386/jaah_00172_7'} | G2797: en | H2797: article | I2797: 1 | J2797: 2 | K2797: 0 | L2797: 0 | M2797: {'value': 0.26632248, 'is_in_top_1_percent': False, 'is_in_top_10_percent': False} | N2797: [] | O2797: []
A2798: https://openalex.org/W4404486856 | B2798: https://doi.org/10.1177/02761467241299334 | C2798: Macromarketing Pedagogy at the 2024 Conference | D2798: 2024 | E2798: 45614 | F2798: {'openalex': 'https://openalex.org/W4404486856', 'doi': 'https://doi.org/10.1177/02761467241299334'} | G2798: en | H2798: article | I2798: 2 | J2798: 2 | K2798: 0 | L2798: 0 | M2798: {'value': 0.34443586, 'is_in_top_1_percent': False, 'is_in_top_10_percent': False} | N2798: [] | O2798: []
A2799: https://openalex.org/W4404509302 | B2799: https://doi.org/10.54254/2753-8818/58/20241351 | C2799: Current trends and ethical considerations in gene therapy | D2799: 2024 | E2799: 45611 | F2799: {'openalex': 'https://openalex.org/W4404509302', 'doi': 'https://doi.org/10.54254/2753-8818/58/20241351'} | G2799: en | H2799: article | I2799: 1 | J2799: 1 | K2799: 0 | L2799: 0 | M2799: {'value': 0.1874231, 'is_in_top_1_percent': False, 'is_in_top_10_percent': False} | N2799: [] | O2799: []
A2800: https://openalex.org/W4404518321 | B2800: https://doi.org/10.1609/aies.v7i1.31740 | C2800: Medical AI, Categories of Value Conflict, and Conflict Bypasses | D2800: 2024 | E2800: 45581 | F2800: {'openalex': 'https://openalex.org/W4404518321', 'doi': 'https://doi.org/10.1609/aies.v7i1.31740'} | G2800: en | H2800: article | I2800: 1 | J2800: 2 | K2800: 0 | L2800: 0 | M2800: {'value': 0.25053202, 'is_in_top_1_percent': False, 'is_in_top_10_percent': False} | N2800: [{'id': 'https://metadata.un.org/sdg/16', 'score': 0.6899999976158142, 'display_name': 'Peace, Justice and strong institutions'}] | O2800: []
A2801: https://openalex.org/W4404522595 | B2801: https://doi.org/10.22541/essoar.173203990.01952203/v1 | C2801: Land-to-Sea Sediment Fluxes from a Major Glacial Lake Outburst Flood Were Stepped Rather Than Instantaneous | D2801: 2024 | E2801: 45615 | F2801: {'openalex': 'https://openalex.org/W4404522595', 'doi': 'https://doi.org/10.22541/essoar.173203990.01952203/v1'} | G2801: en | H2801: preprint | I2801: 2 | J2801: 15 | K2801: 0 | L2801: 0 | M2801: {'value': 0.24274179, 'is_in_top_1_percent': False, 'is_in_top_10_percent': False} | N2801: [{'id': 'https://metadata.un.org/sdg/14', 'score': 0.7400000095367432, 'display_name': 'Life below water'}] | O2801: []
A2802: https://openalex.org/W4404526808 | B2802: https://doi.org/10.3390/s24227346 | C2802: Correction: Kaur, M.; Menon, C. Submillimeter Sized 2D Electrothermal Optical Fiber Scanner. Sensors 2023, 23, 404 | D2802: 2024 | E2802: 45614 | F2802: {'openalex': 'https://openalex.org/W4404526808', 'doi': 'https://doi.org/10.3390/s24227346', 'pmid': 'https://pubmed.ncbi.nlm.nih.gov/39599192'} | G2802: en | H2802: erratum | I2802: 2 | J2802: 2 | K2802: 0 | L2802: 0 | M2802: {'value': 0.19260803, 'is_in_top_1_percent': False, 'is_in_top_10_percent': False} | N2802: [] | O2802: []
A2803: https://openalex.org/W4404535976 | B2803: https://doi.org/10.3390/e26110995 | C2803: Information-Theoretic Generalization Bounds for Batch Reinforcement Learning | D2803: 2024 | E2803: 45614 | F2803: {'openalex': 'https://openalex.org/W4404535976', 'doi': 'https://doi.org/10.3390/e26110995', 'pmid': 'https://pubmed.ncbi.nlm.nih.gov/39593939'} | G2803: en | H2803: article | I2803: 1 | J2803: 1 | K2803: 0 | L2803: 0 | M2803: {'value': 0.18193736, 'is_in_top_1_percent': False, 'is_in_top_10_percent': False} | N2803: [] | O2803: []
A2804: https://openalex.org/W4404545119 | B2804: https://doi.org/10.1007/978-3-031-73036-8_26 | C2804: R3DS: Reality-Linked 3D Scenes forÂ Panoramic Scene Understanding | D2804: 2024 | E2804: 45616 | F2804: {'openalex': 'https://openalex.org/W4404545119', 'doi': 'https://doi.org/10.1007/978-3-031-73036-8_26'} | G2804: en | H2804: book-chapter | I2804: 2 | J2804: 5 | K2804: 0 | L2804: 0 | M2804: {'value': 0.6608473, 'is_in_top_1_percent': False, 'is_in_top_10_percent': False} | N2804: [] | O2804: []
A2805: https://openalex.org/W4404562801 | B2805: https://doi.org/10.1109/mpe.2024.3408111 | C2805: Toward Artificial-Intelligence-Empowered Smarter Power Grid: Forecasting, Dispatch, and Control | D2805: 2024 | E2805: 45597 | F2805: {'openalex': 'https://openalex.org/W4404562801', 'doi': 'https://doi.org/10.1109/mpe.2024.3408111'} | G2805: en | H2805: article | I2805: 3 | J2805: 13 | K2805: 0 | L2805: 0 | M2805: {'value': 0.18854402, 'is_in_top_1_percent': False, 'is_in_top_10_percent': False} | N2805: [{'id': 'https://metadata.un.org/sdg/7', 'score': 0.4300000071525574, 'display_name': 'Affordable and clean energy'}] | O2805: []
... A2920: https://openalex.org/W4405893148 | B2920: https://doi.org/10.1097/qad.0000000000004064 | C2920: The challenge of normalizing vaccine behaviors in the postpandemic era | D2920: 2024 | E2920: 45656 | F2920: {'openalex': 'https://openalex.org/W4405893148', 'doi': 'https://doi.org/10.1097/qad.0000000000004064', 'pmid': 'https://pubmed.ncbi.nlm.nih.gov/39787485'} | G2920: en | H2920: article | I2920: 1 | J2920: 2 | K2920: 0 | L2920: 0 | M2920: {'value': 0.33685187, 'is_in_top_1_percent': False, 'is_in_top_10_percent': False} | N2920: [{'id': 'https://metadata.un.org/sdg/3', 'display_name': 'Good health and well-being', 'score': 0.5799999833106995}] | O2920: []
A2921: https://openalex.org/W4405899945 | C2921: What is food? An investigation into food realizables | D2921: 2024 | E2921: 45488 | F2921: {'openalex': 'https://openalex.org/W4405899945'} | G2921: en | H2921: article | I2921: 2 | J2921: 3 | K2921: 0 | L2921: 0 | M2921: {'value': 0.30135001, 'is_in_top_1_percent': False, 'is_in_top_10_percent': False} | N2921: [{'id': 'https://metadata.un.org/sdg/2', 'display_name': 'Zero hunger', 'score': 0.75}] | O2921: []
A2922: https://openalex.org/W4405907397 | B2922: https://doi.org/10.1109/tmm.2024.3521770 | C2922: Towards Neural Codec-Empowered 360$^\circ$ Video Streaming: A Saliency-Aided Synergistic Approach | D2922: 2024 | E2922: 45656 | F2922: {'openalex': 'https://openalex.org/W4405907397', 'doi': 'https://doi.org/10.1109/tmm.2024.3521770'} | G2922: en | H2922: article | I2922: 2 | J2922: 6 | K2922: 0 | L2922: 0 | M2922: {'value': 0.25440323, 'is_in_top_1_percent': False, 'is_in_top_10_percent': False} | N2922: [] | O2922: []
A2923: https://openalex.org/W4405907834 | B2923: https://doi.org/10.1109/wcnps65035.2024.10814194 | C2923: Metaheuristic Approach Hybridizing Variable Neighborhood Search and Genetic Algorithm to Size Hybrid Backup Systems for Power Outages | D2923: 2024 | E2923: 45638 | F2923: {'openalex': 'https://openalex.org/W4405907834', 'doi': 'https://doi.org/10.1109/wcnps65035.2024.10814194'} | G2923: en | H2923: article | I2923: 1 | J2923: 3 | K2923: 0 | L2923: 0 | M2923: {'value': 0.31572182, 'is_in_top_1_percent': False, 'is_in_top_10_percent': False} | N2923: [{'id': 'https://metadata.un.org/sdg/11', 'display_name': 'Sustainable cities and communities', 'score': 0.4699999988079071}] | O2923: []
A2924: https://openalex.org/W4405911977 | B2924: https://doi.org/10.53979/yillik.2024.15 | C2924: Batu BayÃ¼lgen and Turgut Saner, Architectural Description of Byzantine Remains in Istanbul: Excavations and Surveys in the City within the Walls (1927â€“2021). Istanbul: KoÃ§ University Press, 2024. xxii+696 pages, 44 plans. ISBN 9786259433493 | D2924: 2024 | E2924: 45656 | F2924: {'openalex': 'https://openalex.org/W4405911977', 'doi': 'https://doi.org/10.53979/yillik.2024.15'} | G2924: en | H2924: article | I2924: 2 | J2924: 1 | K2924: 0 | L2924: 0 | M2924: {'value': 0.40893751, 'is_in_top_1_percent': False, 'is_in_top_10_percent': False} | N2924: [{'id': 'https://metadata.un.org/sdg/11', 'display_name': 'Sustainable cities and communities', 'score': 0.8299999833106995}] | O2924: []
A2925: https://openalex.org/W4405913108 | B2925: https://doi.org/10.1080/16843703.2024.2440250 | C2925: Joining behavior and vacation strategy in the queue with heterogeneous customers | D2925: 2024 | E2925: 45656 | F2925: {'openalex': 'https://openalex.org/W4405913108', 'doi': 'https://doi.org/10.1080/16843703.2024.2440250'} | G2925: en | H2925: article | I2925: 3 | J2925: 2 | K2925: 0 | L2925: 0 | M2925: {'value': 0.39696282, 'is_in_top_1_percent': False, 'is_in_top_10_percent': False} | N2925: [{'id': 'https://metadata.un.org/sdg/8', 'display_name': 'Decent work and economic growth', 'score': 0.41999998688697815}] | O2925: []
A2926: https://openalex.org/W4405921348 | B2926: https://doi.org/10.3390/atmos16010021 | C2926: Characterizing Radon Among Public Buildings and Small/Medium-Sized Businesses in a Canadian Province | D2926: 2024 | E2926: 45654 | F2926: {'openalex': 'https://openalex.org/W4405921348', 'doi': 'https://doi.org/10.3390/atmos16010021'} | G2926: en | H2926: article | I2926: 1 | J2926: 5 | K2926: 0 | L2926: 0 | M2926: {'value': 0.3800491, 'is_in_top_1_percent': False, 'is_in_top_10_percent': False} | N2926: [] | O2926: []
A2927: https://openalex.org/W4405960280 | B2927: https://doi.org/10.1093/geroni/igae098.0538 | C2927: KNOWLEDGE MOBILIZATION TO DEVELOP DEMENTIA-INCLUSIVE COMMUNITIES IN THE DEMSCAPE PROJECT | D2927: 2024 | E2927: 45627 | F2927: {'openalex': 'https://openalex.org/W4405960280', 'doi': 'https://doi.org/10.1093/geroni/igae098.0538'} | G2927: en | H2927: article | I2927: 1 | J2927: 3 | K2927: 0 | L2927: 0 | M2927: {'value': 0.48520158, 'is_in_top_1_percent': False, 'is_in_top_10_percent': False} | N2927: [] | O2927: []
A2928: https://openalex.org/W4405960446 | B2928: https://doi.org/10.1093/geroni/igae098.0098 | C2928: SOCIAL ISOLATION AMONG MARGINALIZED OLDER ADULTS: APPLYING A UNIFIED MODEL OF RESILIENCE | D2928: 2024 | E2928: 45627 | F2928: {'openalex': 'https://openalex.org/W4405960446', 'doi': 'https://doi.org/10.1093/geroni/igae098.0098'} | G2928: en | H2928: article | I2928: 1 | J2928: 1 | K2928: 0 | L2928: 0 | M2928: {'value': 0.36057737, 'is_in_top_1_percent': False, 'is_in_top_10_percent': False} | N2928: [] | O2928: []
A2929: https://openalex.org/W4405960779 | B2929: https://doi.org/10.1093/geroni/igae098.2020 | C2929: OLDER ADULTS WITH DISABILITIES AS CORESEARCHERS IN COMMUNITY-ENGAGED RESEARCH ON MOBILITY AND ACCESS | D2929: 2024 | E2929: 45627 | F2929: {'openalex': 'https://openalex.org/W4405960779', 'doi': 'https://doi.org/10.1093/geroni/igae098.2020'} | G2929: en | H2929: article | I2929: 1 | J2929: 5 | K2929: 0 | L2929: 0 | M2929: {'value': 0.45655498, 'is_in_top_1_percent': False, 'is_in_top_10_percent': False} | N2929: [] | O2929: []
A2930: https://openalex.org/W4405960792 | B2930: https://doi.org/10.1093/geroni/igae098.1079 | C2930: CO-CREATING A VIRTUAL REALITY PROGRAM WITH PEOPLE LIVING WITH DEMENTIA IN LONG-TERM CARE | D2930: 2024 | E2930: 45627 | F2930: {'openalex': 'https://openalex.org/W4405960792', 'doi': 'https://doi.org/10.1093/geroni/igae098.1079'} | G2930: en | H2930: article | I2930: 1 | J2930: 8 | K2930: 0 | L2930: 0 | M2930: {'value': 0.44744867, 'is_in_top_1_percent': False, 'is_in_top_10_percent': False} | N2930: [] | O2930: []
A2931: https://openalex.org/W4405960845 | B2931: https://doi.org/10.1093/geroni/igae098.2107 | C2931: THE INTERPLAY OF SOCIAL INTERACTION, POSITIVE AFFECT, AND SUBJECTIVE AGE IN OLDER ADULTS | D2931: 2024 | E2931: 45627 | F2931: {'openalex': 'https://openalex.org/W4405960845', 'doi': 'https://doi.org/10.1093/geroni/igae098.2107'} | G2931: en | H2931: article | I2931: 1 | J2931: 1 | K2931: 0 | L2931: 0 | M2931: {'value': 0.36077187, 'is_in_top_1_percent': False, 'is_in_top_10_percent': False} | N2931: [] | O2931: []
A2932: https://openalex.org/W4405961104 | B2932: https://doi.org/10.1093/geroni/igae098.1337 | C2932: KNOWLEDGE MOBILIZATION TO CREATE DEMENTIA-INCLUSIVE NEIGHBORHOODS: AN EDUCATIONAL AND AWARENESS-RAISING VIDEO | D2932: 2024 | E2932: 45627 | F2932: {'openalex': 'https://openalex.org/W4405961104', 'doi': 'https://doi.org/10.1093/geroni/igae098.1337'} | G2932: en | H2932: article | I2932: 1 | J2932: 6 | K2932: 0 | L2932: 0 | M2932: {'value': 0.48490221, 'is_in_top_1_percent': False, 'is_in_top_10_percent': False} | N2932: [] | O2932: []
A2933: https://openalex.org/W4405961118 | B2933: https://doi.org/10.1093/geroni/igae098.1335 | C2933: EXPLORING FACTORS INFLUENCING WALKING ACTIVITY IN PEOPLE WITH DEMENTIA: A SPATIAL ANALYSIS IN METRO VANCOUVER | D2933: 2024 | E2933: 45627 | F2933: {'openalex': 'https://openalex.org/W4405961118', 'doi': 'https://doi.org/10.1093/geroni/igae098.1335'} | G2933: en | H2933: article | I2933: 1 | J2933: 2 | K2933: 0 | L2933: 0 | M2933: {'value': 0.17233278, 'is_in_top_1_percent': False, 'is_in_top_10_percent': False} | N2933: [] | O2933: []
... A2981: https://openalex.org/W4407029930 | B2981: https://doi.org/10.61838/kman.psynexus.2.2.7 | C2981: Risk-Taking, Cognitive Distortions, and Their Influence on Proactive Coping in Higher Education | D2981: 2024 | E2981: 45292 | F2981: {'openalex': 'https://openalex.org/W4407029930', 'doi': 'https://doi.org/10.61838/kman.psynexus.2.2.7'} | G2981: en | H2981: article | I2981: 1 | J2981: 1 | K2981: 0 | L2981: 0 | M2981: {'value': 0.37877162, 'is_in_top_1_percent': False, 'is_in_top_10_percent': False} | N2981: [] | O2981: []
A2982: https://openalex.org/W4407053306 | C2982: Preliminary study of the metatranscriptomic and metagenomic of Sanguina nivaloides | D2982: 2024 | E2982: 45602 | F2982: {'openalex': 'https://openalex.org/W4407053306'} | G2982: en | H2982: article | I2982: 2 | J2982: 8 | K2982: 0 | L2982: 0 | M2982: {'value': 0.19396858, 'is_in_top_1_percent': False, 'is_in_top_10_percent': False} | N2982: [] | O2982: []
...

Sheet rio results
A1: Title | B1: Authors | C1: Number of Authors | D1: Scopus Author Ids | E1: Year | F1: Full date | G1: Scopus Source title | H1: Language | I1: Citations | J1: Field-Weighted Citation Impact | K1: DOI | L1: Publication type | M1: Open Access | N1: Institutions | O1: Number of Institutions | P1: Scopus Affiliation IDs | Q1: Scopus Affiliation names | R1: Scopus Author ID First Author | S1: Scopus Author ID Last Author | T1: Scopus Author ID Corresponding Author | U1: Scopus Author ID Single Author | V1: Country/Region | W1: Topic Cluster name | X1: Topic name
A2: “Real impact”: Challenges and opportunities in bridging the gap between research and practice – Making a difference in industry, policy, and society | B2: Dwivedi, Y.K.| Jeyaraj, A.| Hughes, L.| Davies, G.H.| Ahuja, M.| Albashrawi, M.A.| Al-Busaidi, A.S.| Al-Sharhan, S.| Al-Sulaiti, K.I.| Altinay, L.| Amalaya, S.| Archak, S.| Ballestar, M.T.| Bhagwat, S.A.| Bharadwaj, A.| Bhushan, A.| Bose, I.| Budhwar, P.| Bunker, D.| Capatina, A.| Carter, L.| Constantiou, I.| Coombs, C.| Crick, T.| Csáki, C.| Darnige, Y.| Dé, R.| Delbridge, R.| Dubey, R.| Gauld, R.| Gutti, R.K.| Hattingh, M.| Haug, A.| Hendricks, L.| Hino, A.| Hsu, C.H.C.| Iivari, N.| Janssen, M.| Jebabli, I.| Jones, P.| Junglas, I.| Kaushik, A.| Khazanchi, D.| Kodama, M.| Kraus, S.| Kumar, V.| Maier, C.| Malik, T.| Matthee, M.| McCarthy, I.P.| Meier, M.| Metri, B.| Micu, A.| Micu, A.-E.| Misra, S.K.| Mishra, A.| Molin-Juustila, T.| Oppermann, L.| O'Regan, N.| Pal, A.| Pandey, N.| Pappas, I.O.| Parker, A.| Pathak, K.| Pienta, D.| Polyviou, A.| Raman, R.| Ribeiro-Navarrete, S.| Ritala, P.| Rosemann, M.| Sarker, S.| Saxena, P.| Schlagwein, D.| Schultze, H.| Sharma, C.| Sharma, S.K.| Simintiras, A.| Singh, V.K.| Smuts, H.| Soldatos, J.| Tiwari, M.K.| Thatcher, J.B.| Vanberghen, C.| Varga, Á.| Vassilakopoulou, P.| Venkatesh, V.| Viglia, G.| Vorley, T.| Wade, M.| Walton, P. | C2: 90 | D2: 35239818900| 16426012500| 57205405210| 57199302634| 7101943053| 57188808764| 55633735500| 6602231773| 57191046640| 6507918447| 58743115600| 14919251500| 57024150400| 56207846800| 7004584448| 58862220500| 52663129200| 6701694690| 15520858500| 35209737400| 7201576525| 12141851800| 7003564476| 14032736300| 36447492200| 58861222200| 14011831800| 6701780449| 36991875200| 6701641862| 15755463000| 54935562100| 57788631900| 57678650900| 54388937800| 7404947039| 22979790000| 16199813000| 56274399100| 55523712300| 22979521800| 58709804800| 6506490534| 55624713900| 57207720523| 57212901290| 35366765400| 58776832300| 36912599800| 57210460027| 57326260300| 14071708100| 58355484100| 35211557400| 57898178300| 57203177364| 33867644000| 15045267400| 6603501742| 57193541504| 57813546700| 55387371600| 57213532596| 58862957700| 57194239065| 55604816600| 55808097300| 56676383100| 24778958800| 6701701206| 35611469700| 58861470600| 37013671400| 9633409300| 59860576800| 58263883500| 6507763214| 57908232100| 35303384200| 8662280800| 60105149700| 7006547020| 58148049100| 24178030000| 36605482100| 35614985000| 41961835900| 23394080600| 7201453261| 59849258600 | E2: 2024 | F2: 45566 | G2: International Journal of Information Management | H2: English | I2: 60 | J2: 73.65 | K2: 10.1016/j.ijinfomgt.2023.102750 | L2: Editorial | M2: Green | N2: King Fahd University of Petroleum and Minerals| Temple University| Fraunhofer Institute for Applied Information Technology| Corvinus University of Budapest| Hong Kong Polytechnic University| Libera Universita Internazionale degli Studi Sociali Guido Carli| Indian Institute of Management Mumbai| Delft University of Technology| Universidad Rey Juan Carlos| University of Bamberg| Loughborough University| Swansea University| Lappeenranta-Lahti University of Technology| European University Institute, San Domenico di Fiesole| Norwegian University of Science and Technology| University of Tennessee, Knoxville| Liverpool John Moores University| Aston University| Virginia Polytechnic Institute and State University| University of Nebraska Omaha| Sultan Qaboos University| Indian Institute of Management Bangalore| ESIC| Management Center Innsbruck| Copenhagen Business School| University of Hyderabad| International University of Rabat| University of Portsmouth| International Institute for Management Development| University of Pretoria| Ovidius University of Constanta| Indian Institute of Management Calcutta| University of Oulu| Oxford Brookes University| University of Otago| Dunarea de Jos University of Galati| University of Sydney| Wright State University| Indian Institute of Management Nagpur| Jaipuria Institute of Management, Lucknow| Cyprus University of Technology| Indian Institute of Management Ahmedabad| University of Oxford| University of Economics and Human Sciences in Warsaw| University of Johannesburg| BASF| ICAR - National Bureau of Plant Genetic Resources| University of Agder| European Commission| Cardiff University| Simon Fraser University| University of Tennessee System| Free University of Bozen-Bolzano| Queensland University of Technology| Symbiosis International University| University of Siegen| College of Charleston| Nihon University| University of Louisville| Waseda University| Emory University| Dundalk Institute of Technology| Edith Cowan University| University of Virginia| Open University Milton Keynes| Montpellier Business School | O2: 66 | P2: 60004572| 60170469| 60104400| 60018306| 60105210| 60020633| 60212277| 60009506| 60071768| 60280380| 60281944| 60160406| 60014564| 113062318| 60012678| 60018940| 60012113| 60116269| 60000928| 126380484| 60033308| 60116225| 125711596| 60025709| 60008717| 60212023| 60020188| 60116333| 60000891| 60001434| 130822119| 60071271| 60023998| 60170149| 60112781| 60028355| 60170411| 60109020| 60100347| 60017311| 60029516| 60021902| 128322922| 130822134| 60004100| 60023462| 60086490| 60008928| 60012954| 60117886| 60006288| 60111570| 60013340| 60015938| 60018988| 60002561| 60009914| 60000717| 128388341| 60011372| 60018491| 60016374| 60115581| 60023386| 60097670| 60002596| 60070899| 60022123| 60080184| 60013141| 60026867| 60026851| 101703527| 60015574| 60116456| 60077474| 60103620| 60268510| 60226620| 60014304| 60011019| 60021918| 60007616| 130821208| 60024260| 130821966| 60030398| 60122660| 60024316| 60029640| 60019299| 60027090| 60025475| 101885340| 60067221| 123054520 | Q2: Swansea University| School of Management| Symbiosis International (Deemed University)| Wright State University| Edith Cowan University| University of Louisville| KFUPM Business School| King Fahd University of Petroleum and Minerals| Sultan Qaboos University| International University of Science and Technology in Kuwait (IUK)| Al Rayyan International University College| Oxford Brookes Business School| Oxford Brookes University| KPMG| ICAR - National Bureau of Plant Genetic Resources, New Delhi| Universidad Rey Juan Carlos| The Open University| Goizueta Business School| Emory University| Bank Muscat SAOG| Indian Institute of Management Ahmedabad| Aston Business School| Natural Hazards Research Australia| The University of Sydney| Universitatea Dunarea de Jos din Galati| The University of Sydney Business School| Copenhagen Business School| Loughborough University, School of Business and Economics| Loughborough University| Budapesti Corvinus Egyetem| Data & Artificial Intelligence Practice Director| Indian Institute of Management Bangalore| Cardiff University| Cardiff Business School| Montpellier Business School| Liverpool John Moores University| Liverpool Business School| Otago Business School| Otago Medical School| University of Otago| University of Hyderabad| University of Pretoria| Norwegian Labour and Welfare Administration (NAV)| Chief Marketing Officer (CMO)| MCI - The Entrepreneurial School| Waseda University| School of Hotel and Tourism Management, The Hong Kong Polytechnic University| The Hong Kong Polytechnic University| Oulun Yliopisto| Faculteit Techniek, Bestuur en Management, TU Delft| Delft University of Technology| International University of Rabat| College of Charleston| Dundalk Institute of Technology| University of Nebraska Omaha| Nihon University| Free University of Bozen-Bolzano| University of Johannesburg| SRV Media Private Ltd| Universität Bamberg| Simon Fraser University| LUISS University| Indian Institute of Management Nagpur| Ovidius University of Constanta| Jaipuria Institute of Management, Lucknow| Fraunhofer Institute for Applied Information Technology FIT| Indian Institute of Management Calcutta| Indian Institute of Management Mumbai| Universitetet i Agder| Norges Teknisk-Naturvitenskapelige Universitet| Green Templeton College| University of Oxford| Somerset House| The University of Tennessee, Knoxville| Haslam College of Business| Cyprus University of Technology| VIZJA University| ESIC University| LUT kauppakorkeakoulu| LUT University| Queensland University of Technology| University of Virginia| BASF SE| IT Strategy & Transformation Professional| Universität Siegen| Innov-acts Ltd| Temple University| Fox School of Business| European University Institute, San Domenico di Fiesole| European Commission| Virginia Tech, Pamplin College of Business| Virginia Polytechnic Institute and State University| University of Portsmouth| University of Aosta Valley| International Institute for Management Development, Lausanne| Capgemini UK Ltd | R2: 35239818900 | S2: 59849258600 | T2: 35239818900 | U2: - | V2: Austria| Spain| Hong Kong| Denmark| Romania| Hungary| Qatar| Belgium| Ireland| Poland| United States| Germany| Saudi Arabia| Switzerland| Netherlands| New Zealand| India| United Kingdom| Oman| Japan| Finland| South Africa| Morocco| Italy| France| Cyprus| Norway| Australia| Kuwait| Canada | W2: Sustainable Development in Higher Education Practices | X2: Transforming Management Education for Business Relevance
A3: Trust in Generative AI among Students: An exploratory study | B3: Amoozadeh, M.| Daniels, D.| Nam, D.| Kumar, A.| Chen, S.| Hilton, M.| Srinivasa Ragavan, S.| Alipour, M.A. | C3: 8 | D3: 58669011600| 58668959400| 57200512561| 58745732300| 58950677000| 56754178400| 57188555414| 55342288200 | E3: 2024 | F3: 45358 | G3: SIGCSE 2024 - Proceedings of the 55th ACM Technical Symposium on Computer Science Education | H3: English | I3: 71 | J3: 46.65 | K3: 10.1145/3626252.3630842 | L3: Conference Paper | N3: Simon Fraser University| Indian Institute of Technology Kanpur| Carnegie Mellon University| University of Houston | O3: 4 | P3: 60005837| 60018491| 60027950| 60021988 | Q3: University of Houston| Simon Fraser University| Carnegie Mellon University| Indian Institute of Technology Kanpur | R3: 58669011600 | S3: 55342288200 | T3: - | U3: - | V3: India| United States| Canada | W3: Integration of Robotics and Computational Thinking in Education | X3: Enhancing Programming Education through Collaborative Learning
A4: PixelSplat: 3D Gaussian Splats from Image Pairs for Scalable Generalizable 3D Reconstruction | B4: Charatan, D.| Li, S.L.| Tagliasacchi, A.| Sitzmann, V. | C4: 4 | D4: 57222107728| 59058332700| 25123272600| 57195995941 | E4: 2024 | F4: 45292 | G4: Proceedings of the IEEE Computer Society Conference on Computer Vision and Pattern Recognition | H4: English | I4: 127 | J4: 43.9 | K4: 10.1109/CVPR52733.2024.01840 | L4: Conference Paper | N4: Simon Fraser University| Massachusetts Institute of Technology| University of Toronto | O4: 3 | P4: 60022195| 60018491| 60016849 | Q4: Massachusetts Institute of Technology| Simon Fraser University| University of Toronto | R4: 57222107728 | S4: 57195995941 | T4: - | U4: - | V4: United States| Canada | W4: Image Segmentation, Deep Neural Networks and Object Detection | X4: Neural Representations for 3D Shape Reconstruction
A5: When Social Comparison Goes Awry: The Case of Pluralistic Ignorance | B5: Miller, D.T.| McFarland, C. | C5: 2 | D5: 24547388400| 7006712946 | E5: 2024 | F5: 45292 | G5: Social Comparison: Contemporary Theory and Research | H5: English | I5: 156 | J5: 41.93 | K5: 10.4324/9781003469490-14 | L5: Chapter | N5: Simon Fraser University| Princeton University | O5: 2 | P5: 60003269| 60018491 | Q5: Princeton University| Simon Fraser University | R5: 24547388400 | S5: 7006712946 | T5: - | U5: - | V5: United States| Canada | W5: - | X5: -
A6: The Human Phenotype Ontology in 2024: phenotypes around the world | B6: Gargano, M.A.| Matentzoglu, N.| Coleman, B.| Addo-Lartey, E.B.| Anagnostopoulos, A.V.| Anderton, J.| Avillach, P.| Bagley, A.M.| Bakštein, E.| Balhoff, J.P.| Baynam, G.| Bello, S.M.| Berk, M.| Bertram, H.| Bishop, S.| Blau, H.| Bodenstein, D.F.| Botas, P.| Boztug, K.| Čady, J.| Callahan, T.J.| Cameron, R.| Carbon, S.J.| Castellanos, F.| Caufield, J.H.| Chan, L.E.| Chute, C.G.| Cruz-Rojo, J.| Dahan-Oliel, N.| Davids, J.R.| Dieuleveult, M.| Souza, V.| de Vries, B.B.A.| Vries, E.| DePaulo, J.R.| Derfalvi, B.| Dhombres, F.| Diaz-Byrd, C.| Dingemans, A.J.M.| Donadille, B.| Duyzend, M.| Elfeky, R.| Essaid, S.| Fabrizzi, C.| Fico, G.| Firth, H.V.| Freudenberg-Hua, Y.| Fullerton, J.M.| Gabriel, D.L.| Gilmour, K.| Giordano, J.| Goes, F.S.| Moses, R.G.| Green, I.| Griese, M.| Groza, T.| Gu, W.| Guthrie, J.| Gyori, B.| Hamosh, A.| Hanauer, M.| Hanušová, K.| He, Y.| Hegde, H.| Helbig, I.| Holasová, K.| Hoyt, C.T.| Huang, S.| Hurwitz, E.| Jacobsen, J.O.B.| Jiang, X.| Joseph, L.| Keramatian, K.| King, B.| Knoflach, K.| Koolen, D.A.| Kraus, M.L.| Kroll, C.| Kusters, M.| Ladewig, M.S.| Lagorce, D.| Lai, M.-C.| Lapunzina, P.| Laraway, B.| Lewis-Smith, D.| Li, X.| Lucano, C.| Majd, M.| Marazita, M.L.| Martinez-Glez, V.| McHenry, T.H.| McInnis, M.G.| McMurry, J.A.| Mihulová, M.| Millett, C.E.| Mitchell, P.B.| Moslerová, V.| Narutomi, K.| Nematollahi, S.| Nevado, J.| Nierenberg, A.A.| Čajbiková, N.N.| Nurnberger, J.I.| Ogishima, S.| Olson, D.| Ortiz, A.| Pachajoa, H.| Nanclares, G.P.| Peters, A.| Putman, T.| Rapp, C.K.| Rath, A.| Reese, J.| Rekerle, L.| Roberts, A.M.| Roy, S.| Sanders, S.J.| Schuetz, C.| Schulte, E.C.| Schulze, T.G.| Schwarz, M.| Scott, K.| Seelow, D.| Seitz, B.| Shen, Y.| Similuk, M.N.| Simon, E.S.| Singh, B.| Smedley, D.| Smith, C.L.| Smolinsky, J.T.| Sperry, S.| Stafford, E.| Stefancsik, R.| Steinhaus, R.| Strawbridge, R.| Sundaramurthi, J.C.| Talapova, P.| Castano, J.A.T.| Tesner, P.| Thomas, R.H.| Thurm, A.| Turnovec, M.| van Gijn, M.E.| Vasilevsky, N.A.| Vlčková, M.| Walden, A.| Wang, K.| Wapner, R.| Ware, J.S.| Wiafe, A.A.| Wiafe, S.A.| Wiggins, L.D.| Williams, A.E.| Wu, C.| Wyrwoll, M.J.| Xiong, H.| Yalin, N.| Yamamoto, Y.| Yatham, L.N.| Yocum, A.K.| Young, A.H.| Yüksel, Z.| Zandi, P.P.| Zankl, A.| Zarante, I.| Zvolský, M.| Toro, S.| Carmody, L.C.| Harris, N.L.| Munoz-Torres, M.C.| Danis, D.| Mungall, C.J.| Köhler, S.| Haendel, M.A.| Robinson, P.N. | C6: 176 | D6: 57205369227| 55995233100| 57223987007| 58799366900| 7005821953| 55358983700| 23972137300| 6701402791| 43060996500| 8637283900| 14324494700| 7004458522| 56760657800| 55555286200| 57218540916| 57205368715| 57212143319| 56266713000| 23472047500| 58799397700| 57192690777| 57454524400| 25959932700| 57209759767| 55329017200| 57215269031| 7006581202| 23492044500| 26666618400| 7006137984| 58865254600| 58865185400| 35459485900| 58865118700| 7004398249| 6506801256| 17134972700| 57482295200| 6603889334| 24375975100| 54683806700| 55645792800| 55995422800| 58799484300| 57199166504| 7003796141| 23099581700| 57213535028| 36975473900| 7006078464| 57191251562| 7004026363| 58799549800| 58799456700| 55139651700| 19638535200| 58799456800| 58559518000| 55892870500| 7003914063| 57200751247| 58345021100| 7404942594| 57202943644| 57201570366| 58799367500| 56305849200| 58799367600| 58705407200| 25932216600| 58799367700| 48061091300| 14060234300| 59029143100| 57221544436| 8893458500| 58540254500| 58799340600| 26434305600| 14015783100| 24171041300| 57211913020| 57214815403| 37761873400| 56974503600| 59886894800| 58345021200| 55533211300| 7006257137| 12763977000| 58799519200| 35353379600| 8308311600| 58799549900| 57194229387| 35354747000| 57200797157| 58799340800| 56131232500| 36780200300| 35375901700| 57888342900| 35353542700| 6507241005| 58323199700| 35741445300| 15122879800| 58865053600| 46761435000| 55323268400| 57221545272| 24333249100| 15048513900| 58071887800| 57199237342| 58799368100| 36119091700| 20436954100| 7102698477| 57203081336| 57198058697| 57933616500| 6506423915| 57203053329| 58799550100| 56912268600| 12765090200| 7405639065| 57796361900| 8048773500| 58799427600| 55764250300| 57526401400| 6506725443| 57205417508| 56208851700| 24492599800| 57224945780| 57219242030| 57201985741| 14326449800| 57217332348| 55537473200| 8586593500| 40361488700| 36446872600| 16308434500| 55547129985| 35391056000| 59300332000| 58799519400| 57221544936| 15046143700| 57225966673| 58799368200| 57193909400| 58799485000| 55858911500| 55476303500| 35431694500| 8980819000| 7403881797| 55385641300| 6701475820| 55803046800| 56055885100| 58123331100| 6603093413| 6603002819| 57188535624| 21934921800| 57209446724| 6602880619| 23980415100| 57619638300| 7403719646 | E6: 2024 | F6: 45296 | G6: Nucleic Acids Research | H6: English | I6: 173 | J6: 37.25 | K6: 10.1093/nar/gkad1005 | L6: Article | M6: Gold|Green | N6: Harvard University| European Molecular Biology Laboratory| Massachusetts General Hospital| Medical Research Council| National Institute of Mental Health| Dalhousie University| Great Ormond Street Hospital for Children NHS Foundation Trust| Lawrence Berkeley National Laboratory| University of Colorado Anschutz Medical Campus| Rutgers - The State University of New Jersey, New Brunswick| University College London| University of Michigan, Ann Arbor| University of Pittsburgh| Northeastern University| University of New South Wales| Tohoku University| Technische Universität Dresden| SUNY Upstate Medical University| University of North Carolina at Chapel Hill| Universidad Javeriana| Instituto de Salud Carlos III| Jackson Laboratory| University of Vienna| University of Edinburgh| Charité – Universitätsmedizin Berlin| Université Paris 13| Sorbonne Université| Indiana University Bloomington| King's College London| Queen Mary University of London| Neuroscience Research Australia| McGill University| Northwell Health System| Deakin University| The Children's Hospital of Philadelphia| Radboud University Nijmegen| Hôpital Armand Trousseau| Hospital Universitario La Paz| Institut national de la santé et de la recherche médicale| Bioscientia Institut für Medizinische Diagnostik GmbH| Universidad ICESI| National Institutes of Health| Ludwig Maximilian University of Munich| University of Sydney| Assistance publique – Hôpitaux de Paris| Newcastle University| University of Pennsylvania| Imperial College London| Brigham and Women’s Hospital| Research Organization of Information and Systems| University of Oxford| Joint Support-Center for Data Science Research| Hospital Universitario 12 de Octubre| Max F. Perutz Laboratories| Children's Cancer Research Institute| Johns Hopkins University| Simon Fraser University| Vienna Biocenter| Columbia University| University of Toronto| South London and Maudsley NHS Foundation Trust| Medical University of Vienna| University of California at San Francisco| United States Department of Energy| Mayo Clinic Rochester, MN| University of Groningen| Shriners Hospitals for Children| University of British Columbia| Centers for Disease Control and Prevention| University of Marburg| Barwon Health| Cambridge University Hospitals NHS Foundation Trust| Hospital Universitario Araba| Charles University| Centro de Investigación Biomédica en Red| Tilburg University| Oregon State University| August Pi i Sunyer Biomedical Research Institute| University of Barcelona | O6: 79 | P6: 130829255| 127692143| 125649015| 60010887| 60015543| 60002746| 100465705| 60108590| 60103947| 60025111| 60136288| 60018805| 60021050| 60025778| 60007200| 60033182| 60023691| 60016849| 129882057| 60022036| 116759577| 60027565| 60018491| 60007174| 60013402| 60006183| 60001117| 60005248| 60004024| 60013384| 60021567| 60026124| 60002573| 60102054| 60002289| 60017145| 60023750| 60015913| 60013700| 60001422| 60000905| 60158017| 60009907| 60029929| 60022148| 60028392| 60028421| 60104561| 60001576| 60030315| 60010814| 60017488| 60016390| 60270066| 60022773| 60018207| 60006577| 60017336| 125622602| 60028717| 60000291| 130679822| 60018597| 60025988| 60028628| 60141178| 60030118| 60022109| 60021435| 60003158| 60010365| 60023077| 60002681| 60015765| 60028162| 60006222| 60016782| 112688391| 60016605| 60023469| 60028333| 128317671| 60029502| 60002494| 60021947| 60008435| 124821061| 60104957| 60259858| 60109349| 60015150| 60015879| 60010719| 60002634| 60026851| 60204338| 60025676| 60018353| 60018741| 60028589| 60026245| 130829582| 60005558| 60120069| 60119141| 107343748| 60011520| 100463463| 60006027| 101732084| 60021658| 60027272| 60014873| 60029582| 60212297| 60028884| 60006579| 60088543| 60025709| 60010710| 60033545| 121046122 | Q6: The Jackson Institute for Genomic Medicine| Semanticly| Rare Disease Ghana Initiative| The Jackson Laboratory| University of Pittsburgh| Harvard Medical School| Shriners Children's Northern California| Národní Ústav Duševního Zdraví, Klecany| Renaissance Computing Institute| The University of North Carolina at Chapel Hill| Perth Children's Hospital| Deakin University| Barwon Health| University of Michigan, Ann Arbor| Michigan Medicine| University of Michigan Medical School| University of California, San Francisco| University of Toronto| Nostos Genomics GmbH| Children's Cancer Research Institute, Vienna| Institute for Health Information and Statistics of the Czech Republic| Columbia University Irving Medical Center| Simon Fraser University| Lawrence Berkeley National Laboratory| Oregon State University| Johns Hopkins Bloomberg School of Public Health| Johns Hopkins University School of Medicine| Johns Hopkins University| Hospital Universitario 12 de Octubre| Shriners Hospitals for Children Montreal| AP-HP Assistance Publique - Hopitaux de Paris| EMBL’s European Bioinformatics Institute| Radboud University Medical Center| Donders Institute for Brain, Cognition and Behaviour| TRANZO Scientific Center for Care and Wellbeing| Tilburg University| Dalhousie University, Faculty of Medicine| Dalhousie University| Hôpital Armand-Trousseau| Sorbonne Université| Inserm| Laboratoire d'Informatique Médicale et d'Ingénieurie des Connaissances en e-Santé| Hôpital Saint-Antoine| Massachusetts General Hospital| University College London| University of Colorado Anschutz Medical Campus| University of Colorado School of Medicine| Centro de Investigación Biomédica En Red de Salud Mental| Universitat de Barcelona| Hospital Clínic de Barcelona| Institut d'Investigacions Biomèdiques August Pi i Sunyer - IDIBAPS| Addenbrooke's Hospital| Cambridge University Hospitals NHS Foundation Trust| Northwell Health System| Neuroscience Research Australia| Great Ormond Street Hospital for Children NHS Foundation Trust| National Institutes of Health (NIH)| National Institute of Allergy and Infectious Diseases (NIAID)| SNOMED International| Ludwig-Maximilians-Universität München| Klinikum der Universität München| Chinese HPO Consortium| Max Perutz Labs| Universität Wien| Northeastern University| Khoury College of Computer Sciences| The Children's Hospital of Philadelphia| Queen Mary University of London| Barts and The London School of Medicine and Dentistry| National Institute of Mental Health| The University of British Columbia| University of British Columbia, Faculty of Medicine| Universitätsklinikum Gießen und Marburg, Standort Marburg| Centre for Addiction and Mental Health| Hospital Universitario La Paz| Newcastle University| Brigham and Women's Hospital| Hospital Universitari Parc Taulí| Charles University| Fakultní Nemocnice v Motole| UNSW Sydney| Children's Medical Center| McGill Faculty of Medicine and Health Sciences| Université McGill| Indiana University School of Medicine| Tohoku University| Data Science| Universidad Icesi| Instituto de Investigación Sanitaria Bioaraba| Hospital Universitario Araba| Imperial College London| Medical Research Council| National Heart and Lung Institute| University of Oxford Medical Sciences Division| University of Oxford| Universitätsklinikum Carl Gustav Carus Dresden| Medizinische Fakultät Carl Gustav Carus| Technische Universität Dresden| SUNY Upstate Medical University| Norton College of Medicine | R6: 57205369227 | S6: 7403719646 | T6: 7403719646 | U6: - | V6: Austria| United Kingdom| Spain| Japan| France| Czech Republic| Ghana| China| United States| Germany| Colombia| Australia| Greece| Netherlands| Canada | W6: Genetic Insights and Treatment Strategies in Leukemia | X6: Genetic Screening and Exome Insights in Rare Diseases
A7: Indicators of Global Climate Change 2023: annual update of key indicators of the state of the climate system and human influence | B7: Forster, P.M.| Smith, C.| Walsh, T.| Lamb, W.F.| Lamboll, R.| Hall, B.| Hauser, M.| Ribes, A.| Rosen, D.| Gillett, N.P.| Palmer, M.D.| Rogelj, J.| Von Schuckmann, K.| Trewin, B.| Allen, M.| Andrew, R.| Betts, R.A.| Borger, A.| Boyer, T.| Broersma, J.A.| Buontempo, C.| Burgess, S.| Cagnazzo, C.| Cheng, L.| Friedlingstein, P.| Gettelman, A.| Gütschow, J.| Ishii, M.| Jenkins, S.| Lan, X.| Morice, C.| Mühle, J.| Kadow, C.| Kennedy, J.| Killick, R.E.| Krummel, P.B.| Minx, J.C.| Myhre, G.| Naik, V.| Peters, G.P.| Pirani, A.| Pongratz, J.| Schleussner, C.-F.| Seneviratne, S.I.| Szopa, S.| Thorne, P.| Kovilakam, M.V.M.| Majamäki, E.| Jalkanen, J.-P.| Van Marle, M.| Hoesly, R.M.| Rohde, R.| Schumacher, D.| Van Der Werf, G.| Vose, R.| Zickfeld, K.| Zhang, X.| Masson-Delmotte, V.| Zhai, P. | C7: 59 | D7: 35547807400| 57191980050| 57224086983| 56599171800| 56705370600| 7401720543| 56684259500| 26635870100| 57218420069| 7006130951| 7401916795| 36151443700| 25822837600| 6602484429| 7404105326| 23993876900| 55206018900| 58476226100| 7006188068| 55051868600| 6506634320| 57221765266| 13607567200| 57192370335| 6602135031| 25031430500| 35203289700| 8507223000| 57201352727| 55801282300| 43261917100| 55917306500| 54894523000| 57223813189| 57191592471| 6602579613| 8513127600| 7003777747| 56244473600| 10639594300| 25321144500| 26421368700| 19337864100| 7003499456| 15726660300| 9272538400| 55832509400| 57348373000| 8359737300| 56957126200| 55189762400| 8314032200| 57210598663| 9045036800| 6603344816| 23010937900| 56005684100| 57202733911| 55543826100 | E7: 2024 | F7: 45448 | G7: Earth System Science Data | H7: English | I7: 154 | J7: 33.56 | K7: 10.5194/essd-16-2625-2024 | L7: Article | M7: Gold|Green | N7: Chinese Academy of Meteorological Sciences| University of Bristol| Ludwig Maximilian University of Munich| Bureau of Meteorology Australia| Imperial College London| International Institute for Applied Systems Analysis, Laxenburg| University of Oxford| Centre national d'études spatiales| University of Leeds| Ca' Foscari University of Venice| École polytechnique| Université PSL| Centre for International Climate and Environmental Research| Mercator Research Institute on Global Commons and Climate Change| Simon Fraser University| Institut de recherche pour le développement| CAS - Institute of Atmospheric Physics| Wageningen University & Research| Université Paris Cité| Université Fédérale Toulouse Midi-Pyrénées| Université Paris-Est Créteil| Met Office| Mercator Océan| Japan Meteorological Agency| University of Colorado Boulder| École normale supérieure| University of Oslo| Euro-Mediterranean Center on Climate Change| Institut Polytechnique de Paris| Humboldt University of Berlin| United States Department of Energy| Service hydrographique et océanographique de la marine| École des Ponts ParisTech| Sorbonne Université| University of Exeter| Paris-Est Sup| Potsdam Institute for Climate Impact Research| Helmholtz-Zentrum Hereon| Max Planck Institute for Meteorology| Swiss Federal Institute of Technology Zurich| Maynooth University| Université Paris-Saclay| National Oceanic and Atmospheric Administration| Commissariat à l’énergie atomique et aux énergies alternatives| CNRS| Météo France| Environment and Climate Change Canada| Finnish Meteorological Institute| University of California at San Diego| Chinese Academy of Sciences| NASA Langley Research Center| Université Paul Sabatier Toulouse III| Pacific Northwest National Laboratory | O7: 53 | P7: 60012070| 60019497| 60018258| 60026851| 60159447| 60015150| 60099375| 60025858| 60028770| 60027245| 60008134| 60000673| 60020650| 60116794| 60008506| 60024826| 130831207| 119771982| 60019499| 60016211| 60027716| 60026479| 60000179| 60019908| 60108665| 60105757| 127190910| 60024168| 60025288| 113958672| 60082966| 60013494| 60028717| 60255200| 60000762| 60045588| 60029937| 60106017| 60007816| 60026281| 113737465| 117553207| 60018491| 60027451| 60028564| 60000221| 60008778| 60004156| 60023471| 60000854| 60033178| 131347367| 60023018| 60030612| 129932660 | Q7: University of Leeds| International Institute for Applied Systems Analysis, Laxenburg| Met Office| University of Oxford| Mercator Research Institute on Global Commons and Climate Change| Imperial College London| Institut für Atmosphäre und Klima| ETH Zürich| Météo France| Université de Toulouse| CNRS Centre National de la Recherche Scientifique| Environment and Climate Change Canada| University of Bristol| Mercator Océan| Bureau of Meteorology Australia| CICERO Senter for Klimaforskning| Ecwmf| NOAA's National Centers for Environmental Information (NCEI)| Chinese Academy of Sciences| Institute of Atmospheric Physics Chinese Academy of Sciences| National Oceanic and Atmospheric Administration| University of Exeter| École Normale Supérieure| Institut Pierre-Simon Laplace| Université PSL| Laboratoire de Météorologie Dynamique| Climate Resource| Meteorological Research Institute| Helmholtz-Zentrum Hereon GmbH| Verdun Hospital| Fondazione Centro Euro-Mediterraneo sui Cambiamenti Climatici| Università Ca' Foscari Venezia| Ludwig-Maximilians-Universität München| Climate Analytics| Humboldt-Universität zu Berlin| Laboratoire des Sciences du Climat et de l'Environnement| Université de Versailles Saint-Quentin-en-Yvelines| Université Paris-Saclay| Commissariat a l'Energie Atomique et aux Energies Alternatives| Maynooth University| Berkeley Earth| NOAA/National Centers for Environmental Information| Simon Fraser University| Chinese Academy of Meteorological Sciences| Max Planck Institute for Meteorology| University of Colorado Boulder| Cooperative Institute for Research in Environmental Sciences| Wageningen University & Research| Pacific Northwest National Laboratory| NASA Langley Research Center| Finnish Meteorological Institute| Delteras| Scripps Institution of Oceanography| University of California, San Diego| Data for Action Foundation | R7: 35547807400 | S7: 55543826100 | T7: 35547807400 | U7: - | V7: Austria| United Kingdom| Japan| Finland| Italy| France| Norway| China| Ireland| United States| Germany| Australia| Switzerland| Netherlands| Canada | W7: Climate Variability and Tropical Cyclone Dynamics | X7: Global Ocean Heat and Salinity Dynamics
A8: Unearthing grounded normative theory: practices and commitments of empirical research in political theory | B8: Ackerly, B.| Cabrera, L.| Forman, F.| Johnson, G.F.| Tenove, C.| Wiener, A. | C8: 6 | D8: 8537848200| 59863939300| 55652948500| 55456265300| 57205450261| 7006864011 | E8: 2024 | F8: 45292 | G8: Critical Review of International Social and Political Philosophy | H8: English | I8: 63 | J8: 30.99 | K8: 10.1080/13698230.2021.1894020 | L8: Article | N8: Vanderbilt University| University of Hamburg| Simon Fraser University| Griffith University Queensland| University of British Columbia| University of California at San Diego | O8: 6 | P8: 60003915| 60032987| 60030612| 60018491| 60010365| 60028229 | Q8: Vanderbilt University| Griffith University| University of California, San Diego| Simon Fraser University| The University of British Columbia| Universität Hamburg | R8: 8537848200 | S8: 7006864011 | T8: 8537848200 | U8: - | V8: United States| Germany| Australia| Canada | W8: Justice, Autonomy, and Democracy in Global Contexts | X8: Global Justice and Human Rights Responsibilities
A9: Effect of Risk Mitigation Guidance opioid and stimulant dispensations on mortality and acute care visits during dual public health emergencies: retrospective cohort study | B9: Slaunwhite, A.| Min, J.E.| Palis, H.| Urbanoski, K.| Pauly, B.| Barker, B.| Crabtree, A.| Bach, P.| Krebs, E.| Dale, L.| Meilleur, L.| Nosyk, B. | C9: 12 | D9: 56479230500| 58856686100| 56397157400| 6506201836| 6603498334| 56100493400| 37048663600| 15759134700| 56338995600| 57216415837| 57220055812| 12809172100 | E9: 2024 | F9: 45292 | G9: BMJ | H9: English | I9: 76 | J9: 30.13 | K9: 10.1136/bmj-2023-076336 | L9: Article | M9: Hybrid gold|Green | N9: British Columbia Centre on Substance Use| Simon Fraser University| University of Victoria BC| University of British Columbia| BC Centre for Disease Control| Provincial Health Services Authority | O9: 6 | P9: 60010365| 60012171| 130408287| 60023077| 60003122| 60082761| 114434791| 60018491| 60138516| 60028379 | Q9: The University of British Columbia| BC Centre for Disease Control| Centre for Advancing Health Outcomes| University of British Columbia, Faculty of Medicine| University of Victoria| Canadian Institute for Substance Use Research| First Nations Health Authority (West Vancouver, BC)| Simon Fraser University| British Columbia Centre on Substance Use| British Columbia Cancer Agency | R9: 56479230500 | S9: 12809172100 | T9: 12809172100 | U9: - | V9: Canada | W9: Opioid Use and Management in Healthcare | X9: Heroin Treatment and Safe Supply Strategies
A10: Human-LLM Collaborative Annotation Through Effective Verification of LLM Labels | B10: Wang, X.| Kim, H.| Rahman, S.| Mitra, K.| Miao, Z. | C10: 5 | D10: 57223025368| 56510426600| 57213470195| 58754481800| 57210125029 | E10: 2024 | F10: 45423 | G10: Conference on Human Factors in Computing Systems - Proceedings | H10: English | I10: 66 | J10: 28.75 | K10: 10.1145/3613904.3641960 | L10: Conference Paper | M10: Gold | N10: Purdue University| Simon Fraser University | O10: 2 | P10: 60009254| 121112693| 60018491 | Q10: Purdue University| Megagon Labs| Simon Fraser University | R10: 57223025368 | S10: 57210125029 | T10: - | U10: - | V10: United States| Canada | W10: Machine Learning Techniques in Sentiment Analysis | X10: Transformative Approaches in Language Model Performance
A11: Theorizing place and aging: Enduring and novel issues in environmental gerontology | B11: Oswald, F.| Wahl, H.-W.| Wanka, A.| Chaudhury, H. | C11: 4 | D11: 7005448758| 7102344394| 56320488900| 9039040400 | E11: 2024 | F11: 45400 | G11: Handbook on Aging and Place | H11: English | I11: 13 | J11: 28.55 | K11: - | L11: Chapter | N11: Goethe University Frankfurt| Simon Fraser University| Heidelberg University | O11: 3 | P11: 60007762| 60016908| 60018491 | Q11: Goethe-Universität Frankfurt am Main| Universität Heidelberg| Simon Fraser University | R11: 7005448758 | S11: 9039040400 | T11: 7005448758 | U11: - | V11: Germany| Canada | W11: Urban Green Spaces and Community Wellbeing | X11: Aging-In-Place Strategies for Enhanced Quality of Life
A12: Global estimates on the number of people blind or visually impaired by cataract: a meta-analysis from 2000 to 2020 | B12: Pesudovs, K.| Lansingh, V.C.| Kempen, J.H.| Tapply, I.| Fernandes, A.G.| Cicinelli, M.V.| Arrigo, A.| Leveziel, N.| Resnikoff, S.| Taylor, H.R.| Sedighi, T.| Flaxman, S.| Bikbov, M.M.| Braithwaite, T.| Bron, A.| Cheng, C.-Y.| Del Monte, M.A.| Ehrlich, J.R.| Ellwein, L.B.| Friedman, D.| Furtado, J.M.| Gazzard, G.| George, R.| Hartnett, M.E.| Jonas, J.B.| Kahloun, R.| Khairallah, M.| Khanna, R.C.| Leasher, J.| Little, J.-A.| Nangia, V.| Nowak, M.| Peto, T.| Ramulu, P.| Topouzis, F.| Tsilimbaris, M.| Wang, Y.X.| Wang, N.| Bourne, R.| Pesudovs, K.| Lansingh, V.C.| Kempen, J.H.| Tapply, I.| Fernandes, A.G.| Cicinelli, M.V.| Arrigo, A.| Leveziel, N.| Briant, P.S.| Vos, T.| Flaxman, S.| Abate, Y.H.| Abdollahi, M.| Abdollahi, M.| Abebe, A.M.| Abiodun, O.| Aboagye, R.G.| Abrha, W.A.| Abualruz, H.| Ali, H.A.| Abu-Gharbieh, E.| Aburuz, S.| Adal, T.G.G.| Adane, M.M.| Addo, I.Y.| Adnani, Q.E.S.| Afzal, M.S.| Aghamiri, S.| Ahinkorah, B.O.| Ahmad, A.| Ahmad, S.| Ahmadi, A.| Ahmed, A.| Ahmed, H.| Alfaar, A.S.| Ali, A.| Ali, S.S.S.| Altaf, A.| Amu, H.| Androudi, S.| Anguita, R.| Anil, A.| Anvari, S.| Anyasodor, A.E.| Appiah, F.| Arabloo, J.| Arafat, M.| Areda, D.| Arefnezhad, R.| Aregawi, B.B.| Asgedom, A.A.| Ashraf, T.| Athari, S.S.| Atinafu, B.T.T.| Atout, M.M.W.| Atreya, A.| Ayatollahi, H.| Azzam, A.Y.| Babamohamadi, H.| Bagherieh, S.| Bahurupi, Y.| Baig, A.A.| Banik, B.| Bardhan, M.| Basu, S.| Batra, K.| Bayileyegn, N.S.| Bazvand, F.| Beyene, A.S.| Bhagat, D.S.| Bhagavathula, A.S.| Bhardwaj, P.| Bhaskar, S.| Bhatti, J.S.| Bineshfar, N.| Birck, M.G.| Bitra, V.R.| Braithwaite, T.| Burkart, K.| Bustanji, Y.| Butt, Z.A.| dos Santos, F.L.C.| Cámera, L.A.| Carneiro, V.L.A.| Cenderadewi, M.| Chandrasekar, E.K.| Chattu, V.K.| Chitranshi, N.| Chopra, H.| Chu, D.-T.| Coberly, K.| Coelho, J.M.| Cruz-Martins, N.| Dadras, O.| Dai, X.| Das, S.| Dascalu, A.M.| Dashti, M.| Dastmardi, M.| Demessa, B.H.| Demisse, B.| Dereje, D.| Derese, A.M.A.| Dervenis, N.| Devanbu, V.G.C.| Do, T.C.| Do, T.H.P.| dos Santos Figueiredo, F.W.| Dziedzic, A.M.| Edinur, H.A.| Efendi, F.| Ehrlich, J.R.| Ekholuenetale, M.| Ekundayo, T.C.| Sayed, I.E.| Elhadi, M.| Emamian, M.H.| Emamverdi, M.| Etemadimanesh, A.| Fagbamigbe, A.F.| Fahim, A.| Farrokhpour, H.| Fatehizadeh, A.| Feizkhah, A.| Desideri, L.F.| Fetensa, G.| Fischer, F.| Forouhari, A.| Foschi, M.| Fowobaje, K.R.| Gaidhane, A.M.| Gandhi, A.P.| Gebregergis, M.W.W.| Gebrehiwot, M.| Gebremariam, B.| Gerema, U.| Ghassemi, F.| Ghozy, S.| Golechha, M.| Goleij, P.| Goulart, B.N.G.| Guan, S.-Y.| Gudisa, Z.| Gupta, S.| Gupta, V.B.| Gupta, V.K.| Haj-Mirzaian, A.| Halimi, A.| Hallaj, S.| Hamidi, S.| Harorani, M.| Hasani, H.| Heyi, D.Z.| Hoan, N.Q.| Holla, R.| Hong, S.H.| Hosseinzadeh, M.| Hu, C.| Huang, J.J.| Huynh, H.-H.| Ibitoye, S.E.| Ilic, I.M.| Immurana, M.| Islam, M.R.| Islam, S.M.S.| Iwu, C.C.D.| Jacob, L.| Jairoun, A.A.| Janodia, M.D.| Jayaram, S.| Jindal, H.A.| Jokar, M.| Joseph, N.| Joshua, C.E.| Kadashetti, V.| Kalankesh, L.R.| Kalhor, R.| Kamath, S.| Kandel, H.| Kantar, R.S.| Karaye, I.M.| Kasraei, H.| Kaup, S.| Kaur, N.| Kaur, R.J.| Kayode, G.A.| Khader, Y.S.| Khajuria, H.| Khalilov, R.| Khatib, M.N.| Kisa, A.| Kosen, S.| Koyanagi, A.| Krishan, K.| Kulimbet, M.| Kumar, N.| Kurmi, O.P.| Lahariya, C.| Lan, T.| Landires, I.| Lee, M.| Lee, S.W.| Lee, W.-C.| Lim, S.S.| Little, J.-A.| Mahajan, P.B.| Maharaj, S.B.| Mahmoudi, A.| Mahmoudi, R.| Malhotra, K.| Mallhi, T.H.| Mansouri, V.| Manu, E.| Marzo, R.R.| Maugeri, A.| McAlinden, C.| Mebratu, W.| Meto, T.M.| Meng, Y.| Mersha, A.M.| Mestrovic, T.| Minh, L.H.N.| Misganaw, A.| Mishra, M.| Misra, S.| Mohamed, N.S.| Mohammadi, S.| Mohammed, M.| Mojiri-forushani, H.| Mokdad, A.H.| Vardanjani, H.M.| Moni, M.A.| Montazeri, F.| Moradi, M.| Motappa, R.| Mousavi, P.| Mulita, A.| Murray, C.J.L.| Naik, G.R.| Naik, G.| Nargus, S.| Natto, Z.S.| Nayak, B.P.| Negaresh, M.| Negash, H.| Nguyen, D.H.| Nguyen, P.T.| Nguyen, V.T.| Niazi, R.K.| Okonji, O.C.| Olagunju, A.T.| Olatubi, M.I.| Ordak, M.| Osuagwu, U.L.| Otstavnov, N.| Owolabi, M.O.| Padubidri, J.R.| Pandey, A.| Panos, G.D.| Pardhan, S.| Park, S.| Patel, J.| Pawar, S.| Peprah, P.| Petcu, I.-R.| Peyman, A.| Pham, H.T.| Pourazizi, M.| Quan, N.K.| Rahim, F.| Rahimi-Movaghar, V.| Rahman, M.H.U.| Rajaa, S.| Ramasamy, S.K.| Ramasubramani, P.| Ranjan, S.| Rashidi, M.-M.| Rath, R.S.| Rauf, A.U.| Rawaf, S.| Damavandi, A.R.| Redwan, E.M.M.| Roy, P.| Pramanik, K.R.| Saadatian, Z.| Sabour, S.| Saddik, B.| Saeed, U.| Safi, S.| Safi, S.Z.| Saghazadeh, A.| Sharif-Askari, F.S.| Sahebkar, A.| Sahraian, M.A.| Sakshaug, J.W.| Saleh, M.A.| Samadzadeh, S.| Samodra, Y.L.| Samuel, V.P.| Samy, A.M.| Saravanan, A.| Selvaraj, S.| Semnani, F.| Senapati, S.| Sethi, Y.| Seyedi, S.A.| Seylani, A.| Shaheen, A.A.| Shahid, S.| Shahwan, M.J.| Shaikh, M.A.| Sham, S.| Shamim, M.A.| Shannawaz, M.| Shashamo, B.B.| Shayan, M.| Shittu, A.| Shiue, I.| Shivakumar, K.M.| Shorofi, S.A.| Sibhat, M.M.| Siddig, E.E.| Silva, J.C.| Singh, J.A.| Singh, P.| Skiadaresi, E.| Solomon, Y.| Sousa, R.A.R.C.| Sreeramareddy, C.T.| Starodubov, V.I.| Subramaniam, M.D.| Susanty, S.| Tabatabaei, S.M.| Taye, B.T.| Teklay, G.| Temsah, M.-H.| Terefa, D.R.| Ticoalu, J.H.V.| Toma, T.M.| Tsatsakis, A.| Tsegay, G.M.| Tumurkhuu, M.| Tusa, B.S.| Ty, S.S.| Ubah, C.S.| Umair, M.| Umar, T.P.| Valizadeh, R.| Van den Eynde, J.| Watson, S.L.W.| Wonde, T.E.| Wondimagegn, G.S.| Xiao, H.| Yao, Y.| Nia, I.Y.| Yiğit, A.| Yismaw, Y.| Yon, D.K.| Yonemoto, N.| You, Y.| Yu, C.| Zastrozhin, M.S.| Zhao, H.| Ziafati, M.| Zielińska, M.| Zikarg, Y.T.| Zoladl, M.| Steinmetz, J.D. | C12: 407 | D12: 7004576721| 57194598546| 57216598048| 57205490881| 57192956381| 37260895200| 56331647600| 35321211600| 7006012071| 55550572900| 55368203500| 35190257400| 6507082164| 55522947000| 7103248039| 55539712500| 7005134758| 57190136174| 7004442455| 7402079597| 36801755000| 7004147260| 7402637163| 7005954310| 7202492953| 14119867400| 7004503022| 14060213400| 57197789738| 22634844800| 57201490837| 18437379100| 7005772831| 6602186935| 57194262710| 59324472200| 47962560100| 7404340277| 7103377631| 59156861800| 57209471470| 57216598048| 57205490881| 57192956381| 37260895200| 56331647600| 35321211600| 57196152334| 57223885848| 35190257400| 58492166600| 57940559800| 57780545000| 57191847346| 7003859089| 57221438826| 57210943530| 57216547615| 58096030700| 24586714800| 55886382800| 57221588673| 57217891132| 56305995900| 60106463900| 56009310800| 57208014122| 57194684030| 57210400531| 57218961022| 57193998515| 57199492030| 57222316680| 55319978300| 57822712300| 57188688612| 57201900507| 57190183918| 6603286512| 56809403300| 58164007300| 55967502900| 57192947419| 57210715590| 57208760927| 56380109600| 57193619525| 57209234011| 57221588539| 57208511484| 56366752600| 26653399600| 57225212559| 57195251851| 55856196800| 55991128900| 57208274797| 36983053200| 57225879659| 56491232000| 49460999600| 57216204052| 60122586900| 59832966100| 57219649874| 57305415100| 26653998700| 57209036705| 57327243700| 56398498300| 57226841442| 57192268582| 14043178800| 57892143000| 59046499100| 56394367200| 55522947000| 29067507300| 8847282600| 57202522739| 56373058500| 7003354253| 57213266524| 57206668799| 57200006411| 55743746500| 15029905100| 57217071283| 56239816300| 58139389800| 57194215965| 57203415019| 57205721978| 57221591169| 55531140000| 16038545200| 57372394700| 57215794006| 58537470400| 57211083382| 59157899800| 58961184500| 35368148900| 55879226900| 58537658400| 58955491100| 57197830836| 56155198800| 57287676500| 55301269100| 57190136174| 57189344745| 57204841448| 57207466387| 57212082248| 55181897800| 57216906536| 57268238000| 50861113000| 56996903600| 57210568865| 36782045000| 57226144762| 57201549628| 57211853863| 55508208800| 57225200038| 57192255295| 57203988822| 25031248900| 57217858382| 58955738100| 57192100745| 57203847504| 57216249028| 35271776100| 55337839100| 36006347600| 57217533849| 55958854600| 56982445100| 57861615300| 57217857409| 57194978364| 35073936800| 57210768364| 57913296900| 57209198237| 24366336000| 57195316126| 55632123200| 57326428900| 58959927100| 55270371800| 57211663879| 57201880569| 58956490200| 56135699200| 58260528100| 57212027408| 57210823522| 57215875071| 57215057958| 57218355467| 57204657478| 56779678900| 57208735762| 12791073000| 57221589240| 56086233400| 57221729841| 35292547200| 58491197900| 56724219200| 57200529685| 55670548600| 57193525413| 57226834655| 56719718400| 55598638900| 57194520224| 56967988200| 58344388100| 57190442227| 53463867400| 55654192600| 56639982500| 57193308858| 25825057100| 6603346067| 57226828739| 59269920500| 57202279708| 57288600700| 36678889900| 57219034567| 13205447400| 57218329495| 15063040000| 58964400000| 57223118056| 57394248700| 57201800433| 22634844800| 57168727200| 54883987800| 56646055600| 55397852300| 57224508895| 57214875058| 59348187900| 57195773594| 57163427600| 56740683100| 35325278500| 57215415625| 59156731000| 59835907300| 57205064523| 6507240107| 57201722696| 57202808713| 57213025989| 35501005200| 57208820453| 57193239265| 58144884000| 57200658736| 7004813962| 56556955100| 35119094400| 57924899400| 57736564200| 57577479200| 58627198400| 58491929200| 57224556036| 14825548600| 56020694000| 58491929300| 37000768500| 56639942500| 57226439849| 57209110507| 57220970272| 58366936400| 58491437100| 57204666021| 57222864302| 26029995700| 57200278115| 55992015900| 46062324800| 57202947262| 57222581892| 58295062300| 57210886573| 55629406000| 7003706887| 57384211300| 59222700400| 58594958600| 57200369019| 57094897500| 16744344900| 58627023500| 56266621400| 57930597600| 23052247800| 6507646446| 57208867497| 57205681553| 58321724400| 57229805800| 58290259300| 57324471900| 57196051098| 57215346048| 6602475959| 57471988800| 59012858000| 58956986100| 58242338100| 56303466100| 16307842100| 23020079300| 36612315100| 57219477293| 35620794800| 55634259200| 56161060900| 26639699900| 57219968932| 35300521200| 7201797507| 25951754100| 57363130700| 12142874900| 36973661300| 58290959400| 57223264725| 57224511550| 38062239700| 57862678600| 57917244500| 57222325334| 57202954176| 57208126144| 6601974519| 57203122601| 58031551200| 58030336800| 56349680200| 57223025060| 57209496707| 16418068900| 35811219800| 57221603938| 35086976700| 57222351357| 55879555400| 8576007400| 7404421736| 57202809996| 37100428500| 57220875005| 57218215064| 57212263335| 6701820838| 58890971900| 57203516467| 55935372700| 57221614117| 55782858000| 56115852000| 57422760200| 57580368800| 59676110000| 35596169100| 57221594727| 59156725100| 57216200356| 57682292500| 57224538923| 56641365200| 57221311061| 57192641339| 56507221200| 7401463790| 57207759070| 57194082186| 57214631433| 57026732300| 58942491800| 57820497600| 57217253497| 57193675906| 57204947657| 49865138500| 57208140344| 56728932200| 59742707300| 58978107400| 58491440100| 57223092789| 53980736300| 57221591053 | E12: 2024 | F12: 45505 | G12: Eye (Basingstoke) | H12: English | I12: 65 | J12: 27.74 | K12: 10.1038/s41433-024-02961-1 | L12: Article | M12: Hybrid gold|Green | N12: Tsinghua University| Temple University| Shahid Beheshti University of Medical Sciences| Qazvin University of Medical Sciences| University of Leeds| London School of Hygiene and Tropical Medicine| University of Bern| Wolkite University| Dire Dawa University| Nova Southeastern University| Shiraz University of Medical Sciences| King Saud bin Abdulaziz University for Health Sciences| University of Thessaly| Charité – Universitätsmedizin Berlin| University of Southern Denmark| University of Sharjah| Moorfields Eye Hospital NHS Foundation Trust| University of Minho| Medical University of Warsaw| Al-Shifa Trust Eye Hospital| University of Human Development| Amity University, Noida| Asian Institute of Medicine, Science & Technology| University of Technology Sydney| Universidade Federal do Rio Grande do Sul| Sungkyunkwan University| Bashkir State Medical University| Northwell Health System| Baptist Hospital Miami| Public Health Foundation of India| Federal Employment Agency| University of Khartoum| University of Washington| Jahrom University of Medical Science| Ludwig Maximilian University of Munich| Juntendo University| Sri Balaji Vidyapeeth University| Hywel Dda University Health Board| Duy Tan University| Leipzig University| National Center of Neurology and Psychiatry Kodaira| Institute of Nano Science and Technology| Philadelphia University| Moscow Institute of Physics and Technology| Shaqra University| Kristiania University College| Hanoi Medical University| Kermanshah University of Medical Sciences| Madda Walabu University| Ardabil University of Medical Sciences| United Arab Emirates University| Jimma University Ethiopia| Kyung Hee University| Mayo Clinic Rochester, MN| Vita-Salute San Raffaele University| Ulster University| San Martino Hospital Genoa| James Cook University Queensland| Utrecht University| University of South Florida| Queen's University Belfast| Vision Research Foundation India| McMaster University| Dilla University| Cambridge University Hospitals NHS Foundation Trust| Mansoura University| Hebei University of Chinese Medicine| The University of the West Indies| Mashhad University of Medical Sciences| Guilan University of Medical Sciences| Chitkara University| Aristotle University of Thessaloniki| Anglia Ruskin University| Thomas Jefferson University| Harvard University| Massachusetts General Hospital| University of Genoa| University of New South Wales| Singapore National Eye Center| University of Utah| Bucharest University of Economic Studies| University Hospital Center of Santo António| Vietnam National University, Hanoi| Indira Gandhi Medical College| Shahroud University of Medical Sciences| South Eastern Sydney and Illawarra Area Health Service| Arak University of Medical Sciences| Coventry University| Abdul Wali Khan University Mardan| Cancer Institute NSW| Al Jouf University| Saveetha Institute of Medical and Technical Sciences (Deemed to be University)| University of Calgary| Washington University St. Louis| Tulane University| Universitas Airlangga| Université de Poitiers| Can Tho University of Medicine and Pharmacy| Bowen University| Abasyn University | O12: 285 | P12: 131479195| 60029251| 60025488| 60003828| 60002746| 60028842| 60077515| 60071181| 128824525| 60017488| 60014992| 60002306| 60009622| 60004688| 60032653| 60020859| 60136196| 60011463| 60028333| 60118547| 60026553| 60170478| 60000913| 60026851| 60227248| 60011520| 60005518| 60030713| 60017161| 60024285| 60025778| 60022590| 60007651| 60008088| 60022148| 60013148| 60026060| 60025134| 60012708| 60016908| 60257150| 126573089| 60055372| 60050038| 60020023| 60027165| 60012831| 60019600| 60020730| 105526379| 60110371| 60029738| 60015891| 60026834| 60015066| 60015331| 60012413| 60026707| 60073453| 60121475| 108227545| 60009982| 60280051| 60016390| 60000905| 60015481| 60091926| 60028548| 60015150| 130346998| 60027708| 60123791| 60123830| 60021948| 60023794| 60109528| 60126119| 60116801| 60109536| 60067411| 60121161| 60070813| 60008665| 60064180| 60109530| 60071189| 60088090| 60069388| 60070625| 60018934| 60023932| 60110524| 60273000| 106139693| 60022730| 60071726| 60071723| 60023146| 60023588| 60089631| 60008042| 60026245| 60107589| 60268797| 113675538| 60025812| 60010987| 60016691| 60108918| 60110821| 60020449| 60001248| 126595830| 60071885| 60159438| 60024852| 60105817| 130003783| 60025928| 60003892| 60109448| 60104681| 60070610| 60012874| 60054151| 114825832| 126389796| 60015290| 60273389| 60024530| 60024502| 60020609| 60110819| 60010859| 60017837| 60031146| 60031892| 60071196| 60122734| 60010571| 60183191| 60071205| 112560804| 60032270| 126259648| 126752312| 60106790| 60002494| 60191838| 60006558| 60111763| 60021221| 60031331| 60014171| 60160817| 60019666| 60008557| 60281827| 60020475| 126006143| 60019870| 60069416| 60021600| 60016849| 60109334| 60109606| 60019544| 60113205| 60071364| 60277921| 60007249| 60034027| 60105804| 60030280| 60029622| 60279801| 60030452| 60033150| 60031210| 60109512| 60023925| 60109870| 124442996| 60118264| 60018756| 60027573| 60000906| 60032354| 60069383| 60006270| 60277094| 60033041| 60072594| 60072595| 60103657| 60196819| 60027550| 60001117| 60005248| 60017326| 60025392| 60120846| 60025153| 60107402| 60120582| 101593964| 131315216| 129930539| 60094583| 128309870| 60109529| 131329069| 60018491| 60005558| 60272432| 129662190| 60009057| 60006726| 130346953| 60109519| 60072223| 60018805| 60029929| 60022761| 60015277| 60032420| 60030612| 60113238| 60031286| 60071376| 60016017| 60015855| 60016524| 60016728| 106027843| 60111656| 60025278| 60017994| 60005455| 126239588| 60068815| 60068827| 60004955| 60084853| 60121699| 60025709| 60021902| 60104561| 60029937| 60003299| 131361114| 60042202| 60103927| 60089253| 100859372| 60105258| 60089223| 60026537| 60080427| 60013933| 60008469| 60189901| 129930604| 121177438| 60029304| 60024099| 60159706| 60001654| 60109780| 60078170| 60032724| 60007989| 60051534| 60076774| 60071969| 60086039| 60111756| 60021134| 60017672| 120877404| 100425036| 60018526| 60108730| 60031828| 126709567| 60115218| 60010261| 60022756| 125108446| 125339222| 60029305| 60211621| 60007511| 60017552| 60014569| 100777094| 60006000| 60071706| 131329379| 60007506| 60104126| 60122524| 60090667| 60018894| 60010146| 124177188| 60023998| 60170432| 60029306| 60199677| 60022095| 60138458| 60026005| 127190966| 60010799| 60120552| 60105852| 60031004| 60112701| 60030988| 60020828| 60189490| 60017803| 60024925| 60027086| 60004582| 116405671| 60026470| 60007740| 60156622| 115259292| 60071418| 60058195| 60031569| 60006448| 60190660| 60069009| 60010499| 60000308| 60199609| 60018680| 60272430| 122729825| 60025016| 60030816| 60015138| 60027272| 60012070| 60163612| 60107810| 60251038| 60275293| 60008488| 60254882| 122695288| 60032838| 60104452| 60104340| 60282908| 60069380| 60111140| 129930588| 101261297| 60022158| 60092393| 128660038| 60278951| 60105168| 60123785| 60001500| 60123810| 60028717| 60112602| 60227738| 60231631| 60012022| 60019160| 60113249| 60016618| 60020187| 60078092| 60286095| 60006577| 60005281| 60072733| 131219386| 114000948| 60270066| 60032480| 60012954| 60010037| 60017810| 60109516| 60022265| 107552774| 60029230| 60105917| 60280532| 60138359| 60281174| 112086188| 60001508| 60069625| 60245372| 60025615| 60105203| 60013183| 60069399| 122277676| 60001524| 60016280| 60018917| 60030398| 60078536| 60021077| 60121253| 60025063| 60109514| 115235305| 60003970| 60342338| 60279163| 60014966| 60005200| 60008724| 60006433| 60000231| 122280559| 60001873| 60017451| 60032116| 60023691| 121489850| 60116386| 60012293| 60033436 | Q12: HelpMeSee| University of Miami| The University of Utah| Massachusetts Eye and Ear| Harvard Medical School| Schepens Eye Research Institute| Myungsung Christian Medical Center| Addis Ababa University| Sight for Souls| Addenbrooke's Hospital| Universidade Federal de São Paulo| University of Calgary| Università Vita-Salute San Raffaele| San Raffaele Scientific Institute| Université de Poitiers| Centre Hospitalier Universitaire de Poitiers| Brien Holden Vision Institute| UNSW Medicine| UNSW Sydney| Melbourne School of Population and Global Health| University of Melbourne| School of Medicine| Anglia Ruskin University| University of Oxford| Ufa Eye Research Institute| King's College London| Guy's and St Thomas' NHS Foundation Trust| Centre Hospitalier Universitaire Dijon Bourgogne| National University of Singapore| Singapore Eye Research Institute| University of Michigan, Ann Arbor| University of Michigan W.K. Kellogg Eye Center| National Eye Institute (NEI)| Universidade de São Paulo| University College London| UCL Institute of Ophthalmology| Medical Research Foundation, Chennai| Sankara Nethralaya| Stanford University| Universität Heidelberg| Medizinische Fakultät Mannheim| Associated Ophthalmologists of Monastir| CHU Fattouma-Bourguiba| Université de Monastir| L.V. Prasad Eye Institute India| University of Rochester| University of Rochester School of Medicine and Dentistry| Nova Southeastern University| Ulster University| Suraj Eye Institute| University of Social Sciences, Lodz| Queen's University Belfast| Wilmer Eye Institute| "University General Hospital of Thessaloniki "AHEPA""| School of Medicine| Aristotle University of Thessaloniki| University of Crete Medical School| Capital Medical University| Beijing Tongren Hospital, Capital Medical University| HelpMeSee, Inc.| Mexican Institute of Ophthalmology| Harvard University| Myungsung Medical College| Cambridge University Hospitals NHS Foundation Trust| Inserm| University of Washington| Institute for Health Metrics and Evaluation| University of Washington School of Medicine| Imperial College London| Aleta Wondo Hospital| Tehran University of Medical Sciences| The Institute of Pharmaceutical Sciences (TIPS)| School of Pharmacy| Shiraz University of Medical Sciences| School of Medicine| Debre Berhan University| Babcock University| University of Health and Allied Sciences, Ghana| Aksum University| Al-Zaytoonah University of Jordan| University of Human Development| University of Sharjah| United Arab Emirates University| The University of Jordan| Wolkite University| Bahir Dar University| Cancer Institute NSW| Universitas Padjadjaran| University of Management and Technology Lahore| Shahid Beheshti University of Medical Sciences| University of Technology Sydney| Shaqra University| Abasyn University| Labanese American University| Shahrekord University of Medical Sciences| Institute of Endemic Diseases Sudan| Khartoum University| Swiss Tropical and Public Health Institute Swiss TPH| Universität Basel| COMSATS University Islamabad | R12: 7004576721 | S12: 57221591053 | T12: 7004576721 | U12: - | V12: Ethiopia| Spain| Mexico| Panama| Denmark| Romania| Viet Nam| Taiwan| Ghana| Belgium| United States| Lesotho| Colombia| Switzerland| Turkey| Palestine| India| Iraq| Lebanon| Japan| South Africa| Italy| Indonesia| Norway| China| Tunisia| Australia| Portugal| Malaysia| Iran| Egypt| Libya| Nepal| Azerbaijan| Botswana| Singapore| Saudi Arabia| Poland| Germany| Greece| Netherlands| Sudan| Argentina| United Arab Emirates| United Kingdom| Finland| Serbia| Pakistan| France| Bangladesh| Trinidad and Tobago| Brazil| South Korea| Croatia| Kazakhstan| Nigeria| Jordan| Russian Federation| Canada | W12: Impact of Eye Health on Quality of Life | X12: Cataract Prevalence and Eye Health Outcomes
A13: Addressing climate change with behavioral science: A global intervention tournament in 63 countries | B13: Vlasceanu, M.| Doell, K.C.| Bak-Coleman, J.B.| Todorova, B.| Berkebile-Weinberg, M.M.| Grayson, S.J.| Patel, Y.| Goldwert, D.| Pei, Y.| Chakroff, A.| Pronizius, E.| van den Broek, K.L.| Vlasceanu, D.| Constantino, S.| Morais, M.J.| Schumann, P.| Rathje, S.| Fang, K.| Aglioti, S.M.| Alfano, M.| Alvarado-Yepez, A.J.| Andersen, A.| Anseel, F.| Apps, M.A.J.| Asadli, C.| Awuor, F.J.| Azevedo, F.| Basaglia, P.| Bélanger, J.J.| Berger, S.| Bertin, P.| Białek, M.| Bialobrzeska, O.| Blaya-Burgo, M.| Bleize, D.N.M.| Bø, S.| Boecker, L.| Boggio, P.S.| Borau, S.| Bos, B.| Bouguettaya, A.| Brauer, M.| Brick, C.| Brik, T.| Briker, R.| Brosch, T.| Buchel, O.| Buonauro, D.| Butalia, R.| Carvacho, H.| Chamberlain, S.A.E.| Chan, H.-Y.| Chow, D.| Chung, D.| Cian, L.| Cohen-Eick, N.| Contreras-Huerta, L.S.| Contu, D.| Cristea, V.| Cutler, J.| D'Ottone, S.| De Keersmaecker, J.| Delcourt, S.| Delouvée, S.| Diel, K.| Douglas, B.D.| Drupp, M.A.| Dubey, S.| Ekmanis, J.| Elbaek, C.T.| Elsherif, M.| Engelhard, I.M.| Escher, Y.A.| Etienne, T.W.| Farage, L.| Farias, A.R.| Feuerriegel, S.| Findor, A.| Freira, L.| Friese, M.| Gains, N.P.| Gallyamova, A.| Geiger, S.J.| Genschow, O.| Gjoneska, B.| Gkinopoulos, T.| Goldberg, B.| Goldenberg, A.| Gradidge, S.| Grassini, S.| Gray, K.| Grelle, S.| Griffin, S.M.| Grigoryan, L.| Grigoryan, A.| Grigoryev, D.| Gruber, J.| Guilaran, J.| Hadar, B.| Hahnel, U.J.J.| Halperin, E.| Harvey, A.J.| Haugestad, C.A.P.| Herman, A.M.| Hershfield, H.E.| Himichi, T.| Hine, D.W.| Hofmann, W.| Howe, L.| Huaman-Chulluncuy, E.T.| Huang, G.| Ishii, T.| Ito, A.| Jia, F.| Jost, J.T.| Jovanović, V.| Jurgiel, D.| Kácha, O.| Kankaanpää, R.| Kantorowicz, J.| Kantorowicz-Reznichenko, E.| Mintz, K.K.| Kaya, I.| Kaya, O.| Khachatryan, N.| Klas, A.| Klein, C.| Klöckner, C.A.| Koppel, L.| Kosachenko, A.I.| Kothe, E.J.| Krebs, R.| Krosch, A.R.| Krouwel, A.P.M.| Kyrychenko, Y.| Lagomarsino, M.| Lamm, C.| Lange, F.| Cunningham, J.L.| Lees, J.| Leung, T.Y.| Levy, N.| Lockwood, P.L.| Longoni, C.| López Ortega, A.| Loschelder, D.D.| Lu, J.G.| Luo, Y.| Luomba, J.| Lutz, A.E.| Majer, J.M.| Markowitz, E.| Marsh, A.A.| Mascarenhas, K.L.| Mbilingi, B.| Mbungu, W.| McHugh, C.| Meijers, M.H.C.| Mercier, H.| Mhagama, F.L.| Michalakis, K.| Mikus, N.| Milliron, S.| Mitkidis, P.| Monge-Rodríguez, F.S.| Mora, Y.L.| Moreau, D.| Motoki, K.| Moyano, M.| Mus, M.| Navajas, J.| Nguyen, T.L.| Nguyen, D.M.| Nguyen, T.| Niemi, L.| Nijssen, S.R.R.| Nilsonne, G.| Nitschke, J.P.| Nockur, L.| Okura, R.| Öner, S.| Özdoğru, A.A.| Palumbo, H.| Panagopoulos, C.| Panasiti, M.S.| Pärnamets, P.| Paruzel-Czachura, M.| Pavlov, Y.G.| Payán-Gómez, C.| Pearson, A.R.| da Costa, L.P.| Petrowsky, H.M.| Pfattheicher, S.| Pham, N.T.| Ponizovskiy, V.| Pretus, C.| Rêgo, G.G.| Reimann, R.| Rhoads, S.A.| Riano-Moreno, J.| Richter, I.| Röer, J.P.| Rosa-Sullivan, J.| Ross, R.M.| Sabherwal, A.| Saito, T.| Sarrasin, O.| Say, N.| Schmid, K.| Schmitt, M.T.| Schoenegger, P.| Scholz, C.| Schug, M.G.| Schulreich, S.| Shreedhar, G.| Shuman, E.| Sivan, S.| Sjåstad, H.| Soliman, M.| Soud, K.| Spampatti, T.| Sparkman, G.| Spasovski, O.| Stanley, S.K.| Stern, J.A.| Strahm, N.| Suko, Y.| Sul, S.| Syropoulos, S.| Taylor, N.C.| Tedaldi, E.| Tinghög, G.| Huynh, L.D.T.| Travaglino, G.A.| Tsakiris, M.| Tüter, İ.| Tyrala, M.| Uluğ, Ö.M.| Urbanek, A.| Valko, D.| van der Linden, S.| van Schie, K.| van Stekelenburg, A.| Vanags, E.| Västfjäll, D.| Vesely, S.| Vintr, J.| Vranka, M.| Wanguche, P.O.| Willer, R.| Wojcik, A.D.| Xu, R.| Yadav, A.| Zawisza, M.| Zhao, X.| Zhao, J.| Żuk, D.| Van Bavel, J.J. | C13: 258 | D13: 57201915022| 56928398300| 55903994100| 57222539523| 57763404300| 58879811500| 58880289000| 57224210291| 58879181600| 55574863500| 57219339352| 57195274688| 58880289100| 36611494500| 55956840800| 58879653900| 57221697332| 58880125600| 7007006465| 36762163600| 57224629053| 58879811600| 6506365274| 37017949200| 58879181700| 57218951401| 57202683756| 58880125700| 55184651600| 57194216631| 57217067931| 56333322000| 56458870800| 57203316861| 57193085700| 57211574442| 56381610700| 10340985700| 57192594944| 57218555607| 57193404175| 56182089500| 35799380500| 57204783906| 57211658614| 21833273000| 57219655063| 57740477200| 57221908883| 35118536400| 58808743200| 57203370709| 57204694910| 21742150900| 37088275700| 58683973500| 56025663300| 57210406861| 58879811700| 57203910287| 58879971200| 56682807000| 57472656800| 13612418500| 57194424358| 57216158879| 36715802200| 58879340000| 57433426100| 57219005068| 57193547763| 6701593489| 58697915000| 57302201900| 57255464900| 57204695509| 53881265200| 15051465700| 57193337463| 12143724600| 24347103700| 58182813400| 57223188714| 50461185200| 57211203812| 55866447200| 57219761729| 56463654200| 57852497300| 57144130500| 15520639300| 57226624123| 7201880907| 56180262200| 57218691109| 57191706675| 8929220900| 57203983779| 57189632557| 55058817700| 35866830500| 55756820400| 57225946221| 56999872700| 53877524700| 55220137200| 7003507712| 55612718000| 56982589200| 57224625506| 56844125900| 36548185800| 36657297600| 37093234800| 24492154100| 35784412400| 58879654200| 57194418491| 57221786258| 56256131200| 56743290300| 57206240912| 39761914400| 37861554400| 56182003500| 57202855638| 36084708900| 6603963589| 57188825958| 57201639224| 35217976300| 36793244200| 36149518500| 16744097100| 58406745100| 57205117517| 56566285000| 55763866300| 57194495949| 57195276259| 24577314900| 7202957468| 55347628400| 55899207500| 57226195724| 36608662400| 57192701797| 57191955731| 55240163500| 57224085408| 56572338000| 9741634300| 7102492815| 57211642030| 57197734109| 55372835900| 57201644809| 36470426700| 15058239700| 57899354900| 58880127300| 56648059800| 58663761800| 55734672700| 37108213400| 57209663574| 36552994500| 57189691781| 12143170500| 59768843700| 56050496500| 58879813200| 57222172756| 57467767800| 56366548400| 57193236264| 14120128400| 59763944200| 57202706538| 58880291300| 56530440700| 29068063500| 58143972800| 7006736244| 14822630500| 55918105000| 55936861100| 57193323692| 54896392800| 12790445300| 57364050200| 57995728500| 51161934700| 57205366200| 57191710525| 57196461358| 56480308400| 57543042000| 57210161085| 57210113671| 55816086700| 53980370700| 58879972900| 23567212800| 57220058451| 57192957394| 23986129600| 57223205561| 33467815300| 57211939303| 57223426293| 56509076200| 17435737500| 55710814200| 55151470000| 57055910700| 58879655700| 57200691996| 57205079964| 58879813300| 57219487726| 55597247500| 36987292000| 57192170506| 56286113900| 58879500000| 57212245175| 55200845000| 57205262930| 58880291400| 57219014759| 25224071700| 57728566100| 55927816700| 8612330500| 58880291500| 57432992000| 57188690265| 56400693300| 57226104705| 54409938000| 56989668400| 57213817527| 57433130100| 6603904733| 55320899700| 57223203005| 56188307200| 58879183500| 16305967100| 35243826100| 58879183600| 59887554500| 36196022900| 56108320300| 55837186700| 58879973100| 22986966200 | E13: 2024 | F13: 45323 | G13: Science Advances | H13: English | I13: 145 | J13: 26.76 | K13: 10.1126/sciadv.adj5778 | L13: Article | M13: Gold|Green | N13: University of Wisconsin-Madison| Universidade Federal do Paraná| Leiden University| University of Melbourne| University of Pittsburgh| University of Michigan, Ann Arbor| Tohoku University| National Kaohsiung University of Science and Technology| University of Bern| University of Hamburg| Kochi University of Technology| Hebrew University of Jerusalem| Norwegian University of Science and Technology| Royal Holloway University of London| KU Leuven| University of Vienna| Clemson University| TBS Business School| University of Limerick| Macedonian Academy of Sciences and Arts| Ural Federal University| Inland Norway University of Applied Sciences| Universidad Adolfo Ibáñez| Universidade de São Paulo| Aarhus University| University of Padua| King's College London| Ghent University| Universidade Presbiteriana Mackenzie| Leuphana University of Lüneburg| University of Wrocław| Deakin University| Radboud University Nijmegen| The University of Auckland| Australian National University| Ludwig Maximilian University of Munich| Claremont Graduate University| National Agricultural Research Organisation Uganda| University of Economics Ho Chi Minh City| Comenius University| Georgetown University| The London School of Economics and Political Science| IRCCS Fondazione Santa Lucia - Roma| Canadian University Dubai| Northwestern University| Witten/Herdecke University| Ruhr University Bochum| Stanford University| Columbia University| University of the Sunshine Coast| University of Haifa| University of Stavanger| Nencki Institute of Experimental Biology of the Polish Academy of Sciences| University of St Andrews| Utrecht University| Bocconi University| Uskudar University| Seton Hall University| SS Cyril and Methodius University in Skopje| University of Novi Sad| École des hautes études en sciences sociales| Charles University| Pompeu Fabra University| Universidad Cooperativa de Colombia| Massachusetts Institute of Technology| Anglia Ruskin University| University of Geneva| Tampere University| Universidad Peruana Cayetano Heredia| Harvard University| University of Silesia in Katowice| Jagiellonian University in Kraków| University of Zurich| University of Economics, Prague| University of Córdoba| Linköping University| Université de Bretagne Sud| Northeastern University| University of York| Icahn School of Medicine at Mount Sinai| University of New South Wales| Japan Women's University| University of Hildesheim| University of SS Cyril and Methodius, Trnava| University of North Carolina at Chapel Hill| University of Salzburg| Université Fédérale Toulouse Midi-Pyrénées| Belgian National Fund for Scientific Research| American University of Sharjah| City University of Hong Kong| Princeton University| Cornell University| École normale supérieure| University of Colorado Boulder| University of Sussex| University of Oslo| University of Amsterdam| Université libre de Bruxelles| University of Massachusetts| University of Tübingen | O13: 173 | P13: 60021784| 60025988| 60030162| 60009982| 60012708| 60007989| 60018815| 60001361| 60015543| 60028628| 60076757| 60020306| 60014416| 60032350| 60019544| 60071237| 60015043| 60028333| 60190890| 60019702| 121551012| 60051229| 60010023| 60028229| 60104576| 60020486| 60110693| 60110710| 60000145| 60016147| 60031620| 60003812| 60016529| 60025233| 60072202| 60011644| 60110373| 60032179| 60002483| 60108591| 60088053| 60018869| 60028163| 60004718| 60010330| 60006594| 60025063| 60029681| 60020585| 60177637| 60011520| 60026553| 60103153| 60021918| 60116392| 60007903| 60003942| 60105484| 130965125| 60033316| 60026905| 60113192| 60030657| 60105533| 60033241| 60071043| 60029616| 60033125| 60006297| 60004517| 60002963| 60000015| 60028717| 60001987| 60015195| 60012521| 60020513| 60072633| 60021361| 60006191| 60019666| 60006303| 60000913| 60029622| 60014497| 60142023| 60025111| 60005322| 60009602| 60016418| 60070851| 60000221| 60071493| 60012513| 60242553| 60023588| 60010348| 60014383| 60010678| 60017317| 60109559| 60027550| 60007399| 60012614| 60071256| 60013983| 60014299| 60008435| 60018676| 60068801| 60021858| 128080537| 60011170| 60006876| 60019816| 60027295| 60022265| 60002999| 60070791| 60018805| 60008950| 60013141| 60009358| 60103702| 60007776| 60008734| 60031101| 60025778| 60027017| 60026610| 60279116| 60141284| 60003269| 60032607| 60021796| 60022195| 60014228| 60010365| 60116748| 60018491| 60002941| 60014313| 60023927| 60008088| 60071687| 60071594| 60008134| 60025070| 60000179| 60108665| 60105767| 60020595| 60033387| 60070041| 60005686| 60025272| 60003138| 60004518| 60109840| 60116768| 60012311| 60028378| 60029111| 60027981| 60106516| 60222522| 60032942| 60006225| 60017246| 128241199| 60104479| 60078566| 60023020| 60012981| 60087108| 60022113| 60003059| 113895860| 60023462| 60000239| 60017004| 60022132| 60163877| 60006796| 60031117| 60072629| 60021677| 60281380| 60008783| 60160279| 60031004| 60000481| 60160411| 60022109| 60008009| 60009789| 60017145| 60016605| 60021988| 60006925| 60138820| 60007363| 60013756 | Q13: New York University| Universität Wien| Columbia University| Harvard University| Stanford University| Universiteit Utrecht| Copernicus Institute of Sustainable Development| University of Pittsburgh School of Medicine| University of Pittsburgh| Northeastern University| Amazon.com, Inc.| Universität Oldenburg| IRCCS Fondazione Santa Lucia| Sapienza Università di Roma| Macquarie University| Universidad Peruana Cayetano Heredia| Universidade Federal do Parana| UNSW Sydney| UNSW Business School| University of Birmingham| Psychology Scientific Research Institute| Kenya Marine and Fisheries Research Institute| Rijksuniversiteit Groningen| Universität Hamburg| NYU Abu Dhabi| University of Bern| Université Côte d'Azur| Laboratoire d'Anthropologie et de Psychologie Cliniques, Cognitives et Sociales| Université Libre de Bruxelles| University of Wrocław| SWPS Uniwersytet Humanistycznospołeczny| Claremont Graduate University| Radboud Universiteit| NHH Norwegian School of Economics| Leuphana Universität Lüneburg| Universidade Presbiteriana Mackenzie| TBS Business School| University of Wisconsin-Madison| Universiteit van Amsterdam| Høgskolen i Innlandet| Kyiv School of Economics, Ukraine| Universiteit Maastricht| Maastricht University School of Business and Economics| Université de Genève| Slovak Academy of Sciences| Pomona College| KU Leuven| Pontificia Universidad Católica de Chile| University of Canterbury| King’s Business School| King's College London| University of Melbourne| Ulsan National Institute of Science and Technology| University of Virginia| Darden School of Business| Hebrew University of Jerusalem| Universidad Adolfo Ibáñez| Canadian University Dubai| Kieskompas–election compass| Universiteit Gent| Universitat Ramon Llull| Universitat Ramon Llull, ESADE| Université Rennes 2| Laboratoire de Psychologie : Cognition, Comportement, Communication (LP3C)| Universität des Saarlandes| Latvijas Universitāte| Aarhus Universitet| University of Leicester| University of Pennsylvania| University of Pennsylvania Annenberg School for Communications| Universität Salzburg| Lusófona University| Ludwig-Maximilians-Universität München| Univerzita Komenského v Bratislave| Universidad Torcuato Di Tella| Thammasat University| HSE University| Macedonian Academy of Sciences and Arts| Uniwersytet Jagielloński| Google LLC| Harvard Business School| Harvard Faculty of Arts and Sciences| Anglia Ruskin University| Universitetet i Bergen| Universitetet i Stavanger| College of Arts & Sciences| The University of North Carolina at Chapel Hill| Ruhr-Universitat Bochum| University of Limerick| University of York| Yerevan State University| University of Colorado Boulder| University of the Philippines Visayas| Reichman University| Baruch Ivcher School of Psychology, Reichman University| Universität Basel| Universitetet i Oslo| Polish Academy of Sciences| Nencki Institute of Experimental Biology of the Polish Academy of Sciences| University of Sussex | R13: 57201915022 | S13: 22986966200 | T13: 57201915022| 56928398300 | U13: - | V13: Austria| Spain| Hong Kong| Thailand| Denmark| Peru| Viet Nam| Taiwan| Belgium| Azerbaijan| Latvia| Israel| Uganda| Ireland| Poland| United States| Germany| Turkey| Switzerland| Colombia| Netherlands| New Zealand| Argentina| Sweden| United Arab Emirates| Chile| India| United Kingdom| Kenya| Japan| Finland| Serbia| France| Italy| North Macedonia| Ukraine| Czech Republic| Brazil| South Korea| Norway| Armenia| Philippines| Australia| Portugal| Tanzania| Russian Federation| Slovakia| Canada | W13: Consumer Behavior and Climate Change Awareness | X13: Public Perception and Policy on Climate Change
A14: Ego-Exo4D: Understanding Skilled Human Activity from First- and Third-Person Perspectives | B14: Grauman, K.| Westbury, A.| Torresani, L.| Kitani, K.| Malik, J.| Afouras, T.| Ashutosh, K.| Baiyya, V.| Bansal, S.| Boote, B.| Byrne, E.| Chavis, Z.| Chen, J.| Cheng, F.| Chu, F.-J.| Crane, S.| Dasgupta, A.| Dong, J.| Escobar, M.| Forigua, C.| Gebreselasie, A.| Haresh, S.| Huang, J.| Islam, M.M.| Jain, S.| Khirodkar, R.| Kukreja, D.| Liang, K.J.| Liu, J.-W.| Majumder, S.| Mao, Y.| Martin, M.| Mavroudi, E.| Nagarajan, T.| Ragusa, F.| Ramakrishnan, S.K.| Seminara, L.| Somayazulu, A.| Song, Y.| Su, S.| Xue, Z.| Zhang, E.| Zhang, J.| Castillo, A.| Chen, C.| Fu, X.| Furuta, R.| González, C.| Gupta, P.| Hu, J.| Huang, Y.| Huang, Y.| Khoo, W.| Kumar, A.| Kuo, R.| Lakhavani, S.| Liu, M.| Luo, M.| Luo, Z.| Meredith, B.| Miller, A.| Oguntola, O.| Pan, X.| Peng, P.| Pramanick, S.| Ramazanova, M.| Ryan, F.| Shan, W.| Somasundaram, K.| Song, C.| Southerland, A.| Tateno, M.| Wang, H.| Wang, Y.| Yagi, T.| Yan, M.| Yang, X.| Yu, Z.| Zha, S.C.| Zhao, C.| Zhao, Z.| Zhu, Z.| Zhuo, J.| Arbeláez, P.| Bertasius, G.| Damen, D.| Engel, J.| Farinella, G.M.| Furnari, A.| Ghanem, B.| Hoffman, J.| Jawahar, C.V.| Newcombe, R.| Park, H.S.| Rehg, J.M.| Sato, Y.| Savva, M.| Shi, J.| Shou, M.Z.| Wray, M. | C14: 100 | D14: 6506707692| 57275414000| 6506606617| 15835267300| 7101991704| 57189000025| 57205095020| 26633590100| 57220731251| 57220804935| 57318236300| 57318366600| 57218344541| 59817548500| 56902201800| 57318100500| 55481097000| 59443594200| 57217546079| 57940459900| 57202948995| 57219589640| 59834275700| 59032385600| 24824397800| 57208014001| 58770003800| 57202922615| 57191902055| 57540615800| 57567008600| 57221147449| 57189592926| 57201187934| 57191972719| 56883876200| 58770587200| 57985185200| 39862197800| 57201326191| 57222956828| 58832172100| 58770743100| 57219316165| 57219740329| 58769848600| 56684674200| 57212061068| 58830762100| 58630761400| 57201856134| 58775612600| 58586258600| 58770147700| 58770294300| 58769848700| 57204285999| 57217168889| 57221249368| 58705370000| 58770003900| 58769848800| 57189074561| 58770442500| 57223683709| 57226279285| 57222063914| 58770294400| 57224667085| 58770743300| 57192421769| 58770442600| 57218524944| 57216714939| 57207777807| 57574109700| 57188768295| 57763417900| 57111792500| 55364708900| 59777561900| 58451423500| 58770004000| 6505891154| 57142525700| 25654582700| 55246374000| 57191972987| 56348910300| 24331436200| 57209558746| 6701503911| 36445070000| 55713635500| 7004835775| 35230954300| 47962533500| 55252537400| 57222111581| 55941899900 | E14: 2024 | F14: 45292 | G14: Proceedings of the IEEE Computer Society Conference on Computer Vision and Pattern Recognition | H14: English | I14: 62 | J14: 21.43 | K14: 10.1109/CVPR52733.2024.01834 | L14: Conference Paper | N14: University of Bristol| University of Texas at Austin| University of Pennsylvania| University of California at Berkeley| Universidad de los Andes Colombia| International Institute of Information Technology Hyderabad| University of Minnesota Twin Cities| Georgia Institute of Technology| Johns Hopkins University| University of Catania| Simon Fraser University| University of North Carolina at Chapel Hill| King Abdullah University of Science and Technology| National University of Singapore| The University of Tokyo| University of Illinois at Urbana-Champaign| Carnegie Mellon University | O14: 17 | P14: 121905326| 60013372| 60027950| 60025038| 60020650| 60000163| 60000745| 60029445| 60017161| 60052106| 60018491| 60025111| 60010146| 60006297| 60025272| 124261391| 60005248| 60092945| 60019647 | Q14: Meta| The University of Texas at Austin| Carnegie Mellon University| University of California, Berkeley| University of Bristol| International Institute of Information Technology, Hyderabad| University of Illinois Urbana-Champaign| University of Minnesota Twin Cities| National University of Singapore| Universidad de Los Andes, Colombia| Simon Fraser University| The University of North Carolina at Chapel Hill| Università degli Studi di Catania| University of Pennsylvania| The University of Tokyo| Indiana University| Johns Hopkins University| King Abdullah University of Science and Technology| Georgia Institute of Technology | R14: 6506707692 | S14: 55941899900 | T14: - | U14: - | V14: India| United Kingdom| Singapore| Japan| Saudi Arabia| United States| Colombia| Italy| Canada | W14: Integration of Robotics and Action Recognition Techniques | X14: Temporal Action Localization in Video Analysis
A15: Examining incel subculture on Reddit | B15: Helm, B.| Scrivens, R.| Holt, T.J.| Chermak, S.| Frank, R. | C15: 5 | D15: 57222484913| 57125976800| 57203081096| 6507987895| 23134558900 | E15: 2024 | F15: 45292 | G15: Journal of Crime and Justice | H15: English | I15: 39 | J15: 20.84 | K15: 10.1080/0735648X.2022.2074867 | L15: Article | N15: Simon Fraser University| Michigan State University | O15: 2 | P15: 60031707| 60018491 | Q15: Michigan State University| Simon Fraser University | R15: 57222484913 | S15: 23134558900 | T15: 57222484913 | U15: - | V15: United States| Canada | W15: Masculinity, Gender Identity, and Health Dynamics | X15: Misogyny and Violence in Online Communities
A16: Correction to: Pre-Aksumite and Aksumite Agricultural Economy at Ona Adi, Tigrai (Ethiopia): First look at a 1000-Year History (African Archaeological Review, (2024), 41, 2, (239-268), 10.1007/s10437-024-09574-9) | B16: Meresa, Y.| Ruiz-Giralt, A.| Beldados, A.| Lancelotti, C.| D’Andrea, A.C. | C16: 5 | D16: 57215021384| 57222259129| 57160304000| 36466630000| 59157783100 | E16: 2024 | F16: 45444 | G16: African Archaeological Review | H16: English | I16: 1 | J16: 20.5 | K16: 10.1007/s10437-024-09595-4 | L16: Erratum | M16: Hybrid gold | N16: ICREA| Aksum University| Simon Fraser University| Pompeu Fabra University| Addis Ababa University | O16: 5 | P16: 60109536| 60032942| 60071181| 60032907| 60018491 | Q16: Aksum University| Universitat Pompeu Fabra Barcelona| Addis Ababa University| Institució Catalana de Recerca i Estudis Avançats| Simon Fraser University | R16: 57215021384 | S16: 59157783100 | T16: 57222259129 | U16: - | V16: Ethiopia| Spain| Canada | W16: - | X16: -
A17: Calibration and specification in policy practice: Micro-dimensions of policy design | B17: Capano, G.| Howlett, M. | C17: 2 | D17: 23767017600| 7004315057 | E17: 2024 | F17: 45292 | G17: Policy Design and Practice | H17: English | I17: 17 | J17: 19.83 | K17: 10.1080/25741292.2024.2353929 | L17: Editorial | M17: Gold|Green | N17: Simon Fraser University| University of Bologna | O17: 2 | P17: 60028218| 60018491 | Q17: Alma Mater Studiorum Università di Bologna| Simon Fraser University | R17: 23767017600 | S17: 7004315057 | T17: 23767017600 | U17: - | V17: Italy| Canada | W17: Public Administration and Gender Representation Dynamics | X17: Policy Instruments and Governance in Public Administration
A18: Situating platform gig economy in the formal subsumption of reproductive labor: Transnational migrant domestic workers and the continuum of exploitation and precarity | B18: Yin, S. | C18: 1 | D18: 57200442395 | E18: 2024 | F18: 45352 | G18: Capital and Class | H18: English | I18: 20 | J18: 18.86 | K18: 10.1177/03098168221145407 | L18: Article | N18: Simon Fraser University | O18: 1 | P18: 60018491 | Q18: Simon Fraser University | R18: - | S18: - | T18: 57200442395 | U18: 57200442395 | V18: Canada | W18: Collective Bargaining and Taxation in Labor Markets | X18: Platform Economy and Worker Dynamics in Gig Labor
A19: INTRODUCTION: Reckoning New Paths | B19: Nicholas, G.| Watkins, J. | C19: 2 | D19: 14828144700| 14008489600 | E19: 2024 | F19: 45292 | G19: Working as Indigenous Archaeologists: Reckoning New Paths Between Past and Present Lives | H19: English | I19: 2 | J19: 18.75 | K19: 10.4324/9781003183853-2 | L19: Editorial | N19: Hokkaido University| Simon Fraser University| Flinders University | O19: 3 | P19: 60018491| 60014652| 60020828| 122442145 | Q19: Simon Fraser University| Hokkaido University| Flinders University| Choctaw Nation of Oklahoma | R19: 14828144700 | S19: 14008489600 | T19: - | U19: - | V19: Japan| United States| Australia| Canada | W19: Cultural Heritage and Archaeology in Amazonia and beyond | X19: Cultural Heritage and Community Engagement in Archaeology
A20: Publisher Correction: Global estimates on the number of people blind or visually impaired by cataract: a meta-analysis from 2000 to 2020 (Eye, (2024), 38, 11, (2156-2172), 10.1038/s41433-024-02961-1) | B20: Bourne, R.R.A.| Wang, N.| Wang, Y.X.| Tsilimbaris, M.| Topouzis, F.| Ramulu, P.| Peto, T.| Nowak, M.| Nangia, V.| Little, J.-A.| Leasher, J.| Khanna, R.C.| Khairallah, M.| Kahloun, R.| Jonas, J.B.| Hartnett, M.E.| George, R.| Gazzard, G.| Furtado, J.M.| Friedman, D.| Ellwein, L.B.| Ehrlich, J.R.| Del Monte, M.A.| Cheng, C.-Y.| Bron, A.| Braithwaite, T.| Bikbov, M.M.| Flaxman, S.| Sedighi, T.| Taylor, H.R.| Resnikoff, S.| Leveziel, N.| Arrigo, A.| Cicinelli, M.V.| Fernandes, A.G.| Tapply, I.| Kempen, J.H.| Lansingh, V.C.| Pesudovs, K.| Steinmetz, J.D.| Zoladl, M.| Zikarg, Y.T.| Zielińska, M.| Ziafati, M.| Zhao, H.| Zastrozhin, M.S.| Yu, C.| You, Y.| Yonemoto, N.| Yon, D.K.| Yismaw, Y.| Yiğit, A.| Nia, I.Y.| Yao, Y.| Xiao, H.| Wondimagegn, G.S.| Wonde, T.E.| Watson, S.L.W.| Van den Eynde, J.| Valizadeh, R.| Umar, T.P.| Umair, M.| Ubah, C.S.| Ty, S.S.| Tusa, B.S.| Tumurkhuu, M.| Tsegay, G.M.| Tsatsakis, A.| Toma, T.M.| Ticoalu, J.H.V.| Terefa, D.R.| Temsah, M.-H.| Teklay, G.| Taye, B.T.| Tabatabaei, S.M.| Susanty, S.| Subramaniam, M.D.| Starodubov, V.I.| Sreeramareddy, C.T.| Sousa, R.A.R.C.| Solomon, Y.| Skiadaresi, E.| Singh, P.| Singh, J.A.| Silva, J.C.| Siddig, E.E.| Sibhat, M.M.| Shorofi, S.A.| Shivakumar, K.M.| Shiue, I.| Shittu, A.| Shayan, M.| Shashamo, B.B.| Shannawaz, M.| Shamim, M.A.| Sham, S.| Shaikh, M.A.| Shahwan, M.J.| Shahid, S.| Shaheen, A.A.| Seylani, A.| Seyedi, S.A.| Sethi, Y.| Senapati, S.| Semnani, F.| Selvaraj, S.| Saravanan, A.| Samy, A.M.| Samuel, V.P.| Samodra, Y.L.| Samadzadeh, S.| Saleh, M.A.| Sakshaug, J.W.| Sahraian, M.A.| Sahebkar, A.| Sharif-Askari, F.S.| Saghazadeh, A.| Safi, S.Z.| Safi, S.| Saeed, U.| Saddik, B.| Sabour, S.| Saadatian, Z.| Pramanik, K.R.| Roy, P.| Redwan, E.M.M.| Damavandi, A.R.| Rawaf, S.| Rauf, A.U.| Rath, R.S.| Rashidi, M.-M.| Ranjan, S.| Ramasubramani, P.| Ramasamy, S.K.| Rajaa, S.| Rahman, M.H.U.| Rahimi-Movaghar, V.| Rahim, F.| Quan, N.K.| Pourazizi, M.| Pham, H.T.| Peyman, A.| Petcu, I.-R.| Peprah, P.| Pawar, S.| Patel, J.| Park, S.| Pardhan, S.| Panos, G.D.| Pandey, A.| Padubidri, J.R.| Owolabi, M.O.| Otstavnov, N.| Osuagwu, U.L.| Ordak, M.| Olatubi, M.I.| Olagunju, A.T.| Okonji, O.C.| Niazi, R.K.| Nguyen, V.T.| Nguyen, P.T.| Nguyen, D.H.| Negash, H.| Negaresh, M.| Nayak, B.P.| Natto, Z.S.| Nargus, S.| Naik, G.| Naik, G.R.| Murray, C.J.L.| Mulita, A.| Mousavi, P.| Motappa, R.| Moradi, M.| Montazeri, F.| Moni, M.A.| Vardanjani, H.M.| Mokdad, A.H.| Mojiri-forushani, H.| Mohammed, M.| Mohammadi, S.| Mohamed, N.S.| Misra, S.| Mishra, M.| Misganaw, A.| Minh, L.H.N.| Mestrovic, T.| Mersha, A.M.| Meng, Y.| Meto, T.M.| Mebratu, W.| McAlinden, C.| Maugeri, A.| Marzo, R.R.| Manu, E.| Mansouri, V.| Mallhi, T.H.| Malhotra, K.| Mahmoudi, R.| Mahmoudi, A.| Maharaj, S.B.| Mahajan, P.B.| Little, J.-A.| Lim, S.S.| Lee, W.-C.| Lee, S.W.| Lee, M.| Landires, I.| Lan, T.| Lahariya, C.| Kurmi, O.P.| Kumar, N.| Kulimbet, M.| Krishan, K.| Koyanagi, A.| Kosen, S.| Kisa, A.| Khatib, M.N.| Khalilov, R.| Khajuria, H.| Khader, Y.S.| Kayode, G.A.| Kaur, R.J.| Kaur, N.| Kaup, S.| Kasraei, H.| Karaye, I.M.| Kantar, R.S.| Kandel, H.| Kamath, S.| Kalhor, R.| Kalankesh, L.R.| Kadashetti, V.| Joshua, C.E.| Joseph, N.| Jokar, M.| Jindal, H.A.| Jayaram, S.| Janodia, M.D.| Jairoun, A.A.| Jacob, L.| Iwu, C.C.D.| Islam, S.M.S.| Islam, M.R.| Immurana, M.| Ilic, I.M.| Ibitoye, S.E.| Huynh, H.-H.| Huang, J.J.| Hu, C.| Hosseinzadeh, M.| Hong, S.H.| Holla, R.| Hoan, N.Q.| Heyi, D.Z.| Hasani, H.| Harorani, M.| Hamidi, S.| Hallaj, S.| Halimi, A.| Haj-Mirzaian, A.| Gupta, V.K.| Gupta, V.B.| Gupta, S.| Gudisa, Z.| Guan, S.-Y.| Goulart, B.N.G.| Goleij, P.| Golechha, M.| Ghozy, S.| Ghassemi, F.| Gerema, U.| Gebremariam, B.| Gebrehiwot, M.| Gebregergis, M.W.W.| Gandhi, A.P.| Gaidhane, A.M.| Fowobaje, K.R.| Foschi, M.| Forouhari, A.| Fischer, F.| Fetensa, G.| Desideri, L.F.| Feizkhah, A.| Fatehizadeh, A.| Farrokhpour, H.| Fahim, A.| Fagbamigbe, A.F.| Etemadimanesh, A.| Emamverdi, M.| Emamian, M.H.| Elhadi, M.| Sayed, I.E.| Ekundayo, T.C.| Ekholuenetale, M.| Ehrlich, J.R.| Efendi, F.| Edinur, H.A.| Dziedzic, A.M.| dos Santos Figueiredo, F.W.| Do, T.H.P.| Do, T.C.| Devanbu, V.G.C.| Dervenis, N.| Derese, A.M.A.| Dereje, D.| Demisse, B.| Demessa, B.H.| Dastmardi, M.| Dashti, M.| Dascalu, A.M.| Das, S.| Dai, X.| Dadras, O.| Cruz-Martins, N.| Coelho, J.M.| Coberly, K.| Chu, D.-T.| Chopra, H.| Chitranshi, N.| Chattu, V.K.| Chandrasekar, E.K.| Cenderadewi, M.| Carneiro, V.L.A.| Cámera, L.A.| dos Santos, F.L.C.| Butt, Z.A.| Bustanji, Y.| Burkart, K.| Braithwaite, T.| Bitra, V.R.| Birck, M.G.| Bineshfar, N.| Bhatti, J.S.| Bhaskar, S.| Bhardwaj, P.| Bhagavathula, A.S.| Bhagat, D.S.| Beyene, A.S.| Bazvand, F.| Bayileyegn, N.S.| Batra, K.| Basu, S.| Bardhan, M.| Banik, B.| Baig, A.A.| Bahurupi, Y.| Bagherieh, S.| Babamohamadi, H.| Azzam, A.Y.| Ayatollahi, H.| Atreya, A.| Atout, M.M.W.| Atinafu, B.T.T.| Athari, S.S.| Ashraf, T.| Asgedom, A.A.| Aregawi, B.B.| Arefnezhad, R.| Areda, D.| Arafat, M.| Arabloo, J.| Appiah, F.| Anyasodor, A.E.| Anvari, S.| Anil, A.| Anguita, R.| Androudi, S.| Amu, H.| Altaf, A.| Ali, S.S.S.| Ali, A.| Alfaar, A.S.| Ahmed, H.| Ahmed, A.| Ahmadi, A.| Ahmad, S.| Ahmad, A.| Ahinkorah, B.O.| Aghamiri, S.| Afzal, M.S.| Adnani, Q.E.S.| Addo, I.Y.| Adane, M.M.| Adal, T.G.G.| Aburuz, S.| Abu-Gharbieh, E.| Ali, H.A.| Abualruz, H.| Abrha, W.A.| Aboagye, R.G.| Abiodun, O.| Abebe, A.M.| Abdollahi, M.| Abdollahi, M.| Abate, Y.H.| Flaxman, S.| Sedighi, T.| Taylor, H.R.| Vos, T.| Briant, P.S.| Leveziel, N.| Arrigo, A.| Cicinelli, M.V.| Fernandes, A.G.| Tapply, I.| Kempen, J.H.| Lansingh, V.C.| Pesudovs, K. | C20: 409 | D20: 7103377631| 7404340277| 47962560100| 59324472200| 57194262710| 6602186935| 58308296100| 18437379100| 57201490837| 22634844800| 57197789738| 14060213400| 7004503022| 14119867400| 7202492953| 7005954310| 7402637163| 7004147260| 36801755000| 7402079597| 7004442455| 57190136174| 7005134758| 55539712500| 7103248039| 55522947000| 6507082164| 35190257400| 55368203500| 57203677366| 7006012071| 35321211600| 56331647600| 37260895200| 57192956381| 57205490881| 57216598048| 57194598546| 7004576721| 57221591053| 53980736300| 57223092789| 58491440100| 58978107400| 59742707300| 56728932200| 57208140344| 49865138500| 57204947657| 57193675906| 57217253497| 57820497600| 58942491800| 57026732300| 57214631433| 57194082186| 57207759070| 7401463790| 56507221200| 57192641339| 57221311061| 56641365200| 57224538923| 57682292500| 57216200356| 59156725100| 57221594727| 35596169100| 59676110000| 57580368800| 57422760200| 56115852000| 55782858000| 57221614117| 55935372700| 57203516467| 58890971900| 6701820838| 57212263335| 57218215064| 57220875005| 37100428500| 57202809996| 7404421736| 8576007400| 55879555400| 57222351357| 35086976700| 57221603938| 35811219800| 16418068900| 57209496707| 57223025060| 56349680200| 58030336800| 58031551200| 56673685600| 6601974519| 57208126144| 57202954176| 57222325334| 57917244500| 57862678600| 38062239700| 57224511550| 57223264725| 58290959400| 36973661300| 12142874900| 57363130700| 25951754100| 7201797507| 35300521200| 57219968932| 26639699900| 56161060900| 55634259200| 35620794800| 57219477293| 36612315100| 23020079300| 16307842100| 56303466100| 58242338100| 58956986100| 8519808500| 57471988800| 6602475959| 57215346048| 57196051098| 57324471900| 58290259300| 57229805800| 58321724400| 57205681553| 57208867497| 6507646446| 23052247800| 57930597600| 56266621400| 58627023500| 16744344900| 57094897500| 57200369019| 58594958600| 59222700400| 57384211300| 7003706887| 55629406000| 57210886573| 58295062300| 57222581892| 57202947262| 46062324800| 55992015900| 57200278115| 26029995700| 57222864302| 57204666021| 58491437100| 58366936400| 57220970272| 57209110507| 57226439849| 56639942500| 37000768500| 58491929300| 56020694000| 14825548600| 55481130700| 58491929200| 58627198400| 57577479200| 57736564200| 57924899400| 35119094400| 56556955100| 7004813962| 57200658736| 58144884000| 57193239265| 57208820453| 35501005200| 57213025989| 57202808713| 57201722696| 6507240107| 57205064523| 59835907300| 59156731000| 57215415625| 35325278500| 56740683100| 57163427600| 57195773594| 59348187900| 57214875058| 57224508895| 55397852300| 56646055600| 54883987800| 57168727200| 22634844800| 57201800433| 57394248700| 57223118056| 58964400000| 15063040000| 57218329495| 13205447400| 23389886800| 36678889900| 57288600700| 57202279708| 59269920500| 57211346192| 6603346067| 25825057100| 57193308858| 56639982500| 55654192600| 53463867400| 57190442227| 58344388100| 56967988200| 57194520224| 55598638900| 56719718400| 57226834655| 57193525413| 55670548600| 57200529685| 56724219200| 58491197900| 35292547200| 57221729841| 56086233400| 57221589240| 12791073000| 57208735762| 56779678900| 57204657478| 57218355467| 57215057958| 57215875071| 57210823522| 57212027408| 58260528100| 56135699200| 58956490200| 57201880569| 57211663879| 55270371800| 58959927100| 57326428900| 55632123200| 57195316126| 24366336000| 57209198237| 57913296900| 57210768364| 35073936800| 57194978364| 57217857409| 57861615300| 56982445100| 55958854600| 57217533849| 36006347600| 55337839100| 35271776100| 57216249028| 57203847504| 57192100745| 58955738100| 57217858382| 25031248900| 57203988822| 57192255295| 57225200038| 55508208800| 57211853863| 57201549628| 57226144762| 36782045000| 57210568865| 56996903600| 50861113000| 57268238000| 57216906536| 55181897800| 57212082248| 57207466387| 57204841448| 57189344745| 57190136174| 55301269100| 57287676500| 56155198800| 57197830836| 58955491100| 58537658400| 55879226900| 35368148900| 58961184500| 59157899800| 57211083382| 58537470400| 57215794006| 57372394700| 16038545200| 55531140000| 57221591169| 57205721978| 57203415019| 57194215965| 58139389800| 56239816300| 57217071283| 15029905100| 55743746500| 57200006411| 57206668799| 57213266524| 7003354253| 56373058500| 57202522739| 8847282600| 29067507300| 55522947000| 56394367200| 59046499100| 57892143000| 14043178800| 57192268582| 57226841442| 56398498300| 57327243700| 57209036705| 26653998700| 57305415100| 57219649874| 59832966100| 60122586900| 57216204052| 49460999600| 56491232000| 57225879659| 36983053200| 57208274797| 55991128900| 55856196800| 57195251851| 57225212559| 26653399600| 56366752600| 57208511484| 57221588539| 57209234011| 57193619525| 56380109600| 57208760927| 57210715590| 57192947419| 55967502900| 58164007300| 56809403300| 6603286512| 57190183918| 57201900507| 57188688612| 57822712300| 55319978300| 57222316680| 57199492030| 57193998515| 57218961022| 57210400531| 57194684030| 57208014122| 56009310800| 60106463900| 56305995900| 57217891132| 57221588673| 55886382800| 24586714800| 58096030700| 57216547615| 57210943530| 57221438826| 7003859089| 57191847346| 57780545000| 57940559800| 58492166600| 35190257400| 55368203500| 57203677366| 57223885848| 57196152334| 35321211600| 56331647600| 37260895200| 57192956381| 57205490881| 57216598048| 57209471470| 59156861800 | E20: 2024 | F20: 45505 | G20: Eye (Basingstoke) | H20: English | I20: 2 | J20: 17.95 | K20: 10.1038/s41433-024-03161-7 | L20: Erratum | M20: Hybrid gold|Green | N20: Tsinghua University| Temple University| Shahid Beheshti University of Medical Sciences| Qazvin University of Medical Sciences| University of Leeds| London School of Hygiene and Tropical Medicine| University of Bern| Wolkite University| Dire Dawa University| Nova Southeastern University| Shiraz University of Medical Sciences| King Saud bin Abdulaziz University for Health Sciences| University of Thessaly| Charité – Universitätsmedizin Berlin| University of Southern Denmark| Moorfields Eye Hospital NHS Foundation Trust| University of Sharjah| University of Minho| Medical University of Warsaw| Al-Shifa Trust Eye Hospital| University of Human Development| Amity University, Noida| Asian Institute of Medicine, Science & Technology| University of Technology Sydney| Universidade Federal do Rio Grande do Sul| Sungkyunkwan University| Bashkir State Medical University| Northwell Health System| Baptist Hospital Miami| Public Health Foundation of India| Federal Employment Agency| University of Khartoum| University of Washington| Jahrom University of Medical Science| Ludwig Maximilian University of Munich| Juntendo University| Sri Balaji Vidyapeeth University| Hywel Dda University Health Board| Duy Tan University| Leipzig University| Institute of Nano Science and Technology| National Center of Neurology and Psychiatry Kodaira| Philadelphia University| Moscow Institute of Physics and Technology| Kristiania University College| Shaqra University| Hanoi Medical University| Kermanshah University of Medical Sciences| Madda Walabu University| Ardabil University of Medical Sciences| United Arab Emirates University| Jimma University Ethiopia| Kyung Hee University| Mayo Clinic Rochester, MN| Vita-Salute San Raffaele University| San Martino Hospital Genoa| Ulster University| James Cook University Queensland| Utrecht University| University of South Florida| Vision Research Foundation India| Queen's University Belfast| McMaster University| Dilla University| Mansoura University| Cambridge University Hospitals NHS Foundation Trust| Hebei University of Chinese Medicine| The University of the West Indies| Mashhad University of Medical Sciences| Guilan University of Medical Sciences| Chitkara University| Aristotle University of Thessaloniki| Anglia Ruskin University| Thomas Jefferson University| Harvard University| Massachusetts General Hospital| University of Genoa| University of New South Wales| Singapore National Eye Center| University of Utah| Bucharest University of Economic Studies| University Hospital Center of Santo António| Vietnam National University, Hanoi| Indira Gandhi Medical College| Shahroud University of Medical Sciences| South Eastern Sydney and Illawarra Area Health Service| Arak University of Medical Sciences| Coventry University| Abdul Wali Khan University Mardan| Cancer Institute NSW| Al Jouf University| Saveetha Institute of Medical and Technical Sciences (Deemed to be University)| University of Calgary| Washington University St. Louis| Tulane University| Universitas Airlangga| Université de Poitiers| Can Tho University of Medicine and Pharmacy| Bowen University| Abasyn University | O20: 286 | P20: 60026553| 60118547| 60170478| 60000913| 131479195| 60029251| 60025488| 60002746| 60028842| 60003828| 60077515| 60071181| 128824525| 60017488| 60014992| 60002306| 60009622| 60004688| 60032653| 60020859| 60136196| 60011463| 60028333| 60026851| 60227248| 60011520| 60005518| 60030713| 60017161| 60024285| 60025778| 60022590| 60033182| 60007651| 60008088| 60013148| 60022148| 60025134| 60026060| 60012708| 60257150| 60016908| 126573089| 60050038| 60055372| 60020023| 60027165| 60012831| 60019600| 60020730| 105526379| 60110371| 60029738| 60015891| 60015331| 60015066| 60026834| 60012413| 60026707| 60073453| 60121475| 108227545| 60009982| 60280051| 60016390| 60000905| 60015481| 60091926| 60028548| 60015150| 130346998| 60027708| 60123791| 60123830| 60023794| 60021948| 60109528| 60126119| 60116801| 60109536| 60067411| 60121161| 60070813| 60008665| 60064180| 60109530| 60071189| 60088090| 60069388| 60070625| 60018934| 60023932| 60110524| 60273000| 106139693| 60022730| 60071723| 60071726| 60023588| 60023146| 60089631| 60008042| 60026245| 60107589| 60268797| 113675538| 60025812| 60010987| 60016691| 60108918| 60110821| 60020449| 60001248| 126253311| 60071885| 60159438| 60024852| 60105817| 130003783| 60025928| 60003892| 60109448| 60104681| 60070610| 60012874| 60054151| 114825832| 126389796| 60015290| 60273389| 60024530| 60020609| 60024502| 60110819| 60010859| 60017837| 60031146| 60031892| 60071196| 60122734| 60183191| 60010571| 60071205| 128418046| 60032270| 126259648| 126752312| 60106790| 60002494| 60191838| 60006558| 60111763| 60021221| 60031331| 60014171| 60160817| 60019666| 60008557| 60281827| 60020475| 126006143| 60019870| 60069416| 60016849| 60021600| 60109334| 60109606| 60019544| 60113205| 60071364| 60277921| 60007249| 60034027| 60105804| 60030280| 60029622| 60279801| 60030452| 60033150| 60031210| 60109512| 60023925| 60109870| 124562458| 60118264| 60018756| 60027573| 60000906| 60032354| 60069383| 60006270| 60277094| 60033041| 60072594| 60072595| 60196819| 60103657| 60027550| 60001117| 60005248| 60017326| 60025392| 60120846| 60107402| 60025153| 60120582| 101593964| 131315216| 129930539| 60094583| 128309870| 60109529| 131329069| 60018491| 60005558| 60272432| 113003696| 60009057| 60006726| 60014454| 60109519| 60072223| 60018805| 60029929| 60022761| 60015277| 60032420| 60030612| 60113238| 60031286| 60071376| 60016017| 60015855| 60016524| 60016728| 106027843| 60111656| 60025278| 60017994| 60005455| 130419978| 60068815| 60068827| 60004955| 60084853| 60121699| 60025709| 60021902| 60104561| 60029937| 60003299| 131361114| 60042202| 60103927| 60089253| 100859372| 60105258| 60089223| 60026537| 60080427| 60013933| 60008469| 60189901| 129930604| 121177438| 60029304| 60024099| 60159706| 60001654| 60109780| 60078170| 60032724| 60007989| 60051534| 60076774| 60071969| 60086039| 60111756| 60017672| 60021134| 120877404| 100425036| 60018526| 60108730| 60031828| 126709567| 60115218| 60022756| 60010261| 125108446| 125339222| 60029305| 60211621| 60007511| 60017552| 60014569| 100777094| 60006000| 60071706| 131329379| 60007506| 60104126| 60122524| 60090667| 60018894| 60010146| 124177225| 60023998| 60170432| 60029306| 60199677| 60022095| 60138458| 60026005| 127190966| 60010799| 60120552| 60105852| 60031004| 60112701| 60030988| 60189490| 60020828| 60017803| 60024925| 60027086| 60004582| 116405671| 60026470| 60156622| 60007740| 115259292| 60071418| 60058195| 60031569| 60006448| 60190660| 60069009| 60010499| 60000308| 60199609| 60018680| 60272430| 122729825| 60025016| 60015138| 60027272| 60163612| 60012070| 60107810| 60251038| 60275293| 60008488| 60254882| 122695288| 60032838| 60104452| 60104340| 60282908| 60069380| 60111140| 129930588| 101261297| 60022158| 60092393| 128660038| 60278951| 60105168| 60123785| 60001500| 60123810| 60028717| 60112602| 60227738| 60231631| 60012022| 60019160| 60113249| 60016618| 60020187| 60078092| 60286095| 60006577| 60005281| 60072733| 131219386| 114000948| 60270066| 60032480| 60012954| 60010037| 60017810| 60109516| 60022265| 107552774| 60029230| 60105917| 60280532| 60138359| 60281174| 112086188| 60001508| 60069625| 60245372| 60025615| 60105203| 60013183| 60069399| 122277676| 60001524| 60018917| 60016280| 60030398| 60078536| 60021077| 60121253| 60025063| 60109514| 115235305| 60003970| 60342338| 60279163| 60014966| 60005200| 60008724| 60006433| 60000231| 122280559| 60001873| 60017451| 60032116| 60023691| 130444161| 60116386| 60012293| 60033436 | Q20: University of Melbourne| Melbourne School of Population and Global Health| School of Medicine| Anglia Ruskin University| HelpMeSee| University of Miami| The University of Utah| Harvard Medical School| Schepens Eye Research Institute| Massachusetts Eye and Ear| Myungsung Christian Medical Center| Addis Ababa University| Sight for Souls| Addenbrooke's Hospital| Universidade Federal de São Paulo| University of Calgary| Università Vita-Salute San Raffaele| San Raffaele Scientific Institute| Université de Poitiers| Centre Hospitalier Universitaire de Poitiers| Brien Holden Vision Institute| UNSW Medicine| UNSW Sydney| University of Oxford| Ufa Eye Research Institute| King's College London| Guy's and St Thomas' NHS Foundation Trust| Centre Hospitalier Universitaire Dijon Bourgogne| National University of Singapore| Singapore Eye Research Institute| University of Michigan, Ann Arbor| University of Michigan W.K. Kellogg Eye Center| University of Michigan Medical School| National Eye Institute (NEI)| Universidade de São Paulo| UCL Institute of Ophthalmology| University College London| Sankara Nethralaya| Medical Research Foundation, Chennai| Stanford University| Medizinische Fakultät Mannheim| Universität Heidelberg| Associated Ophthalmologists of Monastir| Université de Monastir| CHU Fattouma-Bourguiba| L.V. Prasad Eye Institute India| University of Rochester| University of Rochester School of Medicine and Dentistry| Nova Southeastern University| Ulster University| Suraj Eye Institute| University of Social Sciences, Lodz| Queen's University Belfast| Wilmer Eye Institute| Aristotle University of Thessaloniki| School of Medicine| "University General Hospital of Thessaloniki "AHEPA""| University of Crete Medical School| Capital Medical University| Beijing Tongren Hospital, Capital Medical University| HelpMeSee, Inc.| Mexican Institute of Ophthalmology| Harvard University| Myungsung Medical College| Cambridge University Hospitals NHS Foundation Trust| Inserm| University of Washington| Institute for Health Metrics and Evaluation| University of Washington School of Medicine| Imperial College London| Aleta Wondo Hospital| Tehran University of Medical Sciences| The Institute of Pharmaceutical Sciences (TIPS)| School of Pharmacy| School of Medicine| Shiraz University of Medical Sciences| Debre Berhan University| Babcock University| University of Health and Allied Sciences, Ghana| Aksum University| Al-Zaytoonah University of Jordan| University of Human Development| University of Sharjah| United Arab Emirates University| The University of Jordan| Wolkite University| Bahir Dar University| Cancer Institute NSW| Universitas Padjadjaran| University of Management and Technology Lahore| Shahid Beheshti University of Medical Sciences| University of Technology Sydney| Shaqra University| Abasyn University| Labanese American University| Shahrekord University of Medical Sciences| Khartoum University| Institute of Endemic Diseases Sudan| Universität Basel| Swiss Tropical and Public Health Institute Swiss TPH | R20: 7103377631 | S20: 59156861800 | T20: 7004576721 | U20: - | V20: Ethiopia| Mexico| Spain| Panama| Denmark| Romania| Viet Nam| Taiwan| Belgium| Ghana| Lesotho| United States| Turkey| Colombia| Switzerland| Palestine| India| Iraq| Lebanon| Japan| South Africa| Italy| Indonesia| Norway| China| Tunisia| Portugal| Australia| Malaysia| Iran| Egypt| Libya| Nepal| Azerbaijan| Botswana| Singapore| Saudi Arabia| Poland| Germany| Greece| Netherlands| Sudan| Argentina| United Arab Emirates| United Kingdom| Finland| Serbia| Pakistan| France| Bangladesh| Trinidad and Tobago| Brazil| South Korea| Croatia| Kazakhstan| Nigeria| Jordan| Russian Federation| Canada | W20: - | X20: -
A21: 3D Gaussian Splatting as Markov Chain Monte Carlo | B21: Kheradmand, S.| Rebain, D.| Sharma, G.| Sun, W.| Tseng, Y.-C.| Isack, H.| Kar, A.| Tagliasacchi, A.| Yi, K.M. | C21: 9 | D21: 56483176200| 57205667866| 57189234431| 57215770641| 57913630600| 36466512000| 57141775400| 25123272600| 26424457400 | E21: 2024 | F21: 45292 | G21: Advances in Neural Information Processing Systems | H21: English | I21: 19 | J21: 16.71 | K21: - | L21: Conference Paper | N21: Simon Fraser University| University of British Columbia| University of Toronto| Alphabet Inc. | O21: 4 | P21: 60010365| 60006191| 60111161| 60018491| 60016849 | Q21: The University of British Columbia| Google LLC| DeepMind Technologies Limited| Simon Fraser University| University of Toronto | R21: 56483176200 | S21: 26424457400 | T21: - | U21: - | V21: United Kingdom| United States| Canada | W21: Image Segmentation, Deep Neural Networks and Object Detection | X21: Neural Representations for 3D Shape Reconstruction
A22: A Novel Multiple-Medium-AC-Port Power Electronic Transformer | B22: Zhang, J.| Li, H.| Kong, X.| Zhou, J.| Shi, G.| Zang, J.| Wang, J. | C22: 7 | D22: 54401835800| 58540400100| 57245066800| 57203010121| 36462894000| 57202010045| 55878723400 | E22: 2024 | F22: 45474 | G22: IEEE Transactions on Industrial Electronics | H22: English | I22: 87 | J22: 15.55 | K22: 10.1109/TIE.2023.3301550 | L22: Article | N22: State Grid Corporation of China| Simon Fraser University| Shanghai University of Engineering Science| Shanghai Jiao Tong University | O22: 4 | P22: 60025084| 60001604| 100398057| 60004246| 60032504| 60018491 | Q22: Shanghai Jiao Tong University| Ministry of Education of the People's Republic of China| State Grid Suzhou Power Supply Company| State Grid Corporation of China| Shanghai University of Engineering Science| Simon Fraser University | R22: 54401835800 | S22: 55878723400 | T22: 57203010121 | U22: - | V22: China| Canada | W22: Power Electronics Control Systems | X22: Transformers in Power Electronics and Grid Integration
A23: Why and When LLM-Based Assistants Can Go Wrong: Investigating the Effectiveness of Prompt-Based Interactions for Software Help-Seeking | B23: Khurana, A.| Subramonyam, H.| Chilana, P.K. | C23: 3 | D23: 57219766574| 57056308000| 35069141700 | E23: 2024 | F23: 45369 | G23: ACM International Conference Proceeding Series | H23: English | I23: 27 | J23: 15.48 | K23: 10.1145/3640543.3645200 | L23: Conference Paper | M23: Gold|Green | N23: Simon Fraser University| Stanford University | O23: 2 | P23: 60018491| 60012708 | Q23: Simon Fraser University| Stanford University | R23: 57219766574 | S23: 35069141700 | T23: - | U23: - | V23: United States| Canada | W23: User-Centered Design in Digital Interaction | X23: User-Centric Design in Software Help Systems
A24: Empowering Canadian Geography Students and Faculty: New Approaches to Curriculum and Course Material Development Using Generative AI as a Writing Assistant | B24: Day, T.| Perkins, A.J. | C24: 2 | D24: 16312010800| 55331729100 | E24: 2024 | F24: 45292 | G24: Powerful Geography: International Perspectives and Applications | H24: English | I24: 7 | J24: 15.37 | K24: 10.1007/978-3-031-54845-1_5 | L24: Chapter | N24: Simon Fraser University | O24: 1 | P24: 60018491 | Q24: Simon Fraser University | R24: 16312010800 | S24: 55331729100 | T24: 16312010800 | U24: - | V24: Canada | W24: Indigenous Perspectives on Health and Sovereignty | X24: Indigenous Knowledge and Decolonization in Education
A25: Content, Context, and Composition | B25: Pagin, P.| Pelletier, F.J. | C25: 2 | D25: 6603180267| 7004357738 | E25: 2024 | F25: 45292 | G25: Context-Sensitivity and Semantic Minimalism: New Essays on Semantics and Pragmatics | H25: English | I25: 36 | J25: 15.23 | K25: - | L25: Chapter | N25: Simon Fraser University| Stockholm University | O25: 2 | P25: 60028378| 60018491 | Q25: Stockholms universitet| Simon Fraser University | R25: 6603180267 | S25: 7004357738 | T25: - | U25: - | V25: Sweden| Canada | W25: Interplay of Knowledge, Belief, and Language | X25: Tibetan Language Modeling and Semantic Structures
A26: Improving the Hosmer-Lemeshow goodness-of-fit test in large models with replicated Bernoulli trials | B26: Surjanovic, N.| Loughin, T.M. | C26: 2 | D26: 57204248159| 35547944400 | E26: 2024 | F26: 45292 | G26: Journal of Applied Statistics | H26: English | I26: 16 | J26: 14.9 | K26: 10.1080/02664763.2023.2272223 | L26: Note | M26: Hybrid gold|Green | N26: Simon Fraser University| University of British Columbia | O26: 2 | P26: 60010365| 60018491 | Q26: The University of British Columbia| Simon Fraser University | R26: 57204248159 | S26: 35547944400 | T26: 57204248159 | U26: - | V26: Canada | W26: Causal Inference and Estimation in Health Research | X26: Logistic Regression Models for Diverse Applications
A27: 4D-fy: Text-to-4D Generation Using Hybrid Score Distillation Sampling | B27: Bahmani, S.| Skorokhodov, I.| Rong, V.| Wetzstein, G.| Guibas, L.| Wonka, P.| Tulyakov, S.| Park, J.J.| Tagliasacchi, A.| Lindell, D.B. | C27: 10 | D27: 57362551400| 57219794509| 57782064300| 24462821700| 35451872900| 12765329500| 57213004407| 57853598800| 25123272600| 57201292322 | E27: 2024 | F27: 45292 | G27: Proceedings of the IEEE Computer Society Conference on Computer Vision and Pattern Recognition | H27: English | I27: 43 | J27: 14.86 | K27: 10.1109/CVPR52733.2024.00764 | L27: Conference Paper | N27: Simon Fraser University| King Abdullah University of Science and Technology| Stanford University| University of Michigan, Ann Arbor| University of Toronto| Alphabet Inc.| Snap Inc. | O27: 7 | P27: 60278837| 60092945| 60120916| 60012708| 60025778| 60016849| 60018491| 60006191 | Q27: Vector Institute| King Abdullah University of Science and Technology| Snap Inc.| Stanford University| University of Michigan, Ann Arbor| University of Toronto| Simon Fraser University| Google LLC | R27: 57362551400 | S27: 57201292322 | T27: - | U27: - | V27: Saudi Arabia| United States| Canada | W27: Image Segmentation, Deep Neural Networks and Object Detection | X27: Neural Representations for 3D Shape Reconstruction
A28: The role of digital technologies in mathematics education: purposes and perspectives | B28: Drijvers, P.| Sinclair, N. | C28: 2 | D28: 6506336239| 7006432994 | E28: 2024 | F28: 45413 | G28: ZDM - Mathematics Education | H28: English | I28: 30 | J28: 14.3 | K28: 10.1007/s11858-023-01535-x | L28: Article | N28: Simon Fraser University| Utrecht University | O28: 2 | P28: 60007989| 60018491 | Q28: Universiteit Utrecht| Simon Fraser University | R28: 6506336239 | S28: 7006432994 | T28: 6506336239 | U28: - | V28: Netherlands| Canada | W28: Mathematics Education and Teacher Development Insights | X28: Integrating Technology in Mathematics Education
A29: Climate change drives flooding risk increases in the Yellow River Basin | B29: Lan, H.| Zhao, Z.| Li, L.| Li, J.| Fu, B.| Tian, N.| Lai, R.| Zhou, S.| Zhu, Y.| Zhang, F.| Peng, J.| Clague, J.J. | C29: 12 | D29: 7102710925| 57364032100| 55549991600| 55720617300| 57207275546| 57214229888| 43361445900| 56095894000| 56962899600| 57218542149| 57204721822| 7102359243 | E29: 2024 | F29: 45444 | G29: Geography and Sustainability | H29: English | I29: 49 | J29: 14 | K29: 10.1016/j.geosus.2024.01.004 | L29: Article | M29: Gold | N29: CAS - Research Center for Eco-Environmental Sciences| CAS - Institute of Geographical Sciences and Natural Resources Research| Ministry of Water Resources, P.R. China| Simon Fraser University| University of Chinese Academy of Sciences| Lanzhou University| Beijing Normal University| Chinese Academy of Sciences| Chang'an University | O29: 9 | P29: 60019499| 60031150| 60028891| 60027363| 60081484| 60010689| 60023237| 60028265| 60001604| 60018491 | Q29: Chinese Academy of Sciences| Institute of Geographic Sciences and Natural Resources Research, Chinese Academy of Sciences| Chang'an University| University of Chinese Academy of Sciences| Yellow River Conservancy Commission| Research Center for Eco-Environmental Sciences Chinese Academy of Sciences| Beijing Normal University| Lanzhou University| Ministry of Education of the People's Republic of China| Simon Fraser University | R29: 7102710925 | S29: 7102359243 | T29: 7102710925 | U29: - | V29: China| Canada | W29: Climate Change Impacts on Precipitation Patterns and Extreme Events | X29: Flood Trends and Climate Change Impacts
A30: Faith and vaccination: a scoping review of the relationships between religious beliefs and vaccine hesitancy | B30: Tiwana, M.H.| Smith, J. | C30: 2 | D30: 57920225800| 57199012787 | E30: 2024 | F30: 45627 | G30: BMC Public Health | H30: English | I30: 34 | J30: 13.05 | K30: 10.1186/s12889-024-18873-4 | L30: Article | M30: Gold|Green | N30: Simon Fraser University | O30: 1 | P30: 60018491 | Q30: Simon Fraser University | R30: 57920225800 | S30: 57199012787 | T30: 57920225800 | U30: - | V30: Canada | W30: COVID-19, Its Impact, and Vaccination | X30: Vaccine Acceptance and Hesitancy Dynamics
A31: Artificial intelligence for family medicine research in Canada: current state and future directions | B31: Kueper, J.K.| Emu, M.| Banbury, M.| Bjerre, L.M.| Choudhury, S.| Green, M.| Pimlott, N.| Slade, S.| Tsuei, S.H.| Sisler, J. | C31: 10 | D31: 57195421263| 57208388450| 58951770300| 6603222621| 36917872400| 55479519400| 6602984915| 57201848126| 56519983400| 7003991620 | E31: 2024 | F31: 45352 | G31: Canadian Family Physician | H31: English | I31: 19 | J31: 12.42 | K31: 10.46747/cfp.7003161 | L31: Article | M31: Gold|Green | N31: Queen's University Kingston| Simon Fraser University| University of British Columbia| University of Toronto| College of Family Physicians of Canada | O31: 5 | P31: 60016005| 60082919| 60021600| 60016849| 60018491| 60010365 | Q31: Queen’s University| Le Collège des médecins de famille du Canada| University of Toronto Faculty of Medicine| University of Toronto| Simon Fraser University| The University of British Columbia | R31: 57195421263 | S31: 7003991620 | T31: 58951770300 | U31: - | V31: Canada | W31: Image Segmentation, Deep Neural Networks and Object Detection | X31: Artificial Intelligence Transforming Diagnostic Imaging in Healthcare
A32: HiSpMV: Hybrid Row Distribution and Vector Buffering for Imbalanced SpMV Acceleration on FPGAs | B32: Rajashekar, M.B.| Tian, X.| Fang, Z. | C32: 3 | D32: 58992962300| 57866275800| 38361266400 | E32: 2024 | F32: 45383 | G32: FPGA 2024 - Proceedings of the 2024 ACM/SIGDA International Symposium on Field Programmable Gate Arrays | H32: English | I32: 13 | J32: 12.36 | K32: 10.1145/3626202.3637557 | L32: Conference Paper | M32: Gold | N32: Simon Fraser University | O32: 1 | P32: 60018491 | Q32: Simon Fraser University | R32: 58992962300 | S32: 38361266400 | T32: - | U32: - | V32: Canada | W32: Digital Signal Processing Architectures | X32: Matrix Multiplication Architectures in FPGA Design
A33: "Bee and I need diversity!" Break Filter Bubbles in Recommendation Systems through Embodied AI Learning | B33: Zhou, X.| Zhou, Y.| Gong, Y.| Cai, Z.| Qiu, A.| Xiao, Q.| Antle, A.N.| Bai, Z. | C33: 8 | D33: 57217589045| 59209670000| 58576772200| 59273349600| 59210911400| 57226743918| 15060073500| 57220554432 | E33: 2024 | F33: 45460 | G33: Proceedings of ACM Interaction Design and Children Conference: Inclusive Happiness, IDC 2024 | H33: English | I33: 16 | J33: 12.3 | K33: 10.1145/3628516.3655802 | L33: Conference Paper | N33: University of California at Irvine| Simon Fraser University| University of Rochester | O33: 3 | P33: 60027165| 60152526| 60007278| 60018491 | Q33: University of Rochester| Hajim School of Engineering and Applied Sciences| University of California, Irvine| Simon Fraser University | R33: 57217589045 | S33: 57220554432 | T33: - | U33: - | V33: United States| Canada | W33: Integration of Robotics and Computational Thinking in Education | X33: AI and Machine Learning in Educational Design
A34: AI is a viable alternative to high throughput screening: a 318-target study | B34: Wallach, I.| Bernard, D.| Nguyen, K.| Ho, G.| Morrison, A.| Stecula, A.| Rosnik, A.| O’Sullivan, A.M.| Davtyan, A.| Samudio, B.| Thomas, B.| Worley, B.| Butler, B.| Laggner, C.| Thayer, D.| Moharreri, E.| Friedland, G.| Truong, H.| van den Bedem, H.| Ng, H.L.| Stafford, K.| Sarangapani, K.| Giesler, K.| Ngo, L.| Mysinger, M.| Ahmed, M.| Anthis, N.J.| Henriksen, N.| Gniewek, P.| Eckert, S.| de Oliveira, S.| Suterwala, S.| PrasadPrasad, S.V.K.| Shek, S.| Contreras, S.| Hare, S.| Palazzo, T.| O’Brien, T.E.| Van Grack, T.| Williams, T.| Chern, T.-R.| Kenyon, V.| Lee, A.H.| Cann, A.B.| Bergman, B.| Anderson, B.M.| Cox, B.D.| Warrington, J.M.| Sorenson, J.M.| Goldenberg, J.M.| Young, M.A.| DeHaan, N.| Pemberton, R.P.| Schroedl, S.| Abramyan, T.M.| Gupta, T.| Mysore, V.| Presser, A.G.| Ferrando, A.A.| Andricopulo, A.D.| Ghosh, A.| Ayachi, A.G.| Mushtaq, A.| Shaqra, A.M.| Toh, A.K.L.| Smrcka, A.V.| Ciccia, A.| de Oliveira, A.S.| Sverzhinsky, A.| de Sousa, A.M.| Agoulnik, A.I.| Kushnir, A.| Freiberg, A.N.| Statsyuk, A.V.| Gingras, A.R.| Degterev, A.| Tomilov, A.| Vrielink, A.| Garaeva, A.A.| Bryant-Friedrich, A.| Caflisch, A.| Patel, A.K.| Rangarajan, A.V.| Matheeussen, A.| Battistoni, A.| Caporali, A.| Chini, A.| Ilari, A.| Mattevi, A.| Foote, A.T.| Trabocchi, A.| Stahl, A.| Herr, A.B.| Berti, A.| Freywald, A.| Reidenbach, A.G.| Lam, A.| Cuddihy, A.R.| White, A.| Taglialatela, A.| Ojha, A.K.| Cathcart, A.M.| Motyl, A.A.L.| Borowska, A.| D’Antuono, A.| Hirsch, A.K.H.| Porcelli, A.M.| Minakova, A.| Montanaro, A.| Müller, A.| Fiorillo, A.| Virtanen, A.| O’Donoghue, A.J.| Del Rio Flores, A.| Garmendia, A.E.| Pineda-Lucena, A.| Panganiban, A.T.| Samantha, A.| Chatterjee, A.K.| Haas, A.L.| Paparella, A.S.| John, A.L.S.| Prince, A.| ElSheikh, A.| Apfel, A.M.| Colomba, A.| O’Dea, A.| Diallo, B.N.| Ribeiro, B.M.R.M.| Bailey-Elkin, B.A.| Edelman, B.L.| Liou, B.| Perry, B.| Chua, B.S.K.| Kováts, B.| Englinger, B.| Balakrishnan, B.| Gong, B.| Agianian, B.| Pressly, B.| Salas, B.P.M.| Duggan, B.M.| Geisbrecht, B.V.| Dymock, B.W.| Morten, B.C.| Hammock, B.D.| Mota, B.E.F.| Dickinson, B.C.| Fraser, C.| Lempicki, C.| Novina, C.D.| Torner, C.| Ballatore, C.| Bon, C.| Chapman, C.J.| Partch, C.L.| Chaton, C.T.| Huang, C.| Yang, C.-Y.| Kahler, C.M.| Karan, C.| Keller, C.| Dieck, C.L.| Huimei, C.| Liu, C.| Peltier, C.| Mantri, C.K.| Kemet, C.M.| Müller, C.E.| Weber, C.| Zeina, C.M.| Muli, C.S.| Morisseau, C.| Alkan, C.| Reglero, C.| Loy, C.A.| Wilson, C.M.| Myhr, C.| Arrigoni, C.| Paulino, C.| Santiago, C.| Luo, D.| Tumes, D.J.| Keedy, D.A.| Lawrence, D.A.| Chen, D.| Manor, D.| Trader, D.J.| Hildeman, D.A.| Drewry, D.H.| Dowling, D.J.| Hosfield, D.J.| Smith, D.M.| Moreira, D.| Siderovski, D.P.| Shum, D.| Krist, D.T.| Riches, D.W.H.| Ferraris, D.M.| Anderson, D.H.| Coombe, D.R.| Welsbie, D.S.| Hu, D.| Ortiz, D.| Alramadhani, D.| Zhang, D.| Chaudhuri, D.| Slotboom, D.J.| Ronning, D.R.| Lee, D.| Dirksen, D.| Shoue, D.A.| Zochodne, D.W.| Krishnamurthy, D.| Duncan, D.| Glubb, D.M.| Gelardi, E.L.M.| Hsiao, E.C.| Lynn, E.G.| Silva, E.B.| Aguilera, E.| Lenci, E.| Abraham, E.T.| Lama, E.| Mameli, E.| Leung, E.| Christensen, E.M.| Mason, E.R.| Petretto, E.| Trakhtenberg, E.F.| Rubin, E.J.| Strauss, E.| Thompson, E.W.| Cione, E.| Lisabeth, E.M.| Fan, E.| Kroon, E.G.| Jo, E.| García-Cuesta, E.M.| Glukhov, E.| Gavathiotis, E.| Yu, F.| Xiang, F.| Leng, F.| Wang, F.| Ingoglia, F.| van den Akker, F.| Borriello, F.| Vizeacoumar, F.J.| Luh, F.| Buckner, F.S.| Vizeacoumar, F.S.| Bdira, F.B.| Svensson, F.| Rodriguez, G.M.| Bognár, G.| Lembo, G.| Zhang, G.| Dempsey, G.| Eitzen, G.| Mayer, G.| Greene, G.L.| Garcia, G.A.| Lukacs, G.L.| Prikler, G.| Parico, G.C.G.| Colotti, G.| De Keulenaer, G.| Cortopassi, G.| Roti, G.| Girolimetti, G.| Fiermonte, G.| Gasparre, G.| Leuzzi, G.| Dahal, G.| Michlewski, G.| Conn, G.L.| Stuchbury, G.D.| Bowman, G.R.| Popowicz, G.M.| Veit, G.| de Souza, G.E.| Akk, G.| Caljon, G.| Alvarez, G.| Rucinski, G.| Lee, G.| Cildir, G.| Li, H.| Breton, H.E.| Jafar-Nejad, H.| Zhou, H.| Moore, H.P.| Tilford, H.| Yuan, H.| Shim, H.| Wulff, H.| Hoppe, H.| Chaytow, H.| Tam, H.-K.| Van Remmen, H.| Xu, H.| Debonsi, H.M.| Lieberman, H.B.| Jung, H.| Fan, H.-Y.| Feng, H.| Zhou, H.| Kim, H.J.| Greig, I.R.| Caliandro, I.| Corvo, I.| Arozarena, I.| Mungrue, I.N.| Verhamme, I.M.| Qureshi, I.A.| Lotsaris, I.| Cakir, I.| Perry, J.J.P.| Kwiatkowski, J.| Boorman, J.| Ferreira, J.| Fries, J.| Kratz, J.M.| Miner, J.| Siqueira-Neto, J.L.| Granneman, J.G.| Ng, J.| Shorter, J.| Voss, J.H.| Gebauer, J.M.| Chuah, J.| Mousa, J.J.| Maynes, J.T.| Evans, J.D.| Dickhout, J.| MacKeigan, J.P.| Jossart, J.N.| Zhou, J.| Lin, J.| Xu, J.| Wang, J.| Zhu, J.| Liao, J.| Xu, J.| Zhao, J.| Lin, J.| Lee, J.| Reis, J.| Stetefeld, J.| Bruning, J.B.| Bruning, J.B.| Coles, J.G.| Tanner, J.J.| Pascal, J.M.| So, J.| Pederick, J.L.| Costoya, J.A.| Rayman, J.B.| Maciag, J.J.| Nasburg, J.A.| Gruber, J.J.| Finkelstein, J.M.| Watkins, J.| Rodríguez-Frade, J.M.| Arias, J.A.S.| Lasarte, J.J.| Oyarzabal, J.| Milosavljevic, J.| Cools, J.| Lescar, J.| Bogomolovas, J.| Wang, J.| Kee, J.-M.| Liao, J.| Sistla, J.C.| Abrahão, J.S.| Sishtla, K.| Francisco, K.R.| Hansen, K.B.| Molyneaux, K.A.| Cunningham, K.A.| Martin, K.R.| Gadar, K.| Ojo, K.K.| Wong, K.S.| Wentworth, K.L.| Lai, K.| Lobb, K.A.| Hopkins, K.M.| Parang, K.| Machaca, K.| Pham, K.| Ghilarducci, K.| Sugamori, K.S.| McManus, K.J.| Musta, K.| Faller, K.M.E.| Nagamori, K.| Mostert, K.J.| Korotkov, K.V.| Liu, K.| Smith, K.S.| Sarosiek, K.| Rohde, K.H.| Kim, K.K.| Lee, K.H.| Pusztai, L.| Lehtiö, L.| Haupt, L.M.| Cowen, L.E.| Byrne, L.J.| Su, L.| Wert-Lamas, L.| Puchades-Carrasco, L.| Chen, L.| Malkas, L.H.| Zhuo, L.| Hedstrom, L.| Hedstrom, L.| Walensky, L.D.| Antonelli, L.| Iommarini, L.| Whitesell, L.| Randall, L.M.| Fathallah, M.D.| Nagai, M.H.| Kilkenny, M.L.| Ben-Johny, M.| Lussier, M.P.| Windisch, M.P.| Lolicato, M.| Lolli, M.L.| Vleminckx, M.| Caroleo, M.C.| Macias, M.J.| Valli, M.| Barghash, M.M.| Mellado, M.| Tye, M.A.| Wilson, M.A.| Hannink, M.| Ashton, M.R.| Cerna, M.V.C.| Giorgis, M.| Safo, M.K.| Maurice, M.S.| McDowell, M.A.| Pasquali, M.| Mehedi, M.| Serafim, M.S.M.| Soellner, M.B.| Alteen, M.G.| Champion, M.M.| Skorodinsky, M.| O’Mara, M.L.| Bedi, M.| Rizzi, M.| Levin, M.| Mowat, M.| Jackson, M.R.| Paige, M.| Al-Yozbaki, M.| Giardini, M.A.| Maksimainen, M.M.| De Luise, M.| Hussain, M.S.| Christodoulides, M.| Stec, N.| Zelinskaya, N.| Van Pelt, N.| Merrill, N.M.| Singh, N.| Kootstra, N.A.| Singh, N.| Gandhi, N.S.| Chan, N.-L.| Trinh, N.M.| Schneider, N.O.| Matovic, N.| Horstmann, N.| Longo, N.| Bharambe, N.| Rouzbeh, N.| Mahmoodi, N.| Gumede, N.J.| Anastasio, N.C.| Khalaf, N.B.| Rabal, O.| Kandror, O.| Escaffre, O.| Silvennoinen, O.| Bishop, O.T.| Iglesias, P.| Sobrado, P.| Chuong, P.| O’Connell, P.| Martin-Malpartida, P.| Mellor, P.| Fish, P.V. | C34: 687 | D34: 26041264000| 23992427000| 59873174700| 59010205400| 59010603000| 55807065900| 56031547600| 57211692711| 55201894100| 57164784000| 59009802700| 55325610700| 59009599100| 9740505400| 59009194400| 55005981400| 59010603100| 59010205500| 7003624479| 7401619312| 59077212900| 59010005600| 38861626300| 59009395600| 59818363200| 59871760100| 59009395700| 44761124900| 36610112300| 59009802800| 56673658300| 59010406600| 59009194500| 59009802900| 7005598730| 59010205600| 59010603200| 56549015500| 57205467535| 59009803000| 57487057300| 6601905927| 59010406800| 59009599200| 59009194600| 9843001400| 59027945300| 59010603300| 58585975400| 57200371494| 59597977000| 59010406900| 59338974100| 6508232682| 55447201800| 59009599300| 57347496200| 57203682271| 7004532329| 6602185009| 57189638399| 59009803100| 57218843220| 57207687562| 57195231812| 7004180078| 6508056998| 56151571600| 56067626000| 57339802000| 6603393500| 7003544845| 24758111700| 58345939800| 7003712522| 6701735483| 7005894628| 7003338267| 57209659950| 6506324134| 7006219601| 59010409000| 57226474553| 35272580000| 7006452552| 6603715977| 7003514474| 6601938545| 7005232911| 57527801100| 6602401917| 57207719230| 7005295805| 17134465100| 6506874365| 36515425000| 59010409200| 6602085855| 59095374900| 57195568158| 57525576600| 57216763646| 57194034777| 59009804900| 59009601600| 24474499800| 57226204395| 59009397200| 57217099513| 59072326100| 24331133600| 59847534300| 15052458100| 57210752931| 7003421090| 6602107013| 7006465612| 57216813235| 59048082700| 35557190000| 55991729700| 35339298400| 59009196700| 57220770088| 59009805000| 57205011098| 59009397400| 57218542251| 58621633700| 37066922100| 59010409300| 12792895400| 57201902330| 57206780546| 56957170500| 56548827700| 57055432900| 35798110200| 6603505056| 57160271900| 59010605700| 7005773309| 6602002401| 55196912900| 59009601800| 7101843599| 13805145700| 24723872100| 59009397500| 57990055200| 6603399297| 57204068645| 16303293300| 57200701834| 57206391654| 8312805000| 57215716883| 59857886800| 7407026220| 7006552724| 6507900491| 7201710905| 57163570900| 59010207900| 56188999700| 59009602100| 15070777000| 57208687695| 7404109739| 55112033700| 57201502117| 56991175100| 57203044787| 59820425400| 55926005800| 58627786700| 59009397600| 56860806200| 57226729043| 37038307200| 57209566007| 59009805500| 16403003400| 55941822700| 7402207276| 59009602200| 35561171700| 15063329300| 34570222900| 57202105872| 23469353100| 6602858589| 59009197200| 57811409200| 7004949965| 37003962400| 56193836200| 7005837863| 35080282600| 59009601500| 7004163964| 6506144008| 59010409900| 7006878488| 57679191100| 59010007600| 60133270900| 6603039413| 57216377770| 59010410000| 59009602300| 6507369998| 7005642430| 25223097000| 55810657600| 23970679000| 57216648101| 56954689000| 59803936100| 56336001700| 57002846500| 8386615500| 57210209987| 57686270600| 57224131367| 27171151000| 59009806000| 59339748300| 57191842541| 53983403300| 13106213600| 35566168500| 7402849735| 23768196900| 24174804500| 7006443503| 7003820278| 59009397800| 56700176400| 55601108300| 6506522837| 59056107900| 59009197400| 57206356397| 59009806200| 56108851000| 55932216000| 57207529360| 6508242393| 6507981477| 35572272600| 35791247600| 56677854700| 6603427180| 59009602500| 59010007700| 59010208400| 59009602600| 57224509425| 6602891108| 7201807380| 59886624600| 7202755191| 35602405400| 59010605900| 57215579177| 6602135968| 6603078918| 7004495393| 12808329800| 56062263700| 7003522893| 6507765908| 56664157700| 56950674200| 57204377390| 35582390200| 59010410100| 24334008700| 6507135338| 57194736383| 57200418172| 6701443033| 14046562600| 24334202100| 58284454900| 59010208700| 55754070800| 57847839000| 59009197600| 6602238601| 59010410200| 59431480000| 59010007900| 59010208800| 59010008000| 7102828660| 7103057362| 55520141900| 56480066200| 7003401734| 59010209000| 24437462500| 7101773940| 59009197700| 59009602900| 59010008100| 59010209100| 59009806400| 6602146620| 59010606000| 26633655900| 6603036306| 59010009300| 6602161143| 14623211700| 59010210000| 25924163800| 59089426100| 59010009400| 57222967716| 59009604300| 59009806900| 10739967500| 59009604400| 24491356500| 7005838747| 59009198500| 59836497000| 57214879910| 16039262600| 59009198600| 56271011300| 57330579900| 7407667162| 6508131452| 6603881796| 57209069146| 8344201200| 59446194200| 59009198700| 59010411000| 59892310000| 59869473200| 59010411100| 59009198800| 59798213400| 57309659900| 59206865700| 55926964300| 16506358600| 16506358600| 35406223500| 7201406976| 7102681712| 59572869000| 57204434316| 6602224775| 57189397509| 57214088600| 57808204400| 7101971232| 59009604500| 59010411200| 6701571780| 59009807000| 7003598010| 6602795510| 57556871200| 58801025000| 6603844493| 25647616900| 58855075000| 57198996463| 59010210500| 57193646949| 24922468300| 36488562100| 57205558133| 9274178400| 6506335336| 35602229000| 37077638300| 57712346900| 57207559445| 59009604600| 55766312800| 59338812400| 6603496824| 59009807200| 6701806122| 6602158471| 56597650600| 57222464787| 6701410121| 7005089031| 59010009600| 56108203200| 57434913200| 57202039580| 35552072500| 59009199200| 59009199300| 16043944000| 36723787000| 59613292700| 59281612300| 57218887355| 6507478836| 6701861263| 7003498523| 23075649900| 7202509184| 56926772500| 55349605800| 59009399600| 7004666030| 59009399700| 7005260425| 7005260425| 6603921611| 59867034800| 16549467300| 7004292136| 56048974800| 35605561100| 54795680400| 7004249878| 57188628021| 59064988200| 8942425400| 54410860800| 6603475038| 58507696000| 57032514200| 7004997066| 48061587500| 57211854282| 7006474283| 57220062031| 55482055100| 7004649771| 59010606900| 59009199500| 12041476200| 57198331273| 59854453500| 7005510661| 7004328794| 39863243300| 57223858671| 6603223178| 57188865131| 9036013000| 59009807400| 57202555251| 36995198200| 7103199741| 59009199700| 7004355577| 58543487600| 35230302600| 57219089250| 12792581900| 14325666800| 56526866100| 59782310100| 6603751663| 57204588706| 59923265800| 57352898100| 56998584900| 59009807600| 6603966335| 57210594521| 24075789300| 59009199800| 57223164798| 57218868216| 59009807700| 12767126500| 7004663930| 56607231000| 57203727169| 58709220200| 55259925000| 6505944150| 54416944000| 14831613300| 6603176520| 38662481200| 7005900407| 6603302692| 59010009900| 6603634771| 57204652005| 57194249969| 8653546400| 59804900800| 7005747441 | E34: 2024 | F34: 45627 | G34: Scientific Reports | H34: English | I34: 64 | J34: 11.89 | K34: 10.1038/s41598-024-54655-z | L34: Article | M34: Gold|Green | N34: University of Wisconsin-Madison| Louisiana State University| Leiden University| University of Florence| University of California at Berkeley| New York State Department of Health| Charles Sturt University| Weill Cornell Medicine-Qatar| University of Toledo| University College London| Chapman University| Dana-Farber Cancer Institute| University of Michigan, Ann Arbor| University of Calabria| University of Houston| University of Texas MD Anderson Cancer Center| University of North Texas Health Science Center| SUNY Upstate Medical University| University of Bari| Genentech Incorporated| The University of Chicago| University of Tennessee Health Science Center| Broad Institute| CSIC - National Center for Biotechnology| Goethe University Frankfurt| United States Department of Agriculture| University of Rome Tor Vergata| University of North Dakota| Universidade de São Paulo| Indiana University Bloomington| King's College London| University of Hyderabad| University of New Mexico| Florida International University| McGill University| University of Dundee| University of Montana| Nanyang Technological University| Marquette University| University of Rochester| University of Nebraska Medical Center| University of Illinois at Urbana-Champaign| University of California at San Diego| University of South Australia| University of Oulu| University of Washington| University of Missouri| Institute for the Study and Prevention of Cancer| University of Alberta| Ludwig Maximilian University of Munich| University of Leon| International Institute of Molecular and Cell Biology in Warsaw| OpenAI, Inc.| Yale University| University of Oxford| University of Helsinki| Saint Louis University| Georgetown University| VA Medical Center| University of Connecticut| California Institute of Technology| Soka University| University of Adelaide| University of Central Florida| National Jewish Health| Brandeis University| Universidade Federal de Santa Catarina| Stanford University| Albert Einstein College of Medicine| University of Bologna| Columbia University| West Virginia University| George Mason University| University of Freiburg| Wake Forest University| Universidade Federal de Minas Gerais| Technical University of Denmark| University of Antwerp| University of Massachusetts Boston| Brunel University London| Canterbury Christ Church University| University of Navarra| University of Louisville| McMaster University| Institute of Medical and Veterinary Science Australia| University of Cologne| City University of New York| Curtin University| Vanderbilt University| University of California at Riverside| University of Santiago de Compostela| National University of Singapore| Massachusetts Institute of Technology| Cincinnati Children's Hospital Medical Center| F. Hoffmann-La Roche AG| Tampere University| CSIC| City of Hope National Med Center| Harvard University| Rhodes University | O34: 198 | P34: 60300298| 60001673| 60121131| 131208485| 130739910| 129282009| 60026209| 131208093| 60318995| 60085713| 126381589| 60076757| 60025111| 60030945| 131207920| 60076695| 60032499| 60030162| 60008088| 60002388| 60005510| 60015481| 60000986| 60013894| 60011019| 60033182| 60027565| 60017609| 60009507| 60026004| 60122600| 60015206| 60032105| 60014569| 122533273| 60030612| 60015849| 60023143| 60014439| 60031806| 60010023| 60009408| 60012614| 60012708| 60012937| 60027509| 60027272| 60018678| 60021199| 60015197| 60009500| 60021859| 60025038| 60030440| 60015186| 60001001| 60019674| 60021743| 60025778| 60010971| 60028134| 60011666| 60014334| 60004969| 60105701| 60028218| 60032350| 60011170| 60022659| 60032489| 60033320| 60030071| 60017672| 109457933| 60005399| 60095034| 60000305| 60016733| 60011568| 60022148| 60028590| 60026548| 60030074| 60009697| 60102305| 124601904| 60009512| 128455192| 60025488| 60013372| 60000689| 101157835| 60029278| 60009982| 60025641| 60002746| 60002016| 60102151| 60025029| 60024941| 60015941| 60002194| 116119024| 60017994| 60007493| 60028717| 60009254| 60019444| 60031846| 115506947| 60021624| 60030521| 60021143| 60028419| 60010544| 60094178| 60138284| 60003668| 60024582| 60031226| 60002476| 60016261| 60020633| 60021508| 60030835| 60016849| 60023691| 60031828| 60010363| 60121568| 60071612| 60024025| 124188744| 60021121| 60000948| 60001565| 60020261| 60031707| 60072750| 60199632| 60031581| 123595288| 60019816| 60000473| 60117081| 60013278| 60002494| 60022778| 60072262| 60000928| 60006297| 60024007| 60022756| 60025225| 60175947| 60006173| 60002441| 60005455| 60006873| 60001769| 60007762| 60014232| 60030288| 60103153| 60030257| 60015875| 60012259| 60267265| 60268180| 125208096| 60030769| 60029516| 60025709| 60007474| 60007997| 60016240| 60019595| 60029747| 60030319| 60001989| 60032280| 60029526| 60005200| 60026306| 113177420| 60026695| 60006754| 60032179| 60021947| 60022355| 60020623| 60016569| 60027863| 60005429| 60000213| 60022144| 60027165| 60018319| 60012954| 60105312| 60016247| 60085992| 60031101| 60069616| 60029929| 60015720| 60026161| 60018491| 60031004| 119221607| 60002483| 60000209| 60015023| 60027668| 60027090| 60005837| 60119141| 60020657| 60006404| 60024746| 60017367| 60279163| 60011373| 60028458| 131208667| 60024125| 60009071| 60001248| 60010261| 60008877| 60017412| 60011605| 60023927| 60008724| 60011520| 60007566| 60008221| 60031437| 60017060| 60018741| 60026851| 60000291| 60006385| 60018573| 60002952 | Q34: Atomwise Inc.| Amgen Incorporated| OpenAI, Inc.| Model Medicines| Atomic.AI| METiS Therapeutics| Genentech, Inc| US Navy Medical Service Corps Officer (2300/1810D)| Totus Medicines| Cytokinetics, Inc.| Nurix Therapeutics Inc.| Amazon.com, Inc.| The University of North Carolina at Chapel Hill| UNC Eshelman School of Pharmacy| Refibered Inc.| NVIDIA| Harvard T.H. Chan School of Public Health| Columbia University| Universidade de São Paulo| Albert Einstein College of Medicine| Nanyang Technological University| University of Washington| University of Massachusetts Chan Medical School| University of Massachusetts System| Queensland University of Technology| University of Michigan Medical School| Columbia University Irving Medical Center| Universidade Federal de Santa Catarina| University of Montreal| Fundacao Oswaldo Cruz| Herbert Wertheim College of Medicine| Florida International University| NYU Langone Health| The University of Texas Medical Branch at Galveston| University of Houston| University of California, San Diego| Tufts University School of Medicine| Tufts University| University of California, Davis| The University of Western Australia| Rijksuniversiteit Groningen| Wayne State University| Universität Zürich| Stanford University| Universiteit Antwerpen| "Università degli Studi di Roma "Tor Vergata""| The University of Edinburgh| CSIC - Centro Nacional de Biotecnologia (CNB)| Consiglio Nazionale delle Ricerche| Università degli Studi di Pavia| The University of Vermont| Università degli Studi di Firenze| University of California, Berkeley| Cincinnati Children's Hospital Medical Center| University of Saskatchewan| Broad Institute| Boston University| CancerCare Manitoba| University of Michigan, Ann Arbor| Wadsworth Center for Laboratories and Research| New York State Department of Health| State University of New York Albany| Dana-Farber Cancer Institute| Università di Parma| Helmholtz-Institut für Pharmazeutische Forschung Saarland (HIPS)| Alma Mater Studiorum Università di Bologna| Sapienza Università di Roma| Tampere University| University of Connecticut| The Cima Universidad de Navarra| Universidad de Navarra| Tulane National Primate Research Center| Tulane University| Scripps Research| LSU Health New Orleans School of Medicine| Duke-NUS Medical School| Case Western Reserve University| Oregon Health & Science University| Tanta University| University College London| Saint Louis University| Rhodes University| Universidade Federal de Minas Gerais| University of Manitoba| National Jewish Health| Drugs for Neglected Diseases initiative (DNDi)| The University of Adelaide| Mcule.com Ltd.| The University of Utah| The University of Texas at Austin| Kansas State University| UniQuest Pty Ltd| The University of Chicago| Harvard University| Universität Freiburg| Harvard Medical School| IRB Barcelona - Institute for Research in Biomedicine| Istituto Italiano di Tecnologia| QIMR Berghofer Medical Research Institute| University of California, Santa Cruz | R34: 26041264000 | S34: 14048405200 | T34: - | U34: - | V34: India| United Kingdom| Spain| Uruguay| Egypt| Japan| Finland| South Africa| Italy| Denmark| Hungary| Brazil| Taiwan| Qatar| Belgium| South Korea| China| Singapore| Bahrain| Poland| United States| Germany| Australia| Switzerland| Netherlands| New Zealand| Canada | W34: Innovative Approaches in Drug Discovery and Protein Structure | X34: Molecular Docking and Virtual Screening Innovations
A35: The Relation Between Need for Cognition and Academic Achievement: A Meta-Analysis | B35: Liu, Q.| Nesbit, J.C. | C35: 2 | D35: 56413233700| 7003819670 | E35: 2024 | F35: 45383 | G35: Review of Educational Research | H35: English | I35: 39 | J35: 11.78 | K35: 10.3102/00346543231160474 | L35: Article | M35: Hybrid gold | N35: Simon Fraser University | O35: 1 | P35: 60018491 | Q35: Simon Fraser University | R35: 56413233700 | S35: 7003819670 | T35: 56413233700 | U35: - | V35: Canada | W35: Self-Efficacy and Academic Performance in Education | X35: Need for Cognition and Its Impact on Performance
